Workbook

Sheet Base Cedis DW75
N1: VENTA | Q1: COSTO
A2: CONCAT1 | B2: CONCAT2 | C2: No. SF | D2: Nombre SF | E2: Cedis | F2: Destino | G2: Condicion de Expedicion | H2: Nombre Destino | I2: No. de material | J2: Nombre de material | K2: PV | L2: Inicio de vigencia | M2: Fin de vigencia | N2: Importe MP | O2: Importe Flete | P2: UM Venta | Q2: Importe Costo | R2: UM Costo | S2: Validacion 1 | T2: Validacion 2
A3: =CONCATENATE(C3,E3,F3,I3) | B3: =CONCATENATE(C3,E3,I3) | C3: 900000023 | D3: =IFERROR(VLOOKUP(C3,TRAOPE!$G:$H,2,0),"") | E3: DW75 | F3: D278 | G3: =IFERROR(VLOOKUP(A3,Flete!$A:$E,5,0),"") | H3: =IFERROR(VLOOKUP(F3,TRAOPE!$AA:$AB,2,0),"") | I3: 10000742 | J3: =IFERROR(VLOOKUP(I3,Materiales!$A:$H,8,0),"") | K3: =IFERROR(VLOOKUP(I3,Materiales!$A:$G,7,0),"") | L3: 20220516 | M3: 20240822 | O3: =IFERROR(VLOOKUP(A3,Flete!$A:$J,10,0),"") | Q3: =IFERROR(IFERROR(VLOOKUP(A3,TRAOPE!$A:$U,21,0),VLOOKUP(B3,TRAOPE!$A:$U,21,0)),"") | R3: =IFERROR(IFERROR(VLOOKUP(A3,TRAOPE!$A:$W,23,0),VLOOKUP(B3,TRAOPE!$A:$W,23,0)),"") | S3: =IF(AND(P3="TN",R3="TN"),N3+N(O3),IF(G3&""="1",N(K3)*N3,(N3+N(O3))*N(K3))) | T3: =IF(Q3="","",Q3-S3)
A4: =CONCATENATE(C4,E4,F4,I4) | B4: =CONCATENATE(C4,E4,I4) | C4: 900000023 | D4: =IFERROR(VLOOKUP(C4,TRAOPE!$G:$H,2,0),"") | E4: DW75 | F4: D278 | G4: =IFERROR(VLOOKUP(A4,Flete!$A:$E,5,0),"") | H4: =IFERROR(VLOOKUP(F4,TRAOPE!$AA:$AB,2,0),"") | I4: 10009436 | J4: =IFERROR(VLOOKUP(I4,Materiales!$A:$H,8,0),"") | K4: =IFERROR(VLOOKUP(I4,Materiales!$A:$G,7,0),"") | L4: 20220516 | M4: 20240822 | N4: 249.61 | O4: =IFERROR(VLOOKUP(A4,Flete!$A:$J,10,0),"") | P4: TN | Q4: =IFERROR(IFERROR(VLOOKUP(A4,TRAOPE!$A:$U,21,0),VLOOKUP(B4,TRAOPE!$A:$U,21,0)),"") | R4: =IFERROR(IFERROR(VLOOKUP(A4,TRAOPE!$A:$W,23,0),VLOOKUP(B4,TRAOPE!$A:$W,23,0)),"") | S4: =IF(AND(P4="TN",R4="TN"),N4+N(O4),IF(G4&""="1",N(K4)*N4,(N4+N(O4))*N(K4))) | T4: =IF(Q4="","",Q4-S4)
A5: =CONCATENATE(C5,E5,F5,I5) | B5: =CONCATENATE(C5,E5,I5) | C5: 900000023 | D5: =IFERROR(VLOOKUP(C5,TRAOPE!$G:$H,2,0),"") | E5: DW75 | F5: D278 | G5: =IFERROR(VLOOKUP(A5,Flete!$A:$E,5,0),"") | H5: =IFERROR(VLOOKUP(F5,TRAOPE!$AA:$AB,2,0),"") | I5: 10031878 | J5: =IFERROR(VLOOKUP(I5,Materiales!$A:$H,8,0),"") | K5: =IFERROR(VLOOKUP(I5,Materiales!$A:$G,7,0),"") | L5: 20220516 | M5: 20240822 | N5: 267.26 | O5: =IFERROR(VLOOKUP(A5,Flete!$A:$J,10,0),"") | P5: TN | Q5: =IFERROR(IFERROR(VLOOKUP(A5,TRAOPE!$A:$U,21,0),VLOOKUP(B5,TRAOPE!$A:$U,21,0)),"") | R5: =IFERROR(IFERROR(VLOOKUP(A5,TRAOPE!$A:$W,23,0),VLOOKUP(B5,TRAOPE!$A:$W,23,0)),"") | S5: =IF(AND(P5="TN",R5="TN"),N5+N(O5),IF(G5&""="1",N(K5)*N5,(N5+N(O5))*N(K5))) | T5: =IF(Q5="","",Q5-S5)
A6: =CONCATENATE(C6,E6,F6,I6) | B6: =CONCATENATE(C6,E6,I6) | C6: 900000023 | D6: =IFERROR(VLOOKUP(C6,TRAOPE!$G:$H,2,0),"") | E6: DW75 | F6: D278 | G6: =IFERROR(VLOOKUP(A6,Flete!$A:$E,5,0),"") | H6: =IFERROR(VLOOKUP(F6,TRAOPE!$AA:$AB,2,0),"") | I6: 10032115 | J6: =IFERROR(VLOOKUP(I6,Materiales!$A:$H,8,0),"") | K6: =IFERROR(VLOOKUP(I6,Materiales!$A:$G,7,0),"") | L6: 20220516 | M6: 20240822 | N6: 255.79 | O6: =IFERROR(VLOOKUP(A6,Flete!$A:$J,10,0),"") | P6: TN | Q6: =IFERROR(IFERROR(VLOOKUP(A6,TRAOPE!$A:$U,21,0),VLOOKUP(B6,TRAOPE!$A:$U,21,0)),"") | R6: =IFERROR(IFERROR(VLOOKUP(A6,TRAOPE!$A:$W,23,0),VLOOKUP(B6,TRAOPE!$A:$W,23,0)),"") | S6: =IF(AND(P6="TN",R6="TN"),N6+N(O6),IF(G6&""="1",N(K6)*N6,(N6+N(O6))*N(K6))) | T6: =IF(Q6="","",Q6-S6)
A7: =CONCATENATE(C7,E7,F7,I7) | B7: =CONCATENATE(C7,E7,I7) | C7: 900000023 | D7: =IFERROR(VLOOKUP(C7,TRAOPE!$G:$H,2,0),"") | E7: DW75 | F7: D278 | G7: =IFERROR(VLOOKUP(A7,Flete!$A:$E,5,0),"") | H7: =IFERROR(VLOOKUP(F7,TRAOPE!$AA:$AB,2,0),"") | I7: 10032164 | J7: =IFERROR(VLOOKUP(I7,Materiales!$A:$H,8,0),"") | K7: =IFERROR(VLOOKUP(I7,Materiales!$A:$G,7,0),"") | L7: 20220516 | M7: 20240822 | N7: 274.59 | O7: =IFERROR(VLOOKUP(A7,Flete!$A:$J,10,0),"") | P7: TN | Q7: =IFERROR(IFERROR(VLOOKUP(A7,TRAOPE!$A:$U,21,0),VLOOKUP(B7,TRAOPE!$A:$U,21,0)),"") | R7: =IFERROR(IFERROR(VLOOKUP(A7,TRAOPE!$A:$W,23,0),VLOOKUP(B7,TRAOPE!$A:$W,23,0)),"") | S7: =IF(AND(P7="TN",R7="TN"),N7+N(O7),IF(G7&""="1",N(K7)*N7,(N7+N(O7))*N(K7))) | T7: =IF(Q7="","",Q7-S7)
A8: =CONCATENATE(C8,E8,F8,I8) | B8: =CONCATENATE(C8,E8,I8) | C8: 900000023 | D8: =IFERROR(VLOOKUP(C8,TRAOPE!$G:$H,2,0),"") | E8: DW75 | F8: D278 | G8: =IFERROR(VLOOKUP(A8,Flete!$A:$E,5,0),"") | H8: =IFERROR(VLOOKUP(F8,TRAOPE!$AA:$AB,2,0),"") | I8: 10036583 | J8: =IFERROR(VLOOKUP(I8,Materiales!$A:$H,8,0),"") | K8: =IFERROR(VLOOKUP(I8,Materiales!$A:$G,7,0),"") | L8: 20220516 | M8: 20240822 | N8: 247.59 | O8: =IFERROR(VLOOKUP(A8,Flete!$A:$J,10,0),"") | P8: TN | Q8: =IFERROR(IFERROR(VLOOKUP(A8,TRAOPE!$A:$U,21,0),VLOOKUP(B8,TRAOPE!$A:$U,21,0)),"") | R8: =IFERROR(IFERROR(VLOOKUP(A8,TRAOPE!$A:$W,23,0),VLOOKUP(B8,TRAOPE!$A:$W,23,0)),"") | S8: =IF(AND(P8="TN",R8="TN"),N8+N(O8),IF(G8&""="1",N(K8)*N8,(N8+N(O8))*N(K8))) | T8: =IF(Q8="","",Q8-S8)
A9: =CONCATENATE(C9,E9,F9,I9) | B9: =CONCATENATE(C9,E9,I9) | C9: 900000023 | D9: =IFERROR(VLOOKUP(C9,TRAOPE!$G:$H,2,0),"") | E9: DW75 | F9: D312 | G9: =IFERROR(VLOOKUP(A9,Flete!$A:$E,5,0),"") | H9: =IFERROR(VLOOKUP(F9,TRAOPE!$AA:$AB,2,0),"") | I9: 10000742 | J9: =IFERROR(VLOOKUP(I9,Materiales!$A:$H,8,0),"") | K9: =IFERROR(VLOOKUP(I9,Materiales!$A:$G,7,0),"") | L9: 20220516 | M9: 20240822 | N9: 159.27 | O9: =IFERROR(VLOOKUP(A9,Flete!$A:$J,10,0),"") | P9: TN | Q9: =IFERROR(IFERROR(VLOOKUP(A9,TRAOPE!$A:$U,21,0),VLOOKUP(B9,TRAOPE!$A:$U,21,0)),"") | R9: =IFERROR(IFERROR(VLOOKUP(A9,TRAOPE!$A:$W,23,0),VLOOKUP(B9,TRAOPE!$A:$W,23,0)),"") | S9: =IF(AND(P9="TN",R9="TN"),N9+N(O9),IF(G9&""="1",N(K9)*N9,(N9+N(O9))*N(K9))) | T9: =IF(Q9="","",Q9-S9)
A10: =CONCATENATE(C10,E10,F10,I10) | B10: =CONCATENATE(C10,E10,I10) | C10: 900000023 | D10: =IFERROR(VLOOKUP(C10,TRAOPE!$G:$H,2,0),"") | E10: DW75 | F10: D312 | G10: =IFERROR(VLOOKUP(A10,Flete!$A:$E,5,0),"") | H10: =IFERROR(VLOOKUP(F10,TRAOPE!$AA:$AB,2,0),"") | I10: 10009436 | J10: =IFERROR(VLOOKUP(I10,Materiales!$A:$H,8,0),"") | K10: =IFERROR(VLOOKUP(I10,Materiales!$A:$G,7,0),"") | L10: 20220516 | M10: 20240822 | N10: 249.61 | O10: =IFERROR(VLOOKUP(A10,Flete!$A:$J,10,0),"") | P10: TN | Q10: =IFERROR(IFERROR(VLOOKUP(A10,TRAOPE!$A:$U,21,0),VLOOKUP(B10,TRAOPE!$A:$U,21,0)),"") | R10: =IFERROR(IFERROR(VLOOKUP(A10,TRAOPE!$A:$W,23,0),VLOOKUP(B10,TRAOPE!$A:$W,23,0)),"") | S10: =IF(AND(P10="TN",R10="TN"),N10+N(O10),IF(G10&""="1",N(K10)*N10,(N10+N(O10))*N(K10))) | T10: =IF(Q10="","",Q10-S10)
A11: =CONCATENATE(C11,E11,F11,I11) | B11: =CONCATENATE(C11,E11,I11) | C11: 900000023 | D11: =IFERROR(VLOOKUP(C11,TRAOPE!$G:$H,2,0),"") | E11: DW75 | F11: D312 | G11: =IFERROR(VLOOKUP(A11,Flete!$A:$E,5,0),"") | H11: =IFERROR(VLOOKUP(F11,TRAOPE!$AA:$AB,2,0),"") | I11: 10031878 | J11: =IFERROR(VLOOKUP(I11,Materiales!$A:$H,8,0),"") | K11: =IFERROR(VLOOKUP(I11,Materiales!$A:$G,7,0),"") | L11: 20220516 | M11: 20240822 | N11: 267.26 | O11: =IFERROR(VLOOKUP(A11,Flete!$A:$J,10,0),"") | P11: TN | Q11: =IFERROR(IFERROR(VLOOKUP(A11,TRAOPE!$A:$U,21,0),VLOOKUP(B11,TRAOPE!$A:$U,21,0)),"") | R11: =IFERROR(IFERROR(VLOOKUP(A11,TRAOPE!$A:$W,23,0),VLOOKUP(B11,TRAOPE!$A:$W,23,0)),"") | S11: =IF(AND(P11="TN",R11="TN"),N11+N(O11),IF(G11&""="1",N(K11)*N11,(N11+N(O11))*N(K11))) | T11: =IF(Q11="","",Q11-S11)
A12: =CONCATENATE(C12,E12,F12,I12) | B12: =CONCATENATE(C12,E12,I12) | C12: 900000023 | D12: =IFERROR(VLOOKUP(C12,TRAOPE!$G:$H,2,0),"") | E12: DW75 | F12: D312 | G12: =IFERROR(VLOOKUP(A12,Flete!$A:$E,5,0),"") | H12: =IFERROR(VLOOKUP(F12,TRAOPE!$AA:$AB,2,0),"") | I12: 10032115 | J12: =IFERROR(VLOOKUP(I12,Materiales!$A:$H,8,0),"") | K12: =IFERROR(VLOOKUP(I12,Materiales!$A:$G,7,0),"") | L12: 20220516 | M12: 20240822 | N12: 255.79 | O12: =IFERROR(VLOOKUP(A12,Flete!$A:$J,10,0),"") | P12: TN | Q12: =IFERROR(IFERROR(VLOOKUP(A12,TRAOPE!$A:$U,21,0),VLOOKUP(B12,TRAOPE!$A:$U,21,0)),"") | R12: =IFERROR(IFERROR(VLOOKUP(A12,TRAOPE!$A:$W,23,0),VLOOKUP(B12,TRAOPE!$A:$W,23,0)),"") | S12: =IF(AND(P12="TN",R12="TN"),N12+N(O12),IF(G12&""="1",N(K12)*N12,(N12+N(O12))*N(K12))) | T12: =IF(Q12="","",Q12-S12)
A13: =CONCATENATE(C13,E13,F13,I13) | B13: =CONCATENATE(C13,E13,I13) | C13: 900000023 | D13: =IFERROR(VLOOKUP(C13,TRAOPE!$G:$H,2,0),"") | E13: DW75 | F13: D312 | G13: =IFERROR(VLOOKUP(A13,Flete!$A:$E,5,0),"") | H13: =IFERROR(VLOOKUP(F13,TRAOPE!$AA:$AB,2,0),"") | I13: 10032164 | J13: =IFERROR(VLOOKUP(I13,Materiales!$A:$H,8,0),"") | K13: =IFERROR(VLOOKUP(I13,Materiales!$A:$G,7,0),"") | L13: 20220516 | M13: 20240822 | N13: 274.59 | O13: =IFERROR(VLOOKUP(A13,Flete!$A:$J,10,0),"") | P13: TN | Q13: =IFERROR(IFERROR(VLOOKUP(A13,TRAOPE!$A:$U,21,0),VLOOKUP(B13,TRAOPE!$A:$U,21,0)),"") | R13: =IFERROR(IFERROR(VLOOKUP(A13,TRAOPE!$A:$W,23,0),VLOOKUP(B13,TRAOPE!$A:$W,23,0)),"") | S13: =IF(AND(P13="TN",R13="TN"),N13+N(O13),IF(G13&""="1",N(K13)*N13,(N13+N(O13))*N(K13))) | T13: =IF(Q13="","",Q13-S13)
A14: =CONCATENATE(C14,E14,F14,I14) | B14: =CONCATENATE(C14,E14,I14) | C14: 900000023 | D14: =IFERROR(VLOOKUP(C14,TRAOPE!$G:$H,2,0),"") | E14: DW75 | F14: D312 | G14: =IFERROR(VLOOKUP(A14,Flete!$A:$E,5,0),"") | H14: =IFERROR(VLOOKUP(F14,TRAOPE!$AA:$AB,2,0),"") | I14: 10036583 | J14: =IFERROR(VLOOKUP(I14,Materiales!$A:$H,8,0),"") | K14: =IFERROR(VLOOKUP(I14,Materiales!$A:$G,7,0),"") | L14: 20220516 | M14: 20240822 | N14: 247.59 | O14: =IFERROR(VLOOKUP(A14,Flete!$A:$J,10,0),"") | P14: TN | Q14: =IFERROR(IFERROR(VLOOKUP(A14,TRAOPE!$A:$U,21,0),VLOOKUP(B14,TRAOPE!$A:$U,21,0)),"") | R14: =IFERROR(IFERROR(VLOOKUP(A14,TRAOPE!$A:$W,23,0),VLOOKUP(B14,TRAOPE!$A:$W,23,0)),"") | S14: =IF(AND(P14="TN",R14="TN"),N14+N(O14),IF(G14&""="1",N(K14)*N14,(N14+N(O14))*N(K14))) | T14: =IF(Q14="","",Q14-S14)
A15: =CONCATENATE(C15,E15,F15,I15) | B15: =CONCATENATE(C15,E15,I15) | C15: 900000023 | D15: =IFERROR(VLOOKUP(C15,TRAOPE!$G:$H,2,0),"") | E15: DW75 | F15: D327 | G15: =IFERROR(VLOOKUP(A15,Flete!$A:$E,5,0),"") | H15: =IFERROR(VLOOKUP(F15,TRAOPE!$AA:$AB,2,0),"") | I15: 10000742 | J15: =IFERROR(VLOOKUP(I15,Materiales!$A:$H,8,0),"") | K15: =IFERROR(VLOOKUP(I15,Materiales!$A:$G,7,0),"") | L15: 20220516 | M15: 20240822 | N15: 159.27 | O15: =IFERROR(VLOOKUP(A15,Flete!$A:$J,10,0),"") | P15: TN | Q15: =IFERROR(IFERROR(VLOOKUP(A15,TRAOPE!$A:$U,21,0),VLOOKUP(B15,TRAOPE!$A:$U,21,0)),"") | R15: =IFERROR(IFERROR(VLOOKUP(A15,TRAOPE!$A:$W,23,0),VLOOKUP(B15,TRAOPE!$A:$W,23,0)),"") | S15: =IF(AND(P15="TN",R15="TN"),N15+N(O15),IF(G15&""="1",N(K15)*N15,(N15+N(O15))*N(K15))) | T15: =IF(Q15="","",Q15-S15)
... A403: =CONCATENATE(C403,E403,F403,I403) | B403: =CONCATENATE(C403,E403,I403) | C403: 900009317 | D403: =IFERROR(VLOOKUP(C403,TRAOPE!$G:$H,2,0),"") | E403: DW75 | F403: EQ86 | G403: =IFERROR(VLOOKUP(A403,Flete!$A:$E,5,0),"") | H403: =IFERROR(VLOOKUP(F403,TRAOPE!$AA:$AB,2,0),"") | I403: 10269225 | J403: =IFERROR(VLOOKUP(I403,Materiales!$A:$H,8,0),"") | K403: =IFERROR(VLOOKUP(I403,Materiales!$A:$G,7,0),"") | L403: 20260601 | M403: 99991231 | N403: 372.38 | O403: =IFERROR(VLOOKUP(A403,Flete!$A:$J,10,0),"") | P403: TN | Q403: =IFERROR(IFERROR(VLOOKUP(A403,TRAOPE!$A:$U,21,0),VLOOKUP(B403,TRAOPE!$A:$U,21,0)),"") | R403: =IFERROR(IFERROR(VLOOKUP(A403,TRAOPE!$A:$W,23,0),VLOOKUP(B403,TRAOPE!$A:$W,23,0)),"") | S403: =IF(AND(P403="TN",R403="TN"),N403+N(O403),IF(G403&""="1",N(K403)*N403,(N403+N(O403))*N(K403))) | T403: =IF(Q403="","",Q403-S403)

Sheet MP
A1: No. SF | B1: Cedis | C1: Destino | D1: No. Material | E1: Nombre Material | F1: Importe MP | G1: Moneda | H1: Cantidad | I1: UM | J1: C | K1: Inicio Vigencia | L1: Fin Vigencia
A2: 900000023 | B2: DW75 | C2: D278 | D2: 10000742 | K2: 20220516 | L2: 20240822
A3: 900000023 | B3: DW75 | C3: D278 | D3: 10009436 | F3: 249.61 | I3: TN | K3: 20220516 | L3: 20240822
A4: 900000023 | B4: DW75 | C4: D278 | D4: 10031878 | F4: 267.26 | I4: TN | K4: 20220516 | L4: 20240822
A5: 900000023 | B5: DW75 | C5: D278 | D5: 10032115 | F5: 255.79 | I5: TN | K5: 20220516 | L5: 20240822
A6: 900000023 | B6: DW75 | C6: D278 | D6: 10032164 | F6: 274.59 | I6: TN | K6: 20220516 | L6: 20240822
A7: 900000023 | B7: DW75 | C7: D278 | D7: 10036583 | F7: 247.59 | I7: TN | K7: 20220516 | L7: 20240822
A8: 900000023 | B8: DW75 | C8: D312 | D8: 10000742 | F8: 159.27 | I8: TN | K8: 20220516 | L8: 20240822
A9: 900000023 | B9: DW75 | C9: D312 | D9: 10009436 | F9: 249.61 | I9: TN | K9: 20220516 | L9: 20240822
A10: 900000023 | B10: DW75 | C10: D312 | D10: 10031878 | F10: 267.26 | I10: TN | K10: 20220516 | L10: 20240822
A11: 900000023 | B11: DW75 | C11: D312 | D11: 10032115 | F11: 255.79 | I11: TN | K11: 20220516 | L11: 20240822
A12: 900000023 | B12: DW75 | C12: D312 | D12: 10032164 | F12: 274.59 | I12: TN | K12: 20220516 | L12: 20240822
A13: 900000023 | B13: DW75 | C13: D312 | D13: 10036583 | F13: 247.59 | I13: TN | K13: 20220516 | L13: 20240822
A14: 900000023 | B14: DW75 | C14: D327 | D14: 10000742 | F14: 159.27 | I14: TN | K14: 20220516 | L14: 20240822
... A402: 900009317 | B402: DW75 | C402: EQ86 | D402: 10269225 | F402: 372.38 | I402: TN | K402: 20260601 | L402: 99991231

Sheet Flete
A1: Concat1 | B1: No. SF | C1: Cedis | D1: Destino | E1: Cond. Exp. | F1: Material | H1: Nombre Material | J1: Importe Flete | K1: Moneda | L1: Cantidad | M1: UM | N1: C | P1: Inicio Vigencia | Q1: Fin Vigencia
A2: 900000023DW75D27810000742 | B2: 900000023 | C2: DW75 | D2: D278 | E2: 1 | F2: 10000742 | J2: 74.35 | M2: TN | P2: 20220331 | Q2: 20240822
A3: 900000023DW75D27810009436 | B3: 900000023 | C3: DW75 | D3: D278 | E3: 1 | F3: 10009436 | J3: 79.5 | M3: TN | P3: 20220331 | Q3: 20240822
A4: 900000023DW75D27810031878 | B4: 900000023 | C4: DW75 | D4: D278 | E4: 1 | F4: 10031878 | J4: 91.69 | M4: TN | P4: 20220331 | Q4: 20240822
A5: 900000023DW75D27810032115 | B5: 900000023 | C5: DW75 | D5: D278 | E5: 1 | F5: 10032115 | J5: 87.76 | M5: TN | P5: 20220331 | Q5: 20240822
A6: 900000023DW75D27810032164 | B6: 900000023 | C6: DW75 | D6: D278 | E6: 1 | F6: 10032164 | J6: 87.45 | M6: TN | P6: 20220331 | Q6: 20240822
A7: 900000023DW75D27810036583 | B7: 900000023 | C7: DW75 | D7: D278 | E7: 1 | F7: 10036583 | J7: 89.44 | M7: TN | P7: 20220331 | Q7: 20240822
A8: 900000023DW75D31210000742 | B8: 900000023 | C8: DW75 | D8: D312 | E8: 1 | F8: 10000742 | J8: 76.97 | M8: TN | P8: 20220331 | Q8: 20240822
A9: 900000023DW75D31210009436 | B9: 900000023 | C9: DW75 | D9: D312 | E9: 1 | F9: 10009436 | J9: 82.3 | M9: TN | P9: 20220331 | Q9: 20240822
A10: 900000023DW75D31210031878 | B10: 900000023 | C10: DW75 | D10: D312 | E10: 1 | F10: 10031878 | J10: 94.92 | M10: TN | P10: 20220331 | Q10: 20240822
A11: 900000023DW75D31210032115 | B11: 900000023 | C11: DW75 | D11: D312 | E11: 1 | F11: 10032115 | J11: 90.84 | M11: TN | P11: 20220331 | Q11: 20240822
A12: 900000023DW75D31210032164 | B12: 900000023 | C12: DW75 | D12: D312 | E12: 1 | F12: 10032164 | J12: 90.53 | M12: TN | P12: 20220331 | Q12: 20240822
A13: 900000023DW75D31210036583 | B13: 900000023 | C13: DW75 | D13: D312 | E13: 1 | F13: 10036583 | J13: 92.59 | M13: TN | P13: 20220331 | Q13: 20240822
... A410: 900009317DW75EQ8610269225 | B410: 900009317 | C410: DW75 | D410: EQ86 | E410: 1 | F410: 10269225 | J410: 62.84 | M410: TN | P410: 20260601 | Q410: 99991231

Sheet Materiales
A1: Material | B1: TpMt | C1: Denom | D1: UMA | E1: Contador | F1: UMB | G1: PV | H1: Nombre Material
A2: 10000001 | B2: ZFER | C2: 1000 | D2: M3 | E2: 1000 | F2: TN | G2: 1262 | H2: GRAVA ANDESITA 10 MM (3/8")
A3: 10000003 | B3: ZFER | C3: 1000 | D3: M3 | E3: 1000 | F3: TN | G3: 1443 | H3: GRAVA CALIZA 10 MM (3/8")
A4: 10000006 | B4: ZFER | C4: 1000 | D4: M3 | E4: 1000 | F4: TN | G4: 1490 | H4: GRAVA RIO 10 MM (3/8")
A5: 10000007 | B5: ZFER | C5: 1000 | D5: M3 | E5: 1000 | F5: TN | G5: 1488 | H5: GRAVA BASALTO 13 MM (1/2")
A6: 10000008 | B6: ZFER | C6: 1000 | D6: M3 | E6: 1000 | F6: TN | G6: 1358 | H6: GRAVA CALIZA 13 MM (1/2")
A7: 10000011 | B7: ZFER | C7: 1000 | D7: M3 | E7: 1000 | F7: TN | G7: 1323 | H7: GRAVA ANDESITA 20 MM (3/4")
A8: 10000013 | B8: ZFER | C8: 1000 | D8: M3 | E8: 1000 | F8: TN | G8: 1514 | H8: GRAVA BASALTO 20 MM (3/4")
A9: 10000014 | B9: ZFER | C9: 1000 | D9: M3 | E9: 1000 | F9: TN | G9: 1400 | H9: GRAVA CALIZA 20 MM (3/4")
A10: 10000015 | B10: ZFER | C10: 1000 | D10: M3 | E10: 1000 | F10: TN | G10: 1410 | H10: GRAVA GRANITO 20 MM (3/4")
A11: 10000017 | B11: ZFER | C11: 1000 | D11: M3 | E11: 1000 | F11: TN | G11: 1475 | H11: GRAVA RIOLITA 20 MM (3/4")
A12: 10000019 | B12: ZFER | C12: 1000 | D12: M3 | E12: 1000 | F12: TN | G12: 1515 | H12: GRAVA RIO 20 MM (3/4")
A13: 10000020 | B13: ZFER | C13: 1000 | D13: M3 | E13: 1 | F13: TN | G13: 1 | H13: GRAVA MAQUILA 40MM (1 1/2")
... A2291: 10268770 | B2291: ZFE3 | C2291: 1000 | D2291: M3 | E2291: 1000 | F2291: TN | G2291: 1240 | H2291: MP GRAVA TRIT CALIZA 40MM 1 1/2" - ESP
A2292: 10268901 | B2292: ZFE3 | C2292: 1000 | D2292: M3 | E2292: 1000 | G2292: 1560 | H2292: MP GRAVA ANDESITA GRIS 3/4" - CAPADA
A2293: 10267983 | C2293: 1000 | G2293: 1800 | H2293: ESCORIA ALTO HORNO 3/4
A2294: 10268996 | C2294: 1000 | G2294: 1329 | H2294: GRAVA TRITURADA CALIZA 40 MM - 11/2"
A2295: 10269072 | C2295: 1000 | G2295: 1700 | H2295: BASE HIDRÁULICA SCREEN
A2296: 10269225 | B2296: ZFE3 | C2296: 1000 | D2296: M3 | E2296: 1000 | G2296: 1289 | H2296: MP ARENA CALIZA LAVADA MALLA 4 - DELTA I
A2297: 10269245 | B2297: ZFE3 | C2297: 1000 | D2297: M3 | E2297: 1000 | G2297: 1410 | H2297: MP GRAVA TRITURADA CALIZA 3/8 - 10MM
A2298: 10269246 | B2298: ZFE3 | C2298: 1000 | D2298: M3 | E2298: 1000 | G2298: 1400 | H2298: MP GRAVA TRITURADA CALIZA 1 1/2 - 40MM
A2299: 10269247 | B2299: ZFE3 | C2299: 1000 | D2299: M3 | E2299: 1000 | G2299: 1560 | H2299: MP ARENA TRIT CALIZA M-4
A2300: 10270431 | B2300: ZFE3 | C2300: 1000 | D2300: M3 | E2300: 1000 | G2300: 1423 | H2300: MP GRAVA RIOLITA 13 MM - 1/2"
A2301: 10270898 | B2301: ZFE3 | C2301: 1000 | D2301: M3 | E2301: 1000 | G2301: 1551 | H2301: MP BASE H. TRIT. BASALTO 1 1/2" A FINOS
A2302: 10270911 | B2302: ZFE3 | C2302: 1000 | D2302: M3 | E2302: 1000 | G2302: 1360 | H2302: MP GRAVA TRIT. BASALTO 40 MM - 1 1/2"
A2303: 10270912 | B2303: ZFE3 | C2303: 1000 | D2303: M3 | E2303: 1000 | G2303: 1589 | H2303: MP ARENA TRIT. BASALTO MALLA 4
A2304: 10270913 | B2304: ZFE3 | C2304: 1000 | D2304: M3 | E2304: 1000 | G2304: 1395 | H2304: MP GRAVA TRIT. BASALTO 20 MM - 3/4
A2305: 10270914 | B2305: ZFE3 | C2305: 1000 | D2305: M3 | E2305: 1000 | G2305: 1623 | H2305: MP ARENA ANDESITA BC
A2306: 10270824 | B2306: M3 | C2306: 1000 | D2306: M3 | E2306: 10007640 | G2306: 1325 | H2306: MP ARENA TRITURADA CALIZA MALLA 5
A2307: 10270825 | B2307: M3 | C2307: 1000 | D2307: M3 | E2307: 10000003 | G2307: 1242 | H2307: MP GRAVA TRITURADA CALIZA 10MM (3/8”)
... A2319: 10272527 | B2319: ZFE3 | C2319: 1000 | D2319: M3 | E2319: 1000 | G2319: 1620 | H2319: CNC - NO CLASIFICADO
A2320: 10000332 | C2320: 1000 | D2320: M3 | E2320: 1000 | G2320: 800 | H2320: Grava Triturada Pomez - Jal 20 mm - 3/4"
A2321: 10273001 | B2321: ZFE3 | C2321: 1000 | D2321: M3 | E2321: 1000 | G2321: 1688 | H2321: MP ARENA TRIT. BASALTO MALLA 4
A2322: 10273002 | B2322: ZFE3 | C2322: 1000 | D2322: M3 | E2322: 1000 | G2322: 1466 | H2322: MP GRAVA TRIT. BASALTO 20 MM - 3/4"
A2323: 10273351 | B2323: ZFE3 | C2323: 1000 | D2323: M3 | E2323: 1000 | G2323: 1612 | H2323: MP ARENA TRIT. CALIZA MALLA 4
A2324: 10273352 | B2324: ZFE3 | C2324: 1000 | D2324: M3 | E2324: 1000 | G2324: 1492 | H2324: MP GRAVA TRIT. CALIZA 20 MM - 3/4"
A2325: 10271724 | B2325: ZFE3 | C2325: 1000 | D2325: M3 | E2325: 1000 | G2325: 1900 | H2325: MP RESIDUO DE CONCRETO
A2326: 10000677 | C2326: 1000 | D2326: M3 | G2326: 1164 | H2326: Grava Triturada Caliza 20 mm - 3/4"
A2327: 10274190 | B2327: ZFE3 | C2327: 1000 | D2327: M3 | E2327: 1000 | G2327: 1800 | H2327: MP BASE HIDRAULICA ANDESITA 70-30
A2328: 10274601 | B2328: ZFE3 | C2328: 1000 | D2328: M3 | E2328: 1000 | G2328: 1447 | H2328: MP ARENA BASALTO N° 4
A2329: 10274754 | B2329: ZFE3 | C2329: 1000 | D2329: M3 | E2329: 1000 | G2329: 1397 | H2329: MP GRAVA TRIT. ANDESITA 20 MM - 3/4"
A2330: 10169718 | B2330: ZFE3 | C2330: 1000 | D2330: M3 | E2330: 1000 | G2330: 1400 | H2330: GRAVA CLASIFICADA RÍO 40 MM - 1 1/2"
A2331: 10274813 | B2331: ZFE3 | C2331: 1000 | D2331: M3 | E2331: 1000 | G2331: 1448 | H2331: MP ARENA TRIT RÍO MALLA 4
A2332: 10274815 | B2332: ZFE3 | C2332: 1000 | D2332: M3 | E2332: 1000 | G2332: 1366 | H2332: MP ARENA CLASIFICADA RÍO MALLA 5
A2333: 10274816 | B2333: ZFE3 | C2333: 1000 | D2333: M3 | E2333: 1000 | G2333: 1472 | H2333: MP GRAVA CLASIF RÍO 20 MM - 3/4"
A2334: 10275113 | B2334: ZFE3 | C2334: 1000 | D2334: M3 | E2334: 1000 | G2334: 1409 | H2334: MP ARENA TRIT ANDESITA MALLA 4
A2335: 10275114 | B2335: ZFE3 | C2335: 1000 | D2335: M3 | E2335: 1000 | G2335: 1418 | H2335: MP ARENA CLASIF RIO MALLA 4 - LAVADO
A2336: 10275115 | B2336: ZFE3 | C2336: 1000 | D2336: M3 | E2336: 1000 | G2336: 1259 | H2336: MP ARENA TRIT ANDESITA MALLA 4
A2337: 10275116 | B2337: ZFE3 | C2337: 1000 | D2337: M3 | E2337: 1000 | G2337: 1401 | H2337: MP GRAVA TRIT ANDESITA 3/4 - 20 MM
A2338: 10275118 | B2338: ZFE3 | C2338: 1000 | D2338: M3 | E2338: 1000 | G2338: 1401 | H2338: MP ARENA TRIT ANDESITA MALLA 4
... A2361: 10280049 | B2361: ZFE3 | C2361: 1000 | D2361: M3 | E2361: 1000 | G2361: 1584 | H2361: MP B. HID CALIZA 40% FINOS Y 60% GRUESOS
A2362: 10280365 | C2362: 1000 | D2362: M3 | E2362: 1000 | G2362: 1274 | H2362: MP GRAVA BASALTO 20 MM -3/4
A2363: 10280538 | B2363: ZFE3 | C2363: 1000 | D2363: M3 | E2363: 1000 | G2363: 1262 | H2363: MP GRAVA TRIT BASALTO 3/8 - 10MM
A2364: 10280679 | B2364: ZFE3 | C2364: 1000 | D2364: M3 | E2364: 1000 | G2364: 1349 | H2364: MP GRAVA CLASIF RÍO 13MM - 1/2"
A2365: 10281171 | B2365: ZFE3 | C2365: 1000 | D2365: M3 | E2365: 1000 | G2365: 1271 | H2365: MP GRAVA TRIT CALIZA 10MM - 3/8"
A2366: 10281183 | B2366: ZFE3 | C2366: 1000 | D2366: M3 | E2366: 1000 | G2366: 1468 | H2366: MP ARENA TRIT CALIZA MALLA 4
A2367: 10281384 | B2367: ZFE3 | C2367: 1000 | D2367: M3 | E2367: 1000 | G2367: 1285 | H2367: MP GRAVA BASALTO 40 MM (1 1/2")
A2368: 10281379 | B2368: ZFE3 | C2368: 1000 | D2368: M3 | E2368: 1000 | G2368: 1536 | H2368: MP ARENA CLASIF. RÍO MALLA 4
A2369: 10281450 | B2369: ZFE3 | C2369: 1000 | D2369: M3 | E2369: 1000 | G2369: 1325 | H2369: MP GRAVA CLASIF. RIO 20MM - 3/4
A2370: 10281451 | B2370: ZFE3 | C2370: 1000 | D2370: M3 | E2370: 1000 | G2370: 1564 | H2370: MP ARENA CLASIF. RÍO MALLA 4
A2371: 10281452 | B2371: ZFE3 | C2371: 1000 | D2371: M3 | E2371: 1000 | G2371: 1427 | H2371: MP GRAVA CLASIF. RIO 20MM - 3/4

Sheet TRAOPE
A1: Concat1 | B1: Contrato_Pos | C1: Doc. Compras | D1: Pos | E1: Org.compras | F1: Grp-Compr. | G1: Ship From | H1: Nombre SF | I1: Proveedor | J1: Nombre Prov | K1: Cond. Pago | L1: Descr. Cond Pago | M1: Material | N1: Descripción | O1: Centro | P1: Descripción Centro | Q1: In.perído validez | R1: Fin perído validez | S1: Válido de | T1: Validez a | U1: Precio neto pedido | V1: Moneda | W1: UM Precio Pedido | X1: Importe Condición | Y1: Moneda KONP | Z1: UM Ctd Base | AA1: Destino | AB1: Nombre Destino | AC1: Cuenta de mayor | AD1: Centro de costo | AE1: Cond. Exp. | AF1: Descr. Cond. Exp. | AG1: Peso Vol. | AH1: UMB | AI1: Ind. Oblig. Conf. Ped. | AJ1: Ctrl-Conf. | AK1: IVA | AL1: Modif_Date | AM1: Ruta
A2: 900008644DW75D34910252010 | B2: 4600068853-20 | C2: 4600068853 | D2: 20 | E2: MXPO | F2: MXL | G2: 900008644 | H2: SF TC-ED CGC JABALI PLAYA | I2: 5092440 | J2: FERNANDEZ HERNANDEZ YURI HERNAN | K2: Z06 | L2: (AP) 45 Dias | M2: 10252010 | N2: GRAVA TRIT CALIZA 20MM 3/4" - I JABALI P | O2: DW75 | P2: MX-CED. Q. ROO NORTE | Q2: 20231130 | R2: 20281231 | S2: 20240625 | T2: 20291231 | U2: 576.6 | V2: MXN | W2: M3 | X2: 166.6 | Y2: MXN | Z2: M3 | AA2: D349 | AB2: PD0300 PETEMPICH | AC2: 56103637 | AD2: 6644321540 | AE2: 4 | AF2: ENTREGA DIRECTA | AG2: 1.083 | AH2: M3 | AI2: X | AJ2: 4 | AK2: V4 | AL2: 20240625 | AM2: DW75-900008644-D349-10252010-4
A3: 900008644DW75D27810252010 | B3: 4600068853-30 | C3: 4600068853 | D3: 30 | E3: MXPO | F3: MXL | G3: 900008644 | H3: SF TC-ED CGC JABALI PLAYA | I3: 5092440 | J3: FERNANDEZ HERNANDEZ YURI HERNAN | K3: Z06 | L3: (AP) 45 Dias | M3: 10252010 | N3: GRAVA TRIT CALIZA 20MM 3/4" - I JABALI P | O3: DW75 | P3: MX-CED. Q. ROO NORTE | Q3: 20231130 | R3: 20281231 | S3: 20240625 | T3: 20291231 | U3: 728.5 | V3: MXN | W3: M3 | X3: 318.5 | Y3: MXN | Z3: M3 | AA3: D278 | AB3: PD055 CANCUN | AC3: 56103637 | AD3: 6644321540 | AE3: 4 | AF3: ENTREGA DIRECTA | AG3: 1.083 | AH3: M3 | AI3: X | AJ3: 4 | AK3: V4 | AL3: 20240625 | AM3: DW75-900008644-D278-10252010-4
A4: 900008644DW75D34310252010 | B4: 4600068853-50 | C4: 4600068853 | D4: 50 | E4: MXPO | F4: MXL | G4: 900008644 | H4: SF TC-ED CGC JABALI PLAYA | I4: 5092440 | J4: FERNANDEZ HERNANDEZ YURI HERNAN | K4: Z06 | L4: (AP) 45 Dias | M4: 10252010 | N4: GRAVA TRIT CALIZA 20MM 3/4" - I JABALI P | O4: DW75 | P4: MX-CED. Q. ROO NORTE | Q4: 20231130 | R4: 20281231 | S4: 20240625 | T4: 20291231 | U4: 659.9 | V4: MXN | W4: M3 | X4: 249.9 | Y4: MXN | Z4: M3 | AA4: D343 | AB4: PD0270 RIVIERA MAYA | AC4: 56103637 | AD4: 6644321540 | AE4: 4 | AF4: ENTREGA DIRECTA | AG4: 1.083 | AH4: M3 | AI4: X | AJ4: 4 | AK4: V4 | AL4: 20240625 | AM4: DW75-900008644-D343-10252010-4
A5: 900008652DW75D34910252010 | B5: 4600068855-20 | C5: 4600068855 | D5: 20 | E5: MXPO | F5: MXL | G5: 900008652 | H5: SF TC-ED IFLORES JABALI PLAYA | I5: 5005320 | J5: FLORES CAUICH ISMAEL | K5: N90 | L5: (AP) NAFIN 90 Dias | M5: 10252010 | N5: GRAVA TRIT CALIZA 20MM 3/4" - I JABALI P | O5: DW75 | P5: MX-CED. Q. ROO NORTE | Q5: 20231130 | R5: 20281231 | S5: 20231214 | T5: 20281231 | U5: 745 | V5: MXN | W5: M3 | X5: 177 | Y5: MXN | Z5: M3 | AA5: D349 | AB5: PD0300 PETEMPICH | AC5: 56103637 | AD5: 6644321540 | AE5: 4 | AF5: ENTREGA DIRECTA | AG5: 1.083 | AH5: M3 | AI5: X | AJ5: 4 | AK5: V4 | AL5: 20231214 | AM5: DW75-900008652-D349-10252010-4
A6: 900007862DW7510222899 | B6: 4600056560-20 | C6: 4600056560 | D6: 20 | E6: MXPO | F6: MXL | G6: 900007862 | H6: SF TC_MOSECA_INFRA | I6: 5046324 | J6: MORTEROS SECOS DEL CARIBE SA DE CV | K6: Z06 | L6: (AP) 45 Dias | M6: 10222899 | N6: GRAVA TRITURADA CALIZA 20 MM - 3/4" | O6: DW75 | P6: MX-CED. Q. ROO NORTE | Q6: 20230215 | R6: 20281231 | S6: 20250611 | T6: 20301231 | U6: 285.22 | V6: MXN | W6: M3 | X6: 0 | Y6: MXN | Z6: M3 | AC6: 56103637 | AD6: 6644321540 | AE6: 1 | AF6: ENTREGADO | AG6: 1.218 | AH6: M3 | AI6: X | AJ6: 4 | AK6: V4 | AL6: 20250618 | AM6: DW75-900007862-10222899
A7: 900006554DW75D34910147933 | B7: 4600050647-80 | C7: 4600050647 | D7: 80 | E7: MXPO | F7: MXL | G7: 900006554 | H7: TC-ED- MOSECA | I7: 5046324 | J7: MORTEROS SECOS DEL CARIBE SA DE CV | K7: Z06 | L7: (AP) 45 Dias | M7: 10147933 | N7: ARENA TRITURADA CALIZA MALLA 4 LAVADO | O7: DW75 | P7: MX-CED. Q. ROO NORTE | Q7: 20210712 | R7: 20291231 | S7: 20250611 | T7: 20301231 | U7: 465.67 | V7: MXN | W7: M3 | X7: 125.28 | Y7: MXN | Z7: M3 | AA7: D349 | AB7: PD0300 PETEMPICH | AC7: 56103638 | AD7: 6644321540 | AE7: 4 | AF7: ENTREGA DIRECTA | AG7: 1.376 | AH7: M3 | AI7: X | AJ7: 4 | AK7: V4 | AL7: 20250618 | AM7: DW75-900006554-D349-10147933-4
A8: 900006554DW75D34310151191 | B8: 4600050647-30 | C8: 4600050647 | D8: 30 | E8: MXPO | F8: MXL | G8: 900006554 | H8: TC-ED- MOSECA | I8: 5046324 | J8: MORTEROS SECOS DEL CARIBE SA DE CV | K8: Z06 | L8: (AP) 45 Dias | M8: 10151191 | N8: GRAVA TRITURADA CALIZA 40MM 1 ½” | O8: DW75 | P8: MX-CED. Q. ROO NORTE | Q8: 20210712 | R8: 20291231 | S8: 20250611 | T8: 20301231 | U8: 344.73 | V8: MXN | W8: M3 | X8: 59.51 | Y8: MXN | Z8: M3 | AA8: D343 | AB8: PD0270 RIVIERA MAYA | AC8: 56103637 | AD8: 6644321540 | AE8: 4 | AF8: ENTREGA DIRECTA | AG8: 1.287 | AH8: M3 | AI8: X | AJ8: 4 | AK8: V4 | AL8: 20250618 | AM8: DW75-900006554-D343-10151191-4
A9: 900002370DW7510151191 | B9: 4600050628-60 | C9: 4600050628 | D9: 60 | E9: MXPO | F9: MXL | G9: 900002370 | H9: TC-MOSECA | I9: 5046324 | J9: MORTEROS SECOS DEL CARIBE SA DE CV | K9: Z06 | L9: (AP) 45 Dias | M9: 10151191 | N9: GRAVA TRITURADA CALIZA 40MM 1 ½” | O9: DW75 | P9: MX-CED. Q. ROO NORTE | Q9: 20210712 | R9: 20291231 | S9: 20250611 | T9: 20301231 | U9: 285.22 | V9: MXN | W9: M3 | X9: 0 | Y9: MXN | Z9: M3 | AC9: 56103637 | AD9: 6644321540 | AE9: 1 | AF9: ENTREGADO | AG9: 1.287 | AH9: M3 | AI9: X | AJ9: 4 | AK9: V4 | AL9: 20250618 | AM9: DW75-900002370-10151191
A10: 900009317DW7510269225 | B10: 4600071502-10 | C10: 4600071502 | D10: 10 | E10: MXPO | F10: MXL | G10: 900009317 | H10: SF TC-DELTA INFRA | I10: 5001811 | J10: DELTA PREMEZCLADO SA DE CV | K10: N90 | L10: (AP) NAFIN 90 Dias | M10: 10269225 | N10: MP ARENA CALIZA LAVADA MALLA 4 - DELTA I | O10: DW75 | P10: MX-CED. Q. ROO NORTE | Q10: 20250802 | R10: 20301231 | S10: 20250802 | T10: 20301231 | U10: 480 | V10: MXN | W10: M3 | X10: 0 | Y10: MXN | Z10: M3 | AC10: 56103638 | AD10: 6644321540 | AE10: 1 | AF10: ENTREGADO | AG10: 1.186 | AH10: M3 | AI10: X | AJ10: 4 | AK10: V4 | AL10: 20250807 | AM10: DW75-900009317-10269225
A11: 900002370DW7510043601 | B11: 4600050628-20 | C11: 4600050628 | D11: 20 | E11: MXPO | F11: MXL | G11: 900002370 | H11: TC-MOSECA | I11: 5046324 | J11: MORTEROS SECOS DEL CARIBE SA DE CV | K11: Z06 | L11: (AP) 45 Dias | M11: 10043601 | N11: Grava Triturada Caliza 20 mm - 3/4" | O11: DW75 | P11: MX-CED. Q. ROO NORTE | Q11: 20210712 | R11: 20291231 | S11: 20250611 | T11: 20301231 | U11: 285.22 | V11: MXN | W11: M3 | X11: 0 | Y11: MXN | Z11: M3 | AC11: 56103637 | AD11: 6644321540 | AE11: 1 | AF11: ENTREGADO | AG11: 1.175 | AH11: M3 | AI11: X | AJ11: 4 | AK11: V4 | AL11: 20250618 | AM11: DW75-900002370-10043601
A12: 900006554DW75D34310043601 | B12: 4600050647-460 | C12: 4600050647 | D12: 460 | E12: MXPO | F12: MXL | G12: 900006554 | H12: TC-ED- MOSECA | I12: 5046324 | J12: MORTEROS SECOS DEL CARIBE SA DE CV | K12: Z06 | L12: (AP) 45 Dias | M12: 10043601 | N12: Grava Triturada Caliza 20 mm - 3/4" | O12: DW75 | P12: MX-CED. Q. ROO NORTE | Q12: 20210712 | R12: 20291231 | S12: 20250611 | T12: 20301231 | U12: 344.73 | V12: MXN | W12: M3 | X12: 59.51 | Y12: MXN | Z12: M3 | AA12: D343 | AB12: PD0270 RIVIERA MAYA | AC12: 56103637 | AD12: 6644321540 | AE12: 4 | AF12: ENTREGA DIRECTA | AG12: 1.175 | AH12: M3 | AI12: X | AJ12: 4 | AK12: V4 | AL12: 20250618 | AM12: DW75-900006554-D343-10043601-4
A13: 900006554DW75D34910043600 | B13: 4600050647-110 | C13: 4600050647 | D13: 110 | E13: MXPO | F13: MXL | G13: 900006554 | H13: TC-ED- MOSECA | I13: 5046324 | J13: MORTEROS SECOS DEL CARIBE SA DE CV | K13: Z06 | L13: (AP) 45 Dias | M13: 10043600 | N13: Grava Triturada Caliza 13 mm - 1/2" | O13: DW75 | P13: MX-CED. Q. ROO NORTE | Q13: 20210712 | R13: 20291231 | S13: 20250611 | T13: 20301231 | U13: 410.5 | V13: MXN | W13: M3 | X13: 125.28 | Y13: MXN | Z13: M3 | AA13: D349 | AB13: PD0300 PETEMPICH | AC13: 56103637 | AD13: 6644321540 | AE13: 4 | AF13: ENTREGA DIRECTA | AG13: 1.177 | AH13: M3 | AI13: X | AJ13: 4 | AK13: V4 | AL13: 20250618 | AM13: DW75-900006554-D349-10043600-4
A14: 900007862DW7510222898 | B14: 4600056560-10 | C14: 4600056560 | D14: 10 | E14: MXPO | F14: MXL | G14: 900007862 | H14: SF TC_MOSECA_INFRA | I14: 5046324 | J14: MORTEROS SECOS DEL CARIBE SA DE CV | K14: Z06 | L14: (AP) 45 Dias | M14: 10222898 | N14: GRAVA TRITURADA CALIZA 40 MM - 1 1/2" | O14: DW75 | P14: MX-CED. Q. ROO NORTE | Q14: 20230215 | R14: 20281231 | S14: 20250611 | T14: 20301231 | U14: 285.22 | V14: MXN | W14: M3 | X14: 0 | Y14: MXN | Z14: M3 | AC14: 56103637 | AD14: 6644321540 | AE14: 1 | AF14: ENTREGADO | AG14: 1.237 | AH14: M3 | AI14: X | AJ14: 4 | AK14: V4 | AL14: 20250618 | AM14: DW75-900007862-10222898
A15: 900006554DW75D34310043600 | B15: 4600050647-450 | C15: 4600050647 | D15: 450 | E15: MXPO | F15: MXL | G15: 900006554 | H15: TC-ED- MOSECA | I15: 5046324 | J15: MORTEROS SECOS DEL CARIBE SA DE CV | K15: Z06 | L15: (AP) 45 Dias | M15: 10043600 | N15: Grava Triturada Caliza 13 mm - 1/2" | O15: DW75 | P15: MX-CED. Q. ROO NORTE | Q15: 20210712 | R15: 20291231 | S15: 20250611 | T15: 20301231 | U15: 344.73 | V15: MXN | W15: M3 | X15: 59.51 | Y15: MXN | Z15: M3 | AA15: D343 | AB15: PD0270 RIVIERA MAYA | AC15: 56103637 | AD15: 6644321540 | AE15: 4 | AF15: ENTREGA DIRECTA | AG15: 1.177 | AH15: M3 | AI15: X | AJ15: 4 | AK15: V4 | AL15: 20250618 | AM15: DW75-900006554-D343-10043600-4
A16: 900006554DW75D34310147933 | B16: 4600050647-470 | C16: 4600050647 | D16: 470 | E16: MXPO | F16: MXL | G16: 900006554 | H16: TC-ED- MOSECA | I16: 5046324 | J16: MORTEROS SECOS DEL CARIBE SA DE CV | K16: Z06 | L16: (AP) 45 Dias | M16: 10147933 | N16: ARENA TRITURADA CALIZA MALLA 4 LAVADO | O16: DW75 | P16: MX-CED. Q. ROO NORTE | Q16: 20210712 | R16: 20291231 | S16: 20250611 | T16: 20301231 | U16: 399.9 | V16: MXN | W16: M3 | X16: 59.51 | Y16: MXN | Z16: M3 | AA16: D343 | AB16: PD0270 RIVIERA MAYA | AC16: 56103638 | AD16: 6644321540 | AE16: 4 | AF16: ENTREGA DIRECTA | AG16: 1.376 | AH16: M3 | AI16: X | AJ16: 4 | AK16: V4 | AL16: 20250618 | AM16: DW75-900006554-D343-10147933-4
A17: 900006554DW75D27810043601 | B17: 4600050647-230 | C17: 4600050647 | D17: 230 | E17: MXPO | F17: MXL | G17: 900006554 | H17: TC-ED- MOSECA | I17: 5046324 | J17: MORTEROS SECOS DEL CARIBE SA DE CV | K17: Z06 | L17: (AP) 45 Dias | M17: 10043601 | N17: Grava Triturada Caliza 20 mm - 3/4" | O17: DW75 | P17: MX-CED. Q. ROO NORTE | Q17: 20210712 | R17: 20291231 | S17: 20250611 | T17: 20301231 | U17: 363.52 | V17: MXN | W17: M3 | X17: 78.3 | Y17: MXN | Z17: M3 | AA17: D278 | AB17: PD055 CANCUN | AC17: 56103637 | AD17: 6644321540 | AE17: 4 | AF17: ENTREGA DIRECTA | AG17: 1.175 | AH17: M3 | AI17: X | AJ17: 4 | AK17: V4 | AL17: 20250618 | AM17: DW75-900006554-D278-10043601-4
A18: 900006554DW75D27810045642 | B18: 4600050647-220 | C18: 4600050647 | D18: 220 | E18: MXPO | F18: MXL | G18: 900006554 | H18: TC-ED- MOSECA | I18: 5046324 | J18: MORTEROS SECOS DEL CARIBE SA DE CV | K18: Z06 | L18: (AP) 45 Dias | M18: 10045642 | N18: Arena Triturada Caliza Malla 4 | O18: DW75 | P18: MX-CED. Q. ROO NORTE | Q18: 20210712 | R18: 20291231 | S18: 20250611 | T18: 20301231 | U18: 418.69 | V18: MXN | W18: M3 | X18: 78.3 | Y18: MXN | Z18: M3 | AA18: D278 | AB18: PD055 CANCUN | AC18: 56103638 | AD18: 6644321540 | AE18: 4 | AF18: ENTREGA DIRECTA | AG18: 1.471 | AH18: M3 | AI18: X | AJ18: 4 | AK18: V4 | AL18: 20250618 | AM18: DW75-900006554-D278-10045642-4
A19: 900006554DW75D27810151191 | B19: 4600050647-20 | C19: 4600050647 | D19: 20 | E19: MXPO | F19: MXL | G19: 900006554 | H19: TC-ED- MOSECA | I19: 5046324 | J19: MORTEROS SECOS DEL CARIBE SA DE CV | K19: Z06 | L19: (AP) 45 Dias | M19: 10151191 | N19: GRAVA TRITURADA CALIZA 40MM 1 ½” | O19: DW75 | P19: MX-CED. Q. ROO NORTE | Q19: 20210712 | R19: 20291231 | S19: 20250611 | T19: 20301231 | U19: 363.52 | V19: MXN | W19: M3 | X19: 78.3 | Y19: MXN | Z19: M3 | AA19: D278 | AB19: PD055 CANCUN | AC19: 56103637 | AD19: 6644321540 | AE19: 4 | AF19: ENTREGA DIRECTA | AG19: 1.287 | AH19: M3 | AI19: X | AJ19: 4 | AK19: V4 | AL19: 20250618 | AM19: DW75-900006554-D278-10151191-4
A20: 900006554DW75D34910043601 | B20: 4600050647-100 | C20: 4600050647 | D20: 100 | E20: MXPO | F20: MXL | G20: 900006554 | H20: TC-ED- MOSECA | I20: 5046324 | J20: MORTEROS SECOS DEL CARIBE SA DE CV | K20: Z06 | L20: (AP) 45 Dias | M20: 10043601 | N20: Grava Triturada Caliza 20 mm - 3/4" | O20: DW75 | P20: MX-CED. Q. ROO NORTE | Q20: 20210712 | R20: 20291231 | S20: 20250611 | T20: 20301231 | U20: 410.5 | V20: MXN | W20: M3 | X20: 125.28 | Y20: MXN | Z20: M3 | AA20: D349 | AB20: PD0300 PETEMPICH | AC20: 56103637 | AD20: 6644321540 | AE20: 4 | AF20: ENTREGA DIRECTA | AG20: 1.175 | AH20: M3 | AI20: X | AJ20: 4 | AK20: V4 | AL20: 20250618 | AM20: DW75-900006554-D349-10043601-4
A21: 900006554DW75D27810043600 | B21: 4600050647-240 | C21: 4600050647 | D21: 240 | E21: MXPO | F21: MXL | G21: 900006554 | H21: TC-ED- MOSECA | I21: 5046324 | J21: MORTEROS SECOS DEL CARIBE SA DE CV | K21: Z06 | L21: (AP) 45 Dias | M21: 10043600 | N21: Grava Triturada Caliza 13 mm - 1/2" | O21: DW75 | P21: MX-CED. Q. ROO NORTE | Q21: 20210712 | R21: 20291231 | S21: 20250611 | T21: 20301231 | U21: 363.52 | V21: MXN | W21: M3 | X21: 78.3 | Y21: MXN | Z21: M3 | AA21: D278 | AB21: PD055 CANCUN | AC21: 56103637 | AD21: 6644321540 | AE21: 4 | AF21: ENTREGA DIRECTA | AG21: 1.177 | AH21: M3 | AI21: X | AJ21: 4 | AK21: V4 | AL21: 20250618 | AM21: DW75-900006554-D278-10043600-4
A22: 900006554DW75D34910151191 | B22: 4600050647-440 | C22: 4600050647 | D22: 440 | E22: MXPO | F22: MXL | G22: 900006554 | H22: TC-ED- MOSECA | I22: 5046324 | J22: MORTEROS SECOS DEL CARIBE SA DE CV | K22: Z06 | L22: (AP) 45 Dias | M22: 10151191 | N22: GRAVA TRITURADA CALIZA 40MM 1 ½” | O22: DW75 | P22: MX-CED. Q. ROO NORTE | Q22: 20210712 | R22: 20291231 | S22: 20250611 | T22: 20301231 | U22: 410.5 | V22: MXN | W22: M3 | X22: 125.28 | Y22: MXN | Z22: M3 | AA22: D349 | AB22: PD0300 PETEMPICH | AC22: 56103637 | AD22: 6644321540 | AE22: 4 | AF22: ENTREGA DIRECTA | AG22: 1.287 | AH22: M3 | AI22: X | AJ22: 4 | AK22: V4 | AL22: 20250618 | AM22: DW75-900006554-D349-10151191-4
A23: 900002370DW7510045642 | B23: 4600050628-30 | C23: 4600050628 | D23: 30 | E23: MXPO | F23: MXL | G23: 900002370 | H23: TC-MOSECA | I23: 5046324 | J23: MORTEROS SECOS DEL CARIBE SA DE CV | K23: Z06 | L23: (AP) 45 Dias | M23: 10045642 | N23: Arena Triturada Caliza Malla 4 | O23: DW75 | P23: MX-CED. Q. ROO NORTE | Q23: 20210712 | R23: 20291231 | S23: 20250611 | T23: 20301231 | U23: 340.39 | V23: MXN | W23: M3 | X23: 0 | Y23: MXN | Z23: M3 | AC23: 56103638 | AD23: 6644321540 | AE23: 1 | AF23: ENTREGADO | AG23: 1.471 | AH23: M3 | AI23: X | AJ23: 4 | AK23: V4 | AL23: 20250618 | AM23: DW75-900002370-10045642
A24: 900006554DW75D34310045642 | B24: 4600050647-400 | C24: 4600050647 | D24: 400 | E24: MXPO | F24: MXL | G24: 900006554 | H24: TC-ED- MOSECA | I24: 5046324 | J24: MORTEROS SECOS DEL CARIBE SA DE CV | K24: Z06 | L24: (AP) 45 Dias | M24: 10045642 | N24: Arena Triturada Caliza Malla 4 | O24: DW75 | P24: MX-CED. Q. ROO NORTE | Q24: 20210712 | R24: 20291231 | S24: 20250611 | T24: 20301231 | U24: 399.9 | V24: MXN | W24: M3 | X24: 59.51 | Y24: MXN | Z24: M3 | AA24: D343 | AB24: PD0270 RIVIERA MAYA | AC24: 56103638 | AD24: 6644321540 | AE24: 4 | AF24: ENTREGA DIRECTA | AG24: 1.471 | AH24: M3 | AI24: X | AJ24: 4 | AK24: V4 | AL24: 20250618 | AM24: DW75-900006554-D343-10045642-4
A25: 900006554DW75D27810147933 | B25: 4600050647-210 | C25: 4600050647 | D25: 210 | E25: MXPO | F25: MXL | G25: 900006554 | H25: TC-ED- MOSECA | I25: 5046324 | J25: MORTEROS SECOS DEL CARIBE SA DE CV | K25: Z06 | L25: (AP) 45 Dias | M25: 10147933 | N25: ARENA TRITURADA CALIZA MALLA 4 LAVADO | O25: DW75 | P25: MX-CED. Q. ROO NORTE | Q25: 20210712 | R25: 20291231 | S25: 20250611 | T25: 20301231 | U25: 418.69 | V25: MXN | W25: M3 | X25: 78.3 | Y25: MXN | Z25: M3 | AA25: D278 | AB25: PD055 CANCUN | AC25: 56103638 | AD25: 6644321540 | AE25: 4 | AF25: ENTREGA DIRECTA | AG25: 1.376 | AH25: M3 | AI25: X | AJ25: 4 | AK25: V4 | AL25: 20250618 | AM25: DW75-900006554-D278-10147933-4
A26: 900002370DW7510043600 | B26: 4600050628-80 | C26: 4600050628 | D26: 80 | E26: MXPO | F26: MXL | G26: 900002370 | H26: TC-MOSECA | I26: 5046324 | J26: MORTEROS SECOS DEL CARIBE SA DE CV | K26: Z06 | L26: (AP) 45 Dias | M26: 10043600 | N26: Grava Triturada Caliza 13 mm - 1/2" | O26: DW75 | P26: MX-CED. Q. ROO NORTE | Q26: 20210712 | R26: 20291231 | S26: 20250611 | T26: 20301231 | U26: 285.22 | V26: MXN | W26: M3 | X26: 0 | Y26: MXN | Z26: M3 | AC26: 56103637 | AD26: 6644321540 | AE26: 1 | AF26: ENTREGADO | AG26: 1.177 | AH26: M3 | AI26: X | AJ26: 4 | AK26: V4 | AL26: 20250618 | AM26: DW75-900002370-10043600
A27: 900002370DW7510147933 | B27: 4600050628-40 | C27: 4600050628 | D27: 40 | E27: MXPO | F27: MXL | G27: 900002370 | H27: TC-MOSECA | I27: 5046324 | J27: MORTEROS SECOS DEL CARIBE SA DE CV | K27: Z06 | L27: (AP) 45 Dias | M27: 10147933 | N27: ARENA TRITURADA CALIZA MALLA 4 LAVADO | O27: DW75 | P27: MX-CED. Q. ROO NORTE | Q27: 20210712 | R27: 20291231 | S27: 20250611 | T27: 20301231 | U27: 340.39 | V27: MXN | W27: M3 | X27: 0 | Y27: MXN | Z27: M3 | AC27: 56103638 | AD27: 6644321540 | AE27: 1 | AF27: ENTREGADO | AG27: 1.376 | AH27: M3 | AI27: X | AJ27: 4 | AK27: V4 | AL27: 20250618 | AM27: DW75-900002370-10147933
A28: 900006554DW75D34910045642 | B28: 4600050647-90 | C28: 4600050647 | D28: 90 | E28: MXPO | F28: MXL | G28: 900006554 | H28: TC-ED- MOSECA | I28: 5046324 | J28: MORTEROS SECOS DEL CARIBE SA DE CV | K28: Z06 | L28: (AP) 45 Dias | M28: 10045642 | N28: Arena Triturada Caliza Malla 4 | O28: DW75 | P28: MX-CED. Q. ROO NORTE | Q28: 20210712 | R28: 20291231 | S28: 20250611 | T28: 20301231 | U28: 465.67 | V28: MXN | W28: M3 | X28: 125.28 | Y28: MXN | Z28: M3 | AA28: D349 | AB28: PD0300 PETEMPICH | AC28: 56103638 | AD28: 6644321540 | AE28: 4 | AF28: ENTREGA DIRECTA | AG28: 1.471 | AH28: M3 | AI28: X | AJ28: 4 | AK28: V4 | AL28: 20250618 | AM28: DW75-900006554-D349-10045642-4
A29: 900006554DW75D35810151191 | B29: 4600050647-320 | C29: 4600050647 | D29: 320 | E29: MXPO | F29: MXL | G29: 900006554 | H29: TC-ED- MOSECA | I29: 5046324 | J29: MORTEROS SECOS DEL CARIBE SA DE CV | K29: Z06 | L29: (AP) 45 Dias | M29: 10151191 | N29: GRAVA TRITURADA CALIZA 40MM 1 ½” | O29: DW75 | P29: MX-CED. Q. ROO NORTE | Q29: 20210712 | R29: 20291231 | S29: 20260603 | T29: 20301231 | U29: 435.22 | V29: MXN | W29: M3 | X29: 150 | Y29: MXN | Z29: M3 | AA29: D358 | AB29: PD0509 COLOSIO | AC29: 56103637 | AD29: 6644321540 | AE29: 4 | AF29: ENTREGA DIRECTA | AG29: 1.287 | AH29: M3 | AI29: X | AJ29: 4 | AK29: V4 | AL29: 20260605 | AM29: DW75-900006554-D358-10151191-4
A30: 900005822DW7510043601 | B30: 4600050638-20 | C30: 4600050638 | D30: 20 | E30: MXPO | F30: MXL | G30: 900005822 | H30: SF TC-DELTA | I30: 5001811 | J30: DELTA PREMEZCLADO SA DE CV | K30: Z09 | L30: (AP) 90 Dias | M30: 10043601 | N30: Grava Triturada Caliza 20 mm - 3/4" | O30: DW75 | P30: MX-CED. Q. ROO NORTE | Q30: 20210712 | R30: 20301231 | S30: 20260603 | T30: 20301231 | U30: 350 | V30: MXN | W30: M3 | X30: 0 | Y30: MXN | Z30: M3 | AC30: 56103637 | AD30: 6644321540 | AE30: 1 | AF30: ENTREGADO | AG30: 1.175 | AH30: M3 | AI30: X | AJ30: 4 | AK30: V4 | AL30: 20260611 | AM30: DW75-900005822-10043601
A31: 900008644DW75D34910251252 | B31: 4600068853-10 | C31: 4600068853 | D31: 10 | E31: MXPO | F31: MXL | G31: 900008644 | H31: SF TC-ED CGC JABALI PLAYA | I31: 5092440 | J31: FERNANDEZ HERNANDEZ YURI HERNAN | K31: Z06 | L31: (AP) 45 Dias | M31: 10251252 | N31: ARENA TRITURADA CALIZA MALLA 4 | O31: DW75 | P31: MX-CED. Q. ROO NORTE | Q31: 20231130 | R31: 20281231 | S31: 20250906 | T31: 20301231 | U31: 616.6 | V31: MXN | W31: M3 | X31: 166.6 | Y31: MXN | Z31: M3 | AA31: D349 | AB31: PD0300 PETEMPICH | AC31: 56103638 | AD31: 6644321540 | AE31: 4 | AF31: ENTREGA DIRECTA | AG31: 1.406 | AH31: M3 | AI31: X | AJ31: 4 | AK31: V4 | AL31: 20250911 | AM31: DW75-900008644-D349-10251252-4
A32: 900006554DW75D35810043601 | B32: 4600050647-350 | C32: 4600050647 | D32: 350 | E32: MXPO | F32: MXL | G32: 900006554 | H32: TC-ED- MOSECA | I32: 5046324 | J32: MORTEROS SECOS DEL CARIBE SA DE CV | K32: Z06 | L32: (AP) 45 Dias | M32: 10043601 | N32: Grava Triturada Caliza 20 mm - 3/4" | O32: DW75 | P32: MX-CED. Q. ROO NORTE | Q32: 20210712 | R32: 20291231 | S32: 20250807 | T32: 20301231 | U32: 435.22 | V32: MXN | W32: M3 | X32: 150 | Y32: MXN | Z32: M3 | AA32: D358 | AB32: PD0509 COLOSIO | AC32: 56103637 | AD32: 6644321540 | AE32: 4 | AF32: ENTREGA DIRECTA | AG32: 1.175 | AH32: M3 | AI32: X | AJ32: 4 | AK32: V4 | AL32: 20250815 | AM32: DW75-900006554-D358-10043601-4
A33: 900007598DW7510248791 | B33: 4600068822-20 | C33: 4600068822 | D33: 20 | E33: MXPO | F33: MXL | G33: 900007598 | H33: SF TC-CARACOL PRODIS | I33: 5083738 | J33: PROCESOS DISRUPTIVOS S DE RL DE CV | K33: Z04 | L33: (AP) 30 Dias | M33: 10248791 | N33: GRAVA CALIZA TRIT 20MM-CARACOL INFRA | O33: DW75 | P33: MX-CED. Q. ROO NORTE | Q33: 20240122 | R33: 20291231 | S33: 20250901 | T33: 20301231 | U33: 310 | V33: MXN | W33: M3 | X33: 0 | Y33: MXN | Z33: M3 | AC33: 56103637 | AD33: 6644321540 | AE33: 1 | AF33: ENTREGADO | AG33: 1.165 | AH33: M3 | AI33: X | AJ33: 4 | AK33: V4 | AL33: 20250911 | AM33: DW75-900007598-10248791
A34: 900008644DW75D34310251252 | B34: 4600068853-60 | C34: 4600068853 | D34: 60 | E34: MXPO | F34: MXL | G34: 900008644 | H34: SF TC-ED CGC JABALI PLAYA | I34: 5092440 | J34: FERNANDEZ HERNANDEZ YURI HERNAN | K34: Z06 | L34: (AP) 45 Dias | M34: 10251252 | N34: ARENA TRITURADA CALIZA MALLA 4 | O34: DW75 | P34: MX-CED. Q. ROO NORTE | Q34: 20231130 | R34: 20281231 | S34: 20250906 | T34: 20301231 | U34: 699.9 | V34: MXN | W34: M3 | X34: 249.9 | Y34: MXN | Z34: M3 | AA34: D343 | AB34: PD0270 RIVIERA MAYA | AC34: 56103638 | AD34: 6644321540 | AE34: 4 | AF34: ENTREGA DIRECTA | AG34: 1.406 | AH34: M3 | AI34: X | AJ34: 4 | AK34: V4 | AL34: 20250911 | AM34: DW75-900008644-D343-10251252-4
A35: 900008644DW75D27810251252 | B35: 4600068853-40 | C35: 4600068853 | D35: 40 | E35: MXPO | F35: MXL | G35: 900008644 | H35: SF TC-ED CGC JABALI PLAYA | I35: 5092440 | J35: FERNANDEZ HERNANDEZ YURI HERNAN | K35: Z06 | L35: (AP) 45 Dias | M35: 10251252 | N35: ARENA TRITURADA CALIZA MALLA 4 | O35: DW75 | P35: MX-CED. Q. ROO NORTE | Q35: 20231130 | R35: 20281231 | S35: 20250906 | T35: 20301231 | U35: 768.5 | V35: MXN | W35: M3 | X35: 318.5 | Y35: MXN | Z35: M3 | AA35: D278 | AB35: PD055 CANCUN | AC35: 56103638 | AD35: 6644321540 | AE35: 4 | AF35: ENTREGA DIRECTA | AG35: 1.406 | AH35: M3 | AI35: X | AJ35: 4 | AK35: V4 | AL35: 20250911 | AM35: DW75-900008644-D278-10251252-4
A36: 900008643DW7510251252 | B36: 4600069807-20 | C36: 4600069807 | D36: 20 | E36: MXPO | F36: MXL | G36: 900008643 | H36: SF TC-CGC JABALI PLAYA | I36: 5092440 | J36: FERNANDEZ HERNANDEZ YURI HERNAN | K36: Z06 | L36: (AP) 45 Dias | M36: 10251252 | N36: ARENA TRITURADA CALIZA MALLA 4 | O36: DW75 | P36: MX-CED. Q. ROO NORTE | Q36: 20240703 | R36: 20291231 | S36: 20250906 | T36: 20301231 | U36: 450 | V36: MXN | W36: M3 | X36: 0 | Y36: MXN | Z36: M3 | AC36: 56103638 | AD36: 6644321540 | AE36: 1 | AF36: ENTREGADO | AG36: 1.298 | AH36: M3 | AI36: X | AJ36: 4 | AK36: V4 | AL36: 20250911 | AM36: DW75-900008643-10251252
A37: 900005845DW7510161246 | B37: 4600050640-10 | C37: 4600050640 | D37: 10 | E37: MXPO | F37: MXL | G37: 900005845 | H37: SF TC-TRICOBLOCKS | I37: 5070947 | J37: TRICOBLOCKS DEL SURESTE SA DE CV | K37: N90 | L37: (AP) NAFIN 90 Dias | M37: 10161246 | N37: GRAVA CALIZA 20 MM (3/4") | O37: DW75 | P37: MX-CED. Q. ROO NORTE | Q37: 20210712 | R37: 20261231 | S37: 20220306 | T37: 20271231 | U37: 275 | V37: MXN | W37: M3 | X37: 0 | Y37: MXN | Z37: M3 | AC37: 56103637 | AD37: 6644321540 | AE37: 1 | AF37: ENTREGADO | AG37: 1.159 | AH37: M3 | AI37: X | AJ37: 4 | AK37: V4 | AL37: 20230920 | AM37: DW75-900005845-10161246
A38: 900005845DW7510009436 | B38: 4600050640-30 | C38: 4600050640 | D38: 30 | E38: MXPO | F38: MXL | G38: 900005845 | H38: SF TC-TRICOBLOCKS | I38: 5070947 | J38: TRICOBLOCKS DEL SURESTE SA DE CV | K38: N90 | L38: (AP) NAFIN 90 Dias | M38: 10009436 | N38: Arena Triturada Caliza Malla 4 Lavado | O38: DW75 | P38: MX-CED. Q. ROO NORTE | Q38: 20210712 | R38: 20261231 | S38: 20220306 | T38: 20271231 | U38: 330 | V38: MXN | W38: M3 | X38: 0 | Y38: MXN | Z38: M3 | AC38: 56103638 | AD38: 6644321540 | AE38: 1 | AF38: ENTREGADO | AG38: 1.286 | AH38: M3 | AI38: X | AJ38: 4 | AK38: V4 | AL38: 20230920 | AM38: DW75-900005845-10009436
A39: 900005845DW7510032115 | B39: 4600050640-40 | C39: 4600050640 | D39: 40 | E39: MXPO | F39: MXL | G39: 900005845 | H39: SF TC-TRICOBLOCKS | I39: 5070947 | J39: TRICOBLOCKS DEL SURESTE SA DE CV | K39: N90 | L39: (AP) NAFIN 90 Dias | M39: 10032115 | N39: Grava Triturada Caliza 10 mm - 3/8" | O39: DW75 | P39: MX-CED. Q. ROO NORTE | Q39: 20210712 | R39: 20261231 | S39: 20220306 | T39: 20271231 | U39: 275 | V39: MXN | W39: M3 | X39: 0 | Y39: MXN | Z39: M3 | AC39: 56103637 | AD39: 6644321540 | AE39: 1 | AF39: ENTREGADO | AG39: 1.165 | AH39: M3 | AI39: X | AJ39: 4 | AK39: V4 | AL39: 20230920 | AM39: DW75-900005845-10032115
A40: 900005845DW7510000742 | B40: 4600050640-20 | C40: 4600050640 | D40: 20 | E40: MXPO | F40: MXL | G40: 900005845 | H40: SF TC-TRICOBLOCKS | I40: 5070947 | J40: TRICOBLOCKS DEL SURESTE SA DE CV | K40: N90 | L40: (AP) NAFIN 90 Dias | M40: 10000742 | N40: Arena Triturada Caliza Malla 4 | O40: DW75 | P40: MX-CED. Q. ROO NORTE | Q40: 20210712 | R40: 20261231 | S40: 20220306 | T40: 20271231 | U40: 340 | V40: MXN | W40: M3 | X40: 0 | Y40: MXN | Z40: M3 | AC40: 56103638 | AD40: 6644321540 | AE40: 1 | AF40: ENTREGADO | AG40: 1.375 | AH40: M3 | AI40: X | AJ40: 4 | AK40: V4 | AL40: 20230920 | AM40: DW75-900005845-10000742
A41: 900002370DW7510189747 | B41: 4600050628-70 | C41: 4600050628 | D41: 70 | E41: MXPO | F41: MXL | G41: 900002370 | H41: TC-MOSECA | I41: 5046324 | J41: MORTEROS SECOS DEL CARIBE SA DE CV | K41: Z06 | L41: (AP) 45 Dias | M41: 10189747 | N41: GRAVA CALIZA 10MM 3/8 | O41: DW75 | P41: MX-CED. Q. ROO NORTE | Q41: 20210712 | R41: 20291231 | S41: 20240215 | T41: 20291231 | U41: 278.18 | V41: MXN | W41: M3 | X41: 0 | Y41: MXN | Z41: M3 | AC41: 56103637 | AD41: 6644321540 | AE41: 1 | AF41: ENTREGADO | AG41: 1.182 | AH41: M3 | AI41: X | AJ41: 4 | AK41: V4 | AL41: 20240308 | AM41: DW75-900002370-10189747
A42: 900008654DW75D34910251250 | B42: 4600068856-10 | C42: 4600068856 | D42: 10 | E42: MXPO | F42: MXL | G42: 900008654 | H42: SF TC-ED IFLORES REY MESTIZO | I42: 5005320 | J42: FLORES CAUICH ISMAEL | K42: N90 | L42: (AP) NAFIN 90 Dias | M42: 10251250 | N42: ARENA TRITURADA CALIZA MALLA 4 | O42: DW75 | P42: MX-CED. Q. ROO NORTE | Q42: 20231130 | R42: 20281231 | S42: 20231130 | T42: 20281231 | U42: 801 | V42: MXN | W42: M3 | X42: 186 | Y42: MXN | Z42: M3 | AA42: D349 | AB42: PD0300 PETEMPICH | AC42: 56103638 | AD42: 6644321540 | AE42: 4 | AF42: ENTREGA DIRECTA | AG42: 1.404 | AH42: M3 | AI42: X | AJ42: 4 | AK42: V4 | AL42: 20231204 | AM42: DW75-900008654-D349-10251250-4
A43: 900008652DW75D34910251252 | B43: 4600068855-10 | C43: 4600068855 | D43: 10 | E43: MXPO | F43: MXL | G43: 900008652 | H43: SF TC-ED IFLORES JABALI PLAYA | I43: 5005320 | J43: FLORES CAUICH ISMAEL | K43: N90 | L43: (AP) NAFIN 90 Dias | M43: 10251252 | N43: ARENA TRITURADA CALIZA MALLA 4 | O43: DW75 | P43: MX-CED. Q. ROO NORTE | Q43: 20231130 | R43: 20281231 | S43: 20231130 | T43: 20281231 | U43: 803 | V43: MXN | W43: M3 | X43: 177 | Y43: MXN | Z43: M3 | AA43: D349 | AB43: PD0300 PETEMPICH | AC43: 56103638 | AD43: 6644321540 | AE43: 4 | AF43: ENTREGA DIRECTA | AG43: 1.406 | AH43: M3 | AI43: X | AJ43: 4 | AK43: V4 | AL43: 20231204 | AM43: DW75-900008652-D349-10251252-4
A44: 900009313DW75D34910043601 | B44: 4600071608-10 | C44: 4600071608 | D44: 10 | E44: MXPO | F44: MXL | G44: 900009313 | H44: SF TC-ED DELTA | I44: 5001811 | J44: DELTA PREMEZCLADO SA DE CV | K44: N90 | L44: (AP) NAFIN 90 Dias | M44: 10043601 | N44: Grava Triturada Caliza 20 mm - 3/4" | O44: DW75 | P44: MX-CED. Q. ROO NORTE | Q44: 20250902 | R44: 20301231 | S44: 20250902 | T44: 20301231 | U44: 381.2 | V44: MXN | W44: M3 | X44: 50 | Y44: MXN | Z44: M3 | AA44: D349 | AB44: PD0300 PETEMPICH | AC44: 56103637 | AD44: 6644321540 | AE44: 4 | AF44: ENTREGA DIRECTA | AG44: 1.175 | AH44: M3 | AI44: X | AJ44: 4 | AK44: V4 | AL44: 20250903 | AM44: DW75-900009313-D349-10043601-4
A45: 900008642DW75D34910251250 | B45: 4600068854-10 | C45: 4600068854 | D45: 10 | E45: MXPO | F45: MXL | G45: 900008642 | H45: SF TC-ED CGC REY MESTIZO | I45: 5092440 | J45: FERNANDEZ HERNANDEZ YURI HERNAN | K45: Z06 | L45: (AP) 45 Dias | M45: 10251250 | N45: ARENA TRITURADA CALIZA MALLA 4 | O45: DW75 | P45: MX-CED. Q. ROO NORTE | Q45: 20231130 | R45: 20281231 | S45: 20231130 | T45: 20281231 | U45: 706.4 | V45: MXN | W45: M3 | X45: 176.4 | Y45: MXN | Z45: M3 | AA45: D349 | AB45: PD0300 PETEMPICH | AC45: 56103638 | AD45: 6644321540 | AE45: 4 | AF45: ENTREGA DIRECTA | AG45: 1.404 | AH45: M3 | AI45: X | AJ45: 4 | AK45: V4 | AL45: 20231204 | AM45: DW75-900008642-D349-10251250-4
A46: 900005845DW7510266819 | B46: 4600050640-50 | C46: 4600050640 | D46: 50 | E46: MXPO | F46: MXL | G46: 900005845 | H46: SF TC-TRICOBLOCKS | I46: 5070947 | J46: TRICOBLOCKS DEL SURESTE SA DE CV | K46: N90 | L46: (AP) NAFIN 90 Dias | M46: 10266819 | N46: MP BASE H. 40MM A FINOS -SCT ASUR | O46: DW75 | P46: MX-CED. Q. ROO NORTE | Q46: 20210712 | R46: 20261231 | S46: 20251010 | T46: 20301231 | U46: 400 | V46: MXN | W46: M3 | X46: 0 | Y46: MXN | Z46: M3 | AC46: 56103590 | AD46: 6644321540 | AE46: 1 | AF46: ENTREGADO | AG46: 1.377 | AH46: M3 | AI46: X | AJ46: 4 | AK46: V4 | AL46: 20251014 | AM46: DW75-900005845-10266819
A47: 900007756DW7510221763 | B47: 4600055508-10 | C47: 4600055508 | D47: 10 | E47: MXPO | F47: MXL | G47: 900007756 | H47: SF TC-MYM SANTA FE | I47: 5086859 | J47: M Y M CARIBE SA DE CV | K47: Z04 | L47: (AP) 30 Dias | M47: 10221763 | N47: ARENA TRITURADA CALIZA MALLA 4 | O47: DW75 | P47: MX-CED. Q. ROO NORTE | Q47: 20220901 | R47: 20291231 | S47: 20240122 | T47: 20291231 | U47: 515 | V47: MXN | W47: M3 | X47: 0 | Y47: MXN | Z47: M3 | AC47: 56103638 | AD47: 6644321540 | AE47: 1 | AF47: ENTREGADO | AG47: 1.331 | AH47: M3 | AI47: X | AJ47: 4 | AK47: V4 | AL47: 20240125 | AM47: DW75-900007756-10221763
A48: 900007058DW7510000365 | B48: 4600050653-40 | C48: 4600050653 | D48: 40 | E48: MXPO | F48: MXL | G48: 900007058 | H48: SF TC-ABC COMERICIALIZADORA CUN | I48: 5080208 | J48: ARENAS Y BLOQUES COMERCIALIZADORA | K48: Z04 | L48: (AP) 30 Dias | M48: 10000365 | N48: Grava Triturada Caliza 20 mm - 3/4" | O48: DW75 | P48: MX-CED. Q. ROO NORTE | Q48: 20210712 | R48: 20291231 | S48: 20241105 | T48: 20291231 | U48: 403 | V48: MXN | W48: M3 | X48: 0 | Y48: MXN | Z48: M3 | AC48: 56103637 | AD48: 6644321540 | AE48: 1 | AF48: ENTREGADO | AG48: 1.176 | AH48: M3 | AI48: X | AJ48: 4 | AK48: V4 | AL48: 20241107 | AM48: DW75-900007058-10000365
A49: 900007058DW7510000364 | B49: 4600050653-30 | C49: 4600050653 | D49: 30 | E49: MXPO | F49: MXL | G49: 900007058 | H49: SF TC-ABC COMERICIALIZADORA CUN | I49: 5080208 | J49: ARENAS Y BLOQUES COMERCIALIZADORA | K49: Z04 | L49: (AP) 30 Dias | M49: 10000364 | N49: Arena Triturada Caliza Malla 4 | O49: DW75 | P49: MX-CED. Q. ROO NORTE | Q49: 20210712 | R49: 20291231 | S49: 20241105 | T49: 20291231 | U49: 475 | V49: MXN | W49: M3 | X49: 0 | Y49: MXN | Z49: M3 | AC49: 56103638 | AD49: 6644321540 | AE49: 1 | AF49: ENTREGADO | AG49: 1.434 | AH49: M3 | AI49: X | AJ49: 4 | AK49: V4 | AL49: 20241107 | AM49: DW75-900007058-10000364
A50: 900007756DW7510246797 | B50: 4600055508-20 | C50: 4600055508 | D50: 20 | E50: MXPO | F50: MXL | G50: 900007756 | H50: SF TC-MYM SANTA FE | I50: 5086859 | J50: M Y M CARIBE SA DE CV | K50: Z04 | L50: (AP) 30 Dias | M50: 10246797 | N50: ARENA CALIZA TRIT MALLA 4 - MYM INFRA | O50: DW75 | P50: MX-CED. Q. ROO NORTE | Q50: 20220901 | R50: 20291231 | S50: 20231001 | T50: 20281231 | U50: 460 | V50: MXN | W50: M3 | X50: 0 | Y50: MXN | Z50: M3 | AC50: 56103638 | AD50: 6644321540 | AE50: 1 | AF50: ENTREGADO | AG50: 1.265 | AH50: M3 | AI50: X | AJ50: 4 | AK50: V4 | AL50: 20231110 | AM50: DW75-900007756-10246797
A51: 900008643DW7510252010 | B51: 4600069807-10 | C51: 4600069807 | D51: 10 | E51: MXPO | F51: MXL | G51: 900008643 | H51: SF TC-CGC JABALI PLAYA | I51: 5092440 | J51: FERNANDEZ HERNANDEZ YURI HERNAN | K51: Z06 | L51: (AP) 45 Dias | M51: 10252010 | N51: GRAVA TRIT CALIZA 20MM 3/4" - I JABALI P | O51: DW75 | P51: MX-CED. Q. ROO NORTE | Q51: 20240703 | R51: 20291231 | S51: 20240703 | T51: 20291231 | U51: 410 | V51: MXN | W51: M3 | X51: 0 | Y51: MXN | Z51: M3 | AC51: 56103637 | AD51: 6644321540 | AE51: 1 | AF51: ENTREGADO | AG51: 1.083 | AH51: M3 | AI51: X | AJ51: 4 | AK51: V4 | AL51: 20240704 | AM51: DW75-900008643-10252010
A52: 900007757DW7510221764 | B52: 4600055509-10 | C52: 4600055509 | D52: 10 | E52: MXPO | F52: MXL | G52: 900007757 | H52: SF TC-MYM BANCO DE PIEDRA | I52: 5086859 | J52: M Y M CARIBE SA DE CV | K52: Z04 | L52: (AP) 30 Dias | M52: 10221764 | N52: ARENA TRITURADA CALIZA MALLA 4 | O52: DW75 | P52: MX-CED. Q. ROO NORTE | Q52: 20220901 | R52: 20291231 | S52: 20250120 | T52: 20301231 | U52: 450 | V52: MXN | W52: M3 | X52: 0 | Y52: MXN | Z52: M3 | AC52: 56103638 | AD52: 6644321540 | AE52: 1 | AF52: ENTREGADO | AG52: 1.414 | AH52: M3 | AI52: X | AJ52: 4 | AK52: V4 | AL52: 20250122 | AM52: DW75-900007757-10221764
A53: 900008197DW7510234149 | B53: 4600071062-10 | C53: 4600071062 | D53: 10 | E53: MXPO | F53: MXL | G53: 900008197 | H53: SF TC-MYM BANCO DE PIEDRA INFRA | I53: 5086859 | J53: M Y M CARIBE SA DE CV | K53: Z04 | L53: (AP) 30 Dias | M53: 10234149 | N53: ARENA TRITURADA CALIZA MALLA 4 - MYM INF | O53: DW75 | P53: MX-CED. Q. ROO NORTE | Q53: 20250321 | R53: 20301231 | S53: 20250321 | T53: 20301231 | U53: 450 | V53: MXN | W53: M3 | X53: 0 | Y53: MXN | Z53: M3 | AC53: 56103638 | AD53: 6644321540 | AE53: 1 | AF53: ENTREGADO | AG53: 1.394 | AH53: M3 | AI53: X | AJ53: 4 | AK53: V4 | AL53: 20250325 | AM53: DW75-900008197-10234149
A54: 900008197DW7510266819 | B54: 4600071062-20 | C54: 4600071062 | D54: 20 | E54: MXPO | F54: MXL | G54: 900008197 | H54: SF TC-MYM BANCO DE PIEDRA INFRA | I54: 5086859 | J54: M Y M CARIBE SA DE CV | K54: Z04 | L54: (AP) 30 Dias | M54: 10266819 | N54: MP BASE H. 40MM A FINOS -SCT ASUR | O54: DW75 | P54: MX-CED. Q. ROO NORTE | Q54: 20250321 | R54: 20301231 | S54: 20250514 | T54: 20301231 | U54: 380 | V54: MXN | W54: M3 | X54: 0 | Y54: MXN | Z54: M3 | AC54: 56103590 | AD54: 6644321540 | AE54: 1 | AF54: ENTREGADO | AG54: 1.377 | AH54: M3 | AI54: X | AJ54: 4 | AK54: V4 | AL54: 20250515 | AM54: DW75-900008197-10266819
A55: 900007778DW7510224750 | B55: 4600055907-10 | C55: 4600055907 | D55: 10 | E55: MXPO | F55: MXL | G55: 900007778 | H55: SF TC-ALIANCO MAQAR | I55: 5086713 | J55: MINERIA Y SERVICIOS INDUSTRIALES AL | K55: N30 | L55: (AP) NAFIN 30 Dias | M55: 10224750 | N55: ARENA TRITURADA CALIZA MALLA 4 | O55: DW75 | P55: MX-CED. Q. ROO NORTE | Q55: 20221110 | R55: 20271231 | S55: 20221110 | T55: 20271231 | U55: 230.57 | V55: MXN | W55: M3 | X55: 0 | Y55: MXN | Z55: M3 | AC55: 56103638 | AD55: 6644321540 | AE55: 1 | AF55: ENTREGADO | AG55: 1.322 | AH55: M3 | AI55: X | AJ55: 4 | AK55: V4 | AL55: 20230920 | AM55: DW75-900007778-10224750
A56: 900003833DW7510222859 | B56: 4600055439-10 | C56: 4600055439 | D56: 10 | E56: MXPO | F56: MXL | G56: 900003833 | H56: TC-TRIVASA MERIDA | I56: 5006784 | J56: TRIVASA SA DE CV | K56: N90 | L56: (AP) NAFIN 90 Dias | M56: 10222859 | N56: ARENA TRITURADA T.M.N.A 04 MM | O56: DW75 | P56: MX-CED. Q. ROO NORTE | Q56: 20221003 | R56: 20291231 | S56: 20221003 | T56: 20271231 | U56: 267.24 | V56: MXN | W56: M3 | X56: 0 | Y56: MXN | Z56: M3 | AC56: 56103638 | AD56: 6644321540 | AE56: 1 | AF56: ENTREGADO | AG56: 1.62 | AH56: M3 | AI56: X | AJ56: 4 | AK56: V4 | AL56: 20230920 | AM56: DW75-900003833-10222859
A57: 900008636DW7510251586 | B57: 4600068838-10 | C57: 4600068838 | D57: 10 | E57: MXPO | F57: MXL | G57: 900008636 | H57: SF TC-IASSO JABALI TULUM | I57: 5086846 | J57: IASSO CONSTRUCCIONES SA DE CV | K57: N90 | L57: (AP) NAFIN 90 Dias | M57: 10251586 | N57: ARENA CALIZA TRIT MALLA 4 - I JABALI T | O57: DW75 | P57: MX-CED. Q. ROO NORTE | Q57: 20231130 | R57: 20281231 | S57: 20231130 | T57: 20281231 | U57: 410 | V57: MXN | W57: M3 | X57: 0 | Y57: MXN | Z57: M3 | AC57: 56103638 | AD57: 6644321540 | AE57: 1 | AF57: ENTREGADO | AG57: 1.335 | AH57: M3 | AI57: X | AJ57: 4 | AK57: V4 | AL57: 20231201 | AM57: DW75-900008636-10251586
... A59: 900008636DW7510251587 | B59: 4600068838-20 | C59: 4600068838 | D59: 20 | E59: MXPO | F59: MXL | G59: 900008636 | H59: SF TC-IASSO JABALI TULUM | I59: 5086846 | J59: IASSO CONSTRUCCIONES SA DE CV | K59: N90 | L59: (AP) NAFIN 90 Dias | M59: 10251587 | N59: GRAVA TRIT CALIZA 20MM 3/4" - I JABALI T | O59: DW75 | P59: MX-CED. Q. ROO NORTE | Q59: 20231130 | R59: 20281231 | S59: 20231130 | T59: 20281231 | U59: 370 | V59: MXN | W59: M3 | X59: 0 | Y59: MXN | Z59: M3 | AC59: 56103637 | AD59: 6644321540 | AE59: 1 | AF59: ENTREGADO | AG59: 1.325 | AH59: M3 | AI59: X | AJ59: 4 | AK59: V4 | AL59: 20231201 | AM59: DW75-900008636-10251587
A60: 900008652DW75D34310251252 | B60: 4600068855-60 | C60: 4600068855 | D60: 60 | E60: MXPO | F60: MXL | G60: 900008652 | H60: SF TC-ED IFLORES JABALI PLAYA | I60: 5005320 | J60: FLORES CAUICH ISMAEL | K60: N90 | L60: (AP) NAFIN 90 Dias | M60: 10251252 | N60: ARENA TRITURADA CALIZA MALLA 4 | O60: DW75 | P60: MX-CED. Q. ROO NORTE | Q60: 20231130 | R60: 20281231 | S60: 20240126 | T60: 20291231 | U60: 885.6 | V60: MXN | W60: M3 | X60: 259.6 | Y60: MXN | Z60: M3 | AA60: D343 | AB60: PD0270 RIVIERA MAYA | AC60: 56103638 | AD60: 6644321540 | AE60: 4 | AF60: ENTREGA DIRECTA | AG60: 1.406 | AH60: M3 | AI60: X | AJ60: 4 | AK60: V4 | AL60: 20240129 | AM60: DW75-900008652-D343-10251252-4
A61: 900007058DW7510000328 | B61: 4600050653-10 | C61: 4600050653 | D61: 10 | E61: MXPO | F61: MXL | G61: 900007058 | H61: SF TC-ABC COMERICIALIZADORA CUN | I61: 5080208 | J61: ARENAS Y BLOQUES COMERCIALIZADORA | K61: Z04 | L61: (AP) 30 Dias | M61: 10000328 | N61: Arena Triturada Caliza Malla 4 Lavado | O61: DW75 | P61: MX-CED. Q. ROO NORTE | Q61: 20210712 | R61: 20291231 | S61: 20210712 | T61: 20251231 | U61: 242.55 | V61: MXN | W61: M3 | X61: 0 | Y61: MXN | Z61: M3 | AC61: 56103638 | AD61: 6644321540 | AE61: 1 | AF61: ENTREGADO | AG61: 1.489 | AH61: M3 | AI61: X | AJ61: 4 | AK61: V4 | AL61: 20230920 | AM61: DW75-900007058-10000328
A62: 900002370DW7510000587 | B62: 4600050628-50 | C62: 4600050628 | D62: 50 | E62: MXPO | F62: MXL | G62: 900002370 | H62: TC-MOSECA | I62: 5046324 | J62: MORTEROS SECOS DEL CARIBE SA DE CV | K62: Z06 | L62: (AP) 45 Dias | M62: 10000587 | N62: Base H Triturada Caliza 3/4"" a Finos" | O62: DW75 | P62: MX-CED. Q. ROO NORTE | Q62: 20210712 | R62: 20291231 | S62: 20210712 | T62: 20251231 | U62: 104.2 | V62: MXN | W62: M3 | X62: 0 | Y62: MXN | Z62: M3 | AC62: 56103590 | AD62: 6644321540 | AE62: 1 | AF62: ENTREGADO | AG62: 1.5 | AH62: M3 | AI62: X | AJ62: 4 | AK62: V4 | AL62: 20230920 | AM62: DW75-900002370-10000587
A63: 900006554DW75D34910189747 | B63: 4600050647-60 | C63: 4600050647 | D63: 60 | E63: MXPO | F63: MXL | G63: 900006554 | H63: TC-ED- MOSECA | I63: 5046324 | J63: MORTEROS SECOS DEL CARIBE SA DE CV | K63: Z06 | L63: (AP) 45 Dias | M63: 10189747 | N63: GRAVA CALIZA 10MM 3/8 | O63: DW75 | P63: MX-CED. Q. ROO NORTE | Q63: 20210712 | R63: 20291231 | S63: 20250301 | T63: 20301231 | U63: 417.54 | V63: MXN | W63: M3 | X63: 125.28 | Y63: MXN | Z63: M3 | AA63: D349 | AB63: PD0300 PETEMPICH | AC63: 56103637 | AD63: 6644321540 | AE63: 4 | AF63: ENTREGA DIRECTA | AG63: 1.182 | AH63: M3 | AI63: X | AJ63: 4 | AK63: V4 | AL63: 20250313 | AM63: DW75-900006554-D349-10189747-4
A64: 900006554DW75D30610043601 | B64: 4600050647-270 | C64: 4600050647 | D64: 270 | E64: MXPO | F64: MXL | G64: 900006554 | H64: TC-ED- MOSECA | I64: 5046324 | J64: MORTEROS SECOS DEL CARIBE SA DE CV | K64: Z06 | L64: (AP) 45 Dias | M64: 10043601 | N64: Grava Triturada Caliza 20 mm - 3/4" | O64: DW75 | P64: MX-CED. Q. ROO NORTE | Q64: 20210712 | R64: 20291231 | S64: 20210712 | T64: 20251231 | U64: 237.58 | V64: MXN | W64: M3 | X64: 55 | Y64: MXN | Z64: M3 | AA64: D306 | AB64: PD0304 MAYACOBA II | AC64: 56103637 | AD64: 6644321540 | AE64: 4 | AF64: ENTREGA DIRECTA | AG64: 1.175 | AH64: M3 | AI64: X | AJ64: 4 | AK64: V4 | AL64: 20230920 | AM64: DW75-900006554-D306-10043601-4
A65: 900006554DW75D28510189747 | B65: 4600050647-380 | C65: 4600050647 | D65: 380 | E65: MXPO | F65: MXL | G65: 900006554 | H65: TC-ED- MOSECA | I65: 5046324 | J65: MORTEROS SECOS DEL CARIBE SA DE CV | K65: Z06 | L65: (AP) 45 Dias | M65: 10189747 | N65: GRAVA CALIZA 10MM 3/8 | O65: DW75 | P65: MX-CED. Q. ROO NORTE | Q65: 20210712 | R65: 20291231 | S65: 20210712 | T65: 20251231 | U65: 237.58 | V65: MXN | W65: M3 | X65: 55 | Y65: MXN | Z65: M3 | AA65: D285 | AB65: PD0057 PLAYA DEL CARMEN | AC65: 56103637 | AD65: 6644321540 | AE65: 4 | AF65: ENTREGA DIRECTA | AG65: 1.182 | AH65: M3 | AI65: X | AJ65: 4 | AK65: V4 | AL65: 20230920 | AM65: DW75-900006554-D285-10189747-4
A66: 900006554DW75D34310189747 | B66: 4600050647-40 | C66: 4600050647 | D66: 40 | E66: MXPO | F66: MXL | G66: 900006554 | H66: TC-ED- MOSECA | I66: 5046324 | J66: MORTEROS SECOS DEL CARIBE SA DE CV | K66: Z06 | L66: (AP) 45 Dias | M66: 10189747 | N66: GRAVA CALIZA 10MM 3/8 | O66: DW75 | P66: MX-CED. Q. ROO NORTE | Q66: 20210712 | R66: 20291231 | S66: 20250301 | T66: 20301231 | U66: 351.77 | V66: MXN | W66: M3 | X66: 59.51 | Y66: MXN | Z66: M3 | AA66: D343 | AB66: PD0270 RIVIERA MAYA | AC66: 56103637 | AD66: 6644321540 | AE66: 4 | AF66: ENTREGA DIRECTA | AG66: 1.182 | AH66: M3 | AI66: X | AJ66: 4 | AK66: V4 | AL66: 20250313 | AM66: DW75-900006554-D343-10189747-4
A67: 900006554DW75D29710151191 | B67: 4600050647-280 | C67: 4600050647 | D67: 280 | E67: MXPO | F67: MXL | G67: 900006554 | H67: TC-ED- MOSECA | I67: 5046324 | J67: MORTEROS SECOS DEL CARIBE SA DE CV | K67: Z06 | L67: (AP) 45 Dias | M67: 10151191 | N67: GRAVA TRITURADA CALIZA 40MM 1 ½” | O67: DW75 | P67: MX-CED. Q. ROO NORTE | Q67: 20210712 | R67: 20291231 | S67: 20210712 | T67: 20251231 | U67: 252.58 | V67: MXN | W67: M3 | X67: 70 | Y67: MXN | Z67: M3 | AA67: D297 | AB67: PD0455 PAAMUL II | AC67: 56103637 | AD67: 6644321540 | AE67: 4 | AF67: ENTREGA DIRECTA | AG67: 1.287 | AH67: M3 | AI67: X | AJ67: 4 | AK67: V4 | AL67: 20230920 | AM67: DW75-900006554-D297-10151191-4
A68: 900006554DW75D30610151191 | B68: 4600050647-10 | C68: 4600050647 | D68: 10 | E68: MXPO | F68: MXL | G68: 900006554 | H68: TC-ED- MOSECA | I68: 5046324 | J68: MORTEROS SECOS DEL CARIBE SA DE CV | K68: Z06 | L68: (AP) 45 Dias | M68: 10151191 | N68: GRAVA TRITURADA CALIZA 40MM 1 ½” | O68: DW75 | P68: MX-CED. Q. ROO NORTE | Q68: 20210712 | R68: 20291231 | S68: 20210712 | T68: 20251231 | U68: 237.58 | V68: MXN | W68: M3 | X68: 55 | Y68: MXN | Z68: M3 | AA68: D306 | AB68: PD0304 MAYACOBA II | AC68: 56103637 | AD68: 6644321540 | AE68: 4 | AF68: ENTREGA DIRECTA | AG68: 1.287 | AH68: M3 | AI68: X | AJ68: 4 | AK68: V4 | AL68: 20230920 | AM68: DW75-900006554-D306-10151191-4
A69: 900006554DW75D28510151191 | B69: 4600050647-360 | C69: 4600050647 | D69: 360 | E69: MXPO | F69: MXL | G69: 900006554 | H69: TC-ED- MOSECA | I69: 5046324 | J69: MORTEROS SECOS DEL CARIBE SA DE CV | K69: Z06 | L69: (AP) 45 Dias | M69: 10151191 | N69: GRAVA TRITURADA CALIZA 40MM 1 ½” | O69: DW75 | P69: MX-CED. Q. ROO NORTE | Q69: 20210712 | R69: 20291231 | S69: 20210712 | T69: 20251231 | U69: 237.58 | V69: MXN | W69: M3 | X69: 55 | Y69: MXN | Z69: M3 | AA69: D285 | AB69: PD0057 PLAYA DEL CARMEN | AC69: 56103637 | AD69: 6644321540 | AE69: 4 | AF69: ENTREGA DIRECTA | AG69: 1.287 | AH69: M3 | AI69: X | AJ69: 4 | AK69: V4 | AL69: 20230920 | AM69: DW75-900006554-D285-10151191-4
A70: 900008652DW75D34310252010 | B70: 4600068855-50 | C70: 4600068855 | D70: 50 | E70: MXPO | F70: MXL | G70: 900008652 | H70: SF TC-ED IFLORES JABALI PLAYA | I70: 5005320 | J70: FLORES CAUICH ISMAEL | K70: N90 | L70: (AP) NAFIN 90 Dias | M70: 10252010 | N70: GRAVA TRIT CALIZA 20MM 3/4" - I JABALI P | O70: DW75 | P70: MX-CED. Q. ROO NORTE | Q70: 20231130 | R70: 20281231 | S70: 20240126 | T70: 20291231 | U70: 827.6 | V70: MXN | W70: M3 | X70: 259.6 | Y70: MXN | Z70: M3 | AA70: D343 | AB70: PD0270 RIVIERA MAYA | AC70: 56103637 | AD70: 6644321540 | AE70: 4 | AF70: ENTREGA DIRECTA | AG70: 1.083 | AH70: M3 | AI70: X | AJ70: 4 | AK70: V4 | AL70: 20240129 | AM70: DW75-900008652-D343-10252010-4
A71: 900006554DW75D29710189747 | B71: 4600050647-300 | C71: 4600050647 | D71: 300 | E71: MXPO | F71: MXL | G71: 900006554 | H71: TC-ED- MOSECA | I71: 5046324 | J71: MORTEROS SECOS DEL CARIBE SA DE CV | K71: Z06 | L71: (AP) 45 Dias | M71: 10189747 | N71: GRAVA CALIZA 10MM 3/8 | O71: DW75 | P71: MX-CED. Q. ROO NORTE | Q71: 20210712 | R71: 20291231 | S71: 20210712 | T71: 20251231 | U71: 252.58 | V71: MXN | W71: M3 | X71: 70 | Y71: MXN | Z71: M3 | AA71: D297 | AB71: PD0455 PAAMUL II | AC71: 56103637 | AD71: 6644321540 | AE71: 4 | AF71: ENTREGA DIRECTA | AG71: 1.182 | AH71: M3 | AI71: X | AJ71: 4 | AK71: V4 | AL71: 20230920 | AM71: DW75-900006554-D297-10189747-4
A72: 900006554DW75D35810043600 | B72: 4600050647-330 | C72: 4600050647 | D72: 330 | E72: MXPO | F72: MXL | G72: 900006554 | H72: TC-ED- MOSECA | I72: 5046324 | J72: MORTEROS SECOS DEL CARIBE SA DE CV | K72: Z06 | L72: (AP) 45 Dias | M72: 10043600 | N72: Grava Triturada Caliza 13 mm - 1/2" | O72: DW75 | P72: MX-CED. Q. ROO NORTE | Q72: 20210712 | R72: 20291231 | S72: 20210712 | T72: 20251231 | U72: 237.58 | V72: MXN | W72: M3 | X72: 55 | Y72: MXN | Z72: M3 | AA72: D358 | AB72: PD0509 COLOSIO | AC72: 56103637 | AD72: 6644321540 | AE72: 4 | AF72: ENTREGA DIRECTA | AG72: 1.177 | AH72: M3 | AI72: X | AJ72: 4 | AK72: V4 | AL72: 20230920 | AM72: DW75-900006554-D358-10043600-4
A73: 900006554DW75D28510043600 | B73: 4600050647-370 | C73: 4600050647 | D73: 370 | E73: MXPO | F73: MXL | G73: 900006554 | H73: TC-ED- MOSECA | I73: 5046324 | J73: MORTEROS SECOS DEL CARIBE SA DE CV | K73: Z06 | L73: (AP) 45 Dias | M73: 10043600 | N73: Grava Triturada Caliza 13 mm - 1/2" | O73: DW75 | P73: MX-CED. Q. ROO NORTE | Q73: 20210712 | R73: 20291231 | S73: 20210712 | T73: 20251231 | U73: 237.58 | V73: MXN | W73: M3 | X73: 55 | Y73: MXN | Z73: M3 | AA73: D285 | AB73: PD0057 PLAYA DEL CARMEN | AC73: 56103637 | AD73: 6644321540 | AE73: 4 | AF73: ENTREGA DIRECTA | AG73: 1.177 | AH73: M3 | AI73: X | AJ73: 4 | AK73: V4 | AL73: 20230920 | AM73: DW75-900006554-D285-10043600-4
A74: 900006554DW75D28510043601 | B74: 4600050647-390 | C74: 4600050647 | D74: 390 | E74: MXPO | F74: MXL | G74: 900006554 | H74: TC-ED- MOSECA | I74: 5046324 | J74: MORTEROS SECOS DEL CARIBE SA DE CV | K74: Z06 | L74: (AP) 45 Dias | M74: 10043601 | N74: Grava Triturada Caliza 20 mm - 3/4" | O74: DW75 | P74: MX-CED. Q. ROO NORTE | Q74: 20210712 | R74: 20291231 | S74: 20210712 | T74: 20251231 | U74: 237.58 | V74: MXN | W74: M3 | X74: 55 | Y74: MXN | Z74: M3 | AA74: D285 | AB74: PD0057 PLAYA DEL CARMEN | AC74: 56103637 | AD74: 6644321540 | AE74: 4 | AF74: ENTREGA DIRECTA | AG74: 1.175 | AH74: M3 | AI74: X | AJ74: 4 | AK74: V4 | AL74: 20230920 | AM74: DW75-900006554-D285-10043601-4
... A79: 900006554DW75D35810189747 | B79: 4600050647-340 | C79: 4600050647 | D79: 340 | E79: MXPO | F79: MXL | G79: 900006554 | H79: TC-ED- MOSECA | I79: 5046324 | J79: MORTEROS SECOS DEL CARIBE SA DE CV | K79: Z06 | L79: (AP) 45 Dias | M79: 10189747 | N79: GRAVA CALIZA 10MM 3/8 | O79: DW75 | P79: MX-CED. Q. ROO NORTE | Q79: 20210712 | R79: 20291231 | S79: 20210712 | T79: 20251231 | U79: 237.58 | V79: MXN | W79: M3 | X79: 55 | Y79: MXN | Z79: M3 | AA79: D358 | AB79: PD0509 COLOSIO | AC79: 56103637 | AD79: 6644321540 | AE79: 4 | AF79: ENTREGA DIRECTA | AG79: 1.182 | AH79: M3 | AI79: X | AJ79: 4 | AK79: V4 | AL79: 20230920 | AM79: DW75-900006554-D358-10189747-4
A80: 900007598DW7510251421 | B80: 4600068822-10 | C80: 4600068822 | D80: 10 | E80: MXPO | F80: MXL | G80: 900007598 | H80: SF TC-CARACOL PRODIS | I80: 5083738 | J80: PROCESOS DISRUPTIVOS S DE RL DE CV | K80: Z04 | L80: (AP) 30 Dias | M80: 10251421 | N80: ARENA TRIT CALIZA MALLA 4 - CARACOL | O80: DW75 | P80: MX-CED. Q. ROO NORTE | Q80: 20240122 | R80: 20291231 | S80: 20241004 | T80: 20291231 | U80: 430 | V80: MXN | W80: M3 | X80: 0 | Y80: MXN | Z80: M3 | AC80: 56103638 | AD80: 6644321540 | AE80: 1 | AF80: ENTREGADO | AG80: 1.323 | AH80: M3 | AI80: X | AJ80: 4 | AK80: V4 | AL80: 20241009 | AM80: DW75-900007598-10251421
A81: 900006554DW75D30610043600 | B81: 4600050647-250 | C81: 4600050647 | D81: 250 | E81: MXPO | F81: MXL | G81: 900006554 | H81: TC-ED- MOSECA | I81: 5046324 | J81: MORTEROS SECOS DEL CARIBE SA DE CV | K81: Z06 | L81: (AP) 45 Dias | M81: 10043600 | N81: Grava Triturada Caliza 13 mm - 1/2" | O81: DW75 | P81: MX-CED. Q. ROO NORTE | Q81: 20210712 | R81: 20291231 | S81: 20210712 | T81: 20251231 | U81: 237.58 | V81: MXN | W81: M3 | X81: 55 | Y81: MXN | Z81: M3 | AA81: D306 | AB81: PD0304 MAYACOBA II | AC81: 56103637 | AD81: 6644321540 | AE81: 4 | AF81: ENTREGA DIRECTA | AG81: 1.177 | AH81: M3 | AI81: X | AJ81: 4 | AK81: V4 | AL81: 20230920 | AM81: DW75-900006554-D306-10043600-4
A82: 900008652DW75D27810252010 | B82: 4600068855-30 | C82: 4600068855 | D82: 30 | E82: MXPO | F82: MXL | G82: 900008652 | H82: SF TC-ED IFLORES JABALI PLAYA | I82: 5005320 | J82: FLORES CAUICH ISMAEL | K82: N90 | L82: (AP) NAFIN 90 Dias | M82: 10252010 | N82: GRAVA TRIT CALIZA 20MM 3/4" - I JABALI P | O82: DW75 | P82: MX-CED. Q. ROO NORTE | Q82: 20231130 | R82: 20281231 | S82: 20240126 | T82: 20291231 | U82: 897 | V82: MXN | W82: M3 | X82: 329 | Y82: MXN | Z82: M3 | AA82: D278 | AB82: PD055 CANCUN | AC82: 56103637 | AD82: 6644321540 | AE82: 4 | AF82: ENTREGA DIRECTA | AG82: 1.083 | AH82: M3 | AI82: X | AJ82: 4 | AK82: V4 | AL82: 20240129 | AM82: DW75-900008652-D278-10252010-4
A83: 900008652DW75D27810251252 | B83: 4600068855-40 | C83: 4600068855 | D83: 40 | E83: MXPO | F83: MXL | G83: 900008652 | H83: SF TC-ED IFLORES JABALI PLAYA | I83: 5005320 | J83: FLORES CAUICH ISMAEL | K83: N90 | L83: (AP) NAFIN 90 Dias | M83: 10251252 | N83: ARENA TRITURADA CALIZA MALLA 4 | O83: DW75 | P83: MX-CED. Q. ROO NORTE | Q83: 20231130 | R83: 20281231 | S83: 20240126 | T83: 20241231 | U83: 955 | V83: MXN | W83: M3 | X83: 329 | Y83: MXN | Z83: M3 | AA83: D278 | AB83: PD055 CANCUN | AC83: 56103638 | AD83: 6644321540 | AE83: 4 | AF83: ENTREGA DIRECTA | AG83: 1.406 | AH83: M3 | AI83: X | AJ83: 4 | AK83: V4 | AL83: 20240130 | AM83: DW75-900008652-D278-10251252-4
A84: 900007058DW7510232465 | B84: 4600050653-20 | C84: 4600050653 | D84: 20 | E84: MXPO | F84: MXL | G84: 900007058 | H84: SF TC-ABC COMERICIALIZADORA CUN | I84: 5080208 | J84: ARENAS Y BLOQUES COMERCIALIZADORA | K84: Z04 | L84: (AP) 30 Dias | M84: 10232465 | N84: GRAVA TRITURADA CALIZA 13 MM - 1/2" | O84: DW75 | P84: MX-CED. Q. ROO NORTE | Q84: 20210712 | R84: 20291231 | S84: 20230906 | T84: 20281231 | U84: 460 | V84: MXN | W84: M3 | X84: 0 | Y84: MXN | Z84: M3 | AC84: 56103637 | AD84: 6644321540 | AE84: 1 | AF84: ENTREGADO | AG84: 1.205 | AH84: M3 | AI84: X | AJ84: 4 | AK84: V4 | AL84: 20230907 | AM84: DW75-900007058-10232465
A85: 900007968DW7510229016 | B85: 4600068770-10 | C85: 4600068770 | D85: 10 | E85: MXPO | F85: MXL | G85: 900007968 | H85: SF SD TC-MAYUCSA | I85: 5010179 | J85: MATERIALES DE YUCATAN SA DE CV | K85: Z04 | L85: (AP) 30 Dias | M85: 10229016 | N85: ARENA TRITURADA CALIZA MALLA 4 | O85: DW75 | P85: MX-CED. Q. ROO NORTE | Q85: 20231115 | R85: 20281231 | S85: 20231115 | T85: 20281231 | U85: 250 | V85: MXN | W85: M3 | X85: 0 | Y85: MXN | Z85: M3 | AC85: 56103638 | AD85: 6644321540 | AE85: 1 | AF85: ENTREGADO | AG85: 1.413 | AH85: M3 | AI85: X | AJ85: 4 | AK85: V4 | AL85: 20231117 | AM85: DW75-900007968-10229016
