Workbook

Sheet Base Cedis DW65
N1: VENTA | Q1: COSTO
A2: CONCAT1 | B2: CONCAT2 | C2: No. SF | D2: Nombre SF | E2: Cedis | F2: Destino | G2: Condicion de Expedicion | H2: Nombre Destino | I2: No. de material | J2: Nombre de material | K2: PV | L2: Inicio de vigencia | M2: Fin de vigencia | N2: Importe MP | O2: Importe Flete | P2: UM Venta | Q2: Importe Costo | R2: UM Costo | S2: Validacion 1 | T2: Validacion 2
A3: =CONCATENATE(C3,E3,F3,I3) | B3: =CONCATENATE(C3,E3,I3) | C3: 900000000 | D3: =IFERROR(VLOOKUP(C3,TRAOPE!$G:$H,2,0),"") | E3: DW65 | F3: D276 | G3: =IFERROR(VLOOKUP(A3,Flete!$A:$E,5,0),"") | H3: =IFERROR(VLOOKUP(F3,TRAOPE!$AA:$AB,2,0),"") | I3: 10000541 | J3: =IFERROR(VLOOKUP(I3,Materiales!$A:$H,8,0),"") | K3: =IFERROR(VLOOKUP(I3,Materiales!$A:$G,7,0),"") | L3: 20240726 | M3: 20241023 | N3: 117.8 | O3: =IFERROR(VLOOKUP(A3,Flete!$A:$J,10,0),"") | P3: TN | Q3: =IFERROR(IFERROR(VLOOKUP(A3,TRAOPE!$A:$U,21,0),VLOOKUP(B3,TRAOPE!$A:$U,21,0)),"") | R3: =IFERROR(IFERROR(VLOOKUP(A3,TRAOPE!$A:$W,23,0),VLOOKUP(B3,TRAOPE!$A:$W,23,0)),"") | S3: =IF(AND(P3="TN",R3="TN"),N3+N(O3),IF(G3&""="1",N(K3)*N3,(N3+N(O3))*N(K3))) | T3: =IF(Q3="","",Q3-S3)
A4: =CONCATENATE(C4,E4,F4,I4) | B4: =CONCATENATE(C4,E4,I4) | C4: 900000000 | D4: =IFERROR(VLOOKUP(C4,TRAOPE!$G:$H,2,0),"") | E4: DW65 | F4: D330 | G4: =IFERROR(VLOOKUP(A4,Flete!$A:$E,5,0),"") | H4: =IFERROR(VLOOKUP(F4,TRAOPE!$AA:$AB,2,0),"") | I4: 10000541 | J4: =IFERROR(VLOOKUP(I4,Materiales!$A:$H,8,0),"") | K4: =IFERROR(VLOOKUP(I4,Materiales!$A:$G,7,0),"") | L4: 20241114 | M4: 99991231 | N4: 294.5 | O4: =IFERROR(VLOOKUP(A4,Flete!$A:$J,10,0),"") | P4: TN | Q4: =IFERROR(IFERROR(VLOOKUP(A4,TRAOPE!$A:$U,21,0),VLOOKUP(B4,TRAOPE!$A:$U,21,0)),"") | R4: =IFERROR(IFERROR(VLOOKUP(A4,TRAOPE!$A:$W,23,0),VLOOKUP(B4,TRAOPE!$A:$W,23,0)),"") | S4: =IF(AND(P4="TN",R4="TN"),N4+N(O4),IF(G4&""="1",N(K4)*N4,(N4+N(O4))*N(K4))) | T4: =IF(Q4="","",Q4-S4)
A5: =CONCATENATE(C5,E5,F5,I5) | B5: =CONCATENATE(C5,E5,I5) | C5: 900000000 | D5: =IFERROR(VLOOKUP(C5,TRAOPE!$G:$H,2,0),"") | E5: DW65 | F5: D335 | G5: =IFERROR(VLOOKUP(A5,Flete!$A:$E,5,0),"") | H5: =IFERROR(VLOOKUP(F5,TRAOPE!$AA:$AB,2,0),"") | I5: 10000541 | J5: =IFERROR(VLOOKUP(I5,Materiales!$A:$H,8,0),"") | K5: =IFERROR(VLOOKUP(I5,Materiales!$A:$G,7,0),"") | L5: 20241105 | M5: 99991231 | N5: 294.5 | O5: =IFERROR(VLOOKUP(A5,Flete!$A:$J,10,0),"") | P5: TN | Q5: =IFERROR(IFERROR(VLOOKUP(A5,TRAOPE!$A:$U,21,0),VLOOKUP(B5,TRAOPE!$A:$U,21,0)),"") | R5: =IFERROR(IFERROR(VLOOKUP(A5,TRAOPE!$A:$W,23,0),VLOOKUP(B5,TRAOPE!$A:$W,23,0)),"") | S5: =IF(AND(P5="TN",R5="TN"),N5+N(O5),IF(G5&""="1",N(K5)*N5,(N5+N(O5))*N(K5))) | T5: =IF(Q5="","",Q5-S5)
A6: =CONCATENATE(C6,E6,F6,I6) | B6: =CONCATENATE(C6,E6,I6) | C6: 900000023 | D6: =IFERROR(VLOOKUP(C6,TRAOPE!$G:$H,2,0),"") | E6: DW65 | F6: D324 | G6: =IFERROR(VLOOKUP(A6,Flete!$A:$E,5,0),"") | H6: =IFERROR(VLOOKUP(F6,TRAOPE!$AA:$AB,2,0),"") | I6: 10000742 | J6: =IFERROR(VLOOKUP(I6,Materiales!$A:$H,8,0),"") | K6: =IFERROR(VLOOKUP(I6,Materiales!$A:$G,7,0),"") | L6: 20210620 | M6: 20240822 | N6: 152.34 | O6: =IFERROR(VLOOKUP(A6,Flete!$A:$J,10,0),"") | P6: TN | Q6: =IFERROR(IFERROR(VLOOKUP(A6,TRAOPE!$A:$U,21,0),VLOOKUP(B6,TRAOPE!$A:$U,21,0)),"") | R6: =IFERROR(IFERROR(VLOOKUP(A6,TRAOPE!$A:$W,23,0),VLOOKUP(B6,TRAOPE!$A:$W,23,0)),"") | S6: =IF(AND(P6="TN",R6="TN"),N6+N(O6),IF(G6&""="1",N(K6)*N6,(N6+N(O6))*N(K6))) | T6: =IF(Q6="","",Q6-S6)
A7: =CONCATENATE(C7,E7,F7,I7) | B7: =CONCATENATE(C7,E7,I7) | C7: 900000023 | D7: =IFERROR(VLOOKUP(C7,TRAOPE!$G:$H,2,0),"") | E7: DW65 | F7: D324 | G7: =IFERROR(VLOOKUP(A7,Flete!$A:$E,5,0),"") | H7: =IFERROR(VLOOKUP(F7,TRAOPE!$AA:$AB,2,0),"") | I7: 10031878 | J7: =IFERROR(VLOOKUP(I7,Materiales!$A:$H,8,0),"") | K7: =IFERROR(VLOOKUP(I7,Materiales!$A:$G,7,0),"") | L7: 20210620 | M7: 20240822 | N7: 189.69 | O7: =IFERROR(VLOOKUP(A7,Flete!$A:$J,10,0),"") | P7: TN | Q7: =IFERROR(IFERROR(VLOOKUP(A7,TRAOPE!$A:$U,21,0),VLOOKUP(B7,TRAOPE!$A:$U,21,0)),"") | R7: =IFERROR(IFERROR(VLOOKUP(A7,TRAOPE!$A:$W,23,0),VLOOKUP(B7,TRAOPE!$A:$W,23,0)),"") | S7: =IF(AND(P7="TN",R7="TN"),N7+N(O7),IF(G7&""="1",N(K7)*N7,(N7+N(O7))*N(K7))) | T7: =IF(Q7="","",Q7-S7)
A8: =CONCATENATE(C8,E8,F8,I8) | B8: =CONCATENATE(C8,E8,I8) | C8: 900000023 | D8: =IFERROR(VLOOKUP(C8,TRAOPE!$G:$H,2,0),"") | E8: DW65 | F8: D330 | G8: =IFERROR(VLOOKUP(A8,Flete!$A:$E,5,0),"") | H8: =IFERROR(VLOOKUP(F8,TRAOPE!$AA:$AB,2,0),"") | I8: 10000742 | J8: =IFERROR(VLOOKUP(I8,Materiales!$A:$H,8,0),"") | K8: =IFERROR(VLOOKUP(I8,Materiales!$A:$G,7,0),"") | L8: 20210620 | M8: 20240822 | N8: 152.34 | O8: =IFERROR(VLOOKUP(A8,Flete!$A:$J,10,0),"") | P8: TN | Q8: =IFERROR(IFERROR(VLOOKUP(A8,TRAOPE!$A:$U,21,0),VLOOKUP(B8,TRAOPE!$A:$U,21,0)),"") | R8: =IFERROR(IFERROR(VLOOKUP(A8,TRAOPE!$A:$W,23,0),VLOOKUP(B8,TRAOPE!$A:$W,23,0)),"") | S8: =IF(AND(P8="TN",R8="TN"),N8+N(O8),IF(G8&""="1",N(K8)*N8,(N8+N(O8))*N(K8))) | T8: =IF(Q8="","",Q8-S8)
A9: =CONCATENATE(C9,E9,F9,I9) | B9: =CONCATENATE(C9,E9,I9) | C9: 900000023 | D9: =IFERROR(VLOOKUP(C9,TRAOPE!$G:$H,2,0),"") | E9: DW65 | F9: D335 | G9: =IFERROR(VLOOKUP(A9,Flete!$A:$E,5,0),"") | H9: =IFERROR(VLOOKUP(F9,TRAOPE!$AA:$AB,2,0),"") | I9: 10000742 | J9: =IFERROR(VLOOKUP(I9,Materiales!$A:$H,8,0),"") | K9: =IFERROR(VLOOKUP(I9,Materiales!$A:$G,7,0),"") | L9: 20210620 | M9: 20240822 | N9: 152.34 | O9: =IFERROR(VLOOKUP(A9,Flete!$A:$J,10,0),"") | P9: TN | Q9: =IFERROR(IFERROR(VLOOKUP(A9,TRAOPE!$A:$U,21,0),VLOOKUP(B9,TRAOPE!$A:$U,21,0)),"") | R9: =IFERROR(IFERROR(VLOOKUP(A9,TRAOPE!$A:$W,23,0),VLOOKUP(B9,TRAOPE!$A:$W,23,0)),"") | S9: =IF(AND(P9="TN",R9="TN"),N9+N(O9),IF(G9&""="1",N(K9)*N9,(N9+N(O9))*N(K9))) | T9: =IF(Q9="","",Q9-S9)
A10: =CONCATENATE(C10,E10,F10,I10) | B10: =CONCATENATE(C10,E10,I10) | C10: 900000184 | D10: =IFERROR(VLOOKUP(C10,TRAOPE!$G:$H,2,0),"") | E10: DW65 | F10: D307 | G10: =IFERROR(VLOOKUP(A10,Flete!$A:$E,5,0),"") | H10: =IFERROR(VLOOKUP(F10,TRAOPE!$AA:$AB,2,0),"") | I10: 10222859 | J10: =IFERROR(VLOOKUP(I10,Materiales!$A:$H,8,0),"") | K10: =IFERROR(VLOOKUP(I10,Materiales!$A:$G,7,0),"") | L10: 20260301 | M10: 99991231 | N10: 216.93 | O10: =IFERROR(VLOOKUP(A10,Flete!$A:$J,10,0),"") | P10: TN | Q10: =IFERROR(IFERROR(VLOOKUP(A10,TRAOPE!$A:$U,21,0),VLOOKUP(B10,TRAOPE!$A:$U,21,0)),"") | R10: =IFERROR(IFERROR(VLOOKUP(A10,TRAOPE!$A:$W,23,0),VLOOKUP(B10,TRAOPE!$A:$W,23,0)),"") | S10: =IF(AND(P10="TN",R10="TN"),N10+N(O10),IF(G10&""="1",N(K10)*N10,(N10+N(O10))*N(K10))) | T10: =IF(Q10="","",Q10-S10)
A11: =CONCATENATE(C11,E11,F11,I11) | B11: =CONCATENATE(C11,E11,I11) | C11: 900000184 | D11: =IFERROR(VLOOKUP(C11,TRAOPE!$G:$H,2,0),"") | E11: DW65 | F11: D307 | G11: =IFERROR(VLOOKUP(A11,Flete!$A:$E,5,0),"") | H11: =IFERROR(VLOOKUP(F11,TRAOPE!$AA:$AB,2,0),"") | I11: 10224398 | J11: =IFERROR(VLOOKUP(I11,Materiales!$A:$H,8,0),"") | K11: =IFERROR(VLOOKUP(I11,Materiales!$A:$G,7,0),"") | L11: 20260301 | M11: 99991231 | N11: 287.36 | O11: =IFERROR(VLOOKUP(A11,Flete!$A:$J,10,0),"") | P11: TN | Q11: =IFERROR(IFERROR(VLOOKUP(A11,TRAOPE!$A:$U,21,0),VLOOKUP(B11,TRAOPE!$A:$U,21,0)),"") | R11: =IFERROR(IFERROR(VLOOKUP(A11,TRAOPE!$A:$W,23,0),VLOOKUP(B11,TRAOPE!$A:$W,23,0)),"") | S11: =IF(AND(P11="TN",R11="TN"),N11+N(O11),IF(G11&""="1",N(K11)*N11,(N11+N(O11))*N(K11))) | T11: =IF(Q11="","",Q11-S11)
A12: =CONCATENATE(C12,E12,F12,I12) | B12: =CONCATENATE(C12,E12,I12) | C12: 900000184 | D12: =IFERROR(VLOOKUP(C12,TRAOPE!$G:$H,2,0),"") | E12: DW65 | F12: D307 | G12: =IFERROR(VLOOKUP(A12,Flete!$A:$E,5,0),"") | H12: =IFERROR(VLOOKUP(F12,TRAOPE!$AA:$AB,2,0),"") | I12: 10268996 | J12: =IFERROR(VLOOKUP(I12,Materiales!$A:$H,8,0),"") | K12: =IFERROR(VLOOKUP(I12,Materiales!$A:$G,7,0),"") | L12: 20260301 | M12: 99991231 | N12: 291.9 | O12: =IFERROR(VLOOKUP(A12,Flete!$A:$J,10,0),"") | P12: TN | Q12: =IFERROR(IFERROR(VLOOKUP(A12,TRAOPE!$A:$U,21,0),VLOOKUP(B12,TRAOPE!$A:$U,21,0)),"") | R12: =IFERROR(IFERROR(VLOOKUP(A12,TRAOPE!$A:$W,23,0),VLOOKUP(B12,TRAOPE!$A:$W,23,0)),"") | S12: =IF(AND(P12="TN",R12="TN"),N12+N(O12),IF(G12&""="1",N(K12)*N12,(N12+N(O12))*N(K12))) | T12: =IF(Q12="","",Q12-S12)
A13: =CONCATENATE(C13,E13,F13,I13) | B13: =CONCATENATE(C13,E13,I13) | C13: 900000184 | D13: =IFERROR(VLOOKUP(C13,TRAOPE!$G:$H,2,0),"") | E13: DW65 | F13: D307 | G13: =IFERROR(VLOOKUP(A13,Flete!$A:$E,5,0),"") | H13: =IFERROR(VLOOKUP(F13,TRAOPE!$AA:$AB,2,0),"") | I13: 10270825 | J13: =IFERROR(VLOOKUP(I13,Materiales!$A:$H,8,0),"") | K13: =IFERROR(VLOOKUP(I13,Materiales!$A:$G,7,0),"") | L13: 20260301 | M13: 99991231 | N13: 295 | O13: =IFERROR(VLOOKUP(A13,Flete!$A:$J,10,0),"") | P13: TN | Q13: =IFERROR(IFERROR(VLOOKUP(A13,TRAOPE!$A:$U,21,0),VLOOKUP(B13,TRAOPE!$A:$U,21,0)),"") | R13: =IFERROR(IFERROR(VLOOKUP(A13,TRAOPE!$A:$W,23,0),VLOOKUP(B13,TRAOPE!$A:$W,23,0)),"") | S13: =IF(AND(P13="TN",R13="TN"),N13+N(O13),IF(G13&""="1",N(K13)*N13,(N13+N(O13))*N(K13))) | T13: =IF(Q13="","",Q13-S13)
A14: =CONCATENATE(C14,E14,F14,I14) | B14: =CONCATENATE(C14,E14,I14) | C14: 900000360 | D14: =IFERROR(VLOOKUP(C14,TRAOPE!$G:$H,2,0),"") | E14: DW65 | F14: D276 | G14: =IFERROR(VLOOKUP(A14,Flete!$A:$E,5,0),"") | H14: =IFERROR(VLOOKUP(F14,TRAOPE!$AA:$AB,2,0),"") | I14: 10000677 | J14: =IFERROR(VLOOKUP(I14,Materiales!$A:$H,8,0),"") | K14: =IFERROR(VLOOKUP(I14,Materiales!$A:$G,7,0),"") | L14: 20220516 | M14: 20241216 | N14: 164.85 | O14: =IFERROR(VLOOKUP(A14,Flete!$A:$J,10,0),"") | P14: TN | Q14: =IFERROR(IFERROR(VLOOKUP(A14,TRAOPE!$A:$U,21,0),VLOOKUP(B14,TRAOPE!$A:$U,21,0)),"") | R14: =IFERROR(IFERROR(VLOOKUP(A14,TRAOPE!$A:$W,23,0),VLOOKUP(B14,TRAOPE!$A:$W,23,0)),"") | S14: =IF(AND(P14="TN",R14="TN"),N14+N(O14),IF(G14&""="1",N(K14)*N14,(N14+N(O14))*N(K14))) | T14: =IF(Q14="","",Q14-S14)
... A171: =CONCATENATE(C171,E171,F171,I171) | B171: =CONCATENATE(C171,E171,I171) | C171: 900009582 | D171: =IFERROR(VLOOKUP(C171,TRAOPE!$G:$H,2,0),"") | E171: DW65 | F171: D307 | G171: =IFERROR(VLOOKUP(A171,Flete!$A:$E,5,0),"") | H171: =IFERROR(VLOOKUP(F171,TRAOPE!$AA:$AB,2,0),"") | I171: 10281183 | J171: =IFERROR(VLOOKUP(I171,Materiales!$A:$H,8,0),"") | K171: =IFERROR(VLOOKUP(I171,Materiales!$A:$G,7,0),"") | L171: 20260817 | M171: 99991231 | N171: 245.23 | O171: =IFERROR(VLOOKUP(A171,Flete!$A:$J,10,0),"") | P171: TN | Q171: =IFERROR(IFERROR(VLOOKUP(A171,TRAOPE!$A:$U,21,0),VLOOKUP(B171,TRAOPE!$A:$U,21,0)),"") | R171: =IFERROR(IFERROR(VLOOKUP(A171,TRAOPE!$A:$W,23,0),VLOOKUP(B171,TRAOPE!$A:$W,23,0)),"") | S171: =IF(AND(P171="TN",R171="TN"),N171+N(O171),IF(G171&""="1",N(K171)*N171,(N171+N(O171))*N(K171))) | T171: =IF(Q171="","",Q171-S171)

Sheet MP
A1: No. SF | B1: Cedis | C1: Destino | D1: No. Material | E1: Nombre Material | F1: Importe MP | G1: Moneda | H1: Cantidad | I1: UM | J1: C | K1: Inicio Vigencia | L1: Fin Vigencia
A2: 900000000 | B2: DW65 | C2: D276 | D2: 10000541 | F2: 117.8 | I2: TN | K2: 20240726 | L2: 20241023
A3: 900000000 | B3: DW65 | C3: D330 | D3: 10000541 | F3: 294.5 | I3: TN | K3: 20241114 | L3: 99991231
A4: 900000000 | B4: DW65 | C4: D335 | D4: 10000541 | F4: 294.5 | I4: TN | K4: 20241105 | L4: 99991231
A5: 900000023 | B5: DW65 | C5: D324 | D5: 10000742 | F5: 152.34 | I5: TN | K5: 20210620 | L5: 20240822
A6: 900000023 | B6: DW65 | C6: D324 | D6: 10031878 | F6: 189.69 | I6: TN | K6: 20210620 | L6: 20240822
A7: 900000023 | B7: DW65 | C7: D330 | D7: 10000742 | F7: 152.34 | I7: TN | K7: 20210620 | L7: 20240822
A8: 900000023 | B8: DW65 | C8: D335 | D8: 10000742 | F8: 152.34 | I8: TN | K8: 20210620 | L8: 20240822
A9: 900000184 | B9: DW65 | C9: D307 | D9: 10222859 | F9: 216.93 | I9: TN | K9: 20260301 | L9: 99991231
A10: 900000184 | B10: DW65 | C10: D307 | D10: 10224398 | F10: 287.36 | I10: TN | K10: 20260301 | L10: 99991231
A11: 900000184 | B11: DW65 | C11: D307 | D11: 10268996 | F11: 291.9 | I11: TN | K11: 20260301 | L11: 99991231
A12: 900000184 | B12: DW65 | C12: D307 | D12: 10270825 | F12: 295 | I12: TN | K12: 20260301 | L12: 99991231
A13: 900000360 | B13: DW65 | C13: D276 | D13: 10000677 | F13: 164.85 | I13: TN | K13: 20220516 | L13: 20241216
... A170: 900009582 | B170: DW65 | C170: D307 | D170: 10281183 | F170: 245.23 | I170: TN | K170: 20260817 | L170: 99991231

Sheet Flete
A1: Concat1 | B1: No. SF | C1: Cedis | D1: Destino | E1: Cond. Exp. | F1: Material | H1: Nombre Material | J1: Importe Flete | K1: Moneda | L1: Cantidad | M1: UM | N1: C | P1: Inicio Vigencia | Q1: Fin Vigencia
A2: 900000000DW65D27610000541 | B2: 900000000 | C2: DW65 | D2: D276 | E2: 4 | F2: 10000541 | J2: 641.36 | M2: TN | P2: 20240726 | Q2: 20241023
A3: 900000000DW65D33010000541 | B3: 900000000 | C3: DW65 | D3: D330 | E3: 4 | F3: 10000541 | J3: 1276.18 | M3: TN | P3: 20241114 | Q3: 99991231
A4: 900000000DW65D33510000541 | B4: 900000000 | C4: DW65 | D4: D335 | E4: 4 | F4: 10000541 | J4: 1276.18 | M4: TN | P4: 20241105 | Q4: 99991231
A5: 900000023DW65D32410000742 | B5: 900000023 | C5: DW65 | D5: D324 | E5: 1 | F5: 10000742 | J5: 557.58 | M5: TN | P5: 20210620 | Q5: 20240902
A6: 900000023DW65D32410031878 | B6: 900000023 | C6: DW65 | D6: D324 | E6: 1 | F6: 10031878 | J6: 379.37 | M6: TN | P6: 20210620 | Q6: 20240902
A7: 900000023DW65D33010000742 | B7: 900000023 | C7: DW65 | D7: D330 | E7: 1 | F7: 10000742 | J7: 284.3 | M7: TN | P7: 20210620 | Q7: 20240822
A8: 900000023DW65D33510000742 | B8: 900000023 | C8: DW65 | D8: D335 | E8: 1 | F8: 10000742 | J8: 284.3 | M8: TN | P8: 20210620 | Q8: 20240822
A9: 900000184DW65D30710222859 | B9: 900000184 | C9: DW65 | D9: D307 | E9: 4 | F9: 10222859 | J9: 40.83 | M9: TN | P9: 20260301 | Q9: 99991231
A10: 900000184DW65D30710224398 | B10: 900000184 | C10: DW65 | D10: D307 | E10: 4 | F10: 10224398 | J10: 54.09 | M10: TN | P10: 20260301 | Q10: 99991231
A11: 900000184DW65D30710268996 | B11: 900000184 | C11: DW65 | D11: D307 | E11: 4 | F11: 10268996 | J11: 51.89 | M11: TN | P11: 20260301 | Q11: 99991231
A12: 900000184DW65D30710270825 | B12: 900000184 | C12: DW65 | D12: D307 | E12: 4 | F12: 10270825 | J12: 55.52 | M12: TN | P12: 20260301 | Q12: 99991231
A13: 900000360DW65D27610000677 | B13: 900000360 | C13: DW65 | D13: D276 | E13: 1 | F13: 10000677 | J13: 162.11 | M13: TN | P13: 20210620 | Q13: 20241216
... A161: 900009547DW65D32410099383 | B161: 900009547 | C161: DW65 | D161: D324 | E161: 1 | F161: 10099383 | J161: 214.84 | M161: TN | P161: 20260514 | Q161: 99991231

Sheet Materiales
A1: Material | B1: TpMt | C1: Denom | D1: UMA | E1: Contador | F1: UMB | G1: PV | H1: Nombre Material
A2: 10000001 | B2: ZFER | C2: 1000 | D2: M3 | E2: 1000 | F2: TN | G2: 1262 | H2: GRAVA ANDESITA 10 MM (3/8")
A3: 10000003 | B3: ZFER | C3: 1000 | D3: M3 | E3: 1000 | F3: TN | G3: 1443 | H3: GRAVA CALIZA 10 MM (3/8")
A4: 10000006 | B4: ZFER | C4: 1000 | D4: M3 | E4: 1000 | F4: TN | G4: 1490 | H4: GRAVA RIO 10 MM (3/8")
A5: 10000007 | B5: ZFER | C5: 1000 | D5: M3 | E5: 1000 | F5: TN | G5: 1488 | H5: GRAVA BASALTO 13 MM (1/2")
A6: 10000008 | B6: ZFER | C6: 1000 | D6: M3 | E6: 1000 | F6: TN | G6: 1358 | H6: GRAVA CALIZA 13 MM (1/2")
A7: 10000011 | B7: ZFER | C7: 1000 | D7: M3 | E7: 1000 | F7: TN | G7: 1323 | H7: GRAVA ANDESITA 20 MM (3/4")
A8: 10000013 | B8: ZFER | C8: 1000 | D8: M3 | E8: 1000 | F8: TN | G8: 1514 | H8: GRAVA BASALTO 20 MM (3/4")
A9: 10000014 | B9: ZFER | C9: 1000 | D9: M3 | E9: 1000 | F9: TN | G9: 1400 | H9: GRAVA CALIZA 20 MM (3/4")
A10: 10000015 | B10: ZFER | C10: 1000 | D10: M3 | E10: 1000 | F10: TN | G10: 1410 | H10: GRAVA GRANITO 20 MM (3/4")
A11: 10000017 | B11: ZFER | C11: 1000 | D11: M3 | E11: 1000 | F11: TN | G11: 1475 | H11: GRAVA RIOLITA 20 MM (3/4")
A12: 10000019 | B12: ZFER | C12: 1000 | D12: M3 | E12: 1000 | F12: TN | G12: 1515 | H12: GRAVA RIO 20 MM (3/4")
A13: 10000020 | B13: ZFER | C13: 1000 | D13: M3 | E13: 1 | F13: TN | G13: 1 | H13: GRAVA MAQUILA 40MM (1 1/2")
... A2291: 10268770 | B2291: ZFE3 | C2291: 1000 | D2291: M3 | E2291: 1000 | F2291: TN | G2291: 1240 | H2291: MP GRAVA TRIT CALIZA 40MM 1 1/2" - ESP
A2292: 10268901 | B2292: ZFE3 | C2292: 1000 | D2292: M3 | E2292: 1000 | G2292: 1560 | H2292: MP GRAVA ANDESITA GRIS 3/4" - CAPADA
A2293: 10267983 | C2293: 1000 | G2293: 1800 | H2293: ESCORIA ALTO HORNO 3/4
A2294: 10268996 | C2294: 1000 | G2294: 1329 | H2294: GRAVA TRITURADA CALIZA 40 MM - 11/2"
A2295: 10269072 | C2295: 1000 | G2295: 1700 | H2295: BASE HIDRÁULICA SCREEN
A2296: 10269225 | B2296: ZFE3 | C2296: 1000 | D2296: M3 | E2296: 1000 | G2296: 1289 | H2296: MP ARENA CALIZA LAVADA MALLA 4 - DELTA I
A2297: 10269245 | B2297: ZFE3 | C2297: 1000 | D2297: M3 | E2297: 1000 | G2297: 1410 | H2297: MP GRAVA TRITURADA CALIZA 3/8 - 10MM
A2298: 10269246 | B2298: ZFE3 | C2298: 1000 | D2298: M3 | E2298: 1000 | G2298: 1400 | H2298: MP GRAVA TRITURADA CALIZA 1 1/2 - 40MM
A2299: 10269247 | B2299: ZFE3 | C2299: 1000 | D2299: M3 | E2299: 1000 | G2299: 1560 | H2299: MP ARENA TRIT CALIZA M-4
A2300: 10270431 | B2300: ZFE3 | C2300: 1000 | D2300: M3 | E2300: 1000 | G2300: 1423 | H2300: MP GRAVA RIOLITA 13 MM - 1/2"
A2301: 10270898 | B2301: ZFE3 | C2301: 1000 | D2301: M3 | E2301: 1000 | G2301: 1551 | H2301: MP BASE H. TRIT. BASALTO 1 1/2" A FINOS
A2302: 10270911 | B2302: ZFE3 | C2302: 1000 | D2302: M3 | E2302: 1000 | G2302: 1360 | H2302: MP GRAVA TRIT. BASALTO 40 MM - 1 1/2"
A2303: 10270912 | B2303: ZFE3 | C2303: 1000 | D2303: M3 | E2303: 1000 | G2303: 1589 | H2303: MP ARENA TRIT. BASALTO MALLA 4
A2304: 10270913 | B2304: ZFE3 | C2304: 1000 | D2304: M3 | E2304: 1000 | G2304: 1395 | H2304: MP GRAVA TRIT. BASALTO 20 MM - 3/4
A2305: 10270914 | B2305: ZFE3 | C2305: 1000 | D2305: M3 | E2305: 1000 | G2305: 1623 | H2305: MP ARENA ANDESITA BC
A2306: 10270824 | B2306: M3 | C2306: 1000 | D2306: M3 | E2306: 10007640 | G2306: 1325 | H2306: MP ARENA TRITURADA CALIZA MALLA 5
A2307: 10270825 | B2307: M3 | C2307: 1000 | D2307: M3 | E2307: 10000003 | G2307: 1242 | H2307: MP GRAVA TRITURADA CALIZA 10MM (3/8”)
... A2319: 10272527 | B2319: ZFE3 | C2319: 1000 | D2319: M3 | E2319: 1000 | G2319: 1620 | H2319: CNC - NO CLASIFICADO
A2320: 10000332 | C2320: 1000 | D2320: M3 | E2320: 1000 | G2320: 800 | H2320: Grava Triturada Pomez - Jal 20 mm - 3/4"
A2321: 10273001 | B2321: ZFE3 | C2321: 1000 | D2321: M3 | E2321: 1000 | G2321: 1688 | H2321: MP ARENA TRIT. BASALTO MALLA 4
A2322: 10273002 | B2322: ZFE3 | C2322: 1000 | D2322: M3 | E2322: 1000 | G2322: 1466 | H2322: MP GRAVA TRIT. BASALTO 20 MM - 3/4"
A2323: 10273351 | B2323: ZFE3 | C2323: 1000 | D2323: M3 | E2323: 1000 | G2323: 1612 | H2323: MP ARENA TRIT. CALIZA MALLA 4
A2324: 10273352 | B2324: ZFE3 | C2324: 1000 | D2324: M3 | E2324: 1000 | G2324: 1492 | H2324: MP GRAVA TRIT. CALIZA 20 MM - 3/4"
A2325: 10271724 | B2325: ZFE3 | C2325: 1000 | D2325: M3 | E2325: 1000 | G2325: 1900 | H2325: MP RESIDUO DE CONCRETO
A2326: 10000677 | C2326: 1000 | D2326: M3 | G2326: 1164 | H2326: Grava Triturada Caliza 20 mm - 3/4"
A2327: 10274190 | B2327: ZFE3 | C2327: 1000 | D2327: M3 | E2327: 1000 | G2327: 1800 | H2327: MP BASE HIDRAULICA ANDESITA 70-30
A2328: 10274601 | B2328: ZFE3 | C2328: 1000 | D2328: M3 | E2328: 1000 | G2328: 1447 | H2328: MP ARENA BASALTO N° 4
A2329: 10274754 | B2329: ZFE3 | C2329: 1000 | D2329: M3 | E2329: 1000 | G2329: 1397 | H2329: MP GRAVA TRIT. ANDESITA 20 MM - 3/4"
A2330: 10169718 | B2330: ZFE3 | C2330: 1000 | D2330: M3 | E2330: 1000 | G2330: 1400 | H2330: GRAVA CLASIFICADA RÍO 40 MM - 1 1/2"
A2331: 10274813 | B2331: ZFE3 | C2331: 1000 | D2331: M3 | E2331: 1000 | G2331: 1448 | H2331: MP ARENA TRIT RÍO MALLA 4
A2332: 10274815 | B2332: ZFE3 | C2332: 1000 | D2332: M3 | E2332: 1000 | G2332: 1366 | H2332: MP ARENA CLASIFICADA RÍO MALLA 5
A2333: 10274816 | B2333: ZFE3 | C2333: 1000 | D2333: M3 | E2333: 1000 | G2333: 1472 | H2333: MP GRAVA CLASIF RÍO 20 MM - 3/4"
A2334: 10275113 | B2334: ZFE3 | C2334: 1000 | D2334: M3 | E2334: 1000 | G2334: 1409 | H2334: MP ARENA TRIT ANDESITA MALLA 4
A2335: 10275114 | B2335: ZFE3 | C2335: 1000 | D2335: M3 | E2335: 1000 | G2335: 1418 | H2335: MP ARENA CLASIF RIO MALLA 4 - LAVADO
A2336: 10275115 | B2336: ZFE3 | C2336: 1000 | D2336: M3 | E2336: 1000 | G2336: 1259 | H2336: MP ARENA TRIT ANDESITA MALLA 4
A2337: 10275116 | B2337: ZFE3 | C2337: 1000 | D2337: M3 | E2337: 1000 | G2337: 1401 | H2337: MP GRAVA TRIT ANDESITA 3/4 - 20 MM
A2338: 10275118 | B2338: ZFE3 | C2338: 1000 | D2338: M3 | E2338: 1000 | G2338: 1401 | H2338: MP ARENA TRIT ANDESITA MALLA 4
... A2361: 10280049 | B2361: ZFE3 | C2361: 1000 | D2361: M3 | E2361: 1000 | G2361: 1584 | H2361: MP B. HID CALIZA 40% FINOS Y 60% GRUESOS
A2362: 10280365 | C2362: 1000 | D2362: M3 | E2362: 1000 | G2362: 1274 | H2362: MP GRAVA BASALTO 20 MM -3/4
A2363: 10280538 | B2363: ZFE3 | C2363: 1000 | D2363: M3 | E2363: 1000 | G2363: 1262 | H2363: MP GRAVA TRIT BASALTO 3/8 - 10MM
A2364: 10280679 | B2364: ZFE3 | C2364: 1000 | D2364: M3 | E2364: 1000 | G2364: 1349 | H2364: MP GRAVA CLASIF RÍO 13MM - 1/2"
A2365: 10281171 | B2365: ZFE3 | C2365: 1000 | D2365: M3 | E2365: 1000 | G2365: 1271 | H2365: MP GRAVA TRIT CALIZA 10MM - 3/8"
A2366: 10281183 | B2366: ZFE3 | C2366: 1000 | D2366: M3 | E2366: 1000 | G2366: 1468 | H2366: MP ARENA TRIT CALIZA MALLA 4
A2367: 10281384 | B2367: ZFE3 | C2367: 1000 | D2367: M3 | E2367: 1000 | G2367: 1285 | H2367: MP GRAVA BASALTO 40 MM (1 1/2")
A2368: 10281379 | B2368: ZFE3 | C2368: 1000 | D2368: M3 | E2368: 1000 | G2368: 1536 | H2368: MP ARENA CLASIF. RÍO MALLA 4
A2369: 10281450 | B2369: ZFE3 | C2369: 1000 | D2369: M3 | E2369: 1000 | G2369: 1325 | H2369: MP GRAVA CLASIF. RIO 20MM - 3/4
A2370: 10281451 | B2370: ZFE3 | C2370: 1000 | D2370: M3 | E2370: 1000 | G2370: 1564 | H2370: MP ARENA CLASIF. RÍO MALLA 4
A2371: 10281452 | B2371: ZFE3 | C2371: 1000 | D2371: M3 | E2371: 1000 | G2371: 1427 | H2371: MP GRAVA CLASIF. RIO 20MM - 3/4

Sheet TRAOPE
A1: Concat1 | B1: Contrato_Pos | C1: Doc. Compras | D1: Pos | E1: Org.compras | F1: Grp-Compr. | G1: Ship From | H1: Nombre SF | I1: Proveedor | J1: Nombre Prov | K1: Cond. Pago | L1: Descr. Cond Pago | M1: Material | N1: Descripción | O1: Centro | P1: Descripción Centro | Q1: In.perído validez | R1: Fin perído validez | S1: Válido de | T1: Validez a | U1: Precio neto pedido | V1: Moneda | W1: UM Precio Pedido | X1: Importe Condición | Y1: Moneda KONP | Z1: UM Ctd Base | AA1: Destino | AB1: Nombre Destino | AC1: Cuenta de mayor | AD1: Centro de costo | AE1: Cond. Exp. | AF1: Descr. Cond. Exp. | AG1: Peso Vol. | AH1: UMB | AI1: Ind. Oblig. Conf. Ped. | AJ1: Ctrl-Conf. | AK1: IVA | AL1: Modif_Date | AM1: Ruta
A2: 900009582DW65D30710281183 | B2: 4600072550-10 | C2: 4600072550 | D2: 10 | E2: MXPO | F2: MXL | G2: 900009582 | H2: SF TC-ED AVILA | I2: 5096906 | J2: TRITURADOS AVILA SA DE CV | K2: Z09 | L2: (AP) 90 Dias | M2: 10281183 | N2: MP ARENA TRIT CALIZA MALLA 4 | O2: DW65 | P2: MX-CED. YUCATAN-CAMPECHE | Q2: 20260817 | R2: 20301231 | S2: 20260817 | T2: 20301231 | U2: 420 | V2: MXN | W2: M3 | X2: 60 | Y2: MXN | Z2: M3 | AA2: D307 | AB2: PD0475 VALLADOLID 3 | AC2: 56103638 | AD2: 6644211540 | AE2: 4 | AF2: ENTREGA DIRECTA | AG2: 1.468 | AH2: M3 | AI2: X | AJ2: 4 | AK2: V4 | AL2: 20260821 | AM2: DW65-900009582-D307-10281183-4
A3: 900009582DW65D30710281171 | B3: 4600072550-20 | C3: 4600072550 | D3: 20 | E3: MXPO | F3: MXL | G3: 900009582 | H3: SF TC-ED AVILA | I3: 5096906 | J3: TRITURADOS AVILA SA DE CV | K3: Z09 | L3: (AP) 90 Dias | M3: 10281171 | N3: MP GRAVA TRIT CALIZA 10MM - 3/8" | O3: DW65 | P3: MX-CED. YUCATAN-CAMPECHE | Q3: 20260817 | R3: 20301231 | S3: 20260817 | T3: 20301231 | U3: 420 | V3: MXN | W3: M3 | X3: 60 | Y3: MXN | Z3: M3 | AA3: D307 | AB3: PD0475 VALLADOLID 3 | AC3: 56103637 | AD3: 6644211540 | AE3: 4 | AF3: ENTREGA DIRECTA | AG3: 1.271 | AH3: M3 | AI3: X | AJ3: 4 | AK3: V4 | AL3: 20260821 | AM3: DW65-900009582-D307-10281171-4
A4: 900007581DW65D33010217663 | B4: 4600071815-30 | C4: 4600071815 | D4: 30 | E4: MXPO | F4: MXL | G4: 900007581 | H4: SF-TC-ED-FREDDY DE LA CRUZ | I4: 5066828 | J4: DE LA CRUZ GARCIA FREDDY | K4: N90 | L4: (AP) NAFIN 90 Dias | M4: 10217663 | N4: ARENA CLASIFICADA RÍO MALLA 4 -TABASCO | O4: DW65 | P4: MX-CED. YUCATAN-CAMPECHE | Q4: 20251201 | R4: 20301231 | S4: 20260817 | T4: 20301231 | U4: 1612.5 | V4: MXN | W4: M3 | X4: 1512.5 | Y4: MXN | Z4: M3 | AA4: D330 | AB4: PD0441 DZITYA | AC4: 56103638 | AD4: 6644211540 | AE4: 4 | AF4: ENTREGA DIRECTA | AG4: 1.456 | AH4: M3 | AI4: X | AJ4: 4 | AK4: V4 | AL4: 20260821 | AM4: DW65-900007581-D330-10217663-4
A5: 900008300DW65ENXB10032932 | B5: 4600069667-20 | C5: 4600069667 | D5: 20 | E5: MXPO | F5: MXL | G5: 900008300 | H5: SF TC-ED-ICP | I5: 5090046 | J5: IMPULSORA COMERCIAL PETREUS SA DE C | K5: Z09 | L5: (AP) 90 Dias | M5: 10032932 | N5: Grava Triturada Caliza 20 mm - 3/4" | O5: DW65 | P5: MX-CED. YUCATAN-CAMPECHE | Q5: 20240606 | R5: 20291231 | S5: 20240606 | T5: 20291231 | U5: 400 | V5: MXN | W5: M3 | X5: 80 | Y5: MXN | Z5: M3 | AA5: ENXB | AB5: Tren Ligero - Campeche / MOTA ENGIL | AC5: 56103637 | AD5: 6644211540 | AE5: 4 | AF5: ENTREGA DIRECTA | AG5: 1.167 | AH5: M3 | AI5: X | AJ5: 4 | AK5: V4 | AL5: 20240612 | AM5: DW65-900008300-ENXB-10032932-4
A6: 900007052DW65D30410194399 | B6: 4600068564-10 | C6: 4600068564 | D6: 10 | E6: MXPO | F6: MXL | G6: 900007052 | H6: SF TC-ED-SAMUEL CARRASCO | I6: 5080454 | J6: CARRASCO ALCUDIA SAMUEL | K6: N90 | L6: (AP) NAFIN 90 Dias | M6: 10194399 | N6: ARENA CLASIFICADA DE RIO MALLA 4 | O6: DW65 | P6: MX-CED. YUCATAN-CAMPECHE | Q6: 20231003 | R6: 20281231 | S6: 20231003 | T6: 20281231 | U6: 1080 | V6: MXN | W6: M3 | X6: 1010 | Y6: MXN | Z6: M3 | AA6: D304 | AB6: PD0473 VILLA EL CIELO | AC6: 56103638 | AD6: 6644211540 | AE6: 4 | AF6: ENTREGA DIRECTA | AG6: 1.535 | AH6: M3 | AI6: X | AJ6: 4 | AK6: V4 | AL6: 20231005 | AM6: DW65-900007052-D304-10194399-4
A7: 900008008DW65D33510204013 | B7: 4600056242-30 | C7: 4600056242 | D7: 30 | E7: MXPO | F7: MXL | G7: 900008008 | H7: SF TC-ED-B-VILLA | I7: 5059278 | J7: COMERCIALIZADORA BECAN S DE RL | K7: N90 | L7: (AP) NAFIN 90 Dias | M7: 10204013 | N7: GRAVA CLASIFICADA RÍO 20 MM - 3/4" (CONT | O7: DW65 | P7: MX-CED. YUCATAN-CAMPECHE | Q7: 20230118 | R7: 20291231 | S7: 20240705 | T7: 20291231 | U7: 2800 | V7: MXN | W7: M3 | X7: 2000 | Y7: MXN | Z7: M3 | AA7: D335 | AB7: PD0229 MERIDA III | AC7: 56103637 | AD7: 6644211540 | AE7: 4 | AF7: ENTREGA DIRECTA | AG7: 1.44 | AH7: M3 | AI7: X | AJ7: 4 | AK7: V4 | AL7: 20240710 | AM7: DW65-900008008-D335-10204013-4
A8: 900000360DW6510000323 | B8: 4600050621-10 | C8: 4600050621 | D8: 10 | E8: MXPO | F8: MXL | G8: 900000360 | H8: TC-MITZA | I8: 5000354 | J8: PRODUCTOS MITZA SA DE CV | K8: Z04 | L8: (AP) 30 Dias | M8: 10000323 | N8: Arena Triturada Caliza Malla 5 | O8: DW65 | P8: MX-CED. YUCATAN-CAMPECHE | Q8: 20210712 | R8: 20291231 | S8: 20260601 | T8: 20301231 | U8: 309 | V8: MXN | W8: M3 | X8: 0 | Y8: MXN | Z8: M3 | AC8: 56103638 | AD8: 6644211540 | AE8: 1 | AF8: ENTREGADO | AG8: 1.36 | AH8: M3 | AI8: X | AJ8: 4 | AK8: V4 | AL8: 20260605 | AM8: DW65-900000360-10000323
A9: 900000360DW6510170257 | B9: 4600050621-50 | C9: 4600050621 | D9: 50 | E9: MXPO | F9: MXL | G9: 900000360 | H9: TC-MITZA | I9: 5000354 | J9: PRODUCTOS MITZA SA DE CV | K9: Z04 | L9: (AP) 30 Dias | M9: 10170257 | N9: ARENA TRITURADA CALIZA MALLA 4 | O9: DW65 | P9: MX-CED. YUCATAN-CAMPECHE | Q9: 20210712 | R9: 20291231 | S9: 20260601 | T9: 20301231 | U9: 315 | V9: MXN | W9: M3 | X9: 0 | Y9: MXN | Z9: M3 | AC9: 56103638 | AD9: 6644211540 | AE9: 1 | AF9: ENTREGADO | AG9: 1.47 | AH9: M3 | AI9: X | AJ9: 4 | AK9: V4 | AL9: 20260605 | AM9: DW65-900000360-10170257
A10: 900000360DW6510187950 | B10: 4600050621-60 | C10: 4600050621 | D10: 60 | E10: MXPO | F10: MXL | G10: 900000360 | H10: TC-MITZA | I10: 5000354 | J10: PRODUCTOS MITZA SA DE CV | K10: Z04 | L10: (AP) 30 Dias | M10: 10187950 | N10: ARENA TRITURADA CALIZA LAVADA | O10: DW65 | P10: MX-CED. YUCATAN-CAMPECHE | Q10: 20210712 | R10: 20291231 | S10: 20260601 | T10: 20301231 | U10: 303 | V10: MXN | W10: M3 | X10: 0 | Y10: MXN | Z10: M3 | AC10: 56103638 | AD10: 6644211540 | AE10: 1 | AF10: ENTREGADO | AG10: 1.286 | AH10: M3 | AI10: X | AJ10: 4 | AK10: V4 | AL10: 20260605 | AM10: DW65-900000360-10187950
A11: 900000360DW6510000677 | B11: 4600050621-20 | C11: 4600050621 | D11: 20 | E11: MXPO | F11: MXL | G11: 900000360 | H11: TC-MITZA | I11: 5000354 | J11: PRODUCTOS MITZA SA DE CV | K11: Z04 | L11: (AP) 30 Dias | M11: 10000677 | N11: Grava Triturada Caliza 20 mm - 3/4" | O11: DW65 | P11: MX-CED. YUCATAN-CAMPECHE | Q11: 20210712 | R11: 20291231 | S11: 20260601 | T11: 20301231 | U11: 303 | V11: MXN | W11: M3 | X11: 0 | Y11: MXN | Z11: M3 | AC11: 56103637 | AD11: 6644211540 | AE11: 1 | AF11: ENTREGADO | AG11: 1.164 | AH11: M3 | AI11: X | AJ11: 4 | AK11: V4 | AL11: 20260605 | AM11: DW65-900000360-10000677
A12: 900007121DW6510200686 | B12: 4600051014-10 | C12: 4600051014 | D12: 10 | E12: MXPO | F12: MXL | G12: 900007121 | H12: SF TC TRICOBLOCKS UMAN | I12: 5070947 | J12: TRICOBLOCKS DEL SURESTE SA DE CV | K12: N90 | L12: (AP) NAFIN 90 Dias | M12: 10200686 | N12: ARENA TRITURADA CALIZA MALLA 5 | O12: DW65 | P12: MX-CED. YUCATAN-CAMPECHE | Q12: 20210722 | R12: 20281231 | S12: 20230202 | T12: 20281231 | U12: 300 | V12: MXN | W12: M3 | X12: 0 | Y12: MXN | Z12: M3 | AC12: 56103638 | AD12: 6644211540 | AE12: 1 | AF12: ENTREGADO | AG12: 1.37 | AH12: M3 | AI12: X | AJ12: 4 | AK12: V4 | AL12: 20230920 | AM12: DW65-900007121-10200686
A13: 900000360DW6510149182 | B13: 4600050621-40 | C13: 4600050621 | D13: 40 | E13: MXPO | F13: MXL | G13: 900000360 | H13: TC-MITZA | I13: 5000354 | J13: PRODUCTOS MITZA SA DE CV | K13: Z04 | L13: (AP) 30 Dias | M13: 10149182 | N13: GRAVA CALIZA 40 MM (1 1/2") | O13: DW65 | P13: MX-CED. YUCATAN-CAMPECHE | Q13: 20210712 | R13: 20291231 | S13: 20211012 | T13: 20261231 | U13: 191.88 | V13: MXN | W13: M3 | X13: 0 | Y13: MXN | Z13: M3 | AC13: 56103637 | AD13: 6644211540 | AE13: 1 | AF13: ENTREGADO | AG13: 1.124 | AH13: M3 | AI13: X | AJ13: 4 | AK13: V4 | AL13: 20230920 | AM13: DW65-900000360-10149182
A14: 900000360DW6510070235 | B14: 4600050621-30 | C14: 4600050621 | D14: 30 | E14: MXPO | F14: MXL | G14: 900000360 | H14: TC-MITZA | I14: 5000354 | J14: PRODUCTOS MITZA SA DE CV | K14: Z04 | L14: (AP) 30 Dias | M14: 10070235 | N14: GRAVA TRITURADA CALIZA 10 MM - 3/8" | O14: DW65 | P14: MX-CED. YUCATAN-CAMPECHE | Q14: 20210712 | R14: 20291231 | S14: 20220815 | T14: 20271231 | U14: 220.66 | V14: MXN | W14: M3 | X14: 0 | Y14: MXN | Z14: M3 | AC14: 56103637 | AD14: 6644211540 | AE14: 1 | AF14: ENTREGADO | AG14: 1.228 | AH14: M3 | AI14: X | AJ14: 4 | AK14: V4 | AL14: 20230920 | AM14: DW65-900000360-10070235
A15: 900003903DW6510194399 | B15: 4600050616-20 | C15: 4600050616 | D15: 20 | E15: MXPO | F15: MXL | G15: 900003903 | H15: TC ESCUDERO AGUILAR | I15: 5014480 | J15: ESCUDERO AGUILAR ANDRES | K15: N90 | L15: (AP) NAFIN 90 Dias | M15: 10194399 | N15: ARENA CLASIFICADA DE RIO MALLA 4 | O15: DW65 | P15: MX-CED. YUCATAN-CAMPECHE | Q15: 20210712 | R15: 20271231 | S15: 20230124 | T15: 20271231 | U15: 60 | V15: MXN | W15: M3 | X15: 0 | Y15: MXN | Z15: M3 | AC15: 56103638 | AD15: 6644211540 | AE15: 1 | AF15: ENTREGADO | AG15: 1.535 | AH15: M3 | AI15: X | AJ15: 4 | AK15: V4 | AL15: 20230920 | AM15: DW65-900003903-10194399
A16: 900007121DW6510200685 | B16: 4600051014-20 | C16: 4600051014 | D16: 20 | E16: MXPO | F16: MXL | G16: 900007121 | H16: SF TC TRICOBLOCKS UMAN | I16: 5070947 | J16: TRICOBLOCKS DEL SURESTE SA DE CV | K16: N90 | L16: (AP) NAFIN 90 Dias | M16: 10200685 | N16: GRAVA TRITURADA CALIZA 20 MM - 3/4" | O16: DW65 | P16: MX-CED. YUCATAN-CAMPECHE | Q16: 20210722 | R16: 20281231 | S16: 20230202 | T16: 20281231 | U16: 260 | V16: MXN | W16: M3 | X16: 0 | Y16: MXN | Z16: M3 | AC16: 56103637 | AD16: 6644211540 | AE16: 1 | AF16: ENTREGADO | AG16: 1.15 | AH16: M3 | AI16: X | AJ16: 4 | AK16: V4 | AL16: 20230920 | AM16: DW65-900007121-10200685
A17: 900006183DW65D27610169383 | B17: 4600050644-20 | C17: 4600050644 | D17: 20 | E17: MXPO | F17: MXL | G17: 900006183 | H17: SF TC-ED-CISGO SEYBAPLAYA | I17: 5074344 | J17: CONSTRUCTORA INMOBILIARIA Y SUMINIS | K17: Z09 | L17: (AP) 90 Dias | M17: 10169383 | N17: GRAVA TRITURADA CALIZA 20 MM - 3/4" | O17: DW65 | P17: MX-CED. YUCATAN-CAMPECHE | Q17: 20210712 | R17: 20261231 | S17: 20210712 | T17: 20261231 | U17: 390 | V17: MXN | W17: M3 | X17: 270 | Y17: MXN | Z17: M3 | AA17: D276 | AB17: PD0440 CD.DEL CARMEN | AC17: 56103637 | AD17: 6644211540 | AE17: 4 | AF17: ENTREGA DIRECTA | AG17: 1.261 | AH17: M3 | AI17: X | AJ17: 4 | AK17: V4 | AL17: 20260108 | AM17: DW65-900006183-D276-10169383-4
A18: 900004430DW65D27610194399 | B18: 4600050631-70 | C18: 4600050631 | D18: 70 | E18: MXPO | F18: MXL | G18: 900004430 | H18: TC-ED-BECAN | I18: 5059278 | J18: COMERCIALIZADORA BECAN S DE RL | K18: N90 | L18: (AP) NAFIN 90 Dias | M18: 10194399 | N18: ARENA CLASIFICADA DE RIO MALLA 4 | O18: DW65 | P18: MX-CED. YUCATAN-CAMPECHE | Q18: 20210712 | R18: 20291231 | S18: 20210712 | T18: 20251231 | U18: 454 | V18: MXN | W18: M3 | X18: 388 | Y18: MXN | Z18: M3 | AA18: D276 | AB18: PD0440 CD.DEL CARMEN | AC18: 56103638 | AD18: 6644211540 | AE18: 4 | AF18: ENTREGA DIRECTA | AG18: 1.535 | AH18: M3 | AI18: X | AJ18: 4 | AK18: V4 | AL18: 20241230 | AM18: DW65-900004430-D276-10194399-4
A19: 900007098DW65D32410213531 | B19: 4600050656-50 | C19: 4600050656 | D19: 50 | E19: MXPO | F19: MXL | G19: 900007098 | H19: SF TC-ED-MAXCANU | I19: 5080340 | J19: SORIANO DURAN ERIC RICARDO | K19: N90 | L19: (AP) NAFIN 90 Dias | M19: 10213531 | N19: ARENA TRITURADA CALIZA MALLA 5 | O19: DW65 | P19: MX-CED. YUCATAN-CAMPECHE | Q19: 20210712 | R19: 20281231 | S19: 20250215 | T19: 20301231 | U19: 627.31 | V19: MXN | W19: M3 | X19: 257.58 | Y19: MXN | Z19: M3 | AA19: D324 | AB19: PD0400 CAMPECHE II | AC19: 56103638 | AD19: 6644211540 | AE19: 4 | AF19: ENTREGA DIRECTA | AG19: 1.345 | AH19: M3 | AI19: X | AJ19: 4 | AK19: V4 | AL19: 20250226 | AM19: DW65-900007098-D324-10213531-4
A20: 900004430DW65D27610099383 | B20: 4600050631-20 | C20: 4600050631 | D20: 20 | E20: MXPO | F20: MXL | G20: 900004430 | H20: TC-ED-BECAN | I20: 5059278 | J20: COMERCIALIZADORA BECAN S DE RL | K20: N90 | L20: (AP) NAFIN 90 Dias | M20: 10099383 | N20: GRAVA CALIZA 20 MM - 3/4" | O20: DW65 | P20: MX-CED. YUCATAN-CAMPECHE | Q20: 20210712 | R20: 20291231 | S20: 20250215 | T20: 20301231 | U20: 848 | V20: MXN | W20: M3 | X20: 477 | Y20: MXN | Z20: M3 | AA20: D276 | AB20: PD0440 CD.DEL CARMEN | AC20: 56103637 | AD20: 6644211540 | AE20: 4 | AF20: ENTREGA DIRECTA | AG20: 1.28 | AH20: M3 | AI20: X | AJ20: 4 | AK20: V4 | AL20: 20250226 | AM20: DW65-900004430-D276-10099383-4
A21: 900008008DW65D27610194399 | B21: 4600056242-40 | C21: 4600056242 | D21: 40 | E21: MXPO | F21: MXL | G21: 900008008 | H21: SF TC-ED-B-VILLA | I21: 5059278 | J21: COMERCIALIZADORA BECAN S DE RL | K21: N90 | L21: (AP) NAFIN 90 Dias | M21: 10194399 | N21: ARENA CLASIFICADA DE RIO MALLA 4 | O21: DW65 | P21: MX-CED. YUCATAN-CAMPECHE | Q21: 20230118 | R21: 20291231 | S21: 20250215 | T21: 20301231 | U21: 551 | V21: MXN | W21: M3 | X21: 482.3 | Y21: MXN | Z21: M3 | AA21: D276 | AB21: PD0440 CD.DEL CARMEN | AC21: 56103638 | AD21: 6644211540 | AE21: 4 | AF21: ENTREGA DIRECTA | AG21: 1.535 | AH21: M3 | AI21: X | AJ21: 4 | AK21: V4 | AL21: 20250226 | AM21: DW65-900008008-D276-10194399-4
A22: 900003867DW6510258300 | B22: 4600070233-10 | C22: 4600070233 | D22: 10 | E22: MXPO | F22: MXL | G22: 900003867 | H22: SF TC-MAPSA PERIFERICO | I22: 5014125 | J22: MATERIALES ANILLO PERIFERICO | K22: Z06 | L22: (AP) 45 Dias | M22: 10258300 | N22: ARENA TRITURADA CALIZA MALLA 5 | O22: DW65 | P22: MX-CED. YUCATAN-CAMPECHE | Q22: 20240910 | R22: 20291231 | S22: 20250215 | T22: 20301231 | U22: 290 | V22: MXN | W22: M3 | X22: 0 | Y22: MXN | Z22: M3 | AC22: 56103638 | AD22: 6644211540 | AE22: 1 | AF22: ENTREGADO | AG22: 1.389 | AH22: M3 | AI22: X | AJ22: 4 | AK22: V4 | AL22: 20250220 | AM22: DW65-900003867-10258300
A23: 900007098DW65D32410199478 | B23: 4600050656-60 | C23: 4600050656 | D23: 60 | E23: MXPO | F23: MXL | G23: 900007098 | H23: SF TC-ED-MAXCANU | I23: 5080340 | J23: SORIANO DURAN ERIC RICARDO | K23: N90 | L23: (AP) NAFIN 90 Dias | M23: 10199478 | N23: GRAVA TRITURADA CALIZA 20 MM - 3/4" | O23: DW65 | P23: MX-CED. YUCATAN-CAMPECHE | Q23: 20210712 | R23: 20281231 | S23: 20250215 | T23: 20301231 | U23: 615.64 | V23: MXN | W23: M3 | X23: 257.58 | Y23: MXN | Z23: M3 | AA23: D324 | AB23: PD0400 CAMPECHE II | AC23: 56103637 | AD23: 6644211540 | AE23: 4 | AF23: ENTREGA DIRECTA | AG23: 1.28 | AH23: M3 | AI23: X | AJ23: 4 | AK23: V4 | AL23: 20250226 | AM23: DW65-900007098-D324-10199478-4
A24: 900007581DW65D27610217663 | B24: 4600071815-10 | C24: 4600071815 | D24: 10 | E24: MXPO | F24: MXL | G24: 900007581 | H24: SF-TC-ED-FREDDY DE LA CRUZ | I24: 5066828 | J24: DE LA CRUZ GARCIA FREDDY | K24: N90 | L24: (AP) NAFIN 90 Dias | M24: 10217663 | N24: ARENA CLASIFICADA RÍO MALLA 4 -TABASCO | O24: DW65 | P24: MX-CED. YUCATAN-CAMPECHE | Q24: 20251201 | R24: 20301231 | S24: 20251201 | T24: 20301231 | U24: 505 | V24: MXN | W24: M3 | X24: 430 | Y24: MXN | Z24: M3 | AA24: D276 | AB24: PD0440 CD.DEL CARMEN | AC24: 56103638 | AD24: 6644211540 | AE24: 4 | AF24: ENTREGA DIRECTA | AG24: 1.456 | AH24: M3 | AI24: X | AJ24: 4 | AK24: V4 | AL24: 20251204 | AM24: DW65-900007581-D276-10217663-4
A25: 900007581DW65D32410217663 | B25: 4600071815-20 | C25: 4600071815 | D25: 20 | E25: MXPO | F25: MXL | G25: 900007581 | H25: SF-TC-ED-FREDDY DE LA CRUZ | I25: 5066828 | J25: DE LA CRUZ GARCIA FREDDY | K25: N90 | L25: (AP) NAFIN 90 Dias | M25: 10217663 | N25: ARENA CLASIFICADA RÍO MALLA 4 -TABASCO | O25: DW65 | P25: MX-CED. YUCATAN-CAMPECHE | Q25: 20251201 | R25: 20301231 | S25: 20251205 | T25: 20301231 | U25: 1100 | V25: MXN | W25: M3 | X25: 1030 | Y25: MXN | Z25: M3 | AA25: D324 | AB25: PD0400 CAMPECHE II | AC25: 56103638 | AD25: 6644211540 | AE25: 4 | AF25: ENTREGA DIRECTA | AG25: 1.456 | AH25: M3 | AI25: X | AJ25: 4 | AK25: V4 | AL25: 20251209 | AM25: DW65-900007581-D324-10217663-4
A26: 900009308DW6510000372 | B26: 4600071825-10 | C26: 4600071825 | D26: 10 | E26: MXPO | F26: MXL | G26: 900009308 | H26: SF TC FRISO STONE | I26: 5096328 | J26: FRISO STONE SCP DE B Y S RL DE CV | K26: N90 | L26: (AP) NAFIN 90 Dias | M26: 10000372 | N26: Grava Triturada Caliza 20 mm - 3/4" | O26: DW65 | P26: MX-CED. YUCATAN-CAMPECHE | Q26: 20251205 | R26: 20301231 | S26: 20251205 | T26: 20301231 | U26: 287 | V26: MXN | W26: M3 | X26: 0 | Y26: MXN | Z26: M3 | AC26: 56103637 | AD26: 6644211540 | AE26: 1 | AF26: ENTREGADO | AG26: 1.448 | AH26: M3 | AI26: X | AJ26: 4 | AK26: V4 | AL26: 20251209 | AM26: DW65-900009308-10000372
A27: 900006853DW65D30410189800 | B27: 4600050649-10 | C27: 4600050649 | D27: 10 | E27: MXPO | F27: MXL | G27: 900006853 | H27: SF TC-ED B-ARMIN | I27: 5059278 | J27: COMERCIALIZADORA BECAN S DE RL | K27: N90 | L27: (AP) NAFIN 90 Dias | M27: 10189800 | N27: GRAVA TRITURADA CALIZA 3/4 20MM | O27: DW65 | P27: MX-CED. YUCATAN-CAMPECHE | Q27: 20210712 | R27: 20291231 | S27: 20240108 | T27: 20291231 | U27: 590 | V27: MXN | W27: M3 | X27: 240 | Y27: MXN | Z27: M3 | AA27: D304 | AB27: PD0473 VILLA EL CIELO | AC27: 56103637 | AD27: 6644211540 | AE27: 4 | AF27: ENTREGA DIRECTA | AG27: 1.3 | AH27: M3 | AI27: X | AJ27: 4 | AK27: V4 | AL27: 20240129 | AM27: DW65-900006853-D304-10189800-4
A28: 900006853DW65D30410251894 | B28: 4600050649-50 | C28: 4600050649 | D28: 50 | E28: MXPO | F28: MXL | G28: 900006853 | H28: SF TC-ED B-ARMIN | I28: 5059278 | J28: COMERCIALIZADORA BECAN S DE RL | K28: N90 | L28: (AP) NAFIN 90 Dias | M28: 10251894 | N28: GRAVA TRITURADA CALIZA 10MM - 3/8" | O28: DW65 | P28: MX-CED. YUCATAN-CAMPECHE | Q28: 20210712 | R28: 20291231 | S28: 20240108 | T28: 20291231 | U28: 660 | V28: MXN | W28: M3 | X28: 240 | Y28: MXN | Z28: M3 | AA28: D304 | AB28: PD0473 VILLA EL CIELO | AC28: 56103637 | AD28: 6644211540 | AE28: 4 | AF28: ENTREGA DIRECTA | AG28: 1.282 | AH28: M3 | AI28: X | AJ28: 4 | AK28: V4 | AL28: 20240129 | AM28: DW65-900006853-D304-10251894-4
A29: 900008306DW65D30710224397 | B29: 4600058368-10 | C29: 4600058368 | D29: 10 | E29: MXPO | F29: MXL | G29: 900008306 | H29: SF TC-ED MAVASA | I29: 5070717 | J29: MATERIALES Y TRITURADOS VALLADOLID | K29: Z04 | L29: (AP) 30 Dias | M29: 10224397 | N29: ARENA TRITURADA CALIZA MALLA 4 | O29: DW65 | P29: MX-CED. YUCATAN-CAMPECHE | Q29: 20230815 | R29: 20281231 | S29: 20230815 | T29: 20281231 | U29: 395.72 | V29: MXN | W29: M3 | X29: 60.5 | Y29: MXN | Z29: M3 | AA29: D307 | AB29: PD0475 VALLADOLID 3 | AC29: 56103638 | AD29: 6644211540 | AE29: 4 | AF29: ENTREGA DIRECTA | AG29: 1.486 | AH29: M3 | AI29: X | AJ29: 4 | AK29: V4 | AL29: 20230920 | AM29: DW65-900008306-D307-10224397-4
A30: 900008306DW65D30710224398 | B30: 4600058368-20 | C30: 4600058368 | D30: 20 | E30: MXPO | F30: MXL | G30: 900008306 | H30: SF TC-ED MAVASA | I30: 5070717 | J30: MATERIALES Y TRITURADOS VALLADOLID | K30: Z04 | L30: (AP) 30 Dias | M30: 10224398 | N30: GRAVA TRITURADA CALIZA 20MM-3/4" | O30: DW65 | P30: MX-CED. YUCATAN-CAMPECHE | Q30: 20230815 | R30: 20281231 | S30: 20230815 | T30: 20281231 | U30: 395.72 | V30: MXN | W30: M3 | X30: 60.5 | Y30: MXN | Z30: M3 | AA30: D307 | AB30: PD0475 VALLADOLID 3 | AC30: 56103637 | AD30: 6644211540 | AE30: 4 | AF30: ENTREGA DIRECTA | AG30: 1.185 | AH30: M3 | AI30: X | AJ30: 4 | AK30: V4 | AL30: 20230920 | AM30: DW65-900008306-D307-10224398-4
A31: 900006853DW65D32410251894 | B31: 4600050649-60 | C31: 4600050649 | D31: 60 | E31: MXPO | F31: MXL | G31: 900006853 | H31: SF TC-ED B-ARMIN | I31: 5059278 | J31: COMERCIALIZADORA BECAN S DE RL | K31: N90 | L31: (AP) NAFIN 90 Dias | M31: 10251894 | N31: GRAVA TRITURADA CALIZA 10MM - 3/8" | O31: DW65 | P31: MX-CED. YUCATAN-CAMPECHE | Q31: 20210712 | R31: 20291231 | S31: 20240201 | T31: 20291231 | U31: 650 | V31: MXN | W31: M3 | X31: 250 | Y31: MXN | Z31: M3 | AA31: D324 | AB31: PD0400 CAMPECHE II | AC31: 56103637 | AD31: 6644211540 | AE31: 4 | AF31: ENTREGA DIRECTA | AG31: 1.282 | AH31: M3 | AI31: X | AJ31: 4 | AK31: V4 | AL31: 20240202 | AM31: DW65-900006853-D324-10251894-4
A32: 900006853DW65D27610151196 | B32: 4600050649-80 | C32: 4600050649 | D32: 80 | E32: MXPO | F32: MXL | G32: 900006853 | H32: SF TC-ED B-ARMIN | I32: 5059278 | J32: COMERCIALIZADORA BECAN S DE RL | K32: N90 | L32: (AP) NAFIN 90 Dias | M32: 10151196 | N32: ARENA TRITURADA CALIZA MALLA 5 | O32: DW65 | P32: MX-CED. YUCATAN-CAMPECHE | Q32: 20210712 | R32: 20291231 | S32: 20241018 | T32: 20291231 | U32: 900 | V32: MXN | W32: M3 | X32: 430 | Y32: MXN | Z32: M3 | AA32: D276 | AB32: PD0440 CD.DEL CARMEN | AC32: 56103638 | AD32: 6644211540 | AE32: 4 | AF32: ENTREGA DIRECTA | AG32: 1.342 | AH32: M3 | AI32: X | AJ32: 4 | AK32: V4 | AL32: 20241022 | AM32: DW65-900006853-D276-10151196-4
A33: 900006219DW65D32410078676 | B33: 4600050645-10 | C33: 4600050645 | D33: 10 | E33: MXPO | F33: MXL | G33: 900006219 | H33: SF TC-ED-CISGO VILLAHERMOSA | I33: 5074344 | J33: CONSTRUCTORA INMOBILIARIA Y SUMINIS | K33: Z09 | L33: (AP) 90 Dias | M33: 10078676 | N33: ARENA CLASIFICADA DE RIO MALLA 4 | O33: DW65 | P33: MX-CED. YUCATAN-CAMPECHE | Q33: 20210712 | R33: 20261231 | S33: 20210712 | T33: 20261231 | U33: 570 | V33: MXN | W33: M3 | X33: 522 | Y33: MXN | Z33: M3 | AA33: D324 | AB33: PD0400 CAMPECHE II | AC33: 56103638 | AD33: 6644211540 | AE33: 4 | AF33: ENTREGA DIRECTA | AG33: 1.356 | AH33: M3 | AI33: X | AJ33: 4 | AK33: V4 | AL33: 20260108 | AM33: DW65-900006219-D324-10078676-4
A34: 900008344DW6510239845 | B34: 4600068479-20 | C34: 4600068479 | D34: 20 | E34: MXPO | F34: MXL | G34: 900008344 | H34: SF TC-MAVASA (MATISA) | I34: 5070717 | J34: MATERIALES Y TRITURADOS VALLADOLID | K34: Z04 | L34: (AP) 30 Dias | M34: 10239845 | N34: ARENA TRITURADA CALIZA MALLA 4 - MAV. MA | O34: DW65 | P34: MX-CED. YUCATAN-CAMPECHE | Q34: 20230902 | R34: 20281231 | S34: 20230902 | T34: 20281231 | U34: 368.74 | V34: MXN | W34: M3 | X34: 0 | Y34: MXN | Z34: M3 | AC34: 56103638 | AD34: 6644211540 | AE34: 1 | AF34: ENTREGADO | AG34: 1.483 | AH34: M3 | AI34: X | AJ34: 4 | AK34: V4 | AL34: 20230911 | AM34: DW65-900008344-10239845
A35: 900002376DW6510213531 | B35: 4600050629-40 | C35: 4600050629 | D35: 40 | E35: MXPO | F35: MXL | G35: 900002376 | H35: TC-MITZA PLANTA 1 | I35: 5000354 | J35: PRODUCTOS MITZA SA DE CV | K35: Z04 | L35: (AP) 30 Dias | M35: 10213531 | N35: ARENA TRITURADA CALIZA MALLA 5 | O35: DW65 | P35: MX-CED. YUCATAN-CAMPECHE | Q35: 20210712 | R35: 20281231 | U35: 0 | V35: MXN | W35: M3 | AC35: 56103638 | AD35: 6644211540 | AE35: 1 | AF35: ENTREGADO | AG35: 1.345 | AH35: M3 | AI35: X | AJ35: 4 | AK35: V4 | AL35: 20260605 | AM35: DW65-900002376-10213531
A36: 900008008DW65D30410194399 | B36: 4600056242-10 | C36: 4600056242 | D36: 10 | E36: MXPO | F36: MXL | G36: 900008008 | H36: SF TC-ED-B-VILLA | I36: 5059278 | J36: COMERCIALIZADORA BECAN S DE RL | K36: N90 | L36: (AP) NAFIN 90 Dias | M36: 10194399 | N36: ARENA CLASIFICADA DE RIO MALLA 4 | O36: DW65 | P36: MX-CED. YUCATAN-CAMPECHE | Q36: 20230118 | R36: 20291231 | S36: 20240108 | T36: 20291231 | U36: 1300 | V36: MXN | W36: M3 | X36: 1225 | Y36: MXN | Z36: M3 | AA36: D304 | AB36: PD0473 VILLA EL CIELO | AC36: 56103638 | AD36: 6644211540 | AE36: 4 | AF36: ENTREGA DIRECTA | AG36: 1.535 | AH36: M3 | AI36: X | AJ36: 4 | AK36: V4 | AL36: 20240129 | AM36: DW65-900008008-D304-10194399-4
A37: 900006853DW65D30410151196 | B37: 4600050649-40 | C37: 4600050649 | D37: 40 | E37: MXPO | F37: MXL | G37: 900006853 | H37: SF TC-ED B-ARMIN | I37: 5059278 | J37: COMERCIALIZADORA BECAN S DE RL | K37: N90 | L37: (AP) NAFIN 90 Dias | M37: 10151196 | N37: ARENA TRITURADA CALIZA MALLA 5 | O37: DW65 | P37: MX-CED. YUCATAN-CAMPECHE | Q37: 20210712 | R37: 20291231 | S37: 20240108 | T37: 20291231 | U37: 700 | V37: MXN | W37: M3 | X37: 240 | Y37: MXN | Z37: M3 | AA37: D304 | AB37: PD0473 VILLA EL CIELO | AC37: 56103638 | AD37: 6644211540 | AE37: 4 | AF37: ENTREGA DIRECTA | AG37: 1.342 | AH37: M3 | AI37: X | AJ37: 4 | AK37: V4 | AL37: 20240129 | AM37: DW65-900006853-D304-10151196-4
A38: 900000000DW65D33010000541 | B38: 4600069928-30 | C38: 4600069928 | D38: 30 | E38: MXPO | F38: MXL | G38: 900000000 | H38: TC-ED-LAZCANO HUERTA | I38: 5000326 | J38: LAZCANO HUERTA ROCIO NANCY | K38: N90 | L38: (AP) NAFIN 90 Dias | M38: 10000541 | N38: Grava Clasificada Río 10 mm - 3/8" | O38: DW65 | P38: MX-CED. YUCATAN-CAMPECHE | Q38: 20240726 | R38: 20291231 | S38: 20241114 | T38: 20291231 | U38: 2400 | V38: MXN | W38: M3 | X38: 1950 | Y38: MXN | Z38: M3 | AA38: D330 | AB38: PD0441 DZITYA | AC38: 56103637 | AD38: 6644211540 | AE38: 4 | AF38: ENTREGA DIRECTA | AG38: 1.528 | AH38: M3 | AI38: X | AJ38: 4 | AK38: V4 | AL38: 20241117 | AM38: DW65-900000000-D330-10000541-4
A39: 900008008DW65D33510194399 | B39: 4600056242-20 | C39: 4600056242 | D39: 20 | E39: MXPO | F39: MXL | G39: 900008008 | H39: SF TC-ED-B-VILLA | I39: 5059278 | J39: COMERCIALIZADORA BECAN S DE RL | K39: N90 | L39: (AP) NAFIN 90 Dias | M39: 10194399 | N39: ARENA CLASIFICADA DE RIO MALLA 4 | O39: DW65 | P39: MX-CED. YUCATAN-CAMPECHE | Q39: 20230118 | R39: 20291231 | S39: 20240705 | T39: 20291231 | U39: 1900 | V39: MXN | W39: M3 | X39: 1840 | Y39: MXN | Z39: M3 | AA39: D335 | AB39: PD0229 MERIDA III | AC39: 56103638 | AD39: 6644211540 | AE39: 4 | AF39: ENTREGA DIRECTA | AG39: 1.535 | AH39: M3 | AI39: X | AJ39: 4 | AK39: V4 | AL39: 20240710 | AM39: DW65-900008008-D335-10194399-4
A40: 900008867DW65D30710258303 | B40: 4600069794-20 | C40: 4600069794 | D40: 20 | E40: MXPO | F40: MXL | G40: 900008867 | H40: SF TC-ED ICP CHEMAX | I40: 5090046 | J40: IMPULSORA COMERCIAL PETREUS SA DE C | K40: N90 | L40: (AP) NAFIN 90 Dias | M40: 10258303 | N40: GRAVA TRITURADA CALIZA 20 MM - 3/4" | O40: DW65 | P40: MX-CED. YUCATAN-CAMPECHE | Q40: 20240701 | R40: 20291231 | S40: 20240701 | T40: 20291231 | U40: 570 | V40: MXN | W40: M3 | X40: 100 | Y40: MXN | Z40: M3 | AA40: D307 | AB40: PD0475 VALLADOLID 3 | AC40: 56103637 | AD40: 6644211540 | AE40: 4 | AF40: ENTREGA DIRECTA | AG40: 1.153 | AH40: M3 | AI40: X | AJ40: 4 | AK40: V4 | AL40: 20240703 | AM40: DW65-900008867-D307-10258303-4
A41: 900008867DW65D30710258302 | B41: 4600069794-10 | C41: 4600069794 | D41: 10 | E41: MXPO | F41: MXL | G41: 900008867 | H41: SF TC-ED ICP CHEMAX | I41: 5090046 | J41: IMPULSORA COMERCIAL PETREUS SA DE C | K41: N90 | L41: (AP) NAFIN 90 Dias | M41: 10258302 | N41: ARENA TRITURADA CALIZA MALLA 5 | O41: DW65 | P41: MX-CED. YUCATAN-CAMPECHE | Q41: 20240701 | R41: 20291231 | S41: 20240701 | T41: 20291231 | U41: 580 | V41: MXN | W41: M3 | X41: 100 | Y41: MXN | Z41: M3 | AA41: D307 | AB41: PD0475 VALLADOLID 3 | AC41: 56103638 | AD41: 6644211540 | AE41: 4 | AF41: ENTREGA DIRECTA | AG41: 1.296 | AH41: M3 | AI41: X | AJ41: 4 | AK41: V4 | AL41: 20240703 | AM41: DW65-900008867-D307-10258302-4
A42: 900000184DW65D30710270825 | B42: 4600071015-40 | C42: 4600071015 | D42: 40 | E42: MXPO | F42: MXL | G42: 900000184 | H42: TC-ED-TRIVASA | I42: 5006784 | J42: TRIVASA SA DE CV | K42: N90 | L42: (AP) NAFIN 90 Dias | M42: 10270825 | N42: MP GRAVA TRITURADA CALIZA 10MM (3/8”) | O42: DW65 | P42: MX-CED. YUCATAN-CAMPECHE | Q42: 20250313 | R42: 20301231 | S42: 20260301 | T42: 20301231 | U42: 435.35 | V42: MXN | W42: M3 | X42: 68.96 | Y42: MXN | Z42: M3 | AA42: D307 | AB42: PD0475 VALLADOLID 3 | AC42: 56103637 | AD42: 6644211540 | AE42: 4 | AF42: ENTREGA DIRECTA | AG42: 1.242 | AH42: M3 | AI42: X | AJ42: 4 | AK42: V4 | AL42: 20260312 | AM42: DW65-900000184-D307-10270825-4
A43: 900000184DW65D30710224398 | B43: 4600071015-20 | C43: 4600071015 | D43: 20 | E43: MXPO | F43: MXL | G43: 900000184 | H43: TC-ED-TRIVASA | I43: 5006784 | J43: TRIVASA SA DE CV | K43: N90 | L43: (AP) NAFIN 90 Dias | M43: 10224398 | N43: GRAVA TRITURADA CALIZA 20MM-3/4" | O43: DW65 | P43: MX-CED. YUCATAN-CAMPECHE | Q43: 20250313 | R43: 20301231 | S43: 20260301 | T43: 20301231 | U43: 435.35 | V43: MXN | W43: M3 | X43: 68.96 | Y43: MXN | Z43: M3 | AA43: D307 | AB43: PD0475 VALLADOLID 3 | AC43: 56103637 | AD43: 6644211540 | AE43: 4 | AF43: ENTREGA DIRECTA | AG43: 1.185 | AH43: M3 | AI43: X | AJ43: 4 | AK43: V4 | AL43: 20260312 | AM43: DW65-900000184-D307-10224398-4
A44: 900000184DW65D30710222859 | B44: 4600071015-10 | C44: 4600071015 | D44: 10 | E44: MXPO | F44: MXL | G44: 900000184 | H44: TC-ED-TRIVASA | I44: 5006784 | J44: TRIVASA SA DE CV | K44: N90 | L44: (AP) NAFIN 90 Dias | M44: 10222859 | N44: ARENA TRITURADA T.M.N.A 04 MM | O44: DW65 | P44: MX-CED. YUCATAN-CAMPECHE | Q44: 20250313 | R44: 20301231 | S44: 20260301 | T44: 20301231 | U44: 435.35 | V44: MXN | W44: M3 | X44: 68.96 | Y44: MXN | Z44: M3 | AA44: D307 | AB44: PD0475 VALLADOLID 3 | AC44: 56103638 | AD44: 6644211540 | AE44: 4 | AF44: ENTREGA DIRECTA | AG44: 1.62 | AH44: M3 | AI44: X | AJ44: 4 | AK44: V4 | AL44: 20260312 | AM44: DW65-900000184-D307-10222859-4
A45: 900000184DW65D30710268996 | B45: 4600071015-30 | C45: 4600071015 | D45: 30 | E45: MXPO | F45: MXL | G45: 900000184 | H45: TC-ED-TRIVASA | I45: 5006784 | J45: TRIVASA SA DE CV | K45: N90 | L45: (AP) NAFIN 90 Dias | M45: 10268996 | N45: GRAVA TRITURADA CALIZA 40 MM - 11/2" | O45: DW65 | P45: MX-CED. YUCATAN-CAMPECHE | Q45: 20250313 | R45: 20301231 | S45: 20260301 | T45: 20301231 | U45: 456.9 | V45: MXN | W45: M3 | X45: 68.96 | Y45: MXN | Z45: M3 | AA45: D307 | AB45: PD0475 VALLADOLID 3 | AC45: 56103637 | AD45: 6644211540 | AE45: 4 | AF45: ENTREGA DIRECTA | AG45: 1.329 | AH45: M3 | AI45: X | AJ45: 4 | AK45: V4 | AL45: 20260312 | AM45: DW65-900000184-D307-10268996-4
A46: 900003867DW6510258301 | B46: 4600070233-20 | C46: 4600070233 | D46: 20 | E46: MXPO | F46: MXL | G46: 900003867 | H46: SF TC-MAPSA PERIFERICO | I46: 5014125 | J46: MATERIALES ANILLO PERIFERICO | K46: Z06 | L46: (AP) 45 Dias | M46: 10258301 | N46: GRAVA TRITURADA CALIZA 20 MM - 3/4" | O46: DW65 | P46: MX-CED. YUCATAN-CAMPECHE | Q46: 20240910 | R46: 20291231 | S46: 20240910 | T46: 20291231 | U46: 268 | V46: MXN | W46: M3 | X46: 0 | Y46: MXN | Z46: M3 | AC46: 56103637 | AD46: 6644211540 | AE46: 1 | AF46: ENTREGADO | AG46: 1.205 | AH46: M3 | AI46: X | AJ46: 4 | AK46: V4 | AL46: 20240913 | AM46: DW65-900003867-10258301
A47: 900009323DW65D33510270824 | B47: 4600071639-10 | C47: 4600071639 | D47: 10 | E47: MXPO | F47: MXL | G47: 900009323 | H47: SF TC-ED AGG PROSER | I47: 5079389 | J47: AGREGADOS PROSER SA DE CV | K47: Z09 | L47: (AP) 90 Dias | M47: 10270824 | N47: MP ARENA TRITURADA CALIZA MALLA 5 | O47: DW65 | P47: MX-CED. YUCATAN-CAMPECHE | Q47: 20250917 | R47: 20301231 | S47: 20250917 | T47: 20301231 | U47: 340 | V47: MXN | W47: M3 | X47: 50 | Y47: MXN | Z47: M3 | AA47: D335 | AB47: PD0229 MERIDA III | AC47: 56103638 | AD47: 6644211540 | AE47: 4 | AF47: ENTREGA DIRECTA | AG47: 1.325 | AH47: M3 | AI47: X | AJ47: 4 | AK47: V4 | AL47: 20251125 | AM47: DW65-900009323-D335-10270824-4
A48: 900007906DW6510224397 | B48: 4600055674-10 | C48: 4600055674 | D48: 10 | E48: MXPO | F48: MXL | G48: 900007906 | H48: SF TC-MAVASA | I48: 5070717 | J48: MATERIALES Y TRITURADOS VALLADOLID | K48: Z04 | L48: (AP) 30 Dias | M48: 10224397 | N48: ARENA TRITURADA CALIZA MALLA 4 | O48: DW65 | P48: MX-CED. YUCATAN-CAMPECHE | Q48: 20221103 | R48: 20281231 | S48: 20230701 | T48: 20281231 | U48: 335.22 | V48: MXN | W48: M3 | X48: 0 | Y48: MXN | Z48: M3 | AC48: 56103638 | AD48: 6644211540 | AE48: 1 | AF48: ENTREGADO | AG48: 1.486 | AH48: M3 | AI48: X | AJ48: 4 | AK48: V4 | AL48: 20230920 | AM48: DW65-900007906-10224397
A49: 900007968DW6510229016 | B49: 4600056419-10 | C49: 4600056419 | D49: 10 | E49: MXPO | F49: MXL | G49: 900007968 | H49: SF SD TC-MAYUCSA | I49: 5010179 | J49: MATERIALES DE YUCATAN SA DE CV | K49: Z04 | L49: (AP) 30 Dias | M49: 10229016 | N49: ARENA TRITURADA CALIZA MALLA 4 | O49: DW65 | P49: MX-CED. YUCATAN-CAMPECHE | Q49: 20230201 | R49: 20281231 | S49: 20230201 | T49: 20281231 | U49: 217 | V49: MXN | W49: M3 | X49: 0 | Y49: MXN | Z49: M3 | AC49: 56103638 | AD49: 6644211540 | AE49: 1 | AF49: ENTREGADO | AG49: 1.413 | AH49: M3 | AI49: X | AJ49: 4 | AK49: V4 | AL49: 20230920 | AM49: DW65-900007968-10229016
A50: 900003833DW6510224398 | B50: 4600056187-20 | C50: 4600056187 | D50: 20 | E50: MXPO | F50: MXL | G50: 900003833 | H50: TC-TRIVASA MERIDA | I50: 5006784 | J50: TRIVASA SA DE CV | K50: N90 | L50: (AP) NAFIN 90 Dias | M50: 10224398 | N50: GRAVA TRITURADA CALIZA 20MM-3/4" | O50: DW65 | P50: MX-CED. YUCATAN-CAMPECHE | Q50: 20230112 | R50: 20271231 | S50: 20230112 | T50: 20271231 | U50: 280.17 | V50: MXN | W50: M3 | X50: 0 | Y50: MXN | Z50: M3 | AC50: 56103637 | AD50: 6644211540 | AE50: 1 | AF50: ENTREGADO | AG50: 1.185 | AH50: M3 | AI50: X | AJ50: 4 | AK50: V4 | AL50: 20230920 | AM50: DW65-900003833-10224398
A51: 900007906DW6510224398 | B51: 4600055674-20 | C51: 4600055674 | D51: 20 | E51: MXPO | F51: MXL | G51: 900007906 | H51: SF TC-MAVASA | I51: 5070717 | J51: MATERIALES Y TRITURADOS VALLADOLID | K51: Z04 | L51: (AP) 30 Dias | M51: 10224398 | N51: GRAVA TRITURADA CALIZA 20MM-3/4" | O51: DW65 | P51: MX-CED. YUCATAN-CAMPECHE | Q51: 20221103 | R51: 20281231 | S51: 20230701 | T51: 20281231 | U51: 335.22 | V51: MXN | W51: M3 | X51: 0 | Y51: MXN | Z51: M3 | AC51: 56103637 | AD51: 6644211540 | AE51: 1 | AF51: ENTREGADO | AG51: 1.185 | AH51: M3 | AI51: X | AJ51: 4 | AK51: V4 | AL51: 20230920 | AM51: DW65-900007906-10224398
A52: 900007952DW6510194399 | B52: 4600056426-10 | C52: 4600056426 | D52: 10 | E52: MXPO | F52: MXL | G52: 900007952 | H52: SF TC-BANCO GARCIA | I52: 5067302 | J52: GARCIA BALTAZAR MIGUEL | K52: N90 | L52: (AP) NAFIN 90 Dias | M52: 10194399 | N52: ARENA CLASIFICADA DE RIO MALLA 4 | O52: DW65 | P52: MX-CED. YUCATAN-CAMPECHE | Q52: 20230202 | R52: 20271231 | S52: 20230202 | T52: 20271231 | U52: 57 | V52: MXN | W52: M3 | X52: 0 | Y52: MXN | Z52: M3 | AC52: 56103638 | AD52: 6644211540 | AE52: 1 | AF52: ENTREGADO | AG52: 1.535 | AH52: M3 | AI52: X | AJ52: 4 | AK52: V4 | AL52: 20230920 | AM52: DW65-900007952-10194399
A53: 900003833DW6510224397 | B53: 4600056187-10 | C53: 4600056187 | D53: 10 | E53: MXPO | F53: MXL | G53: 900003833 | H53: TC-TRIVASA MERIDA | I53: 5006784 | J53: TRIVASA SA DE CV | K53: N90 | L53: (AP) NAFIN 90 Dias | M53: 10224397 | N53: ARENA TRITURADA CALIZA MALLA 4 | O53: DW65 | P53: MX-CED. YUCATAN-CAMPECHE | Q53: 20230112 | R53: 20271231 | S53: 20230112 | T53: 20271231 | U53: 280.17 | V53: MXN | W53: M3 | X53: 0 | Y53: MXN | Z53: M3 | AC53: 56103638 | AD53: 6644211540 | AE53: 1 | AF53: ENTREGADO | AG53: 1.486 | AH53: M3 | AI53: X | AJ53: 4 | AK53: V4 | AL53: 20230920 | AM53: DW65-900003833-10224397
A54: 900008344DW6510239844 | B54: 4600068479-10 | C54: 4600068479 | D54: 10 | E54: MXPO | F54: MXL | G54: 900008344 | H54: SF TC-MAVASA (MATISA) | I54: 5070717 | J54: MATERIALES Y TRITURADOS VALLADOLID | K54: Z04 | L54: (AP) 30 Dias | M54: 10239844 | N54: GRAVA TRITURADA CALIZA 3/4 - MAV. MATISA | O54: DW65 | P54: MX-CED. YUCATAN-CAMPECHE | Q54: 20230902 | R54: 20281231 | S54: 20230902 | T54: 20281231 | U54: 368.74 | V54: MXN | W54: M3 | X54: 0 | Y54: MXN | Z54: M3 | AC54: 56103637 | AD54: 6644211540 | AE54: 1 | AF54: ENTREGADO | AG54: 1.355 | AH54: M3 | AI54: X | AJ54: 4 | AK54: V4 | AL54: 20230911 | AM54: DW65-900008344-10239844
A55: 900008049DW65D33510256033 | B55: 4600056703-30 | C55: 4600056703 | D55: 30 | E55: MXPO | F55: MXL | G55: 900008049 | H55: SF TC-ED- JJDR | I55: 5088349 | J55: ACARREOS Y AGREGADOS JJDR SA DE CV | K55: Z04 | L55: (AP) 30 Dias | M55: 10256033 | N55: GRAVA TRITURADA CALIZA 40 MM - 1 1/2" | O55: DW65 | P55: MX-CED. YUCATAN-CAMPECHE | Q55: 20230227 | R55: 20291231 | S55: 20240411 | T55: 20291231 | U55: 320 | V55: MXN | W55: M3 | X55: 70 | Y55: MXN | Z55: M3 | AA55: D335 | AB55: PD0229 MERIDA III | AC55: 56103637 | AD55: 6644211540 | AE55: 4 | AF55: ENTREGA DIRECTA | AG55: 1.339 | AH55: M3 | AI55: X | AJ55: 4 | AK55: V4 | AL55: 20240413 | AM55: DW65-900008049-D335-10256033-4
A56: 900008049DW65D33010256033 | B56: 4600056703-40 | C56: 4600056703 | D56: 40 | E56: MXPO | F56: MXL | G56: 900008049 | H56: SF TC-ED- JJDR | I56: 5088349 | J56: ACARREOS Y AGREGADOS JJDR SA DE CV | K56: Z04 | L56: (AP) 30 Dias | M56: 10256033 | N56: GRAVA TRITURADA CALIZA 40 MM - 1 1/2" | O56: DW65 | P56: MX-CED. YUCATAN-CAMPECHE | Q56: 20230227 | R56: 20291231 | S56: 20240411 | T56: 20291231 | U56: 345 | V56: MXN | W56: M3 | X56: 95 | Y56: MXN | Z56: M3 | AA56: D330 | AB56: PD0441 DZITYA | AC56: 56103637 | AD56: 6644211540 | AE56: 4 | AF56: ENTREGA DIRECTA | AG56: 1.339 | AH56: M3 | AI56: X | AJ56: 4 | AK56: V4 | AL56: 20240413 | AM56: DW65-900008049-D330-10256033-4
A57: 900008621DW65D30410230731 | B57: 4600068662-10 | C57: 4600068662 | D57: 10 | E57: MXPO | F57: MXL | G57: 900008621 | H57: SF TC-ED FEDMAC SEYBA | I57: 5088376 | J57: COMERCIALIZADORA FEDMAC DE MEXICO S | K57: N90 | L57: (AP) NAFIN 90 Dias | M57: 10230731 | N57: GRAVA TRITURADA CALIZA 3/4 20MM | O57: DW65 | P57: MX-CED. YUCATAN-CAMPECHE | Q57: 20231020 | R57: 20281231 | S57: 20231020 | T57: 20281231 | U57: 663 | V57: MXN | W57: M3 | X57: 343 | Y57: MXN | Z57: M3 | AA57: D304 | AB57: PD0473 VILLA EL CIELO | AC57: 56103637 | AD57: 6644211540 | AE57: 4 | AF57: ENTREGA DIRECTA | AG57: 1.292 | AH57: M3 | AI57: X | AJ57: 4 | AK57: V4 | AL57: 20231024 | AM57: DW65-900008621-D304-10230731-4
A58: 900005305DW6510145057 | B58: 4600050632-20 | C58: 4600050632 | D58: 20 | E58: MXPO | F58: MXL | G58: 900005305 | H58: TC- MAPSA TEBEC | I58: 5014125 | J58: MATERIALES ANILLO PERIFERICO | K58: Z06 | L58: (AP) 45 Dias | M58: 10145057 | N58: GRAVA TRITURADA CALIZA 20MM-3/4" | O58: DW65 | P58: MX-CED. YUCATAN-CAMPECHE | Q58: 20210712 | R58: 20281231 | S58: 20260201 | T58: 20301231 | U58: 305.55 | V58: MXN | W58: M3 | X58: 0 | Y58: MXN | Z58: M3 | AC58: 56103637 | AD58: 6644211540 | AE58: 1 | AF58: ENTREGADO | AG58: 1.24 | AH58: M3 | AI58: X | AJ58: 4 | AK58: V4 | AL58: 20260223 | AM58: DW65-900005305-10145057
A59: 900007025DW6510193619 | B59: 4600050652-10 | C59: 4600050652 | D59: 10 | E59: MXPO | F59: MXL | G59: 900007025 | H59: SF TC- MAPSA TEBEC II | I59: 5014125 | J59: MATERIALES ANILLO PERIFERICO | K59: Z06 | L59: (AP) 45 Dias | M59: 10193619 | N59: ARENA TRITURADA CALIZA MALLA 5 | O59: DW65 | P59: MX-CED. YUCATAN-CAMPECHE | Q59: 20210712 | R59: 20261231 | S59: 20260201 | T59: 20301231 | U59: 304.5 | V59: MXN | W59: M3 | X59: 0 | Y59: MXN | Z59: M3 | AC59: 56103638 | AD59: 6644211540 | AE59: 1 | AF59: ENTREGADO | AG59: 1.34 | AH59: M3 | AI59: X | AJ59: 4 | AK59: V4 | AL59: 20260223 | AM59: DW65-900007025-10193619
A60: 900005305DW6510145056 | B60: 4600050632-10 | C60: 4600050632 | D60: 10 | E60: MXPO | F60: MXL | G60: 900005305 | H60: TC- MAPSA TEBEC | I60: 5014125 | J60: MATERIALES ANILLO PERIFERICO | K60: Z06 | L60: (AP) 45 Dias | M60: 10145056 | N60: GRAVA TRITURADA CALIZA 10MM-3/8" | O60: DW65 | P60: MX-CED. YUCATAN-CAMPECHE | Q60: 20210712 | R60: 20281231 | S60: 20260201 | T60: 20301231 | U60: 305.55 | V60: MXN | W60: M3 | X60: 0 | Y60: MXN | Z60: M3 | AC60: 56103637 | AD60: 6644211540 | AE60: 1 | AF60: ENTREGADO | AG60: 1.114 | AH60: M3 | AI60: X | AJ60: 4 | AK60: V4 | AL60: 20260223 | AM60: DW65-900005305-10145056
A61: 900005305DW6510153353 | B61: 4600050632-40 | C61: 4600050632 | D61: 40 | E61: MXPO | F61: MXL | G61: 900005305 | H61: TC- MAPSA TEBEC | I61: 5014125 | J61: MATERIALES ANILLO PERIFERICO | K61: Z06 | L61: (AP) 45 Dias | M61: 10153353 | N61: GRAVA TRITURADA CALIZA 40 MM - 11/2" | O61: DW65 | P61: MX-CED. YUCATAN-CAMPECHE | Q61: 20210712 | R61: 20281231 | S61: 20260201 | T61: 20301231 | U61: 330.75 | V61: MXN | W61: M3 | X61: 0 | Y61: MXN | Z61: M3 | AC61: 56103637 | AD61: 6644211540 | AE61: 1 | AF61: ENTREGADO | AG61: 1.192 | AH61: M3 | AI61: X | AJ61: 4 | AK61: V4 | AL61: 20260223 | AM61: DW65-900005305-10153353
A62: 900005305DW6510151196 | B62: 4600050632-30 | C62: 4600050632 | D62: 30 | E62: MXPO | F62: MXL | G62: 900005305 | H62: TC- MAPSA TEBEC | I62: 5014125 | J62: MATERIALES ANILLO PERIFERICO | K62: Z06 | L62: (AP) 45 Dias | M62: 10151196 | N62: ARENA TRITURADA CALIZA MALLA 5 | O62: DW65 | P62: MX-CED. YUCATAN-CAMPECHE | Q62: 20210712 | R62: 20281231 | S62: 20260201 | T62: 20301231 | U62: 311.85 | V62: MXN | W62: M3 | X62: 0 | Y62: MXN | Z62: M3 | AC62: 56103638 | AD62: 6644211540 | AE62: 1 | AF62: ENTREGADO | AG62: 1.342 | AH62: M3 | AI62: X | AJ62: 4 | AK62: V4 | AL62: 20260223 | AM62: DW65-900005305-10151196
A63: 900000743DW6510000561 | B63: 4600050622-10 | C63: 4600050622 | D63: 10 | E63: MXPO | F63: MXL | G63: 900000743 | H63: TC SIGSA | I63: 5021622 | J63: SERVICIOS DE INGENIERIA DEL GOLFO | K63: N60 | L63: (AP) NAFIN 60 Dias | M63: 10000561 | N63: Grava Triturada Caliza 20 mm - 3/4" | O63: DW65 | P63: MX-CED. YUCATAN-CAMPECHE | Q63: 20210712 | R63: 20261231 | S63: 20210712 | T63: 20261231 | U63: 192 | V63: MXN | W63: M3 | X63: 0 | Y63: MXN | Z63: M3 | AC63: 56103637 | AD63: 6644211540 | AE63: 1 | AF63: ENTREGADO | AG63: 1.43 | AH63: M3 | AI63: X | AJ63: 4 | AK63: V4 | AL63: 20260108 | AM63: DW65-900000743-10000561
A64: 900003903DW6510078676 | B64: 4600050616-10 | C64: 4600050616 | D64: 10 | E64: MXPO | F64: MXL | G64: 900003903 | H64: TC ESCUDERO AGUILAR | I64: 5014480 | J64: ESCUDERO AGUILAR ANDRES | K64: N90 | L64: (AP) NAFIN 90 Dias | M64: 10078676 | N64: ARENA CLASIFICADA DE RIO MALLA 4 | O64: DW65 | P64: MX-CED. YUCATAN-CAMPECHE | Q64: 20210712 | R64: 20271231 | S64: 20210712 | T64: 20251231 | U64: 49 | V64: MXN | W64: M3 | X64: 0 | Y64: MXN | Z64: M3 | AC64: 56103638 | AD64: 6644211540 | AE64: 1 | AF64: ENTREGADO | AG64: 1.356 | AH64: M3 | AI64: X | AJ64: 4 | AK64: V4 | AL64: 20230920 | AM64: DW65-900003903-10078676
A65: 900005305DW6510168313 | B65: 4600050632-50 | C65: 4600050632 | D65: 50 | E65: MXPO | F65: MXL | G65: 900005305 | H65: TC- MAPSA TEBEC | I65: 5014125 | J65: MATERIALES ANILLO PERIFERICO | K65: Z06 | L65: (AP) 45 Dias | M65: 10168313 | N65: GRAVA TRITURADA CALIZA 13MM--1/2" | O65: DW65 | P65: MX-CED. YUCATAN-CAMPECHE | Q65: 20210712 | R65: 20281231 | S65: 20210712 | T65: 20251231 | U65: 245 | V65: MXN | W65: M3 | X65: 0 | Y65: MXN | Z65: M3 | AC65: 56103637 | AD65: 6644211540 | AE65: 1 | AF65: ENTREGADO | AG65: 1.178 | AH65: M3 | AI65: X | AJ65: 4 | AK65: V4 | AL65: 20230920 | AM65: DW65-900005305-10168313
A66: 900009547DW6510099383 | B66: 4600072253-10 | C66: 4600072253 | D66: 10 | E66: MXPO | F66: MXL | G66: 900009547 | H66: SF TC-BECAN | I66: 5059278 | J66: COMERCIALIZADORA BECAN S DE RL | K66: N90 | L66: (AP) NAFIN 90 Dias | M66: 10099383 | N66: GRAVA CALIZA 20 MM - 3/4" | O66: DW65 | P66: MX-CED. YUCATAN-CAMPECHE | Q66: 20260514 | R66: 20301231 | S66: 20260514 | T66: 20301231 | U66: 330 | V66: MXN | W66: M3 | X66: 0 | Y66: MXN | Z66: M3 | AC66: 56103637 | AD66: 6644211540 | AE66: 1 | AF66: ENTREGADO | AG66: 1.28 | AH66: M3 | AI66: X | AJ66: 4 | AK66: V4 | AL66: 20260520 | AM66: DW65-900009547-10099383
A67: 900009546DW6510199478 | B67: 4600072252-10 | C67: 4600072252 | D67: 10 | E67: MXPO | F67: MXL | G67: 900009546 | H67: SF TC-MAXCANU | I67: 5080340 | J67: SORIANO DURAN ERIC RICARDO | K67: N90 | L67: (AP) NAFIN 90 Dias | M67: 10199478 | N67: GRAVA TRITURADA CALIZA 20 MM - 3/4" | O67: DW65 | P67: MX-CED. YUCATAN-CAMPECHE | Q67: 20260514 | R67: 20301231 | S67: 20260514 | T67: 20301231 | U67: 358.06 | V67: MXN | W67: M3 | X67: 0 | Y67: MXN | Z67: M3 | AC67: 56103637 | AD67: 6644211540 | AE67: 1 | AF67: ENTREGADO | AG67: 1.347 | AH67: M3 | AI67: X | AJ67: 4 | AK67: V4 | AL67: 20260520 | AM67: DW65-900009546-10199478
A68: 900009546DW6510213531 | B68: 4600072252-20 | C68: 4600072252 | D68: 20 | E68: MXPO | F68: MXL | G68: 900009546 | H68: SF TC-MAXCANU | I68: 5080340 | J68: SORIANO DURAN ERIC RICARDO | K68: N90 | L68: (AP) NAFIN 90 Dias | M68: 10213531 | N68: ARENA TRITURADA CALIZA MALLA 5 | O68: DW65 | P68: MX-CED. YUCATAN-CAMPECHE | Q68: 20260514 | R68: 20301231 | S68: 20260514 | T68: 20301231 | U68: 369.73 | V68: MXN | W68: M3 | X68: 0 | Y68: MXN | Z68: M3 | AC68: 56103638 | AD68: 6644211540 | AE68: 1 | AF68: ENTREGADO | AG68: 1.345 | AH68: M3 | AI68: X | AJ68: 4 | AK68: V4 | AL68: 20260520 | AM68: DW65-900009546-10213531
A69: 900004430DW65D32410099383 | B69: 4600050631-80 | C69: 4600050631 | D69: 80 | E69: MXPO | F69: MXL | G69: 900004430 | H69: TC-ED-BECAN | I69: 5059278 | J69: COMERCIALIZADORA BECAN S DE RL | K69: N90 | L69: (AP) NAFIN 90 Dias | M69: 10099383 | N69: GRAVA CALIZA 20 MM - 3/4" | O69: DW65 | P69: MX-CED. YUCATAN-CAMPECHE | Q69: 20210712 | R69: 20291231 | S69: 20250207 | T69: 20301231 | U69: 605 | V69: MXN | W69: M3 | X69: 275 | Y69: MXN | Z69: M3 | AA69: D324 | AB69: PD0400 CAMPECHE II | AC69: 56103637 | AD69: 6644211540 | AE69: 4 | AF69: ENTREGA DIRECTA | AG69: 1.28 | AH69: M3 | AI69: X | AJ69: 4 | AK69: V4 | AL69: 20250210 | AM69: DW65-900004430-D324-10099383-4
A70: 900006853DW65D27610251894 | B70: 4600050649-70 | C70: 4600050649 | D70: 70 | E70: MXPO | F70: MXL | G70: 900006853 | H70: SF TC-ED B-ARMIN | I70: 5059278 | J70: COMERCIALIZADORA BECAN S DE RL | K70: N90 | L70: (AP) NAFIN 90 Dias | M70: 10251894 | N70: GRAVA TRITURADA CALIZA 10MM - 3/8" | O70: DW65 | P70: MX-CED. YUCATAN-CAMPECHE | Q70: 20210712 | R70: 20291231 | S70: 20240910 | T70: 20291231 | U70: 880 | V70: MXN | W70: M3 | X70: 430 | Y70: MXN | Z70: M3 | AA70: D276 | AB70: PD0440 CD.DEL CARMEN | AC70: 56103637 | AD70: 6644211540 | AE70: 4 | AF70: ENTREGA DIRECTA | AG70: 1.282 | AH70: M3 | AI70: X | AJ70: 4 | AK70: V4 | AL70: 20240911 | AM70: DW65-900006853-D276-10251894-4
A71: 900008008DW65D33010194399 | B71: 4600056242-50 | C71: 4600056242 | D71: 50 | E71: MXPO | F71: MXL | G71: 900008008 | H71: SF TC-ED-B-VILLA | I71: 5059278 | J71: COMERCIALIZADORA BECAN S DE RL | K71: N90 | L71: (AP) NAFIN 90 Dias | M71: 10194399 | N71: ARENA CLASIFICADA DE RIO MALLA 4 | O71: DW65 | P71: MX-CED. YUCATAN-CAMPECHE | Q71: 20230118 | R71: 20291231 | S71: 20250318 | T71: 20301231 | U71: 1998 | V71: MXN | W71: M3 | X71: 1938 | Y71: MXN | Z71: M3 | AA71: D330 | AB71: PD0441 DZITYA | AC71: 56103638 | AD71: 6644211540 | AE71: 4 | AF71: ENTREGA DIRECTA | AG71: 1.535 | AH71: M3 | AI71: X | AJ71: 4 | AK71: V4 | AL71: 20250321 | AM71: DW65-900008008-D330-10194399-4
A72: 900000000DW65D33510000541 | B72: 4600069928-20 | C72: 4600069928 | D72: 20 | E72: MXPO | F72: MXL | G72: 900000000 | H72: TC-ED-LAZCANO HUERTA | I72: 5000326 | J72: LAZCANO HUERTA ROCIO NANCY | K72: N90 | L72: (AP) NAFIN 90 Dias | M72: 10000541 | N72: Grava Clasificada Río 10 mm - 3/8" | O72: DW65 | P72: MX-CED. YUCATAN-CAMPECHE | Q72: 20240726 | R72: 20291231 | S72: 20241105 | T72: 20291231 | U72: 2400 | V72: MXN | W72: M3 | X72: 1950 | Y72: MXN | Z72: M3 | AA72: D335 | AB72: PD0229 MERIDA III | AC72: 56103637 | AD72: 6644211540 | AE72: 4 | AF72: ENTREGA DIRECTA | AG72: 1.528 | AH72: M3 | AI72: X | AJ72: 4 | AK72: V4 | AL72: 20241107 | AM72: DW65-900000000-D335-10000541-4
A73: 900007953DW65D27610194399 | B73: 4600068510-10 | C73: 4600068510 | D73: 10 | E73: MXPO | F73: MXL | G73: 900007953 | H73: SF TC-ED-BANCO GARCIA | I73: 5067302 | J73: GARCIA BALTAZAR MIGUEL | K73: N90 | L73: (AP) NAFIN 90 Dias | M73: 10194399 | N73: ARENA CLASIFICADA DE RIO MALLA 4 | O73: DW65 | P73: MX-CED. YUCATAN-CAMPECHE | Q73: 20230919 | R73: 20281231 | S73: 20230919 | T73: 20281231 | U73: 553.4 | V73: MXN | W73: M3 | X73: 488.4 | Y73: MXN | Z73: M3 | AA73: D276 | AB73: PD0440 CD.DEL CARMEN | AC73: 56103638 | AD73: 6644211540 | AE73: 4 | AF73: ENTREGA DIRECTA | AG73: 1.535 | AH73: M3 | AI73: X | AJ73: 4 | AK73: V4 | AL73: 20230920 | AM73: DW65-900007953-D276-10194399-4
