Workbook

Sheet Base Cedis D814
N1: VENTA | Q1: COSTO
A2: CONCAT1 | B2: CONCAT2 | C2: No. SF | D2: Nombre SF | E2: Cedis | F2: Destino | G2: Condicion de Expedicion | H2: Nombre Destino | I2: No. de material | J2: Nombre de material | K2: PV | L2: Inicio de vigencia | M2: Fin de vigencia | N2: Importe MP | O2: Importe Flete | P2: UM Venta | Q2: Importe Costo | R2: UM Costo | S2: Validacion 1 | T2: Validacion 2
A3: =CONCATENATE(C3,E3,F3,I3) | B3: =CONCATENATE(C3,E3,I3) | C3: 900005920 | D3: =IFERROR(VLOOKUP(C3,TRAOPE!$G:$H,2,0),"") | E3: D814 | F3: ER67 | G3: =IFERROR(VLOOKUP(A3,Flete!$A:$E,5,0),"") | H3: =IFERROR(VLOOKUP(F3,TRAOPE!$AA:$AB,2,0),"") | I3: 10003240 | J3: =IFERROR(VLOOKUP(I3,Materiales!$A:$H,8,0),"") | K3: =IFERROR(VLOOKUP(I3,Materiales!$A:$G,7,0),"") | L3: 20220504 | M3: 20230127 | N3: 179.68 | O3: =IFERROR(VLOOKUP(A3,Flete!$A:$J,10,0),"") | P3: TN | Q3: =IFERROR(IFERROR(VLOOKUP(A3,TRAOPE!$A:$U,21,0),VLOOKUP(B3,TRAOPE!$A:$U,21,0)),"") | R3: =IFERROR(IFERROR(VLOOKUP(A3,TRAOPE!$A:$W,23,0),VLOOKUP(B3,TRAOPE!$A:$W,23,0)),"") | S3: =IF(AND(P3="TN",R3="TN"),N3+N(O3),IF(G3&""="1",N(K3)*N3,(N3+N(O3))*N(K3))) | T3: =IF(Q3="","",Q3-S3)
A4: =CONCATENATE(C4,E4,F4,I4) | B4: =CONCATENATE(C4,E4,I4) | C4: 900006731 | D4: =IFERROR(VLOOKUP(C4,TRAOPE!$G:$H,2,0),"") | E4: D814 | F4: EO04 | G4: =IFERROR(VLOOKUP(A4,Flete!$A:$E,5,0),"") | H4: =IFERROR(VLOOKUP(F4,TRAOPE!$AA:$AB,2,0),"") | I4: 10000561 | J4: =IFERROR(VLOOKUP(I4,Materiales!$A:$H,8,0),"") | K4: =IFERROR(VLOOKUP(I4,Materiales!$A:$G,7,0),"") | L4: 20220504 | M4: 20230127 | N4: 161.94 | O4: =IFERROR(VLOOKUP(A4,Flete!$A:$J,10,0),"") | P4: TN | Q4: =IFERROR(IFERROR(VLOOKUP(A4,TRAOPE!$A:$U,21,0),VLOOKUP(B4,TRAOPE!$A:$U,21,0)),"") | R4: =IFERROR(IFERROR(VLOOKUP(A4,TRAOPE!$A:$W,23,0),VLOOKUP(B4,TRAOPE!$A:$W,23,0)),"") | S4: =IF(AND(P4="TN",R4="TN"),N4+N(O4),IF(G4&""="1",N(K4)*N4,(N4+N(O4))*N(K4))) | T4: =IF(Q4="","",Q4-S4)
A5: =CONCATENATE(C5,E5,F5,I5) | B5: =CONCATENATE(C5,E5,I5) | C5: 900006731 | D5: =IFERROR(VLOOKUP(C5,TRAOPE!$G:$H,2,0),"") | E5: D814 | F5: EO04 | G5: =IFERROR(VLOOKUP(A5,Flete!$A:$E,5,0),"") | H5: =IFERROR(VLOOKUP(F5,TRAOPE!$AA:$AB,2,0),"") | I5: 10123034 | J5: =IFERROR(VLOOKUP(I5,Materiales!$A:$H,8,0),"") | K5: =IFERROR(VLOOKUP(I5,Materiales!$A:$G,7,0),"") | L5: 20220504 | M5: 20230127 | N5: 55.11 | O5: =IFERROR(VLOOKUP(A5,Flete!$A:$J,10,0),"") | P5: TN | Q5: =IFERROR(IFERROR(VLOOKUP(A5,TRAOPE!$A:$U,21,0),VLOOKUP(B5,TRAOPE!$A:$U,21,0)),"") | R5: =IFERROR(IFERROR(VLOOKUP(A5,TRAOPE!$A:$W,23,0),VLOOKUP(B5,TRAOPE!$A:$W,23,0)),"") | S5: =IF(AND(P5="TN",R5="TN"),N5+N(O5),IF(G5&""="1",N(K5)*N5,(N5+N(O5))*N(K5))) | T5: =IF(Q5="","",Q5-S5)
A6: =CONCATENATE(C6,E6,F6,I6) | B6: =CONCATENATE(C6,E6,I6) | C6: 900006732 | D6: =IFERROR(VLOOKUP(C6,TRAOPE!$G:$H,2,0),"") | E6: D814 | F6: EO04 | G6: =IFERROR(VLOOKUP(A6,Flete!$A:$E,5,0),"") | H6: =IFERROR(VLOOKUP(F6,TRAOPE!$AA:$AB,2,0),"") | I6: 10000372 | J6: =IFERROR(VLOOKUP(I6,Materiales!$A:$H,8,0),"") | K6: =IFERROR(VLOOKUP(I6,Materiales!$A:$G,7,0),"") | L6: 20220504 | M6: 20230127 | N6: 165.02 | O6: =IFERROR(VLOOKUP(A6,Flete!$A:$J,10,0),"") | P6: TN | Q6: =IFERROR(IFERROR(VLOOKUP(A6,TRAOPE!$A:$U,21,0),VLOOKUP(B6,TRAOPE!$A:$U,21,0)),"") | R6: =IFERROR(IFERROR(VLOOKUP(A6,TRAOPE!$A:$W,23,0),VLOOKUP(B6,TRAOPE!$A:$W,23,0)),"") | S6: =IF(AND(P6="TN",R6="TN"),N6+N(O6),IF(G6&""="1",N(K6)*N6,(N6+N(O6))*N(K6))) | T6: =IF(Q6="","",Q6-S6)
A7: =CONCATENATE(C7,E7,F7,I7) | B7: =CONCATENATE(C7,E7,I7) | C7: 900006732 | D7: =IFERROR(VLOOKUP(C7,TRAOPE!$G:$H,2,0),"") | E7: D814 | F7: EO04 | G7: =IFERROR(VLOOKUP(A7,Flete!$A:$E,5,0),"") | H7: =IFERROR(VLOOKUP(F7,TRAOPE!$AA:$AB,2,0),"") | I7: 10123034 | J7: =IFERROR(VLOOKUP(I7,Materiales!$A:$H,8,0),"") | K7: =IFERROR(VLOOKUP(I7,Materiales!$A:$G,7,0),"") | L7: 20220504 | M7: 20230127 | N7: 124 | O7: =IFERROR(VLOOKUP(A7,Flete!$A:$J,10,0),"") | P7: TN | Q7: =IFERROR(IFERROR(VLOOKUP(A7,TRAOPE!$A:$U,21,0),VLOOKUP(B7,TRAOPE!$A:$U,21,0)),"") | R7: =IFERROR(IFERROR(VLOOKUP(A7,TRAOPE!$A:$W,23,0),VLOOKUP(B7,TRAOPE!$A:$W,23,0)),"") | S7: =IF(AND(P7="TN",R7="TN"),N7+N(O7),IF(G7&""="1",N(K7)*N7,(N7+N(O7))*N(K7))) | T7: =IF(Q7="","",Q7-S7)
A8: =CONCATENATE(C8,E8,F8,I8) | B8: =CONCATENATE(C8,E8,I8) | C8: 900006733 | D8: =IFERROR(VLOOKUP(C8,TRAOPE!$G:$H,2,0),"") | E8: D814 | F8: EO04 | G8: =IFERROR(VLOOKUP(A8,Flete!$A:$E,5,0),"") | H8: =IFERROR(VLOOKUP(F8,TRAOPE!$AA:$AB,2,0),"") | I8: 10049559 | J8: =IFERROR(VLOOKUP(I8,Materiales!$A:$H,8,0),"") | K8: =IFERROR(VLOOKUP(I8,Materiales!$A:$G,7,0),"") | L8: 20220504 | M8: 20230127 | N8: 176.48 | O8: =IFERROR(VLOOKUP(A8,Flete!$A:$J,10,0),"") | P8: TN | Q8: =IFERROR(IFERROR(VLOOKUP(A8,TRAOPE!$A:$U,21,0),VLOOKUP(B8,TRAOPE!$A:$U,21,0)),"") | R8: =IFERROR(IFERROR(VLOOKUP(A8,TRAOPE!$A:$W,23,0),VLOOKUP(B8,TRAOPE!$A:$W,23,0)),"") | S8: =IF(AND(P8="TN",R8="TN"),N8+N(O8),IF(G8&""="1",N(K8)*N8,(N8+N(O8))*N(K8))) | T8: =IF(Q8="","",Q8-S8)
A9: =CONCATENATE(C9,E9,F9,I9) | B9: =CONCATENATE(C9,E9,I9) | C9: 900006734 | D9: =IFERROR(VLOOKUP(C9,TRAOPE!$G:$H,2,0),"") | E9: D814 | F9: EO04 | G9: =IFERROR(VLOOKUP(A9,Flete!$A:$E,5,0),"") | H9: =IFERROR(VLOOKUP(F9,TRAOPE!$AA:$AB,2,0),"") | I9: 10000452 | J9: =IFERROR(VLOOKUP(I9,Materiales!$A:$H,8,0),"") | K9: =IFERROR(VLOOKUP(I9,Materiales!$A:$G,7,0),"") | L9: 20220504 | M9: 20230127 | N9: 172.33 | O9: =IFERROR(VLOOKUP(A9,Flete!$A:$J,10,0),"") | P9: TN | Q9: =IFERROR(IFERROR(VLOOKUP(A9,TRAOPE!$A:$U,21,0),VLOOKUP(B9,TRAOPE!$A:$U,21,0)),"") | R9: =IFERROR(IFERROR(VLOOKUP(A9,TRAOPE!$A:$W,23,0),VLOOKUP(B9,TRAOPE!$A:$W,23,0)),"") | S9: =IF(AND(P9="TN",R9="TN"),N9+N(O9),IF(G9&""="1",N(K9)*N9,(N9+N(O9))*N(K9))) | T9: =IF(Q9="","",Q9-S9)
A10: =CONCATENATE(C10,E10,F10,I10) | B10: =CONCATENATE(C10,E10,I10) | C10: 900006740 | D10: =IFERROR(VLOOKUP(C10,TRAOPE!$G:$H,2,0),"") | E10: D814 | F10: EO04 | G10: =IFERROR(VLOOKUP(A10,Flete!$A:$E,5,0),"") | H10: =IFERROR(VLOOKUP(F10,TRAOPE!$AA:$AB,2,0),"") | I10: 10147454 | J10: =IFERROR(VLOOKUP(I10,Materiales!$A:$H,8,0),"") | K10: =IFERROR(VLOOKUP(I10,Materiales!$A:$G,7,0),"") | L10: 20220504 | M10: 20230127 | N10: 142.06 | O10: =IFERROR(VLOOKUP(A10,Flete!$A:$J,10,0),"") | P10: TN | Q10: =IFERROR(IFERROR(VLOOKUP(A10,TRAOPE!$A:$U,21,0),VLOOKUP(B10,TRAOPE!$A:$U,21,0)),"") | R10: =IFERROR(IFERROR(VLOOKUP(A10,TRAOPE!$A:$W,23,0),VLOOKUP(B10,TRAOPE!$A:$W,23,0)),"") | S10: =IF(AND(P10="TN",R10="TN"),N10+N(O10),IF(G10&""="1",N(K10)*N10,(N10+N(O10))*N(K10))) | T10: =IF(Q10="","",Q10-S10)
A11: =CONCATENATE(C11,E11,F11,I11) | B11: =CONCATENATE(C11,E11,I11) | C11: 900006741 | D11: =IFERROR(VLOOKUP(C11,TRAOPE!$G:$H,2,0),"") | E11: D814 | F11: EO04 | G11: =IFERROR(VLOOKUP(A11,Flete!$A:$E,5,0),"") | H11: =IFERROR(VLOOKUP(F11,TRAOPE!$AA:$AB,2,0),"") | I11: 10000834 | J11: =IFERROR(VLOOKUP(I11,Materiales!$A:$H,8,0),"") | K11: =IFERROR(VLOOKUP(I11,Materiales!$A:$G,7,0),"") | L11: 20220504 | M11: 20230127 | N11: 36.38 | O11: =IFERROR(VLOOKUP(A11,Flete!$A:$J,10,0),"") | P11: TN | Q11: =IFERROR(IFERROR(VLOOKUP(A11,TRAOPE!$A:$U,21,0),VLOOKUP(B11,TRAOPE!$A:$U,21,0)),"") | R11: =IFERROR(IFERROR(VLOOKUP(A11,TRAOPE!$A:$W,23,0),VLOOKUP(B11,TRAOPE!$A:$W,23,0)),"") | S11: =IF(AND(P11="TN",R11="TN"),N11+N(O11),IF(G11&""="1",N(K11)*N11,(N11+N(O11))*N(K11))) | T11: =IF(Q11="","",Q11-S11)
A12: =CONCATENATE(C12,E12,F12,I12) | B12: =CONCATENATE(C12,E12,I12) | C12: 900006742 | D12: =IFERROR(VLOOKUP(C12,TRAOPE!$G:$H,2,0),"") | E12: D814 | F12: EO04 | G12: =IFERROR(VLOOKUP(A12,Flete!$A:$E,5,0),"") | H12: =IFERROR(VLOOKUP(F12,TRAOPE!$AA:$AB,2,0),"") | I12: 10000834 | J12: =IFERROR(VLOOKUP(I12,Materiales!$A:$H,8,0),"") | K12: =IFERROR(VLOOKUP(I12,Materiales!$A:$G,7,0),"") | L12: 20220504 | M12: 20230127 | N12: 37.21 | O12: =IFERROR(VLOOKUP(A12,Flete!$A:$J,10,0),"") | P12: TN | Q12: =IFERROR(IFERROR(VLOOKUP(A12,TRAOPE!$A:$U,21,0),VLOOKUP(B12,TRAOPE!$A:$U,21,0)),"") | R12: =IFERROR(IFERROR(VLOOKUP(A12,TRAOPE!$A:$W,23,0),VLOOKUP(B12,TRAOPE!$A:$W,23,0)),"") | S12: =IF(AND(P12="TN",R12="TN"),N12+N(O12),IF(G12&""="1",N(K12)*N12,(N12+N(O12))*N(K12))) | T12: =IF(Q12="","",Q12-S12)
A13: =CONCATENATE(C13,E13,F13,I13) | B13: =CONCATENATE(C13,E13,I13) | C13: 900006743 | D13: =IFERROR(VLOOKUP(C13,TRAOPE!$G:$H,2,0),"") | E13: D814 | F13: EO04 | G13: =IFERROR(VLOOKUP(A13,Flete!$A:$E,5,0),"") | H13: =IFERROR(VLOOKUP(F13,TRAOPE!$AA:$AB,2,0),"") | I13: 10000834 | J13: =IFERROR(VLOOKUP(I13,Materiales!$A:$H,8,0),"") | K13: =IFERROR(VLOOKUP(I13,Materiales!$A:$G,7,0),"") | L13: 20220504 | M13: 20230127 | N13: 38.04 | O13: =IFERROR(VLOOKUP(A13,Flete!$A:$J,10,0),"") | P13: TN | Q13: =IFERROR(IFERROR(VLOOKUP(A13,TRAOPE!$A:$U,21,0),VLOOKUP(B13,TRAOPE!$A:$U,21,0)),"") | R13: =IFERROR(IFERROR(VLOOKUP(A13,TRAOPE!$A:$W,23,0),VLOOKUP(B13,TRAOPE!$A:$W,23,0)),"") | S13: =IF(AND(P13="TN",R13="TN"),N13+N(O13),IF(G13&""="1",N(K13)*N13,(N13+N(O13))*N(K13))) | T13: =IF(Q13="","",Q13-S13)
A14: =CONCATENATE(C14,E14,F14,I14) | B14: =CONCATENATE(C14,E14,I14) | C14: 900006744 | D14: =IFERROR(VLOOKUP(C14,TRAOPE!$G:$H,2,0),"") | E14: D814 | F14: EO04 | G14: =IFERROR(VLOOKUP(A14,Flete!$A:$E,5,0),"") | H14: =IFERROR(VLOOKUP(F14,TRAOPE!$AA:$AB,2,0),"") | I14: 10000834 | J14: =IFERROR(VLOOKUP(I14,Materiales!$A:$H,8,0),"") | K14: =IFERROR(VLOOKUP(I14,Materiales!$A:$G,7,0),"") | L14: 20220504 | M14: 20230127 | N14: 38.04 | O14: =IFERROR(VLOOKUP(A14,Flete!$A:$J,10,0),"") | P14: TN | Q14: =IFERROR(IFERROR(VLOOKUP(A14,TRAOPE!$A:$U,21,0),VLOOKUP(B14,TRAOPE!$A:$U,21,0)),"") | R14: =IFERROR(IFERROR(VLOOKUP(A14,TRAOPE!$A:$W,23,0),VLOOKUP(B14,TRAOPE!$A:$W,23,0)),"") | S14: =IF(AND(P14="TN",R14="TN"),N14+N(O14),IF(G14&""="1",N(K14)*N14,(N14+N(O14))*N(K14))) | T14: =IF(Q14="","",Q14-S14)
... A619: =CONCATENATE(C619,E619,F619,I619) | B619: =CONCATENATE(C619,E619,I619) | C619: 900009035 | D619: =IFERROR(VLOOKUP(C619,TRAOPE!$G:$H,2,0),"") | E619: D814 | F619: 67313510 | G619: =IFERROR(VLOOKUP(A619,Flete!$A:$E,5,0),"") | H619: =IFERROR(VLOOKUP(F619,TRAOPE!$AA:$AB,2,0),"") | I619: 10173699 | J619: =IFERROR(VLOOKUP(I619,Materiales!$A:$H,8,0),"") | K619: =IFERROR(VLOOKUP(I619,Materiales!$A:$G,7,0),"") | L619: 20250505 | M619: 20250507 | N619: 93 | O619: =IFERROR(VLOOKUP(A619,Flete!$A:$J,10,0),"") | P619: M3 | Q619: =IFERROR(IFERROR(VLOOKUP(A619,TRAOPE!$A:$U,21,0),VLOOKUP(B619,TRAOPE!$A:$U,21,0)),"") | R619: =IFERROR(IFERROR(VLOOKUP(A619,TRAOPE!$A:$W,23,0),VLOOKUP(B619,TRAOPE!$A:$W,23,0)),"") | S619: =IF(AND(P619="TN",R619="TN"),N619+N(O619),IF(G619&""="1",N(K619)*N619,(N619+N(O619))*N(K619))) | T619: =IF(Q619="","",Q619-S619)

Sheet MP
A1: No. SF | B1: Cedis | C1: Destino | D1: No. Material | E1: Nombre Material | F1: Importe MP | G1: Moneda | H1: Cantidad | I1: UM | J1: C | K1: Inicio Vigencia | L1: Fin Vigencia
A2: 900005920 | B2: D814 | C2: ER67 | D2: 10003240 | F2: 179.68 | I2: TN | K2: 20220504 | L2: 20230127
A3: 900006731 | B3: D814 | C3: EO04 | D3: 10000561 | F3: 161.94 | I3: TN | K3: 20220504 | L3: 20230127
A4: 900006731 | B4: D814 | C4: EO04 | D4: 10123034 | F4: 55.11 | I4: TN | K4: 20220504 | L4: 20230127
A5: 900006732 | B5: D814 | C5: EO04 | D5: 10000372 | F5: 165.02 | I5: TN | K5: 20220504 | L5: 20230127
A6: 900006732 | B6: D814 | C6: EO04 | D6: 10123034 | F6: 124 | I6: TN | K6: 20220504 | L6: 20230127
A7: 900006733 | B7: D814 | C7: EO04 | D7: 10049559 | F7: 176.48 | I7: TN | K7: 20220504 | L7: 20230127
A8: 900006734 | B8: D814 | C8: EO04 | D8: 10000452 | F8: 172.33 | I8: TN | K8: 20220504 | L8: 20230127
A9: 900006740 | B9: D814 | C9: EO04 | D9: 10147454 | F9: 142.06 | I9: TN | K9: 20220504 | L9: 20230127
A10: 900006741 | B10: D814 | C10: EO04 | D10: 10000834 | F10: 36.38 | I10: TN | K10: 20220504 | L10: 20230127
A11: 900006742 | B11: D814 | C11: EO04 | D11: 10000834 | F11: 37.21 | I11: TN | K11: 20220504 | L11: 20230127
A12: 900006743 | B12: D814 | C12: EO04 | D12: 10000834 | F12: 38.04 | I12: TN | K12: 20220504 | L12: 20230127
A13: 900006744 | B13: D814 | C13: EO04 | D13: 10000834 | F13: 38.04 | I13: TN | K13: 20220504 | L13: 20230127
... A618: 900009035 | B618: D814 | C618: 67313510 | D618: 10173699 | F618: 93 | I618: M3 | K618: 20250505 | L618: 20250507

Sheet Flete
A1: Concat1 | B1: No. SF | C1: Cedis | D1: Destino | E1: Cond. Exp. | F1: Material | H1: Nombre Material | J1: Importe Flete | K1: Moneda | L1: Cantidad | M1: UM | N1: C | P1: Inicio Vigencia | Q1: Fin Vigencia
A2: 900000129D8146511942310000834 | B2: 900000129 | C2: D814 | D2: 65119423 | E2: 1 | F2: 10000834 | J2: 50 | M2: M3 | P2: 20170210 | Q2: 99991231
A3: 900000129D8146574530510000834 | B3: 900000129 | C3: D814 | D3: 65745305 | E3: 1 | F3: 10000834 | J3: 4.08 | M3: M3 | P3: 20170210 | Q3: 99991231
A4: 900001325D8146574530510000223 | B4: 900001325 | C4: D814 | D4: 65745305 | E4: 1 | F4: 10000223 | J4: 11.92 | M4: M3 | P4: 20170210 | Q4: 99991231
A5: 900002302D8146511942310000834 | B5: 900002302 | C5: D814 | D5: 65119423 | E5: 1 | F5: 10000834 | J5: 57 | M5: M3 | P5: 20170210 | Q5: 99991231
A6: 900002862D8146574530510000452 | B6: 900002862 | C6: D814 | D6: 65745305 | E6: 1 | F6: 10000452 | J6: 11.52 | M6: M3 | P6: 20140801 | Q6: 99991231
A7: 900003621D8146574530510000223 | B7: 900003621 | C7: D814 | D7: 65745305 | E7: 1 | F7: 10000223 | J7: 150 | M7: M3 | P7: 20170210 | Q7: 99991231
A8: 900003624D8146574530510000452 | B8: 900003624 | C8: D814 | D8: 65745305 | E8: 1 | F8: 10000452 | J8: 145 | M8: M3 | P8: 20141106 | Q8: 99991231
A9: 900003631D8146574530510000834 | B9: 900003631 | C9: D814 | D9: 65745305 | E9: 1 | F9: 10000834 | J9: 51 | M9: M3 | P9: 20170210 | Q9: 99991231
A10: 900003735D8146636065010000541 | B10: 900003735 | C10: D814 | D10: 66360650 | E10: 4 | F10: 10000541 | J10: 315.4 | M10: M3 | P10: 20170210 | Q10: 20240320
A11: 900003735D8146657340610000541 | B11: 900003735 | C11: D814 | D11: 66573406 | E11: 4 | F11: 10000541 | J11: 653.05 | M11: M3 | P11: 20170210 | Q11: 20240320
A12: 900003735D8146664759010000541 | B12: 900003735 | C12: D814 | D12: 66647590 | E12: 4 | F12: 10000541 | J12: 232 | M12: M3 | P12: 20170210 | Q12: 20240320
A13: 900003735D8146677929210000541 | B13: 900003735 | C13: D814 | D13: 66779292 | E13: 4 | F13: 10000541 | J13: 200.4 | M13: M3 | P13: 20170210 | Q13: 20240320
... A433: 900009035D8146731351010173699 | B433: 900009035 | C433: D814 | D433: 67313510 | E433: 4 | F433: 10173699 | J433: 137 | M433: M3 | P433: 20250304 | Q433: 20250507

Sheet Materiales
A1: Material | B1: TpMt | C1: Denom | D1: UMA | E1: Contador | F1: UMB | G1: PV | H1: Nombre Material
A2: 10000001 | B2: ZFER | C2: 1000 | D2: M3 | E2: 1000 | F2: TN | G2: 1262 | H2: GRAVA ANDESITA 10 MM (3/8")
A3: 10000003 | B3: ZFER | C3: 1000 | D3: M3 | E3: 1000 | F3: TN | G3: 1443 | H3: GRAVA CALIZA 10 MM (3/8")
A4: 10000006 | B4: ZFER | C4: 1000 | D4: M3 | E4: 1000 | F4: TN | G4: 1490 | H4: GRAVA RIO 10 MM (3/8")
A5: 10000007 | B5: ZFER | C5: 1000 | D5: M3 | E5: 1000 | F5: TN | G5: 1488 | H5: GRAVA BASALTO 13 MM (1/2")
A6: 10000008 | B6: ZFER | C6: 1000 | D6: M3 | E6: 1000 | F6: TN | G6: 1358 | H6: GRAVA CALIZA 13 MM (1/2")
A7: 10000011 | B7: ZFER | C7: 1000 | D7: M3 | E7: 1000 | F7: TN | G7: 1323 | H7: GRAVA ANDESITA 20 MM (3/4")
A8: 10000013 | B8: ZFER | C8: 1000 | D8: M3 | E8: 1000 | F8: TN | G8: 1514 | H8: GRAVA BASALTO 20 MM (3/4")
A9: 10000014 | B9: ZFER | C9: 1000 | D9: M3 | E9: 1000 | F9: TN | G9: 1400 | H9: GRAVA CALIZA 20 MM (3/4")
A10: 10000015 | B10: ZFER | C10: 1000 | D10: M3 | E10: 1000 | F10: TN | G10: 1410 | H10: GRAVA GRANITO 20 MM (3/4")
A11: 10000017 | B11: ZFER | C11: 1000 | D11: M3 | E11: 1000 | F11: TN | G11: 1475 | H11: GRAVA RIOLITA 20 MM (3/4")
A12: 10000019 | B12: ZFER | C12: 1000 | D12: M3 | E12: 1000 | F12: TN | G12: 1515 | H12: GRAVA RIO 20 MM (3/4")
A13: 10000020 | B13: ZFER | C13: 1000 | D13: M3 | E13: 1 | F13: TN | G13: 1 | H13: GRAVA MAQUILA 40MM (1 1/2")
... A2291: 10268770 | B2291: ZFE3 | C2291: 1000 | D2291: M3 | E2291: 1000 | F2291: TN | G2291: 1240 | H2291: MP GRAVA TRIT CALIZA 40MM 1 1/2" - ESP
A2292: 10268901 | B2292: ZFE3 | C2292: 1000 | D2292: M3 | E2292: 1000 | G2292: 1560 | H2292: MP GRAVA ANDESITA GRIS 3/4" - CAPADA
A2293: 10267983 | C2293: 1000 | G2293: 1800 | H2293: ESCORIA ALTO HORNO 3/4
A2294: 10268996 | C2294: 1000 | G2294: 1329 | H2294: GRAVA TRITURADA CALIZA 40 MM - 11/2"
A2295: 10269072 | C2295: 1000 | G2295: 1700 | H2295: BASE HIDRÁULICA SCREEN
A2296: 10269225 | B2296: ZFE3 | C2296: 1000 | D2296: M3 | E2296: 1000 | G2296: 1289 | H2296: MP ARENA CALIZA LAVADA MALLA 4 - DELTA I
A2297: 10269245 | B2297: ZFE3 | C2297: 1000 | D2297: M3 | E2297: 1000 | G2297: 1410 | H2297: MP GRAVA TRITURADA CALIZA 3/8 - 10MM
A2298: 10269246 | B2298: ZFE3 | C2298: 1000 | D2298: M3 | E2298: 1000 | G2298: 1400 | H2298: MP GRAVA TRITURADA CALIZA 1 1/2 - 40MM
A2299: 10269247 | B2299: ZFE3 | C2299: 1000 | D2299: M3 | E2299: 1000 | G2299: 1560 | H2299: MP ARENA TRIT CALIZA M-4
A2300: 10270431 | B2300: ZFE3 | C2300: 1000 | D2300: M3 | E2300: 1000 | G2300: 1423 | H2300: MP GRAVA RIOLITA 13 MM - 1/2"
A2301: 10270898 | B2301: ZFE3 | C2301: 1000 | D2301: M3 | E2301: 1000 | G2301: 1551 | H2301: MP BASE H. TRIT. BASALTO 1 1/2" A FINOS
A2302: 10270911 | B2302: ZFE3 | C2302: 1000 | D2302: M3 | E2302: 1000 | G2302: 1360 | H2302: MP GRAVA TRIT. BASALTO 40 MM - 1 1/2"
A2303: 10270912 | B2303: ZFE3 | C2303: 1000 | D2303: M3 | E2303: 1000 | G2303: 1589 | H2303: MP ARENA TRIT. BASALTO MALLA 4
A2304: 10270913 | B2304: ZFE3 | C2304: 1000 | D2304: M3 | E2304: 1000 | G2304: 1395 | H2304: MP GRAVA TRIT. BASALTO 20 MM - 3/4
A2305: 10270914 | B2305: ZFE3 | C2305: 1000 | D2305: M3 | E2305: 1000 | G2305: 1623 | H2305: MP ARENA ANDESITA BC
A2306: 10270824 | B2306: M3 | C2306: 1000 | D2306: M3 | E2306: 10007640 | G2306: 1325 | H2306: MP ARENA TRITURADA CALIZA MALLA 5
A2307: 10270825 | B2307: M3 | C2307: 1000 | D2307: M3 | E2307: 10000003 | G2307: 1242 | H2307: MP GRAVA TRITURADA CALIZA 10MM (3/8”)
... A2319: 10272527 | B2319: ZFE3 | C2319: 1000 | D2319: M3 | E2319: 1000 | G2319: 1620 | H2319: CNC - NO CLASIFICADO
A2320: 10000332 | C2320: 1000 | D2320: M3 | E2320: 1000 | G2320: 800 | H2320: Grava Triturada Pomez - Jal 20 mm - 3/4"
A2321: 10273001 | B2321: ZFE3 | C2321: 1000 | D2321: M3 | E2321: 1000 | G2321: 1688 | H2321: MP ARENA TRIT. BASALTO MALLA 4
A2322: 10273002 | B2322: ZFE3 | C2322: 1000 | D2322: M3 | E2322: 1000 | G2322: 1466 | H2322: MP GRAVA TRIT. BASALTO 20 MM - 3/4"
A2323: 10273351 | B2323: ZFE3 | C2323: 1000 | D2323: M3 | E2323: 1000 | G2323: 1612 | H2323: MP ARENA TRIT. CALIZA MALLA 4
A2324: 10273352 | B2324: ZFE3 | C2324: 1000 | D2324: M3 | E2324: 1000 | G2324: 1492 | H2324: MP GRAVA TRIT. CALIZA 20 MM - 3/4"
A2325: 10271724 | B2325: ZFE3 | C2325: 1000 | D2325: M3 | E2325: 1000 | G2325: 1900 | H2325: MP RESIDUO DE CONCRETO
A2326: 10000677 | C2326: 1000 | D2326: M3 | G2326: 1164 | H2326: Grava Triturada Caliza 20 mm - 3/4"
A2327: 10274190 | B2327: ZFE3 | C2327: 1000 | D2327: M3 | E2327: 1000 | G2327: 1800 | H2327: MP BASE HIDRAULICA ANDESITA 70-30
A2328: 10274601 | B2328: ZFE3 | C2328: 1000 | D2328: M3 | E2328: 1000 | G2328: 1447 | H2328: MP ARENA BASALTO N° 4
A2329: 10274754 | B2329: ZFE3 | C2329: 1000 | D2329: M3 | E2329: 1000 | G2329: 1397 | H2329: MP GRAVA TRIT. ANDESITA 20 MM - 3/4"
A2330: 10169718 | B2330: ZFE3 | C2330: 1000 | D2330: M3 | E2330: 1000 | G2330: 1400 | H2330: GRAVA CLASIFICADA RÍO 40 MM - 1 1/2"
A2331: 10274813 | B2331: ZFE3 | C2331: 1000 | D2331: M3 | E2331: 1000 | G2331: 1448 | H2331: MP ARENA TRIT RÍO MALLA 4
A2332: 10274815 | B2332: ZFE3 | C2332: 1000 | D2332: M3 | E2332: 1000 | G2332: 1366 | H2332: MP ARENA CLASIFICADA RÍO MALLA 5
A2333: 10274816 | B2333: ZFE3 | C2333: 1000 | D2333: M3 | E2333: 1000 | G2333: 1472 | H2333: MP GRAVA CLASIF RÍO 20 MM - 3/4"
A2334: 10275113 | B2334: ZFE3 | C2334: 1000 | D2334: M3 | E2334: 1000 | G2334: 1409 | H2334: MP ARENA TRIT ANDESITA MALLA 4
A2335: 10275114 | B2335: ZFE3 | C2335: 1000 | D2335: M3 | E2335: 1000 | G2335: 1418 | H2335: MP ARENA CLASIF RIO MALLA 4 - LAVADO
A2336: 10275115 | B2336: ZFE3 | C2336: 1000 | D2336: M3 | E2336: 1000 | G2336: 1259 | H2336: MP ARENA TRIT ANDESITA MALLA 4
A2337: 10275116 | B2337: ZFE3 | C2337: 1000 | D2337: M3 | E2337: 1000 | G2337: 1401 | H2337: MP GRAVA TRIT ANDESITA 3/4 - 20 MM
A2338: 10275118 | B2338: ZFE3 | C2338: 1000 | D2338: M3 | E2338: 1000 | G2338: 1401 | H2338: MP ARENA TRIT ANDESITA MALLA 4
... A2361: 10280049 | B2361: ZFE3 | C2361: 1000 | D2361: M3 | E2361: 1000 | G2361: 1584 | H2361: MP B. HID CALIZA 40% FINOS Y 60% GRUESOS
A2362: 10280365 | C2362: 1000 | D2362: M3 | E2362: 1000 | G2362: 1274 | H2362: MP GRAVA BASALTO 20 MM -3/4
A2363: 10280538 | B2363: ZFE3 | C2363: 1000 | D2363: M3 | E2363: 1000 | G2363: 1262 | H2363: MP GRAVA TRIT BASALTO 3/8 - 10MM
A2364: 10280679 | B2364: ZFE3 | C2364: 1000 | D2364: M3 | E2364: 1000 | G2364: 1349 | H2364: MP GRAVA CLASIF RÍO 13MM - 1/2"
A2365: 10281171 | B2365: ZFE3 | C2365: 1000 | D2365: M3 | E2365: 1000 | G2365: 1271 | H2365: MP GRAVA TRIT CALIZA 10MM - 3/8"
A2366: 10281183 | B2366: ZFE3 | C2366: 1000 | D2366: M3 | E2366: 1000 | G2366: 1468 | H2366: MP ARENA TRIT CALIZA MALLA 4
A2367: 10281384 | B2367: ZFE3 | C2367: 1000 | D2367: M3 | E2367: 1000 | G2367: 1285 | H2367: MP GRAVA BASALTO 40 MM (1 1/2")
A2368: 10281379 | B2368: ZFE3 | C2368: 1000 | D2368: M3 | E2368: 1000 | G2368: 1536 | H2368: MP ARENA CLASIF. RÍO MALLA 4
A2369: 10281450 | B2369: ZFE3 | C2369: 1000 | D2369: M3 | E2369: 1000 | G2369: 1325 | H2369: MP GRAVA CLASIF. RIO 20MM - 3/4
A2370: 10281451 | B2370: ZFE3 | C2370: 1000 | D2370: M3 | E2370: 1000 | G2370: 1564 | H2370: MP ARENA CLASIF. RÍO MALLA 4
A2371: 10281452 | B2371: ZFE3 | C2371: 1000 | D2371: M3 | E2371: 1000 | G2371: 1427 | H2371: MP GRAVA CLASIF. RIO 20MM - 3/4

Sheet TRAOPE
A1: Concat1 | B1: Contrato_Pos | C1: Doc. Compras | D1: Pos | E1: Org.compras | F1: Grp-Compr. | G1: Ship From | H1: Nombre SF | I1: Proveedor | J1: Nombre Prov | K1: Cond. Pago | L1: Descr. Cond Pago | M1: Material | N1: Descripción | O1: Centro | P1: Descripción Centro | Q1: In.perído validez | R1: Fin perído validez | S1: Válido de | T1: Validez a | U1: Precio neto pedido | V1: Moneda | W1: UM Precio Pedido | X1: Importe Condición | Y1: Moneda KONP | Z1: UM Ctd Base | AA1: Destino | AB1: Nombre Destino | AC1: Cuenta de mayor | AD1: Centro de costo | AE1: Cond. Exp. | AF1: Descr. Cond. Exp. | AG1: Peso Vol. | AH1: UMB | AI1: Ind. Oblig. Conf. Ped. | AJ1: Ctrl-Conf. | AK1: IVA | AL1: Modif_Date | AM1: Ruta
A2: 900009035D8146731351010173699 | B2: 4600070543-90 | C2: 4600070543 | D2: 90 | E2: MXPO | F2: MXL | G2: 900009035 | H2: SF TP-ED- GRUPO AF | I2: 5094278 | J2: LOGISTICA Y SERVICIOS ESPECIALIZADO | K2: Z09 | L2: (AP) 90 Dias | M2: 10173699 | N2: ARENA CLASIFICADA RIO MALLA 4 LAVADA | O2: D814 | P2: MX-CED. TABASCO | Q2: 20241115 | R2: 20291231 | S2: 20250407 | T2: 20301231 | U2: 212 | V2: MXN | W2: M3 | X2: 137 | Y2: MXN | Z2: M3 | AA2: 67313510 | AB2: OBRA NEXUMRAIL | AC2: 56103638 | AD2: 6622041540 | AE2: 4 | AF2: ENTREGA DIRECTA | AG2: 1.576 | AH2: M3 | AI2: X | AJ2: 4 | AK2: V4 | AL2: 20250410 | AM2: D814-900009035-67313510-10173699-4
A3: 900009035D8146731351010147454 | B3: 4600070543-80 | C3: 4600070543 | D3: 80 | E3: MXPO | F3: MXL | G3: 900009035 | H3: SF TP-ED- GRUPO AF | I3: 5094278 | J3: LOGISTICA Y SERVICIOS ESPECIALIZADO | K3: Z09 | L3: (AP) 90 Dias | M3: 10147454 | N3: GRAVA TRITURADA CALIZA 20 MM - 3/4" | O3: D814 | P3: MX-CED. TABASCO | Q3: 20241115 | R3: 20291231 | S3: 20250407 | T3: 20301231 | U3: 643 | V3: MXN | W3: M3 | X3: 348 | Y3: MXN | Z3: M3 | AA3: 67313510 | AB3: OBRA NEXUMRAIL | AC3: 56103637 | AD3: 6622041540 | AE3: 4 | AF3: ENTREGA DIRECTA | AG3: 1.556 | AH3: M3 | AI3: X | AJ3: 4 | AK3: V4 | AL3: 20250410 | AM3: D814-900009035-67313510-10147454-4
A4: 900006706D8146678288110193885 | B4: 4600047553-120 | C4: 4600047553 | D4: 120 | E4: MXPO | F4: MXL | G4: 900006706 | H4: SF TP-ED-FRISO TEAPA | I4: 5070657 | J4: FRISO SILRO SA DE CV | K4: N90 | L4: (AP) NAFIN 90 Dias | M4: 10193885 | N4: BASE H CALIZA GRIS 1 1/2 PARA PATIO NG | O4: D814 | P4: MX-CED. TABASCO | Q4: 20200717 | R4: 20281231 | S4: 20210504 | T4: 20261231 | U4: 450 | V4: MXN | W4: M3 | X4: 350 | Y4: MXN | Z4: M3 | AA4: 66782881 | AB4: PLANTA HOKCHI | AC4: 56103590 | AD4: 6622041540 | AE4: 4 | AF4: ENTREGA DIRECTA | AG4: 1.52 | AH4: M3 | AI4: X | AJ4: 4 | AK4: V4 | AL4: 20230920 | AM4: D814-900006706-66782881-10193885-4
A5: 900007054D8146694653610197737 | B5: 4600049598-150 | C5: 4600049598 | D5: 150 | E5: MXPO | F5: MXL | G5: 900007054 | H5: SF TP-ED-SAMUEL CARRASCO | I5: 5080454 | J5: CARRASCO ALCUDIA SAMUEL | K5: N90 | L5: (AP) NAFIN 90 Dias | M5: 10197737 | N5: ARENA CLASIFICADA RÍO MALLA 4- NG | O5: D814 | P5: MX-CED. TABASCO | Q5: 20210407 | R5: 20291231 | S5: 20230619 | T5: 20281231 | U5: 470 | V5: MXN | W5: M3 | X5: 350 | Y5: MXN | Z5: M3 | AA5: 66946536 | AB5: P6 - Pulmón - Refinería Dos Bocas | AC5: 56103638 | AD5: 6622041867 | AE5: 4 | AF5: ENTREGA DIRECTA | AG5: 1.55 | AH5: M3 | AI5: X | AJ5: 4 | AK5: V4 | AL5: 20230920 | AM5: D814-900007054-66946536-10197737-4
A6: 900006706D8146700595910147454 | B6: 4600047553-210 | C6: 4600047553 | D6: 210 | E6: MXPO | F6: MXL | G6: 900006706 | H6: SF TP-ED-FRISO TEAPA | I6: 5070657 | J6: FRISO SILRO SA DE CV | K6: N90 | L6: (AP) NAFIN 90 Dias | M6: 10147454 | N6: GRAVA TRITURADA CALIZA 20 MM - 3/4" | O6: D814 | P6: MX-CED. TABASCO | Q6: 20200717 | R6: 20281231 | S6: 20210918 | T6: 20261231 | U6: 400 | V6: MXN | W6: M3 | X6: 190 | Y6: MXN | Z6: M3 | AA6: 67005959 | AB6: INATERRA NUEVO CEDIS WALMART (LVC) | AC6: 56103637 | AD6: 6622041540 | AE6: 4 | AF6: ENTREGA DIRECTA | AG6: 1.556 | AH6: M3 | AI6: X | AJ6: 4 | AK6: V4 | AL6: 20230920 | AM6: D814-900006706-67005959-10147454-4
A7: 900005557D8146655463110116007 | B7: 4600041437-30 | C7: 4600041437 | D7: 30 | E7: MXPO | F7: MXL | G7: 900005557 | H7: TP-ED-DANIEL BECERRA | I7: 5070594 | J7: BECERRA MAYORGA DANIEL | K7: N90 | L7: (AP) NAFIN 90 Dias | M7: 10116007 | N7: PIEDRA BOLA 4" A 6" | O7: D814 | P7: MX-CED. TABASCO | Q7: 20180307 | R7: 20241231 | S7: 20180717 | T7: 20241231 | U7: 700 | V7: MXN | W7: M3 | X7: 350 | Y7: MXN | Z7: M3 | AA7: 66554631 | AC7: 56103591 | AD7: 6622041540 | AE7: 4 | AF7: ENTREGA DIRECTA | AG7: 1.6 | AH7: M3 | AI7: X | AJ7: 4 | AK7: V4 | AL7: 20230920 | AM7: D814-900005557-66554631-10116007-4
A8: 900009035D8146731342610000273 | B8: 4600070543-70 | C8: 4600070543 | D8: 70 | E8: MXPO | F8: MXL | G8: 900009035 | H8: SF TP-ED- GRUPO AF | I8: 5094278 | J8: LOGISTICA Y SERVICIOS ESPECIALIZADO | K8: Z09 | L8: (AP) 90 Dias | M8: 10000273 | N8: Base H Triturada Caliza 3/4" a Finos | O8: D814 | P8: MX-CED. TABASCO | Q8: 20241115 | R8: 20291231 | S8: 20250407 | T8: 20301231 | U8: 660 | V8: MXN | W8: M3 | X8: 360 | Y8: MXN | Z8: M3 | AA8: 67313426 | AB8: OBRA SILVERIO SOSA | AC8: 56103590 | AD8: 6622041540 | AE8: 4 | AF8: ENTREGA DIRECTA | AG8: 1.69 | AH8: M3 | AI8: X | AJ8: 4 | AK8: V4 | AL8: 20250410 | AM8: D814-900009035-67313426-10000273-4
A9: 900004418D81410183939 | B9: 4600038499-110 | C9: 4600038499 | D9: 110 | E9: MXPO | F9: MXL | G9: 900004418 | H9: TP-SIGSA | I9: 5021622 | J9: SERVICIOS DE INGENIERIA DEL GOLFO | K9: N60 | L9: (AP) NAFIN 60 Dias | M9: 10183939 | N9: BASE HIDRÁULICA 1 1/2" A FINOS 70/30 | O9: D814 | P9: MX-CED. TABASCO | Q9: 20170623 | R9: 20281231 | S9: 20231214 | T9: 20281231 | U9: 195 | V9: MXN | W9: M3 | X9: 0 | Y9: MXN | Z9: M3 | AC9: 56103590 | AD9: 6622041540 | AE9: 1 | AF9: ENTREGADO | AG9: 2.136 | AH9: M3 | AI9: X | AJ9: 4 | AK9: V4 | AL9: 20240331 | AM9: D814-900004418-10183939
A10: 900000743D81410166283 | B10: 4600029541-40 | C10: 4600029541 | D10: 40 | E10: MXPO | F10: MXL | G10: 900000743 | H10: TC SIGSA | I10: 5021622 | J10: SERVICIOS DE INGENIERIA DEL GOLFO | K10: N60 | L10: (AP) NAFIN 60 Dias | M10: 10166283 | N10: GRAVA TRITURADA CALIZA 20 MM - 3/4" | O10: D814 | P10: MX-CED. TABASCO | Q10: 20150205 | R10: 20241231 | S10: 20210408 | T10: 20261231 | U10: 234 | V10: MXN | W10: M3 | AC10: 56103637 | AD10: 6622041540 | AE10: 1 | AF10: ENTREGADO | AG10: 1.361 | AH10: M3 | AI10: X | AJ10: 4 | AK10: V4 | AL10: 20230920 | AM10: D814-900000743-10166283
A11: 900006703D81410000373 | B11: 4600048191-40 | C11: 4600048191 | D11: 40 | E11: MXPO | F11: MXL | G11: 900006703 | H11: SF TC- FRISO TEAPA | I11: 5070657 | J11: FRISO SILRO SA DE CV | K11: N90 | L11: (AP) NAFIN 90 Dias | M11: 10000373 | N11: Grava Triturada Caliza 13 mm - 1/2" | O11: D814 | P11: MX-CED. TABASCO | Q11: 20201006 | R11: 20291231 | S11: 20210526 | T11: 20261231 | U11: 480 | V11: MXN | W11: M3 | AC11: 56103637 | AD11: 6622041540 | AE11: 1 | AF11: ENTREGADO | AG11: 1.395 | AH11: M3 | AI11: X | AJ11: 4 | AK11: V4 | AL11: 20230920 | AM11: D814-900006703-10000373
A12: 900009316D81410147454 | B12: 4600071857-10 | C12: 4600071857 | D12: 10 | E12: MXPO | F12: MXL | G12: 900009316 | H12: SF TP FRISO STONE | I12: 5096328 | J12: FRISO STONE SCP DE B Y S RL DE CV | K12: N90 | L12: (AP) NAFIN 90 Dias | M12: 10147454 | N12: GRAVA TRITURADA CALIZA 20 MM - 3/4" | O12: D814 | P12: MX-CED. TABASCO | Q12: 20251211 | R12: 20301231 | S12: 20251211 | T12: 20301231 | U12: 287 | V12: MXN | W12: M3 | X12: 0 | Y12: MXN | Z12: M3 | AC12: 56103637 | AD12: 6622041540 | AE12: 1 | AF12: ENTREGADO | AG12: 1.556 | AH12: M3 | AI12: X | AJ12: 4 | AK12: V4 | AL12: 20251219 | AM12: D814-900009316-10147454
A13: 900006409D8146658035110147454 | B13: 4600071076-10 | C13: 4600071076 | D13: 10 | E13: MXPO | F13: MXL | G13: 900006409 | H13: SF TP-ED-GOLPAC | I13: 5041845 | J13: CONSTRUCCIONES Y URBANIZACIONES | K13: Z03 | L13: (AP) 15 Dias | M13: 10147454 | N13: GRAVA TRITURADA CALIZA 20 MM - 3/4" | O13: D814 | P13: MX-CED. TABASCO | Q13: 20250325 | R13: 20301231 | S13: 20250325 | T13: 20301231 | U13: 450 | V13: MXN | W13: M3 | X13: 155 | Y13: MXN | Z13: M3 | AA13: 66580351 | AB13: COLVI VILLAHERMOSA | AC13: 56103637 | AD13: 6622041540 | AE13: 4 | AF13: ENTREGA DIRECTA | AG13: 1.556 | AH13: M3 | AI13: X | AJ13: 4 | AK13: V4 | AL13: 20250328 | AM13: D814-900006409-66580351-10147454-4
A14: 900004418D81410059808 | B14: 4600038499-20 | C14: 4600038499 | D14: 20 | E14: MXPO | F14: MXL | G14: 900004418 | H14: TP-SIGSA | I14: 5021622 | J14: SERVICIOS DE INGENIERIA DEL GOLFO | K14: N60 | L14: (AP) NAFIN 60 Dias | M14: 10059808 | N14: SUB-BASE DE 1 ½” A FINOS | O14: D814 | P14: MX-CED. TABASCO | Q14: 20170623 | R14: 20281231 | S14: 20180314 | T14: 20241231 | U14: 107 | V14: MXN | W14: M3 | X14: 0 | Y14: MXN | Z14: M3 | AC14: 56103590 | AD14: 6622041540 | AE14: 1 | AF14: ENTREGADO | AG14: 1.65 | AH14: M3 | AI14: X | AJ14: 4 | AK14: V4 | AL14: 20230920 | AM14: D814-900004418-10059808
A15: 900003902D81410000834 | B15: 4600040799-10 | C15: 4600040799 | D15: 10 | E15: MXPO | F15: MXL | G15: 900003902 | H15: TP ESCUDERO AGUILAR | I15: 5014480 | J15: ESCUDERO AGUILAR ANDRES | K15: N90 | L15: (AP) NAFIN 90 Dias | M15: 10000834 | N15: Arena Clasificada Río Malla 4 | O15: D814 | P15: MX-CED. TABASCO | Q15: 20171228 | R15: 20281231 | S15: 20220404 | T15: 20271231 | U15: 53 | V15: MXN | W15: M3 | X15: 0 | Y15: MXN | Z15: M3 | AC15: 56103638 | AD15: 6622041540 | AE15: 1 | AF15: ENTREGADO | AG15: 1.273 | AH15: M3 | AI15: X | AJ15: 4 | AK15: V4 | AL15: 20230920 | AM15: D814-900003902-10000834
A16: 900003902D81410079650 | B16: 4600040799-20 | C16: 4600040799 | D16: 20 | E16: MXPO | F16: MXL | G16: 900003902 | H16: TP ESCUDERO AGUILAR | I16: 5014480 | J16: ESCUDERO AGUILAR ANDRES | K16: N90 | L16: (AP) NAFIN 90 Dias | M16: 10079650 | N16: ARENA DE RIO MALLA 4 | O16: D814 | P16: MX-CED. TABASCO | Q16: 20171228 | R16: 20281231 | S16: 20230515 | T16: 20281231 | U16: 66 | V16: MXN | W16: M3 | X16: 0 | Y16: MXN | Z16: M3 | AC16: 56103638 | AD16: 6622041540 | AE16: 1 | AF16: ENTREGADO | AG16: 1.448 | AH16: M3 | AI16: X | AJ16: 4 | AK16: V4 | AL16: 20230920 | AM16: D814-900003902-10079650
A17: 900005888D81410000561 | B17: 4600043667-20 | C17: 4600043667 | D17: 20 | E17: MXPO | F17: MXL | G17: 900005888 | H17: SF TP-FERMIN SABIAUR | I17: 5073829 | J17: SABIAUR PEREZ FERMIN | K17: N90 | L17: (AP) NAFIN 90 Dias | M17: 10000561 | N17: Grava Triturada Caliza 20 mm - 3/4" | O17: D814 | P17: MX-CED. TABASCO | Q17: 20181217 | R17: 20281231 | S17: 20190919 | T17: 20241231 | U17: 175 | V17: MXN | W17: M3 | X17: 0 | Y17: MXN | Z17: M3 | AC17: 56103637 | AD17: 6622041540 | AE17: 1 | AF17: ENTREGADO | AG17: 1.43 | AH17: M3 | AI17: X | AJ17: 4 | AK17: V4 | AL17: 20230920 | AM17: D814-900005888-10000561
A18: 900006705D81410123034 | B18: 4600047626-50 | C18: 4600047626 | D18: 50 | E18: MXPO | F18: MXL | G18: 900006705 | H18: SF TP- FRISO TEAPA | I18: 5070657 | J18: FRISO SILRO SA DE CV | K18: N90 | L18: (AP) NAFIN 90 Dias | M18: 10123034 | N18: ARENA TRITURADA CALIZA MALLA 4 | O18: D814 | P18: MX-CED. TABASCO | Q18: 20200727 | R18: 20281231 | S18: 20230106 | T18: 20271231 | U18: 150 | V18: MXN | W18: M3 | X18: 0 | Y18: MXN | Z18: M3 | AC18: 56103638 | AD18: 6622041540 | AE18: 1 | AF18: ENTREGADO | AG18: 1.528 | AH18: M3 | AI18: X | AJ18: 4 | AK18: V4 | AL18: 20230920 | AM18: D814-900006705-10123034
A19: 900006705D81410191484 | B19: 4600047626-60 | C19: 4600047626 | D19: 60 | E19: MXPO | F19: MXL | G19: 900006705 | H19: SF TP- FRISO TEAPA | I19: 5070657 | J19: FRISO SILRO SA DE CV | K19: N90 | L19: (AP) NAFIN 90 Dias | M19: 10191484 | N19: ARENA TRITURADA CALIZA MALLA 4-NG | O19: D814 | P19: MX-CED. TABASCO | Q19: 20200727 | R19: 20281231 | S19: 20230106 | T19: 20271231 | U19: 150 | V19: MXN | W19: M3 | X19: 0 | Y19: MXN | Z19: M3 | AC19: 56103638 | AD19: 6622041540 | AE19: 1 | AF19: ENTREGADO | AG19: 1.3 | AH19: M3 | AI19: X | AJ19: 4 | AK19: V4 | AL19: 20230920 | AM19: D814-900006705-10191484
A20: 900006321D81410191076 | B20: 4600047726-30 | C20: 4600047726 | D20: 30 | E20: MXPO | F20: MXL | G20: 900006321 | H20: SF TP-LBE SAMARIA TABASCO | I20: 5076625 | J20: LBE CONSTRUCTORES SA DE CV | K20: N90 | L20: (AP) NAFIN 90 Dias | M20: 10191076 | N20: ARENA RIO LIMOSA NG | O20: D814 | P20: MX-CED. TABASCO | Q20: 20200806 | R20: 20271231 | S20: 20230123 | T20: 20271231 | U20: 52 | V20: MXN | W20: M3 | X20: 0 | Y20: MXN | Z20: M3 | AC20: 56103638 | AD20: 6622041540 | AE20: 1 | AF20: ENTREGADO | AG20: 1.52 | AH20: M3 | AI20: X | AJ20: 4 | AK20: V4 | AL20: 20230920 | AM20: D814-900006321-10191076
A21: 900006815D81410079650 | B21: 4600048233-10 | C21: 4600048233 | D21: 10 | E21: MXPO | F21: MXL | G21: 900006815 | H21: SF TP-CAPASA | I21: 5079230 | J21: CONSTRUCCION ARRENDAMIENTOS | K21: N90 | L21: (AP) NAFIN 90 Dias | M21: 10079650 | N21: ARENA DE RIO MALLA 4 | O21: D814 | P21: MX-CED. TABASCO | Q21: 20201009 | R21: 20291231 | S21: 20220607 | T21: 20271231 | U21: 60 | V21: MXN | W21: M3 | X21: 0 | Y21: MXN | Z21: M3 | AC21: 56103638 | AD21: 6622041540 | AE21: 1 | AF21: ENTREGADO | AG21: 1.448 | AH21: M3 | AI21: X | AJ21: 4 | AK21: V4 | AL21: 20230920 | AM21: D814-900006815-10079650
A22: 900004418D81410000561 | B22: 4600038499-60 | C22: 4600038499 | D22: 60 | E22: MXPO | F22: MXL | G22: 900004418 | H22: TP-SIGSA | I22: 5021622 | J22: SERVICIOS DE INGENIERIA DEL GOLFO | K22: N60 | L22: (AP) NAFIN 60 Dias | M22: 10000561 | N22: Grava Triturada Caliza 20 mm - 3/4" | O22: D814 | P22: MX-CED. TABASCO | Q22: 20170623 | R22: 20281231 | S22: 20220615 | T22: 20271231 | U22: 250 | V22: MXN | W22: M3 | X22: 0 | Y22: MXN | Z22: M3 | AC22: 56103637 | AD22: 6622041540 | AE22: 1 | AF22: ENTREGADO | AG22: 1.43 | AH22: M3 | AI22: X | AJ22: 4 | AK22: V4 | AL22: 20230920 | AM22: D814-900004418-10000561
A23: 900006236D81410151600 | B23: 4600045630-10 | C23: 4600045630 | D23: 10 | E23: MXPO | F23: MXL | G23: 900006236 | H23: SF TC-VYCSA F SABIAUR | I23: 5073829 | J23: SABIAUR PEREZ FERMIN | K23: N90 | L23: (AP) NAFIN 90 Dias | M23: 10151600 | N23: GRAVA TRITURADA CALIZA 40 MM - 1 1/2" | O23: D814 | P23: MX-CED. TABASCO | Q23: 20190925 | R23: 20241231 | S23: 20190925 | T23: 20241231 | U23: 240 | V23: MXN | W23: M3 | X23: 0 | Y23: MXN | Z23: M3 | AC23: 56103637 | AD23: 6622041540 | AE23: 1 | AF23: ENTREGADO | AG23: 1.398 | AH23: M3 | AI23: X | AJ23: 4 | AK23: V4 | AL23: 20230920 | AM23: D814-900006236-10151600
A24: 900006705D81410000421 | B24: 4600047626-30 | C24: 4600047626 | D24: 30 | E24: MXPO | F24: MXL | G24: 900006705 | H24: SF TP- FRISO TEAPA | I24: 5070657 | J24: FRISO SILRO SA DE CV | K24: N90 | L24: (AP) NAFIN 90 Dias | M24: 10000421 | N24: Grava Triturada Caliza 40 mm - 1 1/2" | O24: D814 | P24: MX-CED. TABASCO | Q24: 20200727 | R24: 20281231 | S24: 20220726 | T24: 20271231 | U24: 220 | V24: MXN | W24: M3 | X24: 0 | Y24: MXN | Z24: M3 | AC24: 56103637 | AD24: 6622041540 | AE24: 1 | AF24: ENTREGADO | AG24: 1.496 | AH24: M3 | AI24: X | AJ24: 4 | AK24: V4 | AL24: 20230920 | AM24: D814-900006705-10000421
A25: 900005888D81410191175 | B25: 4600043667-30 | C25: 4600043667 | D25: 30 | E25: MXPO | F25: MXL | G25: 900005888 | H25: SF TP-FERMIN SABIAUR | I25: 5073829 | J25: SABIAUR PEREZ FERMIN | K25: N90 | L25: (AP) NAFIN 90 Dias | M25: 10191175 | N25: GRAVA TRITURADA CALIZA 40MM - 1 1/2 NG | O25: D814 | P25: MX-CED. TABASCO | Q25: 20181217 | R25: 20281231 | S25: 20230316 | T25: 20281231 | U25: 354.9 | V25: MXN | W25: M3 | X25: 0 | Y25: MXN | Z25: M3 | AC25: 56103637 | AD25: 6622041540 | AE25: 1 | AF25: ENTREGADO | AG25: 1.72 | AH25: M3 | AI25: X | AJ25: 4 | AK25: V4 | AL25: 20230920 | AM25: D814-900005888-10191175
... A28: 900004418D81410123034 | B28: 4600038499-90 | C28: 4600038499 | D28: 90 | E28: MXPO | F28: MXL | G28: 900004418 | H28: TP-SIGSA | I28: 5021622 | J28: SERVICIOS DE INGENIERIA DEL GOLFO | K28: N60 | L28: (AP) NAFIN 60 Dias | M28: 10123034 | N28: ARENA TRITURADA CALIZA MALLA 4 | O28: D814 | P28: MX-CED. TABASCO | Q28: 20170623 | R28: 20281231 | S28: 20230317 | T28: 20281231 | U28: 200 | V28: MXN | W28: M3 | X28: 0 | Y28: MXN | Z28: M3 | AC28: 56103638 | AD28: 6622041540 | AE28: 1 | AF28: ENTREGADO | AG28: 1.528 | AH28: M3 | AI28: X | AJ28: 4 | AK28: V4 | AL28: 20230920 | AM28: D814-900004418-10123034
A29: 900003735D8146664759010000541 | B29: 4600041691-50 | C29: 4600041691 | D29: 50 | E29: MXPO | F29: MXL | G29: 900003735 | H29: TP-ED-LAZCANO HUERTA | I29: 5000326 | J29: LAZCANO HUERTA ROCIO NANCY | K29: Z09 | L29: (AP) 90 Dias | M29: 10000541 | N29: Grava Clasificada Río 10 mm - 3/8" | O29: D814 | P29: MX-CED. TABASCO | Q29: 20180405 | R29: 20241231 | S29: 20200128 | T29: 20291231 | U29: 368.42 | V29: MXN | W29: M3 | X29: 0 | Y29: MXN | Z29: M3 | AA29: 66647590 | AB29: CP-I CLUSTER 7 ANRROCA (CISP) | AC29: 56103637 | AD29: 6622041540 | AE29: 4 | AF29: ENTREGA DIRECTA | AG29: 1.528 | AH29: M3 | AI29: X | AJ29: 4 | AK29: V4 | AL29: 20230920 | AM29: D814-900003735-66647590-10000541-4
A30: 900005888D81410001643 | B30: 4600043667-10 | C30: 4600043667 | D30: 10 | E30: MXPO | F30: MXL | G30: 900005888 | H30: SF TP-FERMIN SABIAUR | I30: 5073829 | J30: SABIAUR PEREZ FERMIN | K30: N90 | L30: (AP) NAFIN 90 Dias | M30: 10001643 | N30: Crudo Clasificado Río | O30: D814 | P30: MX-CED. TABASCO | Q30: 20181217 | R30: 20281231 | S30: 20190201 | T30: 20241231 | U30: 320 | V30: MXN | W30: M3 | X30: 0 | Y30: MXN | Z30: M3 | AC30: 56103636 | AD30: 6622041540 | AE30: 1 | AF30: ENTREGADO | AG30: 1.48 | AH30: M3 | AI30: X | AJ30: 4 | AK30: V4 | AL30: 20230920 | AM30: D814-900005888-10001643
A31: 900006705D81410147454 | B31: 4600047626-10 | C31: 4600047626 | D31: 10 | E31: MXPO | F31: MXL | G31: 900006705 | H31: SF TP- FRISO TEAPA | I31: 5070657 | J31: FRISO SILRO SA DE CV | K31: N90 | L31: (AP) NAFIN 90 Dias | M31: 10147454 | N31: GRAVA TRITURADA CALIZA 20 MM - 3/4" | O31: D814 | P31: MX-CED. TABASCO | Q31: 20200727 | R31: 20281231 | S31: 20230726 | T31: 20281231 | U31: 254 | V31: MXN | W31: M3 | X31: 0 | Y31: MXN | Z31: M3 | AC31: 56103637 | AD31: 6622041540 | AE31: 1 | AF31: ENTREGADO | AG31: 1.556 | AH31: M3 | AI31: X | AJ31: 4 | AK31: V4 | AL31: 20230920 | AM31: D814-900006705-10147454
A32: 900004418D81410047545 | B32: 4600038499-40 | C32: 4600038499 | D32: 40 | E32: MXPO | F32: MXL | G32: 900004418 | H32: TP-SIGSA | I32: 5021622 | J32: SERVICIOS DE INGENIERIA DEL GOLFO | K32: N60 | L32: (AP) NAFIN 60 Dias | M32: 10047545 | N32: Grava Triturada Caliza 20 mm - 3/4" -B | O32: D814 | P32: MX-CED. TABASCO | Q32: 20170623 | R32: 20281231 | S32: 20191108 | T32: 20241231 | U32: 175 | V32: MXN | W32: M3 | X32: 0 | Y32: MXN | Z32: M3 | AC32: 56103637 | AD32: 6622041540 | AE32: 1 | AF32: ENTREGADO | AG32: 1.46 | AH32: M3 | AI32: X | AJ32: 4 | AK32: V4 | AL32: 20230920 | AM32: D814-900004418-10047545
A33: 900004418D81410047545 | B33: 4600038499-80 | C33: 4600038499 | D33: 80 | E33: MXPO | F33: MXL | G33: 900004418 | H33: TP-SIGSA | I33: 5021622 | J33: SERVICIOS DE INGENIERIA DEL GOLFO | K33: N60 | L33: (AP) NAFIN 60 Dias | M33: 10047545 | N33: Grava Triturada Caliza 20 mm - 3/4" -B | O33: D814 | P33: MX-CED. TABASCO | Q33: 20170623 | R33: 20281231 | S33: 20211215 | T33: 20261231 | U33: 234 | V33: MXN | W33: M3 | X33: 0 | Y33: MXN | Z33: M3 | AC33: 56103637 | AD33: 6622041540 | AE33: 2 | AF33: RECOGIDO | AG33: 1.46 | AH33: M3 | AI33: X | AJ33: 4 | AK33: V4 | AL33: 20230920 | AM33: D814-900004418-10047545
A34: 900006321D81410079650 | B34: 4600047726-10 | C34: 4600047726 | D34: 10 | E34: MXPO | F34: MXL | G34: 900006321 | H34: SF TP-LBE SAMARIA TABASCO | I34: 5076625 | J34: LBE CONSTRUCTORES SA DE CV | K34: N90 | L34: (AP) NAFIN 90 Dias | M34: 10079650 | N34: ARENA DE RIO MALLA 4 | O34: D814 | P34: MX-CED. TABASCO | Q34: 20200806 | R34: 20271231 | S34: 20220404 | T34: 20271231 | U34: 51 | V34: MXN | W34: M3 | X34: 0 | Y34: MXN | Z34: M3 | AC34: 56103638 | AD34: 6622041540 | AE34: 1 | AF34: ENTREGADO | AG34: 1.448 | AH34: M3 | AI34: X | AJ34: 4 | AK34: V4 | AL34: 20230920 | AM34: D814-900006321-10079650
A35: 900007620D81410197438 | B35: 4600054015-20 | C35: 4600054015 | D35: 20 | E35: MXPO | F35: MXL | G35: 900007620 | H35: SF TP-FRISO CONSMIN TAB | I35: 5083592 | J35: FRISO CONSMIN SA DE CV | K35: N45 | L35: (AP) NAFIN 45 Dias | M35: 10197438 | N35: BASE H CALIZA 1 1/2" A FINOS ESPECIAL | O35: D814 | P35: MX-CED. TABASCO | Q35: 20220519 | R35: 20291231 | S35: 20230426 | T35: 20281231 | U35: 230 | V35: MXN | W35: M3 | X35: 0 | Y35: MXN | Z35: M3 | AC35: 56103590 | AD35: 6622041540 | AE35: 1 | AF35: ENTREGADO | AG35: 1.65 | AH35: M3 | AI35: X | AJ35: 4 | AK35: V4 | AL35: 20230920 | AM35: D814-900007620-10197438
A36: 900006321D81410210039 | B36: 4600053374-10 | C36: 4600053374 | D36: 10 | E36: MXPO | F36: MXL | G36: 900006321 | H36: SF TP-LBE SAMARIA TABASCO | I36: 5076625 | J36: LBE CONSTRUCTORES SA DE CV | K36: N90 | L36: (AP) NAFIN 90 Dias | M36: 10210039 | N36: ARENA CLASIFICADA RÍO MALLA 4 | O36: D814 | P36: MX-CED. TABASCO | Q36: 20220304 | R36: 20271231 | S36: 20220304 | T36: 20271231 | U36: 47 | V36: MXN | W36: M3 | X36: 0 | Y36: MXN | Z36: M3 | AC36: 56103638 | AD36: 6622041540 | AE36: 1 | AF36: ENTREGADO | AG36: 1.485 | AH36: M3 | AI36: X | AJ36: 4 | AK36: V4 | AL36: 20230920 | AM36: D814-900006321-10210039
A37: 900007620D81410047545 | B37: 4600054015-50 | C37: 4600054015 | D37: 50 | E37: MXPO | F37: MXL | G37: 900007620 | H37: SF TP-FRISO CONSMIN TAB | I37: 5083592 | J37: FRISO CONSMIN SA DE CV | K37: N45 | L37: (AP) NAFIN 45 Dias | M37: 10047545 | N37: Grava Triturada Caliza 20 mm - 3/4" -B | O37: D814 | P37: MX-CED. TABASCO | Q37: 20220519 | R37: 20291231 | S37: 20230416 | T37: 20281231 | U37: 252 | V37: MXN | W37: M3 | X37: 0 | Y37: MXN | Z37: M3 | AC37: 56103637 | AD37: 6622041540 | AE37: 1 | AF37: ENTREGADO | AG37: 1.46 | AH37: M3 | AI37: X | AJ37: 4 | AK37: V4 | AL37: 20230920 | AM37: D814-900007620-10047545
A38: 900006706D8146688714110193744 | B38: 4600047553-60 | C38: 4600047553 | D38: 60 | E38: MXPO | F38: MXL | G38: 900006706 | H38: SF TP-ED-FRISO TEAPA | I38: 5070657 | J38: FRISO SILRO SA DE CV | K38: N90 | L38: (AP) NAFIN 90 Dias | M38: 10193744 | N38: PIEDRA CALIZA BLANCA 2 1/2 A 3 - NG | O38: D814 | P38: MX-CED. TABASCO | Q38: 20200717 | R38: 20281231 | S38: 20210302 | T38: 20291231 | U38: 480 | V38: MXN | W38: M3 | X38: 380 | Y38: MXN | Z38: M3 | AA38: 66887141 | AB38: Tanque T3 Refinería Dos Bocas | AC38: 56103637 | AD38: 6622041540 | AE38: 4 | AF38: ENTREGA DIRECTA | AG38: 1.56 | AH38: M3 | AI38: X | AJ38: 4 | AK38: V4 | AL38: 20230920 | AM38: D814-900006706-66887141-10193744-4
A39: 900006706D8146694653610193744 | B39: 4600047553-70 | C39: 4600047553 | D39: 70 | E39: MXPO | F39: MXL | G39: 900006706 | H39: SF TP-ED-FRISO TEAPA | I39: 5070657 | J39: FRISO SILRO SA DE CV | K39: N90 | L39: (AP) NAFIN 90 Dias | M39: 10193744 | N39: PIEDRA CALIZA BLANCA 2 1/2 A 3 - NG | O39: D814 | P39: MX-CED. TABASCO | Q39: 20200717 | R39: 20281231 | S39: 20210316 | T39: 20291231 | U39: 480 | V39: MXN | W39: M3 | X39: 380 | Y39: MXN | Z39: M3 | AA39: 66946536 | AB39: P6 - Pulmón - Refinería Dos Bocas | AC39: 56103637 | AD39: 6622041540 | AE39: 4 | AF39: ENTREGA DIRECTA | AG39: 1.56 | AH39: M3 | AI39: X | AJ39: 4 | AK39: V4 | AL39: 20230920 | AM39: D814-900006706-66946536-10193744-4
A40: 900006706D8146687594810191175 | B40: 4600047553-110 | C40: 4600047553 | D40: 110 | E40: MXPO | F40: MXL | G40: 900006706 | H40: SF TP-ED-FRISO TEAPA | I40: 5070657 | J40: FRISO SILRO SA DE CV | K40: N90 | L40: (AP) NAFIN 90 Dias | M40: 10191175 | N40: GRAVA TRITURADA CALIZA 40MM - 1 1/2 NG | O40: D814 | P40: MX-CED. TABASCO | Q40: 20200717 | R40: 20281231 | S40: 20210406 | T40: 20261231 | U40: 480 | V40: MXN | W40: M3 | X40: 330 | Y40: MXN | Z40: M3 | AA40: 66875948 | AB40: COGENERACIÓN TECHINT REF | AC40: 56103637 | AD40: 6622041540 | AE40: 4 | AF40: ENTREGA DIRECTA | AG40: 1.72 | AH40: M3 | AI40: X | AJ40: 4 | AK40: V4 | AL40: 20230920 | AM40: D814-900006706-66875948-10191175-4
A41: 900006706D8146694653610000372 | B41: 4600047553-270 | C41: 4600047553 | D41: 270 | E41: MXPO | F41: MXL | G41: 900006706 | H41: SF TP-ED-FRISO TEAPA | I41: 5070657 | J41: FRISO SILRO SA DE CV | K41: N90 | L41: (AP) NAFIN 90 Dias | M41: 10000372 | N41: Grava Triturada Caliza 20 mm - 3/4" | O41: D814 | P41: MX-CED. TABASCO | Q41: 20200717 | R41: 20281231 | S41: 20220104 | T41: 20271231 | U41: 495 | V41: MXN | W41: M3 | X41: 330 | Y41: MXN | Z41: M3 | AA41: 66946536 | AB41: P6 - Pulmón - Refinería Dos Bocas | AC41: 56103637 | AD41: 6622041540 | AE41: 4 | AF41: ENTREGA DIRECTA | AG41: 1.448 | AH41: M3 | AI41: X | AJ41: 4 | AK41: V4 | AL41: 20230920 | AM41: D814-900006706-66946536-10000372-4
A42: 900007054D8146687594810000372 | B42: 4600049598-80 | C42: 4600049598 | D42: 80 | E42: MXPO | F42: MXL | G42: 900007054 | H42: SF TP-ED-SAMUEL CARRASCO | I42: 5080454 | J42: CARRASCO ALCUDIA SAMUEL | K42: N90 | L42: (AP) NAFIN 90 Dias | M42: 10000372 | N42: Grava Triturada Caliza 20 mm - 3/4" | O42: D814 | P42: MX-CED. TABASCO | Q42: 20210407 | R42: 20291231 | S42: 20220131 | T42: 20261231 | U42: 550 | V42: MXN | W42: M3 | X42: 380 | Y42: MXN | Z42: M3 | AA42: 66875948 | AB42: COGENERACIÓN TECHINT REF | AC42: 56103637 | AD42: 6622041540 | AE42: 4 | AF42: ENTREGA DIRECTA | AG42: 1.448 | AH42: M3 | AI42: X | AJ42: 4 | AK42: V4 | AL42: 20230920 | AM42: D814-900007054-66875948-10000372-4
A43: 900006706D8146688638110147454 | B43: 4600047553-40 | C43: 4600047553 | D43: 40 | E43: MXPO | F43: MXL | G43: 900006706 | H43: SF TP-ED-FRISO TEAPA | I43: 5070657 | J43: FRISO SILRO SA DE CV | K43: N90 | L43: (AP) NAFIN 90 Dias | M43: 10147454 | N43: GRAVA TRITURADA CALIZA 20 MM - 3/4" | O43: D814 | P43: MX-CED. TABASCO | Q43: 20200717 | R43: 20281231 | S43: 20220730 | T43: 20271231 | U43: 375 | V43: MXN | W43: M3 | X43: 145 | Y43: MXN | Z43: M3 | AA43: 66886381 | AB43: CONCRETEC VILLAHERMOSA | AC43: 56103637 | AD43: 6622041540 | AE43: 4 | AF43: ENTREGA DIRECTA | AG43: 1.556 | AH43: M3 | AI43: X | AJ43: 4 | AK43: V4 | AL43: 20230920 | AM43: D814-900006706-66886381-10147454-4
A44: 900005557D8146648621410001643 | B44: 4600041437-70 | C44: 4600041437 | D44: 70 | E44: MXPO | F44: MXL | G44: 900005557 | H44: TP-ED-DANIEL BECERRA | I44: 5070594 | J44: BECERRA MAYORGA DANIEL | K44: N90 | L44: (AP) NAFIN 90 Dias | M44: 10001643 | N44: Crudo Clasificado Río | O44: D814 | P44: MX-CED. TABASCO | Q44: 20180307 | R44: 20241231 | S44: 20190529 | T44: 20241231 | U44: 355 | V44: MXN | W44: M3 | X44: 30 | Y44: MXN | Z44: M3 | AA44: 66486214 | AB44: (P) TUBOCRETO PLANTA TEAPA. | AC44: 56103636 | AD44: 6622041540 | AE44: 4 | AF44: ENTREGA DIRECTA | AG44: 1.48 | AH44: M3 | AI44: X | AJ44: 4 | AK44: V4 | AL44: 20230920 | AM44: D814-900005557-66486214-10001643-4
A45: 900006706D8146703286810193885 | B45: 4600047553-280 | C45: 4600047553 | D45: 280 | E45: MXPO | F45: MXL | G45: 900006706 | H45: SF TP-ED-FRISO TEAPA | I45: 5070657 | J45: FRISO SILRO SA DE CV | K45: N90 | L45: (AP) NAFIN 90 Dias | M45: 10193885 | N45: BASE H CALIZA GRIS 1 1/2 PARA PATIO NG | O45: D814 | P45: MX-CED. TABASCO | Q45: 20200717 | R45: 20281231 | S45: 20220107 | T45: 20271231 | U45: 345 | V45: MXN | W45: M3 | X45: 245 | Y45: MXN | Z45: M3 | AA45: 67032868 | AB45: FRACC SANTO DOMINGO (EAOG) | AC45: 56103590 | AD45: 6622041540 | AE45: 4 | AF45: ENTREGA DIRECTA | AG45: 1.52 | AH45: M3 | AI45: X | AJ45: 4 | AK45: V4 | AL45: 20230920 | AM45: D814-900006706-67032868-10193885-4
A46: 900006706D8146708843510147454 | B46: 4600047553-380 | C46: 4600047553 | D46: 380 | E46: MXPO | F46: MXL | G46: 900006706 | H46: SF TP-ED-FRISO TEAPA | I46: 5070657 | J46: FRISO SILRO SA DE CV | K46: N90 | L46: (AP) NAFIN 90 Dias | M46: 10147454 | N46: GRAVA TRITURADA CALIZA 20 MM - 3/4" | O46: D814 | P46: MX-CED. TABASCO | Q46: 20200717 | R46: 20281231 | S46: 20230609 | T46: 20281231 | U46: 520 | V46: MXN | W46: M3 | X46: 270 | Y46: MXN | Z46: M3 | AA46: 67088435 | AB46: Agregados CPI Comalcalco | AC46: 56103637 | AD46: 6622041540 | AE46: 4 | AF46: ENTREGA DIRECTA | AG46: 1.556 | AH46: M3 | AI46: X | AJ46: 4 | AK46: V4 | AL46: 20230920 | AM46: D814-900006706-67088435-10147454-4
A47: 900005557D8146501147410079650 | B47: 4600041437-80 | C47: 4600041437 | D47: 80 | E47: MXPO | F47: MXL | G47: 900005557 | H47: TP-ED-DANIEL BECERRA | I47: 5070594 | J47: BECERRA MAYORGA DANIEL | K47: N90 | L47: (AP) NAFIN 90 Dias | M47: 10079650 | N47: ARENA DE RIO MALLA 4 | O47: D814 | P47: MX-CED. TABASCO | Q47: 20180307 | R47: 20241231 | S47: 20210813 | T47: 20241231 | U47: 165 | V47: MXN | W47: M3 | X47: 123 | Y47: MXN | Z47: M3 | AA47: 65011474 | AB47: INGENIERIA MEXICANA DEL SURESTE, S. | AC47: 56103638 | AD47: 6622041540 | AE47: 4 | AF47: ENTREGA DIRECTA | AG47: 1.448 | AH47: M3 | AI47: X | AJ47: 4 | AK47: V4 | AL47: 20230920 | AM47: D814-900005557-65011474-10079650-4
A48: 900006419D814DG6810000373 | B48: 4600046193-110 | C48: 4600046193 | D48: 110 | E48: MXPO | F48: MXL | G48: 900006419 | H48: SF TC-ED-CATAB | I48: 5051216 | J48: COMERCIALIZADORA DE AGREGADOS TABAS | K48: N60 | L48: (AP) NAFIN 60 Dias | M48: 10000373 | N48: Grava Triturada Caliza 13 mm - 1/2" | O48: D814 | P48: MX-CED. TABASCO | Q48: 20191219 | R48: 20241231 | S48: 20191219 | T48: 20241231 | U48: 507.5 | V48: MXN | W48: M3 | X48: 202.5 | Y48: MXN | Z48: M3 | AA48: DG68 | AB48: PD0477 CARDENAS | AC48: 56103637 | AD48: 6622041540 | AE48: 4 | AF48: ENTREGA DIRECTA | AG48: 1.395 | AH48: M3 | AI48: X | AJ48: 4 | AK48: V4 | AL48: 20230920 | AM48: D814-900006419-DG68-10000373-4
A49: 900007054D8146501147410197737 | B49: 4600049598-90 | C49: 4600049598 | D49: 90 | E49: MXPO | F49: MXL | G49: 900007054 | H49: SF TP-ED-SAMUEL CARRASCO | I49: 5080454 | J49: CARRASCO ALCUDIA SAMUEL | K49: N90 | L49: (AP) NAFIN 90 Dias | M49: 10197737 | N49: ARENA CLASIFICADA RÍO MALLA 4- NG | O49: D814 | P49: MX-CED. TABASCO | Q49: 20210407 | R49: 20291231 | S49: 20220411 | T49: 20271231 | U49: 228 | V49: MXN | W49: M3 | X49: 173 | Y49: MXN | Z49: M3 | AA49: 65011474 | AB49: INGENIERIA MEXICANA DEL SURESTE, S. | AC49: 56103638 | AD49: 6622041867 | AE49: 4 | AF49: ENTREGA DIRECTA | AG49: 1.55 | AH49: M3 | AI49: X | AJ49: 4 | AK49: V4 | AL49: 20230920 | AM49: D814-900007054-65011474-10197737-4
... A60: 900007621D8146704594010191175 | B60: 4600054100-10 | C60: 4600054100 | D60: 10 | E60: MXPO | F60: MXL | G60: 900007621 | H60: SF TP-ED-FRISO CONSMIN TAB | I60: 5083592 | J60: FRISO CONSMIN SA DE CV | K60: N45 | L60: (AP) NAFIN 45 Dias | M60: 10191175 | N60: GRAVA TRITURADA CALIZA 40MM - 1 1/2 NG | O60: D814 | P60: MX-CED. TABASCO | Q60: 20220602 | R60: 20281231 | S60: 20220602 | T60: 20271231 | U60: 535 | V60: MXN | W60: M3 | X60: 315 | Y60: MXN | Z60: M3 | AA60: 67045940 | AB60: CEMENTO COGENERACION (EAOG) | AC60: 56103637 | AD60: 6622041540 | AE60: 4 | AF60: ENTREGA DIRECTA | AG60: 1.72 | AH60: M3 | AI60: X | AJ60: 4 | AK60: V4 | AL60: 20230920 | AM60: D814-900007621-67045940-10191175-4
A61: 900003735D8146643882310000541 | B61: 4600041691-10 | C61: 4600041691 | D61: 10 | E61: MXPO | F61: MXL | G61: 900003735 | H61: TP-ED-LAZCANO HUERTA | I61: 5000326 | J61: LAZCANO HUERTA ROCIO NANCY | K61: Z09 | L61: (AP) 90 Dias | M61: 10000541 | N61: Grava Clasificada Río 10 mm - 3/8" | O61: D814 | P61: MX-CED. TABASCO | Q61: 20180405 | R61: 20241231 | S61: 20180622 | T61: 20241231 | U61: 330 | V61: MXN | W61: M3 | X61: 200.4 | Y61: MXN | Z61: M3 | AA61: 66438823 | AC61: 56103637 | AD61: 6622041540 | AE61: 4 | AF61: ENTREGA DIRECTA | AG61: 1.528 | AH61: M3 | AI61: X | AJ61: 4 | AK61: V4 | AL61: 20230920 | AM61: D814-900003735-66438823-10000541-4
A62: 900006706D8146686296110191255 | B62: 4600047553-80 | C62: 4600047553 | D62: 80 | E62: MXPO | F62: MXL | G62: 900006706 | H62: SF TP-ED-FRISO TEAPA | I62: 5070657 | J62: FRISO SILRO SA DE CV | K62: N90 | L62: (AP) NAFIN 90 Dias | M62: 10191255 | N62: GRAVA TRITURADA CALIZA 20MM-3/4 NG | O62: D814 | P62: MX-CED. TABASCO | Q62: 20200717 | R62: 20281231 | S62: 20210322 | T62: 20261231 | U62: 515 | V62: MXN | W62: M3 | X62: 355 | Y62: MXN | Z62: M3 | AA62: 66862961 | AB62: PILAS CIMESA REFINERIA (EAOG) | AC62: 56103637 | AD62: 6622041540 | AE62: 4 | AF62: ENTREGA DIRECTA | AG62: 1.5 | AH62: M3 | AI62: X | AJ62: 4 | AK62: V4 | AL62: 20230920 | AM62: D814-900006706-66862961-10191255-4
A63: 900006706D8146694653610000421 | B63: 4600047553-350 | C63: 4600047553 | D63: 350 | E63: MXPO | F63: MXL | G63: 900006706 | H63: SF TP-ED-FRISO TEAPA | I63: 5070657 | J63: FRISO SILRO SA DE CV | K63: N90 | L63: (AP) NAFIN 90 Dias | M63: 10000421 | N63: Grava Triturada Caliza 40 mm - 1 1/2" | O63: D814 | P63: MX-CED. TABASCO | Q63: 20200717 | R63: 20281231 | S63: 20220624 | T63: 20271231 | U63: 532.4 | V63: MXN | W63: M3 | X63: 340 | Y63: MXN | Z63: M3 | AA63: 66946536 | AB63: P6 - Pulmón - Refinería Dos Bocas | AC63: 56103637 | AD63: 6622041540 | AE63: 4 | AF63: ENTREGA DIRECTA | AG63: 1.496 | AH63: M3 | AI63: X | AJ63: 4 | AK63: V4 | AL63: 20230920 | AM63: D814-900006706-66946536-10000421-4
A64: 900006706D8146704594010191255 | B64: 4600047553-390 | C64: 4600047553 | D64: 390 | E64: MXPO | F64: MXL | G64: 900006706 | H64: SF TP-ED-FRISO TEAPA | I64: 5070657 | J64: FRISO SILRO SA DE CV | K64: N90 | L64: (AP) NAFIN 90 Dias | M64: 10191255 | N64: GRAVA TRITURADA CALIZA 20MM-3/4 NG | O64: D814 | P64: MX-CED. TABASCO | Q64: 20200717 | R64: 20281231 | S64: 20220914 | T64: 20271231 | U64: 503 | V64: MXN | W64: M3 | X64: 273 | Y64: MXN | Z64: M3 | AA64: 67045940 | AB64: CEMENTO COGENERACION (EAOG) | AC64: 56103637 | AD64: 6622041540 | AE64: 4 | AF64: ENTREGA DIRECTA | AG64: 1.5 | AH64: M3 | AI64: X | AJ64: 4 | AK64: V4 | AL64: 20230920 | AM64: D814-900006706-67045940-10191255-4
A65: 900006706D8146637217110147454 | B65: 4600047553-420 | C65: 4600047553 | D65: 420 | E65: MXPO | F65: MXL | G65: 900006706 | H65: SF TP-ED-FRISO TEAPA | I65: 5070657 | J65: FRISO SILRO SA DE CV | K65: N90 | L65: (AP) NAFIN 90 Dias | M65: 10147454 | N65: GRAVA TRITURADA CALIZA 20 MM - 3/4" | O65: D814 | P65: MX-CED. TABASCO | Q65: 20200717 | R65: 20281231 | S65: 20221119 | T65: 20271231 | U65: 369 | V65: MXN | W65: M3 | X65: 139 | Y65: MXN | Z65: M3 | AA65: 66372171 | AB65: ALMACEN CONCRETEV | AC65: 56103637 | AD65: 6622041540 | AE65: 4 | AF65: ENTREGA DIRECTA | AG65: 1.556 | AH65: M3 | AI65: X | AJ65: 4 | AK65: V4 | AL65: 20230920 | AM65: D814-900006706-66372171-10147454-4
A66: 900004613D8146704707810000541 | B66: 4600050018-50 | C66: 4600050018 | D66: 50 | E66: MXPO | F66: MXL | G66: 900004613 | H66: TP-ED-TALLER ORTIZ | I66: 5062978 | J66: TALLERES Y TRANSPORTES SA DE CV | K66: N90 | L66: (AP) NAFIN 90 Dias | M66: 10000541 | N66: Grava Clasificada Río 10 mm - 3/8" | O66: D814 | P66: MX-CED. TABASCO | Q66: 20210517 | R66: 20261231 | S66: 20220725 | T66: 20271231 | U66: 550 | V66: MXN | W66: M3 | X66: 420 | Y66: MXN | Z66: M3 | AA66: 67047078 | AB66: PANCOR REFINERIA OLMECA | AC66: 56103637 | AD66: 6622041540 | AE66: 4 | AF66: ENTREGA DIRECTA | AG66: 1.528 | AH66: M3 | AI66: X | AJ66: 4 | AK66: V4 | AL66: 20230920 | AM66: D814-900004613-67047078-10000541-4
A67: 900000515D814DG2410049559 | B67: 4600034904-50 | C67: 4600034904 | D67: 50 | E67: MXPO | F67: MXL | G67: 900000515 | H67: TC-ED-MAROGU | I67: 5007923 | J67: COMERCIALIZADORA Y AGREG. MAROGU SA | K67: Z09 | L67: (AP) 90 Dias | M67: 10049559 | N67: Grava Triturada Caliza 20 mm - 3/4" | O67: D814 | P67: MX-CED. TABASCO | Q67: 20160808 | R67: 20241231 | S67: 20160808 | T67: 20241231 | U67: 306 | V67: MXN | W67: M3 | X67: 141 | Y67: MXN | Z67: M3 | AA67: DG24 | AB67: DG24 PD0403 PETEMPICH II | AC67: 56103637 | AD67: 6622041540 | AE67: 4 | AF67: ENTREGA DIRECTA | AG67: 1.342 | AH67: M3 | AI67: X | AJ67: 4 | AK67: V4 | AL67: 20230920 | AM67: D814-900000515-DG24-10049559-4
A68: 900006419D814DG6810000421 | B68: 4600046193-30 | C68: 4600046193 | D68: 30 | E68: MXPO | F68: MXL | G68: 900006419 | H68: SF TC-ED-CATAB | I68: 5051216 | J68: COMERCIALIZADORA DE AGREGADOS TABAS | K68: N60 | L68: (AP) NAFIN 60 Dias | M68: 10000421 | N68: Grava Triturada Caliza 40 mm - 1 1/2" | O68: D814 | P68: MX-CED. TABASCO | Q68: 20191219 | R68: 20241231 | S68: 20191219 | T68: 20241231 | U68: 446.5 | V68: MXN | W68: M3 | X68: 202.5 | Y68: MXN | Z68: M3 | AA68: DG68 | AB68: PD0477 CARDENAS | AC68: 56103637 | AD68: 6622041540 | AE68: 4 | AF68: ENTREGA DIRECTA | AG68: 1.496 | AH68: M3 | AI68: X | AJ68: 4 | AK68: V4 | AL68: 20230920 | AM68: D814-900006419-DG68-10000421-4
A69: 900006706D8146694653610000861 | B69: 4600047553-90 | C69: 4600047553 | D69: 90 | E69: MXPO | F69: MXL | G69: 900006706 | H69: SF TP-ED-FRISO TEAPA | I69: 5070657 | J69: FRISO SILRO SA DE CV | K69: N90 | L69: (AP) NAFIN 90 Dias | M69: 10000861 | N69: Base H Triturada Caliza 1 1/2" a Finos | O69: D814 | P69: MX-CED. TABASCO | Q69: 20200717 | R69: 20281231 | S69: 20210323 | T69: 20261231 | U69: 485 | V69: MXN | W69: M3 | X69: 335 | Y69: MXN | Z69: M3 | AA69: 66946536 | AB69: P6 - Pulmón - Refinería Dos Bocas | AC69: 56103590 | AD69: 6622041540 | AE69: 4 | AF69: ENTREGA DIRECTA | AG69: 1.52 | AH69: M3 | AI69: X | AJ69: 4 | AK69: V4 | AL69: 20230920 | AM69: D814-900006706-66946536-10000861-4
A70: 900006706D8146686140810191175 | B70: 4600047553-360 | C70: 4600047553 | D70: 360 | E70: MXPO | F70: MXL | G70: 900006706 | H70: SF TP-ED-FRISO TEAPA | I70: 5070657 | J70: FRISO SILRO SA DE CV | K70: N90 | L70: (AP) NAFIN 90 Dias | M70: 10191175 | N70: GRAVA TRITURADA CALIZA 40MM - 1 1/2 NG | O70: D814 | P70: MX-CED. TABASCO | Q70: 20200717 | R70: 20281231 | S70: 20220628 | T70: 20271231 | U70: 532 | V70: MXN | W70: M3 | X70: 340 | Y70: MXN | Z70: M3 | AA70: 66861408 | AB70: Refinería Dos Bocas | AC70: 56103637 | AD70: 6622041540 | AE70: 4 | AF70: ENTREGA DIRECTA | AG70: 1.72 | AH70: M3 | AI70: X | AJ70: 4 | AK70: V4 | AL70: 20230920 | AM70: D814-900006706-66861408-10191175-4
A71: 900007054D8146686296110191076 | B71: 4600049598-40 | C71: 4600049598 | D71: 40 | E71: MXPO | F71: MXL | G71: 900007054 | H71: SF TP-ED-SAMUEL CARRASCO | I71: 5080454 | J71: CARRASCO ALCUDIA SAMUEL | K71: N90 | L71: (AP) NAFIN 90 Dias | M71: 10191076 | N71: ARENA RIO LIMOSA NG | O71: D814 | P71: MX-CED. TABASCO | Q71: 20210407 | R71: 20291231 | S71: 20210614 | T71: 20261231 | U71: 180 | V71: MXN | W71: M3 | X71: 124 | Y71: MXN | Z71: M3 | AA71: 66862961 | AB71: PILAS CIMESA REFINERIA (EAOG) | AC71: 56103638 | AD71: 6622041540 | AE71: 4 | AF71: ENTREGA DIRECTA | AG71: 1.52 | AH71: M3 | AI71: X | AJ71: 4 | AK71: V4 | AL71: 20230920 | AM71: D814-900007054-66862961-10191076-4
A72: 900007054D8146688638110191076 | B72: 4600049598-130 | C72: 4600049598 | D72: 130 | E72: MXPO | F72: MXL | G72: 900007054 | H72: SF TP-ED-SAMUEL CARRASCO | I72: 5080454 | J72: CARRASCO ALCUDIA SAMUEL | K72: N90 | L72: (AP) NAFIN 90 Dias | M72: 10191076 | N72: ARENA RIO LIMOSA NG | O72: D814 | P72: MX-CED. TABASCO | Q72: 20210407 | R72: 20291231 | S72: 20221101 | T72: 20271231 | U72: 610 | V72: MXN | W72: M3 | X72: 560 | Y72: MXN | Z72: M3 | AA72: 66886381 | AB72: CONCRETEC VILLAHERMOSA | AC72: 56103638 | AD72: 6622041540 | AE72: 4 | AF72: ENTREGA DIRECTA | AG72: 1.52 | AH72: M3 | AI72: X | AJ72: 4 | AK72: V4 | AL72: 20230920 | AM72: D814-900007054-66886381-10191076-4
A73: 900004842D8146632286510000834 | B73: 4600035006-20 | C73: 4600035006 | D73: 20 | E73: MXPO | F73: MXL | G73: 900004842 | H73: TP-ED-MAROGU | I73: 5007923 | J73: COMERCIALIZADORA Y AGREG. MAROGU SA | K73: N90 | L73: (AP) NAFIN 90 Dias | M73: 10000834 | N73: Arena Clasificada Río Malla 4 | O73: D814 | P73: MX-CED. TABASCO | Q73: 20160818 | R73: 20241231 | S73: 20160817 | T73: 20241231 | U73: 172 | V73: MXN | W73: M3 | X73: 72 | Y73: MXN | Z73: M3 | AA73: 66322865 | AB73: Prefabricados Villahermosa | AC73: 56103638 | AD73: 6622041540 | AE73: 4 | AF73: ENTREGA DIRECTA | AG73: 1.273 | AH73: M3 | AI73: X | AJ73: 4 | AK73: V4 | AL73: 20230920 | AM73: D814-900004842-66322865-10000834-4
A74: 900004842D8146691404010191175 | B74: 4600035006-30 | C74: 4600035006 | D74: 30 | E74: MXPO | F74: MXL | G74: 900004842 | H74: TP-ED-MAROGU | I74: 5007923 | J74: COMERCIALIZADORA Y AGREG. MAROGU SA | K74: N90 | L74: (AP) NAFIN 90 Dias | M74: 10191175 | N74: GRAVA TRITURADA CALIZA 40MM - 1 1/2 NG | O74: D814 | P74: MX-CED. TABASCO | Q74: 20160818 | R74: 20241231 | S74: 20201120 | T74: 20291231 | U74: 520 | V74: MXN | W74: M3 | X74: 370 | Y74: MXN | Z74: M3 | AA74: 66914040 | AB74: INDCAPHER, S.A. DE C.V. | AC74: 56103637 | AD74: 6622041540 | AE74: 4 | AF74: ENTREGA DIRECTA | AG74: 1.72 | AH74: M3 | AI74: X | AJ74: 4 | AK74: V4 | AL74: 20230920 | AM74: D814-900004842-66914040-10191175-4
A75: 900003735D8146670203410000541 | B75: 4600041691-20 | C75: 4600041691 | D75: 20 | E75: MXPO | F75: MXL | G75: 900003735 | H75: TP-ED-LAZCANO HUERTA | I75: 5000326 | J75: LAZCANO HUERTA ROCIO NANCY | K75: Z09 | L75: (AP) 90 Dias | M75: 10000541 | N75: Grava Clasificada Río 10 mm - 3/8" | O75: D814 | P75: MX-CED. TABASCO | Q75: 20180405 | R75: 20241231 | S75: 20190529 | T75: 20241231 | U75: 330 | V75: MXN | W75: M3 | X75: 200.4 | Y75: MXN | Z75: M3 | AA75: 66702034 | AC75: 56103637 | AD75: 6622041540 | AE75: 4 | AF75: ENTREGA DIRECTA | AG75: 1.528 | AH75: M3 | AI75: X | AJ75: 4 | AK75: V4 | AL75: 20230920 | AM75: D814-900003735-66702034-10000541-4
A76: 900006706D8146516644810147454 | B76: 4600047553-50 | C76: 4600047553 | D76: 50 | E76: MXPO | F76: MXL | G76: 900006706 | H76: SF TP-ED-FRISO TEAPA | I76: 5070657 | J76: FRISO SILRO SA DE CV | K76: N90 | L76: (AP) NAFIN 90 Dias | M76: 10147454 | N76: GRAVA TRITURADA CALIZA 20 MM - 3/4" | O76: D814 | P76: MX-CED. TABASCO | Q76: 20200717 | R76: 20281231 | S76: 20221119 | T76: 20271231 | U76: 369 | V76: MXN | W76: M3 | X76: 139 | Y76: MXN | Z76: M3 | AA76: 65166448 | AB76: ARCOSA S.A. DE C.V. | AC76: 56103637 | AD76: 6622041540 | AE76: 4 | AF76: ENTREGA DIRECTA | AG76: 1.556 | AH76: M3 | AI76: X | AJ76: 4 | AK76: V4 | AL76: 20230920 | AM76: D814-900006706-65166448-10147454-4
A77: 900007054D8146686296110202196 | B77: 4600049598-70 | C77: 4600049598 | D77: 70 | E77: MXPO | F77: MXL | G77: 900007054 | H77: SF TP-ED-SAMUEL CARRASCO | I77: 5080454 | J77: CARRASCO ALCUDIA SAMUEL | K77: N90 | L77: (AP) NAFIN 90 Dias | M77: 10202196 | N77: LODO BENTONITICO-NG | O77: D814 | P77: MX-CED. TABASCO | Q77: 20210407 | R77: 20291231 | S77: 20210914 | T77: 20261231 | U77: 190 | V77: MXN | W77: M3 | X77: 134 | Y77: MXN | Z77: M3 | AA77: 66862961 | AB77: PILAS CIMESA REFINERIA (EAOG) | AC77: 56103590 | AD77: 6622041540 | AE77: 4 | AF77: ENTREGA DIRECTA | AG77: 1 | AH77: M3 | AI77: X | AJ77: 4 | AK77: V4 | AL77: 20230920 | AM77: D814-900007054-66862961-10202196-4
A78: 900007341D8146694653610201412 | B78: 4600052184-20 | C78: 4600052184 | D78: 20 | E78: MXPO | F78: MXL | G78: 900007341 | H78: SF TP-ED-ALFONSO ESPADAS | I78: 5079231 | J78: ESPADAS HERNANDEZ ALFONSO | K78: N90 | L78: (AP) NAFIN 90 Dias | M78: 10201412 | N78: REVESTIMIENTO ROJO 1 1/2 A 1 - NG | O78: D814 | P78: MX-CED. TABASCO | Q78: 20211009 | R78: 20281231 | S78: 20211009 | T78: 20261231 | U78: 500 | V78: MXN | W78: M3 | X78: 450 | Y78: MXN | Z78: M3 | AA78: 66946536 | AB78: P6 - Pulmón - Refinería Dos Bocas | AC78: 56103637 | AD78: 6622041540 | AE78: 4 | AF78: ENTREGA DIRECTA | AG78: 1.72 | AH78: M3 | AI78: X | AJ78: 4 | AK78: V4 | AL78: 20230920 | AM78: D814-900007341-66946536-10201412-4
A79: 900007341D8146711585110218414 | B79: 4600052184-80 | C79: 4600052184 | D79: 80 | E79: MXPO | F79: MXL | G79: 900007341 | H79: SF TP-ED-ALFONSO ESPADAS | I79: 5079231 | J79: ESPADAS HERNANDEZ ALFONSO | K79: N90 | L79: (AP) NAFIN 90 Dias | M79: 10218414 | N79: GRAVA DE RIO TRITURADA 20 MM | O79: D814 | P79: MX-CED. TABASCO | Q79: 20211009 | R79: 20281231 | S79: 20221222 | T79: 20271231 | U79: 658 | V79: MXN | W79: M3 | X79: 308 | Y79: MXN | Z79: M3 | AA79: 67115851 | AB79: COPI PARAISO | AC79: 56103637 | AD79: 6622041540 | AE79: 4 | AF79: ENTREGA DIRECTA | AG79: 1.515 | AH79: M3 | AI79: X | AJ79: 4 | AK79: V4 | AL79: 20230920 | AM79: D814-900007341-67115851-10218414-4
A80: 900007341D8146711585110197737 | B80: 4600052184-90 | C80: 4600052184 | D80: 90 | E80: MXPO | F80: MXL | G80: 900007341 | H80: SF TP-ED-ALFONSO ESPADAS | I80: 5079231 | J80: ESPADAS HERNANDEZ ALFONSO | K80: N90 | L80: (AP) NAFIN 90 Dias | M80: 10197737 | N80: ARENA CLASIFICADA RÍO MALLA 4- NG | O80: D814 | P80: MX-CED. TABASCO | Q80: 20211009 | R80: 20281231 | S80: 20221222 | T80: 20271231 | U80: 438 | V80: MXN | W80: M3 | X80: 308 | Y80: MXN | Z80: M3 | AA80: 67115851 | AB80: COPI PARAISO | AC80: 56103638 | AD80: 6622041867 | AE80: 4 | AF80: ENTREGA DIRECTA | AG80: 1.55 | AH80: M3 | AI80: X | AJ80: 4 | AK80: V4 | AL80: 20230920 | AM80: D814-900007341-67115851-10197737-4
A81: 900007376D8146694653610191175 | B81: 4600053375-10 | C81: 4600053375 | D81: 10 | E81: MXPO | F81: MXL | G81: 900007376 | H81: SF TP ED-JASSO | I81: 5070649 | J81: CARLOS CESAR JASSO RODRIGUEZ | K81: N90 | L81: (AP) NAFIN 90 Dias | M81: 10191175 | N81: GRAVA TRITURADA CALIZA 40MM - 1 1/2 NG | O81: D814 | P81: MX-CED. TABASCO | Q81: 20220307 | R81: 20271231 | S81: 20220307 | T81: 20271231 | U81: 590 | V81: MXN | W81: M3 | X81: 490 | Y81: MXN | Z81: M3 | AA81: 66946536 | AB81: P6 - Pulmón - Refinería Dos Bocas | AC81: 56103637 | AD81: 6622041540 | AE81: 4 | AF81: ENTREGA DIRECTA | AG81: 1.72 | AH81: M3 | AI81: X | AJ81: 4 | AK81: V4 | AL81: 20230920 | AM81: D814-900007376-66946536-10191175-4
A82: 900007491D8146616773110191255 | B82: 4600054838-30 | C82: 4600054838 | D82: 30 | E82: MXPO | F82: MXL | G82: 900007491 | H82: SF-TP-ED- AURELIO CABRERA | I82: 5082823 | J82: CABRERA MARIN AURELIO ANTONIO | K82: Z09 | L82: (AP) 90 Dias | M82: 10191255 | N82: GRAVA TRITURADA CALIZA 20MM-3/4 NG | O82: D814 | P82: MX-CED. TABASCO | Q82: 20220810 | R82: 20271231 | S82: 20221017 | T82: 20271231 | U82: 455 | V82: MXN | W82: M3 | X82: 355 | Y82: MXN | Z82: M3 | AA82: 66167731 | AB82: CONCRETAB (ECA) | AC82: 56103637 | AD82: 6622041540 | AE82: 4 | AF82: ENTREGA DIRECTA | AG82: 1.5 | AH82: M3 | AI82: X | AJ82: 4 | AK82: V4 | AL82: 20230920 | AM82: D814-900007491-66167731-10191255-4
A83: 900005557D8146657351410001643 | B83: 4600041437-60 | C83: 4600041437 | D83: 60 | E83: MXPO | F83: MXL | G83: 900005557 | H83: TP-ED-DANIEL BECERRA | I83: 5070594 | J83: BECERRA MAYORGA DANIEL | K83: N90 | L83: (AP) NAFIN 90 Dias | M83: 10001643 | N83: Crudo Clasificado Río | O83: D814 | P83: MX-CED. TABASCO | Q83: 20180307 | R83: 20241231 | S83: 20190201 | T83: 20241231 | U83: 487 | V83: MXN | W83: M3 | X83: 167 | Y83: MXN | Z83: M3 | AA83: 66573514 | AC83: 56103636 | AD83: 6622041540 | AE83: 4 | AF83: ENTREGA DIRECTA | AG83: 1.48 | AH83: M3 | AI83: X | AJ83: 4 | AK83: V4 | AL83: 20230920 | AM83: D814-900005557-66573514-10001643-4
A84: 900003735D8146677929210000541 | B84: 4600041691-30 | C84: 4600041691 | D84: 30 | E84: MXPO | F84: MXL | G84: 900003735 | H84: TP-ED-LAZCANO HUERTA | I84: 5000326 | J84: LAZCANO HUERTA ROCIO NANCY | K84: Z09 | L84: (AP) 90 Dias | M84: 10000541 | N84: Grava Clasificada Río 10 mm - 3/8" | O84: D814 | P84: MX-CED. TABASCO | Q84: 20180405 | R84: 20241231 | S84: 20190529 | T84: 20241231 | U84: 330 | V84: MXN | W84: M3 | X84: 200.4 | Y84: MXN | Z84: M3 | AA84: 66779292 | AB84: CP-I GRAVA DE 3/8 MECTAB (EAOG) | AC84: 56103637 | AD84: 6622041540 | AE84: 4 | AF84: ENTREGA DIRECTA | AG84: 1.528 | AH84: M3 | AI84: X | AJ84: 4 | AK84: V4 | AL84: 20230920 | AM84: D814-900003735-66779292-10000541-4
A85: 900006706D8146705845510147454 | B85: 4600047553-340 | C85: 4600047553 | D85: 340 | E85: MXPO | F85: MXL | G85: 900006706 | H85: SF TP-ED-FRISO TEAPA | I85: 5070657 | J85: FRISO SILRO SA DE CV | K85: N90 | L85: (AP) NAFIN 90 Dias | M85: 10147454 | N85: GRAVA TRITURADA CALIZA 20 MM - 3/4" | O85: D814 | P85: MX-CED. TABASCO | Q85: 20200717 | R85: 20281231 | S85: 20220608 | T85: 20271231 | U85: 506 | V85: MXN | W85: M3 | X85: 296 | Y85: MXN | Z85: M3 | AA85: 67058455 | AB85: LA CRUZ AZUL PLANTA COMALCALCO | AC85: 56103637 | AD85: 6622041540 | AE85: 4 | AF85: ENTREGA DIRECTA | AG85: 1.556 | AH85: M3 | AI85: X | AJ85: 4 | AK85: V4 | AL85: 20230920 | AM85: D814-900006706-67058455-10147454-4
A86: 900006706D8146658035110147454 | B86: 4600047553-370 | C86: 4600047553 | D86: 370 | E86: MXPO | F86: MXL | G86: 900006706 | H86: SF TP-ED-FRISO TEAPA | I86: 5070657 | J86: FRISO SILRO SA DE CV | K86: N90 | L86: (AP) NAFIN 90 Dias | M86: 10147454 | N86: GRAVA TRITURADA CALIZA 20 MM - 3/4" | O86: D814 | P86: MX-CED. TABASCO | Q86: 20200717 | R86: 20281231 | S86: 20220721 | T86: 20271231 | U86: 384 | V86: MXN | W86: M3 | X86: 154 | Y86: MXN | Z86: M3 | AA86: 66580351 | AB86: COLVI VILLAHERMOSA | AC86: 56103637 | AD86: 6622041540 | AE86: 4 | AF86: ENTREGA DIRECTA | AG86: 1.556 | AH86: M3 | AI86: X | AJ86: 4 | AK86: V4 | AL86: 20230920 | AM86: D814-900006706-66580351-10147454-4
A87: 900006706D8146710668810147454 | B87: 4600047553-410 | C87: 4600047553 | D87: 410 | E87: MXPO | F87: MXL | G87: 900006706 | H87: SF TP-ED-FRISO TEAPA | I87: 5070657 | J87: FRISO SILRO SA DE CV | K87: N90 | L87: (AP) NAFIN 90 Dias | M87: 10147454 | N87: GRAVA TRITURADA CALIZA 20 MM - 3/4" | O87: D814 | P87: MX-CED. TABASCO | Q87: 20200717 | R87: 20281231 | S87: 20221101 | T87: 20271231 | U87: 369 | V87: MXN | W87: M3 | X87: 169 | Y87: MXN | Z87: M3 | AA87: 67106688 | AB87: BASALTOS ARCOSA GEN | AC87: 56103637 | AD87: 6622041540 | AE87: 4 | AF87: ENTREGA DIRECTA | AG87: 1.556 | AH87: M3 | AI87: X | AJ87: 4 | AK87: V4 | AL87: 20230920 | AM87: D814-900006706-67106688-10147454-4
A88: 900007621D8146705845510147454 | B88: 4600054022-20 | C88: 4600054022 | D88: 20 | E88: MXPO | F88: MXL | G88: 900007621 | H88: SF TP-ED-FRISO CONSMIN TAB | I88: 5083592 | J88: FRISO CONSMIN SA DE CV | K88: N45 | L88: (AP) NAFIN 45 Dias | M88: 10147454 | N88: GRAVA TRITURADA CALIZA 20 MM - 3/4" | O88: D814 | P88: MX-CED. TABASCO | Q88: 20220523 | R88: 20291231 | S88: 20220608 | T88: 20271231 | U88: 506 | V88: MXN | W88: M3 | X88: 296 | Y88: MXN | Z88: M3 | AA88: 67058455 | AB88: LA CRUZ AZUL PLANTA COMALCALCO | AC88: 56103637 | AD88: 6622041540 | AE88: 4 | AF88: ENTREGA DIRECTA | AG88: 1.556 | AH88: M3 | AI88: X | AJ88: 4 | AK88: V4 | AL88: 20230920 | AM88: D814-900007621-67058455-10147454-4
A89: 900007621D8146710668810147454 | B89: 4600054100-40 | C89: 4600054100 | D89: 40 | E89: MXPO | F89: MXL | G89: 900007621 | H89: SF TP-ED-FRISO CONSMIN TAB | I89: 5083592 | J89: FRISO CONSMIN SA DE CV | K89: N45 | L89: (AP) NAFIN 45 Dias | M89: 10147454 | N89: GRAVA TRITURADA CALIZA 20 MM - 3/4" | O89: D814 | P89: MX-CED. TABASCO | Q89: 20220602 | R89: 20281231 | S89: 20221101 | T89: 20271231 | U89: 369 | V89: MXN | W89: M3 | X89: 169 | Y89: MXN | Z89: M3 | AA89: 67106688 | AB89: BASALTOS ARCOSA GEN | AC89: 56103637 | AD89: 6622041540 | AE89: 4 | AF89: ENTREGA DIRECTA | AG89: 1.556 | AH89: M3 | AI89: X | AJ89: 4 | AK89: V4 | AL89: 20230920 | AM89: D814-900007621-67106688-10147454-4
A90: 900007491D8146516644810123034 | B90: 4600054838-40 | C90: 4600054838 | D90: 40 | E90: MXPO | F90: MXL | G90: 900007491 | H90: SF-TP-ED- AURELIO CABRERA | I90: 5082823 | J90: CABRERA MARIN AURELIO ANTONIO | K90: Z09 | L90: (AP) 90 Dias | M90: 10123034 | N90: ARENA TRITURADA CALIZA MALLA 4 | O90: D814 | P90: MX-CED. TABASCO | Q90: 20220810 | R90: 20271231 | S90: 20221119 | T90: 20271231 | U90: 345 | V90: MXN | W90: M3 | X90: 265 | Y90: MXN | Z90: M3 | AA90: 65166448 | AB90: ARCOSA S.A. DE C.V. | AC90: 56103638 | AD90: 6622041540 | AE90: 4 | AF90: ENTREGA DIRECTA | AG90: 1.528 | AH90: M3 | AI90: X | AJ90: 4 | AK90: V4 | AL90: 20230920 | AM90: D814-900007491-65166448-10123034-4
A91: 900006706D8146687594810191255 | B91: 4600047553-240 | C91: 4600047553 | D91: 240 | E91: MXPO | F91: MXL | G91: 900006706 | H91: SF TP-ED-FRISO TEAPA | I91: 5070657 | J91: FRISO SILRO SA DE CV | K91: N90 | L91: (AP) NAFIN 90 Dias | M91: 10191255 | N91: GRAVA TRITURADA CALIZA 20MM-3/4 NG | O91: D814 | P91: MX-CED. TABASCO | Q91: 20200717 | R91: 20281231 | S91: 20211008 | T91: 20261231 | U91: 514 | V91: MXN | W91: M3 | X91: 324 | Y91: MXN | Z91: M3 | AA91: 66875948 | AB91: COGENERACIÓN TECHINT REF | AC91: 56103637 | AD91: 6622041540 | AE91: 4 | AF91: ENTREGA DIRECTA | AG91: 1.5 | AH91: M3 | AI91: X | AJ91: 4 | AK91: V4 | AL91: 20230920 | AM91: D814-900006706-66875948-10191255-4
A92: 900007054D8146694653610000861 | B92: 4600049598-10 | C92: 4600049598 | D92: 10 | E92: MXPO | F92: MXL | G92: 900007054 | H92: SF TP-ED-SAMUEL CARRASCO | I92: 5080454 | J92: CARRASCO ALCUDIA SAMUEL | K92: N90 | L92: (AP) NAFIN 90 Dias | M92: 10000861 | N92: Base H Triturada Caliza 1 1/2" a Finos | O92: D814 | P92: MX-CED. TABASCO | Q92: 20210407 | R92: 20291231 | S92: 20210407 | T92: 20261231 | U92: 490 | V92: MXN | W92: M3 | X92: 335 | Y92: MXN | Z92: M3 | AA92: 66946536 | AB92: P6 - Pulmón - Refinería Dos Bocas | AC92: 56103590 | AD92: 6622041540 | AE92: 4 | AF92: ENTREGA DIRECTA | AG92: 1.52 | AH92: M3 | AI92: X | AJ92: 4 | AK92: V4 | AL92: 20230920 | AM92: D814-900007054-66946536-10000861-4
A93: 900007054D8146694653610210039 | B93: 4600049598-140 | C93: 4600049598 | D93: 140 | E93: MXPO | F93: MXL | G93: 900007054 | H93: SF TP-ED-SAMUEL CARRASCO | I93: 5080454 | J93: CARRASCO ALCUDIA SAMUEL | K93: N90 | L93: (AP) NAFIN 90 Dias | M93: 10210039 | N93: ARENA CLASIFICADA RÍO MALLA 4 | O93: D814 | P93: MX-CED. TABASCO | Q93: 20210407 | R93: 20291231 | S93: 20230607 | T93: 20281231 | U93: 244 | V93: MXN | W93: M3 | X93: 174 | Y93: MXN | Z93: M3 | AA93: 66946536 | AB93: P6 - Pulmón - Refinería Dos Bocas | AC93: 56103638 | AD93: 6622041540 | AE93: 4 | AF93: ENTREGA DIRECTA | AG93: 1.485 | AH93: M3 | AI93: X | AJ93: 4 | AK93: V4 | AL93: 20230920 | AM93: D814-900007054-66946536-10210039-4
A94: 900004613D8146688638110000541 | B94: 4600050018-20 | C94: 4600050018 | D94: 20 | E94: MXPO | F94: MXL | G94: 900004613 | H94: TP-ED-TALLER ORTIZ | I94: 5062978 | J94: TALLERES Y TRANSPORTES SA DE CV | K94: N90 | L94: (AP) NAFIN 90 Dias | M94: 10000541 | N94: Grava Clasificada Río 10 mm - 3/8" | O94: D814 | P94: MX-CED. TABASCO | Q94: 20210517 | R94: 20261231 | S94: 20210831 | T94: 20261231 | U94: 470 | V94: MXN | W94: M3 | X94: 340 | Y94: MXN | Z94: M3 | AA94: 66886381 | AB94: CONCRETEC VILLAHERMOSA | AC94: 56103637 | AD94: 6622041540 | AE94: 4 | AF94: ENTREGA DIRECTA | AG94: 1.528 | AH94: M3 | AI94: X | AJ94: 4 | AK94: V4 | AL94: 20230920 | AM94: D814-900004613-66886381-10000541-4
A95: 900007341D8146694653610000861 | B95: 4600052184-60 | C95: 4600052184 | D95: 60 | E95: MXPO | F95: MXL | G95: 900007341 | H95: SF TP-ED-ALFONSO ESPADAS | I95: 5079231 | J95: ESPADAS HERNANDEZ ALFONSO | K95: N90 | L95: (AP) NAFIN 90 Dias | M95: 10000861 | N95: Base H Triturada Caliza 1 1/2" a Finos | O95: D814 | P95: MX-CED. TABASCO | Q95: 20211009 | R95: 20281231 | S95: 20220317 | T95: 20271231 | U95: 495 | V95: MXN | W95: M3 | X95: 395 | Y95: MXN | Z95: M3 | AA95: 66946536 | AB95: P6 - Pulmón - Refinería Dos Bocas | AC95: 56103590 | AD95: 6622041540 | AE95: 4 | AF95: ENTREGA DIRECTA | AG95: 1.52 | AH95: M3 | AI95: X | AJ95: 4 | AK95: V4 | AL95: 20230920 | AM95: D814-900007341-66946536-10000861-4
... A147: 900007054D8146704594010191175 | B147: 4600049598-110 | C147: 4600049598 | D147: 110 | E147: MXPO | F147: MXL | G147: 900007054 | H147: SF TP-ED-SAMUEL CARRASCO | I147: 5080454 | J147: CARRASCO ALCUDIA SAMUEL | K147: N90 | L147: (AP) NAFIN 90 Dias | M147: 10191175 | N147: GRAVA TRITURADA CALIZA 40MM - 1 1/2 NG | O147: D814 | P147: MX-CED. TABASCO | Q147: 20210407 | R147: 20291231 | S147: 20220429 | T147: 20271231 | U147: 585 | V147: MXN | W147: M3 | X147: 485 | Y147: MXN | Z147: M3 | AA147: 67045940 | AB147: CEMENTO COGENERACION (EAOG) | AC147: 56103637 | AD147: 6622041540 | AE147: 4 | AF147: ENTREGA DIRECTA | AG147: 1.72 | AH147: M3 | AI147: X | AJ147: 4 | AK147: V4 | AL147: 20230920 | AM147: D814-900007054-67045940-10191175-4
A148: 900007954D81410191076 | B148: 4600056016-10 | C148: 4600056016 | D148: 10 | E148: MXPO | F148: MXL | G148: 900007954 | H148: SF TP-BANCO GARCIA | I148: 5067302 | J148: GARCIA BALTAZAR MIGUEL | K148: N90 | L148: (AP) NAFIN 90 Dias | M148: 10191076 | N148: ARENA RIO LIMOSA NG | O148: D814 | P148: MX-CED. TABASCO | Q148: 20221220 | R148: 20281231 | S148: 20231124 | T148: 20281231 | U148: 65 | V148: MXN | W148: M3 | X148: 0 | Y148: MXN | Z148: M3 | AC148: 56103638 | AD148: 6622041540 | AE148: 1 | AF148: ENTREGADO | AG148: 1.52 | AH148: M3 | AI148: X | AJ148: 4 | AK148: V4 | AL148: 20231128 | AM148: D814-900007954-10191076
A149: 900006568D81410079650 | B149: 4600047552-10 | C149: 4600047552 | D149: 10 | E149: MXPO | F149: MXL | G149: 900006568 | H149: SF TP-ENLACES CORPORATIVOS | I149: 5078187 | J149: ENLACE CORPORATIVO DEL SURESTE | K149: N90 | L149: (AP) NAFIN 90 Dias | M149: 10079650 | N149: ARENA DE RIO MALLA 4 | O149: D814 | P149: MX-CED. TABASCO | Q149: 20200717 | R149: 20301231 | S149: 20200717 | T149: 20301231 | U149: 46 | V149: MXN | W149: M3 | AC149: 56103638 | AD149: 6622041540 | AE149: 1 | AF149: ENTREGADO | AG149: 1.448 | AH149: M3 | AI149: X | AJ149: 4 | AK149: V4 | AL149: 20230920 | AM149: D814-900006568-10079650
A150: 900006409D8146731351010147454 | B150: 4600071076-20 | C150: 4600071076 | D150: 20 | E150: MXPO | F150: MXL | G150: 900006409 | H150: SF TP-ED-GOLPAC | I150: 5041845 | J150: CONSTRUCCIONES Y URBANIZACIONES | K150: Z03 | L150: (AP) 15 Dias | M150: 10147454 | N150: GRAVA TRITURADA CALIZA 20 MM - 3/4" | O150: D814 | P150: MX-CED. TABASCO | Q150: 20250325 | R150: 20301231 | S150: 20250414 | T150: 20301231 | U150: 684 | V150: MXN | W150: M3 | X150: 389 | Y150: MXN | Z150: M3 | AA150: 67313510 | AB150: OBRA NEXUMRAIL | AC150: 56103637 | AD150: 6622041540 | AE150: 4 | AF150: ENTREGA DIRECTA | AG150: 1.556 | AH150: M3 | AI150: X | AJ150: 4 | AK150: V4 | AL150: 20250415 | AM150: D814-900006409-67313510-10147454-4
A151: 900006409D8146731351010030634 | B151: 4600071076-40 | C151: 4600071076 | D151: 40 | E151: MXPO | F151: MXL | G151: 900006409 | H151: SF TP-ED-GOLPAC | I151: 5041845 | J151: CONSTRUCCIONES Y URBANIZACIONES | K151: Z03 | L151: (AP) 15 Dias | M151: 10030634 | N151: Arena Clasificada Río 1813 | O151: D814 | P151: MX-CED. TABASCO | Q151: 20250325 | R151: 20301231 | S151: 20250414 | T151: 20301231 | U151: 265 | V151: MXN | W151: M3 | X151: 190 | Y151: MXN | Z151: M3 | AA151: 67313510 | AB151: OBRA NEXUMRAIL | AC151: 56103638 | AD151: 6622041540 | AE151: 4 | AF151: ENTREGA DIRECTA | AG151: 2.4 | AH151: M3 | AI151: X | AJ151: 4 | AK151: V4 | AL151: 20250415 | AM151: D814-900006409-67313510-10030634-4
A152: 900008332D81410193885 | B152: 4600058331-30 | C152: 4600058331 | D152: 30 | E152: MXPO | F152: MXL | G152: 900008332 | H152: SF TP- HOLCIM RZ | I152: 5075390 | J152: CORPORACION ANRROCA SA DE CV | K152: E90 | L152: (AP) E-FACTOR 90 Dias | M152: 10193885 | N152: BASE H CALIZA GRIS 1 1/2 PARA PATIO NG | O152: D814 | P152: MX-CED. TABASCO | Q152: 20230810 | R152: 20281231 | S152: 20230818 | T152: 20281231 | U152: 240 | V152: MXN | W152: M3 | X152: 0 | Y152: MXN | Z152: M3 | AC152: 56103590 | AD152: 6622041540 | AE152: 1 | AF152: ENTREGADO | AG152: 1.52 | AH152: M3 | AI152: X | AJ152: 4 | AK152: V4 | AL152: 20230920 | AM152: D814-900008332-10193885
A153: 900007341D8146687594810000861 | B153: 4600052184-30 | C153: 4600052184 | D153: 30 | E153: MXPO | F153: MXL | G153: 900007341 | H153: SF TP-ED-ALFONSO ESPADAS | I153: 5079231 | J153: ESPADAS HERNANDEZ ALFONSO | K153: N90 | L153: (AP) NAFIN 90 Dias | M153: 10000861 | N153: Base H Triturada Caliza 1 1/2" a Finos | O153: D814 | P153: MX-CED. TABASCO | Q153: 20211009 | R153: 20281231 | S153: 20220111 | T153: 20271231 | U153: 535 | V153: MXN | W153: M3 | X153: 304 | Y153: MXN | Z153: M3 | AA153: 66875948 | AB153: COGENERACIÓN TECHINT REF | AC153: 56103590 | AD153: 6622041540 | AE153: 4 | AF153: ENTREGA DIRECTA | AG153: 1.52 | AH153: M3 | AI153: X | AJ153: 4 | AK153: V4 | AL153: 20230920 | AM153: D814-900007341-66875948-10000861-4
A154: 900007341D8146711393810191175 | B154: 4600052184-130 | C154: 4600052184 | D154: 130 | E154: MXPO | F154: MXL | G154: 900007341 | H154: SF TP-ED-ALFONSO ESPADAS | I154: 5079231 | J154: ESPADAS HERNANDEZ ALFONSO | K154: N90 | L154: (AP) NAFIN 90 Dias | M154: 10191175 | N154: GRAVA TRITURADA CALIZA 40MM - 1 1/2 NG | O154: D814 | P154: MX-CED. TABASCO | Q154: 20211009 | R154: 20281231 | S154: 20230315 | T154: 20281231 | U154: 690 | V154: MXN | W154: M3 | X154: 590 | Y154: MXN | Z154: M3 | AA154: 67113938 | AB154: Bateria de separacion tecominoacan | AC154: 56103637 | AD154: 6622041540 | AE154: 1 | AF154: ENTREGADO | AG154: 1.72 | AH154: M3 | AI154: X | AJ154: 4 | AK154: V4 | AL154: 20230920 | AM154: D814-900007341-10191175
A155: 900008332D81410147454 | B155: 4600058331-10 | C155: 4600058331 | D155: 10 | E155: MXPO | F155: MXL | G155: 900008332 | H155: SF TP- HOLCIM RZ | I155: 5075390 | J155: CORPORACION ANRROCA SA DE CV | K155: E90 | L155: (AP) E-FACTOR 90 Dias | M155: 10147454 | N155: GRAVA TRITURADA CALIZA 20 MM - 3/4" | O155: D814 | P155: MX-CED. TABASCO | Q155: 20230810 | R155: 20281231 | S155: 20230810 | T155: 20281231 | U155: 350 | V155: MXN | W155: M3 | X155: 0 | Y155: MXN | Z155: M3 | AC155: 56103637 | AD155: 6622041540 | AE155: 1 | AF155: ENTREGADO | AG155: 1.556 | AH155: M3 | AI155: X | AJ155: 4 | AK155: V4 | AL155: 20230920 | AM155: D814-900008332-10147454
A156: 900008332D81410183939 | B156: 4600058331-20 | C156: 4600058331 | D156: 20 | E156: MXPO | F156: MXL | G156: 900008332 | H156: SF TP- HOLCIM RZ | I156: 5075390 | J156: CORPORACION ANRROCA SA DE CV | K156: E90 | L156: (AP) E-FACTOR 90 Dias | M156: 10183939 | N156: BASE HIDRÁULICA 1 1/2" A FINOS 70/30 | O156: D814 | P156: MX-CED. TABASCO | Q156: 20230810 | R156: 20281231 | S156: 20230818 | T156: 20281231 | U156: 240 | V156: MXN | W156: M3 | X156: 0 | Y156: MXN | Z156: M3 | AC156: 56103590 | AD156: 6622041540 | AE156: 1 | AF156: ENTREGADO | AG156: 2.136 | AH156: M3 | AI156: X | AJ156: 4 | AK156: V4 | AL156: 20230920 | AM156: D814-900008332-10183939
A157: 900007621D8146694653610173716 | B157: 4600054022-30 | C157: 4600054022 | D157: 30 | E157: MXPO | F157: MXL | G157: 900007621 | H157: SF TP-ED-FRISO CONSMIN TAB | I157: 5083592 | J157: FRISO CONSMIN SA DE CV | K157: N45 | L157: (AP) NAFIN 45 Dias | M157: 10173716 | N157: GRAVON DE 4" A 2" - NG | O157: D814 | P157: MX-CED. TABASCO | Q157: 20220523 | R157: 20291231 | S157: 20230105 | T157: 20271231 | U157: 522.4 | V157: MXN | W157: M3 | X157: 428 | Y157: MXN | Z157: M3 | AA157: 66946536 | AB157: P6 - Pulmón - Refinería Dos Bocas | AC157: 56103637 | AD157: 6622041540 | AE157: 4 | AF157: ENTREGA DIRECTA | AG157: 1.235 | AH157: M3 | AI157: X | AJ157: 4 | AK157: V4 | AL157: 20230920 | AM157: D814-900007621-66946536-10173716-4
A158: 900007621D8146694653610193885 | B158: 4600054022-40 | C158: 4600054022 | D158: 40 | E158: MXPO | F158: MXL | G158: 900007621 | H158: SF TP-ED-FRISO CONSMIN TAB | I158: 5083592 | J158: FRISO CONSMIN SA DE CV | K158: N45 | L158: (AP) NAFIN 45 Dias | M158: 10193885 | N158: BASE H CALIZA GRIS 1 1/2 PARA PATIO NG | O158: D814 | P158: MX-CED. TABASCO | Q158: 20220523 | R158: 20291231 | S158: 20230105 | T158: 20271231 | U158: 522.4 | V158: MXN | W158: M3 | X158: 428 | Y158: MXN | Z158: M3 | AA158: 66946536 | AB158: P6 - Pulmón - Refinería Dos Bocas | AC158: 56103590 | AD158: 6622041540 | AE158: 4 | AF158: ENTREGA DIRECTA | AG158: 1.52 | AH158: M3 | AI158: X | AJ158: 4 | AK158: V4 | AL158: 20230920 | AM158: D814-900007621-66946536-10193885-4
A159: 900007491D8146688638110191255 | B159: 4600054838-20 | C159: 4600054838 | D159: 20 | E159: MXPO | F159: MXL | G159: 900007491 | H159: SF-TP-ED- AURELIO CABRERA | I159: 5082823 | J159: CABRERA MARIN AURELIO ANTONIO | K159: Z09 | L159: (AP) 90 Dias | M159: 10191255 | N159: GRAVA TRITURADA CALIZA 20MM-3/4 NG | O159: D814 | P159: MX-CED. TABASCO | Q159: 20220810 | R159: 20271231 | S159: 20221017 | T159: 20271231 | U159: 585 | V159: MXN | W159: M3 | X159: 485 | Y159: MXN | Z159: M3 | AA159: 66886381 | AB159: CONCRETEC VILLAHERMOSA | AC159: 56103637 | AD159: 6622041540 | AE159: 4 | AF159: ENTREGA DIRECTA | AG159: 1.5 | AH159: M3 | AI159: X | AJ159: 4 | AK159: V4 | AL159: 20230920 | AM159: D814-900007491-66886381-10191255-4
A160: 900007950D81410210260 | B160: 4600069891-30 | C160: 4600069891 | D160: 30 | E160: MXPO | F160: MXL | G160: 900007950 | H160: SF TP-TRAPA | I160: 5087333 | J160: GARCIA MONTILLA VICTOR DAVID | K160: Z09 | L160: (AP) 90 Dias | M160: 10210260 | N160: GRAVA TRITURADA CALIZA 20MM - 3/4" | O160: D814 | P160: MX-CED. TABASCO | Q160: 20240719 | R160: 20291231 | S160: 20240719 | T160: 20291231 | U160: 210 | V160: MXN | W160: M3 | X160: 0 | Y160: MXN | Z160: M3 | AC160: 56103637 | AD160: 6622041540 | AE160: 1 | AF160: ENTREGADO | AG160: 1.491 | AH160: M3 | AI160: X | AJ160: 4 | AK160: V4 | AL160: 20240725 | AM160: D814-900007950-10210260
A161: 900009035D8146729810410000273 | B161: 4600070543-40 | C161: 4600070543 | D161: 40 | E161: MXPO | F161: MXL | G161: 900009035 | H161: SF TP-ED- GRUPO AF | I161: 5094278 | J161: LOGISTICA Y SERVICIOS ESPECIALIZADO | K161: Z09 | L161: (AP) 90 Dias | M161: 10000273 | N161: Base H Triturada Caliza 3/4" a Finos | O161: D814 | P161: MX-CED. TABASCO | Q161: 20241115 | R161: 20291231 | S161: 20241217 | T161: 20291231 | U161: 660 | V161: MXN | W161: M3 | X161: 340 | Y161: MXN | Z161: M3 | AA161: 67298104 | AB161: OBRA SAFINEIA | AC161: 56103590 | AD161: 6622041540 | AE161: 4 | AF161: ENTREGA DIRECTA | AG161: 1.69 | AH161: M3 | AI161: X | AJ161: 4 | AK161: V4 | AL161: 20250114 | AM161: D814-900009035-67298104-10000273-4
A162: 900007620D81410000273 | B162: 4600054015-60 | C162: 4600054015 | D162: 60 | E162: MXPO | F162: MXL | G162: 900007620 | H162: SF TP-FRISO CONSMIN TAB | I162: 5083592 | J162: FRISO CONSMIN SA DE CV | K162: N45 | L162: (AP) NAFIN 45 Dias | M162: 10000273 | N162: Base H Triturada Caliza 3/4" a Finos | O162: D814 | P162: MX-CED. TABASCO | Q162: 20220519 | R162: 20291231 | S162: 20241217 | T162: 20291231 | U162: 290 | V162: MXN | W162: M3 | X162: 0 | Y162: MXN | Z162: M3 | AC162: 56103590 | AD162: 6622041540 | AE162: 2 | AF162: RECOGIDO | AG162: 1.69 | AH162: M3 | AJ162: 4 | AK162: V4 | AL162: 20250104 | AM162: D814-900007620-10000273
A163: 900009035D8146729523310183939 | B163: 4600070543-30 | C163: 4600070543 | D163: 30 | E163: MXPO | F163: MXL | G163: 900009035 | H163: SF TP-ED- GRUPO AF | I163: 5094278 | J163: LOGISTICA Y SERVICIOS ESPECIALIZADO | K163: Z09 | L163: (AP) 90 Dias | M163: 10183939 | N163: BASE HIDRÁULICA 1 1/2" A FINOS 70/30 | O163: D814 | P163: MX-CED. TABASCO | Q163: 20241115 | R163: 20291231 | S163: 20241217 | T163: 20291231 | U163: 675 | V163: MXN | W163: M3 | X163: 400 | Y163: MXN | Z163: M3 | AA163: 67295233 | AB163: C2402 PAVIMENTACION ASIPONA (AOO) | AC163: 56103590 | AD163: 6622041540 | AE163: 4 | AF163: ENTREGA DIRECTA | AG163: 2.136 | AH163: M3 | AI163: X | AJ163: 4 | AK163: V4 | AL163: 20250104 | AM163: D814-900009035-67295233-10183939-4
...
