Workbook

Sheet Base Cedis DW68
N1: VENTA | Q1: COSTO
A2: CONCAT1 | B2: CONCAT2 | C2: No. SF | D2: Nombre SF | E2: Cedis | F2: Destino | G2: Condicion de Expedicion | H2: Nombre Destino | I2: No. de material | J2: Nombre de material | K2: PV | L2: Inicio de vigencia | M2: Fin de vigencia | N2: Importe MP | O2: Importe Flete | P2: UM Venta | Q2: Importe Costo | R2: UM Costo | S2: Validacion 1 | T2: Validacion 2
A3: =CONCATENATE(C3,E3,F3,I3) | B3: =CONCATENATE(C3,E3,I3) | C3: 900000085 | D3: =IFERROR(VLOOKUP(C3,TRAOPE!$G:$H,2,0),"") | E3: DW68 | F3: D042 | G3: =IFERROR(VLOOKUP(A3,Flete!$A:$E,5,0),"") | H3: =IFERROR(VLOOKUP(F3,TRAOPE!$AA:$AB,2,0),"") | I3: 10000191 | J3: =IFERROR(VLOOKUP(I3,Materiales!$A:$H,8,0),"") | K3: =IFERROR(VLOOKUP(I3,Materiales!$A:$G,7,0),"") | L3: 20220516 | M3: 20251031 | N3: 124.11 | O3: =IFERROR(VLOOKUP(A3,Flete!$A:$J,10,0),"") | P3: TN | Q3: =IFERROR(IFERROR(VLOOKUP(A3,TRAOPE!$A:$U,21,0),VLOOKUP(B3,TRAOPE!$A:$U,21,0)),"") | R3: =IFERROR(IFERROR(VLOOKUP(A3,TRAOPE!$A:$W,23,0),VLOOKUP(B3,TRAOPE!$A:$W,23,0)),"") | S3: =IF(AND(P3="TN",R3="TN"),N3+N(O3),IF(G3&""="1",N(K3)*N3,(N3+N(O3))*N(K3))) | T3: =IF(Q3="","",Q3-S3)
A4: =CONCATENATE(C4,E4,F4,I4) | B4: =CONCATENATE(C4,E4,I4) | C4: 900000085 | D4: =IFERROR(VLOOKUP(C4,TRAOPE!$G:$H,2,0),"") | E4: DW68 | F4: D042 | G4: =IFERROR(VLOOKUP(A4,Flete!$A:$E,5,0),"") | H4: =IFERROR(VLOOKUP(F4,TRAOPE!$AA:$AB,2,0),"") | I4: 10110630 | J4: =IFERROR(VLOOKUP(I4,Materiales!$A:$H,8,0),"") | K4: =IFERROR(VLOOKUP(I4,Materiales!$A:$G,7,0),"") | L4: 20220516 | M4: 20251031 | N4: 155.26 | O4: =IFERROR(VLOOKUP(A4,Flete!$A:$J,10,0),"") | P4: TN | Q4: =IFERROR(IFERROR(VLOOKUP(A4,TRAOPE!$A:$U,21,0),VLOOKUP(B4,TRAOPE!$A:$U,21,0)),"") | R4: =IFERROR(IFERROR(VLOOKUP(A4,TRAOPE!$A:$W,23,0),VLOOKUP(B4,TRAOPE!$A:$W,23,0)),"") | S4: =IF(AND(P4="TN",R4="TN"),N4+N(O4),IF(G4&""="1",N(K4)*N4,(N4+N(O4))*N(K4))) | T4: =IF(Q4="","",Q4-S4)
A5: =CONCATENATE(C5,E5,F5,I5) | B5: =CONCATENATE(C5,E5,I5) | C5: 900000085 | D5: =IFERROR(VLOOKUP(C5,TRAOPE!$G:$H,2,0),"") | E5: DW68 | F5: D042 | G5: =IFERROR(VLOOKUP(A5,Flete!$A:$E,5,0),"") | H5: =IFERROR(VLOOKUP(F5,TRAOPE!$AA:$AB,2,0),"") | I5: 10141571 | J5: =IFERROR(VLOOKUP(I5,Materiales!$A:$H,8,0),"") | K5: =IFERROR(VLOOKUP(I5,Materiales!$A:$G,7,0),"") | L5: 20220516 | M5: 20251031 | N5: 231.34 | O5: =IFERROR(VLOOKUP(A5,Flete!$A:$J,10,0),"") | P5: TN | Q5: =IFERROR(IFERROR(VLOOKUP(A5,TRAOPE!$A:$U,21,0),VLOOKUP(B5,TRAOPE!$A:$U,21,0)),"") | R5: =IFERROR(IFERROR(VLOOKUP(A5,TRAOPE!$A:$W,23,0),VLOOKUP(B5,TRAOPE!$A:$W,23,0)),"") | S5: =IF(AND(P5="TN",R5="TN"),N5+N(O5),IF(G5&""="1",N(K5)*N5,(N5+N(O5))*N(K5))) | T5: =IF(Q5="","",Q5-S5)
A6: =CONCATENATE(C6,E6,F6,I6) | B6: =CONCATENATE(C6,E6,I6) | C6: 900000085 | D6: =IFERROR(VLOOKUP(C6,TRAOPE!$G:$H,2,0),"") | E6: DW68 | F6: D209 | G6: =IFERROR(VLOOKUP(A6,Flete!$A:$E,5,0),"") | H6: =IFERROR(VLOOKUP(F6,TRAOPE!$AA:$AB,2,0),"") | I6: 10000191 | J6: =IFERROR(VLOOKUP(I6,Materiales!$A:$H,8,0),"") | K6: =IFERROR(VLOOKUP(I6,Materiales!$A:$G,7,0),"") | L6: 20220516 | M6: 20251031 | N6: 124.11 | O6: =IFERROR(VLOOKUP(A6,Flete!$A:$J,10,0),"") | P6: TN | Q6: =IFERROR(IFERROR(VLOOKUP(A6,TRAOPE!$A:$U,21,0),VLOOKUP(B6,TRAOPE!$A:$U,21,0)),"") | R6: =IFERROR(IFERROR(VLOOKUP(A6,TRAOPE!$A:$W,23,0),VLOOKUP(B6,TRAOPE!$A:$W,23,0)),"") | S6: =IF(AND(P6="TN",R6="TN"),N6+N(O6),IF(G6&""="1",N(K6)*N6,(N6+N(O6))*N(K6))) | T6: =IF(Q6="","",Q6-S6)
A7: =CONCATENATE(C7,E7,F7,I7) | B7: =CONCATENATE(C7,E7,I7) | C7: 900000085 | D7: =IFERROR(VLOOKUP(C7,TRAOPE!$G:$H,2,0),"") | E7: DW68 | F7: D209 | G7: =IFERROR(VLOOKUP(A7,Flete!$A:$E,5,0),"") | H7: =IFERROR(VLOOKUP(F7,TRAOPE!$AA:$AB,2,0),"") | I7: 10110630 | J7: =IFERROR(VLOOKUP(I7,Materiales!$A:$H,8,0),"") | K7: =IFERROR(VLOOKUP(I7,Materiales!$A:$G,7,0),"") | L7: 20220516 | M7: 20251031 | N7: 155.26 | O7: =IFERROR(VLOOKUP(A7,Flete!$A:$J,10,0),"") | P7: TN | Q7: =IFERROR(IFERROR(VLOOKUP(A7,TRAOPE!$A:$U,21,0),VLOOKUP(B7,TRAOPE!$A:$U,21,0)),"") | R7: =IFERROR(IFERROR(VLOOKUP(A7,TRAOPE!$A:$W,23,0),VLOOKUP(B7,TRAOPE!$A:$W,23,0)),"") | S7: =IF(AND(P7="TN",R7="TN"),N7+N(O7),IF(G7&""="1",N(K7)*N7,(N7+N(O7))*N(K7))) | T7: =IF(Q7="","",Q7-S7)
A8: =CONCATENATE(C8,E8,F8,I8) | B8: =CONCATENATE(C8,E8,I8) | C8: 900000085 | D8: =IFERROR(VLOOKUP(C8,TRAOPE!$G:$H,2,0),"") | E8: DW68 | F8: D209 | G8: =IFERROR(VLOOKUP(A8,Flete!$A:$E,5,0),"") | H8: =IFERROR(VLOOKUP(F8,TRAOPE!$AA:$AB,2,0),"") | I8: 10141571 | J8: =IFERROR(VLOOKUP(I8,Materiales!$A:$H,8,0),"") | K8: =IFERROR(VLOOKUP(I8,Materiales!$A:$G,7,0),"") | L8: 20220516 | M8: 20251031 | N8: 231.34 | O8: =IFERROR(VLOOKUP(A8,Flete!$A:$J,10,0),"") | P8: TN | Q8: =IFERROR(IFERROR(VLOOKUP(A8,TRAOPE!$A:$U,21,0),VLOOKUP(B8,TRAOPE!$A:$U,21,0)),"") | R8: =IFERROR(IFERROR(VLOOKUP(A8,TRAOPE!$A:$W,23,0),VLOOKUP(B8,TRAOPE!$A:$W,23,0)),"") | S8: =IF(AND(P8="TN",R8="TN"),N8+N(O8),IF(G8&""="1",N(K8)*N8,(N8+N(O8))*N(K8))) | T8: =IF(Q8="","",Q8-S8)
A9: =CONCATENATE(C9,E9,F9,I9) | B9: =CONCATENATE(C9,E9,I9) | C9: 900000085 | D9: =IFERROR(VLOOKUP(C9,TRAOPE!$G:$H,2,0),"") | E9: DW68 | F9: D211 | G9: =IFERROR(VLOOKUP(A9,Flete!$A:$E,5,0),"") | H9: =IFERROR(VLOOKUP(F9,TRAOPE!$AA:$AB,2,0),"") | I9: 10000191 | J9: =IFERROR(VLOOKUP(I9,Materiales!$A:$H,8,0),"") | K9: =IFERROR(VLOOKUP(I9,Materiales!$A:$G,7,0),"") | L9: 20220516 | M9: 20251031 | N9: 124.11 | O9: =IFERROR(VLOOKUP(A9,Flete!$A:$J,10,0),"") | P9: TN | Q9: =IFERROR(IFERROR(VLOOKUP(A9,TRAOPE!$A:$U,21,0),VLOOKUP(B9,TRAOPE!$A:$U,21,0)),"") | R9: =IFERROR(IFERROR(VLOOKUP(A9,TRAOPE!$A:$W,23,0),VLOOKUP(B9,TRAOPE!$A:$W,23,0)),"") | S9: =IF(AND(P9="TN",R9="TN"),N9+N(O9),IF(G9&""="1",N(K9)*N9,(N9+N(O9))*N(K9))) | T9: =IF(Q9="","",Q9-S9)
A10: =CONCATENATE(C10,E10,F10,I10) | B10: =CONCATENATE(C10,E10,I10) | C10: 900000085 | D10: =IFERROR(VLOOKUP(C10,TRAOPE!$G:$H,2,0),"") | E10: DW68 | F10: D211 | G10: =IFERROR(VLOOKUP(A10,Flete!$A:$E,5,0),"") | H10: =IFERROR(VLOOKUP(F10,TRAOPE!$AA:$AB,2,0),"") | I10: 10110630 | J10: =IFERROR(VLOOKUP(I10,Materiales!$A:$H,8,0),"") | K10: =IFERROR(VLOOKUP(I10,Materiales!$A:$G,7,0),"") | L10: 20220516 | M10: 20251031 | N10: 155.26 | O10: =IFERROR(VLOOKUP(A10,Flete!$A:$J,10,0),"") | P10: TN | Q10: =IFERROR(IFERROR(VLOOKUP(A10,TRAOPE!$A:$U,21,0),VLOOKUP(B10,TRAOPE!$A:$U,21,0)),"") | R10: =IFERROR(IFERROR(VLOOKUP(A10,TRAOPE!$A:$W,23,0),VLOOKUP(B10,TRAOPE!$A:$W,23,0)),"") | S10: =IF(AND(P10="TN",R10="TN"),N10+N(O10),IF(G10&""="1",N(K10)*N10,(N10+N(O10))*N(K10))) | T10: =IF(Q10="","",Q10-S10)
A11: =CONCATENATE(C11,E11,F11,I11) | B11: =CONCATENATE(C11,E11,I11) | C11: 900000085 | D11: =IFERROR(VLOOKUP(C11,TRAOPE!$G:$H,2,0),"") | E11: DW68 | F11: D211 | G11: =IFERROR(VLOOKUP(A11,Flete!$A:$E,5,0),"") | H11: =IFERROR(VLOOKUP(F11,TRAOPE!$AA:$AB,2,0),"") | I11: 10141571 | J11: =IFERROR(VLOOKUP(I11,Materiales!$A:$H,8,0),"") | K11: =IFERROR(VLOOKUP(I11,Materiales!$A:$G,7,0),"") | L11: 20220516 | M11: 20251031 | N11: 231.34 | O11: =IFERROR(VLOOKUP(A11,Flete!$A:$J,10,0),"") | P11: TN | Q11: =IFERROR(IFERROR(VLOOKUP(A11,TRAOPE!$A:$U,21,0),VLOOKUP(B11,TRAOPE!$A:$U,21,0)),"") | R11: =IFERROR(IFERROR(VLOOKUP(A11,TRAOPE!$A:$W,23,0),VLOOKUP(B11,TRAOPE!$A:$W,23,0)),"") | S11: =IF(AND(P11="TN",R11="TN"),N11+N(O11),IF(G11&""="1",N(K11)*N11,(N11+N(O11))*N(K11))) | T11: =IF(Q11="","",Q11-S11)
A12: =CONCATENATE(C12,E12,F12,I12) | B12: =CONCATENATE(C12,E12,I12) | C12: 900000085 | D12: =IFERROR(VLOOKUP(C12,TRAOPE!$G:$H,2,0),"") | E12: DW68 | F12: D214 | G12: =IFERROR(VLOOKUP(A12,Flete!$A:$E,5,0),"") | H12: =IFERROR(VLOOKUP(F12,TRAOPE!$AA:$AB,2,0),"") | I12: 10000191 | J12: =IFERROR(VLOOKUP(I12,Materiales!$A:$H,8,0),"") | K12: =IFERROR(VLOOKUP(I12,Materiales!$A:$G,7,0),"") | L12: 20220516 | M12: 20251031 | N12: 124.11 | O12: =IFERROR(VLOOKUP(A12,Flete!$A:$J,10,0),"") | P12: TN | Q12: =IFERROR(IFERROR(VLOOKUP(A12,TRAOPE!$A:$U,21,0),VLOOKUP(B12,TRAOPE!$A:$U,21,0)),"") | R12: =IFERROR(IFERROR(VLOOKUP(A12,TRAOPE!$A:$W,23,0),VLOOKUP(B12,TRAOPE!$A:$W,23,0)),"") | S12: =IF(AND(P12="TN",R12="TN"),N12+N(O12),IF(G12&""="1",N(K12)*N12,(N12+N(O12))*N(K12))) | T12: =IF(Q12="","",Q12-S12)
A13: =CONCATENATE(C13,E13,F13,I13) | B13: =CONCATENATE(C13,E13,I13) | C13: 900000085 | D13: =IFERROR(VLOOKUP(C13,TRAOPE!$G:$H,2,0),"") | E13: DW68 | F13: D214 | G13: =IFERROR(VLOOKUP(A13,Flete!$A:$E,5,0),"") | H13: =IFERROR(VLOOKUP(F13,TRAOPE!$AA:$AB,2,0),"") | I13: 10110630 | J13: =IFERROR(VLOOKUP(I13,Materiales!$A:$H,8,0),"") | K13: =IFERROR(VLOOKUP(I13,Materiales!$A:$G,7,0),"") | L13: 20220516 | M13: 20251031 | N13: 155.26 | O13: =IFERROR(VLOOKUP(A13,Flete!$A:$J,10,0),"") | P13: TN | Q13: =IFERROR(IFERROR(VLOOKUP(A13,TRAOPE!$A:$U,21,0),VLOOKUP(B13,TRAOPE!$A:$U,21,0)),"") | R13: =IFERROR(IFERROR(VLOOKUP(A13,TRAOPE!$A:$W,23,0),VLOOKUP(B13,TRAOPE!$A:$W,23,0)),"") | S13: =IF(AND(P13="TN",R13="TN"),N13+N(O13),IF(G13&""="1",N(K13)*N13,(N13+N(O13))*N(K13))) | T13: =IF(Q13="","",Q13-S13)
A14: =CONCATENATE(C14,E14,F14,I14) | B14: =CONCATENATE(C14,E14,I14) | C14: 900000085 | D14: =IFERROR(VLOOKUP(C14,TRAOPE!$G:$H,2,0),"") | E14: DW68 | F14: D214 | G14: =IFERROR(VLOOKUP(A14,Flete!$A:$E,5,0),"") | H14: =IFERROR(VLOOKUP(F14,TRAOPE!$AA:$AB,2,0),"") | I14: 10141571 | J14: =IFERROR(VLOOKUP(I14,Materiales!$A:$H,8,0),"") | K14: =IFERROR(VLOOKUP(I14,Materiales!$A:$G,7,0),"") | L14: 20220516 | M14: 20251031 | N14: 231.34 | O14: =IFERROR(VLOOKUP(A14,Flete!$A:$J,10,0),"") | P14: TN | Q14: =IFERROR(IFERROR(VLOOKUP(A14,TRAOPE!$A:$U,21,0),VLOOKUP(B14,TRAOPE!$A:$U,21,0)),"") | R14: =IFERROR(IFERROR(VLOOKUP(A14,TRAOPE!$A:$W,23,0),VLOOKUP(B14,TRAOPE!$A:$W,23,0)),"") | S14: =IF(AND(P14="TN",R14="TN"),N14+N(O14),IF(G14&""="1",N(K14)*N14,(N14+N(O14))*N(K14))) | T14: =IF(Q14="","",Q14-S14)
... A801: =CONCATENATE(C801,E801,F801,I801) | B801: =CONCATENATE(C801,E801,I801) | C801: 900009420 | D801: =IFERROR(VLOOKUP(C801,TRAOPE!$G:$H,2,0),"") | E801: DW68 | F801: ENV9 | G801: =IFERROR(VLOOKUP(A801,Flete!$A:$E,5,0),"") | H801: =IFERROR(VLOOKUP(F801,TRAOPE!$AA:$AB,2,0),"") | I801: 10270913 | J801: =IFERROR(VLOOKUP(I801,Materiales!$A:$H,8,0),"") | K801: =IFERROR(VLOOKUP(I801,Materiales!$A:$G,7,0),"") | L801: 20260126 | M801: 99991231 | N801: 202.8 | O801: =IFERROR(VLOOKUP(A801,Flete!$A:$J,10,0),"") | P801: TN | Q801: =IFERROR(IFERROR(VLOOKUP(A801,TRAOPE!$A:$U,21,0),VLOOKUP(B801,TRAOPE!$A:$U,21,0)),"") | R801: =IFERROR(IFERROR(VLOOKUP(A801,TRAOPE!$A:$W,23,0),VLOOKUP(B801,TRAOPE!$A:$W,23,0)),"") | S801: =IF(AND(P801="TN",R801="TN"),N801+N(O801),IF(G801&""="1",N(K801)*N801,(N801+N(O801))*N(K801))) | T801: =IF(Q801="","",Q801-S801)

Sheet MP
A1: No. SF | B1: Cedis | C1: Destino | D1: No. Material | E1: Nombre Material | F1: Importe MP | G1: Moneda | H1: Cantidad | I1: UM | J1: C | K1: Inicio Vigencia | L1: Fin Vigencia
A2: 900000085 | B2: DW68 | C2: D042 | D2: 10000191 | F2: 124.11 | I2: TN | K2: 20220516 | L2: 20251031
A3: 900000085 | B3: DW68 | C3: D042 | D3: 10110630 | F3: 155.26 | I3: TN | K3: 20220516 | L3: 20251031
A4: 900000085 | B4: DW68 | C4: D042 | D4: 10141571 | F4: 231.34 | I4: TN | K4: 20220516 | L4: 20251031
A5: 900000085 | B5: DW68 | C5: D209 | D5: 10000191 | F5: 124.11 | I5: TN | K5: 20220516 | L5: 20251031
A6: 900000085 | B6: DW68 | C6: D209 | D6: 10110630 | F6: 155.26 | I6: TN | K6: 20220516 | L6: 20251031
A7: 900000085 | B7: DW68 | C7: D209 | D7: 10141571 | F7: 231.34 | I7: TN | K7: 20220516 | L7: 20251031
A8: 900000085 | B8: DW68 | C8: D211 | D8: 10000191 | F8: 124.11 | I8: TN | K8: 20220516 | L8: 20251031
A9: 900000085 | B9: DW68 | C9: D211 | D9: 10110630 | F9: 155.26 | I9: TN | K9: 20220516 | L9: 20251031
A10: 900000085 | B10: DW68 | C10: D211 | D10: 10141571 | F10: 231.34 | I10: TN | K10: 20220516 | L10: 20251031
A11: 900000085 | B11: DW68 | C11: D214 | D11: 10000191 | F11: 124.11 | I11: TN | K11: 20220516 | L11: 20251031
A12: 900000085 | B12: DW68 | C12: D214 | D12: 10110630 | F12: 155.26 | I12: TN | K12: 20220516 | L12: 20251031
A13: 900000085 | B13: DW68 | C13: D214 | D13: 10141571 | F13: 231.34 | I13: TN | K13: 20220516 | L13: 20251031
... A800: 900009420 | B800: DW68 | C800: ENV9 | D800: 10270913 | F800: 202.8 | I800: TN | K800: 20260126 | L800: 99991231

Sheet Flete
A1: Concat1 | B1: No. SF | C1: Cedis | D1: Destino | E1: Cond. Exp. | F1: Material | H1: Nombre Material | J1: Importe Flete | K1: Moneda | L1: Cantidad | M1: UM | N1: C | P1: Inicio Vigencia | Q1: Fin Vigencia
A2: 900000085DW68D04210000191 | B2: 900000085 | C2: DW68 | D2: D042 | E2: 1 | F2: 10000191 | J2: 56.76 | M2: TN | P2: 20210620 | Q2: 20251031
A3: 900000085DW68D04210110630 | B3: 900000085 | C3: DW68 | D3: D042 | E3: 1 | F3: 10110630 | J3: 56.76 | M3: TN | P3: 20210620 | Q3: 20251031
A4: 900000085DW68D04210141571 | B4: 900000085 | C4: DW68 | D4: D042 | E4: 1 | F4: 10141571 | J4: 56.76 | M4: TN | P4: 20210620 | Q4: 20251031
A5: 900000085DW68D20910000191 | B5: 900000085 | C5: DW68 | D5: D209 | E5: 1 | F5: 10000191 | J5: 50.92 | M5: TN | P5: 20210620 | Q5: 20251031
A6: 900000085DW68D20910110630 | B6: 900000085 | C6: DW68 | D6: D209 | E6: 1 | F6: 10110630 | J6: 50.92 | M6: TN | P6: 20210620 | Q6: 20251031
A7: 900000085DW68D20910141571 | B7: 900000085 | C7: DW68 | D7: D209 | E7: 1 | F7: 10141571 | J7: 50.92 | M7: TN | P7: 20210620 | Q7: 20251031
A8: 900000085DW68D21110000191 | B8: 900000085 | C8: DW68 | D8: D211 | E8: 1 | F8: 10000191 | J8: 41.7 | M8: TN | P8: 20210620 | Q8: 20251031
A9: 900000085DW68D21110110630 | B9: 900000085 | C9: DW68 | D9: D211 | E9: 1 | F9: 10110630 | J9: 41.7 | M9: TN | P9: 20210620 | Q9: 20251031
A10: 900000085DW68D21110141571 | B10: 900000085 | C10: DW68 | D10: D211 | E10: 1 | F10: 10141571 | J10: 41.7 | M10: TN | P10: 20210620 | Q10: 20251031
A11: 900000085DW68D21410000191 | B11: 900000085 | C11: DW68 | D11: D214 | E11: 1 | F11: 10000191 | J11: 59.33 | M11: TN | P11: 20210620 | Q11: 20251031
A12: 900000085DW68D21410110630 | B12: 900000085 | C12: DW68 | D12: D214 | E12: 1 | F12: 10110630 | J12: 59.33 | M12: TN | P12: 20210620 | Q12: 20251031
A13: 900000085DW68D21410141571 | B13: 900000085 | C13: DW68 | D13: D214 | E13: 1 | F13: 10141571 | J13: 59.33 | M13: TN | P13: 20210620 | Q13: 20251031
... A725: 900009420DW68ENV910270913 | B725: 900009420 | C725: DW68 | D725: ENV9 | E725: 4 | F725: 10270913 | J725: 0.01 | M725: TN | P725: 20260126 | Q725: 99991231

Sheet Materiales
A1: Material | B1: TpMt | C1: Denom | D1: UMA | E1: Contador | F1: UMB | G1: PV | H1: Nombre Material
A2: 10000001 | B2: ZFER | C2: 1000 | D2: M3 | E2: 1000 | F2: TN | G2: 1262 | H2: GRAVA ANDESITA 10 MM (3/8")
A3: 10000003 | B3: ZFER | C3: 1000 | D3: M3 | E3: 1000 | F3: TN | G3: 1443 | H3: GRAVA CALIZA 10 MM (3/8")
A4: 10000006 | B4: ZFER | C4: 1000 | D4: M3 | E4: 1000 | F4: TN | G4: 1490 | H4: GRAVA RIO 10 MM (3/8")
A5: 10000007 | B5: ZFER | C5: 1000 | D5: M3 | E5: 1000 | F5: TN | G5: 1488 | H5: GRAVA BASALTO 13 MM (1/2")
A6: 10000008 | B6: ZFER | C6: 1000 | D6: M3 | E6: 1000 | F6: TN | G6: 1358 | H6: GRAVA CALIZA 13 MM (1/2")
A7: 10000011 | B7: ZFER | C7: 1000 | D7: M3 | E7: 1000 | F7: TN | G7: 1323 | H7: GRAVA ANDESITA 20 MM (3/4")
A8: 10000013 | B8: ZFER | C8: 1000 | D8: M3 | E8: 1000 | F8: TN | G8: 1514 | H8: GRAVA BASALTO 20 MM (3/4")
A9: 10000014 | B9: ZFER | C9: 1000 | D9: M3 | E9: 1000 | F9: TN | G9: 1400 | H9: GRAVA CALIZA 20 MM (3/4")
A10: 10000015 | B10: ZFER | C10: 1000 | D10: M3 | E10: 1000 | F10: TN | G10: 1410 | H10: GRAVA GRANITO 20 MM (3/4")
A11: 10000017 | B11: ZFER | C11: 1000 | D11: M3 | E11: 1000 | F11: TN | G11: 1475 | H11: GRAVA RIOLITA 20 MM (3/4")
A12: 10000019 | B12: ZFER | C12: 1000 | D12: M3 | E12: 1000 | F12: TN | G12: 1515 | H12: GRAVA RIO 20 MM (3/4")
A13: 10000020 | B13: ZFER | C13: 1000 | D13: M3 | E13: 1 | F13: TN | G13: 1 | H13: GRAVA MAQUILA 40MM (1 1/2")
... A2291: 10268770 | B2291: ZFE3 | C2291: 1000 | D2291: M3 | E2291: 1000 | F2291: TN | G2291: 1240 | H2291: MP GRAVA TRIT CALIZA 40MM 1 1/2" - ESP
A2292: 10268901 | B2292: ZFE3 | C2292: 1000 | D2292: M3 | E2292: 1000 | G2292: 1560 | H2292: MP GRAVA ANDESITA GRIS 3/4" - CAPADA
A2293: 10267983 | C2293: 1000 | G2293: 1800 | H2293: ESCORIA ALTO HORNO 3/4
A2294: 10268996 | C2294: 1000 | G2294: 1329 | H2294: GRAVA TRITURADA CALIZA 40 MM - 11/2"
A2295: 10269072 | C2295: 1000 | G2295: 1700 | H2295: BASE HIDRÁULICA SCREEN
A2296: 10269225 | B2296: ZFE3 | C2296: 1000 | D2296: M3 | E2296: 1000 | G2296: 1289 | H2296: MP ARENA CALIZA LAVADA MALLA 4 - DELTA I
A2297: 10269245 | B2297: ZFE3 | C2297: 1000 | D2297: M3 | E2297: 1000 | G2297: 1410 | H2297: MP GRAVA TRITURADA CALIZA 3/8 - 10MM
A2298: 10269246 | B2298: ZFE3 | C2298: 1000 | D2298: M3 | E2298: 1000 | G2298: 1400 | H2298: MP GRAVA TRITURADA CALIZA 1 1/2 - 40MM
A2299: 10269247 | B2299: ZFE3 | C2299: 1000 | D2299: M3 | E2299: 1000 | G2299: 1560 | H2299: MP ARENA TRIT CALIZA M-4
A2300: 10270431 | B2300: ZFE3 | C2300: 1000 | D2300: M3 | E2300: 1000 | G2300: 1423 | H2300: MP GRAVA RIOLITA 13 MM - 1/2"
A2301: 10270898 | B2301: ZFE3 | C2301: 1000 | D2301: M3 | E2301: 1000 | G2301: 1551 | H2301: MP BASE H. TRIT. BASALTO 1 1/2" A FINOS
A2302: 10270911 | B2302: ZFE3 | C2302: 1000 | D2302: M3 | E2302: 1000 | G2302: 1360 | H2302: MP GRAVA TRIT. BASALTO 40 MM - 1 1/2"
A2303: 10270912 | B2303: ZFE3 | C2303: 1000 | D2303: M3 | E2303: 1000 | G2303: 1589 | H2303: MP ARENA TRIT. BASALTO MALLA 4
A2304: 10270913 | B2304: ZFE3 | C2304: 1000 | D2304: M3 | E2304: 1000 | G2304: 1395 | H2304: MP GRAVA TRIT. BASALTO 20 MM - 3/4
A2305: 10270914 | B2305: ZFE3 | C2305: 1000 | D2305: M3 | E2305: 1000 | G2305: 1623 | H2305: MP ARENA ANDESITA BC
A2306: 10270824 | B2306: M3 | C2306: 1000 | D2306: M3 | E2306: 10007640 | G2306: 1325 | H2306: MP ARENA TRITURADA CALIZA MALLA 5
A2307: 10270825 | B2307: M3 | C2307: 1000 | D2307: M3 | E2307: 10000003 | G2307: 1242 | H2307: MP GRAVA TRITURADA CALIZA 10MM (3/8”)
... A2319: 10272527 | B2319: ZFE3 | C2319: 1000 | D2319: M3 | E2319: 1000 | G2319: 1620 | H2319: CNC - NO CLASIFICADO
A2320: 10000332 | C2320: 1000 | D2320: M3 | E2320: 1000 | G2320: 800 | H2320: Grava Triturada Pomez - Jal 20 mm - 3/4"
A2321: 10273001 | B2321: ZFE3 | C2321: 1000 | D2321: M3 | E2321: 1000 | G2321: 1688 | H2321: MP ARENA TRIT. BASALTO MALLA 4
A2322: 10273002 | B2322: ZFE3 | C2322: 1000 | D2322: M3 | E2322: 1000 | G2322: 1466 | H2322: MP GRAVA TRIT. BASALTO 20 MM - 3/4"
A2323: 10273351 | B2323: ZFE3 | C2323: 1000 | D2323: M3 | E2323: 1000 | G2323: 1612 | H2323: MP ARENA TRIT. CALIZA MALLA 4
A2324: 10273352 | B2324: ZFE3 | C2324: 1000 | D2324: M3 | E2324: 1000 | G2324: 1492 | H2324: MP GRAVA TRIT. CALIZA 20 MM - 3/4"
A2325: 10271724 | B2325: ZFE3 | C2325: 1000 | D2325: M3 | E2325: 1000 | G2325: 1900 | H2325: MP RESIDUO DE CONCRETO
A2326: 10000677 | C2326: 1000 | D2326: M3 | G2326: 1164 | H2326: Grava Triturada Caliza 20 mm - 3/4"
A2327: 10274190 | B2327: ZFE3 | C2327: 1000 | D2327: M3 | E2327: 1000 | G2327: 1800 | H2327: MP BASE HIDRAULICA ANDESITA 70-30
A2328: 10274601 | B2328: ZFE3 | C2328: 1000 | D2328: M3 | E2328: 1000 | G2328: 1447 | H2328: MP ARENA BASALTO N° 4
A2329: 10274754 | B2329: ZFE3 | C2329: 1000 | D2329: M3 | E2329: 1000 | G2329: 1397 | H2329: MP GRAVA TRIT. ANDESITA 20 MM - 3/4"
A2330: 10169718 | B2330: ZFE3 | C2330: 1000 | D2330: M3 | E2330: 1000 | G2330: 1400 | H2330: GRAVA CLASIFICADA RÍO 40 MM - 1 1/2"
A2331: 10274813 | B2331: ZFE3 | C2331: 1000 | D2331: M3 | E2331: 1000 | G2331: 1448 | H2331: MP ARENA TRIT RÍO MALLA 4
A2332: 10274815 | B2332: ZFE3 | C2332: 1000 | D2332: M3 | E2332: 1000 | G2332: 1366 | H2332: MP ARENA CLASIFICADA RÍO MALLA 5
A2333: 10274816 | B2333: ZFE3 | C2333: 1000 | D2333: M3 | E2333: 1000 | G2333: 1472 | H2333: MP GRAVA CLASIF RÍO 20 MM - 3/4"
A2334: 10275113 | B2334: ZFE3 | C2334: 1000 | D2334: M3 | E2334: 1000 | G2334: 1409 | H2334: MP ARENA TRIT ANDESITA MALLA 4
A2335: 10275114 | B2335: ZFE3 | C2335: 1000 | D2335: M3 | E2335: 1000 | G2335: 1418 | H2335: MP ARENA CLASIF RIO MALLA 4 - LAVADO
A2336: 10275115 | B2336: ZFE3 | C2336: 1000 | D2336: M3 | E2336: 1000 | G2336: 1259 | H2336: MP ARENA TRIT ANDESITA MALLA 4
A2337: 10275116 | B2337: ZFE3 | C2337: 1000 | D2337: M3 | E2337: 1000 | G2337: 1401 | H2337: MP GRAVA TRIT ANDESITA 3/4 - 20 MM
A2338: 10275118 | B2338: ZFE3 | C2338: 1000 | D2338: M3 | E2338: 1000 | G2338: 1401 | H2338: MP ARENA TRIT ANDESITA MALLA 4
... A2361: 10280049 | B2361: ZFE3 | C2361: 1000 | D2361: M3 | E2361: 1000 | G2361: 1584 | H2361: MP B. HID CALIZA 40% FINOS Y 60% GRUESOS
A2362: 10280365 | C2362: 1000 | D2362: M3 | E2362: 1000 | G2362: 1274 | H2362: MP GRAVA BASALTO 20 MM -3/4
A2363: 10280538 | B2363: ZFE3 | C2363: 1000 | D2363: M3 | E2363: 1000 | G2363: 1262 | H2363: MP GRAVA TRIT BASALTO 3/8 - 10MM
A2364: 10280679 | B2364: ZFE3 | C2364: 1000 | D2364: M3 | E2364: 1000 | G2364: 1349 | H2364: MP GRAVA CLASIF RÍO 13MM - 1/2"
A2365: 10281171 | B2365: ZFE3 | C2365: 1000 | D2365: M3 | E2365: 1000 | G2365: 1271 | H2365: MP GRAVA TRIT CALIZA 10MM - 3/8"
A2366: 10281183 | B2366: ZFE3 | C2366: 1000 | D2366: M3 | E2366: 1000 | G2366: 1468 | H2366: MP ARENA TRIT CALIZA MALLA 4
A2367: 10281384 | B2367: ZFE3 | C2367: 1000 | D2367: M3 | E2367: 1000 | G2367: 1285 | H2367: MP GRAVA BASALTO 40 MM (1 1/2")
A2368: 10281379 | B2368: ZFE3 | C2368: 1000 | D2368: M3 | E2368: 1000 | G2368: 1536 | H2368: MP ARENA CLASIF. RÍO MALLA 4
A2369: 10281450 | B2369: ZFE3 | C2369: 1000 | D2369: M3 | E2369: 1000 | G2369: 1325 | H2369: MP GRAVA CLASIF. RIO 20MM - 3/4
A2370: 10281451 | B2370: ZFE3 | C2370: 1000 | D2370: M3 | E2370: 1000 | G2370: 1564 | H2370: MP ARENA CLASIF. RÍO MALLA 4
A2371: 10281452 | B2371: ZFE3 | C2371: 1000 | D2371: M3 | E2371: 1000 | G2371: 1427 | H2371: MP GRAVA CLASIF. RIO 20MM - 3/4

Sheet TRAOPE
A1: Concat1 | B1: Contrato_Pos | C1: Doc. Compras | D1: Pos | E1: Org.compras | F1: Grp-Compr. | G1: Ship From | H1: Nombre SF | I1: Proveedor | J1: Nombre Prov | K1: Cond. Pago | L1: Descr. Cond Pago | M1: Material | N1: Descripción | O1: Centro | P1: Descripción Centro | Q1: In.perído validez | R1: Fin perído validez | S1: Válido de | T1: Validez a | U1: Precio neto pedido | V1: Moneda | W1: UM Precio Pedido | X1: Importe Condición | Y1: Moneda KONP | Z1: UM Ctd Base | AA1: Destino | AB1: Nombre Destino | AC1: Cuenta de mayor | AD1: Centro de costo | AE1: Cond. Exp. | AF1: Descr. Cond. Exp. | AG1: Peso Vol. | AH1: UMB | AI1: Ind. Oblig. Conf. Ped. | AJ1: Ctrl-Conf. | AK1: IVA | AL1: Modif_Date | AM1: Ruta
A2: 900004065DW68D22010000320 | B2: 4600050428-240 | C2: 4600050428 | D2: 240 | E2: MXPO | F2: MXL | G2: 900004065 | H2: TC-ED CALIDRA | I2: 5002756 | J2: CALIDRA DE OCCIDENTE SA DE CV | K2: Z07 | L2: (AP) 60 Dias | M2: 10000320 | N2: Arena Triturada Caliza Malla 4 | O2: DW68 | P2: MX-CED. GUADALAJARA | Q2: 20210801 | R2: 20281231 | S2: 20260709 | T2: 20301231 | U2: 386.79 | V2: MXN | W2: TN | X2: 277.59 | Y2: MXN | Z2: TN | AA2: D220 | AB2: PD0131 TEPATITLAN | AC2: 56103638 | AD2: 6644241540 | AE2: 4 | AF2: ENTREGA DIRECTA | AG2: 1 | AH2: TO | AI2: X | AJ2: 4 | AK2: V4 | AL2: 20260713 | AM2: DW68-900004065-D220-10000320-4
A3: 900009399DW6810000439 | B3: 4600071814-20 | C3: 4600071814 | D3: 20 | E3: MXPO | F3: MXL | G3: 900009399 | H3: SF TC – NOE TESISTAN | I3: 5003391 | J3: MENDOZA VELAZQUEZ NOE | K3: E60 | L3: (AP) E-FACTOR 60 Dias | M3: 10000439 | N3: Grava Triturada Basalto 10 mm - 3/8" | O3: DW68 | P3: MX-CED. GUADALAJARA | Q3: 20251201 | R3: 20301231 | S3: 20260706 | T3: 20301231 | U3: 390 | V3: MXN | W3: M3 | X3: 0 | Y3: MXN | Z3: M3 | AC3: 56103637 | AD3: 6644241540 | AE3: 1 | AF3: ENTREGADO | AG3: 1.437 | AH3: M3 | AI3: X | AJ3: 4 | AK3: V4 | AL3: 20260710 | AM3: DW68-900009399-10000439
A4: 900009233DW68D21110270911 | B4: 4600072356-30 | C4: 4600072356 | D4: 30 | E4: MXPO | F4: MXL | G4: 900009233 | H4: SF TC–ED GYB BURRITOS | I4: 5098612 | J4: URBANIZACIONES G Y B SA DE CV | K4: Z09 | L4: (AP) 90 Dias | M4: 10270911 | N4: MP GRAVA TRIT. BASALTO 40 MM - 1 1/2" | O4: DW68 | P4: MX-CED. GUADALAJARA | Q4: 20260701 | R4: 20301231 | S4: 20260701 | T4: 20301231 | U4: 412 | V4: MXN | W4: M3 | X4: 152 | Y4: MXN | Z4: M3 | AA4: D211 | AB4: PD0149 GDL. MATRIZ | AC4: 56103637 | AD4: 6644241540 | AE4: 4 | AF4: ENTREGA DIRECTA | AG4: 1.36 | AH4: M3 | AI4: X | AJ4: 4 | AK4: V4 | AL4: 20260722 | AM4: DW68-900009233-D211-10270911-4
A5: 900009233DW68D20910270911 | B5: 4600072356-20 | C5: 4600072356 | D5: 20 | E5: MXPO | F5: MXL | G5: 900009233 | H5: SF TC–ED GYB BURRITOS | I5: 5098612 | J5: URBANIZACIONES G Y B SA DE CV | K5: Z09 | L5: (AP) 90 Dias | M5: 10270911 | N5: MP GRAVA TRIT. BASALTO 40 MM - 1 1/2" | O5: DW68 | P5: MX-CED. GUADALAJARA | Q5: 20260701 | R5: 20301231 | S5: 20260701 | T5: 20301231 | U5: 400 | V5: MXN | W5: M3 | X5: 140 | Y5: MXN | Z5: M3 | AA5: D209 | AB5: PD0127 MANANTIAL | AC5: 56103637 | AD5: 6644241540 | AE5: 4 | AF5: ENTREGA DIRECTA | AG5: 1.36 | AH5: M3 | AI5: X | AJ5: 4 | AK5: V4 | AL5: 20260722 | AM5: DW68-900009233-D209-10270911-4
A6: 900009233DW68D24710270911 | B6: 4600072356-60 | C6: 4600072356 | D6: 60 | E6: MXPO | F6: MXL | G6: 900009233 | H6: SF TC–ED GYB BURRITOS | I6: 5098612 | J6: URBANIZACIONES G Y B SA DE CV | K6: Z09 | L6: (AP) 90 Dias | M6: 10270911 | N6: MP GRAVA TRIT. BASALTO 40 MM - 1 1/2" | O6: DW68 | P6: MX-CED. GUADALAJARA | Q6: 20260701 | R6: 20301231 | S6: 20260701 | T6: 20301231 | U6: 452 | V6: MXN | W6: M3 | X6: 192 | Y6: MXN | Z6: M3 | AA6: D247 | AB6: PD0518 TONALA | AC6: 56103637 | AD6: 6644241540 | AE6: 4 | AF6: ENTREGA DIRECTA | AG6: 1.36 | AH6: M3 | AI6: X | AJ6: 4 | AK6: V4 | AL6: 20260722 | AM6: DW68-900009233-D247-10270911-4
A7: 900009233DW68D24210270911 | B7: 4600072356-50 | C7: 4600072356 | D7: 50 | E7: MXPO | F7: MXL | G7: 900009233 | H7: SF TC–ED GYB BURRITOS | I7: 5098612 | J7: URBANIZACIONES G Y B SA DE CV | K7: Z09 | L7: (AP) 90 Dias | M7: 10270911 | N7: MP GRAVA TRIT. BASALTO 40 MM - 1 1/2" | O7: DW68 | P7: MX-CED. GUADALAJARA | Q7: 20260701 | R7: 20301231 | S7: 20260701 | T7: 20301231 | U7: 476 | V7: MXN | W7: M3 | X7: 216 | Y7: MXN | Z7: M3 | AA7: D242 | AB7: PD0454 CD. LA GRANJA II | AC7: 56103637 | AD7: 6644241540 | AE7: 4 | AF7: ENTREGA DIRECTA | AG7: 1.36 | AH7: M3 | AI7: X | AJ7: 4 | AK7: V4 | AL7: 20260722 | AM7: DW68-900009233-D242-10270911-4
A8: 900009233DW68D26710270911 | B8: 4600072356-90 | C8: 4600072356 | D8: 90 | E8: MXPO | F8: MXL | G8: 900009233 | H8: SF TC–ED GYB BURRITOS | I8: 5098612 | J8: URBANIZACIONES G Y B SA DE CV | K8: Z09 | L8: (AP) 90 Dias | M8: 10270911 | N8: MP GRAVA TRIT. BASALTO 40 MM - 1 1/2" | O8: DW68 | P8: MX-CED. GUADALAJARA | Q8: 20260701 | R8: 20301231 | S8: 20260701 | T8: 20301231 | U8: 548 | V8: MXN | W8: M3 | X8: 288 | Y8: MXN | Z8: M3 | AA8: D267 | AB8: PD0280 PLANTA COLOTLAN | AC8: 56103637 | AD8: 6644241540 | AE8: 4 | AF8: ENTREGA DIRECTA | AG8: 1.36 | AH8: M3 | AI8: X | AJ8: 4 | AK8: V4 | AL8: 20260722 | AM8: DW68-900009233-D267-10270911-4
A9: 900009233DW68D25110270911 | B9: 4600072356-70 | C9: 4600072356 | D9: 70 | E9: MXPO | F9: MXL | G9: 900009233 | H9: SF TC–ED GYB BURRITOS | I9: 5098612 | J9: URBANIZACIONES G Y B SA DE CV | K9: Z09 | L9: (AP) 90 Dias | M9: 10270911 | N9: MP GRAVA TRIT. BASALTO 40 MM - 1 1/2" | O9: DW68 | P9: MX-CED. GUADALAJARA | Q9: 20260701 | R9: 20301231 | S9: 20260701 | T9: 20301231 | U9: 368 | V9: MXN | W9: M3 | X9: 108 | Y9: MXN | Z9: M3 | AA9: D251 | AB9: PD0339 EL SALTO | AC9: 56103637 | AD9: 6644241540 | AE9: 4 | AF9: ENTREGA DIRECTA | AG9: 1.36 | AH9: M3 | AI9: X | AJ9: 4 | AK9: V4 | AL9: 20260722 | AM9: DW68-900009233-D251-10270911-4
A10: 900009233DW68D04210270911 | B10: 4600072356-10 | C10: 4600072356 | D10: 10 | E10: MXPO | F10: MXL | G10: 900009233 | H10: SF TC–ED GYB BURRITOS | I10: 5098612 | J10: URBANIZACIONES G Y B SA DE CV | K10: Z09 | L10: (AP) 90 Dias | M10: 10270911 | N10: MP GRAVA TRIT. BASALTO 40 MM - 1 1/2" | O10: DW68 | P10: MX-CED. GUADALAJARA | Q10: 20260701 | R10: 20301231 | S10: 20260701 | T10: 20301231 | U10: 472 | V10: MXN | W10: M3 | X10: 212 | Y10: MXN | Z10: M3 | AA10: D042 | AB10: PD0406 PLANTA PONIENTE | AC10: 56103637 | AD10: 6644241540 | AE10: 4 | AF10: ENTREGA DIRECTA | AG10: 1.36 | AH10: M3 | AI10: X | AJ10: 4 | AK10: V4 | AL10: 20260722 | AM10: DW68-900009233-D042-10270911-4
A11: 900009233DW68D22810270911 | B11: 4600072356-40 | C11: 4600072356 | D11: 40 | E11: MXPO | F11: MXL | G11: 900009233 | H11: SF TC–ED GYB BURRITOS | I11: 5098612 | J11: URBANIZACIONES G Y B SA DE CV | K11: Z09 | L11: (AP) 90 Dias | M11: 10270911 | N11: MP GRAVA TRIT. BASALTO 40 MM - 1 1/2" | O11: DW68 | P11: MX-CED. GUADALAJARA | Q11: 20260701 | R11: 20301231 | S11: 20260701 | T11: 20301231 | U11: 400 | V11: MXN | W11: M3 | X11: 140 | Y11: MXN | Z11: M3 | AA11: D228 | AB11: PD0123 TLAJOMULCO | AC11: 56103637 | AD11: 6644241540 | AE11: 4 | AF11: ENTREGA DIRECTA | AG11: 1.36 | AH11: M3 | AI11: X | AJ11: 4 | AK11: V4 | AL11: 20260722 | AM11: DW68-900009233-D228-10270911-4
A12: 900009233DW68D26410270911 | B12: 4600072356-80 | C12: 4600072356 | D12: 80 | E12: MXPO | F12: MXL | G12: 900009233 | H12: SF TC–ED GYB BURRITOS | I12: 5098612 | J12: URBANIZACIONES G Y B SA DE CV | K12: Z09 | L12: (AP) 90 Dias | M12: 10270911 | N12: MP GRAVA TRIT. BASALTO 40 MM - 1 1/2" | O12: DW68 | P12: MX-CED. GUADALAJARA | Q12: 20260701 | R12: 20301231 | S12: 20260701 | T12: 20301231 | U12: 396 | V12: MXN | W12: M3 | X12: 136 | Y12: MXN | Z12: M3 | AA12: D264 | AB12: PD0083 GUADALAJARA I III | AC12: 56103637 | AD12: 6644241540 | AE12: 4 | AF12: ENTREGA DIRECTA | AG12: 1.36 | AH12: M3 | AI12: X | AJ12: 4 | AK12: V4 | AL12: 20260722 | AM12: DW68-900009233-D264-10270911-4
A13: 900009399DW6810003240 | B13: 4600071814-30 | C13: 4600071814 | D13: 30 | E13: MXPO | F13: MXL | G13: 900009399 | H13: SF TC – NOE TESISTAN | I13: 5003391 | J13: MENDOZA VELAZQUEZ NOE | K13: E60 | L13: (AP) E-FACTOR 60 Dias | M13: 10003240 | N13: Grava Triturada Basalto 40 mm - 1 1/2" | O13: DW68 | P13: MX-CED. GUADALAJARA | Q13: 20251201 | R13: 20301231 | S13: 20260706 | T13: 20301231 | U13: 315 | V13: MXN | W13: M3 | X13: 0 | Y13: MXN | Z13: M3 | AC13: 56103637 | AD13: 6644241540 | AE13: 1 | AF13: ENTREGADO | AG13: 1.406 | AH13: M3 | AI13: X | AJ13: 4 | AK13: V4 | AL13: 20260710 | AM13: DW68-900009399-10003240
A14: 900000472DW68D04210001456 | B14: 4600050411-80 | C14: 4600050411 | D14: 80 | E14: MXPO | F14: MXL | G14: 900000472 | H14: TC-ED-TRIMCAV | I14: 5010147 | J14: TRITURACIONES DE MARMOL Y CALCIOS | K14: Z04 | L14: (AP) 30 Dias | M14: 10001456 | N14: Grava Triturada Marmol 40 mm - 1 1/2" | O14: DW68 | P14: MX-CED. GUADALAJARA | Q14: 20210712 | R14: 20291231 | S14: 20250301 | T14: 20301231 | U14: 1557.44 | V14: MXN | W14: TN | X14: 1059.48 | Y14: MXN | Z14: TN | AA14: D042 | AB14: PD0406 PLANTA PONIENTE | AC14: 56103637 | AD14: 6644241867 | AE14: 4 | AF14: ENTREGA DIRECTA | AG14: 1 | AH14: TO | AI14: X | AJ14: 4 | AK14: V4 | AL14: 20250410 | AM14: DW68-900000472-D042-10001456-4
A15: 900000472DW68D04210000655 | B15: 4600050411-60 | C15: 4600050411 | D15: 60 | E15: MXPO | F15: MXL | G15: 900000472 | H15: TC-ED-TRIMCAV | I15: 5010147 | J15: TRITURACIONES DE MARMOL Y CALCIOS | K15: Z04 | L15: (AP) 30 Dias | M15: 10000655 | N15: Grava Triturada Marmol 10 mm - 3/8" | O15: DW68 | P15: MX-CED. GUADALAJARA | Q15: 20210712 | R15: 20291231 | S15: 20250301 | T15: 20301231 | U15: 1557.44 | V15: MXN | W15: TN | X15: 1059.48 | Y15: MXN | Z15: TN | AA15: D042 | AB15: PD0406 PLANTA PONIENTE | AC15: 56103637 | AD15: 6644241867 | AE15: 4 | AF15: ENTREGA DIRECTA | AG15: 1 | AH15: TO | AI15: X | AJ15: 4 | AK15: V4 | AL15: 20250410 | AM15: DW68-900000472-D042-10000655-4
A16: 900007315DW68D22810000200 | B16: 4600052017-50 | C16: 4600052017 | D16: 50 | E16: MXPO | F16: MXL | G16: 900007315 | H16: SF TC-ED- DE CARGA BDE | I16: 5081782 | J16: SOLUCIONES DE TRANSPORTE DE CARGA B | K16: Z09 | L16: (AP) 90 Dias | M16: 10000200 | N16: Grava Triturada Pomez - Jal 20 mm - 3/4" | O16: DW68 | P16: MX-CED. GUADALAJARA | Q16: 20210901 | R16: 20281231 | S16: 20250801 | T16: 20301231 | U16: 142.34 | V16: MXN | W16: M3 | X16: 63.14 | Y16: MXN | Z16: M3 | AA16: D228 | AB16: PD0123 TLAJOMULCO | AC16: 56103637 | AD16: 6644241540 | AE16: 4 | AF16: ENTREGA DIRECTA | AG16: 0.826 | AH16: M3 | AI16: X | AJ16: 4 | AK16: V4 | AL16: 20250806 | AM16: DW68-900007315-D228-10000200-4
A17: 900007315DW68D24710000200 | B17: 4600052017-70 | C17: 4600052017 | D17: 70 | E17: MXPO | F17: MXL | G17: 900007315 | H17: SF TC-ED- DE CARGA BDE | I17: 5081782 | J17: SOLUCIONES DE TRANSPORTE DE CARGA B | K17: Z09 | L17: (AP) 90 Dias | M17: 10000200 | N17: Grava Triturada Pomez - Jal 20 mm - 3/4" | O17: DW68 | P17: MX-CED. GUADALAJARA | Q17: 20210901 | R17: 20281231 | S17: 20250801 | T17: 20301231 | U17: 297.29 | V17: MXN | W17: M3 | X17: 218.1 | Y17: MXN | Z17: M3 | AA17: D247 | AB17: PD0518 TONALA | AC17: 56103637 | AD17: 6644241540 | AE17: 4 | AF17: ENTREGA DIRECTA | AG17: 0.826 | AH17: M3 | AI17: X | AJ17: 4 | AK17: V4 | AL17: 20250806 | AM17: DW68-900007315-D247-10000200-4
A18: 900007315DW68D20910000200 | B18: 4600052017-60 | C18: 4600052017 | D18: 60 | E18: MXPO | F18: MXL | G18: 900007315 | H18: SF TC-ED- DE CARGA BDE | I18: 5081782 | J18: SOLUCIONES DE TRANSPORTE DE CARGA B | K18: Z09 | L18: (AP) 90 Dias | M18: 10000200 | N18: Grava Triturada Pomez - Jal 20 mm - 3/4" | O18: DW68 | P18: MX-CED. GUADALAJARA | Q18: 20210901 | R18: 20281231 | S18: 20250801 | T18: 20301231 | U18: 240.6 | V18: MXN | W18: M3 | X18: 161.4 | Y18: MXN | Z18: M3 | AA18: D209 | AB18: PD0127 MANANTIAL | AC18: 56103637 | AD18: 6644241540 | AE18: 4 | AF18: ENTREGA DIRECTA | AG18: 0.826 | AH18: M3 | AI18: X | AJ18: 4 | AK18: V4 | AL18: 20250806 | AM18: DW68-900007315-D209-10000200-4
A19: 900000472DW68D24210001456 | B19: 4600050411-40 | C19: 4600050411 | D19: 40 | E19: MXPO | F19: MXL | G19: 900000472 | H19: TC-ED-TRIMCAV | I19: 5010147 | J19: TRITURACIONES DE MARMOL Y CALCIOS | K19: Z04 | L19: (AP) 30 Dias | M19: 10001456 | N19: Grava Triturada Marmol 40 mm - 1 1/2" | O19: DW68 | P19: MX-CED. GUADALAJARA | Q19: 20210712 | R19: 20291231 | S19: 20250301 | T19: 20301231 | U19: 1557.44 | V19: MXN | W19: TN | X19: 1059.48 | Y19: MXN | Z19: TN | AA19: D242 | AB19: PD0454 CD. LA GRANJA II | AC19: 56103637 | AD19: 6644241867 | AE19: 4 | AF19: ENTREGA DIRECTA | AG19: 1 | AH19: TO | AI19: X | AJ19: 4 | AK19: V4 | AL19: 20250410 | AM19: DW68-900000472-D242-10001456-4
A20: 900002733DW68D04210018375 | B20: 4600050422-30 | C20: 4600050422 | D20: 30 | E20: MXPO | F20: MXL | G20: 900002733 | H20: TC-ED- BANDERAS | I20: 5046238 | J20: SOLUCIONES LOGISTICAS PARA LA | K20: N90 | L20: (AP) NAFIN 90 Dias | M20: 10018375 | N20: Arena Triturada Basalto Malla 4 - BC | O20: DW68 | P20: MX-CED. GUADALAJARA | Q20: 20210801 | R20: 20261231 | S20: 20210712 | T20: 20261231 | U20: 410 | V20: MXN | W20: M3 | X20: 350 | Y20: MXN | Z20: M3 | AA20: D042 | AB20: PD0406 PLANTA PONIENTE | AC20: 56103638 | AD20: 6644241540 | AE20: 4 | AF20: ENTREGA DIRECTA | AG20: 1.32 | AH20: M3 | AI20: X | AJ20: 4 | AK20: V4 | AL20: 20260108 | AM20: DW68-900002733-D042-10018375-4
A21: 900007315DW68D24210000200 | B21: 4600052017-30 | C21: 4600052017 | D21: 30 | E21: MXPO | F21: MXL | G21: 900007315 | H21: SF TC-ED- DE CARGA BDE | I21: 5081782 | J21: SOLUCIONES DE TRANSPORTE DE CARGA B | K21: Z09 | L21: (AP) 90 Dias | M21: 10000200 | N21: Grava Triturada Pomez - Jal 20 mm - 3/4" | O21: DW68 | P21: MX-CED. GUADALAJARA | Q21: 20210901 | R21: 20281231 | S21: 20250801 | T21: 20301231 | U21: 240.6 | V21: MXN | W21: M3 | X21: 161.4 | Y21: MXN | Z21: M3 | AA21: D242 | AB21: PD0454 CD. LA GRANJA II | AC21: 56103637 | AD21: 6644241540 | AE21: 4 | AF21: ENTREGA DIRECTA | AG21: 0.826 | AH21: M3 | AI21: X | AJ21: 4 | AK21: V4 | AL21: 20250806 | AM21: DW68-900007315-D242-10000200-4
A22: 900007315DW68D04210000200 | B22: 4600052017-200 | C22: 4600052017 | D22: 200 | E22: MXPO | F22: MXL | G22: 900007315 | H22: SF TC-ED- DE CARGA BDE | I22: 5081782 | J22: SOLUCIONES DE TRANSPORTE DE CARGA B | K22: Z09 | L22: (AP) 90 Dias | M22: 10000200 | N22: Grava Triturada Pomez - Jal 20 mm - 3/4" | O22: DW68 | P22: MX-CED. GUADALAJARA | Q22: 20210901 | R22: 20281231 | S22: 20250801 | T22: 20301231 | U22: 240.6 | V22: MXN | W22: M3 | X22: 161.4 | Y22: MXN | Z22: M3 | AA22: D042 | AB22: PD0406 PLANTA PONIENTE | AC22: 56103637 | AD22: 6644241540 | AE22: 4 | AF22: ENTREGA DIRECTA | AG22: 0.826 | AH22: M3 | AI22: X | AJ22: 4 | AK22: V4 | AL22: 20250806 | AM22: DW68-900007315-D042-10000200-4
A23: 900000472DW68D26410000635 | B23: 4600050411-90 | C23: 4600050411 | D23: 90 | E23: MXPO | F23: MXL | G23: 900000472 | H23: TC-ED-TRIMCAV | I23: 5010147 | J23: TRITURACIONES DE MARMOL Y CALCIOS | K23: Z04 | L23: (AP) 30 Dias | M23: 10000635 | N23: Arena Triturada Marmol Malla 4 | O23: DW68 | P23: MX-CED. GUADALAJARA | Q23: 20210712 | R23: 20291231 | S23: 20250301 | T23: 20301231 | U23: 1557.44 | V23: MXN | W23: TN | X23: 1059.48 | Y23: MXN | Z23: TN | AA23: D264 | AB23: PD0083 GUADALAJARA I III | AC23: 56103638 | AD23: 6644241867 | AE23: 4 | AF23: ENTREGA DIRECTA | AG23: 1 | AH23: TO | AI23: X | AJ23: 4 | AK23: V4 | AL23: 20250410 | AM23: DW68-900000472-D264-10000635-4
A24: 900000472DW68D24210000643 | B24: 4600050411-30 | C24: 4600050411 | D24: 30 | E24: MXPO | F24: MXL | G24: 900000472 | H24: TC-ED-TRIMCAV | I24: 5010147 | J24: TRITURACIONES DE MARMOL Y CALCIOS | K24: Z04 | L24: (AP) 30 Dias | M24: 10000643 | N24: Grava Triturada Marmol 20 mm - 3/4" | O24: DW68 | P24: MX-CED. GUADALAJARA | Q24: 20210712 | R24: 20291231 | S24: 20250301 | T24: 20301231 | U24: 1557.44 | V24: MXN | W24: TN | X24: 1059.48 | Y24: MXN | Z24: TN | AA24: D242 | AB24: PD0454 CD. LA GRANJA II | AC24: 56103637 | AD24: 6644241867 | AE24: 4 | AF24: ENTREGA DIRECTA | AG24: 1 | AH24: TO | AI24: X | AJ24: 4 | AK24: V4 | AL24: 20250410 | AM24: DW68-900000472-D242-10000643-4
A25: 900007315DW68D26410000200 | B25: 4600052017-40 | C25: 4600052017 | D25: 40 | E25: MXPO | F25: MXL | G25: 900007315 | H25: SF TC-ED- DE CARGA BDE | I25: 5081782 | J25: SOLUCIONES DE TRANSPORTE DE CARGA B | K25: Z09 | L25: (AP) 90 Dias | M25: 10000200 | N25: Grava Triturada Pomez - Jal 20 mm - 3/4" | O25: DW68 | P25: MX-CED. GUADALAJARA | Q25: 20210901 | R25: 20281231 | S25: 20250801 | T25: 20301231 | U25: 222.97 | V25: MXN | W25: M3 | X25: 143.77 | Y25: MXN | Z25: M3 | AA25: D264 | AB25: PD0083 GUADALAJARA I III | AC25: 56103637 | AD25: 6644241540 | AE25: 4 | AF25: ENTREGA DIRECTA | AG25: 0.826 | AH25: M3 | AI25: X | AJ25: 4 | AK25: V4 | AL25: 20250806 | AM25: DW68-900007315-D264-10000200-4
... A42: 900000472DW68D20910112095 | B42: 4600050411-160 | C42: 4600050411 | D42: 160 | E42: MXPO | F42: MXL | G42: 900000472 | H42: TC-ED-TRIMCAV | I42: 5010147 | J42: TRITURACIONES DE MARMOL Y CALCIOS | K42: Z04 | L42: (AP) 30 Dias | M42: 10112095 | N42: ARENA BARITA | O42: DW68 | P42: MX-CED. GUADALAJARA | Q42: 20210712 | R42: 20291231 | S42: 20210712 | T42: 20251231 | U42: 7700 | V42: MXN | W42: TN | X42: 1000 | Y42: MXN | Z42: TN | AA42: D209 | AB42: PD0127 MANANTIAL | AC42: 56103638 | AD42: 6644241540 | AE42: 4 | AF42: ENTREGA DIRECTA | AG42: 1 | AH42: TO | AI42: X | AJ42: 4 | AK42: V4 | AL42: 20230920 | AM42: DW68-900000472-D209-10112095-4
A43: 900009220DW68D24710000437 | B43: 4600071229-60 | C43: 4600071229 | D43: 60 | E43: MXPO | F43: MXL | G43: 900009220 | H43: SF TC ED-AKOPAN | I43: 5060172 | J43: DESARROLLADORA AKOPAN SA DE CV | K43: N30 | L43: (AP) NAFIN 30 Dias | M43: 10000437 | N43: Grava Triturada Basalto 20 mm - 3/4" | O43: DW68 | P43: MX-CED. GUADALAJARA | Q43: 20250507 | R43: 20301231 | U43: 0 | V43: MXN | W43: M3 | AA43: D247 | AB43: PD0518 TONALA | AC43: 56103637 | AD43: 6644241540 | AE43: 4 | AF43: ENTREGA DIRECTA | AG43: 1.505 | AH43: M3 | AI43: X | AJ43: 4 | AK43: V4 | AL43: 20260507 | AM43: DW68-900009220-D247-10000437-4
A44: 900009396DW68D57710270898 | B44: 4600071942-70 | C44: 4600071942 | D44: 70 | E44: MXPO | F44: MXL | G44: 900009396 | H44: SF TC-ED GASA | I44: 5097224 | J44: TRITURADOS GASA SA DE CV | K44: Z09 | L44: (AP) 90 Dias | M44: 10270898 | N44: MP BASE H. TRIT. BASALTO 1 1/2" A FINOS | O44: DW68 | P44: MX-CED. GUADALAJARA | Q44: 20260126 | R44: 20301231 | U44: 0 | V44: MXN | W44: M3 | AA44: D577 | AB44: D577 PD0681 PROY APTO GDL | AC44: 56103590 | AD44: 6644241540 | AE44: 4 | AF44: ENTREGA DIRECTA | AG44: 1.551 | AH44: M3 | AI44: X | AJ44: 4 | AK44: V4 | AL44: 20260331 | AM44: DW68-900009396-D577-10270898-4
A45: 900000085DW6810110630 | B45: 4600050405-30 | C45: 4600050405 | D45: 30 | E45: MXPO | F45: MXL | G45: 900000085 | H45: TC ASFALTOS GUADALAJARA- TONALA | I45: 5003735 | J45: ASFALTOS GUADALAJARA SAPI DE CV | K45: Z04 | L45: (AP) 30 Dias | M45: 10110630 | N45: GRAVA TRITURADA BASALTO 40 MM - 1 1/2" A | O45: DW68 | P45: MX-CED. GUADALAJARA | Q45: 20210712 | R45: 20261231 | S45: 20210712 | T45: 20261231 | U45: 220 | V45: MXN | W45: M3 | AC45: 56103637 | AD45: 6644241540 | AE45: 1 | AF45: ENTREGADO | AG45: 1.417 | AH45: M3 | AI45: X | AJ45: 4 | AK45: V4 | AL45: 20260108 | AM45: DW68-900000085-10110630
A46: 900000620DW68ENV910000439 | B46: 4600071941-60 | C46: 4600071941 | D46: 60 | E46: MXPO | F46: MXL | G46: 900000620 | H46: TC-ED- GRAVASE STA. ROSA | I46: 5009010 | J46: GRAVASE SA DE CV | K46: Z04 | L46: (AP) 30 Dias | M46: 10000439 | N46: Grava Triturada Basalto 10 mm - 3/8" | O46: DW68 | P46: MX-CED. GUADALAJARA | Q46: 20260126 | R46: 20301231 | U46: 0 | V46: MXN | W46: TN | AA46: ENV9 | AB46: VIALIDADES AEROPUERTO GDL F1 Y F2 / | AC46: 56103637 | AD46: 6644241540 | AE46: 4 | AF46: ENTREGA DIRECTA | AG46: 1 | AH46: TO | AI46: X | AJ46: 4 | AK46: V4 | AL46: 20260331 | AM46: DW68-900000620-ENV9-10000439-4
A47: 900009301DW6810270913 | B47: 4600071506-50 | C47: 4600071506 | D47: 50 | E47: MXPO | F47: MXL | G47: 900009301 | H47: SF TC-GRAVASE SANTA ROSA | I47: 5009010 | J47: GRAVASE SA DE CV | K47: Z04 | L47: (AP) 30 Dias | M47: 10270913 | N47: MP GRAVA TRIT. BASALTO 20 MM - 3/4 | O47: DW68 | P47: MX-CED. GUADALAJARA | Q47: 20250801 | R47: 20301231 | S47: 20260509 | T47: 20301231 | U47: 231.12 | V47: MXN | W47: TN | X47: 0 | Y47: MXN | Z47: TN | AC47: 56103637 | AD47: 6644241540 | AE47: 2 | AF47: RECOGIDO | AG47: 1 | AH47: TO | AI47: X | AJ47: 4 | AK47: V4 | AL47: 20260513 | AM47: DW68-900009301-10270913
A48: 900009301DW6810270911 | B48: 4600071506-20 | C48: 4600071506 | D48: 20 | E48: MXPO | F48: MXL | G48: 900009301 | H48: SF TC-GRAVASE SANTA ROSA | I48: 5009010 | J48: GRAVASE SA DE CV | K48: Z04 | L48: (AP) 30 Dias | M48: 10270911 | N48: MP GRAVA TRIT. BASALTO 40 MM - 1 1/2" | O48: DW68 | P48: MX-CED. GUADALAJARA | Q48: 20250801 | R48: 20301231 | S48: 20260509 | T48: 20301231 | U48: 214 | V48: MXN | W48: TN | X48: 0 | Y48: MXN | Z48: TN | AC48: 56103637 | AD48: 6644241540 | AE48: 2 | AF48: RECOGIDO | AG48: 1 | AH48: TO | AI48: X | AJ48: 4 | AK48: V4 | AL48: 20260513 | AM48: DW68-900009301-10270911
A49: 900009301DW6810209065 | B49: 4600071506-10 | C49: 4600071506 | D49: 10 | E49: MXPO | F49: MXL | G49: 900009301 | H49: SF TC-GRAVASE SANTA ROSA | I49: 5009010 | J49: GRAVASE SA DE CV | K49: Z04 | L49: (AP) 30 Dias | M49: 10209065 | N49: FILTRO 5" A 7/8" | O49: DW68 | P49: MX-CED. GUADALAJARA | Q49: 20250801 | R49: 20301231 | S49: 20260509 | T49: 20301231 | U49: 107.12 | V49: MXN | W49: TN | X49: 0 | Y49: MXN | Z49: TN | AC49: 56103637 | AD49: 6644241540 | AE49: 2 | AF49: RECOGIDO | AG49: 1 | AH49: TO | AI49: X | AJ49: 4 | AK49: V4 | AL49: 20260513 | AM49: DW68-900009301-10209065
A50: 900009301DW6810270912 | B50: 4600071506-30 | C50: 4600071506 | D50: 30 | E50: MXPO | F50: MXL | G50: 900009301 | H50: SF TC-GRAVASE SANTA ROSA | I50: 5009010 | J50: GRAVASE SA DE CV | K50: Z04 | L50: (AP) 30 Dias | M50: 10270912 | N50: MP ARENA TRIT. BASALTO MALLA 4 | O50: DW68 | P50: MX-CED. GUADALAJARA | Q50: 20250801 | R50: 20301231 | S50: 20260509 | T50: 20301231 | U50: 245 | V50: MXN | W50: TN | X50: 0 | Y50: MXN | Z50: TN | AC50: 56103638 | AD50: 6644241540 | AE50: 2 | AF50: RECOGIDO | AG50: 1 | AH50: TO | AI50: X | AJ50: 4 | AK50: V4 | AL50: 20260513 | AM50: DW68-900009301-10270912
A51: 900009301DW6810000439 | B51: 4600071506-40 | C51: 4600071506 | D51: 40 | E51: MXPO | F51: MXL | G51: 900009301 | H51: SF TC-GRAVASE SANTA ROSA | I51: 5009010 | J51: GRAVASE SA DE CV | K51: Z04 | L51: (AP) 30 Dias | M51: 10000439 | N51: Grava Triturada Basalto 10 mm - 3/8" | O51: DW68 | P51: MX-CED. GUADALAJARA | Q51: 20250801 | R51: 20301231 | S51: 20260509 | T51: 20301231 | U51: 254 | V51: MXN | W51: TN | X51: 0 | Y51: MXN | Z51: TN | AC51: 56103637 | AD51: 6644241540 | AE51: 2 | AF51: RECOGIDO | AG51: 1 | AH51: TO | AI51: X | AJ51: 4 | AK51: V4 | AL51: 20260513 | AM51: DW68-900009301-10000439
A52: 900009301DW6810270898 | B52: 4600071506-60 | C52: 4600071506 | D52: 60 | E52: MXPO | F52: MXL | G52: 900009301 | H52: SF TC-GRAVASE SANTA ROSA | I52: 5009010 | J52: GRAVASE SA DE CV | K52: Z04 | L52: (AP) 30 Dias | M52: 10270898 | N52: MP BASE H. TRIT. BASALTO 1 1/2" A FINOS | O52: DW68 | P52: MX-CED. GUADALAJARA | Q52: 20250801 | R52: 20301231 | S52: 20260509 | T52: 20301231 | U52: 184.44 | V52: MXN | W52: TN | X52: 0 | Y52: MXN | Z52: TN | AC52: 56103590 | AD52: 6644241540 | AE52: 2 | AF52: RECOGIDO | AG52: 1 | AH52: TO | AI52: X | AJ52: 4 | AK52: V4 | AL52: 20260513 | AM52: DW68-900009301-10270898
A53: 900004356DW6810268650 | B53: 4600050433-40 | C53: 4600050433 | D53: 40 | E53: MXPO | F53: MXL | G53: 900004356 | H53: TC-AKOPAN | I53: 5060172 | J53: DESARROLLADORA AKOPAN SA DE CV | K53: N30 | L53: (AP) NAFIN 30 Dias | M53: 10268650 | N53: MP GRAVA TRIT BASALTO 40MM - 1 1/2 | O53: DW68 | P53: MX-CED. GUADALAJARA | Q53: 20210801 | R53: 20291231 | S53: 20260526 | T53: 20301231 | U53: 295 | V53: MXN | W53: M3 | X53: 0 | Y53: MXN | Z53: M3 | AC53: 56103637 | AD53: 6644241540 | AE53: 1 | AF53: ENTREGADO | AG53: 1.3 | AH53: M3 | AI53: X | AJ53: 4 | AK53: V4 | AL53: 20260604 | AM53: DW68-900004356-10268650
A54: 900002068DW68D26810000835 | B54: 4600050418-130 | C54: 4600050418 | D54: 130 | E54: MXPO | F54: MXL | G54: 900002068 | H54: TC-ED- EL PACHON | I54: 5043944 | J54: CONSTRUCCIONES MAREVA DE OCCIDENTE | K54: Z04 | L54: (AP) 30 Dias | M54: 10000835 | N54: Arena Clasificada Río Malla 4 | O54: DW68 | P54: MX-CED. GUADALAJARA | Q54: 20210712 | R54: 20281231 | S54: 20250701 | T54: 20301231 | U54: 216.23 | V54: MXN | W54: M3 | X54: 133.81 | Y54: MXN | Z54: M3 | AA54: D268 | AB54: PD418 AEROPUERTO GDL | AC54: 56103638 | AD54: 6644241540 | AE54: 4 | AF54: ENTREGA DIRECTA | AG54: 1.18 | AH54: M3 | AI54: X | AJ54: 4 | AK54: V4 | AL54: 20250718 | AM54: DW68-900002068-D268-10000835-4
A55: 900002068DW68D24210000835 | B55: 4600050418-80 | C55: 4600050418 | D55: 80 | E55: MXPO | F55: MXL | G55: 900002068 | H55: TC-ED- EL PACHON | I55: 5043944 | J55: CONSTRUCCIONES MAREVA DE OCCIDENTE | K55: Z04 | L55: (AP) 30 Dias | M55: 10000835 | N55: Arena Clasificada Río Malla 4 | O55: DW68 | P55: MX-CED. GUADALAJARA | Q55: 20210712 | R55: 20281231 | S55: 20250701 | T55: 20301231 | U55: 220.51 | V55: MXN | W55: M3 | X55: 138.09 | Y55: MXN | Z55: M3 | AA55: D242 | AB55: PD0454 CD. LA GRANJA II | AC55: 56103638 | AD55: 6644241540 | AE55: 4 | AF55: ENTREGA DIRECTA | AG55: 1.18 | AH55: M3 | AI55: X | AJ55: 4 | AK55: V4 | AL55: 20250718 | AM55: DW68-900002068-D242-10000835-4
A56: 900002068DW68D24710000835 | B56: 4600050418-120 | C56: 4600050418 | D56: 120 | E56: MXPO | F56: MXL | G56: 900002068 | H56: TC-ED- EL PACHON | I56: 5043944 | J56: CONSTRUCCIONES MAREVA DE OCCIDENTE | K56: Z04 | L56: (AP) 30 Dias | M56: 10000835 | N56: Arena Clasificada Río Malla 4 | O56: DW68 | P56: MX-CED. GUADALAJARA | Q56: 20210712 | R56: 20281231 | S56: 20250701 | T56: 20301231 | U56: 284.21 | V56: MXN | W56: M3 | X56: 201.79 | Y56: MXN | Z56: M3 | AA56: D247 | AB56: PD0518 TONALA | AC56: 56103638 | AD56: 6644241540 | AE56: 4 | AF56: ENTREGA DIRECTA | AG56: 1.18 | AH56: M3 | AI56: X | AJ56: 4 | AK56: V4 | AL56: 20250718 | AM56: DW68-900002068-D247-10000835-4
A57: 900002068DW68D21110000835 | B57: 4600050418-60 | C57: 4600050418 | D57: 60 | E57: MXPO | F57: MXL | G57: 900002068 | H57: TC-ED- EL PACHON | I57: 5043944 | J57: CONSTRUCCIONES MAREVA DE OCCIDENTE | K57: Z04 | L57: (AP) 30 Dias | M57: 10000835 | N57: Arena Clasificada Río Malla 4 | O57: DW68 | P57: MX-CED. GUADALAJARA | Q57: 20210712 | R57: 20281231 | S57: 20250701 | T57: 20301231 | U57: 203.21 | V57: MXN | W57: M3 | X57: 120.79 | Y57: MXN | Z57: M3 | AA57: D211 | AB57: PD0149 GDL. MATRIZ | AC57: 56103638 | AD57: 6644241540 | AE57: 4 | AF57: ENTREGA DIRECTA | AG57: 1.18 | AH57: M3 | AI57: X | AJ57: 4 | AK57: V4 | AL57: 20250718 | AM57: DW68-900002068-D211-10000835-4
A58: 900002122DW6810000835 | B58: 4600050419-10 | C58: 4600050419 | D58: 10 | E58: MXPO | F58: MXL | G58: 900002122 | H58: TC- EL PACHON | I58: 5043944 | J58: CONSTRUCCIONES MAREVA DE OCCIDENTE | K58: Z04 | L58: (AP) 30 Dias | M58: 10000835 | N58: Arena Clasificada Río Malla 4 | O58: DW68 | P58: MX-CED. GUADALAJARA | Q58: 20210712 | R58: 20261231 | S58: 20250701 | T58: 20301231 | U58: 82.42 | V58: MXN | W58: M3 | X58: 0 | Y58: MXN | Z58: M3 | AC58: 56103638 | AD58: 6644241540 | AE58: 1 | AF58: ENTREGADO | AG58: 1.18 | AH58: M3 | AI58: X | AJ58: 4 | AK58: V4 | AL58: 20250718 | AM58: DW68-900002122-10000835
A59: 900002068DW68D04210000835 | B59: 4600050418-100 | C59: 4600050418 | D59: 100 | E59: MXPO | F59: MXL | G59: 900002068 | H59: TC-ED- EL PACHON | I59: 5043944 | J59: CONSTRUCCIONES MAREVA DE OCCIDENTE | K59: Z04 | L59: (AP) 30 Dias | M59: 10000835 | N59: Arena Clasificada Río Malla 4 | O59: DW68 | P59: MX-CED. GUADALAJARA | Q59: 20210712 | R59: 20281231 | S59: 20250701 | T59: 20301231 | U59: 222.41 | V59: MXN | W59: M3 | X59: 139.99 | Y59: MXN | Z59: M3 | AA59: D042 | AB59: PD0406 PLANTA PONIENTE | AC59: 56103638 | AD59: 6644241540 | AE59: 4 | AF59: ENTREGA DIRECTA | AG59: 1.18 | AH59: M3 | AI59: X | AJ59: 4 | AK59: V4 | AL59: 20250718 | AM59: DW68-900002068-D042-10000835-4
A60: 900002068DW68D21310000835 | B60: 4600050418-50 | C60: 4600050418 | D60: 50 | E60: MXPO | F60: MXL | G60: 900002068 | H60: TC-ED- EL PACHON | I60: 5043944 | J60: CONSTRUCCIONES MAREVA DE OCCIDENTE | K60: Z04 | L60: (AP) 30 Dias | M60: 10000835 | N60: Arena Clasificada Río Malla 4 | O60: DW68 | P60: MX-CED. GUADALAJARA | Q60: 20210712 | R60: 20281231 | S60: 20250701 | T60: 20301231 | U60: 328.51 | V60: MXN | W60: M3 | X60: 246.09 | Y60: MXN | Z60: M3 | AA60: D213 | AB60: PD0154 OCOTLAN | AC60: 56103638 | AD60: 6644241540 | AE60: 4 | AF60: ENTREGA DIRECTA | AG60: 1.18 | AH60: M3 | AI60: X | AJ60: 4 | AK60: V4 | AL60: 20250718 | AM60: DW68-900002068-D213-10000835-4
A61: 900002068DW68D26710000835 | B61: 4600050418-90 | C61: 4600050418 | D61: 90 | E61: MXPO | F61: MXL | G61: 900002068 | H61: TC-ED- EL PACHON | I61: 5043944 | J61: CONSTRUCCIONES MAREVA DE OCCIDENTE | K61: Z04 | L61: (AP) 30 Dias | M61: 10000835 | N61: Arena Clasificada Río Malla 4 | O61: DW68 | P61: MX-CED. GUADALAJARA | Q61: 20210712 | R61: 20281231 | S61: 20250701 | T61: 20301231 | U61: 287.68 | V61: MXN | W61: M3 | X61: 205.26 | Y61: MXN | Z61: M3 | AA61: D267 | AB61: PD0280 PLANTA COLOTLAN | AC61: 56103638 | AD61: 6644241540 | AE61: 4 | AF61: ENTREGA DIRECTA | AG61: 1.18 | AH61: M3 | AI61: X | AJ61: 4 | AK61: V4 | AL61: 20250718 | AM61: DW68-900002068-D267-10000835-4
A62: 900002068DW68D22010000835 | B62: 4600050418-40 | C62: 4600050418 | D62: 40 | E62: MXPO | F62: MXL | G62: 900002068 | H62: TC-ED- EL PACHON | I62: 5043944 | J62: CONSTRUCCIONES MAREVA DE OCCIDENTE | K62: Z04 | L62: (AP) 30 Dias | M62: 10000835 | N62: Arena Clasificada Río Malla 4 | O62: DW68 | P62: MX-CED. GUADALAJARA | Q62: 20210712 | R62: 20281231 | S62: 20250701 | T62: 20301231 | U62: 365.37 | V62: MXN | W62: M3 | X62: 282.95 | Y62: MXN | Z62: M3 | AA62: D220 | AB62: PD0131 TEPATITLAN | AC62: 56103638 | AD62: 6644241540 | AE62: 4 | AF62: ENTREGA DIRECTA | AG62: 1.18 | AH62: M3 | AI62: X | AJ62: 4 | AK62: V4 | AL62: 20250718 | AM62: DW68-900002068-D220-10000835-4
A63: 900002068DW68D22810000835 | B63: 4600050418-30 | C63: 4600050418 | D63: 30 | E63: MXPO | F63: MXL | G63: 900002068 | H63: TC-ED- EL PACHON | I63: 5043944 | J63: CONSTRUCCIONES MAREVA DE OCCIDENTE | K63: Z04 | L63: (AP) 30 Dias | M63: 10000835 | N63: Arena Clasificada Río Malla 4 | O63: DW68 | P63: MX-CED. GUADALAJARA | Q63: 20210712 | R63: 20281231 | S63: 20250701 | T63: 20301231 | U63: 197.42 | V63: MXN | W63: M3 | X63: 115 | Y63: MXN | Z63: M3 | AA63: D228 | AB63: PD0123 TLAJOMULCO | AC63: 56103638 | AD63: 6644241540 | AE63: 4 | AF63: ENTREGA DIRECTA | AG63: 1.18 | AH63: M3 | AI63: X | AJ63: 4 | AK63: V4 | AL63: 20250718 | AM63: DW68-900002068-D228-10000835-4
A64: 900002068DW68D25110000835 | B64: 4600050418-110 | C64: 4600050418 | D64: 110 | E64: MXPO | F64: MXL | G64: 900002068 | H64: TC-ED- EL PACHON | I64: 5043944 | J64: CONSTRUCCIONES MAREVA DE OCCIDENTE | K64: Z04 | L64: (AP) 30 Dias | M64: 10000835 | N64: Arena Clasificada Río Malla 4 | O64: DW68 | P64: MX-CED. GUADALAJARA | Q64: 20210712 | R64: 20281231 | S64: 20250701 | T64: 20301231 | U64: 291.8 | V64: MXN | W64: M3 | X64: 209.38 | Y64: MXN | Z64: M3 | AA64: D251 | AB64: PD0339 EL SALTO | AC64: 56103638 | AD64: 6644241540 | AE64: 4 | AF64: ENTREGA DIRECTA | AG64: 1.18 | AH64: M3 | AI64: X | AJ64: 4 | AK64: V4 | AL64: 20250718 | AM64: DW68-900002068-D251-10000835-4
A65: 900002068DW68D26410000835 | B65: 4600050418-10 | C65: 4600050418 | D65: 10 | E65: MXPO | F65: MXL | G65: 900002068 | H65: TC-ED- EL PACHON | I65: 5043944 | J65: CONSTRUCCIONES MAREVA DE OCCIDENTE | K65: Z04 | L65: (AP) 30 Dias | M65: 10000835 | N65: Arena Clasificada Río Malla 4 | O65: DW68 | P65: MX-CED. GUADALAJARA | Q65: 20210712 | R65: 20281231 | S65: 20250701 | T65: 20301231 | U65: 241.22 | V65: MXN | W65: M3 | X65: 158.8 | Y65: MXN | Z65: M3 | AA65: D264 | AB65: PD0083 GUADALAJARA I III | AC65: 56103638 | AD65: 6644241540 | AE65: 4 | AF65: ENTREGA DIRECTA | AG65: 1.18 | AH65: M3 | AI65: X | AJ65: 4 | AK65: V4 | AL65: 20250718 | AM65: DW68-900002068-D264-10000835-4
A66: 900002068DW68D20910000835 | B66: 4600050418-70 | C66: 4600050418 | D66: 70 | E66: MXPO | F66: MXL | G66: 900002068 | H66: TC-ED- EL PACHON | I66: 5043944 | J66: CONSTRUCCIONES MAREVA DE OCCIDENTE | K66: Z04 | L66: (AP) 30 Dias | M66: 10000835 | N66: Arena Clasificada Río Malla 4 | O66: DW68 | P66: MX-CED. GUADALAJARA | Q66: 20210712 | R66: 20281231 | S66: 20250701 | T66: 20301231 | U66: 223.6 | V66: MXN | W66: M3 | X66: 141.18 | Y66: MXN | Z66: M3 | AA66: D209 | AB66: PD0127 MANANTIAL | AC66: 56103638 | AD66: 6644241540 | AE66: 4 | AF66: ENTREGA DIRECTA | AG66: 1.18 | AH66: M3 | AI66: X | AJ66: 4 | AK66: V4 | AL66: 20250718 | AM66: DW68-900002068-D209-10000835-4
A67: 900004166DW6810110630 | B67: 4600050431-40 | C67: 4600050431 | D67: 40 | E67: MXPO | F67: MXL | G67: 900004166 | H67: TC- ASFALTOS GDL LA VEGA | I67: 5003735 | J67: ASFALTOS GUADALAJARA SAPI DE CV | K67: Z04 | L67: (AP) 30 Dias | M67: 10110630 | N67: GRAVA TRITURADA BASALTO 40 MM - 1 1/2" A | O67: DW68 | P67: MX-CED. GUADALAJARA | Q67: 20210801 | R67: 20281231 | S67: 20230629 | T67: 20281231 | U67: 235 | V67: MXN | W67: M3 | X67: 0 | Y67: MXN | Z67: M3 | AC67: 56103637 | AD67: 6644241540 | AE67: 1 | AF67: ENTREGADO | AG67: 1.417 | AH67: M3 | AI67: X | AJ67: 4 | AK67: V4 | AL67: 20230920 | AM67: DW68-900004166-10110630
A68: 900000367DW6810000726 | B68: 4600050407-10 | C68: 4600050407 | D68: 10 | E68: MXPO | F68: MXL | G68: 900000367 | H68: TC ASFALTOS GUADALAJARA- ZAPOTE | I68: 5003735 | J68: ASFALTOS GUADALAJARA SAPI DE CV | K68: Z04 | L68: (AP) 30 Dias | M68: 10000726 | N68: Grava Triturada Basalto 13 mm - 1/2" | O68: DW68 | P68: MX-CED. GUADALAJARA | Q68: 20210712 | R68: 20261231 | S68: 20220406 | T68: 20271231 | U68: 350 | V68: MXN | W68: M3 | X68: 0 | Y68: MXN | Z68: M3 | AC68: 56103637 | AD68: 6644241540 | AE68: 1 | AF68: ENTREGADO | AG68: 1.333 | AH68: M3 | AI68: X | AJ68: 4 | AK68: V4 | AL68: 20230920 | AM68: DW68-900000367-10000726
A69: 900004166DW6810004258 | B69: 4600050431-20 | C69: 4600050431 | D69: 20 | E69: MXPO | F69: MXL | G69: 900004166 | H69: TC- ASFALTOS GDL LA VEGA | I69: 5003735 | J69: ASFALTOS GUADALAJARA SAPI DE CV | K69: Z04 | L69: (AP) 30 Dias | M69: 10004258 | N69: Sello Triturado Basalto 10 mm - 3/8" | O69: DW68 | P69: MX-CED. GUADALAJARA | Q69: 20210801 | R69: 20281231 | S69: 20230629 | T69: 20281231 | U69: 480 | V69: MXN | W69: M3 | X69: 0 | Y69: MXN | Z69: M3 | AC69: 56103637 | AD69: 6644241540 | AE69: 1 | AF69: ENTREGADO | AG69: 1.53 | AH69: M3 | AI69: X | AJ69: 4 | AK69: V4 | AL69: 20230920 | AM69: DW68-900004166-10004258
A70: 900000408DW6810000191 | B70: 4600050408-30 | C70: 4600050408 | D70: 30 | E70: MXPO | F70: MXL | G70: 900000408 | H70: TC ASFALTOS GUADALAJARA- VALLE GPE | I70: 5003735 | J70: ASFALTOS GUADALAJARA SAPI DE CV | K70: Z04 | L70: (AP) 30 Dias | M70: 10000191 | N70: Grava Triturada Basalto 20 mm - 3/4" | O70: DW68 | P70: MX-CED. GUADALAJARA | Q70: 20210712 | R70: 20281231 | S70: 20230505 | T70: 20281231 | U70: 250 | V70: MXN | W70: M3 | X70: 0 | Y70: MXN | Z70: M3 | AC70: 56103637 | AD70: 6644241540 | AE70: 1 | AF70: ENTREGADO | AG70: 1.41 | AH70: M3 | AI70: X | AJ70: 4 | AK70: V4 | AL70: 20230920 | AM70: DW68-900000408-10000191
A71: 900000408DW6810000388 | B71: 4600050408-20 | C71: 4600050408 | D71: 20 | E71: MXPO | F71: MXL | G71: 900000408 | H71: TC ASFALTOS GUADALAJARA- VALLE GPE | I71: 5003735 | J71: ASFALTOS GUADALAJARA SAPI DE CV | K71: Z04 | L71: (AP) 30 Dias | M71: 10000388 | N71: Grava Triturada Basalto 40 mm - 1 1/2" | O71: DW68 | P71: MX-CED. GUADALAJARA | Q71: 20210712 | R71: 20281231 | S71: 20230505 | T71: 20281231 | U71: 250 | V71: MXN | W71: M3 | X71: 0 | Y71: MXN | Z71: M3 | AC71: 56103637 | AD71: 6644241540 | AE71: 1 | AF71: ENTREGADO | AG71: 1.395 | AH71: M3 | AI71: X | AJ71: 4 | AK71: V4 | AL71: 20230920 | AM71: DW68-900000408-10000388
A72: 900004166DW6810000384 | B72: 4600050431-30 | C72: 4600050431 | D72: 30 | E72: MXPO | F72: MXL | G72: 900004166 | H72: TC- ASFALTOS GDL LA VEGA | I72: 5003735 | J72: ASFALTOS GUADALAJARA SAPI DE CV | K72: Z04 | L72: (AP) 30 Dias | M72: 10000384 | N72: Arena Triturada Basalto Malla 4 | O72: DW68 | P72: MX-CED. GUADALAJARA | Q72: 20210801 | R72: 20281231 | S72: 20230629 | T72: 20281231 | U72: 330 | V72: MXN | W72: M3 | X72: 0 | Y72: MXN | Z72: M3 | AC72: 56103638 | AD72: 6644241540 | AE72: 1 | AF72: ENTREGADO | AG72: 1.61 | AH72: M3 | AI72: X | AJ72: 4 | AK72: V4 | AL72: 20230920 | AM72: DW68-900004166-10000384
A73: 900004166DW6810034701 | B73: 4600050431-10 | C73: 4600050431 | D73: 10 | E73: MXPO | F73: MXL | G73: 900004166 | H73: TC- ASFALTOS GDL LA VEGA | I73: 5003735 | J73: ASFALTOS GUADALAJARA SAPI DE CV | K73: Z04 | L73: (AP) 30 Dias | M73: 10034701 | N73: Grava Triturada Basalto 20 mm - 3/4 | O73: DW68 | P73: MX-CED. GUADALAJARA | Q73: 20210801 | R73: 20281231 | S73: 20230629 | T73: 20281231 | U73: 250 | V73: MXN | W73: M3 | X73: 0 | Y73: MXN | Z73: M3 | AC73: 56103637 | AD73: 6644241540 | AE73: 1 | AF73: ENTREGADO | AG73: 1.375 | AH73: M3 | AI73: X | AJ73: 4 | AK73: V4 | AL73: 20230920 | AM73: DW68-900004166-10034701
A74: 900005508DW68D26410000388 | B74: 4600050448-120 | C74: 4600050448 | D74: 120 | E74: MXPO | F74: MXL | G74: 900005508 | H74: TC-ED JUAN DAVALOS | I74: 5014444 | J74: DAVALOS GUTIERREZ JUAN JOSE | K74: N90 | L74: (AP) NAFIN 90 Dias | M74: 10000388 | N74: Grava Triturada Basalto 40 mm - 1 1/2" | O74: DW68 | P74: MX-CED. GUADALAJARA | Q74: 20210801 | R74: 20261231 | S74: 20220701 | T74: 20271231 | U74: 242 | V74: MXN | W74: M3 | X74: 117 | Y74: MXN | Z74: M3 | AA74: D264 | AB74: PD0083 GUADALAJARA I III | AC74: 56103637 | AD74: 6644241540 | AE74: 4 | AF74: ENTREGA DIRECTA | AG74: 1.395 | AH74: M3 | AI74: X | AJ74: 4 | AK74: V4 | AL74: 20230920 | AM74: DW68-900005508-D264-10000388-4
A75: 900005508DW68D20910000388 | B75: 4600050448-10 | C75: 4600050448 | D75: 10 | E75: MXPO | F75: MXL | G75: 900005508 | H75: TC-ED JUAN DAVALOS | I75: 5014444 | J75: DAVALOS GUTIERREZ JUAN JOSE | K75: N90 | L75: (AP) NAFIN 90 Dias | M75: 10000388 | N75: Grava Triturada Basalto 40 mm - 1 1/2" | O75: DW68 | P75: MX-CED. GUADALAJARA | Q75: 20210801 | R75: 20261231 | S75: 20220701 | T75: 20271231 | U75: 228 | V75: MXN | W75: M3 | X75: 103 | Y75: MXN | Z75: M3 | AA75: D209 | AB75: PD0127 MANANTIAL | AC75: 56103637 | AD75: 6644241540 | AE75: 4 | AF75: ENTREGA DIRECTA | AG75: 1.395 | AH75: M3 | AI75: X | AJ75: 4 | AK75: V4 | AL75: 20230920 | AM75: DW68-900005508-D209-10000388-4
A76: 900005508DW68D04210000388 | B76: 4600050448-140 | C76: 4600050448 | D76: 140 | E76: MXPO | F76: MXL | G76: 900005508 | H76: TC-ED JUAN DAVALOS | I76: 5014444 | J76: DAVALOS GUTIERREZ JUAN JOSE | K76: N90 | L76: (AP) NAFIN 90 Dias | M76: 10000388 | N76: Grava Triturada Basalto 40 mm - 1 1/2" | O76: DW68 | P76: MX-CED. GUADALAJARA | Q76: 20210801 | R76: 20261231 | S76: 20220701 | T76: 20271231 | U76: 254 | V76: MXN | W76: M3 | X76: 129 | Y76: MXN | Z76: M3 | AA76: D042 | AB76: PD0406 PLANTA PONIENTE | AC76: 56103637 | AD76: 6644241540 | AE76: 4 | AF76: ENTREGA DIRECTA | AG76: 1.395 | AH76: M3 | AI76: X | AJ76: 4 | AK76: V4 | AL76: 20230920 | AM76: DW68-900005508-D042-10000388-4
A77: 900005508DW68D24210000388 | B77: 4600050448-100 | C77: 4600050448 | D77: 100 | E77: MXPO | F77: MXL | G77: 900005508 | H77: TC-ED JUAN DAVALOS | I77: 5014444 | J77: DAVALOS GUTIERREZ JUAN JOSE | K77: N90 | L77: (AP) NAFIN 90 Dias | M77: 10000388 | N77: Grava Triturada Basalto 40 mm - 1 1/2" | O77: DW68 | P77: MX-CED. GUADALAJARA | Q77: 20210801 | R77: 20261231 | S77: 20220701 | T77: 20271231 | U77: 266 | V77: MXN | W77: M3 | X77: 141 | Y77: MXN | Z77: M3 | AA77: D242 | AB77: PD0454 CD. LA GRANJA II | AC77: 56103637 | AD77: 6644241540 | AE77: 4 | AF77: ENTREGA DIRECTA | AG77: 1.395 | AH77: M3 | AI77: X | AJ77: 4 | AK77: V4 | AL77: 20230920 | AM77: DW68-900005508-D242-10000388-4
A78: 900005508DW68D25110000388 | B78: 4600050448-180 | C78: 4600050448 | D78: 180 | E78: MXPO | F78: MXL | G78: 900005508 | H78: TC-ED JUAN DAVALOS | I78: 5014444 | J78: DAVALOS GUTIERREZ JUAN JOSE | K78: N90 | L78: (AP) NAFIN 90 Dias | M78: 10000388 | N78: Grava Triturada Basalto 40 mm - 1 1/2" | O78: DW68 | P78: MX-CED. GUADALAJARA | Q78: 20210801 | R78: 20261231 | S78: 20220701 | T78: 20271231 | U78: 227 | V78: MXN | W78: M3 | X78: 102 | Y78: MXN | Z78: M3 | AA78: D251 | AB78: PD0339 EL SALTO | AC78: 56103637 | AD78: 6644241540 | AE78: 4 | AF78: ENTREGA DIRECTA | AG78: 1.395 | AH78: M3 | AI78: X | AJ78: 4 | AK78: V4 | AL78: 20230920 | AM78: DW68-900005508-D251-10000388-4
A79: 900002068DW68D21410000835 | B79: 4600050418-20 | C79: 4600050418 | D79: 20 | E79: MXPO | F79: MXL | G79: 900002068 | H79: TC-ED- EL PACHON | I79: 5043944 | J79: CONSTRUCCIONES MAREVA DE OCCIDENTE | K79: Z04 | L79: (AP) 30 Dias | M79: 10000835 | N79: Arena Clasificada Río Malla 4 | O79: DW68 | P79: MX-CED. GUADALAJARA | Q79: 20210712 | R79: 20281231 | S79: 20230202 | T79: 20281231 | U79: 191.53 | V79: MXN | W79: M3 | X79: 125.53 | Y79: MXN | Z79: M3 | AA79: D214 | AB79: PD0174 EL SALTO 2 | AC79: 56103638 | AD79: 6644241540 | AE79: 4 | AF79: ENTREGA DIRECTA | AG79: 1.18 | AH79: M3 | AI79: X | AJ79: 4 | AK79: V4 | AL79: 20230920 | AM79: DW68-900002068-D214-10000835-4
A80: 900004153DW68D25110000388 | B80: 4600050430-390 | C80: 4600050430 | D80: 390 | E80: MXPO | F80: MXL | G80: 900004153 | H80: TC-ED GRAVASE PONCITLAN | I80: 5009010 | J80: GRAVASE SA DE CV | K80: Z04 | L80: (AP) 30 Dias | M80: 10000388 | N80: Grava Triturada Basalto 40 mm - 1 1/2" | O80: DW68 | P80: MX-CED. GUADALAJARA | Q80: 20210801 | R80: 20291231 | S80: 20260201 | T80: 20301231 | U80: 328.32 | V80: MXN | W80: TN | X80: 157.62 | Y80: MXN | Z80: TN | AA80: D251 | AB80: PD0339 EL SALTO | AC80: 56103637 | AD80: 6644241540 | AE80: 4 | AF80: ENTREGA DIRECTA | AG80: 1 | AH80: TO | AI80: X | AJ80: 4 | AK80: V4 | AL80: 20260304 | AM80: DW68-900004153-D251-10000388-4
A81: 900009395DW6810270898 | B81: 4600071760-10 | C81: 4600071760 | D81: 10 | E81: MXPO | F81: MXL | G81: 900009395 | H81: SF TC-GASA | I81: 5097224 | J81: TRITURADOS GASA SA DE CV | K81: Z09 | L81: (AP) 90 Dias | M81: 10270898 | N81: MP BASE H. TRIT. BASALTO 1 1/2" A FINOS | O81: DW68 | P81: MX-CED. GUADALAJARA | Q81: 20251110 | R81: 20301231 | S81: 20251110 | T81: 20301231 | U81: 270 | V81: MXN | W81: M3 | X81: 0 | Y81: MXN | Z81: M3 | AC81: 56103590 | AD81: 6644241540 | AE81: 2 | AF81: RECOGIDO | AG81: 1.551 | AH81: M3 | AI81: X | AJ81: 4 | AK81: V4 | AL81: 20251222 | AM81: DW68-900009395-10270898
A82: 900009420DW68D57710251385 | B82: 4600071943-270 | C82: 4600071943 | D82: 270 | E82: MXPO | F82: MXL | G82: 900009420 | H82: SF TC-ED HOLCIM GDL | I82: 5040590 | J82: HOLCIM MEXICO OPERACIONES SA DE CV | K82: Z06 | L82: (AP) 45 Dias | M82: 10251385 | N82: BASE H TRITURADA BASALTO 1 1/2" A FINOS- | O82: DW68 | P82: MX-CED. GUADALAJARA | Q82: 20260126 | R82: 20301231 | U82: 0 | V82: MXN | W82: TN | AA82: D577 | AB82: D577 PD0681 PROY APTO GDL | AC82: 56103590 | AD82: 6644241540 | AE82: 4 | AF82: ENTREGA DIRECTA | AG82: 1 | AH82: TO | AI82: X | AJ82: 4 | AK82: V4 | AL82: 20260331 | AM82: DW68-900009420-D577-10251385-4
A83: 900009420DW68D57710270913 | B83: 4600071943-300 | C83: 4600071943 | D83: 300 | E83: MXPO | F83: MXL | G83: 900009420 | H83: SF TC-ED HOLCIM GDL | I83: 5040590 | J83: HOLCIM MEXICO OPERACIONES SA DE CV | K83: Z06 | L83: (AP) 45 Dias | M83: 10270913 | N83: MP GRAVA TRIT. BASALTO 20 MM - 3/4 | O83: DW68 | P83: MX-CED. GUADALAJARA | Q83: 20260126 | R83: 20301231 | U83: 0 | V83: MXN | W83: TN | AA83: D577 | AB83: D577 PD0681 PROY APTO GDL | AC83: 56103637 | AD83: 6644241540 | AE83: 4 | AF83: ENTREGA DIRECTA | AG83: 1 | AH83: TO | AI83: X | AJ83: 4 | AK83: V4 | AL83: 20260331 | AM83: DW68-900009420-D577-10270913-4
A84: 900009420DW68ENV810209065 | B84: 4600071943-140 | C84: 4600071943 | D84: 140 | E84: MXPO | F84: MXL | G84: 900009420 | H84: SF TC-ED HOLCIM GDL | I84: 5040590 | J84: HOLCIM MEXICO OPERACIONES SA DE CV | K84: Z06 | L84: (AP) 45 Dias | M84: 10209065 | N84: FILTRO 5" A 7/8" | O84: DW68 | P84: MX-CED. GUADALAJARA | Q84: 20260126 | R84: 20301231 | S84: 20260126 | T84: 20301231 | U84: 145 | V84: MXN | W84: TN | X84: 0.01 | Y84: MXN | Z84: TN | AA84: ENV8 | AB84: Plataforma Aeropuerto GDL / GAP | AC84: 56103637 | AD84: 6644241540 | AE84: 4 | AF84: ENTREGA DIRECTA | AG84: 1 | AH84: TO | AI84: X | AJ84: 4 | AK84: V4 | AL84: 20260127 | AM84: DW68-900009420-ENV8-10209065-4
A85: 900000620DW68ENL110270911 | B85: 4600071941-20 | C85: 4600071941 | D85: 20 | E85: MXPO | F85: MXL | G85: 900000620 | H85: TC-ED- GRAVASE STA. ROSA | I85: 5009010 | J85: GRAVASE SA DE CV | K85: Z04 | L85: (AP) 30 Dias | M85: 10270911 | N85: MP GRAVA TRIT. BASALTO 40 MM - 1 1/2" | O85: DW68 | P85: MX-CED. GUADALAJARA | Q85: 20260126 | R85: 20301231 | S85: 20260126 | T85: 20301231 | U85: 214 | V85: MXN | W85: TN | X85: 0.01 | Y85: MXN | Z85: TN | AA85: ENL1 | AB85: MX-PD0681 INFRA APTO GDL | AC85: 56103637 | AD85: 6644241540 | AE85: 4 | AF85: ENTREGA DIRECTA | AG85: 1 | AH85: TO | AI85: X | AJ85: 4 | AK85: V4 | AL85: 20260127 | AM85: DW68-900000620-ENL1-10270911-4
A86: 900009234DW6810209065 | B86: 4600071790-10 | C86: 4600071790 | D86: 10 | E86: MXPO | F86: MXL | G86: 900009234 | H86: SF TC-GYB BURRITOS | I86: 5010137 | J86: URBANIZACIONES G Y B SA DE CV | K86: Z09 | L86: (AP) 90 Dias | M86: 10209065 | N86: FILTRO 5" A 7/8" | O86: DW68 | P86: MX-CED. GUADALAJARA | Q86: 20251124 | R86: 20301231 | S86: 20251124 | T86: 20301231 | U86: 145 | V86: MXN | W86: M3 | X86: 0 | Y86: MXN | Z86: M3 | AC86: 56103637 | AD86: 6644241540 | AE86: 1 | AF86: ENTREGADO | AG86: 1.365 | AH86: M3 | AI86: X | AJ86: 4 | AK86: V4 | AL86: 20251125 | AM86: DW68-900009234-10209065
A87: 900009419DW6810270912 | B87: 4600071812-30 | C87: 4600071812 | D87: 30 | E87: MXPO | F87: MXL | G87: 900009419 | H87: SF TC-HOLCIM GDL | I87: 5040590 | J87: HOLCIM MEXICO OPERACIONES SA DE CV | K87: Z06 | L87: (AP) 45 Dias | M87: 10270912 | N87: MP ARENA TRIT. BASALTO MALLA 4 | O87: DW68 | P87: MX-CED. GUADALAJARA | Q87: 20251202 | R87: 20301231 | S87: 20251202 | T87: 20301231 | U87: 179.4 | V87: MXN | W87: TN | X87: 0 | Y87: MXN | Z87: TN | AC87: 56103638 | AD87: 6644241540 | AE87: 1 | AF87: ENTREGADO | AG87: 1 | AH87: TO | AI87: X | AJ87: 4 | AK87: V4 | AL87: 20251203 | AM87: DW68-900009419-10270912
A88: 900009420DW68ENL110209065 | B88: 4600071943-80 | C88: 4600071943 | D88: 80 | E88: MXPO | F88: MXL | G88: 900009420 | H88: SF TC-ED HOLCIM GDL | I88: 5040590 | J88: HOLCIM MEXICO OPERACIONES SA DE CV | K88: Z06 | L88: (AP) 45 Dias | M88: 10209065 | N88: FILTRO 5" A 7/8" | O88: DW68 | P88: MX-CED. GUADALAJARA | Q88: 20260126 | R88: 20301231 | S88: 20260126 | T88: 20301231 | U88: 145 | V88: MXN | W88: TN | X88: 0.01 | Y88: MXN | Z88: TN | AA88: ENL1 | AB88: MX-PD0681 INFRA APTO GDL | AC88: 56103637 | AD88: 6644241540 | AE88: 4 | AF88: ENTREGA DIRECTA | AG88: 1 | AH88: TO | AI88: X | AJ88: 4 | AK88: V4 | AL88: 20260127 | AM88: DW68-900009420-ENL1-10209065-4
A89: 900009420DW68ENV910251385 | B89: 4600071943-210 | C89: 4600071943 | D89: 210 | E89: MXPO | F89: MXL | G89: 900009420 | H89: SF TC-ED HOLCIM GDL | I89: 5040590 | J89: HOLCIM MEXICO OPERACIONES SA DE CV | K89: Z06 | L89: (AP) 45 Dias | M89: 10251385 | N89: BASE H TRITURADA BASALTO 1 1/2" A FINOS- | O89: DW68 | P89: MX-CED. GUADALAJARA | Q89: 20260126 | R89: 20301231 | S89: 20260126 | T89: 20301231 | U89: 220 | V89: MXN | W89: TN | X89: 0.01 | Y89: MXN | Z89: TN | AA89: ENV9 | AB89: VIALIDADES AEROPUERTO GDL F1 Y F2 / | AC89: 56103590 | AD89: 6644241540 | AE89: 4 | AF89: ENTREGA DIRECTA | AG89: 1 | AH89: TO | AI89: X | AJ89: 4 | AK89: V4 | AL89: 20260127 | AM89: DW68-900009420-ENV9-10251385-4
A90: 900009420DW68ENEB10000439 | B90: 4600071943-10 | C90: 4600071943 | D90: 10 | E90: MXPO | F90: MXL | G90: 900009420 | H90: SF TC-ED HOLCIM GDL | I90: 5040590 | J90: HOLCIM MEXICO OPERACIONES SA DE CV | K90: Z06 | L90: (AP) 45 Dias | M90: 10000439 | N90: Grava Triturada Basalto 10 mm - 3/8" | O90: DW68 | P90: MX-CED. GUADALAJARA | Q90: 20260126 | R90: 20301231 | S90: 20260126 | T90: 20301231 | U90: 217.6 | V90: MXN | W90: TN | X90: 0.01 | Y90: MXN | Z90: TN | AA90: ENEB | AB90: DISTRIBUIDOR VIAL AEROP. GDL - T2 / | AC90: 56103637 | AD90: 6644241540 | AE90: 4 | AF90: ENTREGA DIRECTA | AG90: 1 | AH90: TO | AI90: X | AJ90: 4 | AK90: V4 | AL90: 20260127 | AM90: DW68-900009420-ENEB-10000439-4
A91: 900009396DW68ENV910270898 | B91: 4600071942-50 | C91: 4600071942 | D91: 50 | E91: MXPO | F91: MXL | G91: 900009396 | H91: SF TC-ED GASA | I91: 5097224 | J91: TRITURADOS GASA SA DE CV | K91: Z09 | L91: (AP) 90 Dias | M91: 10270898 | N91: MP BASE H. TRIT. BASALTO 1 1/2" A FINOS | O91: DW68 | P91: MX-CED. GUADALAJARA | Q91: 20260126 | R91: 20301231 | S91: 20260126 | T91: 20301231 | U91: 270 | V91: MXN | W91: M3 | X91: 0.01 | Y91: MXN | Z91: M3 | AA91: ENV9 | AB91: VIALIDADES AEROPUERTO GDL F1 Y F2 / | AC91: 56103590 | AD91: 6644241540 | AE91: 4 | AF91: ENTREGA DIRECTA | AG91: 1.551 | AH91: M3 | AI91: X | AJ91: 4 | AK91: V4 | AL91: 20260127 | AM91: DW68-900009396-ENV9-10270898-4
A92: 900009396DW68ENEB10209065 | B92: 4600071942-10 | C92: 4600071942 | D92: 10 | E92: MXPO | F92: MXL | G92: 900009396 | H92: SF TC-ED GASA | I92: 5097224 | J92: TRITURADOS GASA SA DE CV | K92: Z09 | L92: (AP) 90 Dias | M92: 10209065 | N92: FILTRO 5" A 7/8" | O92: DW68 | P92: MX-CED. GUADALAJARA | Q92: 20260126 | R92: 20301231 | S92: 20260126 | T92: 20301231 | U92: 190 | V92: MXN | W92: M3 | X92: 0.01 | Y92: MXN | Z92: M3 | AA92: ENEB | AB92: DISTRIBUIDOR VIAL AEROP. GDL - T2 / | AC92: 56103637 | AD92: 6644241540 | AE92: 4 | AF92: ENTREGA DIRECTA | AG92: 1.365 | AH92: M3 | AI92: X | AJ92: 4 | AK92: V4 | AL92: 20260127 | AM92: DW68-900009396-ENEB-10209065-4
A93: 900009420DW68ENL110251385 | B93: 4600071943-90 | C93: 4600071943 | D93: 90 | E93: MXPO | F93: MXL | G93: 900009420 | H93: SF TC-ED HOLCIM GDL | I93: 5040590 | J93: HOLCIM MEXICO OPERACIONES SA DE CV | K93: Z06 | L93: (AP) 45 Dias | M93: 10251385 | N93: BASE H TRITURADA BASALTO 1 1/2" A FINOS- | O93: DW68 | P93: MX-CED. GUADALAJARA | Q93: 20260126 | R93: 20301231 | S93: 20260126 | T93: 20301231 | U93: 220 | V93: MXN | W93: TN | X93: 0.01 | Y93: MXN | Z93: TN | AA93: ENL1 | AB93: MX-PD0681 INFRA APTO GDL | AC93: 56103590 | AD93: 6644241540 | AE93: 4 | AF93: ENTREGA DIRECTA | AG93: 1 | AH93: TO | AI93: X | AJ93: 4 | AK93: V4 | AL93: 20260127 | AM93: DW68-900009420-ENL1-10251385-4
A94: 900009419DW6810251385 | B94: 4600071812-60 | C94: 4600071812 | D94: 60 | E94: MXPO | F94: MXL | G94: 900009419 | H94: SF TC-HOLCIM GDL | I94: 5040590 | J94: HOLCIM MEXICO OPERACIONES SA DE CV | K94: Z06 | L94: (AP) 45 Dias | M94: 10251385 | N94: BASE H TRITURADA BASALTO 1 1/2" A FINOS- | O94: DW68 | P94: MX-CED. GUADALAJARA | Q94: 20251202 | R94: 20301231 | S94: 20251202 | T94: 20301231 | U94: 220 | V94: MXN | W94: TN | X94: 0 | Y94: MXN | Z94: TN | AC94: 56103590 | AD94: 6644241540 | AE94: 1 | AF94: ENTREGADO | AG94: 1 | AH94: TO | AI94: X | AJ94: 4 | AK94: V4 | AL94: 20251203 | AM94: DW68-900009419-10251385
A95: 900009419DW6810209065 | B95: 4600071812-10 | C95: 4600071812 | D95: 10 | E95: MXPO | F95: MXL | G95: 900009419 | H95: SF TC-HOLCIM GDL | I95: 5040590 | J95: HOLCIM MEXICO OPERACIONES SA DE CV | K95: Z06 | L95: (AP) 45 Dias | M95: 10209065 | N95: FILTRO 5" A 7/8" | O95: DW68 | P95: MX-CED. GUADALAJARA | Q95: 20251202 | R95: 20301231 | S95: 20251202 | T95: 20301231 | U95: 145 | V95: MXN | W95: TN | X95: 0 | Y95: MXN | Z95: TN | AC95: 56103637 | AD95: 6644241540 | AE95: 1 | AF95: ENTREGADO | AG95: 1 | AH95: TO | AI95: X | AJ95: 4 | AK95: V4 | AL95: 20251203 | AM95: DW68-900009419-10209065
A96: 900009419DW6810000439 | B96: 4600071812-40 | C96: 4600071812 | D96: 40 | E96: MXPO | F96: MXL | G96: 900009419 | H96: SF TC-HOLCIM GDL | I96: 5040590 | J96: HOLCIM MEXICO OPERACIONES SA DE CV | K96: Z06 | L96: (AP) 45 Dias | M96: 10000439 | N96: Grava Triturada Basalto 10 mm - 3/8" | O96: DW68 | P96: MX-CED. GUADALAJARA | Q96: 20251202 | R96: 20301231 | S96: 20251202 | T96: 20301231 | U96: 217.6 | V96: MXN | W96: TN | X96: 0 | Y96: MXN | Z96: TN | AC96: 56103637 | AD96: 6644241540 | AE96: 1 | AF96: ENTREGADO | AG96: 1 | AH96: TO | AI96: X | AJ96: 4 | AK96: V4 | AL96: 20251203 | AM96: DW68-900009419-10000439
A97: 900009420DW68ENV810000439 | B97: 4600071943-130 | C97: 4600071943 | D97: 130 | E97: MXPO | F97: MXL | G97: 900009420 | H97: SF TC-ED HOLCIM GDL | I97: 5040590 | J97: HOLCIM MEXICO OPERACIONES SA DE CV | K97: Z06 | L97: (AP) 45 Dias | M97: 10000439 | N97: Grava Triturada Basalto 10 mm - 3/8" | O97: DW68 | P97: MX-CED. GUADALAJARA | Q97: 20260126 | R97: 20301231 | S97: 20260126 | T97: 20301231 | U97: 217.6 | V97: MXN | W97: TN | X97: 0.01 | Y97: MXN | Z97: TN | AA97: ENV8 | AB97: Plataforma Aeropuerto GDL / GAP | AC97: 56103637 | AD97: 6644241540 | AE97: 4 | AF97: ENTREGA DIRECTA | AG97: 1 | AH97: TO | AI97: X | AJ97: 4 | AK97: V4 | AL97: 20260127 | AM97: DW68-900009420-ENV8-10000439-4
A98: 900009420DW68ENV910209065 | B98: 4600071943-200 | C98: 4600071943 | D98: 200 | E98: MXPO | F98: MXL | G98: 900009420 | H98: SF TC-ED HOLCIM GDL | I98: 5040590 | J98: HOLCIM MEXICO OPERACIONES SA DE CV | K98: Z06 | L98: (AP) 45 Dias | M98: 10209065 | N98: FILTRO 5" A 7/8" | O98: DW68 | P98: MX-CED. GUADALAJARA | Q98: 20260126 | R98: 20301231 | S98: 20260126 | T98: 20301231 | U98: 145 | V98: MXN | W98: TN | X98: 0.01 | Y98: MXN | Z98: TN | AA98: ENV9 | AB98: VIALIDADES AEROPUERTO GDL F1 Y F2 / | AC98: 56103637 | AD98: 6644241540 | AE98: 4 | AF98: ENTREGA DIRECTA | AG98: 1 | AH98: TO | AI98: X | AJ98: 4 | AK98: V4 | AL98: 20260127 | AM98: DW68-900009420-ENV9-10209065-4
A99: 900009420DW68ENL110000439 | B99: 4600071943-70 | C99: 4600071943 | D99: 70 | E99: MXPO | F99: MXL | G99: 900009420 | H99: SF TC-ED HOLCIM GDL | I99: 5040590 | J99: HOLCIM MEXICO OPERACIONES SA DE CV | K99: Z06 | L99: (AP) 45 Dias | M99: 10000439 | N99: Grava Triturada Basalto 10 mm - 3/8" | O99: DW68 | P99: MX-CED. GUADALAJARA | Q99: 20260126 | R99: 20301231 | S99: 20260126 | T99: 20301231 | U99: 217.6 | V99: MXN | W99: TN | X99: 0.01 | Y99: MXN | Z99: TN | AA99: ENL1 | AB99: MX-PD0681 INFRA APTO GDL | AC99: 56103637 | AD99: 6644241540 | AE99: 4 | AF99: ENTREGA DIRECTA | AG99: 1 | AH99: TO | AI99: X | AJ99: 4 | AK99: V4 | AL99: 20260127 | AM99: DW68-900009420-ENL1-10000439-4
A100: 900009420DW68ENEB10270912 | B100: 4600071943-50 | C100: 4600071943 | D100: 50 | E100: MXPO | F100: MXL | G100: 900009420 | H100: SF TC-ED HOLCIM GDL | I100: 5040590 | J100: HOLCIM MEXICO OPERACIONES SA DE CV | K100: Z06 | L100: (AP) 45 Dias | M100: 10270912 | N100: MP ARENA TRIT. BASALTO MALLA 4 | O100: DW68 | P100: MX-CED. GUADALAJARA | Q100: 20260126 | R100: 20301231 | S100: 20260127 | T100: 99991231 | U100: 179.4 | V100: MXN | W100: TN | X100: 0.01 | Y100: MXN | Z100: TN | AA100: ENEB | AB100: DISTRIBUIDOR VIAL AEROP. GDL - T2 / | AC100: 56103638 | AD100: 6644241540 | AE100: 4 | AF100: ENTREGA DIRECTA | AG100: 1 | AH100: TO | AI100: X | AJ100: 4 | AK100: V4 | AL100: 20260127 | AM100: DW68-900009420-ENEB-10270912-4
A101: 900009420DW68ENV910270913 | B101: 4600071943-240 | C101: 4600071943 | D101: 240 | E101: MXPO | F101: MXL | G101: 900009420 | H101: SF TC-ED HOLCIM GDL | I101: 5040590 | J101: HOLCIM MEXICO OPERACIONES SA DE CV | K101: Z06 | L101: (AP) 45 Dias | M101: 10270913 | N101: MP GRAVA TRIT. BASALTO 20 MM - 3/4 | O101: DW68 | P101: MX-CED. GUADALAJARA | Q101: 20260126 | R101: 20301231 | S101: 20260126 | T101: 20301231 | U101: 202.8 | V101: MXN | W101: TN | X101: 0.01 | Y101: MXN | Z101: TN | AA101: ENV9 | AB101: VIALIDADES AEROPUERTO GDL F1 Y F2 / | AC101: 56103637 | AD101: 6644241540 | AE101: 4 | AF101: ENTREGA DIRECTA | AG101: 1 | AH101: TO | AI101: X | AJ101: 4 | AK101: V4 | AL101: 20260127 | AM101: DW68-900009420-ENV9-10270913-4
A102: 900009396DW68ENV910209065 | B102: 4600071942-40 | C102: 4600071942 | D102: 40 | E102: MXPO | F102: MXL | G102: 900009396 | H102: SF TC-ED GASA | I102: 5097224 | J102: TRITURADOS GASA SA DE CV | K102: Z09 | L102: (AP) 90 Dias | M102: 10209065 | N102: FILTRO 5" A 7/8" | O102: DW68 | P102: MX-CED. GUADALAJARA | Q102: 20260126 | R102: 20301231 | S102: 20260126 | T102: 20301231 | U102: 190 | V102: MXN | W102: M3 | X102: 0.01 | Y102: MXN | Z102: M3 | AA102: ENV9 | AB102: VIALIDADES AEROPUERTO GDL F1 Y F2 / | AC102: 56103637 | AD102: 6644241540 | AE102: 4 | AF102: ENTREGA DIRECTA | AG102: 1.365 | AH102: M3 | AI102: X | AJ102: 4 | AK102: V4 | AL102: 20260127 | AM102: DW68-900009396-ENV9-10209065-4
A103: 900009420DW68ENV810270913 | B103: 4600071943-180 | C103: 4600071943 | D103: 180 | E103: MXPO | F103: MXL | G103: 900009420 | H103: SF TC-ED HOLCIM GDL | I103: 5040590 | J103: HOLCIM MEXICO OPERACIONES SA DE CV | K103: Z06 | L103: (AP) 45 Dias | M103: 10270913 | N103: MP GRAVA TRIT. BASALTO 20 MM - 3/4 | O103: DW68 | P103: MX-CED. GUADALAJARA | Q103: 20260126 | R103: 20301231 | S103: 20260126 | T103: 20301231 | U103: 202.8 | V103: MXN | W103: TN | X103: 0.01 | Y103: MXN | Z103: TN | AA103: ENV8 | AB103: Plataforma Aeropuerto GDL / GAP | AC103: 56103637 | AD103: 6644241540 | AE103: 4 | AF103: ENTREGA DIRECTA | AG103: 1 | AH103: TO | AI103: X | AJ103: 4 | AK103: V4 | AL103: 20260127 | AM103: DW68-900009420-ENV8-10270913-4
A104: 900009420DW68ENV810251385 | B104: 4600071943-150 | C104: 4600071943 | D104: 150 | E104: MXPO | F104: MXL | G104: 900009420 | H104: SF TC-ED HOLCIM GDL | I104: 5040590 | J104: HOLCIM MEXICO OPERACIONES SA DE CV | K104: Z06 | L104: (AP) 45 Dias | M104: 10251385 | N104: BASE H TRITURADA BASALTO 1 1/2" A FINOS- | O104: DW68 | P104: MX-CED. GUADALAJARA | Q104: 20260126 | R104: 20301231 | S104: 20260126 | T104: 20301231 | U104: 220 | V104: MXN | W104: TN | X104: 0.01 | Y104: MXN | Z104: TN | AA104: ENV8 | AB104: Plataforma Aeropuerto GDL / GAP | AC104: 56103590 | AD104: 6644241540 | AE104: 4 | AF104: ENTREGA DIRECTA | AG104: 1 | AH104: TO | AI104: X | AJ104: 4 | AK104: V4 | AL104: 20260127 | AM104: DW68-900009420-ENV8-10251385-4
A105: 900009420DW68ENV810270912 | B105: 4600071943-170 | C105: 4600071943 | D105: 170 | E105: MXPO | F105: MXL | G105: 900009420 | H105: SF TC-ED HOLCIM GDL | I105: 5040590 | J105: HOLCIM MEXICO OPERACIONES SA DE CV | K105: Z06 | L105: (AP) 45 Dias | M105: 10270912 | N105: MP ARENA TRIT. BASALTO MALLA 4 | O105: DW68 | P105: MX-CED. GUADALAJARA | Q105: 20260126 | R105: 20301231 | S105: 20260126 | T105: 20301231 | U105: 179.4 | V105: MXN | W105: TN | X105: 0.01 | Y105: MXN | Z105: TN | AA105: ENV8 | AB105: Plataforma Aeropuerto GDL / GAP | AC105: 56103638 | AD105: 6644241540 | AE105: 4 | AF105: ENTREGA DIRECTA | AG105: 1 | AH105: TO | AI105: X | AJ105: 4 | AK105: V4 | AL105: 20260127 | AM105: DW68-900009420-ENV8-10270912-4
A106: 900009420DW68ENEB10251385 | B106: 4600071943-30 | C106: 4600071943 | D106: 30 | E106: MXPO | F106: MXL | G106: 900009420 | H106: SF TC-ED HOLCIM GDL | I106: 5040590 | J106: HOLCIM MEXICO OPERACIONES SA DE CV | K106: Z06 | L106: (AP) 45 Dias | M106: 10251385 | N106: BASE H TRITURADA BASALTO 1 1/2" A FINOS- | O106: DW68 | P106: MX-CED. GUADALAJARA | Q106: 20260126 | R106: 20301231 | S106: 20260126 | T106: 20301231 | U106: 220 | V106: MXN | W106: TN | X106: 0.01 | Y106: MXN | Z106: TN | AA106: ENEB | AB106: DISTRIBUIDOR VIAL AEROP. GDL - T2 / | AC106: 56103590 | AD106: 6644241540 | AE106: 4 | AF106: ENTREGA DIRECTA | AG106: 1 | AH106: TO | AI106: X | AJ106: 4 | AK106: V4 | AL106: 20260127 | AM106: DW68-900009420-ENEB-10251385-4
A107: 900009420DW68ENV910270912 | B107: 4600071943-230 | C107: 4600071943 | D107: 230 | E107: MXPO | F107: MXL | G107: 900009420 | H107: SF TC-ED HOLCIM GDL | I107: 5040590 | J107: HOLCIM MEXICO OPERACIONES SA DE CV | K107: Z06 | L107: (AP) 45 Dias | M107: 10270912 | N107: MP ARENA TRIT. BASALTO MALLA 4 | O107: DW68 | P107: MX-CED. GUADALAJARA | Q107: 20260126 | R107: 20301231 | S107: 20260126 | T107: 20301231 | U107: 179.4 | V107: MXN | W107: TN | X107: 0.01 | Y107: MXN | Z107: TN | AA107: ENV9 | AB107: VIALIDADES AEROPUERTO GDL F1 Y F2 / | AC107: 56103638 | AD107: 6644241540 | AE107: 4 | AF107: ENTREGA DIRECTA | AG107: 1 | AH107: TO | AI107: X | AJ107: 4 | AK107: V4 | AL107: 20260127 | AM107: DW68-900009420-ENV9-10270912-4
A108: 900009396DW68ENL110270898 | B108: 4600071942-30 | C108: 4600071942 | D108: 30 | E108: MXPO | F108: MXL | G108: 900009396 | H108: SF TC-ED GASA | I108: 5097224 | J108: TRITURADOS GASA SA DE CV | K108: Z09 | L108: (AP) 90 Dias | M108: 10270898 | N108: MP BASE H. TRIT. BASALTO 1 1/2" A FINOS | O108: DW68 | P108: MX-CED. GUADALAJARA | Q108: 20260126 | R108: 20301231 | S108: 20260126 | T108: 20301231 | U108: 270 | V108: MXN | W108: M3 | X108: 0.01 | Y108: MXN | Z108: M3 | AA108: ENL1 | AB108: MX-PD0681 INFRA APTO GDL | AC108: 56103590 | AD108: 6644241540 | AE108: 4 | AF108: ENTREGA DIRECTA | AG108: 1.551 | AH108: M3 | AI108: X | AJ108: 4 | AK108: V4 | AL108: 20260127 | AM108: DW68-900009396-ENL1-10270898-4
A109: 900009396DW68ENL110209065 | B109: 4600071942-20 | C109: 4600071942 | D109: 20 | E109: MXPO | F109: MXL | G109: 900009396 | H109: SF TC-ED GASA | I109: 5097224 | J109: TRITURADOS GASA SA DE CV | K109: Z09 | L109: (AP) 90 Dias | M109: 10209065 | N109: FILTRO 5" A 7/8" | O109: DW68 | P109: MX-CED. GUADALAJARA | Q109: 20260126 | R109: 20301231 | S109: 20260126 | T109: 20301231 | U109: 190 | V109: MXN | W109: M3 | X109: 0.01 | Y109: MXN | Z109: M3 | AA109: ENL1 | AB109: MX-PD0681 INFRA APTO GDL | AC109: 56103637 | AD109: 6644241540 | AE109: 4 | AF109: ENTREGA DIRECTA | AG109: 1.365 | AH109: M3 | AI109: X | AJ109: 4 | AK109: V4 | AL109: 20260127 | AM109: DW68-900009396-ENL1-10209065-4
A110: 900009395DW6810209065 | B110: 4600071760-20 | C110: 4600071760 | D110: 20 | E110: MXPO | F110: MXL | G110: 900009395 | H110: SF TC-GASA | I110: 5097224 | J110: TRITURADOS GASA SA DE CV | K110: Z09 | L110: (AP) 90 Dias | M110: 10209065 | N110: FILTRO 5" A 7/8" | O110: DW68 | P110: MX-CED. GUADALAJARA | Q110: 20251110 | R110: 20301231 | S110: 20251121 | T110: 20301231 | U110: 190 | V110: MXN | W110: M3 | X110: 0 | Y110: MXN | Z110: M3 | AC110: 56103637 | AD110: 6644241540 | AE110: 2 | AF110: RECOGIDO | AG110: 1.365 | AH110: M3 | AI110: X | AJ110: 4 | AK110: V4 | AL110: 20251222 | AM110: DW68-900009395-10209065
A111: 900009419DW6810270913 | B111: 4600071812-50 | C111: 4600071812 | D111: 50 | E111: MXPO | F111: MXL | G111: 900009419 | H111: SF TC-HOLCIM GDL | I111: 5040590 | J111: HOLCIM MEXICO OPERACIONES SA DE CV | K111: Z06 | L111: (AP) 45 Dias | M111: 10270913 | N111: MP GRAVA TRIT. BASALTO 20 MM - 3/4 | O111: DW68 | P111: MX-CED. GUADALAJARA | Q111: 20251202 | R111: 20301231 | S111: 20251202 | T111: 20301231 | U111: 202.8 | V111: MXN | W111: TN | X111: 0 | Y111: MXN | Z111: TN | AC111: 56103637 | AD111: 6644241540 | AE111: 1 | AF111: ENTREGADO | AG111: 1 | AH111: TO | AI111: X | AJ111: 4 | AK111: V4 | AL111: 20251203 | AM111: DW68-900009419-10270913
A112: 900009420DW68ENEB10209065 | B112: 4600071943-20 | C112: 4600071943 | D112: 20 | E112: MXPO | F112: MXL | G112: 900009420 | H112: SF TC-ED HOLCIM GDL | I112: 5040590 | J112: HOLCIM MEXICO OPERACIONES SA DE CV | K112: Z06 | L112: (AP) 45 Dias | M112: 10209065 | N112: FILTRO 5" A 7/8" | O112: DW68 | P112: MX-CED. GUADALAJARA | Q112: 20260126 | R112: 20301231 | S112: 20260126 | T112: 20301231 | U112: 145 | V112: MXN | W112: TN | X112: 0.01 | Y112: MXN | Z112: TN | AA112: ENEB | AB112: DISTRIBUIDOR VIAL AEROP. GDL - T2 / | AC112: 56103637 | AD112: 6644241540 | AE112: 4 | AF112: ENTREGA DIRECTA | AG112: 1 | AH112: TO | AI112: X | AJ112: 4 | AK112: V4 | AL112: 20260127 | AM112: DW68-900009420-ENEB-10209065-4
A113: 900009420DW68ENL110270912 | B113: 4600071943-110 | C113: 4600071943 | D113: 110 | E113: MXPO | F113: MXL | G113: 900009420 | H113: SF TC-ED HOLCIM GDL | I113: 5040590 | J113: HOLCIM MEXICO OPERACIONES SA DE CV | K113: Z06 | L113: (AP) 45 Dias | M113: 10270912 | N113: MP ARENA TRIT. BASALTO MALLA 4 | O113: DW68 | P113: MX-CED. GUADALAJARA | Q113: 20260126 | R113: 20301231 | S113: 20260126 | T113: 20301231 | U113: 179.4 | V113: MXN | W113: TN | X113: 0.01 | Y113: MXN | Z113: TN | AA113: ENL1 | AB113: MX-PD0681 INFRA APTO GDL | AC113: 56103638 | AD113: 6644241540 | AE113: 4 | AF113: ENTREGA DIRECTA | AG113: 1 | AH113: TO | AI113: X | AJ113: 4 | AK113: V4 | AL113: 20260127 | AM113: DW68-900009420-ENL1-10270912-4
A114: 900009420DW68ENEB10270913 | B114: 4600071943-60 | C114: 4600071943 | D114: 60 | E114: MXPO | F114: MXL | G114: 900009420 | H114: SF TC-ED HOLCIM GDL | I114: 5040590 | J114: HOLCIM MEXICO OPERACIONES SA DE CV | K114: Z06 | L114: (AP) 45 Dias | M114: 10270913 | N114: MP GRAVA TRIT. BASALTO 20 MM - 3/4 | O114: DW68 | P114: MX-CED. GUADALAJARA | Q114: 20260126 | R114: 20301231 | S114: 20260126 | T114: 99991231 | U114: 202.8 | V114: MXN | W114: TN | X114: 0.01 | Y114: MXN | Z114: TN | AA114: ENEB | AB114: DISTRIBUIDOR VIAL AEROP. GDL - T2 / | AC114: 56103637 | AD114: 6644241540 | AE114: 4 | AF114: ENTREGA DIRECTA | AG114: 1 | AH114: TO | AI114: X | AJ114: 4 | AK114: V4 | AL114: 20260127 | AM114: DW68-900009420-ENEB-10270913-4
A115: 900009420DW68ENL110270913 | B115: 4600071943-120 | C115: 4600071943 | D115: 120 | E115: MXPO | F115: MXL | G115: 900009420 | H115: SF TC-ED HOLCIM GDL | I115: 5040590 | J115: HOLCIM MEXICO OPERACIONES SA DE CV | K115: Z06 | L115: (AP) 45 Dias | M115: 10270913 | N115: MP GRAVA TRIT. BASALTO 20 MM - 3/4 | O115: DW68 | P115: MX-CED. GUADALAJARA | Q115: 20260126 | R115: 20301231 | S115: 20260126 | T115: 20301231 | U115: 202.8 | V115: MXN | W115: TN | X115: 0.01 | Y115: MXN | Z115: TN | AA115: ENL1 | AB115: MX-PD0681 INFRA APTO GDL | AC115: 56103637 | AD115: 6644241540 | AE115: 4 | AF115: ENTREGA DIRECTA | AG115: 1 | AH115: TO | AI115: X | AJ115: 4 | AK115: V4 | AL115: 20260127 | AM115: DW68-900009420-ENL1-10270913-4
A116: 900009420DW68ENV910000439 | B116: 4600071943-190 | C116: 4600071943 | D116: 190 | E116: MXPO | F116: MXL | G116: 900009420 | H116: SF TC-ED HOLCIM GDL | I116: 5040590 | J116: HOLCIM MEXICO OPERACIONES SA DE CV | K116: Z06 | L116: (AP) 45 Dias | M116: 10000439 | N116: Grava Triturada Basalto 10 mm - 3/8" | O116: DW68 | P116: MX-CED. GUADALAJARA | Q116: 20260126 | R116: 20301231 | S116: 20260126 | T116: 20301231 | U116: 217.6 | V116: MXN | W116: TN | X116: 0.01 | Y116: MXN | Z116: TN | AA116: ENV9 | AB116: VIALIDADES AEROPUERTO GDL F1 Y F2 / | AC116: 56103637 | AD116: 6644241540 | AE116: 4 | AF116: ENTREGA DIRECTA | AG116: 1 | AH116: TO | AI116: X | AJ116: 4 | AK116: V4 | AL116: 20260127 | AM116: DW68-900009420-ENV9-10000439-4
...
