Workbook

Sheet Base Cedis DW70
N1: VENTA | Q1: COSTO
A2: CONCAT1 | B2: CONCAT2 | C2: No. SF | D2: Nombre SF | E2: Cedis | F2: Destino | G2: Condicion de Expedicion | H2: Nombre Destino | I2: No. de material | J2: Nombre de material | K2: PV | L2: Inicio de vigencia | M2: Fin de vigencia | N2: Importe MP | O2: Importe Flete | P2: UM Venta | Q2: Importe Costo | R2: UM Costo | S2: Validacion 1 | T2: Validacion 2
A3: =CONCATENATE(C3,E3,F3,I3) | B3: =CONCATENATE(C3,E3,I3) | C3: 900000034 | D3: =IFERROR(VLOOKUP(C3,TRAOPE!$G:$H,2,0),"") | E3: DW70 | F3: D074 | G3: =IFERROR(VLOOKUP(A3,Flete!$A:$E,5,0),"") | H3: =IFERROR(VLOOKUP(F3,TRAOPE!$AA:$AB,2,0),"") | I3: 10000623 | J3: =IFERROR(VLOOKUP(I3,Materiales!$A:$H,8,0),"") | K3: =IFERROR(VLOOKUP(I3,Materiales!$A:$G,7,0),"") | L3: 20250701 | M3: 99991231 | N3: 100 | O3: =IFERROR(VLOOKUP(A3,Flete!$A:$J,10,0),"") | P3: TN | Q3: =IFERROR(IFERROR(VLOOKUP(A3,TRAOPE!$A:$U,21,0),VLOOKUP(B3,TRAOPE!$A:$U,21,0)),"") | R3: =IFERROR(IFERROR(VLOOKUP(A3,TRAOPE!$A:$W,23,0),VLOOKUP(B3,TRAOPE!$A:$W,23,0)),"") | S3: =IF(AND(P3="TN",R3="TN"),N3+N(O3),IF(G3&""="1",N(K3)*N3,(N3+N(O3))*N(K3))) | T3: =IF(Q3="","",Q3-S3)
A4: =CONCATENATE(C4,E4,F4,I4) | B4: =CONCATENATE(C4,E4,I4) | C4: 900000034 | D4: =IFERROR(VLOOKUP(C4,TRAOPE!$G:$H,2,0),"") | E4: DW70 | F4: D074 | G4: =IFERROR(VLOOKUP(A4,Flete!$A:$E,5,0),"") | H4: =IFERROR(VLOOKUP(F4,TRAOPE!$AA:$AB,2,0),"") | I4: 10000811 | J4: =IFERROR(VLOOKUP(I4,Materiales!$A:$H,8,0),"") | K4: =IFERROR(VLOOKUP(I4,Materiales!$A:$G,7,0),"") | L4: 20230501 | M4: 20250131 | N4: 100.01 | O4: =IFERROR(VLOOKUP(A4,Flete!$A:$J,10,0),"") | P4: TN | Q4: =IFERROR(IFERROR(VLOOKUP(A4,TRAOPE!$A:$U,21,0),VLOOKUP(B4,TRAOPE!$A:$U,21,0)),"") | R4: =IFERROR(IFERROR(VLOOKUP(A4,TRAOPE!$A:$W,23,0),VLOOKUP(B4,TRAOPE!$A:$W,23,0)),"") | S4: =IF(AND(P4="TN",R4="TN"),N4+N(O4),IF(G4&""="1",N(K4)*N4,(N4+N(O4))*N(K4))) | T4: =IF(Q4="","",Q4-S4)
A5: =CONCATENATE(C5,E5,F5,I5) | B5: =CONCATENATE(C5,E5,I5) | C5: 900000034 | D5: =IFERROR(VLOOKUP(C5,TRAOPE!$G:$H,2,0),"") | E5: DW70 | F5: D075 | G5: =IFERROR(VLOOKUP(A5,Flete!$A:$E,5,0),"") | H5: =IFERROR(VLOOKUP(F5,TRAOPE!$AA:$AB,2,0),"") | I5: 10000623 | J5: =IFERROR(VLOOKUP(I5,Materiales!$A:$H,8,0),"") | K5: =IFERROR(VLOOKUP(I5,Materiales!$A:$G,7,0),"") | L5: 20250701 | M5: 99991231 | N5: 100 | O5: =IFERROR(VLOOKUP(A5,Flete!$A:$J,10,0),"") | P5: TN | Q5: =IFERROR(IFERROR(VLOOKUP(A5,TRAOPE!$A:$U,21,0),VLOOKUP(B5,TRAOPE!$A:$U,21,0)),"") | R5: =IFERROR(IFERROR(VLOOKUP(A5,TRAOPE!$A:$W,23,0),VLOOKUP(B5,TRAOPE!$A:$W,23,0)),"") | S5: =IF(AND(P5="TN",R5="TN"),N5+N(O5),IF(G5&""="1",N(K5)*N5,(N5+N(O5))*N(K5))) | T5: =IF(Q5="","",Q5-S5)
A6: =CONCATENATE(C6,E6,F6,I6) | B6: =CONCATENATE(C6,E6,I6) | C6: 900000034 | D6: =IFERROR(VLOOKUP(C6,TRAOPE!$G:$H,2,0),"") | E6: DW70 | F6: D075 | G6: =IFERROR(VLOOKUP(A6,Flete!$A:$E,5,0),"") | H6: =IFERROR(VLOOKUP(F6,TRAOPE!$AA:$AB,2,0),"") | I6: 10000811 | J6: =IFERROR(VLOOKUP(I6,Materiales!$A:$H,8,0),"") | K6: =IFERROR(VLOOKUP(I6,Materiales!$A:$G,7,0),"") | L6: 20230501 | M6: 20250131 | N6: 100.01 | O6: =IFERROR(VLOOKUP(A6,Flete!$A:$J,10,0),"") | P6: TN | Q6: =IFERROR(IFERROR(VLOOKUP(A6,TRAOPE!$A:$U,21,0),VLOOKUP(B6,TRAOPE!$A:$U,21,0)),"") | R6: =IFERROR(IFERROR(VLOOKUP(A6,TRAOPE!$A:$W,23,0),VLOOKUP(B6,TRAOPE!$A:$W,23,0)),"") | S6: =IF(AND(P6="TN",R6="TN"),N6+N(O6),IF(G6&""="1",N(K6)*N6,(N6+N(O6))*N(K6))) | T6: =IF(Q6="","",Q6-S6)
A7: =CONCATENATE(C7,E7,F7,I7) | B7: =CONCATENATE(C7,E7,I7) | C7: 900000034 | D7: =IFERROR(VLOOKUP(C7,TRAOPE!$G:$H,2,0),"") | E7: DW70 | F7: D077 | G7: =IFERROR(VLOOKUP(A7,Flete!$A:$E,5,0),"") | H7: =IFERROR(VLOOKUP(F7,TRAOPE!$AA:$AB,2,0),"") | I7: 10000623 | J7: =IFERROR(VLOOKUP(I7,Materiales!$A:$H,8,0),"") | K7: =IFERROR(VLOOKUP(I7,Materiales!$A:$G,7,0),"") | L7: 20260508 | M7: 99991231 | N7: 100 | O7: =IFERROR(VLOOKUP(A7,Flete!$A:$J,10,0),"") | P7: TN | Q7: =IFERROR(IFERROR(VLOOKUP(A7,TRAOPE!$A:$U,21,0),VLOOKUP(B7,TRAOPE!$A:$U,21,0)),"") | R7: =IFERROR(IFERROR(VLOOKUP(A7,TRAOPE!$A:$W,23,0),VLOOKUP(B7,TRAOPE!$A:$W,23,0)),"") | S7: =IF(AND(P7="TN",R7="TN"),N7+N(O7),IF(G7&""="1",N(K7)*N7,(N7+N(O7))*N(K7))) | T7: =IF(Q7="","",Q7-S7)
A8: =CONCATENATE(C8,E8,F8,I8) | B8: =CONCATENATE(C8,E8,I8) | C8: 900000034 | D8: =IFERROR(VLOOKUP(C8,TRAOPE!$G:$H,2,0),"") | E8: DW70 | F8: D077 | G8: =IFERROR(VLOOKUP(A8,Flete!$A:$E,5,0),"") | H8: =IFERROR(VLOOKUP(F8,TRAOPE!$AA:$AB,2,0),"") | I8: 10000811 | J8: =IFERROR(VLOOKUP(I8,Materiales!$A:$H,8,0),"") | K8: =IFERROR(VLOOKUP(I8,Materiales!$A:$G,7,0),"") | L8: 20230501 | M8: 20250131 | N8: 100.01 | O8: =IFERROR(VLOOKUP(A8,Flete!$A:$J,10,0),"") | P8: TN | Q8: =IFERROR(IFERROR(VLOOKUP(A8,TRAOPE!$A:$U,21,0),VLOOKUP(B8,TRAOPE!$A:$U,21,0)),"") | R8: =IFERROR(IFERROR(VLOOKUP(A8,TRAOPE!$A:$W,23,0),VLOOKUP(B8,TRAOPE!$A:$W,23,0)),"") | S8: =IF(AND(P8="TN",R8="TN"),N8+N(O8),IF(G8&""="1",N(K8)*N8,(N8+N(O8))*N(K8))) | T8: =IF(Q8="","",Q8-S8)
A9: =CONCATENATE(C9,E9,F9,I9) | B9: =CONCATENATE(C9,E9,I9) | C9: 900000034 | D9: =IFERROR(VLOOKUP(C9,TRAOPE!$G:$H,2,0),"") | E9: DW70 | F9: D079 | G9: =IFERROR(VLOOKUP(A9,Flete!$A:$E,5,0),"") | H9: =IFERROR(VLOOKUP(F9,TRAOPE!$AA:$AB,2,0),"") | I9: 10000623 | J9: =IFERROR(VLOOKUP(I9,Materiales!$A:$H,8,0),"") | K9: =IFERROR(VLOOKUP(I9,Materiales!$A:$G,7,0),"") | L9: 20250701 | M9: 99991231 | N9: 100 | O9: =IFERROR(VLOOKUP(A9,Flete!$A:$J,10,0),"") | P9: TN | Q9: =IFERROR(IFERROR(VLOOKUP(A9,TRAOPE!$A:$U,21,0),VLOOKUP(B9,TRAOPE!$A:$U,21,0)),"") | R9: =IFERROR(IFERROR(VLOOKUP(A9,TRAOPE!$A:$W,23,0),VLOOKUP(B9,TRAOPE!$A:$W,23,0)),"") | S9: =IF(AND(P9="TN",R9="TN"),N9+N(O9),IF(G9&""="1",N(K9)*N9,(N9+N(O9))*N(K9))) | T9: =IF(Q9="","",Q9-S9)
A10: =CONCATENATE(C10,E10,F10,I10) | B10: =CONCATENATE(C10,E10,I10) | C10: 900000034 | D10: =IFERROR(VLOOKUP(C10,TRAOPE!$G:$H,2,0),"") | E10: DW70 | F10: D079 | G10: =IFERROR(VLOOKUP(A10,Flete!$A:$E,5,0),"") | H10: =IFERROR(VLOOKUP(F10,TRAOPE!$AA:$AB,2,0),"") | I10: 10000811 | J10: =IFERROR(VLOOKUP(I10,Materiales!$A:$H,8,0),"") | K10: =IFERROR(VLOOKUP(I10,Materiales!$A:$G,7,0),"") | L10: 20230501 | M10: 20250131 | N10: 100.01 | O10: =IFERROR(VLOOKUP(A10,Flete!$A:$J,10,0),"") | P10: TN | Q10: =IFERROR(IFERROR(VLOOKUP(A10,TRAOPE!$A:$U,21,0),VLOOKUP(B10,TRAOPE!$A:$U,21,0)),"") | R10: =IFERROR(IFERROR(VLOOKUP(A10,TRAOPE!$A:$W,23,0),VLOOKUP(B10,TRAOPE!$A:$W,23,0)),"") | S10: =IF(AND(P10="TN",R10="TN"),N10+N(O10),IF(G10&""="1",N(K10)*N10,(N10+N(O10))*N(K10))) | T10: =IF(Q10="","",Q10-S10)
A11: =CONCATENATE(C11,E11,F11,I11) | B11: =CONCATENATE(C11,E11,I11) | C11: 900000034 | D11: =IFERROR(VLOOKUP(C11,TRAOPE!$G:$H,2,0),"") | E11: DW70 | F11: D080 | G11: =IFERROR(VLOOKUP(A11,Flete!$A:$E,5,0),"") | H11: =IFERROR(VLOOKUP(F11,TRAOPE!$AA:$AB,2,0),"") | I11: 10000623 | J11: =IFERROR(VLOOKUP(I11,Materiales!$A:$H,8,0),"") | K11: =IFERROR(VLOOKUP(I11,Materiales!$A:$G,7,0),"") | L11: 20250701 | M11: 99991231 | N11: 100 | O11: =IFERROR(VLOOKUP(A11,Flete!$A:$J,10,0),"") | P11: TN | Q11: =IFERROR(IFERROR(VLOOKUP(A11,TRAOPE!$A:$U,21,0),VLOOKUP(B11,TRAOPE!$A:$U,21,0)),"") | R11: =IFERROR(IFERROR(VLOOKUP(A11,TRAOPE!$A:$W,23,0),VLOOKUP(B11,TRAOPE!$A:$W,23,0)),"") | S11: =IF(AND(P11="TN",R11="TN"),N11+N(O11),IF(G11&""="1",N(K11)*N11,(N11+N(O11))*N(K11))) | T11: =IF(Q11="","",Q11-S11)
A12: =CONCATENATE(C12,E12,F12,I12) | B12: =CONCATENATE(C12,E12,I12) | C12: 900000034 | D12: =IFERROR(VLOOKUP(C12,TRAOPE!$G:$H,2,0),"") | E12: DW70 | F12: D080 | G12: =IFERROR(VLOOKUP(A12,Flete!$A:$E,5,0),"") | H12: =IFERROR(VLOOKUP(F12,TRAOPE!$AA:$AB,2,0),"") | I12: 10000811 | J12: =IFERROR(VLOOKUP(I12,Materiales!$A:$H,8,0),"") | K12: =IFERROR(VLOOKUP(I12,Materiales!$A:$G,7,0),"") | L12: 20230501 | M12: 20250131 | N12: 100.01 | O12: =IFERROR(VLOOKUP(A12,Flete!$A:$J,10,0),"") | P12: TN | Q12: =IFERROR(IFERROR(VLOOKUP(A12,TRAOPE!$A:$U,21,0),VLOOKUP(B12,TRAOPE!$A:$U,21,0)),"") | R12: =IFERROR(IFERROR(VLOOKUP(A12,TRAOPE!$A:$W,23,0),VLOOKUP(B12,TRAOPE!$A:$W,23,0)),"") | S12: =IF(AND(P12="TN",R12="TN"),N12+N(O12),IF(G12&""="1",N(K12)*N12,(N12+N(O12))*N(K12))) | T12: =IF(Q12="","",Q12-S12)
A13: =CONCATENATE(C13,E13,F13,I13) | B13: =CONCATENATE(C13,E13,I13) | C13: 900000034 | D13: =IFERROR(VLOOKUP(C13,TRAOPE!$G:$H,2,0),"") | E13: DW70 | F13: D081 | G13: =IFERROR(VLOOKUP(A13,Flete!$A:$E,5,0),"") | H13: =IFERROR(VLOOKUP(F13,TRAOPE!$AA:$AB,2,0),"") | I13: 10000623 | J13: =IFERROR(VLOOKUP(I13,Materiales!$A:$H,8,0),"") | K13: =IFERROR(VLOOKUP(I13,Materiales!$A:$G,7,0),"") | L13: 20250701 | M13: 99991231 | N13: 100 | O13: =IFERROR(VLOOKUP(A13,Flete!$A:$J,10,0),"") | P13: TN | Q13: =IFERROR(IFERROR(VLOOKUP(A13,TRAOPE!$A:$U,21,0),VLOOKUP(B13,TRAOPE!$A:$U,21,0)),"") | R13: =IFERROR(IFERROR(VLOOKUP(A13,TRAOPE!$A:$W,23,0),VLOOKUP(B13,TRAOPE!$A:$W,23,0)),"") | S13: =IF(AND(P13="TN",R13="TN"),N13+N(O13),IF(G13&""="1",N(K13)*N13,(N13+N(O13))*N(K13))) | T13: =IF(Q13="","",Q13-S13)
A14: =CONCATENATE(C14,E14,F14,I14) | B14: =CONCATENATE(C14,E14,I14) | C14: 900000034 | D14: =IFERROR(VLOOKUP(C14,TRAOPE!$G:$H,2,0),"") | E14: DW70 | F14: D081 | G14: =IFERROR(VLOOKUP(A14,Flete!$A:$E,5,0),"") | H14: =IFERROR(VLOOKUP(F14,TRAOPE!$AA:$AB,2,0),"") | I14: 10000811 | J14: =IFERROR(VLOOKUP(I14,Materiales!$A:$H,8,0),"") | K14: =IFERROR(VLOOKUP(I14,Materiales!$A:$G,7,0),"") | L14: 20230501 | M14: 20250131 | N14: 100.01 | O14: =IFERROR(VLOOKUP(A14,Flete!$A:$J,10,0),"") | P14: TN | Q14: =IFERROR(IFERROR(VLOOKUP(A14,TRAOPE!$A:$U,21,0),VLOOKUP(B14,TRAOPE!$A:$U,21,0)),"") | R14: =IFERROR(IFERROR(VLOOKUP(A14,TRAOPE!$A:$W,23,0),VLOOKUP(B14,TRAOPE!$A:$W,23,0)),"") | S14: =IF(AND(P14="TN",R14="TN"),N14+N(O14),IF(G14&""="1",N(K14)*N14,(N14+N(O14))*N(K14))) | T14: =IF(Q14="","",Q14-S14)
... A1403: =CONCATENATE(C1403,E1403,F1403,I1403) | B1403: =CONCATENATE(C1403,E1403,I1403) | C1403: 900009585 | D1403: =IFERROR(VLOOKUP(C1403,TRAOPE!$G:$H,2,0),"") | E1403: DW70 | F1403: D681 | G1403: =IFERROR(VLOOKUP(A1403,Flete!$A:$E,5,0),"") | H1403: =IFERROR(VLOOKUP(F1403,TRAOPE!$AA:$AB,2,0),"") | I1403: 10000811 | J1403: =IFERROR(VLOOKUP(I1403,Materiales!$A:$H,8,0),"") | K1403: =IFERROR(VLOOKUP(I1403,Materiales!$A:$G,7,0),"") | L1403: 20260814 | M1403: 99991231 | N1403: 155.49 | O1403: =IFERROR(VLOOKUP(A1403,Flete!$A:$J,10,0),"") | P1403: TN | Q1403: =IFERROR(IFERROR(VLOOKUP(A1403,TRAOPE!$A:$U,21,0),VLOOKUP(B1403,TRAOPE!$A:$U,21,0)),"") | R1403: =IFERROR(IFERROR(VLOOKUP(A1403,TRAOPE!$A:$W,23,0),VLOOKUP(B1403,TRAOPE!$A:$W,23,0)),"") | S1403: =IF(AND(P1403="TN",R1403="TN"),N1403+N(O1403),IF(G1403&""="1",N(K1403)*N1403,(N1403+N(O1403))*N(K1403))) | T1403: =IF(Q1403="","",Q1403-S1403)

Sheet MP
A1: No. SF | B1: Cedis | C1: Destino | D1: No. Material | E1: Nombre Material | F1: Importe MP | G1: Moneda | H1: Cantidad | I1: UM | J1: C | K1: Inicio Vigencia | L1: Fin Vigencia
A2: 900000034 | B2: DW70 | C2: D074 | D2: 10000623 | F2: 100 | I2: TN | K2: 20250701 | L2: 99991231
A3: 900000034 | B3: DW70 | C3: D074 | D3: 10000811 | F3: 100.01 | I3: TN | K3: 20230501 | L3: 20250131
A4: 900000034 | B4: DW70 | C4: D075 | D4: 10000623 | F4: 100 | I4: TN | K4: 20250701 | L4: 99991231
A5: 900000034 | B5: DW70 | C5: D075 | D5: 10000811 | F5: 100.01 | I5: TN | K5: 20230501 | L5: 20250131
A6: 900000034 | B6: DW70 | C6: D077 | D6: 10000623 | F6: 100 | I6: TN | K6: 20260508 | L6: 99991231
A7: 900000034 | B7: DW70 | C7: D077 | D7: 10000811 | F7: 100.01 | I7: TN | K7: 20230501 | L7: 20250131
A8: 900000034 | B8: DW70 | C8: D079 | D8: 10000623 | F8: 100 | I8: TN | K8: 20250701 | L8: 99991231
A9: 900000034 | B9: DW70 | C9: D079 | D9: 10000811 | F9: 100.01 | I9: TN | K9: 20230501 | L9: 20250131
A10: 900000034 | B10: DW70 | C10: D080 | D10: 10000623 | F10: 100 | I10: TN | K10: 20250701 | L10: 99991231
A11: 900000034 | B11: DW70 | C11: D080 | D11: 10000811 | F11: 100.01 | I11: TN | K11: 20230501 | L11: 20250131
A12: 900000034 | B12: DW70 | C12: D081 | D12: 10000623 | F12: 100 | I12: TN | K12: 20250701 | L12: 99991231
A13: 900000034 | B13: DW70 | C13: D081 | D13: 10000811 | F13: 100.01 | I13: TN | K13: 20230501 | L13: 20250131
... A1402: 900009585 | B1402: DW70 | C1402: D681 | D1402: 10000811 | F1402: 155.49 | I1402: TN | K1402: 20260814 | L1402: 99991231

Sheet Flete
A1: Concat1 | B1: No. SF | C1: Cedis | D1: Destino | E1: Cond. Exp. | F1: Material | H1: Nombre Material | J1: Importe Flete | K1: Moneda | L1: Cantidad | M1: UM | N1: C | P1: Inicio Vigencia | Q1: Fin Vigencia
A2: 900000034DW70D07410000623 | B2: 900000034 | C2: DW70 | D2: D074 | E2: 1 | F2: 10000623 | J2: 263.76 | M2: TN | P2: 20260430 | Q2: 99991231
A3: 900000034DW70D07410000811 | B3: 900000034 | C3: DW70 | D3: D074 | E3: 1 | F3: 10000811 | J3: 189.28 | M3: TN | P3: 20220331 | Q3: 20250131
A4: 900000034DW70D07510000623 | B4: 900000034 | C4: DW70 | D4: D075 | E4: 1 | F4: 10000623 | J4: 218.72 | M4: TN | P4: 20260430 | Q4: 99991231
A5: 900000034DW70D07510000811 | B5: 900000034 | C5: DW70 | D5: D075 | E5: 1 | F5: 10000811 | J5: 156.97 | M5: TN | P5: 20220331 | Q5: 20250131
A6: 900000034DW70D07710000623 | B6: 900000034 | C6: DW70 | D6: D077 | E6: 1 | F6: 10000623 | J6: 223.62 | M6: TN | P6: 20260508 | Q6: 99991231
A7: 900000034DW70D07710000811 | B7: 900000034 | C7: DW70 | D7: D077 | E7: 1 | F7: 10000811 | J7: 240.06 | M7: TN | P7: 20220331 | Q7: 20250131
A8: 900000034DW70D07910000623 | B8: 900000034 | C8: DW70 | D8: D079 | E8: 1 | F8: 10000623 | J8: 331.31 | M8: TN | P8: 20260430 | Q8: 99991231
A9: 900000034DW70D07910000811 | B9: 900000034 | C9: DW70 | D9: D079 | E9: 1 | F9: 10000811 | J9: 237.75 | M9: TN | P9: 20220331 | Q9: 20250131
A10: 900000034DW70D08010000623 | B10: 900000034 | C10: DW70 | D10: D080 | E10: 1 | F10: 10000623 | J10: 218.72 | M10: TN | P10: 20260430 | Q10: 99991231
A11: 900000034DW70D08010000811 | B11: 900000034 | C11: DW70 | D11: D080 | E11: 1 | F11: 10000811 | J11: 156.97 | M11: TN | P11: 20220331 | Q11: 20250131
A12: 900000034DW70D08110000623 | B12: 900000034 | C12: DW70 | D12: D081 | E12: 1 | F12: 10000623 | J12: 202.65 | M12: TN | P12: 20260430 | Q12: 99991231
A13: 900000034DW70D08110000811 | B13: 900000034 | C13: DW70 | D13: D081 | E13: 1 | F13: 10000811 | J13: 145.43 | M13: TN | P13: 20220331 | Q13: 20250131
... A1318: 900009480DW70D68110275115 | B1318: 900009480 | C1318: DW70 | D1318: D681 | E1318: 1 | F1318: 10275115 | J1318: 262.98 | M1318: TN | P1318: 20260430 | Q1318: 99991231

Sheet Materiales
A1: Material | B1: TpMt | C1: Denom | D1: UMA | E1: Contador | F1: UMB | G1: PV | H1: Nombre Material
A2: 10000001 | B2: ZFER | C2: 1000 | D2: M3 | E2: 1000 | F2: TN | G2: 1262 | H2: GRAVA ANDESITA 10 MM (3/8")
A3: 10000003 | B3: ZFER | C3: 1000 | D3: M3 | E3: 1000 | F3: TN | G3: 1443 | H3: GRAVA CALIZA 10 MM (3/8")
A4: 10000006 | B4: ZFER | C4: 1000 | D4: M3 | E4: 1000 | F4: TN | G4: 1490 | H4: GRAVA RIO 10 MM (3/8")
A5: 10000007 | B5: ZFER | C5: 1000 | D5: M3 | E5: 1000 | F5: TN | G5: 1488 | H5: GRAVA BASALTO 13 MM (1/2")
A6: 10000008 | B6: ZFER | C6: 1000 | D6: M3 | E6: 1000 | F6: TN | G6: 1358 | H6: GRAVA CALIZA 13 MM (1/2")
A7: 10000011 | B7: ZFER | C7: 1000 | D7: M3 | E7: 1000 | F7: TN | G7: 1323 | H7: GRAVA ANDESITA 20 MM (3/4")
A8: 10000013 | B8: ZFER | C8: 1000 | D8: M3 | E8: 1000 | F8: TN | G8: 1514 | H8: GRAVA BASALTO 20 MM (3/4")
A9: 10000014 | B9: ZFER | C9: 1000 | D9: M3 | E9: 1000 | F9: TN | G9: 1400 | H9: GRAVA CALIZA 20 MM (3/4")
A10: 10000015 | B10: ZFER | C10: 1000 | D10: M3 | E10: 1000 | F10: TN | G10: 1410 | H10: GRAVA GRANITO 20 MM (3/4")
A11: 10000017 | B11: ZFER | C11: 1000 | D11: M3 | E11: 1000 | F11: TN | G11: 1475 | H11: GRAVA RIOLITA 20 MM (3/4")
A12: 10000019 | B12: ZFER | C12: 1000 | D12: M3 | E12: 1000 | F12: TN | G12: 1515 | H12: GRAVA RIO 20 MM (3/4")
A13: 10000020 | B13: ZFER | C13: 1000 | D13: M3 | E13: 1 | F13: TN | G13: 1 | H13: GRAVA MAQUILA 40MM (1 1/2")
... A2291: 10268770 | B2291: ZFE3 | C2291: 1000 | D2291: M3 | E2291: 1000 | F2291: TN | G2291: 1240 | H2291: MP GRAVA TRIT CALIZA 40MM 1 1/2" - ESP
A2292: 10268901 | B2292: ZFE3 | C2292: 1000 | D2292: M3 | E2292: 1000 | G2292: 1560 | H2292: MP GRAVA ANDESITA GRIS 3/4" - CAPADA
A2293: 10267983 | C2293: 1000 | G2293: 1800 | H2293: ESCORIA ALTO HORNO 3/4
A2294: 10268996 | C2294: 1000 | G2294: 1329 | H2294: GRAVA TRITURADA CALIZA 40 MM - 11/2"
A2295: 10269072 | C2295: 1000 | G2295: 1700 | H2295: BASE HIDRÁULICA SCREEN
A2296: 10269225 | B2296: ZFE3 | C2296: 1000 | D2296: M3 | E2296: 1000 | G2296: 1289 | H2296: MP ARENA CALIZA LAVADA MALLA 4 - DELTA I
A2297: 10269245 | B2297: ZFE3 | C2297: 1000 | D2297: M3 | E2297: 1000 | G2297: 1410 | H2297: MP GRAVA TRITURADA CALIZA 3/8 - 10MM
A2298: 10269246 | B2298: ZFE3 | C2298: 1000 | D2298: M3 | E2298: 1000 | G2298: 1400 | H2298: MP GRAVA TRITURADA CALIZA 1 1/2 - 40MM
A2299: 10269247 | B2299: ZFE3 | C2299: 1000 | D2299: M3 | E2299: 1000 | G2299: 1560 | H2299: MP ARENA TRIT CALIZA M-4
A2300: 10270431 | B2300: ZFE3 | C2300: 1000 | D2300: M3 | E2300: 1000 | G2300: 1423 | H2300: MP GRAVA RIOLITA 13 MM - 1/2"
A2301: 10270898 | B2301: ZFE3 | C2301: 1000 | D2301: M3 | E2301: 1000 | G2301: 1551 | H2301: MP BASE H. TRIT. BASALTO 1 1/2" A FINOS
A2302: 10270911 | B2302: ZFE3 | C2302: 1000 | D2302: M3 | E2302: 1000 | G2302: 1360 | H2302: MP GRAVA TRIT. BASALTO 40 MM - 1 1/2"
A2303: 10270912 | B2303: ZFE3 | C2303: 1000 | D2303: M3 | E2303: 1000 | G2303: 1589 | H2303: MP ARENA TRIT. BASALTO MALLA 4
A2304: 10270913 | B2304: ZFE3 | C2304: 1000 | D2304: M3 | E2304: 1000 | G2304: 1395 | H2304: MP GRAVA TRIT. BASALTO 20 MM - 3/4
A2305: 10270914 | B2305: ZFE3 | C2305: 1000 | D2305: M3 | E2305: 1000 | G2305: 1623 | H2305: MP ARENA ANDESITA BC
A2306: 10270824 | B2306: M3 | C2306: 1000 | D2306: M3 | E2306: 10007640 | G2306: 1325 | H2306: MP ARENA TRITURADA CALIZA MALLA 5
A2307: 10270825 | B2307: M3 | C2307: 1000 | D2307: M3 | E2307: 10000003 | G2307: 1242 | H2307: MP GRAVA TRITURADA CALIZA 10MM (3/8”)
... A2319: 10272527 | B2319: ZFE3 | C2319: 1000 | D2319: M3 | E2319: 1000 | G2319: 1620 | H2319: CNC - NO CLASIFICADO
A2320: 10000332 | C2320: 1000 | D2320: M3 | E2320: 1000 | G2320: 800 | H2320: Grava Triturada Pomez - Jal 20 mm - 3/4"
A2321: 10273001 | B2321: ZFE3 | C2321: 1000 | D2321: M3 | E2321: 1000 | G2321: 1688 | H2321: MP ARENA TRIT. BASALTO MALLA 4
A2322: 10273002 | B2322: ZFE3 | C2322: 1000 | D2322: M3 | E2322: 1000 | G2322: 1466 | H2322: MP GRAVA TRIT. BASALTO 20 MM - 3/4"
A2323: 10273351 | B2323: ZFE3 | C2323: 1000 | D2323: M3 | E2323: 1000 | G2323: 1612 | H2323: MP ARENA TRIT. CALIZA MALLA 4
A2324: 10273352 | B2324: ZFE3 | C2324: 1000 | D2324: M3 | E2324: 1000 | G2324: 1492 | H2324: MP GRAVA TRIT. CALIZA 20 MM - 3/4"
A2325: 10271724 | B2325: ZFE3 | C2325: 1000 | D2325: M3 | E2325: 1000 | G2325: 1900 | H2325: MP RESIDUO DE CONCRETO
A2326: 10000677 | C2326: 1000 | D2326: M3 | G2326: 1164 | H2326: Grava Triturada Caliza 20 mm - 3/4"
A2327: 10274190 | B2327: ZFE3 | C2327: 1000 | D2327: M3 | E2327: 1000 | G2327: 1800 | H2327: MP BASE HIDRAULICA ANDESITA 70-30
A2328: 10274601 | B2328: ZFE3 | C2328: 1000 | D2328: M3 | E2328: 1000 | G2328: 1447 | H2328: MP ARENA BASALTO N° 4
A2329: 10274754 | B2329: ZFE3 | C2329: 1000 | D2329: M3 | E2329: 1000 | G2329: 1397 | H2329: MP GRAVA TRIT. ANDESITA 20 MM - 3/4"
A2330: 10169718 | B2330: ZFE3 | C2330: 1000 | D2330: M3 | E2330: 1000 | G2330: 1400 | H2330: GRAVA CLASIFICADA RÍO 40 MM - 1 1/2"
A2331: 10274813 | B2331: ZFE3 | C2331: 1000 | D2331: M3 | E2331: 1000 | G2331: 1448 | H2331: MP ARENA TRIT RÍO MALLA 4
A2332: 10274815 | B2332: ZFE3 | C2332: 1000 | D2332: M3 | E2332: 1000 | G2332: 1366 | H2332: MP ARENA CLASIFICADA RÍO MALLA 5
A2333: 10274816 | B2333: ZFE3 | C2333: 1000 | D2333: M3 | E2333: 1000 | G2333: 1472 | H2333: MP GRAVA CLASIF RÍO 20 MM - 3/4"
A2334: 10275113 | B2334: ZFE3 | C2334: 1000 | D2334: M3 | E2334: 1000 | G2334: 1409 | H2334: MP ARENA TRIT ANDESITA MALLA 4
A2335: 10275114 | B2335: ZFE3 | C2335: 1000 | D2335: M3 | E2335: 1000 | G2335: 1418 | H2335: MP ARENA CLASIF RIO MALLA 4 - LAVADO
A2336: 10275115 | B2336: ZFE3 | C2336: 1000 | D2336: M3 | E2336: 1000 | G2336: 1259 | H2336: MP ARENA TRIT ANDESITA MALLA 4
A2337: 10275116 | B2337: ZFE3 | C2337: 1000 | D2337: M3 | E2337: 1000 | G2337: 1401 | H2337: MP GRAVA TRIT ANDESITA 3/4 - 20 MM
A2338: 10275118 | B2338: ZFE3 | C2338: 1000 | D2338: M3 | E2338: 1000 | G2338: 1401 | H2338: MP ARENA TRIT ANDESITA MALLA 4
... A2361: 10280049 | B2361: ZFE3 | C2361: 1000 | D2361: M3 | E2361: 1000 | G2361: 1584 | H2361: MP B. HID CALIZA 40% FINOS Y 60% GRUESOS
A2362: 10280365 | C2362: 1000 | D2362: M3 | E2362: 1000 | G2362: 1274 | H2362: MP GRAVA BASALTO 20 MM -3/4
A2363: 10280538 | B2363: ZFE3 | C2363: 1000 | D2363: M3 | E2363: 1000 | G2363: 1262 | H2363: MP GRAVA TRIT BASALTO 3/8 - 10MM
A2364: 10280679 | B2364: ZFE3 | C2364: 1000 | D2364: M3 | E2364: 1000 | G2364: 1349 | H2364: MP GRAVA CLASIF RÍO 13MM - 1/2"
A2365: 10281171 | B2365: ZFE3 | C2365: 1000 | D2365: M3 | E2365: 1000 | G2365: 1271 | H2365: MP GRAVA TRIT CALIZA 10MM - 3/8"
A2366: 10281183 | B2366: ZFE3 | C2366: 1000 | D2366: M3 | E2366: 1000 | G2366: 1468 | H2366: MP ARENA TRIT CALIZA MALLA 4
A2367: 10281384 | B2367: ZFE3 | C2367: 1000 | D2367: M3 | E2367: 1000 | G2367: 1285 | H2367: MP GRAVA BASALTO 40 MM (1 1/2")
A2368: 10281379 | B2368: ZFE3 | C2368: 1000 | D2368: M3 | E2368: 1000 | G2368: 1536 | H2368: MP ARENA CLASIF. RÍO MALLA 4
A2369: 10281450 | B2369: ZFE3 | C2369: 1000 | D2369: M3 | E2369: 1000 | G2369: 1325 | H2369: MP GRAVA CLASIF. RIO 20MM - 3/4
A2370: 10281451 | B2370: ZFE3 | C2370: 1000 | D2370: M3 | E2370: 1000 | G2370: 1564 | H2370: MP ARENA CLASIF. RÍO MALLA 4
A2371: 10281452 | B2371: ZFE3 | C2371: 1000 | D2371: M3 | E2371: 1000 | G2371: 1427 | H2371: MP GRAVA CLASIF. RIO 20MM - 3/4

Sheet TRAOPE
A1: Concat1 | B1: Contrato_Pos | C1: Doc. Compras | D1: Pos | E1: Org.compras | F1: Grp-Compr. | G1: Ship From | H1: Nombre SF | I1: Proveedor | J1: Nombre Prov | K1: Cond. Pago | L1: Descr. Cond Pago | M1: Material | N1: Descripción | O1: Centro | P1: Descripción Centro | Q1: In.perído validez | R1: Fin perído validez | S1: Válido de | T1: Validez a | U1: Precio neto pedido | V1: Moneda | W1: UM Precio Pedido | X1: Importe Condición | Y1: Moneda KONP | Z1: UM Ctd Base | AA1: Destino | AB1: Nombre Destino | AC1: Cuenta de mayor | AD1: Centro de costo | AE1: Cond. Exp. | AF1: Descr. Cond. Exp. | AG1: Peso Vol. | AH1: UMB | AI1: Ind. Oblig. Conf. Ped. | AJ1: Ctrl-Conf. | AK1: IVA | AL1: Modif_Date | AM1: Ruta
A2: 900006172DW70D07410000811 | B2: 4600072309-160 | C2: 4600072309 | D2: 160 | E2: MXPO | F2: MXL | G2: 900006172 | H2: SF TC-ED ESTRATEGIAS SANTA CALIZA | I2: 5049458 | J2: ESTRATEGIAS AVANZADAS PARA OBTEN | K2: Z03 | L2: (AP) 15 Dias | M2: 10000811 | N2: Grava Triturada Caliza 20 mm - 3/4" | O2: DW70 | P2: MX-CED. CENTRO | Q2: 20260616 | R2: 20301231 | S2: 20260805 | T2: 20301231 | U2: 569 | V2: MXN | W2: M3 | X2: 413 | Y2: MXN | Z2: M3 | AA2: D074 | AB2: PD0063 CENTRAL | AC2: 56103637 | AD2: 6644261540 | AE2: 4 | AF2: ENTREGA DIRECTA | AG2: 1.447 | AH2: M3 | AI2: X | AJ2: 4 | AK2: V4 | AL2: 20260811 | AM2: DW70-900006172-D074-10000811-4
A3: 900006172DW70D09810000811 | B3: 4600072309-250 | C3: 4600072309 | D3: 250 | E3: MXPO | F3: MXL | G3: 900006172 | H3: SF TC-ED ESTRATEGIAS SANTA CALIZA | I3: 5049458 | J3: ESTRATEGIAS AVANZADAS PARA OBTEN | K3: Z03 | L3: (AP) 15 Dias | M3: 10000811 | N3: Grava Triturada Caliza 20 mm - 3/4" | O3: DW70 | P3: MX-CED. CENTRO | Q3: 20260616 | R3: 20301231 | S3: 20260805 | T3: 20301231 | U3: 405 | V3: MXN | W3: M3 | X3: 249 | Y3: MXN | Z3: M3 | AA3: D098 | AB3: PD0315 CUAUTITLAN II | AC3: 56103637 | AD3: 6644261540 | AE3: 4 | AF3: ENTREGA DIRECTA | AG3: 1.447 | AH3: M3 | AI3: X | AJ3: 4 | AK3: V4 | AL3: 20260811 | AM3: DW70-900006172-D098-10000811-4
A4: 900006172DW70D09310000811 | B4: 4600072309-280 | C4: 4600072309 | D4: 280 | E4: MXPO | F4: MXL | G4: 900006172 | H4: SF TC-ED ESTRATEGIAS SANTA CALIZA | I4: 5049458 | J4: ESTRATEGIAS AVANZADAS PARA OBTEN | K4: Z03 | L4: (AP) 15 Dias | M4: 10000811 | N4: Grava Triturada Caliza 20 mm - 3/4" | O4: DW70 | P4: MX-CED. CENTRO | Q4: 20260616 | R4: 20301231 | S4: 20260805 | T4: 20301231 | U4: 347 | V4: MXN | W4: M3 | X4: 191 | Y4: MXN | Z4: M3 | AA4: D093 | AB4: PD0556 ZUMPANGO | AC4: 56103637 | AD4: 6644261540 | AE4: 4 | AF4: ENTREGA DIRECTA | AG4: 1.447 | AH4: M3 | AI4: X | AJ4: 4 | AK4: V4 | AL4: 20260811 | AM4: DW70-900006172-D093-10000811-4
A5: 900003438DW70D68110000811 | B5: 4600050497-950 | C5: 4600050497 | D5: 950 | E5: MXPO | F5: MXL | G5: 900003438 | H5: TC-ED-ESTRATEGIAS AVANZADAS | I5: 5049458 | J5: ESTRATEGIAS AVANZADAS PARA OBTEN | K5: Z03 | L5: (AP) 15 Dias | M5: 10000811 | N5: Grava Triturada Caliza 20 mm - 3/4" | O5: DW70 | P5: MX-CED. CENTRO | Q5: 20210712 | R5: 20281231 | S5: 20260819 | T5: 20301231 | U5: 522 | V5: MXN | W5: M3 | X5: 322 | Y5: MXN | Z5: M3 | AA5: D681 | AB5: PD0639 TULTEPEC | AC5: 56103637 | AD5: 6644261540 | AE5: 4 | AF5: ENTREGA DIRECTA | AG5: 1.447 | AH5: M3 | AI5: X | AJ5: 4 | AK5: V4 | AL5: 20260821 | AM5: DW70-900003438-D681-10000811-4
A6: 900009585DW70D68110000811 | B6: 4600072549-30 | C6: 4600072549 | D6: 30 | E6: MXPO | F6: MXL | G6: 900009585 | H6: SF TC-ED ESTRATEGIAS MAQ Y CANTERAS | I6: 5049458 | J6: ESTRATEGIAS AVANZADAS PARA OBTEN | K6: Z03 | L6: (AP) 15 Dias | M6: 10000811 | N6: Grava Triturada Caliza 20 mm - 3/4" | O6: DW70 | P6: MX-CED. CENTRO | Q6: 20260814 | R6: 20301231 | S6: 20260814 | T6: 20301231 | U6: 492.4 | V6: MXN | W6: M3 | X6: 267.4 | Y6: MXN | Z6: M3 | AA6: D681 | AB6: PD0639 TULTEPEC | AC6: 56103637 | AD6: 6644261540 | AE6: 4 | AF6: ENTREGA DIRECTA | AG6: 1.447 | AH6: M3 | AI6: X | AJ6: 4 | AK6: V4 | AL6: 20260821 | AM6: DW70-900009585-D681-10000811-4
A7: 900006172DW70D07510000811 | B7: 4600072309-170 | C7: 4600072309 | D7: 170 | E7: MXPO | F7: MXL | G7: 900006172 | H7: SF TC-ED ESTRATEGIAS SANTA CALIZA | I7: 5049458 | J7: ESTRATEGIAS AVANZADAS PARA OBTEN | K7: Z03 | L7: (AP) 15 Dias | M7: 10000811 | N7: Grava Triturada Caliza 20 mm - 3/4" | O7: DW70 | P7: MX-CED. CENTRO | Q7: 20260616 | R7: 20301231 | S7: 20260805 | T7: 20301231 | U7: 507 | V7: MXN | W7: M3 | X7: 351 | Y7: MXN | Z7: M3 | AA7: D075 | AB7: PD0065 CEYLAN | AC7: 56103637 | AD7: 6644261540 | AE7: 4 | AF7: ENTREGA DIRECTA | AG7: 1.447 | AH7: M3 | AI7: X | AJ7: 4 | AK7: V4 | AL7: 20260811 | AM7: DW70-900006172-D075-10000811-4
A8: 900006172DW70D13610000811 | B8: 4600072309-240 | C8: 4600072309 | D8: 240 | E8: MXPO | F8: MXL | G8: 900006172 | H8: SF TC-ED ESTRATEGIAS SANTA CALIZA | I8: 5049458 | J8: ESTRATEGIAS AVANZADAS PARA OBTEN | K8: Z03 | L8: (AP) 15 Dias | M8: 10000811 | N8: Grava Triturada Caliza 20 mm - 3/4" | O8: DW70 | P8: MX-CED. CENTRO | Q8: 20260616 | R8: 20301231 | S8: 20260805 | T8: 20301231 | U8: 627 | V8: MXN | W8: M3 | X8: 471 | Y8: MXN | Z8: M3 | AA8: D136 | AB8: PD0237 LA ESTRELLA | AC8: 56103637 | AD8: 6644261540 | AE8: 4 | AF8: ENTREGA DIRECTA | AG8: 1.447 | AH8: M3 | AI8: X | AJ8: 4 | AK8: V4 | AL8: 20260811 | AM8: DW70-900006172-D136-10000811-4
A9: 900009292DW7010058345 | B9: 4600071553-60 | C9: 4600071553 | D9: 60 | E9: MXPO | F9: MXL | G9: 900009292 | H9: SF TC-GRAVICOR GIL | I9: 5096226 | J9: GIL HERNANDEZ RACIEL | K9: N90 | L9: (AP) NAFIN 90 Dias | M9: 10058345 | N9: Arena Triturada Caliza Malla 4 | O9: DW70 | P9: MX-CED. CENTRO | Q9: 20250813 | R9: 20301231 | S9: 20260814 | T9: 20301231 | U9: 150 | V9: MXN | W9: M3 | X9: 0 | Y9: MXN | Z9: M3 | AC9: 56103638 | AD9: 6644261540 | AE9: 1 | AF9: ENTREGADO | AG9: 1.575 | AH9: M3 | AI9: X | AJ9: 4 | AK9: V4 | AL9: 20260821 | AM9: DW70-900009292-10058345
A10: 900006172DW70D08510000811 | B10: 4600072309-230 | C10: 4600072309 | D10: 230 | E10: MXPO | F10: MXL | G10: 900006172 | H10: SF TC-ED ESTRATEGIAS SANTA CALIZA | I10: 5049458 | J10: ESTRATEGIAS AVANZADAS PARA OBTEN | K10: Z03 | L10: (AP) 15 Dias | M10: 10000811 | N10: Grava Triturada Caliza 20 mm - 3/4" | O10: DW70 | P10: MX-CED. CENTRO | Q10: 20260616 | R10: 20301231 | S10: 20260805 | T10: 20301231 | U10: 636 | V10: MXN | W10: M3 | X10: 480 | Y10: MXN | Z10: M3 | AA10: D085 | AB10: PD0189 ROJO GOMEZ | AC10: 56103637 | AD10: 6644261540 | AE10: 4 | AF10: ENTREGA DIRECTA | AG10: 1.447 | AH10: M3 | AI10: X | AJ10: 4 | AK10: V4 | AL10: 20260811 | AM10: DW70-900006172-D085-10000811-4
A11: 900006172DW70D07710000811 | B11: 4600072309-180 | C11: 4600072309 | D11: 180 | E11: MXPO | F11: MXL | G11: 900006172 | H11: SF TC-ED ESTRATEGIAS SANTA CALIZA | I11: 5049458 | J11: ESTRATEGIAS AVANZADAS PARA OBTEN | K11: Z03 | L11: (AP) 15 Dias | M11: 10000811 | N11: Grava Triturada Caliza 20 mm - 3/4" | O11: DW70 | P11: MX-CED. CENTRO | Q11: 20260616 | R11: 20301231 | S11: 20260805 | T11: 20301231 | U11: 667 | V11: MXN | W11: M3 | X11: 511 | Y11: MXN | Z11: M3 | AA11: D077 | AB11: PD0067 LOS REYES | AC11: 56103637 | AD11: 6644261540 | AE11: 4 | AF11: ENTREGA DIRECTA | AG11: 1.447 | AH11: M3 | AI11: X | AJ11: 4 | AK11: V4 | AL11: 20260811 | AM11: DW70-900006172-D077-10000811-4
A12: 900003438DW70D08610000811 | B12: 4600050497-860 | C12: 4600050497 | D12: 860 | E12: MXPO | F12: MXL | G12: 900003438 | H12: TC-ED-ESTRATEGIAS AVANZADAS | I12: 5049458 | J12: ESTRATEGIAS AVANZADAS PARA OBTEN | K12: Z03 | L12: (AP) 15 Dias | M12: 10000811 | N12: Grava Triturada Caliza 20 mm - 3/4" | O12: DW70 | P12: MX-CED. CENTRO | Q12: 20210712 | R12: 20281231 | S12: 20260819 | T12: 20301231 | U12: 576.5 | V12: MXN | W12: M3 | X12: 376.5 | Y12: MXN | Z12: M3 | AA12: D086 | AB12: PD0190 XALOSTC | AC12: 56103637 | AD12: 6644261540 | AE12: 4 | AF12: ENTREGA DIRECTA | AG12: 1.447 | AH12: M3 | AI12: X | AJ12: 4 | AK12: V4 | AL12: 20260821 | AM12: DW70-900003438-D086-10000811-4
A13: 900006544DW7010185477 | B13: 4600050562-20 | C13: 4600050562 | D13: 20 | E13: MXPO | F13: MXL | G13: 900006544 | H13: TC-MARTINEZ VILLEGAS | I13: 5078107 | J13: MARTINEZ VILLEGAS SA DE CV | K13: Z04 | L13: (AP) 30 Dias | M13: 10185477 | N13: GRAVA TRITURADA ANDESITA 20 MM - 3/4" | O13: DW70 | P13: MX-CED. CENTRO | Q13: 20210712 | R13: 20261231 | S13: 20260805 | T13: 20301231 | U13: 160 | V13: MXN | W13: M3 | X13: 0 | Y13: MXN | Z13: M3 | AC13: 56103637 | AD13: 6644261540 | AE13: 1 | AF13: ENTREGADO | AG13: 1.39 | AH13: M3 | AI13: X | AJ13: 4 | AK13: V4 | AL13: 20260813 | AM13: DW70-900006544-10185477
A14: 900006172DW70D14510000811 | B14: 4600072309-270 | C14: 4600072309 | D14: 270 | E14: MXPO | F14: MXL | G14: 900006172 | H14: SF TC-ED ESTRATEGIAS SANTA CALIZA | I14: 5049458 | J14: ESTRATEGIAS AVANZADAS PARA OBTEN | K14: Z03 | L14: (AP) 15 Dias | M14: 10000811 | N14: Grava Triturada Caliza 20 mm - 3/4" | O14: DW70 | P14: MX-CED. CENTRO | Q14: 20260616 | R14: 20301231 | S14: 20260805 | T14: 20301231 | U14: 454 | V14: MXN | W14: M3 | X14: 298 | Y14: MXN | Z14: M3 | AA14: D145 | AB14: PD0458 ECATEPEC II | AC14: 56103637 | AD14: 6644261540 | AE14: 4 | AF14: ENTREGA DIRECTA | AG14: 1.447 | AH14: M3 | AI14: X | AJ14: 4 | AK14: V4 | AL14: 20260811 | AM14: DW70-900006172-D145-10000811-4
A15: 900009585DW70D14510000811 | B15: 4600072549-20 | C15: 4600072549 | D15: 20 | E15: MXPO | F15: MXL | G15: 900009585 | H15: SF TC-ED ESTRATEGIAS MAQ Y CANTERAS | I15: 5049458 | J15: ESTRATEGIAS AVANZADAS PARA OBTEN | K15: Z03 | L15: (AP) 15 Dias | M15: 10000811 | N15: Grava Triturada Caliza 20 mm - 3/4" | O15: DW70 | P15: MX-CED. CENTRO | Q15: 20260814 | R15: 20301231 | S15: 20260814 | T15: 20301231 | U15: 501.2 | V15: MXN | W15: M3 | X15: 276.2 | Y15: MXN | Z15: M3 | AA15: D145 | AB15: PD0458 ECATEPEC II | AC15: 56103637 | AD15: 6644261540 | AE15: 4 | AF15: ENTREGA DIRECTA | AG15: 1.447 | AH15: M3 | AI15: X | AJ15: 4 | AK15: V4 | AL15: 20260821 | AM15: DW70-900009585-D145-10000811-4
A16: 900003438DW70D09810000811 | B16: 4600050497-880 | C16: 4600050497 | D16: 880 | E16: MXPO | F16: MXL | G16: 900003438 | H16: TC-ED-ESTRATEGIAS AVANZADAS | I16: 5049458 | J16: ESTRATEGIAS AVANZADAS PARA OBTEN | K16: Z03 | L16: (AP) 15 Dias | M16: 10000811 | N16: Grava Triturada Caliza 20 mm - 3/4" | O16: DW70 | P16: MX-CED. CENTRO | Q16: 20210712 | R16: 20281231 | S16: 20260819 | T16: 20301231 | U16: 427 | V16: MXN | W16: M3 | X16: 227 | Y16: MXN | Z16: M3 | AA16: D098 | AB16: PD0315 CUAUTITLAN II | AC16: 56103637 | AD16: 6644261540 | AE16: 4 | AF16: ENTREGA DIRECTA | AG16: 1.447 | AH16: M3 | AI16: X | AJ16: 4 | AK16: V4 | AL16: 20260821 | AM16: DW70-900003438-D098-10000811-4
A17: 900006172DW70D68110000811 | B17: 4600072309-290 | C17: 4600072309 | D17: 290 | E17: MXPO | F17: MXL | G17: 900006172 | H17: SF TC-ED ESTRATEGIAS SANTA CALIZA | I17: 5049458 | J17: ESTRATEGIAS AVANZADAS PARA OBTEN | K17: Z03 | L17: (AP) 15 Dias | M17: 10000811 | N17: Grava Triturada Caliza 20 mm - 3/4" | O17: DW70 | P17: MX-CED. CENTRO | Q17: 20260616 | R17: 20301231 | S17: 20260805 | T17: 20301231 | U17: 436 | V17: MXN | W17: M3 | X17: 280 | Y17: MXN | Z17: M3 | AA17: D681 | AB17: PD0639 TULTEPEC | AC17: 56103637 | AD17: 6644261540 | AE17: 4 | AF17: ENTREGA DIRECTA | AG17: 1.447 | AH17: M3 | AI17: X | AJ17: 4 | AK17: V4 | AL17: 20260811 | AM17: DW70-900006172-D681-10000811-4
A18: 900006172DW70D07910000811 | B18: 4600072309-190 | C18: 4600072309 | D18: 190 | E18: MXPO | F18: MXL | G18: 900006172 | H18: SF TC-ED ESTRATEGIAS SANTA CALIZA | I18: 5049458 | J18: ESTRATEGIAS AVANZADAS PARA OBTEN | K18: Z03 | L18: (AP) 15 Dias | M18: 10000811 | N18: Grava Triturada Caliza 20 mm - 3/4" | O18: DW70 | P18: MX-CED. CENTRO | Q18: 20260616 | R18: 20301231 | S18: 20260805 | T18: 20301231 | U18: 694 | V18: MXN | W18: M3 | X18: 538 | Y18: MXN | Z18: M3 | AA18: D079 | AB18: PD0071 XOCHIMILCO | AC18: 56103637 | AD18: 6644261540 | AE18: 4 | AF18: ENTREGA DIRECTA | AG18: 1.447 | AH18: M3 | AI18: X | AJ18: 4 | AK18: V4 | AL18: 20260811 | AM18: DW70-900006172-D079-10000811-4
A19: 900009585DW70D09310000811 | B19: 4600072549-10 | C19: 4600072549 | D19: 10 | E19: MXPO | F19: MXL | G19: 900009585 | H19: SF TC-ED ESTRATEGIAS MAQ Y CANTERAS | I19: 5049458 | J19: ESTRATEGIAS AVANZADAS PARA OBTEN | K19: Z03 | L19: (AP) 15 Dias | M19: 10000811 | N19: Grava Triturada Caliza 20 mm - 3/4" | O19: DW70 | P19: MX-CED. CENTRO | Q19: 20260814 | R19: 20301231 | S19: 20260814 | T19: 20301231 | U19: 405.9 | V19: MXN | W19: M3 | X19: 180.9 | Y19: MXN | Z19: M3 | AA19: D093 | AB19: PD0556 ZUMPANGO | AC19: 56103637 | AD19: 6644261540 | AE19: 4 | AF19: ENTREGA DIRECTA | AG19: 1.447 | AH19: M3 | AI19: X | AJ19: 4 | AK19: V4 | AL19: 20260821 | AM19: DW70-900009585-D093-10000811-4
A20: 900009292DW7010000811 | B20: 4600071553-30 | C20: 4600071553 | D20: 30 | E20: MXPO | F20: MXL | G20: 900009292 | H20: SF TC-GRAVICOR GIL | I20: 5096226 | J20: GIL HERNANDEZ RACIEL | K20: N90 | L20: (AP) NAFIN 90 Dias | M20: 10000811 | N20: Grava Triturada Caliza 20 mm - 3/4" | O20: DW70 | P20: MX-CED. CENTRO | Q20: 20250813 | R20: 20301231 | S20: 20260814 | T20: 20301231 | U20: 225 | V20: MXN | W20: M3 | X20: 0 | Y20: MXN | Z20: M3 | AC20: 56103637 | AD20: 6644261540 | AE20: 1 | AF20: ENTREGADO | AG20: 1.447 | AH20: M3 | AI20: X | AJ20: 4 | AK20: V4 | AL20: 20260821 | AM20: DW70-900009292-10000811
A21: 900003438DW70D08110000811 | B21: 4600050497-820 | C21: 4600050497 | D21: 820 | E21: MXPO | F21: MXL | G21: 900003438 | H21: TC-ED-ESTRATEGIAS AVANZADAS | I21: 5049458 | J21: ESTRATEGIAS AVANZADAS PARA OBTEN | K21: Z03 | L21: (AP) 15 Dias | M21: 10000811 | N21: Grava Triturada Caliza 20 mm - 3/4" | O21: DW70 | P21: MX-CED. CENTRO | Q21: 20210712 | R21: 20281231 | S21: 20260819 | T21: 20301231 | U21: 536 | V21: MXN | W21: M3 | X21: 336 | Y21: MXN | Z21: M3 | AA21: D081 | AB21: PD0088 ARMAS | AC21: 56103637 | AD21: 6644261540 | AE21: 4 | AF21: ENTREGA DIRECTA | AG21: 1.447 | AH21: M3 | AI21: X | AJ21: 4 | AK21: V4 | AL21: 20260821 | AM21: DW70-900003438-D081-10000811-4
A22: 900003438DW70D14510000811 | B22: 4600050497-910 | C22: 4600050497 | D22: 910 | E22: MXPO | F22: MXL | G22: 900003438 | H22: TC-ED-ESTRATEGIAS AVANZADAS | I22: 5049458 | J22: ESTRATEGIAS AVANZADAS PARA OBTEN | K22: Z03 | L22: (AP) 15 Dias | M22: 10000811 | N22: Grava Triturada Caliza 20 mm - 3/4" | O22: DW70 | P22: MX-CED. CENTRO | Q22: 20210712 | R22: 20281231 | S22: 20260819 | T22: 20301231 | U22: 540.5 | V22: MXN | W22: M3 | X22: 340.5 | Y22: MXN | Z22: M3 | AA22: D145 | AB22: PD0458 ECATEPEC II | AC22: 56103637 | AD22: 6644261540 | AE22: 4 | AF22: ENTREGA DIRECTA | AG22: 1.447 | AH22: M3 | AI22: X | AJ22: 4 | AK22: V4 | AL22: 20260821 | AM22: DW70-900003438-D145-10000811-4
A23: 900006172DW70D08310000811 | B23: 4600072309-210 | C23: 4600072309 | D23: 210 | E23: MXPO | F23: MXL | G23: 900006172 | H23: SF TC-ED ESTRATEGIAS SANTA CALIZA | I23: 5049458 | J23: ESTRATEGIAS AVANZADAS PARA OBTEN | K23: Z03 | L23: (AP) 15 Dias | M23: 10000811 | N23: Grava Triturada Caliza 20 mm - 3/4" | O23: DW70 | P23: MX-CED. CENTRO | Q23: 20260616 | R23: 20301231 | S23: 20260805 | T23: 20301231 | U23: 579 | V23: MXN | W23: M3 | X23: 423 | Y23: MXN | Z23: M3 | AA23: D083 | AB23: PD0099 MINAS | AC23: 56103637 | AD23: 6644261540 | AE23: 4 | AF23: ENTREGA DIRECTA | AG23: 1.447 | AH23: M3 | AI23: X | AJ23: 4 | AK23: V4 | AL23: 20260811 | AM23: DW70-900006172-D083-10000811-4
A24: 900006172DW70D10510000811 | B24: 4600072309-260 | C24: 4600072309 | D24: 260 | E24: MXPO | F24: MXL | G24: 900006172 | H24: SF TC-ED ESTRATEGIAS SANTA CALIZA | I24: 5049458 | J24: ESTRATEGIAS AVANZADAS PARA OBTEN | K24: Z03 | L24: (AP) 15 Dias | M24: 10000811 | N24: Grava Triturada Caliza 20 mm - 3/4" | O24: DW70 | P24: MX-CED. CENTRO | Q24: 20260616 | R24: 20301231 | S24: 20260805 | T24: 20301231 | U24: 516 | V24: MXN | W24: M3 | X24: 360 | Y24: MXN | Z24: M3 | AA24: D105 | AB24: PD0331 NAUCALPAN II | AC24: 56103637 | AD24: 6644261540 | AE24: 4 | AF24: ENTREGA DIRECTA | AG24: 1.447 | AH24: M3 | AI24: X | AJ24: 4 | AK24: V4 | AL24: 20260811 | AM24: DW70-900006172-D105-10000811-4
A25: 900006172DW70D08110000811 | B25: 4600072309-200 | C25: 4600072309 | D25: 200 | E25: MXPO | F25: MXL | G25: 900006172 | H25: SF TC-ED ESTRATEGIAS SANTA CALIZA | I25: 5049458 | J25: ESTRATEGIAS AVANZADAS PARA OBTEN | K25: Z03 | L25: (AP) 15 Dias | M25: 10000811 | N25: Grava Triturada Caliza 20 mm - 3/4" | O25: DW70 | P25: MX-CED. CENTRO | Q25: 20260616 | R25: 20301231 | S25: 20260805 | T25: 20301231 | U25: 507 | V25: MXN | W25: M3 | X25: 351 | Y25: MXN | Z25: M3 | AA25: D081 | AB25: PD0088 ARMAS | AC25: 56103637 | AD25: 6644261540 | AE25: 4 | AF25: ENTREGA DIRECTA | AG25: 1.447 | AH25: M3 | AI25: X | AJ25: 4 | AK25: V4 | AL25: 20260811 | AM25: DW70-900006172-D081-10000811-4
A26: 900006172DW70D08410000811 | B26: 4600072309-220 | C26: 4600072309 | D26: 220 | E26: MXPO | F26: MXL | G26: 900006172 | H26: SF TC-ED ESTRATEGIAS SANTA CALIZA | I26: 5049458 | J26: ESTRATEGIAS AVANZADAS PARA OBTEN | K26: Z03 | L26: (AP) 15 Dias | M26: 10000811 | N26: Grava Triturada Caliza 20 mm - 3/4" | O26: DW70 | P26: MX-CED. CENTRO | Q26: 20260616 | R26: 20301231 | S26: 20260805 | T26: 20301231 | U26: 627 | V26: MXN | W26: M3 | X26: 471 | Y26: MXN | Z26: M3 | AA26: D084 | AB26: PD0186 IZTAPALAPA | AC26: 56103637 | AD26: 6644261540 | AE26: 4 | AF26: ENTREGA DIRECTA | AG26: 1.447 | AH26: M3 | AI26: X | AJ26: 4 | AK26: V4 | AL26: 20260811 | AM26: DW70-900006172-D084-10000811-4
A27: 900003438DW70D09310000811 | B27: 4600050497-930 | C27: 4600050497 | D27: 930 | E27: MXPO | F27: MXL | G27: 900003438 | H27: TC-ED-ESTRATEGIAS AVANZADAS | I27: 5049458 | J27: ESTRATEGIAS AVANZADAS PARA OBTEN | K27: Z03 | L27: (AP) 15 Dias | M27: 10000811 | N27: Grava Triturada Caliza 20 mm - 3/4" | O27: DW70 | P27: MX-CED. CENTRO | Q27: 20210712 | R27: 20281231 | S27: 20260819 | T27: 20301231 | U27: 413.5 | V27: MXN | W27: M3 | X27: 213.5 | Y27: MXN | Z27: M3 | AA27: D093 | AB27: PD0556 ZUMPANGO | AC27: 56103637 | AD27: 6644261540 | AE27: 4 | AF27: ENTREGA DIRECTA | AG27: 1.447 | AH27: M3 | AI27: X | AJ27: 4 | AK27: V4 | AL27: 20260821 | AM27: DW70-900003438-D093-10000811-4
A28: 900003438DW70D08510002802 | B28: 4600050497-500 | C28: 4600050497 | D28: 500 | E28: MXPO | F28: MXL | G28: 900003438 | H28: TC-ED-ESTRATEGIAS AVANZADAS | I28: 5049458 | J28: ESTRATEGIAS AVANZADAS PARA OBTEN | K28: Z03 | L28: (AP) 15 Dias | M28: 10002802 | N28: Arena Clasificada Río Malla 4 Lavado | O28: DW70 | P28: MX-CED. CENTRO | Q28: 20210712 | R28: 20281231 | S28: 20240827 | T28: 20291231 | U28: 327.98 | V28: MXN | W28: M3 | X28: 192.98 | Y28: MXN | Z28: M3 | AA28: D085 | AB28: PD0189 ROJO GOMEZ | AC28: 56103638 | AD28: 6644261540 | AE28: 4 | AF28: ENTREGA DIRECTA | AG28: 1.463 | AH28: M3 | AI28: X | AJ28: 4 | AK28: V4 | AL28: 20240830 | AM28: DW70-900003438-D085-10002802-4
A29: 900003438DW70D07410002802 | B29: 4600050497-440 | C29: 4600050497 | D29: 440 | E29: MXPO | F29: MXL | G29: 900003438 | H29: TC-ED-ESTRATEGIAS AVANZADAS | I29: 5049458 | J29: ESTRATEGIAS AVANZADAS PARA OBTEN | K29: Z03 | L29: (AP) 15 Dias | M29: 10002802 | N29: Arena Clasificada Río Malla 4 Lavado | O29: DW70 | P29: MX-CED. CENTRO | Q29: 20210712 | R29: 20281231 | S29: 20240827 | T29: 20291231 | U29: 371.83 | V29: MXN | W29: M3 | X29: 236.83 | Y29: MXN | Z29: M3 | AA29: D074 | AB29: PD0063 CENTRAL | AC29: 56103638 | AD29: 6644261540 | AE29: 4 | AF29: ENTREGA DIRECTA | AG29: 1.463 | AH29: M3 | AI29: X | AJ29: 4 | AK29: V4 | AL29: 20240830 | AM29: DW70-900003438-D074-10002802-4
A30: 900003438DW70D07910002802 | B30: 4600050497-460 | C30: 4600050497 | D30: 460 | E30: MXPO | F30: MXL | G30: 900003438 | H30: TC-ED-ESTRATEGIAS AVANZADAS | I30: 5049458 | J30: ESTRATEGIAS AVANZADAS PARA OBTEN | K30: Z03 | L30: (AP) 15 Dias | M30: 10002802 | N30: Arena Clasificada Río Malla 4 Lavado | O30: DW70 | P30: MX-CED. CENTRO | Q30: 20210712 | R30: 20281231 | S30: 20240827 | T30: 20291231 | U30: 375.48 | V30: MXN | W30: M3 | X30: 240.48 | Y30: MXN | Z30: M3 | AA30: D079 | AB30: PD0071 XOCHIMILCO | AC30: 56103638 | AD30: 6644261540 | AE30: 4 | AF30: ENTREGA DIRECTA | AG30: 1.463 | AH30: M3 | AI30: X | AJ30: 4 | AK30: V4 | AL30: 20240830 | AM30: DW70-900003438-D079-10002802-4
A31: 900003438DW70D08010002802 | B31: 4600050497-470 | C31: 4600050497 | D31: 470 | E31: MXPO | F31: MXL | G31: 900003438 | H31: TC-ED-ESTRATEGIAS AVANZADAS | I31: 5049458 | J31: ESTRATEGIAS AVANZADAS PARA OBTEN | K31: Z03 | L31: (AP) 15 Dias | M31: 10002802 | N31: Arena Clasificada Río Malla 4 Lavado | O31: DW70 | P31: MX-CED. CENTRO | Q31: 20210712 | R31: 20281231 | S31: 20240827 | T31: 20291231 | U31: 375.48 | V31: MXN | W31: M3 | X31: 240.48 | Y31: MXN | Z31: M3 | AA31: D080 | AB31: PD0086 VALLEJO | AC31: 56103638 | AD31: 6644261540 | AE31: 4 | AF31: ENTREGA DIRECTA | AG31: 1.463 | AH31: M3 | AI31: X | AJ31: 4 | AK31: V4 | AL31: 20240830 | AM31: DW70-900003438-D080-10002802-4
A32: 900003438DW70D14510002802 | B32: 4600050497-420 | C32: 4600050497 | D32: 420 | E32: MXPO | F32: MXL | G32: 900003438 | H32: TC-ED-ESTRATEGIAS AVANZADAS | I32: 5049458 | J32: ESTRATEGIAS AVANZADAS PARA OBTEN | K32: Z03 | L32: (AP) 15 Dias | M32: 10002802 | N32: Arena Clasificada Río Malla 4 Lavado | O32: DW70 | P32: MX-CED. CENTRO | Q32: 20210712 | R32: 20281231 | S32: 20240827 | T32: 20291231 | U32: 280.48 | V32: MXN | W32: M3 | X32: 145.48 | Y32: MXN | Z32: M3 | AA32: D145 | AB32: PD0458 ECATEPEC II | AC32: 56103638 | AD32: 6644261540 | AE32: 4 | AF32: ENTREGA DIRECTA | AG32: 1.463 | AH32: M3 | AI32: X | AJ32: 4 | AK32: V4 | AL32: 20240830 | AM32: DW70-900003438-D145-10002802-4
... A185: 900003438DW70D08810000623 | B185: 4600050497-220 | C185: 4600050497 | D185: 220 | E185: MXPO | F185: MXL | G185: 900003438 | H185: TC-ED-ESTRATEGIAS AVANZADAS | I185: 5049458 | J185: ESTRATEGIAS AVANZADAS PARA OBTEN | K185: Z03 | L185: (AP) 15 Dias | M185: 10000623 | N185: Grava Triturada Caliza 10 mm - 3/8" | O185: DW70 | P185: MX-CED. CENTRO | Q185: 20210712 | R185: 20281231 | S185: 20210712 | T185: 20251231 | U185: 195.72 | V185: MXN | W185: M3 | X185: 60.72 | Y185: MXN | Z185: M3 | AA185: D088 | AB185: PD081 HUEHUETOCA V | AC185: 56103637 | AD185: 6644261540 | AE185: 4 | AF185: ENTREGA DIRECTA | AG185: 1.41 | AH185: M3 | AI185: X | AJ185: 4 | AK185: V4 | AL185: 20230920 | AM185: DW70-900003438-D088-10000623-4
A186: 900009480DW7010000160 | B186: 4600071977-10 | C186: 4600071977 | D186: 10 | E186: MXPO | F186: MXL | G186: 900009480 | H186: SF TC-LOMA ANCHA SC | I186: 5047262 | J186: AGREGADOS PETREOS SAN CRISTOBAL | K186: Z03 | L186: (AP) 15 Dias | M186: 10000160 | N186: Arena Triturada Andesita Malla 4 | O186: DW70 | P186: MX-CED. CENTRO | Q186: 20260211 | R186: 20301231 | U186: 0 | V186: MXN | W186: M3 | AC186: 56103638 | AD186: 6644261540 | AE186: 1 | AF186: ENTREGADO | AG186: 1.409 | AH186: M3 | AI186: X | AJ186: 4 | AK186: V4 | AL186: 20260311 | AM186: DW70-900009480-10000160
A187: 900008265DW70ENXE10271724 | B187: 4600071526-50 | C187: 4600071526 | D187: 50 | E187: MXPO | F187: MXL | G187: 900008265 | H187: SF TC-ED CONCRETOS Y PAVIMENTOS | I187: 5089601 | J187: CONCRETOS Y PAVIMENTOS EXTERIORES S | K187: N90 | L187: (AP) NAFIN 90 Dias | M187: 10271724 | N187: MP RESIDUO DE CONCRETO | O187: DW70 | P187: MX-CED. CENTRO | Q187: 20250807 | R187: 20301231 | S187: 20251218 | T187: 20301231 | U187: 241.8 | V187: MXN | W187: M3 | X187: 200 | Y187: MXN | Z187: M3 | AA187: ENXE | AB187: PUENTES PERIFERICO ORIENTE/SICT | AC187: 56103636 | AD187: 6644261540 | AE187: 4 | AF187: ENTREGA DIRECTA | AG187: 1.9 | AH187: M3 | AI187: X | AJ187: 4 | AK187: V4 | AL187: 20251224 | AM187: DW70-900008265-ENXE-10271724-4
A188: 900006172DW70D08110233033 | B188: 4600072309-60 | C188: 4600072309 | D188: 60 | E188: MXPO | F188: MXL | G188: 900006172 | H188: SF TC-ED ESTRATEGIAS SANTA CALIZA | I188: 5049458 | J188: ESTRATEGIAS AVANZADAS PARA OBTEN | K188: Z03 | L188: (AP) 15 Dias | M188: 10233033 | N188: GRAVA TRITURADA CALIZA 13 MM - 1/2" P | O188: DW70 | P188: MX-CED. CENTRO | Q188: 20260616 | R188: 20301231 | S188: 20260616 | T188: 20301231 | U188: 507 | V188: MXN | W188: M3 | X188: 351 | Y188: MXN | Z188: M3 | AA188: D081 | AB188: PD0088 ARMAS | AC188: 56103637 | AD188: 6644261540 | AE188: 4 | AF188: ENTREGA DIRECTA | AG188: 1.4 | AH188: M3 | AI188: X | AJ188: 4 | AK188: V4 | AL188: 20260622 | AM188: DW70-900006172-D081-10233033-4
A189: 900000472DW70D13610000175 | B189: 4600050481-1090 | C189: 4600050481 | D189: 1090 | E189: MXPO | F189: MXL | G189: 900000472 | H189: TC-ED-TRIMCAV | I189: 5010147 | J189: TRITURACIONES DE MARMOL Y CALCIOS | K189: Z04 | L189: (AP) 30 Dias | M189: 10000175 | N189: Arena Triturada Caliza Malla 4 | O189: DW70 | P189: MX-CED. CENTRO | Q189: 20210712 | R189: 20291231 | S189: 20260605 | T189: 20301231 | U189: 600 | V189: MXN | W189: TN | X189: 440.86 | Y189: MXN | Z189: TN | AA189: D136 | AB189: PD0237 LA ESTRELLA | AC189: 56103638 | AD189: 6644261540 | AE189: 4 | AF189: ENTREGA DIRECTA | AG189: 1 | AH189: TO | AI189: X | AJ189: 4 | AK189: V4 | AL189: 20260611 | AM189: DW70-900000472-D136-10000175-4
A190: 900006172DW70D10510233033 | B190: 4600072309-120 | C190: 4600072309 | D190: 120 | E190: MXPO | F190: MXL | G190: 900006172 | H190: SF TC-ED ESTRATEGIAS SANTA CALIZA | I190: 5049458 | J190: ESTRATEGIAS AVANZADAS PARA OBTEN | K190: Z03 | L190: (AP) 15 Dias | M190: 10233033 | N190: GRAVA TRITURADA CALIZA 13 MM - 1/2" P | O190: DW70 | P190: MX-CED. CENTRO | Q190: 20260616 | R190: 20301231 | S190: 20260616 | T190: 20301231 | U190: 516 | V190: MXN | W190: M3 | X190: 360 | Y190: MXN | Z190: M3 | AA190: D105 | AB190: PD0331 NAUCALPAN II | AC190: 56103637 | AD190: 6644261540 | AE190: 4 | AF190: ENTREGA DIRECTA | AG190: 1.4 | AH190: M3 | AI190: X | AJ190: 4 | AK190: V4 | AL190: 20260622 | AM190: DW70-900006172-D105-10233033-4
A191: 900006172DW70D08510233033 | B191: 4600072309-90 | C191: 4600072309 | D191: 90 | E191: MXPO | F191: MXL | G191: 900006172 | H191: SF TC-ED ESTRATEGIAS SANTA CALIZA | I191: 5049458 | J191: ESTRATEGIAS AVANZADAS PARA OBTEN | K191: Z03 | L191: (AP) 15 Dias | M191: 10233033 | N191: GRAVA TRITURADA CALIZA 13 MM - 1/2" P | O191: DW70 | P191: MX-CED. CENTRO | Q191: 20260616 | R191: 20301231 | S191: 20260616 | T191: 20301231 | U191: 636 | V191: MXN | W191: M3 | X191: 480 | Y191: MXN | Z191: M3 | AA191: D085 | AB191: PD0189 ROJO GOMEZ | AC191: 56103637 | AD191: 6644261540 | AE191: 4 | AF191: ENTREGA DIRECTA | AG191: 1.4 | AH191: M3 | AI191: X | AJ191: 4 | AK191: V4 | AL191: 20260622 | AM191: DW70-900006172-D085-10233033-4
A192: 900006172DW70D14510233033 | B192: 4600072309-130 | C192: 4600072309 | D192: 130 | E192: MXPO | F192: MXL | G192: 900006172 | H192: SF TC-ED ESTRATEGIAS SANTA CALIZA | I192: 5049458 | J192: ESTRATEGIAS AVANZADAS PARA OBTEN | K192: Z03 | L192: (AP) 15 Dias | M192: 10233033 | N192: GRAVA TRITURADA CALIZA 13 MM - 1/2" P | O192: DW70 | P192: MX-CED. CENTRO | Q192: 20260616 | R192: 20301231 | S192: 20260616 | T192: 20301231 | U192: 454 | V192: MXN | W192: M3 | X192: 298 | Y192: MXN | Z192: M3 | AA192: D145 | AB192: PD0458 ECATEPEC II | AC192: 56103637 | AD192: 6644261540 | AE192: 4 | AF192: ENTREGA DIRECTA | AG192: 1.4 | AH192: M3 | AI192: X | AJ192: 4 | AK192: V4 | AL192: 20260622 | AM192: DW70-900006172-D145-10233033-4
A193: 900006172DW70D09810233033 | B193: 4600072309-110 | C193: 4600072309 | D193: 110 | E193: MXPO | F193: MXL | G193: 900006172 | H193: SF TC-ED ESTRATEGIAS SANTA CALIZA | I193: 5049458 | J193: ESTRATEGIAS AVANZADAS PARA OBTEN | K193: Z03 | L193: (AP) 15 Dias | M193: 10233033 | N193: GRAVA TRITURADA CALIZA 13 MM - 1/2" P | O193: DW70 | P193: MX-CED. CENTRO | Q193: 20260616 | R193: 20301231 | S193: 20260616 | T193: 20301231 | U193: 405 | V193: MXN | W193: M3 | X193: 249 | Y193: MXN | Z193: M3 | AA193: D098 | AB193: PD0315 CUAUTITLAN II | AC193: 56103637 | AD193: 6644261540 | AE193: 4 | AF193: ENTREGA DIRECTA | AG193: 1.4 | AH193: M3 | AI193: X | AJ193: 4 | AK193: V4 | AL193: 20260622 | AM193: DW70-900006172-D098-10233033-4
A194: 900006172DW70D08310233033 | B194: 4600072309-70 | C194: 4600072309 | D194: 70 | E194: MXPO | F194: MXL | G194: 900006172 | H194: SF TC-ED ESTRATEGIAS SANTA CALIZA | I194: 5049458 | J194: ESTRATEGIAS AVANZADAS PARA OBTEN | K194: Z03 | L194: (AP) 15 Dias | M194: 10233033 | N194: GRAVA TRITURADA CALIZA 13 MM - 1/2" P | O194: DW70 | P194: MX-CED. CENTRO | Q194: 20260616 | R194: 20301231 | S194: 20260616 | T194: 20301231 | U194: 579 | V194: MXN | W194: M3 | X194: 423 | Y194: MXN | Z194: M3 | AA194: D083 | AB194: PD0099 MINAS | AC194: 56103637 | AD194: 6644261540 | AE194: 4 | AF194: ENTREGA DIRECTA | AG194: 1.4 | AH194: M3 | AI194: X | AJ194: 4 | AK194: V4 | AL194: 20260622 | AM194: DW70-900006172-D083-10233033-4
A195: 900006172DW70D07410233033 | B195: 4600072309-10 | C195: 4600072309 | D195: 10 | E195: MXPO | F195: MXL | G195: 900006172 | H195: SF TC-ED ESTRATEGIAS SANTA CALIZA | I195: 5049458 | J195: ESTRATEGIAS AVANZADAS PARA OBTEN | K195: Z03 | L195: (AP) 15 Dias | M195: 10233033 | N195: GRAVA TRITURADA CALIZA 13 MM - 1/2" P | O195: DW70 | P195: MX-CED. CENTRO | Q195: 20260616 | R195: 20301231 | S195: 20260616 | T195: 20301231 | U195: 569 | V195: MXN | W195: M3 | X195: 413 | Y195: MXN | Z195: M3 | AA195: D074 | AB195: PD0063 CENTRAL | AC195: 56103637 | AD195: 6644261540 | AE195: 4 | AF195: ENTREGA DIRECTA | AG195: 1.4 | AH195: M3 | AI195: X | AJ195: 4 | AK195: V4 | AL195: 20260622 | AM195: DW70-900006172-D074-10233033-4
A196: 900006172DW70D07910233033 | B196: 4600072309-40 | C196: 4600072309 | D196: 40 | E196: MXPO | F196: MXL | G196: 900006172 | H196: SF TC-ED ESTRATEGIAS SANTA CALIZA | I196: 5049458 | J196: ESTRATEGIAS AVANZADAS PARA OBTEN | K196: Z03 | L196: (AP) 15 Dias | M196: 10233033 | N196: GRAVA TRITURADA CALIZA 13 MM - 1/2" P | O196: DW70 | P196: MX-CED. CENTRO | Q196: 20260616 | R196: 20301231 | S196: 20260616 | T196: 20301231 | U196: 694 | V196: MXN | W196: M3 | X196: 538 | Y196: MXN | Z196: M3 | AA196: D079 | AB196: PD0071 XOCHIMILCO | AC196: 56103637 | AD196: 6644261540 | AE196: 4 | AF196: ENTREGA DIRECTA | AG196: 1.4 | AH196: M3 | AI196: X | AJ196: 4 | AK196: V4 | AL196: 20260622 | AM196: DW70-900006172-D079-10233033-4
A197: 900008570DW7010248830 | B197: 4600068578-10 | C197: 4600068578 | D197: 10 | E197: MXPO | F197: MXL | G197: 900008570 | H197: SF TC-MINA EL DUENDE | I197: 5090107 | J197: MORALES BARRIOS GASPAR GERARDO | K197: Z09 | L197: (AP) 90 Dias | M197: 10248830 | N197: ARENA CLASIFICADA RIO LAVADA MALLA 4 | O197: DW70 | P197: MX-CED. CENTRO | Q197: 20231005 | R197: 20291231 | S197: 20260601 | T197: 20301231 | U197: 150 | V197: MXN | W197: M3 | X197: 0 | Y197: MXN | Z197: M3 | AC197: 56103638 | AD197: 6644261540 | AE197: 1 | AF197: ENTREGADO | AG197: 1.608 | AH197: M3 | AI197: X | AJ197: 4 | AK197: V4 | AL197: 20260611 | AM197: DW70-900008570-10248830
A198: 900006172DW70D07510233033 | B198: 4600072309-20 | C198: 4600072309 | D198: 20 | E198: MXPO | F198: MXL | G198: 900006172 | H198: SF TC-ED ESTRATEGIAS SANTA CALIZA | I198: 5049458 | J198: ESTRATEGIAS AVANZADAS PARA OBTEN | K198: Z03 | L198: (AP) 15 Dias | M198: 10233033 | N198: GRAVA TRITURADA CALIZA 13 MM - 1/2" P | O198: DW70 | P198: MX-CED. CENTRO | Q198: 20260616 | R198: 20301231 | S198: 20260616 | T198: 20301231 | U198: 507 | V198: MXN | W198: M3 | X198: 351 | Y198: MXN | Z198: M3 | AA198: D075 | AB198: PD0065 CEYLAN | AC198: 56103637 | AD198: 6644261540 | AE198: 4 | AF198: ENTREGA DIRECTA | AG198: 1.4 | AH198: M3 | AI198: X | AJ198: 4 | AK198: V4 | AL198: 20260622 | AM198: DW70-900006172-D075-10233033-4
A199: 900006172DW70D68110233033 | B199: 4600072309-150 | C199: 4600072309 | D199: 150 | E199: MXPO | F199: MXL | G199: 900006172 | H199: SF TC-ED ESTRATEGIAS SANTA CALIZA | I199: 5049458 | J199: ESTRATEGIAS AVANZADAS PARA OBTEN | K199: Z03 | L199: (AP) 15 Dias | M199: 10233033 | N199: GRAVA TRITURADA CALIZA 13 MM - 1/2" P | O199: DW70 | P199: MX-CED. CENTRO | Q199: 20260616 | R199: 20301231 | S199: 20260616 | T199: 20301231 | U199: 436 | V199: MXN | W199: M3 | X199: 280 | Y199: MXN | Z199: M3 | AA199: D681 | AB199: PD0639 TULTEPEC | AC199: 56103637 | AD199: 6644261540 | AE199: 4 | AF199: ENTREGA DIRECTA | AG199: 1.4 | AH199: M3 | AI199: X | AJ199: 4 | AK199: V4 | AL199: 20260622 | AM199: DW70-900006172-D681-10233033-4
A200: 900006172DW70D13610233033 | B200: 4600072309-100 | C200: 4600072309 | D200: 100 | E200: MXPO | F200: MXL | G200: 900006172 | H200: SF TC-ED ESTRATEGIAS SANTA CALIZA | I200: 5049458 | J200: ESTRATEGIAS AVANZADAS PARA OBTEN | K200: Z03 | L200: (AP) 15 Dias | M200: 10233033 | N200: GRAVA TRITURADA CALIZA 13 MM - 1/2" P | O200: DW70 | P200: MX-CED. CENTRO | Q200: 20260616 | R200: 20301231 | S200: 20260616 | T200: 20301231 | U200: 627 | V200: MXN | W200: M3 | X200: 471 | Y200: MXN | Z200: M3 | AA200: D136 | AB200: PD0237 LA ESTRELLA | AC200: 56103637 | AD200: 6644261540 | AE200: 4 | AF200: ENTREGA DIRECTA | AG200: 1.4 | AH200: M3 | AI200: X | AJ200: 4 | AK200: V4 | AL200: 20260622 | AM200: DW70-900006172-D136-10233033-4
A201: 900006172DW70D08010233033 | B201: 4600072309-50 | C201: 4600072309 | D201: 50 | E201: MXPO | F201: MXL | G201: 900006172 | H201: SF TC-ED ESTRATEGIAS SANTA CALIZA | I201: 5049458 | J201: ESTRATEGIAS AVANZADAS PARA OBTEN | K201: Z03 | L201: (AP) 15 Dias | M201: 10233033 | N201: GRAVA TRITURADA CALIZA 13 MM - 1/2" P | O201: DW70 | P201: MX-CED. CENTRO | Q201: 20260616 | R201: 20301231 | S201: 20260616 | T201: 20301231 | U201: 507 | V201: MXN | W201: M3 | X201: 351 | Y201: MXN | Z201: M3 | AA201: D080 | AB201: PD0086 VALLEJO | AC201: 56103637 | AD201: 6644261540 | AE201: 4 | AF201: ENTREGA DIRECTA | AG201: 1.4 | AH201: M3 | AI201: X | AJ201: 4 | AK201: V4 | AL201: 20260622 | AM201: DW70-900006172-D080-10233033-4
A202: 900006172DW70D08410233033 | B202: 4600072309-80 | C202: 4600072309 | D202: 80 | E202: MXPO | F202: MXL | G202: 900006172 | H202: SF TC-ED ESTRATEGIAS SANTA CALIZA | I202: 5049458 | J202: ESTRATEGIAS AVANZADAS PARA OBTEN | K202: Z03 | L202: (AP) 15 Dias | M202: 10233033 | N202: GRAVA TRITURADA CALIZA 13 MM - 1/2" P | O202: DW70 | P202: MX-CED. CENTRO | Q202: 20260616 | R202: 20301231 | S202: 20260616 | T202: 20301231 | U202: 627 | V202: MXN | W202: M3 | X202: 471 | Y202: MXN | Z202: M3 | AA202: D084 | AB202: PD0186 IZTAPALAPA | AC202: 56103637 | AD202: 6644261540 | AE202: 4 | AF202: ENTREGA DIRECTA | AG202: 1.4 | AH202: M3 | AI202: X | AJ202: 4 | AK202: V4 | AL202: 20260622 | AM202: DW70-900006172-D084-10233033-4
A203: 900006172DW70D07710233033 | B203: 4600072309-30 | C203: 4600072309 | D203: 30 | E203: MXPO | F203: MXL | G203: 900006172 | H203: SF TC-ED ESTRATEGIAS SANTA CALIZA | I203: 5049458 | J203: ESTRATEGIAS AVANZADAS PARA OBTEN | K203: Z03 | L203: (AP) 15 Dias | M203: 10233033 | N203: GRAVA TRITURADA CALIZA 13 MM - 1/2" P | O203: DW70 | P203: MX-CED. CENTRO | Q203: 20260616 | R203: 20301231 | S203: 20260616 | T203: 20301231 | U203: 677 | V203: MXN | W203: M3 | X203: 521 | Y203: MXN | Z203: M3 | AA203: D077 | AB203: PD0067 LOS REYES | AC203: 56103637 | AD203: 6644261540 | AE203: 4 | AF203: ENTREGA DIRECTA | AG203: 1.4 | AH203: M3 | AI203: X | AJ203: 4 | AK203: V4 | AL203: 20260622 | AM203: DW70-900006172-D077-10233033-4
A204: 900006172DW70D09310233033 | B204: 4600072309-140 | C204: 4600072309 | D204: 140 | E204: MXPO | F204: MXL | G204: 900006172 | H204: SF TC-ED ESTRATEGIAS SANTA CALIZA | I204: 5049458 | J204: ESTRATEGIAS AVANZADAS PARA OBTEN | K204: Z03 | L204: (AP) 15 Dias | M204: 10233033 | N204: GRAVA TRITURADA CALIZA 13 MM - 1/2" P | O204: DW70 | P204: MX-CED. CENTRO | Q204: 20260616 | R204: 20301231 | S204: 20260616 | T204: 20301231 | U204: 347 | V204: MXN | W204: M3 | X204: 191 | Y204: MXN | Z204: M3 | AA204: D093 | AB204: PD0556 ZUMPANGO | AC204: 56103637 | AD204: 6644261540 | AE204: 4 | AF204: ENTREGA DIRECTA | AG204: 1.4 | AH204: M3 | AI204: X | AJ204: 4 | AK204: V4 | AL204: 20260622 | AM204: DW70-900006172-D093-10233033-4
A205: 900000034DW7010000623 | B205: 4600050469-10 | C205: 4600050469 | D205: 10 | E205: MXPO | F205: MXL | G205: 900000034 | H205: TC-EJIDO PROGRESO | I205: 5001924 | J205: EJIDO PROGRESO | K205: Z04 | L205: (AP) 30 Dias | M205: 10000623 | N205: Grava Triturada Caliza 10 mm - 3/8" | O205: DW70 | P205: MX-CED. CENTRO | Q205: 20210712 | R205: 20291231 | S205: 20250701 | T205: 20301231 | U205: 100 | V205: MXN | W205: TN | X205: 0 | Y205: MXN | Z205: TN | AC205: 56103637 | AD205: 6644261540 | AE205: 1 | AF205: ENTREGADO | AG205: 1 | AH205: TO | AI205: X | AJ205: 4 | AK205: V4 | AL205: 20250911 | AM205: DW70-900000034-10000623
A206: 900009292DW7010000630 | B206: 4600071553-20 | C206: 4600071553 | D206: 20 | E206: MXPO | F206: MXL | G206: 900009292 | H206: SF TC-GRAVICOR GIL | I206: 5096226 | J206: GIL HERNANDEZ RACIEL | K206: N90 | L206: (AP) NAFIN 90 Dias | M206: 10000630 | N206: Grava Triturada Caliza 13 mm - 1/2" | O206: DW70 | P206: MX-CED. CENTRO | Q206: 20250813 | R206: 20301231 | S206: 20250813 | T206: 20301231 | U206: 193.58 | V206: MXN | W206: M3 | X206: 0 | Y206: MXN | Z206: M3 | AC206: 56103637 | AD206: 6644261540 | AE206: 1 | AF206: ENTREGADO | AG206: 1.4 | AH206: M3 | AI206: X | AJ206: 4 | AK206: V4 | AL206: 20250815 | AM206: DW70-900009292-10000630
A207: 900009292DW7010269246 | B207: 4600071553-40 | C207: 4600071553 | D207: 40 | E207: MXPO | F207: MXL | G207: 900009292 | H207: SF TC-GRAVICOR GIL | I207: 5096226 | J207: GIL HERNANDEZ RACIEL | K207: N90 | L207: (AP) NAFIN 90 Dias | M207: 10269246 | N207: MP GRAVA TRITURADA CALIZA 1 1/2 - 40MM | O207: DW70 | P207: MX-CED. CENTRO | Q207: 20250813 | R207: 20301231 | S207: 20250813 | T207: 20301231 | U207: 193.58 | V207: MXN | W207: M3 | X207: 0 | Y207: MXN | Z207: M3 | AC207: 56103637 | AD207: 6644261540 | AE207: 1 | AF207: ENTREGADO | AG207: 1.4 | AH207: M3 | AI207: X | AJ207: 4 | AK207: V4 | AL207: 20250815 | AM207: DW70-900009292-10269246
A208: 900009292DW7010269245 | B208: 4600071553-10 | C208: 4600071553 | D208: 10 | E208: MXPO | F208: MXL | G208: 900009292 | H208: SF TC-GRAVICOR GIL | I208: 5096226 | J208: GIL HERNANDEZ RACIEL | K208: N90 | L208: (AP) NAFIN 90 Dias | M208: 10269245 | N208: MP GRAVA TRITURADA CALIZA 3/8 - 10MM | O208: DW70 | P208: MX-CED. CENTRO | Q208: 20250813 | R208: 20301231 | S208: 20250813 | T208: 20301231 | U208: 199.67 | V208: MXN | W208: M3 | X208: 0 | Y208: MXN | Z208: M3 | AC208: 56103637 | AD208: 6644261540 | AE208: 1 | AF208: ENTREGADO | AG208: 1.41 | AH208: M3 | AI208: X | AJ208: 4 | AK208: V4 | AL208: 20250815 | AM208: DW70-900009292-10269245
A209: 900004046DW7010002802 | B209: 4600050501-10 | C209: 4600050501 | D209: 10 | E209: MXPO | F209: MXL | G209: 900004046 | H209: TC-SAN JUAN (HUDASA) | I209: 5054686 | J209: GRUPO MERCANTIL HUDASA SA DE CV | K209: Z06 | L209: (AP) 45 Dias | M209: 10002802 | N209: Arena Clasificada Río Malla 4 Lavado | O209: DW70 | P209: MX-CED. CENTRO | Q209: 20210712 | R209: 20261231 | S209: 20210712 | T209: 20261231 | U209: 135 | V209: MXN | W209: M3 | X209: 0 | Y209: MXN | Z209: M3 | AC209: 56103638 | AD209: 6644261540 | AE209: 1 | AF209: ENTREGADO | AG209: 1.463 | AH209: M3 | AI209: X | AJ209: 4 | AK209: V4 | AL209: 20260108 | AM209: DW70-900004046-10002802
A210: 900005400DW7010059181 | B210: 4600050519-30 | C210: 4600050519 | D210: 30 | E210: MXPO | F210: MXL | G210: 900005400 | H210: TC-DESARROLLO MINERO | I210: 5069420 | J210: PROMOTORA DE DESARROLLO MINERO | K210: Z09 | L210: (AP) 90 Dias | M210: 10059181 | N210: Arena Triturada Andesita Malla 4 | O210: DW70 | P210: MX-CED. CENTRO | Q210: 20210712 | R210: 20261231 | S210: 20210712 | T210: 20261231 | U210: 78.75 | V210: MXN | W210: M3 | X210: 0 | Y210: MXN | Z210: M3 | AC210: 56103638 | AD210: 6644261540 | AE210: 1 | AF210: ENTREGADO | AG210: 1.221 | AH210: M3 | AI210: X | AJ210: 4 | AK210: V4 | AL210: 20260108 | AM210: DW70-900005400-10059181
A211: 900006140DW7010169677 | B211: 4600050550-10 | C211: 4600050550 | D211: 10 | E211: MXPO | F211: MXL | G211: 900006140 | H211: SF TC-ROCA DURA SANTA FE | I211: 5032274 | J211: TRITURADORA ROCA DURA SAN MIGUEL | K211: Z03 | L211: (AP) 15 Dias | M211: 10169677 | N211: BALASTO TRITURADO CALIZA 4" A FINOS | O211: DW70 | P211: MX-CED. CENTRO | Q211: 20210712 | R211: 20261231 | S211: 20210712 | T211: 20261231 | U211: 250 | V211: MXN | W211: M3 | X211: 0 | Y211: MXN | Z211: M3 | AC211: 56103591 | AD211: 6644261540 | AE211: 1 | AF211: ENTREGADO | AG211: 1.6 | AH211: M3 | AI211: X | AJ211: 4 | AK211: V4 | AL211: 20260108 | AM211: DW70-900006140-10169677
A212: 900006140DW7010165990 | B212: 4600050550-20 | C212: 4600050550 | D212: 20 | E212: MXPO | F212: MXL | G212: 900006140 | H212: SF TC-ROCA DURA SANTA FE | I212: 5032274 | J212: TRITURADORA ROCA DURA SAN MIGUEL | K212: Z03 | L212: (AP) 15 Dias | M212: 10165990 | N212: DESPERDICIO TRITURADO CALIZA | O212: DW70 | P212: MX-CED. CENTRO | Q212: 20210712 | R212: 20261231 | S212: 20210712 | T212: 20261231 | U212: 250 | V212: MXN | W212: M3 | X212: 0 | Y212: MXN | Z212: M3 | AC212: 56103695 | AD212: 6644261540 | AE212: 1 | AF212: ENTREGADO | AG212: 1.1 | AH212: M3 | AI212: X | AJ212: 4 | AK212: V4 | AL212: 20260108 | AM212: DW70-900006140-10165990
A213: 900006140DW7010165760 | B213: 4600050550-30 | C213: 4600050550 | D213: 30 | E213: MXPO | F213: MXL | G213: 900006140 | H213: SF TC-ROCA DURA SANTA FE | I213: 5032274 | J213: TRITURADORA ROCA DURA SAN MIGUEL | K213: Z03 | L213: (AP) 15 Dias | M213: 10165760 | N213: BALASTO TRITURADO BASALTO 6" A FINOS | O213: DW70 | P213: MX-CED. CENTRO | Q213: 20210712 | R213: 20261231 | S213: 20210712 | T213: 20261231 | U213: 250 | V213: MXN | W213: M3 | X213: 0 | Y213: MXN | Z213: M3 | AC213: 56103591 | AD213: 6644261540 | AE213: 1 | AF213: ENTREGADO | AG213: 1.65 | AH213: M3 | AI213: X | AJ213: 4 | AK213: V4 | AL213: 20260108 | AM213: DW70-900006140-10165760
A214: 900005400DW7010000627 | B214: 4600050519-20 | C214: 4600050519 | D214: 20 | E214: MXPO | F214: MXL | G214: 900005400 | H214: TC-DESARROLLO MINERO | I214: 5069420 | J214: PROMOTORA DE DESARROLLO MINERO | K214: Z09 | L214: (AP) 90 Dias | M214: 10000627 | N214: Grava Triturada Andesita 10 mm - 3/8" | O214: DW70 | P214: MX-CED. CENTRO | Q214: 20210712 | R214: 20261231 | S214: 20210712 | T214: 20261231 | U214: 78.75 | V214: MXN | W214: M3 | X214: 0 | Y214: MXN | Z214: M3 | AC214: 56103637 | AD214: 6644261540 | AE214: 1 | AF214: ENTREGADO | AG214: 1.33 | AH214: M3 | AI214: X | AJ214: 4 | AK214: V4 | AL214: 20260108 | AM214: DW70-900005400-10000627
A215: 900006227DW7010170112 | B215: 4600050552-10 | C215: 4600050552 | D215: 10 | E215: MXPO | F215: MXL | G215: 900006227 | H215: SF TC-EL ARBOLILLO | I215: 5075949 | J215: AZUL CONCRETOS Y PREMEZCLADOS | K215: Z06 | L215: (AP) 45 Dias | M215: 10170112 | N215: GRAVA TRITURADA CALIZA 20 MM - 3/4" | O215: DW70 | P215: MX-CED. CENTRO | Q215: 20210712 | R215: 20261231 | S215: 20211111 | T215: 20261231 | U215: 135 | V215: MXN | W215: M3 | X215: 0 | Y215: MXN | Z215: M3 | AC215: 56103637 | AD215: 6644261540 | AE215: 1 | AF215: ENTREGADO | AG215: 1.423 | AH215: M3 | AI215: X | AJ215: 4 | AK215: V4 | AL215: 20230920 | AM215: DW70-900006227-10170112
A216: 900005705DW7010000811 | B216: 4600050539-10 | C216: 4600050539 | D216: 10 | E216: MXPO | F216: MXL | G216: 900005705 | H216: TC-ROCA DURA LERMA | I216: 5032274 | J216: TRITURADORA ROCA DURA SAN MIGUEL | K216: Z03 | L216: (AP) 15 Dias | M216: 10000811 | N216: Grava Triturada Caliza 20 mm - 3/4" | O216: DW70 | P216: MX-CED. CENTRO | Q216: 20210712 | R216: 20261231 | S216: 20220215 | T216: 20271231 | U216: 365.18 | V216: MXN | W216: M3 | X216: 0 | Y216: MXN | Z216: M3 | AC216: 56103637 | AD216: 6644261540 | AE216: 1 | AF216: ENTREGADO | AG216: 1.447 | AH216: M3 | AI216: X | AJ216: 4 | AK216: V4 | AL216: 20230920 | AM216: DW70-900005705-10000811
... A242: 900007455DW7010000624 | B242: 4600052690-20 | C242: 4600052690 | D242: 20 | E242: MXPO | F242: MXL | G242: 900007455 | H242: SF TC-EL ARBOLILLO II | I242: 5082691 | J242: CEMENTOS Y CONCRETOS LA CRUZ AZUL S | K242: Z06 | L242: (AP) 45 Dias | M242: 10000624 | N242: Grava Triturada Caliza 40 mm - 1 1/2" | O242: DW70 | P242: MX-CED. CENTRO | Q242: 20211101 | R242: 20261231 | S242: 20211101 | T242: 20261231 | U242: 135 | V242: MXN | W242: M3 | X242: 0 | Y242: MXN | Z242: M3 | AC242: 56103637 | AD242: 6644261540 | AE242: 1 | AF242: ENTREGADO | AG242: 1.45 | AH242: M3 | AI242: X | AJ242: 4 | AK242: V4 | AL242: 20230920 | AM242: DW70-900007455-10000624
A243: 900008265DW70ENXE10260055 | B243: 4600071526-30 | C243: 4600071526 | D243: 30 | E243: MXPO | F243: MXL | G243: 900008265 | H243: SF TC-ED CONCRETOS Y PAVIMENTOS | I243: 5089601 | J243: CONCRETOS Y PAVIMENTOS EXTERIORES S | K243: N90 | L243: (AP) NAFIN 90 Dias | M243: 10260055 | N243: GREÑA | O243: DW70 | P243: MX-CED. CENTRO | Q243: 20250807 | R243: 20301231 | S243: 20250821 | T243: 20301231 | U243: 424.5 | V243: MXN | W243: M3 | X243: 320 | Y243: MXN | Z243: M3 | AA243: ENXE | AB243: PUENTES PERIFERICO ORIENTE/SICT | AC243: 56103637 | AD243: 6644261540 | AE243: 4 | AF243: ENTREGA DIRECTA | AG243: 2.5 | AH243: M3 | AI243: X | AJ243: 4 | AK243: V4 | AL243: 20250830 | AM243: DW70-900008265-ENXE-10260055-4
A244: 900004090DW70D08810000623 | B244: 4600050503-20 | C244: 4600050503 | D244: 20 | E244: MXPO | F244: MXL | G244: 900004090 | H244: TC-ED-ESTRATEGIAS AVANZADAS (CONEJO | I244: 5049458 | J244: ESTRATEGIAS AVANZADAS PARA OBTEN | K244: Z03 | L244: (AP) 15 Dias | M244: 10000623 | N244: Grava Triturada Caliza 10 mm - 3/8" | O244: DW70 | P244: MX-CED. CENTRO | Q244: 20210712 | R244: 20261231 | S244: 20210712 | T244: 20261231 | U244: 201 | V244: MXN | W244: M3 | X244: 66 | Y244: MXN | Z244: M3 | AA244: D088 | AB244: PD081 HUEHUETOCA V | AC244: 56103637 | AD244: 6644261540 | AE244: 4 | AF244: ENTREGA DIRECTA | AG244: 1.41 | AH244: M3 | AI244: X | AJ244: 4 | AK244: V4 | AL244: 20260108 | AM244: DW70-900004090-D088-10000623-4
A245: 900004090DW70D09310000623 | B245: 4600050503-10 | C245: 4600050503 | D245: 10 | E245: MXPO | F245: MXL | G245: 900004090 | H245: TC-ED-ESTRATEGIAS AVANZADAS (CONEJO | I245: 5049458 | J245: ESTRATEGIAS AVANZADAS PARA OBTEN | K245: Z03 | L245: (AP) 15 Dias | M245: 10000623 | N245: Grava Triturada Caliza 10 mm - 3/8" | O245: DW70 | P245: MX-CED. CENTRO | Q245: 20210712 | R245: 20261231 | S245: 20210712 | T245: 20261231 | U245: 261.72 | V245: MXN | W245: M3 | X245: 126.72 | Y245: MXN | Z245: M3 | AA245: D093 | AB245: PD0556 ZUMPANGO | AC245: 56103637 | AD245: 6644261540 | AE245: 4 | AF245: ENTREGA DIRECTA | AG245: 1.41 | AH245: M3 | AI245: X | AJ245: 4 | AK245: V4 | AL245: 20260108 | AM245: DW70-900004090-D093-10000623-4
A246: 900004090DW70D10510000623 | B246: 4600050503-50 | C246: 4600050503 | D246: 50 | E246: MXPO | F246: MXL | G246: 900004090 | H246: TC-ED-ESTRATEGIAS AVANZADAS (CONEJO | I246: 5049458 | J246: ESTRATEGIAS AVANZADAS PARA OBTEN | K246: Z03 | L246: (AP) 15 Dias | M246: 10000623 | N246: Grava Triturada Caliza 10 mm - 3/8" | O246: DW70 | P246: MX-CED. CENTRO | Q246: 20210712 | R246: 20261231 | S246: 20210712 | T246: 20261231 | U246: 317.16 | V246: MXN | W246: M3 | X246: 182.16 | Y246: MXN | Z246: M3 | AA246: D105 | AB246: PD0331 NAUCALPAN II | AC246: 56103637 | AD246: 6644261540 | AE246: 4 | AF246: ENTREGA DIRECTA | AG246: 1.41 | AH246: M3 | AI246: X | AJ246: 4 | AK246: V4 | AL246: 20260108 | AM246: DW70-900004090-D105-10000623-4
A247: 900000472DW70D08310000655 | B247: 4600050481-240 | C247: 4600050481 | D247: 240 | E247: MXPO | F247: MXL | G247: 900000472 | H247: TC-ED-TRIMCAV | I247: 5010147 | J247: TRITURACIONES DE MARMOL Y CALCIOS | K247: Z04 | L247: (AP) 30 Dias | M247: 10000655 | N247: Grava Triturada Marmol 10 mm - 3/8" | O247: DW70 | P247: MX-CED. CENTRO | Q247: 20210712 | R247: 20291231 | S247: 20260301 | T247: 20301231 | U247: 1150.11 | V247: MXN | W247: TN | X247: 605.33 | Y247: MXN | Z247: TN | AA247: D083 | AB247: PD0099 MINAS | AC247: 56103637 | AD247: 6644261540 | AE247: 4 | AF247: ENTREGA DIRECTA | AG247: 1 | AH247: TO | AI247: X | AJ247: 4 | AK247: V4 | AL247: 20260306 | AM247: DW70-900000472-D083-10000655-4
A248: 900000472DW70D08310000643 | B248: 4600050481-630 | C248: 4600050481 | D248: 630 | E248: MXPO | F248: MXL | G248: 900000472 | H248: TC-ED-TRIMCAV | I248: 5010147 | J248: TRITURACIONES DE MARMOL Y CALCIOS | K248: Z04 | L248: (AP) 30 Dias | M248: 10000643 | N248: Grava Triturada Marmol 20 mm - 3/4" | O248: DW70 | P248: MX-CED. CENTRO | Q248: 20210712 | R248: 20291231 | S248: 20260301 | T248: 20301231 | U248: 1150.11 | V248: MXN | W248: TN | X248: 605.33 | Y248: MXN | Z248: TN | AA248: D083 | AB248: PD0099 MINAS | AC248: 56103637 | AD248: 6644261540 | AE248: 4 | AF248: ENTREGA DIRECTA | AG248: 1 | AH248: TO | AI248: X | AJ248: 4 | AK248: V4 | AL248: 20260306 | AM248: DW70-900000472-D083-10000643-4
A249: 900000472DW70D13610000643 | B249: 4600050481-340 | C249: 4600050481 | D249: 340 | E249: MXPO | F249: MXL | G249: 900000472 | H249: TC-ED-TRIMCAV | I249: 5010147 | J249: TRITURACIONES DE MARMOL Y CALCIOS | K249: Z04 | L249: (AP) 30 Dias | M249: 10000643 | N249: Grava Triturada Marmol 20 mm - 3/4" | O249: DW70 | P249: MX-CED. CENTRO | Q249: 20210712 | R249: 20291231 | S249: 20260301 | T249: 20301231 | U249: 1150.11 | V249: MXN | W249: TN | X249: 605.33 | Y249: MXN | Z249: TN | AA249: D136 | AB249: PD0237 LA ESTRELLA | AC249: 56103637 | AD249: 6644261540 | AE249: 4 | AF249: ENTREGA DIRECTA | AG249: 1 | AH249: TO | AI249: X | AJ249: 4 | AK249: V4 | AL249: 20260306 | AM249: DW70-900000472-D136-10000643-4
A250: 900000472DW70D08310000635 | B250: 4600050481-960 | C250: 4600050481 | D250: 960 | E250: MXPO | F250: MXL | G250: 900000472 | H250: TC-ED-TRIMCAV | I250: 5010147 | J250: TRITURACIONES DE MARMOL Y CALCIOS | K250: Z04 | L250: (AP) 30 Dias | M250: 10000635 | N250: Arena Triturada Marmol Malla 4 | O250: DW70 | P250: MX-CED. CENTRO | Q250: 20210712 | R250: 20291231 | S250: 20260301 | T250: 20301231 | U250: 1150.11 | V250: MXN | W250: TN | X250: 605.33 | Y250: MXN | Z250: TN | AA250: D083 | AB250: PD0099 MINAS | AC250: 56103638 | AD250: 6644261540 | AE250: 4 | AF250: ENTREGA DIRECTA | AG250: 1 | AH250: TO | AI250: X | AJ250: 4 | AK250: V4 | AL250: 20260306 | AM250: DW70-900000472-D083-10000635-4
A251: 900008619DW70D08510019515 | B251: 4600071885-10 | C251: 4600071885 | D251: 10 | E251: MXPO | F251: MXL | G251: 900008619 | H251: SF TC-ED DOS CERROS | I251: 5036168 | J251: TRITURADOS DOS CERROS SA DE CV | K251: Z09 | L251: (AP) 90 Dias | M251: 10019515 | N251: Grava Triturada Tezontle 20mm - 3/4" | O251: DW70 | P251: MX-CED. CENTRO | Q251: 20260107 | R251: 20301231 | S251: 20260107 | T251: 20301231 | U251: 480 | V251: MXN | W251: M3 | X251: 300 | Y251: MXN | Z251: M3 | AA251: D085 | AB251: PD0189 ROJO GOMEZ | AC251: 56103637 | AD251: 6644261540 | AE251: 4 | AF251: ENTREGA DIRECTA | AG251: 1.3 | AH251: M3 | AI251: X | AJ251: 4 | AK251: V4 | AL251: 20260112 | AM251: DW70-900008619-D085-10019515-4
A252: 900000472DW70D13610000635 | B252: 4600050481-350 | C252: 4600050481 | D252: 350 | E252: MXPO | F252: MXL | G252: 900000472 | H252: TC-ED-TRIMCAV | I252: 5010147 | J252: TRITURACIONES DE MARMOL Y CALCIOS | K252: Z04 | L252: (AP) 30 Dias | M252: 10000635 | N252: Arena Triturada Marmol Malla 4 | O252: DW70 | P252: MX-CED. CENTRO | Q252: 20210712 | R252: 20291231 | S252: 20260301 | T252: 20301231 | U252: 1150.11 | V252: MXN | W252: TN | X252: 605.33 | Y252: MXN | Z252: TN | AA252: D136 | AB252: PD0237 LA ESTRELLA | AC252: 56103638 | AD252: 6644261540 | AE252: 4 | AF252: ENTREGA DIRECTA | AG252: 1 | AH252: TO | AI252: X | AJ252: 4 | AK252: V4 | AL252: 20260306 | AM252: DW70-900000472-D136-10000635-4
A253: 900001810DW7010000160 | B253: 4600050493-30 | C253: 4600050493 | D253: 30 | E253: MXPO | F253: MXL | G253: 900001810 | H253: TC-TRIVOMEX | I253: 5033501 | J253: TRITURADOS VOLCANICOS DE MEXICO | K253: Z04 | L253: (AP) 30 Dias | M253: 10000160 | N253: Arena Triturada Andesita Malla 4 | O253: DW70 | P253: MX-CED. CENTRO | Q253: 20210712 | R253: 20291231 | U253: 0 | V253: MXN | W253: M3 | AC253: 56103638 | AD253: 6644261540 | AE253: 1 | AF253: ENTREGADO | AG253: 1.409 | AH253: M3 | AI253: X | AJ253: 4 | AK253: V4 | AL253: 20260319 | AM253: DW70-900001810-10000160
A254: 900007079DW70ENDB10175723 | B254: 4600071478-20 | C254: 4600071478 | D254: 20 | E254: MXPO | F254: MXL | G254: 900007079 | H254: SF TC-ED-TRIVOMEX | I254: 5033501 | J254: TRITURADOS VOLCANICOS DE MEXICO | K254: Z04 | L254: (AP) 30 Dias | M254: 10175723 | N254: BASE HIDRAULICA ANDESITA DE 1 1/2" A FIN | O254: DW70 | P254: MX-CED. CENTRO | Q254: 20250722 | R254: 20301231 | S254: 20250722 | T254: 20301231 | U254: 310 | V254: MXN | W254: M3 | X254: 150 | Y254: MXN | Z254: M3 | AA254: ENDB | AB254: FABRICA VESTIMENTA Y EQ (FAVE) E3 / | AC254: 56103590 | AD254: 6644261540 | AE254: 4 | AF254: ENTREGA DIRECTA | AG254: 1.65 | AH254: M3 | AI254: X | AJ254: 4 | AK254: V4 | AL254: 20250729 | AM254: DW70-900007079-ENDB-10175723-4
A255: 900007079DW70ENDB10000206 | B255: 4600071478-30 | C255: 4600071478 | D255: 30 | E255: MXPO | F255: MXL | G255: 900007079 | H255: SF TC-ED-TRIVOMEX | I255: 5033501 | J255: TRITURADOS VOLCANICOS DE MEXICO | K255: Z04 | L255: (AP) 30 Dias | M255: 10000206 | N255: Tepetate Triturado Tierra NA | O255: DW70 | P255: MX-CED. CENTRO | Q255: 20250722 | R255: 20301231 | S255: 20250722 | T255: 20301231 | U255: 170 | V255: MXN | W255: M3 | X255: 150 | Y255: MXN | Z255: M3 | AA255: ENDB | AB255: FABRICA VESTIMENTA Y EQ (FAVE) E3 / | AC255: 56103695 | AD255: 6644261540 | AE255: 4 | AF255: ENTREGA DIRECTA | AG255: 1.249 | AH255: M3 | AI255: X | AJ255: 4 | AK255: V4 | AL255: 20250729 | AM255: DW70-900007079-ENDB-10000206-4
A256: 900004090DW70D09410220798 | B256: 4600054870-10 | C256: 4600054870 | D256: 10 | E256: MXPO | F256: MXL | G256: 900004090 | H256: TC-ED-ESTRATEGIAS AVANZADAS (CONEJO | I256: 5049458 | J256: ESTRATEGIAS AVANZADAS PARA OBTEN | K256: Z03 | L256: (AP) 15 Dias | M256: 10220798 | N256: BALASTRE ANDESITA | O256: DW70 | P256: MX-CED. CENTRO | Q256: 20220810 | R256: 20271231 | S256: 20220810 | T256: 20271231 | U256: 385 | V256: MXN | W256: M3 | X256: 192.5 | Y256: MXN | Z256: M3 | AA256: D094 | AB256: PD0284 PLANTA DEACERO | AC256: 56103591 | AD256: 6644261540 | AE256: 4 | AF256: ENTREGA DIRECTA | AG256: 1.7 | AH256: M3 | AI256: X | AJ256: 4 | AK256: V4 | AL256: 20230920 | AM256: DW70-900004090-D094-10220798-4
A257: 900007079DW70ENDB10000160 | B257: 4600071478-10 | C257: 4600071478 | D257: 10 | E257: MXPO | F257: MXL | G257: 900007079 | H257: SF TC-ED-TRIVOMEX | I257: 5033501 | J257: TRITURADOS VOLCANICOS DE MEXICO | K257: Z04 | L257: (AP) 30 Dias | M257: 10000160 | N257: Arena Triturada Andesita Malla 4 | O257: DW70 | P257: MX-CED. CENTRO | Q257: 20250722 | R257: 20301231 | S257: 20250722 | T257: 20301231 | U257: 268 | V257: MXN | W257: M3 | X257: 150 | Y257: MXN | Z257: M3 | AA257: ENDB | AB257: FABRICA VESTIMENTA Y EQ (FAVE) E3 / | AC257: 56103638 | AD257: 6644261540 | AE257: 4 | AF257: ENTREGA DIRECTA | AG257: 1.409 | AH257: M3 | AI257: X | AJ257: 4 | AK257: V4 | AL257: 20250729 | AM257: DW70-900007079-ENDB-10000160-4
A258: 900004090DW70D09410220799 | B258: 4600054870-20 | C258: 4600054870 | D258: 20 | E258: MXPO | F258: MXL | G258: 900004090 | H258: TC-ED-ESTRATEGIAS AVANZADAS (CONEJO | I258: 5049458 | J258: ESTRATEGIAS AVANZADAS PARA OBTEN | K258: Z03 | L258: (AP) 15 Dias | M258: 10220799 | N258: SCREEN CALIZA | O258: DW70 | P258: MX-CED. CENTRO | Q258: 20220810 | R258: 20271231 | S258: 20220810 | T258: 20271231 | U258: 210 | V258: MXN | W258: M3 | X258: 105 | Y258: MXN | Z258: M3 | AA258: D094 | AB258: PD0284 PLANTA DEACERO | AC258: 56103695 | AD258: 6644261540 | AE258: 4 | AF258: ENTREGA DIRECTA | AG258: 1.6 | AH258: M3 | AI258: X | AJ258: 4 | AK258: V4 | AL258: 20230920 | AM258: DW70-900004090-D094-10220799-4
A259: 900005730DW70ENAS10216851 | B259: 4600068533-30 | C259: 4600068533 | D259: 30 | E259: MXPO | F259: MXL | G259: 900005730 | H259: TC-ED OLIELL | I259: 5048484 | J259: COMERCIALIZADORA Y TRANSPORTADORA O | K259: N90 | L259: (AP) NAFIN 90 Dias | M259: 10216851 | N259: BASE HIDRAÚLICA - TEPETATE NG | O259: DW70 | P259: MX-CED. CENTRO | Q259: 20230925 | R259: 20281231 | S259: 20241125 | T259: 20291231 | U259: 192 | V259: MXN | W259: M3 | X259: 170 | Y259: MXN | Z259: M3 | AA259: ENAS | AB259: Fabrica de Vestimenta y Eq (FAVE) E | AC259: 56103590 | AD259: 6644261540 | AE259: 4 | AF259: ENTREGA DIRECTA | AG259: 1.249 | AH259: M3 | AI259: X | AJ259: 4 | AK259: V4 | AL259: 20250204 | AM259: DW70-900005730-ENAS-10216851-4
A260: 900000137DW7010000624 | B260: 4600050478-20 | C260: 4600050478 | D260: 20 | E260: MXPO | F260: MXL | G260: 900000137 | H260: TC-LA VALENCIANA | I260: 5005431 | J260: CANTERAS LA VALENCIANA SA DE CV | K260: Z03 | L260: (AP) 15 Dias | M260: 10000624 | N260: Grava Triturada Caliza 40 mm - 1 1/2" | O260: DW70 | P260: MX-CED. CENTRO | Q260: 20210712 | R260: 20281231 | S260: 20260201 | T260: 20301231 | U260: 159.52 | V260: MXN | W260: M3 | X260: 0 | Y260: MXN | Z260: M3 | AC260: 56103637 | AD260: 6644261540 | AE260: 1 | AF260: ENTREGADO | AG260: 1.45 | AH260: M3 | AI260: X | AJ260: 4 | AK260: V4 | AL260: 20260212 | AM260: DW70-900000137-10000624
A261: 900000137DW7010058345 | B261: 4600050478-40 | C261: 4600050478 | D261: 40 | E261: MXPO | F261: MXL | G261: 900000137 | H261: TC-LA VALENCIANA | I261: 5005431 | J261: CANTERAS LA VALENCIANA SA DE CV | K261: Z03 | L261: (AP) 15 Dias | M261: 10058345 | N261: Arena Triturada Caliza Malla 4 | O261: DW70 | P261: MX-CED. CENTRO | Q261: 20210712 | R261: 20281231 | S261: 20260201 | T261: 20301231 | U261: 135 | V261: MXN | W261: M3 | X261: 0 | Y261: MXN | Z261: M3 | AC261: 56103638 | AD261: 6644261540 | AE261: 1 | AF261: ENTREGADO | AG261: 1.575 | AH261: M3 | AI261: X | AJ261: 4 | AK261: V4 | AL261: 20260212 | AM261: DW70-900000137-10058345
A262: 900000137DW7010000811 | B262: 4600050478-10 | C262: 4600050478 | D262: 10 | E262: MXPO | F262: MXL | G262: 900000137 | H262: TC-LA VALENCIANA | I262: 5005431 | J262: CANTERAS LA VALENCIANA SA DE CV | K262: Z03 | L262: (AP) 15 Dias | M262: 10000811 | N262: Grava Triturada Caliza 20 mm - 3/4" | O262: DW70 | P262: MX-CED. CENTRO | Q262: 20210712 | R262: 20281231 | S262: 20260201 | T262: 20301231 | U262: 166.58 | V262: MXN | W262: M3 | X262: 0 | Y262: MXN | Z262: M3 | AC262: 56103637 | AD262: 6644261540 | AE262: 1 | AF262: ENTREGADO | AG262: 1.447 | AH262: M3 | AI262: X | AJ262: 4 | AK262: V4 | AL262: 20260212 | AM262: DW70-900000137-10000811
A263: 900000137DW7010000630 | B263: 4600050478-30 | C263: 4600050478 | D263: 30 | E263: MXPO | F263: MXL | G263: 900000137 | H263: TC-LA VALENCIANA | I263: 5005431 | J263: CANTERAS LA VALENCIANA SA DE CV | K263: Z03 | L263: (AP) 15 Dias | M263: 10000630 | N263: Grava Triturada Caliza 13 mm - 1/2" | O263: DW70 | P263: MX-CED. CENTRO | Q263: 20210712 | R263: 20281231 | S263: 20260201 | T263: 20301231 | U263: 151.74 | V263: MXN | W263: M3 | X263: 0 | Y263: MXN | Z263: M3 | AC263: 56103637 | AD263: 6644261540 | AE263: 1 | AF263: ENTREGADO | AG263: 1.4 | AH263: M3 | AI263: X | AJ263: 4 | AK263: V4 | AL263: 20260212 | AM263: DW70-900000137-10000630
A264: 900000137DW7010147486 | B264: 4600050478-70 | C264: 4600050478 | D264: 70 | E264: MXPO | F264: MXL | G264: 900000137 | H264: TC-LA VALENCIANA | I264: 5005431 | J264: CANTERAS LA VALENCIANA SA DE CV | K264: Z03 | L264: (AP) 15 Dias | M264: 10147486 | N264: BALASTO TRITURADO | O264: DW70 | P264: MX-CED. CENTRO | Q264: 20210712 | R264: 20281231 | S264: 20260201 | T264: 20301231 | U264: 166.57 | V264: MXN | W264: M3 | X264: 0 | Y264: MXN | Z264: M3 | AC264: 56103591 | AD264: 6644261540 | AE264: 1 | AF264: ENTREGADO | AG264: 1.56 | AH264: M3 | AI264: X | AJ264: 4 | AK264: V4 | AL264: 20260212 | AM264: DW70-900000137-10147486
A265: 900005730DW70ENDB10000357 | B265: 4600068533-70 | C265: 4600068533 | D265: 70 | E265: MXPO | F265: MXL | G265: 900005730 | H265: TC-ED OLIELL | I265: 5048484 | J265: COMERCIALIZADORA Y TRANSPORTADORA O | K265: N90 | L265: (AP) NAFIN 90 Dias | M265: 10000357 | N265: Grava Triturada Andesita 20 mm - 3/4" | O265: DW70 | P265: MX-CED. CENTRO | Q265: 20230925 | R265: 20281231 | S265: 20250401 | T265: 20301231 | U265: 687.66 | V265: MXN | W265: M3 | X265: 300 | Y265: MXN | Z265: M3 | AA265: ENDB | AB265: FABRICA VESTIMENTA Y EQ (FAVE) E3 / | AC265: 56103637 | AD265: 6644261540 | AE265: 4 | AF265: ENTREGA DIRECTA | AG265: 1.326 | AH265: M3 | AI265: X | AJ265: 4 | AK265: V4 | AL265: 20250403 | AM265: DW70-900005730-ENDB-10000357-4
A266: 900005730DW70ENAW10000357 | B266: 4600068533-50 | C266: 4600068533 | D266: 50 | E266: MXPO | F266: MXL | G266: 900005730 | H266: TC-ED OLIELL | I266: 5048484 | J266: COMERCIALIZADORA Y TRANSPORTADORA O | K266: N90 | L266: (AP) NAFIN 90 Dias | M266: 10000357 | N266: Grava Triturada Andesita 20 mm - 3/4" | O266: DW70 | P266: MX-CED. CENTRO | Q266: 20230925 | R266: 20281231 | S266: 20250401 | T266: 20301231 | U266: 774 | V266: MXN | W266: M3 | X266: 500 | Y266: MXN | Z266: M3 | AA266: ENAW | AB266: COMPLEJO DEPORTIVO (CENCIS) / SEMAR | AC266: 56103637 | AD266: 6644261540 | AE266: 4 | AF266: ENTREGA DIRECTA | AG266: 1.326 | AH266: M3 | AI266: X | AJ266: 4 | AK266: V4 | AL266: 20250403 | AM266: DW70-900005730-ENAW-10000357-4
A267: 900005730DW70ENDB10000160 | B267: 4600068533-60 | C267: 4600068533 | D267: 60 | E267: MXPO | F267: MXL | G267: 900005730 | H267: TC-ED OLIELL | I267: 5048484 | J267: COMERCIALIZADORA Y TRANSPORTADORA O | K267: N90 | L267: (AP) NAFIN 90 Dias | M267: 10000160 | N267: Arena Triturada Andesita Malla 4 | O267: DW70 | P267: MX-CED. CENTRO | Q267: 20230925 | R267: 20281231 | S267: 20250401 | T267: 20301231 | U267: 665.32 | V267: MXN | W267: M3 | X267: 300 | Y267: MXN | Z267: M3 | AA267: ENDB | AB267: FABRICA VESTIMENTA Y EQ (FAVE) E3 / | AC267: 56103638 | AD267: 6644261540 | AE267: 4 | AF267: ENTREGA DIRECTA | AG267: 1.409 | AH267: M3 | AI267: X | AJ267: 4 | AK267: V4 | AL267: 20250403 | AM267: DW70-900005730-ENDB-10000160-4
A268: 900008265DW70ENXE10216851 | B268: 4600071526-20 | C268: 4600071526 | D268: 20 | E268: MXPO | F268: MXL | G268: 900008265 | H268: SF TC-ED CONCRETOS Y PAVIMENTOS | I268: 5089601 | J268: CONCRETOS Y PAVIMENTOS EXTERIORES S | K268: N90 | L268: (AP) NAFIN 90 Dias | M268: 10216851 | N268: BASE HIDRAÚLICA - TEPETATE NG | O268: DW70 | P268: MX-CED. CENTRO | Q268: 20250807 | R268: 20301231 | S268: 20250807 | T268: 20301231 | U268: 224 | V268: MXN | W268: M3 | X268: 198 | Y268: MXN | Z268: M3 | AA268: ENXE | AB268: PUENTES PERIFERICO ORIENTE/SICT | AC268: 56103590 | AD268: 6644261540 | AE268: 4 | AF268: ENTREGA DIRECTA | AG268: 1.249 | AH268: M3 | AI268: X | AJ268: 4 | AK268: V4 | AL268: 20250813 | AM268: DW70-900008265-ENXE-10216851-4
A269: 900005730DW70ENAW10185476 | B269: 4600068533-40 | C269: 4600068533 | D269: 40 | E269: MXPO | F269: MXL | G269: 900005730 | H269: TC-ED OLIELL | I269: 5048484 | J269: COMERCIALIZADORA Y TRANSPORTADORA O | K269: N90 | L269: (AP) NAFIN 90 Dias | M269: 10185476 | N269: ARENA TRITURADA ANDESITA MALLA 4 | O269: DW70 | P269: MX-CED. CENTRO | Q269: 20230925 | R269: 20281231 | S269: 20250227 | T269: 20301231 | U269: 619.65 | V269: MXN | W269: M3 | X269: 500 | Y269: MXN | Z269: M3 | AA269: ENAW | AB269: COMPLEJO DEPORTIVO (CENCIS) / SEMAR | AC269: 56103638 | AD269: 6644261540 | AE269: 4 | AF269: ENTREGA DIRECTA | AG269: 1.54 | AH269: M3 | AI269: X | AJ269: 4 | AK269: V4 | AL269: 20250304 | AM269: DW70-900005730-ENAW-10185476-4
A270: 900002813DW7010000623 | B270: 4600069509-20 | C270: 4600069509 | D270: 20 | E270: MXPO | F270: MXL | G270: 900002813 | H270: TC-CAL DE APASCO | I270: 5002762 | J270: CAL DE APASCO SA | K270: N90 | L270: (AP) NAFIN 90 Dias | M270: 10000623 | N270: Grava Triturada Caliza 10 mm - 3/8" | O270: DW70 | P270: MX-CED. CENTRO | Q270: 20240513 | R270: 20291231 | S270: 20250621 | T270: 20301231 | U270: 110 | V270: MXN | W270: TN | X270: 0 | Y270: MXN | Z270: TN | AC270: 56103637 | AD270: 6644261540 | AE270: 1 | AF270: ENTREGADO | AG270: 1 | AH270: TO | AI270: X | AJ270: 4 | AK270: V4 | AL270: 20250625 | AM270: DW70-900002813-10000623
A271: 900005974DW7010000357 | B271: 4600072187-20 | C271: 4600072187 | D271: 20 | E271: MXPO | F271: MXL | G271: 900005974 | H271: SF TC-BASALTEX | I271: 5074602 | J271: BASALTEX SA DE CV | K271: Z03 | L271: (AP) 15 Dias | M271: 10000357 | N271: Grava Triturada Andesita 20 mm - 3/4" | O271: DW70 | P271: MX-CED. CENTRO | Q271: 20260413 | R271: 20301231 | S271: 20260413 | T271: 20301231 | U271: 145 | V271: MXN | W271: M3 | X271: 0 | Y271: MXN | Z271: M3 | AC271: 56103637 | AD271: 6644261540 | AE271: 1 | AF271: ENTREGADO | AG271: 1.326 | AH271: M3 | AI271: X | AJ271: 4 | AK271: V4 | AL271: 20260417 | AM271: DW70-900005974-10000357
A272: 900001810DW7010000206 | B272: 4600050493-60 | C272: 4600050493 | D272: 60 | E272: MXPO | F272: MXL | G272: 900001810 | H272: TC-TRIVOMEX | I272: 5033501 | J272: TRITURADOS VOLCANICOS DE MEXICO | K272: Z04 | L272: (AP) 30 Dias | M272: 10000206 | N272: Tepetate Triturado Tierra NA | O272: DW70 | P272: MX-CED. CENTRO | Q272: 20210712 | R272: 20291231 | S272: 20250620 | T272: 20301231 | U272: 20 | V272: MXN | W272: M3 | X272: 0 | Y272: MXN | Z272: M3 | AC272: 56103695 | AD272: 6644261540 | AE272: 1 | AF272: ENTREGADO | AG272: 1.249 | AH272: M3 | AI272: X | AJ272: 4 | AK272: V4 | AL272: 20250625 | AM272: DW70-900001810-10000206
A273: 900001810DW7010175723 | B273: 4600050493-40 | C273: 4600050493 | D273: 40 | E273: MXPO | F273: MXL | G273: 900001810 | H273: TC-TRIVOMEX | I273: 5033501 | J273: TRITURADOS VOLCANICOS DE MEXICO | K273: Z04 | L273: (AP) 30 Dias | M273: 10175723 | N273: BASE HIDRAULICA ANDESITA DE 1 1/2" A FIN | O273: DW70 | P273: MX-CED. CENTRO | Q273: 20210712 | R273: 20291231 | S273: 20250620 | T273: 20301231 | U273: 127 | V273: MXN | W273: M3 | X273: 0 | Y273: MXN | Z273: M3 | AC273: 56103590 | AD273: 6644261540 | AE273: 1 | AF273: ENTREGADO | AG273: 1.65 | AH273: M3 | AI273: X | AJ273: 4 | AK273: V4 | AL273: 20250625 | AM273: DW70-900001810-10175723
A274: 900002813DW7010000133 | B274: 4600069509-30 | C274: 4600069509 | D274: 30 | E274: MXPO | F274: MXL | G274: 900002813 | H274: TC-CAL DE APASCO | I274: 5002762 | J274: CAL DE APASCO SA | K274: N90 | L274: (AP) NAFIN 90 Dias | M274: 10000133 | N274: Grava Triturada Caliza 20 mm - 3/4" | O274: DW70 | P274: MX-CED. CENTRO | Q274: 20240513 | R274: 20291231 | S274: 20250621 | T274: 20301231 | U274: 100 | V274: MXN | W274: TN | X274: 0 | Y274: MXN | Z274: TN | AC274: 56103637 | AD274: 6644261540 | AE274: 1 | AF274: ENTREGADO | AG274: 1 | AH274: TO | AI274: X | AJ274: 4 | AK274: V4 | AL274: 20250625 | AM274: DW70-900002813-10000133
A275: 900002813DW7010257024 | B275: 4600069509-10 | C275: 4600069509 | D275: 10 | E275: MXPO | F275: MXL | G275: 900002813 | H275: TC-CAL DE APASCO | I275: 5002762 | J275: CAL DE APASCO SA | K275: N90 | L275: (AP) NAFIN 90 Dias | M275: 10257024 | N275: ARENA TRITURADA CALIZA 4 | O275: DW70 | P275: MX-CED. CENTRO | Q275: 20240513 | R275: 20291231 | S275: 20250621 | T275: 20301231 | U275: 115 | V275: MXN | W275: TN | X275: 0 | Y275: MXN | Z275: TN | AC275: 56103638 | AD275: 6644261540 | AE275: 1 | AF275: ENTREGADO | AG275: 1 | AH275: TO | AI275: X | AJ275: 4 | AK275: V4 | AL275: 20250625 | AM275: DW70-900002813-10257024
A276: 900005974DW7010000160 | B276: 4600072187-10 | C276: 4600072187 | D276: 10 | E276: MXPO | F276: MXL | G276: 900005974 | H276: SF TC-BASALTEX | I276: 5074602 | J276: BASALTEX SA DE CV | K276: Z03 | L276: (AP) 15 Dias | M276: 10000160 | N276: Arena Triturada Andesita Malla 4 | O276: DW70 | P276: MX-CED. CENTRO | Q276: 20260413 | R276: 20301231 | S276: 20260413 | T276: 20301231 | U276: 150 | V276: MXN | W276: M3 | X276: 0 | Y276: MXN | Z276: M3 | AC276: 56103638 | AD276: 6644261540 | AE276: 1 | AF276: ENTREGADO | AG276: 1.409 | AH276: M3 | AI276: X | AJ276: 4 | AK276: V4 | AL276: 20260417 | AM276: DW70-900005974-10000160
A277: 900008265DW70ENXE10215074 | B277: 4600071526-10 | C277: 4600071526 | D277: 10 | E277: MXPO | F277: MXL | G277: 900008265 | H277: SF TC-ED CONCRETOS Y PAVIMENTOS | I277: 5089601 | J277: CONCRETOS Y PAVIMENTOS EXTERIORES S | K277: N90 | L277: (AP) NAFIN 90 Dias | M277: 10215074 | N277: TEZONTLE 3" | O277: DW70 | P277: MX-CED. CENTRO | Q277: 20250807 | R277: 20301231 | S277: 20250807 | T277: 20301231 | U277: 435.5 | V277: MXN | W277: M3 | X277: 320 | Y277: MXN | Z277: M3 | AA277: ENXE | AB277: PUENTES PERIFERICO ORIENTE/SICT | AC277: 56103637 | AD277: 6644261540 | AE277: 4 | AF277: ENTREGA DIRECTA | AG277: 1.3 | AH277: M3 | AI277: X | AJ277: 4 | AK277: V4 | AL277: 20250813 | AM277: DW70-900008265-ENXE-10215074-4
...
