Workbook

Sheet Base Cedis D845
N1: VENTA | Q1: COSTO
A2: CONCAT1 | B2: CONCAT2 | C2: No. SF | D2: Nombre SF | E2: Cedis | F2: Destino | G2: Condicion de Expedicion | H2: Nombre Destino | I2: No. de material | J2: Nombre de material | K2: PV | L2: Inicio de vigencia | M2: Fin de vigencia | N2: Importe MP | O2: Importe Flete | P2: UM Venta | Q2: Importe Costo | R2: UM Costo | S2: Validacion 1 | T2: Validacion 2
A3: =CONCATENATE(C3,E3,F3,I3) | B3: =CONCATENATE(C3,E3,I3) | C3: 900003571 | D3: =IFERROR(VLOOKUP(C3,TRAOPE!$G:$H,2,0),"") | E3: D845 | F3: 66389450 | G3: =IFERROR(VLOOKUP(A3,Flete!$A:$E,5,0),"") | H3: =IFERROR(VLOOKUP(F3,TRAOPE!$AA:$AB,2,0),"") | I3: 10000578 | J3: =IFERROR(VLOOKUP(I3,Materiales!$A:$H,8,0),"") | K3: =IFERROR(VLOOKUP(I3,Materiales!$A:$G,7,0),"") | L3: 20190601 | M3: 20230219 | N3: 75 | O3: =IFERROR(VLOOKUP(A3,Flete!$A:$J,10,0),"") | P3: TN | Q3: =IFERROR(IFERROR(VLOOKUP(A3,TRAOPE!$A:$U,21,0),VLOOKUP(B3,TRAOPE!$A:$U,21,0)),"") | R3: =IFERROR(IFERROR(VLOOKUP(A3,TRAOPE!$A:$W,23,0),VLOOKUP(B3,TRAOPE!$A:$W,23,0)),"") | S3: =IF(AND(P3="TN",R3="TN"),N3+N(O3),IF(G3&""="1",N(K3)*N3,(N3+N(O3))*N(K3))) | T3: =IF(Q3="","",Q3-S3)
A4: =CONCATENATE(C4,E4,F4,I4) | B4: =CONCATENATE(C4,E4,I4) | C4: 900003571 | D4: =IFERROR(VLOOKUP(C4,TRAOPE!$G:$H,2,0),"") | E4: D845 | F4: 66779741 | G4: =IFERROR(VLOOKUP(A4,Flete!$A:$E,5,0),"") | H4: =IFERROR(VLOOKUP(F4,TRAOPE!$AA:$AB,2,0),"") | I4: 10026100 | J4: =IFERROR(VLOOKUP(I4,Materiales!$A:$H,8,0),"") | K4: =IFERROR(VLOOKUP(I4,Materiales!$A:$G,7,0),"") | L4: 20190524 | M4: 20230219 | N4: 66 | O4: =IFERROR(VLOOKUP(A4,Flete!$A:$J,10,0),"") | P4: TN | Q4: =IFERROR(IFERROR(VLOOKUP(A4,TRAOPE!$A:$U,21,0),VLOOKUP(B4,TRAOPE!$A:$U,21,0)),"") | R4: =IFERROR(IFERROR(VLOOKUP(A4,TRAOPE!$A:$W,23,0),VLOOKUP(B4,TRAOPE!$A:$W,23,0)),"") | S4: =IF(AND(P4="TN",R4="TN"),N4+N(O4),IF(G4&""="1",N(K4)*N4,(N4+N(O4))*N(K4))) | T4: =IF(Q4="","",Q4-S4)
A5: =CONCATENATE(C5,E5,F5,I5) | B5: =CONCATENATE(C5,E5,I5) | C5: 900003571 | D5: =IFERROR(VLOOKUP(C5,TRAOPE!$G:$H,2,0),"") | E5: D845 | F5: 66827900 | G5: =IFERROR(VLOOKUP(A5,Flete!$A:$E,5,0),"") | H5: =IFERROR(VLOOKUP(F5,TRAOPE!$AA:$AB,2,0),"") | I5: 10000578 | J5: =IFERROR(VLOOKUP(I5,Materiales!$A:$H,8,0),"") | K5: =IFERROR(VLOOKUP(I5,Materiales!$A:$G,7,0),"") | L5: 20190601 | M5: 20230219 | N5: 82 | O5: =IFERROR(VLOOKUP(A5,Flete!$A:$J,10,0),"") | P5: TN | Q5: =IFERROR(IFERROR(VLOOKUP(A5,TRAOPE!$A:$U,21,0),VLOOKUP(B5,TRAOPE!$A:$U,21,0)),"") | R5: =IFERROR(IFERROR(VLOOKUP(A5,TRAOPE!$A:$W,23,0),VLOOKUP(B5,TRAOPE!$A:$W,23,0)),"") | S5: =IF(AND(P5="TN",R5="TN"),N5+N(O5),IF(G5&""="1",N(K5)*N5,(N5+N(O5))*N(K5))) | T5: =IF(Q5="","",Q5-S5)
A6: =CONCATENATE(C6,E6,F6,I6) | B6: =CONCATENATE(C6,E6,I6) | C6: 900005260 | D6: =IFERROR(VLOOKUP(C6,TRAOPE!$G:$H,2,0),"") | E6: D845 | F6: 66256509 | G6: =IFERROR(VLOOKUP(A6,Flete!$A:$E,5,0),"") | H6: =IFERROR(VLOOKUP(F6,TRAOPE!$AA:$AB,2,0),"") | I6: 10000536 | J6: =IFERROR(VLOOKUP(I6,Materiales!$A:$H,8,0),"") | K6: =IFERROR(VLOOKUP(I6,Materiales!$A:$G,7,0),"") | L6: 20200918 | M6: 20230219 | N6: 78.75 | O6: =IFERROR(VLOOKUP(A6,Flete!$A:$J,10,0),"") | P6: TN | Q6: =IFERROR(IFERROR(VLOOKUP(A6,TRAOPE!$A:$U,21,0),VLOOKUP(B6,TRAOPE!$A:$U,21,0)),"") | R6: =IFERROR(IFERROR(VLOOKUP(A6,TRAOPE!$A:$W,23,0),VLOOKUP(B6,TRAOPE!$A:$W,23,0)),"") | S6: =IF(AND(P6="TN",R6="TN"),N6+N(O6),IF(G6&""="1",N(K6)*N6,(N6+N(O6))*N(K6))) | T6: =IF(Q6="","",Q6-S6)
A7: =CONCATENATE(C7,E7,F7,I7) | B7: =CONCATENATE(C7,E7,I7) | C7: 900005260 | D7: =IFERROR(VLOOKUP(C7,TRAOPE!$G:$H,2,0),"") | E7: D845 | F7: 66256509 | G7: =IFERROR(VLOOKUP(A7,Flete!$A:$E,5,0),"") | H7: =IFERROR(VLOOKUP(F7,TRAOPE!$AA:$AB,2,0),"") | I7: 10000578 | J7: =IFERROR(VLOOKUP(I7,Materiales!$A:$H,8,0),"") | K7: =IFERROR(VLOOKUP(I7,Materiales!$A:$G,7,0),"") | L7: 20200918 | M7: 20230219 | N7: 81.8 | O7: =IFERROR(VLOOKUP(A7,Flete!$A:$J,10,0),"") | P7: TN | Q7: =IFERROR(IFERROR(VLOOKUP(A7,TRAOPE!$A:$U,21,0),VLOOKUP(B7,TRAOPE!$A:$U,21,0)),"") | R7: =IFERROR(IFERROR(VLOOKUP(A7,TRAOPE!$A:$W,23,0),VLOOKUP(B7,TRAOPE!$A:$W,23,0)),"") | S7: =IF(AND(P7="TN",R7="TN"),N7+N(O7),IF(G7&""="1",N(K7)*N7,(N7+N(O7))*N(K7))) | T7: =IF(Q7="","",Q7-S7)
A8: =CONCATENATE(C8,E8,F8,I8) | B8: =CONCATENATE(C8,E8,I8) | C8: 900005260 | D8: =IFERROR(VLOOKUP(C8,TRAOPE!$G:$H,2,0),"") | E8: D845 | F8: 66256509 | G8: =IFERROR(VLOOKUP(A8,Flete!$A:$E,5,0),"") | H8: =IFERROR(VLOOKUP(F8,TRAOPE!$AA:$AB,2,0),"") | I8: 10000617 | J8: =IFERROR(VLOOKUP(I8,Materiales!$A:$H,8,0),"") | K8: =IFERROR(VLOOKUP(I8,Materiales!$A:$G,7,0),"") | L8: 20200918 | M8: 20230219 | N8: 95.55 | O8: =IFERROR(VLOOKUP(A8,Flete!$A:$J,10,0),"") | P8: TN | Q8: =IFERROR(IFERROR(VLOOKUP(A8,TRAOPE!$A:$U,21,0),VLOOKUP(B8,TRAOPE!$A:$U,21,0)),"") | R8: =IFERROR(IFERROR(VLOOKUP(A8,TRAOPE!$A:$W,23,0),VLOOKUP(B8,TRAOPE!$A:$W,23,0)),"") | S8: =IF(AND(P8="TN",R8="TN"),N8+N(O8),IF(G8&""="1",N(K8)*N8,(N8+N(O8))*N(K8))) | T8: =IF(Q8="","",Q8-S8)
A9: =CONCATENATE(C9,E9,F9,I9) | B9: =CONCATENATE(C9,E9,I9) | C9: 900005260 | D9: =IFERROR(VLOOKUP(C9,TRAOPE!$G:$H,2,0),"") | E9: D845 | F9: 66256509 | G9: =IFERROR(VLOOKUP(A9,Flete!$A:$E,5,0),"") | H9: =IFERROR(VLOOKUP(F9,TRAOPE!$AA:$AB,2,0),"") | I9: 10000656 | J9: =IFERROR(VLOOKUP(I9,Materiales!$A:$H,8,0),"") | K9: =IFERROR(VLOOKUP(I9,Materiales!$A:$G,7,0),"") | L9: 20200918 | M9: 20230219 | N9: 75 | O9: =IFERROR(VLOOKUP(A9,Flete!$A:$J,10,0),"") | P9: TN | Q9: =IFERROR(IFERROR(VLOOKUP(A9,TRAOPE!$A:$U,21,0),VLOOKUP(B9,TRAOPE!$A:$U,21,0)),"") | R9: =IFERROR(IFERROR(VLOOKUP(A9,TRAOPE!$A:$W,23,0),VLOOKUP(B9,TRAOPE!$A:$W,23,0)),"") | S9: =IF(AND(P9="TN",R9="TN"),N9+N(O9),IF(G9&""="1",N(K9)*N9,(N9+N(O9))*N(K9))) | T9: =IF(Q9="","",Q9-S9)
A10: =CONCATENATE(C10,E10,F10,I10) | B10: =CONCATENATE(C10,E10,I10) | C10: 900005260 | D10: =IFERROR(VLOOKUP(C10,TRAOPE!$G:$H,2,0),"") | E10: D845 | F10: 66389450 | G10: =IFERROR(VLOOKUP(A10,Flete!$A:$E,5,0),"") | H10: =IFERROR(VLOOKUP(F10,TRAOPE!$AA:$AB,2,0),"") | I10: 10000536 | J10: =IFERROR(VLOOKUP(I10,Materiales!$A:$H,8,0),"") | K10: =IFERROR(VLOOKUP(I10,Materiales!$A:$G,7,0),"") | L10: 20200817 | M10: 20230219 | N10: 78.75 | O10: =IFERROR(VLOOKUP(A10,Flete!$A:$J,10,0),"") | P10: TN | Q10: =IFERROR(IFERROR(VLOOKUP(A10,TRAOPE!$A:$U,21,0),VLOOKUP(B10,TRAOPE!$A:$U,21,0)),"") | R10: =IFERROR(IFERROR(VLOOKUP(A10,TRAOPE!$A:$W,23,0),VLOOKUP(B10,TRAOPE!$A:$W,23,0)),"") | S10: =IF(AND(P10="TN",R10="TN"),N10+N(O10),IF(G10&""="1",N(K10)*N10,(N10+N(O10))*N(K10))) | T10: =IF(Q10="","",Q10-S10)
A11: =CONCATENATE(C11,E11,F11,I11) | B11: =CONCATENATE(C11,E11,I11) | C11: 900005260 | D11: =IFERROR(VLOOKUP(C11,TRAOPE!$G:$H,2,0),"") | E11: D845 | F11: 66389450 | G11: =IFERROR(VLOOKUP(A11,Flete!$A:$E,5,0),"") | H11: =IFERROR(VLOOKUP(F11,TRAOPE!$AA:$AB,2,0),"") | I11: 10000578 | J11: =IFERROR(VLOOKUP(I11,Materiales!$A:$H,8,0),"") | K11: =IFERROR(VLOOKUP(I11,Materiales!$A:$G,7,0),"") | L11: 20200817 | M11: 20230219 | N11: 81.8 | O11: =IFERROR(VLOOKUP(A11,Flete!$A:$J,10,0),"") | P11: TN | Q11: =IFERROR(IFERROR(VLOOKUP(A11,TRAOPE!$A:$U,21,0),VLOOKUP(B11,TRAOPE!$A:$U,21,0)),"") | R11: =IFERROR(IFERROR(VLOOKUP(A11,TRAOPE!$A:$W,23,0),VLOOKUP(B11,TRAOPE!$A:$W,23,0)),"") | S11: =IF(AND(P11="TN",R11="TN"),N11+N(O11),IF(G11&""="1",N(K11)*N11,(N11+N(O11))*N(K11))) | T11: =IF(Q11="","",Q11-S11)
A12: =CONCATENATE(C12,E12,F12,I12) | B12: =CONCATENATE(C12,E12,I12) | C12: 900005260 | D12: =IFERROR(VLOOKUP(C12,TRAOPE!$G:$H,2,0),"") | E12: D845 | F12: 66389450 | G12: =IFERROR(VLOOKUP(A12,Flete!$A:$E,5,0),"") | H12: =IFERROR(VLOOKUP(F12,TRAOPE!$AA:$AB,2,0),"") | I12: 10000617 | J12: =IFERROR(VLOOKUP(I12,Materiales!$A:$H,8,0),"") | K12: =IFERROR(VLOOKUP(I12,Materiales!$A:$G,7,0),"") | L12: 20200817 | M12: 20230219 | N12: 95.55 | O12: =IFERROR(VLOOKUP(A12,Flete!$A:$J,10,0),"") | P12: TN | Q12: =IFERROR(IFERROR(VLOOKUP(A12,TRAOPE!$A:$U,21,0),VLOOKUP(B12,TRAOPE!$A:$U,21,0)),"") | R12: =IFERROR(IFERROR(VLOOKUP(A12,TRAOPE!$A:$W,23,0),VLOOKUP(B12,TRAOPE!$A:$W,23,0)),"") | S12: =IF(AND(P12="TN",R12="TN"),N12+N(O12),IF(G12&""="1",N(K12)*N12,(N12+N(O12))*N(K12))) | T12: =IF(Q12="","",Q12-S12)
A13: =CONCATENATE(C13,E13,F13,I13) | B13: =CONCATENATE(C13,E13,I13) | C13: 900005260 | D13: =IFERROR(VLOOKUP(C13,TRAOPE!$G:$H,2,0),"") | E13: D845 | F13: 66389450 | G13: =IFERROR(VLOOKUP(A13,Flete!$A:$E,5,0),"") | H13: =IFERROR(VLOOKUP(F13,TRAOPE!$AA:$AB,2,0),"") | I13: 10000656 | J13: =IFERROR(VLOOKUP(I13,Materiales!$A:$H,8,0),"") | K13: =IFERROR(VLOOKUP(I13,Materiales!$A:$G,7,0),"") | L13: 20200817 | M13: 20230219 | N13: 75 | O13: =IFERROR(VLOOKUP(A13,Flete!$A:$J,10,0),"") | P13: TN | Q13: =IFERROR(IFERROR(VLOOKUP(A13,TRAOPE!$A:$U,21,0),VLOOKUP(B13,TRAOPE!$A:$U,21,0)),"") | R13: =IFERROR(IFERROR(VLOOKUP(A13,TRAOPE!$A:$W,23,0),VLOOKUP(B13,TRAOPE!$A:$W,23,0)),"") | S13: =IF(AND(P13="TN",R13="TN"),N13+N(O13),IF(G13&""="1",N(K13)*N13,(N13+N(O13))*N(K13))) | T13: =IF(Q13="","",Q13-S13)
A14: =CONCATENATE(C14,E14,F14,I14) | B14: =CONCATENATE(C14,E14,I14) | C14: 900005260 | D14: =IFERROR(VLOOKUP(C14,TRAOPE!$G:$H,2,0),"") | E14: D845 | F14: 66704967 | G14: =IFERROR(VLOOKUP(A14,Flete!$A:$E,5,0),"") | H14: =IFERROR(VLOOKUP(F14,TRAOPE!$AA:$AB,2,0),"") | I14: 10000536 | J14: =IFERROR(VLOOKUP(I14,Materiales!$A:$H,8,0),"") | K14: =IFERROR(VLOOKUP(I14,Materiales!$A:$G,7,0),"") | L14: 20190808 | M14: 20230219 | N14: 80 | O14: =IFERROR(VLOOKUP(A14,Flete!$A:$J,10,0),"") | P14: TN | Q14: =IFERROR(IFERROR(VLOOKUP(A14,TRAOPE!$A:$U,21,0),VLOOKUP(B14,TRAOPE!$A:$U,21,0)),"") | R14: =IFERROR(IFERROR(VLOOKUP(A14,TRAOPE!$A:$W,23,0),VLOOKUP(B14,TRAOPE!$A:$W,23,0)),"") | S14: =IF(AND(P14="TN",R14="TN"),N14+N(O14),IF(G14&""="1",N(K14)*N14,(N14+N(O14))*N(K14))) | T14: =IF(Q14="","",Q14-S14)
... A336: =CONCATENATE(C336,E336,F336,I336) | B336: =CONCATENATE(C336,E336,I336) | C336: 900009255 | D336: =IFERROR(VLOOKUP(C336,TRAOPE!$G:$H,2,0),"") | E336: D845 | F336: 67318246 | G336: =IFERROR(VLOOKUP(A336,Flete!$A:$E,5,0),"") | H336: =IFERROR(VLOOKUP(F336,TRAOPE!$AA:$AB,2,0),"") | I336: 10169508 | J336: =IFERROR(VLOOKUP(I336,Materiales!$A:$H,8,0),"") | K336: =IFERROR(VLOOKUP(I336,Materiales!$A:$G,7,0),"") | L336: 20250528 | M336: 20250710 | N336: 194 | O336: =IFERROR(VLOOKUP(A336,Flete!$A:$J,10,0),"") | P336: TN | Q336: =IFERROR(IFERROR(VLOOKUP(A336,TRAOPE!$A:$U,21,0),VLOOKUP(B336,TRAOPE!$A:$U,21,0)),"") | R336: =IFERROR(IFERROR(VLOOKUP(A336,TRAOPE!$A:$W,23,0),VLOOKUP(B336,TRAOPE!$A:$W,23,0)),"") | S336: =IF(AND(P336="TN",R336="TN"),N336+N(O336),IF(G336&""="1",N(K336)*N336,(N336+N(O336))*N(K336))) | T336: =IF(Q336="","",Q336-S336)

Sheet MP
A1: No. SF | B1: Cedis | C1: Destino | D1: No. Material | E1: Nombre Material | F1: Importe MP | G1: Moneda | H1: Cantidad | I1: UM | J1: C | K1: Inicio Vigencia | L1: Fin Vigencia
A2: 900003571 | B2: D845 | C2: 66389450 | D2: 10000578 | F2: 75 | I2: TN | K2: 20190601 | L2: 20230219
A3: 900003571 | B3: D845 | C3: 66779741 | D3: 10026100 | F3: 66 | I3: TN | K3: 20190524 | L3: 20230219
A4: 900003571 | B4: D845 | C4: 66827900 | D4: 10000578 | F4: 82 | I4: TN | K4: 20190601 | L4: 20230219
A5: 900005260 | B5: D845 | C5: 66256509 | D5: 10000536 | F5: 78.75 | I5: TN | K5: 20200918 | L5: 20230219
A6: 900005260 | B6: D845 | C6: 66256509 | D6: 10000578 | F6: 81.8 | I6: TN | K6: 20200918 | L6: 20230219
A7: 900005260 | B7: D845 | C7: 66256509 | D7: 10000617 | F7: 95.55 | I7: TN | K7: 20200918 | L7: 20230219
A8: 900005260 | B8: D845 | C8: 66256509 | D8: 10000656 | F8: 75 | I8: TN | K8: 20200918 | L8: 20230219
A9: 900005260 | B9: D845 | C9: 66389450 | D9: 10000536 | F9: 78.75 | I9: TN | K9: 20200817 | L9: 20230219
A10: 900005260 | B10: D845 | C10: 66389450 | D10: 10000578 | F10: 81.8 | I10: TN | K10: 20200817 | L10: 20230219
A11: 900005260 | B11: D845 | C11: 66389450 | D11: 10000617 | F11: 95.55 | I11: TN | K11: 20200817 | L11: 20230219
A12: 900005260 | B12: D845 | C12: 66389450 | D12: 10000656 | F12: 75 | I12: TN | K12: 20200817 | L12: 20230219
A13: 900005260 | B13: D845 | C13: 66704967 | D13: 10000536 | F13: 80 | I13: TN | K13: 20190808 | L13: 20230219
... A335: 900009255 | B335: D845 | C335: 67318246 | D335: 10169508 | F335: 194 | I335: TN | K335: 20250528 | L335: 20250710

Sheet Flete
A1: Concat1 | B1: No. SF | C1: Cedis | D1: Destino | E1: Cond. Exp. | F1: Material | H1: Nombre Material | J1: Importe Flete | K1: Moneda | L1: Cantidad | M1: UM | N1: C | P1: Inicio Vigencia | Q1: Fin Vigencia
A2: 900006074D8456500513910000536 | B2: 900006074 | C2: D845 | D2: 65005139 | E2: 4 | F2: 10000536 | J2: 72 | M2: TN | P2: 20260212 | Q2: 99991231
A3: 900006074D8456500513910000578 | B3: 900006074 | C3: D845 | D3: 65005139 | E3: 4 | F3: 10000578 | J3: 72 | M3: TN | P3: 20260212 | Q3: 99991231
A4: 900006074D8456500513910000617 | B4: 900006074 | C4: D845 | D4: 65005139 | E4: 4 | F4: 10000617 | J4: 72 | M4: TN | P4: 20260212 | Q4: 99991231
A5: 900006074D8456500513910000656 | B5: 900006074 | C5: D845 | D5: 65005139 | E5: 4 | F5: 10000656 | J5: 72 | M5: TN | P5: 20260212 | Q5: 99991231
A6: 900006074D8456500513910058501 | B6: 900006074 | C6: D845 | D6: 65005139 | E6: 4 | F6: 10058501 | J6: 65 | M6: TN | P6: 20191211 | Q6: 20251031
A7: 900006074D8456500513910167749 | B7: 900006074 | C7: D845 | D7: 65005139 | E7: 4 | F7: 10167749 | J7: 72 | M7: TN | P7: 20260212 | Q7: 99991231
A8: 900006074D8456500513910169508 | B8: 900006074 | C8: D845 | D8: 65005139 | E8: 4 | F8: 10169508 | J8: 72 | M8: TN | P8: 20260212 | Q8: 99991231
A9: 900006074D8456500698910000536 | B9: 900006074 | C9: D845 | D9: 65006989 | E9: 4 | F9: 10000536 | J9: 323 | M9: TN | P9: 20251230 | Q9: 99991231
A10: 900006074D8456500698910000578 | B10: 900006074 | C10: D845 | D10: 65006989 | E10: 4 | F10: 10000578 | J10: 323 | M10: TN | P10: 20251230 | Q10: 99991231
A11: 900006074D8456500698910000617 | B11: 900006074 | C11: D845 | D11: 65006989 | E11: 4 | F11: 10000617 | J11: 323 | M11: TN | P11: 20251230 | Q11: 99991231
A12: 900006074D8456500698910000656 | B12: 900006074 | C12: D845 | D12: 65006989 | E12: 4 | F12: 10000656 | J12: 323 | M12: TN | P12: 20251230 | Q12: 99991231
A13: 900006074D8456565836210000536 | B13: 900006074 | C13: D845 | D13: 65658362 | E13: 4 | F13: 10000536 | J13: 38 | M13: TN | P13: 20191211 | Q13: 20251031
... A127: 900008838D8456724110210167749 | B127: 900008838 | C127: D845 | D127: 67241102 | E127: 4 | F127: 10167749 | J127: 150 | M127: TN | P127: 20240706 | Q127: 20240814

Sheet Materiales
A1: Material | B1: TpMt | C1: Denom | D1: UMA | E1: Contador | F1: UMB | G1: PV | H1: Nombre Material
A2: 10000001 | B2: ZFER | C2: 1000 | D2: M3 | E2: 1000 | F2: TN | G2: 1262 | H2: GRAVA ANDESITA 10 MM (3/8")
A3: 10000003 | B3: ZFER | C3: 1000 | D3: M3 | E3: 1000 | F3: TN | G3: 1443 | H3: GRAVA CALIZA 10 MM (3/8")
A4: 10000006 | B4: ZFER | C4: 1000 | D4: M3 | E4: 1000 | F4: TN | G4: 1490 | H4: GRAVA RIO 10 MM (3/8")
A5: 10000007 | B5: ZFER | C5: 1000 | D5: M3 | E5: 1000 | F5: TN | G5: 1488 | H5: GRAVA BASALTO 13 MM (1/2")
A6: 10000008 | B6: ZFER | C6: 1000 | D6: M3 | E6: 1000 | F6: TN | G6: 1358 | H6: GRAVA CALIZA 13 MM (1/2")
A7: 10000011 | B7: ZFER | C7: 1000 | D7: M3 | E7: 1000 | F7: TN | G7: 1323 | H7: GRAVA ANDESITA 20 MM (3/4")
A8: 10000013 | B8: ZFER | C8: 1000 | D8: M3 | E8: 1000 | F8: TN | G8: 1514 | H8: GRAVA BASALTO 20 MM (3/4")
A9: 10000014 | B9: ZFER | C9: 1000 | D9: M3 | E9: 1000 | F9: TN | G9: 1400 | H9: GRAVA CALIZA 20 MM (3/4")
A10: 10000015 | B10: ZFER | C10: 1000 | D10: M3 | E10: 1000 | F10: TN | G10: 1410 | H10: GRAVA GRANITO 20 MM (3/4")
A11: 10000017 | B11: ZFER | C11: 1000 | D11: M3 | E11: 1000 | F11: TN | G11: 1475 | H11: GRAVA RIOLITA 20 MM (3/4")
A12: 10000019 | B12: ZFER | C12: 1000 | D12: M3 | E12: 1000 | F12: TN | G12: 1515 | H12: GRAVA RIO 20 MM (3/4")
A13: 10000020 | B13: ZFER | C13: 1000 | D13: M3 | E13: 1 | F13: TN | G13: 1 | H13: GRAVA MAQUILA 40MM (1 1/2")
... A2291: 10268770 | B2291: ZFE3 | C2291: 1000 | D2291: M3 | E2291: 1000 | F2291: TN | G2291: 1240 | H2291: MP GRAVA TRIT CALIZA 40MM 1 1/2" - ESP
A2292: 10268901 | B2292: ZFE3 | C2292: 1000 | D2292: M3 | E2292: 1000 | G2292: 1560 | H2292: MP GRAVA ANDESITA GRIS 3/4" - CAPADA
A2293: 10267983 | C2293: 1000 | G2293: 1800 | H2293: ESCORIA ALTO HORNO 3/4
A2294: 10268996 | C2294: 1000 | G2294: 1329 | H2294: GRAVA TRITURADA CALIZA 40 MM - 11/2"
A2295: 10269072 | C2295: 1000 | G2295: 1700 | H2295: BASE HIDRÁULICA SCREEN
A2296: 10269225 | B2296: ZFE3 | C2296: 1000 | D2296: M3 | E2296: 1000 | G2296: 1289 | H2296: MP ARENA CALIZA LAVADA MALLA 4 - DELTA I
A2297: 10269245 | B2297: ZFE3 | C2297: 1000 | D2297: M3 | E2297: 1000 | G2297: 1410 | H2297: MP GRAVA TRITURADA CALIZA 3/8 - 10MM
A2298: 10269246 | B2298: ZFE3 | C2298: 1000 | D2298: M3 | E2298: 1000 | G2298: 1400 | H2298: MP GRAVA TRITURADA CALIZA 1 1/2 - 40MM
A2299: 10269247 | B2299: ZFE3 | C2299: 1000 | D2299: M3 | E2299: 1000 | G2299: 1560 | H2299: MP ARENA TRIT CALIZA M-4
A2300: 10270431 | B2300: ZFE3 | C2300: 1000 | D2300: M3 | E2300: 1000 | G2300: 1423 | H2300: MP GRAVA RIOLITA 13 MM - 1/2"
A2301: 10270898 | B2301: ZFE3 | C2301: 1000 | D2301: M3 | E2301: 1000 | G2301: 1551 | H2301: MP BASE H. TRIT. BASALTO 1 1/2" A FINOS
A2302: 10270911 | B2302: ZFE3 | C2302: 1000 | D2302: M3 | E2302: 1000 | G2302: 1360 | H2302: MP GRAVA TRIT. BASALTO 40 MM - 1 1/2"
A2303: 10270912 | B2303: ZFE3 | C2303: 1000 | D2303: M3 | E2303: 1000 | G2303: 1589 | H2303: MP ARENA TRIT. BASALTO MALLA 4
A2304: 10270913 | B2304: ZFE3 | C2304: 1000 | D2304: M3 | E2304: 1000 | G2304: 1395 | H2304: MP GRAVA TRIT. BASALTO 20 MM - 3/4
A2305: 10270914 | B2305: ZFE3 | C2305: 1000 | D2305: M3 | E2305: 1000 | G2305: 1623 | H2305: MP ARENA ANDESITA BC
A2306: 10270824 | B2306: M3 | C2306: 1000 | D2306: M3 | E2306: 10007640 | G2306: 1325 | H2306: MP ARENA TRITURADA CALIZA MALLA 5
A2307: 10270825 | B2307: M3 | C2307: 1000 | D2307: M3 | E2307: 10000003 | G2307: 1242 | H2307: MP GRAVA TRITURADA CALIZA 10MM (3/8”)
... A2319: 10272527 | B2319: ZFE3 | C2319: 1000 | D2319: M3 | E2319: 1000 | G2319: 1620 | H2319: CNC - NO CLASIFICADO
A2320: 10000332 | C2320: 1000 | D2320: M3 | E2320: 1000 | G2320: 800 | H2320: Grava Triturada Pomez - Jal 20 mm - 3/4"
A2321: 10273001 | B2321: ZFE3 | C2321: 1000 | D2321: M3 | E2321: 1000 | G2321: 1688 | H2321: MP ARENA TRIT. BASALTO MALLA 4
A2322: 10273002 | B2322: ZFE3 | C2322: 1000 | D2322: M3 | E2322: 1000 | G2322: 1466 | H2322: MP GRAVA TRIT. BASALTO 20 MM - 3/4"
A2323: 10273351 | B2323: ZFE3 | C2323: 1000 | D2323: M3 | E2323: 1000 | G2323: 1612 | H2323: MP ARENA TRIT. CALIZA MALLA 4
A2324: 10273352 | B2324: ZFE3 | C2324: 1000 | D2324: M3 | E2324: 1000 | G2324: 1492 | H2324: MP GRAVA TRIT. CALIZA 20 MM - 3/4"
A2325: 10271724 | B2325: ZFE3 | C2325: 1000 | D2325: M3 | E2325: 1000 | G2325: 1900 | H2325: MP RESIDUO DE CONCRETO
A2326: 10000677 | C2326: 1000 | D2326: M3 | G2326: 1164 | H2326: Grava Triturada Caliza 20 mm - 3/4"
A2327: 10274190 | B2327: ZFE3 | C2327: 1000 | D2327: M3 | E2327: 1000 | G2327: 1800 | H2327: MP BASE HIDRAULICA ANDESITA 70-30
A2328: 10274601 | B2328: ZFE3 | C2328: 1000 | D2328: M3 | E2328: 1000 | G2328: 1447 | H2328: MP ARENA BASALTO N° 4
A2329: 10274754 | B2329: ZFE3 | C2329: 1000 | D2329: M3 | E2329: 1000 | G2329: 1397 | H2329: MP GRAVA TRIT. ANDESITA 20 MM - 3/4"
A2330: 10169718 | B2330: ZFE3 | C2330: 1000 | D2330: M3 | E2330: 1000 | G2330: 1400 | H2330: GRAVA CLASIFICADA RÍO 40 MM - 1 1/2"
A2331: 10274813 | B2331: ZFE3 | C2331: 1000 | D2331: M3 | E2331: 1000 | G2331: 1448 | H2331: MP ARENA TRIT RÍO MALLA 4
A2332: 10274815 | B2332: ZFE3 | C2332: 1000 | D2332: M3 | E2332: 1000 | G2332: 1366 | H2332: MP ARENA CLASIFICADA RÍO MALLA 5
A2333: 10274816 | B2333: ZFE3 | C2333: 1000 | D2333: M3 | E2333: 1000 | G2333: 1472 | H2333: MP GRAVA CLASIF RÍO 20 MM - 3/4"
A2334: 10275113 | B2334: ZFE3 | C2334: 1000 | D2334: M3 | E2334: 1000 | G2334: 1409 | H2334: MP ARENA TRIT ANDESITA MALLA 4
A2335: 10275114 | B2335: ZFE3 | C2335: 1000 | D2335: M3 | E2335: 1000 | G2335: 1418 | H2335: MP ARENA CLASIF RIO MALLA 4 - LAVADO
A2336: 10275115 | B2336: ZFE3 | C2336: 1000 | D2336: M3 | E2336: 1000 | G2336: 1259 | H2336: MP ARENA TRIT ANDESITA MALLA 4
A2337: 10275116 | B2337: ZFE3 | C2337: 1000 | D2337: M3 | E2337: 1000 | G2337: 1401 | H2337: MP GRAVA TRIT ANDESITA 3/4 - 20 MM
A2338: 10275118 | B2338: ZFE3 | C2338: 1000 | D2338: M3 | E2338: 1000 | G2338: 1401 | H2338: MP ARENA TRIT ANDESITA MALLA 4
... A2361: 10280049 | B2361: ZFE3 | C2361: 1000 | D2361: M3 | E2361: 1000 | G2361: 1584 | H2361: MP B. HID CALIZA 40% FINOS Y 60% GRUESOS
A2362: 10280365 | C2362: 1000 | D2362: M3 | E2362: 1000 | G2362: 1274 | H2362: MP GRAVA BASALTO 20 MM -3/4
A2363: 10280538 | B2363: ZFE3 | C2363: 1000 | D2363: M3 | E2363: 1000 | G2363: 1262 | H2363: MP GRAVA TRIT BASALTO 3/8 - 10MM
A2364: 10280679 | B2364: ZFE3 | C2364: 1000 | D2364: M3 | E2364: 1000 | G2364: 1349 | H2364: MP GRAVA CLASIF RÍO 13MM - 1/2"
A2365: 10281171 | B2365: ZFE3 | C2365: 1000 | D2365: M3 | E2365: 1000 | G2365: 1271 | H2365: MP GRAVA TRIT CALIZA 10MM - 3/8"
A2366: 10281183 | B2366: ZFE3 | C2366: 1000 | D2366: M3 | E2366: 1000 | G2366: 1468 | H2366: MP ARENA TRIT CALIZA MALLA 4
A2367: 10281384 | B2367: ZFE3 | C2367: 1000 | D2367: M3 | E2367: 1000 | G2367: 1285 | H2367: MP GRAVA BASALTO 40 MM (1 1/2")
A2368: 10281379 | B2368: ZFE3 | C2368: 1000 | D2368: M3 | E2368: 1000 | G2368: 1536 | H2368: MP ARENA CLASIF. RÍO MALLA 4
A2369: 10281450 | B2369: ZFE3 | C2369: 1000 | D2369: M3 | E2369: 1000 | G2369: 1325 | H2369: MP GRAVA CLASIF. RIO 20MM - 3/4
A2370: 10281451 | B2370: ZFE3 | C2370: 1000 | D2370: M3 | E2370: 1000 | G2370: 1564 | H2370: MP ARENA CLASIF. RÍO MALLA 4
A2371: 10281452 | B2371: ZFE3 | C2371: 1000 | D2371: M3 | E2371: 1000 | G2371: 1427 | H2371: MP GRAVA CLASIF. RIO 20MM - 3/4

Sheet TRAOPE
A1: Concat1 | B1: Contrato_Pos | C1: Doc. Compras | D1: Pos | E1: Org.compras | F1: Grp-Compr. | G1: Ship From | H1: Nombre SF | I1: Proveedor | J1: Nombre Prov | K1: Cond. Pago | L1: Descr. Cond Pago | M1: Material | N1: Descripción | O1: Centro | P1: Descripción Centro | Q1: In.perído validez | R1: Fin perído validez | S1: Válido de | T1: Validez a | U1: Precio neto pedido | V1: Moneda | W1: UM Precio Pedido | X1: Importe Condición | Y1: Moneda KONP | Z1: UM Ctd Base | AA1: Destino | AB1: Nombre Destino | AC1: Cuenta de mayor | AD1: Centro de costo | AE1: Cond. Exp. | AF1: Descr. Cond. Exp. | AG1: Peso Vol. | AH1: UMB | AI1: Ind. Oblig. Conf. Ped. | AJ1: Ctrl-Conf. | AK1: IVA | AL1: Modif_Date | AM1: Ruta
A2: 900009255D84510000656 | B2: 4600071321-20 | C2: 4600071321 | D2: 20 | E2: MXPO | F2: MXL | G2: 900009255 | H2: SF TP-GRAMOL CLIENTES FORANEOS | I2: 5005459 | J2: TRITURADOS GRAMOL SA DE CV | K2: Z04 | L2: (AP) 30 Dias | M2: 10000656 | N2: Grava Triturada Caliza 10 mm - 3/8" | O2: D845 | P2: MX-CED. SLP | Q2: 20250604 | R2: 20301231 | S2: 20260826 | T2: 20301231 | U2: 176 | V2: MXN | W2: TN | X2: 0 | Y2: MXN | Z2: TN | AC2: 56103637 | AD2: 6622351540 | AE2: 1 | AF2: ENTREGADO | AG2: 1 | AH2: TO | AI2: X | AJ2: 4 | AK2: V4 | AL2: 20260826 | AM2: D845-900009255-10000656
A3: 900009255D84510058501 | B3: 4600072516-10 | C3: 4600072516 | D3: 10 | E3: MXPO | F3: MXL | G3: 900009255 | H3: SF TP-GRAMOL CLIENTES FORANEOS | I3: 5005459 | J3: TRITURADOS GRAMOL SA DE CV | K3: Z04 | L3: (AP) 30 Dias | M3: 10058501 | N3: Base H Triturada Caliza 1 1/2" a Finos | O3: D845 | P3: MX-CED. SLP | Q3: 20260804 | R3: 20301231 | S3: 20260804 | T3: 20301231 | U3: 175 | V3: MXN | W3: TN | X3: 0 | Y3: MXN | Z3: TN | AC3: 56103590 | AD3: 6622351540 | AE3: 1 | AF3: ENTREGADO | AG3: 1 | AH3: TO | AI3: X | AJ3: 4 | AK3: V4 | AL3: 20260806 | AM3: D845-900009255-10058501
A4: 900008838D8456724110210167749 | B4: 4600069664-10 | C4: 4600069664 | D4: 10 | E4: MXPO | F4: MXL | G4: 900008838 | H4: SF TP-ED LA MISION RP | I4: 5086121 | J4: LA MISION RP DEL BAJIO S DE RL DE C | K4: N15 | L4: (AP) NAFIN 15 Dias | M4: 10167749 | N4: BASE H CALIZA 1 1/2" A FINOS ESPECIAL | O4: D845 | P4: MX-CED. SLP | Q4: 20240606 | R4: 20291231 | S4: 20240606 | T4: 20291231 | U4: 307 | V4: MXN | W4: TN | X4: 150 | Y4: MXN | Z4: TN | AA4: 67241102 | AB4: Estación Moctezuma Lmr | AC4: 56103590 | AD4: 6622351540 | AE4: 4 | AF4: ENTREGA DIRECTA | AG4: 1 | AH4: TO | AI4: X | AJ4: 4 | AK4: V4 | AL4: 20240806 | AM4: D845-900008838-67241102-10167749-4
A5: 900006074D8456731824610169508 | B5: 4600044538-1090 | C5: 4600044538 | D5: 1090 | E5: MXPO | F5: MXL | G5: 900006074 | H5: SF TP-ED- GRAMOL SLP | I5: 5005459 | J5: TRITURADOS GRAMOL SA DE CV | K5: Z04 | L5: (AP) 30 Dias | M5: 10169508 | N5: GRAVA TRITURADA CALIZA 13 MM - 1/2" | O5: D845 | P5: MX-CED. SLP | Q5: 20190415 | R5: 20291231 | S5: 20250517 | T5: 20301231 | U5: 314 | V5: MXN | W5: TN | X5: 141 | Y5: MXN | Z5: TN | AA5: 67318246 | AB5: DC CONCRETOS EL FUERTE | AC5: 56103637 | AD5: 6622351540 | AE5: 4 | AF5: ENTREGA DIRECTA | AG5: 1 | AH5: TO | AI5: X | AJ5: 4 | AK5: V4 | AL5: 20250520 | AM5: D845-900006074-67318246-10169508-4
A6: 900006074D8456699814910167749 | B6: 4600044538-480 | C6: 4600044538 | D6: 480 | E6: MXPO | F6: MXL | G6: 900006074 | H6: SF TP-ED- GRAMOL SLP | I6: 5005459 | J6: TRITURADOS GRAMOL SA DE CV | K6: Z04 | L6: (AP) 30 Dias | M6: 10167749 | N6: BASE H CALIZA 1 1/2" A FINOS ESPECIAL | O6: D845 | P6: MX-CED. SLP | Q6: 20190415 | R6: 20291231 | S6: 20211203 | T6: 20261231 | U6: 175 | V6: MXN | W6: TN | X6: 85 | Y6: MXN | Z6: TN | AA6: 66998149 | AB6: KANSAS | AC6: 56103590 | AD6: 6622351540 | AE6: 4 | AF6: ENTREGA DIRECTA | AG6: 1 | AH6: TO | AI6: X | AJ6: 4 | AK6: V4 | AL6: 20230920 | AM6: D845-900006074-66998149-10167749-4
A7: 900006074D8456699814910000617 | B7: 4600044538-490 | C7: 4600044538 | D7: 490 | E7: MXPO | F7: MXL | G7: 900006074 | H7: SF TP-ED- GRAMOL SLP | I7: 5005459 | J7: TRITURADOS GRAMOL SA DE CV | K7: Z04 | L7: (AP) 30 Dias | M7: 10000617 | N7: Arena Triturada Caliza Malla 5 | O7: D845 | P7: MX-CED. SLP | Q7: 20190415 | R7: 20291231 | S7: 20220223 | T7: 20271231 | U7: 182 | V7: MXN | W7: TN | X7: 85 | Y7: MXN | Z7: TN | AA7: 66998149 | AB7: KANSAS | AC7: 56103638 | AD7: 6622351540 | AE7: 4 | AF7: ENTREGA DIRECTA | AG7: 1 | AH7: TO | AI7: X | AJ7: 4 | AK7: V4 | AL7: 20230920 | AM7: D845-900006074-66998149-10000617-4
A8: 900006074D8456699814910000656 | B8: 4600044538-500 | C8: 4600044538 | D8: 500 | E8: MXPO | F8: MXL | G8: 900006074 | H8: SF TP-ED- GRAMOL SLP | I8: 5005459 | J8: TRITURADOS GRAMOL SA DE CV | K8: Z04 | L8: (AP) 30 Dias | M8: 10000656 | N8: Grava Triturada Caliza 10 mm - 3/8" | O8: D845 | P8: MX-CED. SLP | Q8: 20190415 | R8: 20291231 | S8: 20220223 | T8: 20271231 | U8: 180 | V8: MXN | W8: TN | X8: 85 | Y8: MXN | Z8: TN | AA8: 66998149 | AB8: KANSAS | AC8: 56103637 | AD8: 6622351540 | AE8: 4 | AF8: ENTREGA DIRECTA | AG8: 1 | AH8: TO | AI8: X | AJ8: 4 | AK8: V4 | AL8: 20230920 | AM8: D845-900006074-66998149-10000656-4
A9: 900006074D8456725700110000536 | B9: 4600044538-1000 | C9: 4600044538 | D9: 1000 | E9: MXPO | F9: MXL | G9: 900006074 | H9: SF TP-ED- GRAMOL SLP | I9: 5005459 | J9: TRITURADOS GRAMOL SA DE CV | K9: Z04 | L9: (AP) 30 Dias | M9: 10000536 | N9: Grava Triturada Caliza 40 mm - 1 1/2" | O9: D845 | P9: MX-CED. SLP | Q9: 20190415 | R9: 20291231 | S9: 20250409 | T9: 20301231 | U9: 270 | V9: MXN | W9: TN | X9: 89 | Y9: MXN | Z9: TN | AA9: 67257001 | AB9: KANSAS TERCERA GRANDE (ERA) | AC9: 56103637 | AD9: 6622351540 | AE9: 4 | AF9: ENTREGA DIRECTA | AG9: 1 | AH9: TO | AI9: X | AJ9: 4 | AK9: V4 | AL9: 20250410 | AM9: D845-900006074-67257001-10000536-4
A10: 900006074D8456717023610167749 | B10: 4600044538-830 | C10: 4600044538 | D10: 830 | E10: MXPO | F10: MXL | G10: 900006074 | H10: SF TP-ED- GRAMOL SLP | I10: 5005459 | J10: TRITURADOS GRAMOL SA DE CV | K10: Z04 | L10: (AP) 30 Dias | M10: 10167749 | N10: BASE H CALIZA 1 1/2" A FINOS ESPECIAL | O10: D845 | P10: MX-CED. SLP | Q10: 20190415 | R10: 20291231 | S10: 20240325 | T10: 20291231 | U10: 219 | V10: MXN | W10: TN | X10: 66 | Y10: MXN | Z10: TN | AA10: 67170236 | AB10: URBANIZACIÓN RANCHO ZAMORA 2DA(ERA | AC10: 56103590 | AD10: 6622351540 | AE10: 4 | AF10: ENTREGA DIRECTA | AG10: 1 | AH10: TO | AI10: X | AJ10: 4 | AK10: V4 | AL10: 20240331 | AM10: D845-900006074-67170236-10167749-4
A11: 900006074D8456699814910178270 | B11: 4600044538-470 | C11: 4600044538 | D11: 470 | E11: MXPO | F11: MXL | G11: 900006074 | H11: SF TP-ED- GRAMOL SLP | I11: 5005459 | J11: TRITURADOS GRAMOL SA DE CV | K11: Z04 | L11: (AP) 30 Dias | M11: 10178270 | N11: SUB BASE H TRITURADA CALIZA 1 1/2" A FIN | O11: D845 | P11: MX-CED. SLP | Q11: 20190415 | R11: 20291231 | S11: 20211203 | T11: 20261231 | U11: 155 | V11: MXN | W11: TN | X11: 85 | Y11: MXN | Z11: TN | AA11: 66998149 | AB11: KANSAS | AC11: 56103590 | AD11: 6622351540 | AE11: 4 | AF11: ENTREGA DIRECTA | AG11: 1 | AH11: TO | AI11: X | AJ11: 4 | AK11: V4 | AL11: 20230920 | AM11: D845-900006074-66998149-10178270-4
A12: 900006124D84510000646 | B12: 4600044703-10 | C12: 4600044703 | D12: 10 | E12: MXPO | F12: MXL | G12: 900006124 | H12: SF TP- INCASA | I12: 5001208 | J12: INDUSTRIALIZADORA DE CALIZA SA DE | K12: Z04 | L12: (AP) 30 Dias | M12: 10000646 | N12: Grava Triturada Caliza 20 mm - 3/4" | O12: D845 | P12: MX-CED. SLP | Q12: 20190501 | R12: 20291231 | S12: 20210308 | T12: 20291231 | U12: 87 | V12: MXN | W12: TN | AC12: 56103637 | AD12: 6622351540 | AE12: 1 | AF12: ENTREGADO | AG12: 1 | AH12: TO | AI12: X | AJ12: 4 | AK12: V4 | AL12: 20230920 | AM12: D845-900006124-10000646
A13: 900006074D8456734808910167749 | B13: 4600044538-1230 | C13: 4600044538 | D13: 1230 | E13: MXPO | F13: MXL | G13: 900006074 | H13: SF TP-ED- GRAMOL SLP | I13: 5005459 | J13: TRITURADOS GRAMOL SA DE CV | K13: Z04 | L13: (AP) 30 Dias | M13: 10167749 | N13: BASE H CALIZA 1 1/2" A FINOS ESPECIAL | O13: D845 | P13: MX-CED. SLP | Q13: 20190415 | R13: 20291231 | S13: 20251118 | T13: 20301231 | U13: 269 | V13: MXN | W13: TN | X13: 86 | Y13: MXN | Z13: TN | AA13: 67348089 | AB13: CIMENTACIÓN DE TANQUE BOSCALIA | AC13: 56103590 | AD13: 6622351540 | AE13: 4 | AF13: ENTREGA DIRECTA | AG13: 1 | AH13: TO | AI13: X | AJ13: 4 | AK13: V4 | AL13: 20251120 | AM13: D845-900006074-67348089-10167749-4
A14: 900006074D8456734854410167749 | B14: 4600044538-1220 | C14: 4600044538 | D14: 1220 | E14: MXPO | F14: MXL | G14: 900006074 | H14: SF TP-ED- GRAMOL SLP | I14: 5005459 | J14: TRITURADOS GRAMOL SA DE CV | K14: Z04 | L14: (AP) 30 Dias | M14: 10167749 | N14: BASE H CALIZA 1 1/2" A FINOS ESPECIAL | O14: D845 | P14: MX-CED. SLP | Q14: 20190415 | R14: 20291231 | S14: 20251118 | T14: 20301231 | U14: 258 | V14: MXN | W14: TN | X14: 75 | Y14: MXN | Z14: TN | AA14: 67348544 | AB14: PRIVADA HIDALGO LA PILA GLL | AC14: 56103590 | AD14: 6622351540 | AE14: 4 | AF14: ENTREGA DIRECTA | AG14: 1 | AH14: TO | AI14: X | AJ14: 4 | AK14: V4 | AL14: 20251120 | AM14: D845-900006074-67348544-10167749-4
A15: 900003510D84510000405 | B15: 4600038453-30 | C15: 4600038453 | D15: 30 | E15: MXPO | F15: MXL | G15: 900003510 | H15: TP-TRISEGO | I15: 5041773 | J15: TRISEGO SA DE CV | K15: N90 | L15: (AP) NAFIN 90 Dias | M15: 10000405 | N15: Grava Triturada Caliza 20 mm - 3/4" | O15: D845 | P15: MX-CED. SLP | Q15: 20170621 | R15: 20241231 | S15: 20170621 | T15: 20241231 | U15: 110 | V15: MXN | W15: M3 | X15: 0 | Y15: MXN | Z15: M3 | AC15: 56103637 | AD15: 6622351540 | AE15: 1 | AF15: ENTREGADO | AG15: 1.4 | AH15: M3 | AI15: X | AJ15: 4 | AK15: V4 | AL15: 20230920 | AM15: D845-900003510-10000405
A16: 900003510D84510000624 | B16: 4600038453-40 | C16: 4600038453 | D16: 40 | E16: MXPO | F16: MXL | G16: 900003510 | H16: TP-TRISEGO | I16: 5041773 | J16: TRISEGO SA DE CV | K16: N90 | L16: (AP) NAFIN 90 Dias | M16: 10000624 | N16: Grava Triturada Caliza 40 mm - 1 1/2" | O16: D845 | P16: MX-CED. SLP | Q16: 20170621 | R16: 20241231 | S16: 20170621 | T16: 20241231 | U16: 110 | V16: MXN | W16: M3 | X16: 0 | Y16: MXN | Z16: M3 | AC16: 56103637 | AD16: 6622351540 | AE16: 1 | AF16: ENTREGADO | AG16: 1.45 | AH16: M3 | AI16: X | AJ16: 4 | AK16: V4 | AL16: 20230920 | AM16: D845-900003510-10000624
A17: 900003510D84510000403 | B17: 4600038453-10 | C17: 4600038453 | D17: 10 | E17: MXPO | F17: MXL | G17: 900003510 | H17: TP-TRISEGO | I17: 5041773 | J17: TRISEGO SA DE CV | K17: N90 | L17: (AP) NAFIN 90 Dias | M17: 10000403 | N17: Arena Triturada Caliza Malla 4 | O17: D845 | P17: MX-CED. SLP | Q17: 20170621 | R17: 20241231 | S17: 20170621 | T17: 20241231 | U17: 137 | V17: MXN | W17: M3 | X17: 0 | Y17: MXN | Z17: M3 | AC17: 56103638 | AD17: 6622351540 | AE17: 1 | AF17: ENTREGADO | AG17: 1.56 | AH17: M3 | AI17: X | AJ17: 4 | AK17: V4 | AL17: 20230920 | AM17: D845-900003510-10000403
A18: 900003510D84510000617 | B18: 4600038453-20 | C18: 4600038453 | D18: 20 | E18: MXPO | F18: MXL | G18: 900003510 | H18: TP-TRISEGO | I18: 5041773 | J18: TRISEGO SA DE CV | K18: N90 | L18: (AP) NAFIN 90 Dias | M18: 10000617 | N18: Arena Triturada Caliza Malla 5 | O18: D845 | P18: MX-CED. SLP | Q18: 20170621 | R18: 20241231 | S18: 20170621 | T18: 20241231 | U18: 137 | V18: MXN | W18: M3 | X18: 0 | Y18: MXN | Z18: M3 | AC18: 56103638 | AD18: 6622351540 | AE18: 1 | AF18: ENTREGADO | AG18: 1.56 | AH18: M3 | AI18: X | AJ18: 4 | AK18: V4 | AL18: 20230920 | AM18: D845-900003510-10000617
A19: 900003510D84510043202 | B19: 4600038453-50 | C19: 4600038453 | D19: 50 | E19: MXPO | F19: MXL | G19: 900003510 | H19: TP-TRISEGO | I19: 5041773 | J19: TRISEGO SA DE CV | K19: N90 | L19: (AP) NAFIN 90 Dias | M19: 10043202 | N19: Grava Triturada Caliza 10 mm - 3/8" | O19: D845 | P19: MX-CED. SLP | Q19: 20170621 | R19: 20241231 | S19: 20170621 | T19: 20241231 | U19: 115 | V19: MXN | W19: M3 | X19: 0 | Y19: MXN | Z19: M3 | AC19: 56103637 | AD19: 6622351540 | AE19: 1 | AF19: ENTREGADO | AG19: 1.355 | AH19: M3 | AI19: X | AJ19: 4 | AK19: V4 | AL19: 20230920 | AM19: D845-900003510-10043202
A20: 900005260D84510217514 | B20: 4600068951-190 | C20: 4600068951 | D20: 190 | E20: MXPO | F20: MXL | G20: 900005260 | H20: TP-GRAMOL SLP ESPECIAL | I20: 5005459 | J20: TRITURADOS GRAMOL SA DE CV | K20: Z04 | L20: (AP) 30 Dias | M20: 10217514 | N20: ECOBASE | O20: D845 | P20: MX-CED. SLP | Q20: 20231201 | R20: 20291231 | S20: 20250127 | T20: 20301231 | U20: 75 | V20: MXN | W20: M3 | X20: 0 | Y20: MXN | Z20: M3 | AC20: 56103590 | AD20: 6622351540 | AE20: 1 | AF20: ENTREGADO | AG20: 1.5 | AH20: M3 | AI20: X | AJ20: 4 | AK20: V4 | AL20: 20250212 | AM20: D845-900005260-10217514
A21: 900006074D8456735589710000578 | B21: 4600044538-1390 | C21: 4600044538 | D21: 1390 | E21: MXPO | F21: MXL | G21: 900006074 | H21: SF TP-ED- GRAMOL SLP | I21: 5005459 | J21: TRITURADOS GRAMOL SA DE CV | K21: Z04 | L21: (AP) 30 Dias | M21: 10000578 | N21: GRAVA TRITURADA CALIZA 20 MM - 3/4" | O21: D845 | P21: MX-CED. SLP | Q21: 20190415 | R21: 20291231 | S21: 20260123 | T21: 20301231 | U21: 251 | V21: MXN | W21: TN | X21: 70 | Y21: MXN | Z21: TN | AA21: 67355897 | AB21: ACCESO A HUIZACHES | AC21: 56103637 | AD21: 6622351540 | AE21: 4 | AF21: ENTREGA DIRECTA | AG21: 1 | AH21: TO | AI21: X | AJ21: 4 | AK21: V4 | AL21: 20260127 | AM21: D845-900006074-67355897-10000578-4
A22: 900006074D8456735589710167749 | B22: 4600044538-1370 | C22: 4600044538 | D22: 1370 | E22: MXPO | F22: MXL | G22: 900006074 | H22: SF TP-ED- GRAMOL SLP | I22: 5005459 | J22: TRITURADOS GRAMOL SA DE CV | K22: Z04 | L22: (AP) 30 Dias | M22: 10167749 | N22: BASE H CALIZA 1 1/2" A FINOS ESPECIAL | O22: D845 | P22: MX-CED. SLP | Q22: 20190415 | R22: 20291231 | S22: 20260123 | T22: 20301231 | U22: 253 | V22: MXN | W22: TN | X22: 70 | Y22: MXN | Z22: TN | AA22: 67355897 | AB22: ACCESO A HUIZACHES | AC22: 56103590 | AD22: 6622351540 | AE22: 4 | AF22: ENTREGA DIRECTA | AG22: 1 | AH22: TO | AI22: X | AJ22: 4 | AK22: V4 | AL22: 20260127 | AM22: D845-900006074-67355897-10167749-4
A23: 900006074D8456720008610167749 | B23: 4600044538-730 | C23: 4600044538 | D23: 730 | E23: MXPO | F23: MXL | G23: 900006074 | H23: SF TP-ED- GRAMOL SLP | I23: 5005459 | J23: TRITURADOS GRAMOL SA DE CV | K23: Z04 | L23: (AP) 30 Dias | M23: 10167749 | N23: BASE H CALIZA 1 1/2" A FINOS ESPECIAL | O23: D845 | P23: MX-CED. SLP | Q23: 20190415 | R23: 20291231 | S23: 20240227 | T23: 20291231 | U23: 218 | V23: MXN | W23: TN | X23: 65 | Y23: MXN | Z23: TN | AA23: 67200086 | AB23: MABE AGREGADOS (ERA) | AC23: 56103590 | AD23: 6622351540 | AE23: 4 | AF23: ENTREGA DIRECTA | AG23: 1 | AH23: TO | AI23: X | AJ23: 4 | AK23: V4 | AL23: 20240229 | AM23: D845-900006074-67200086-10167749-4
A24: 900006074D8456720008610000578 | B24: 4600044538-750 | C24: 4600044538 | D24: 750 | E24: MXPO | F24: MXL | G24: 900006074 | H24: SF TP-ED- GRAMOL SLP | I24: 5005459 | J24: TRITURADOS GRAMOL SA DE CV | K24: Z04 | L24: (AP) 30 Dias | M24: 10000578 | N24: Grava Triturada Caliza 20 mm - 3/4" | O24: D845 | P24: MX-CED. SLP | Q24: 20190415 | R24: 20291231 | S24: 20240227 | T24: 20291231 | U24: 215 | V24: MXN | W24: TN | X24: 65 | Y24: MXN | Z24: TN | AA24: 67200086 | AB24: MABE AGREGADOS (ERA) | AC24: 56103637 | AD24: 6622351540 | AE24: 4 | AF24: ENTREGA DIRECTA | AG24: 1 | AH24: TO | AI24: X | AJ24: 4 | AK24: V4 | AL24: 20240229 | AM24: D845-900006074-67200086-10000578-4
A25: 900006074D8456737467110167749 | B25: 4600044538-1400 | C25: 4600044538 | D25: 1400 | E25: MXPO | F25: MXL | G25: 900006074 | H25: SF TP-ED- GRAMOL SLP | I25: 5005459 | J25: TRITURADOS GRAMOL SA DE CV | K25: Z04 | L25: (AP) 30 Dias | M25: 10167749 | N25: BASE H CALIZA 1 1/2" A FINOS ESPECIAL | O25: D845 | P25: MX-CED. SLP | Q25: 20190415 | R25: 20291231 | S25: 20260417 | T25: 20301231 | U25: 306 | V25: MXN | W25: TN | X25: 86 | Y25: MXN | Z25: TN | AA25: 67374671 | AB25: ACCESO A LOS DUARTE | AC25: 56103590 | AD25: 6622351540 | AE25: 4 | AF25: ENTREGA DIRECTA | AG25: 1 | AH25: TO | AI25: X | AJ25: 4 | AK25: V4 | AL25: 20260422 | AM25: D845-900006074-67374671-10167749-4
A26: 900006074D8456735589710000536 | B26: 4600044538-1380 | C26: 4600044538 | D26: 1380 | E26: MXPO | F26: MXL | G26: 900006074 | H26: SF TP-ED- GRAMOL SLP | I26: 5005459 | J26: TRITURADOS GRAMOL SA DE CV | K26: Z04 | L26: (AP) 30 Dias | M26: 10000536 | N26: Grava Triturada Caliza 40 mm - 1 1/2" | O26: D845 | P26: MX-CED. SLP | Q26: 20190415 | R26: 20291231 | S26: 20260123 | T26: 20301231 | U26: 251 | V26: MXN | W26: TN | X26: 70 | Y26: MXN | Z26: TN | AA26: 67355897 | AB26: ACCESO A HUIZACHES | AC26: 56103637 | AD26: 6622351540 | AE26: 4 | AF26: ENTREGA DIRECTA | AG26: 1 | AH26: TO | AI26: X | AJ26: 4 | AK26: V4 | AL26: 20260127 | AM26: D845-900006074-67355897-10000536-4
A27: 900006074D8456728337510167749 | B27: 4600044538-960 | C27: 4600044538 | D27: 960 | E27: MXPO | F27: MXL | G27: 900006074 | H27: SF TP-ED- GRAMOL SLP | I27: 5005459 | J27: TRITURADOS GRAMOL SA DE CV | K27: Z04 | L27: (AP) 30 Dias | M27: 10167749 | N27: BASE H CALIZA 1 1/2" A FINOS ESPECIAL | O27: D845 | P27: MX-CED. SLP | Q27: 20190415 | R27: 20291231 | S27: 20240918 | T27: 20291231 | U27: 238 | V27: MXN | W27: TN | X27: 85 | Y27: MXN | Z27: TN | AA27: 67283375 | AB27: LA SECA 24 K | AC27: 56103590 | AD27: 6622351540 | AE27: 4 | AF27: ENTREGA DIRECTA | AG27: 1 | AH27: TO | AI27: X | AJ27: 4 | AK27: V4 | AL27: 20241004 | AM27: D845-900006074-67283375-10167749-4
A28: 900006074D8456730740210000536 | B28: 4600044538-1140 | C28: 4600044538 | D28: 1140 | E28: MXPO | F28: MXL | G28: 900006074 | H28: SF TP-ED- GRAMOL SLP | I28: 5005459 | J28: TRITURADOS GRAMOL SA DE CV | K28: Z04 | L28: (AP) 30 Dias | M28: 10000536 | N28: Grava Triturada Caliza 40 mm - 1 1/2" | O28: D845 | P28: MX-CED. SLP | Q28: 20190415 | R28: 20291231 | S28: 20250708 | T28: 20301231 | U28: 231 | V28: MXN | W28: TN | X28: 50 | Y28: MXN | Z28: TN | AA28: 67307402 | AB28: C1802 WTC 3B SLP | AC28: 56103637 | AD28: 6622351540 | AE28: 4 | AF28: ENTREGA DIRECTA | AG28: 1 | AH28: TO | AI28: X | AJ28: 4 | AK28: V4 | AL28: 20250711 | AM28: D845-900006074-67307402-10000536-4
A29: 900006074D8456730740210167749 | B29: 4600044538-1150 | C29: 4600044538 | D29: 1150 | E29: MXPO | F29: MXL | G29: 900006074 | H29: SF TP-ED- GRAMOL SLP | I29: 5005459 | J29: TRITURADOS GRAMOL SA DE CV | K29: Z04 | L29: (AP) 30 Dias | M29: 10167749 | N29: BASE H CALIZA 1 1/2" A FINOS ESPECIAL | O29: D845 | P29: MX-CED. SLP | Q29: 20190415 | R29: 20291231 | S29: 20250708 | T29: 20301231 | U29: 233 | V29: MXN | W29: TN | X29: 50 | Y29: MXN | Z29: TN | AA29: 67307402 | AB29: C1802 WTC 3B SLP | AC29: 56103590 | AD29: 6622351540 | AE29: 4 | AF29: ENTREGA DIRECTA | AG29: 1 | AH29: TO | AI29: X | AJ29: 4 | AK29: V4 | AL29: 20250711 | AM29: D845-900006074-67307402-10167749-4
A30: 900006074D8456730740210000578 | B30: 4600044538-1130 | C30: 4600044538 | D30: 1130 | E30: MXPO | F30: MXL | G30: 900006074 | H30: SF TP-ED- GRAMOL SLP | I30: 5005459 | J30: TRITURADOS GRAMOL SA DE CV | K30: Z04 | L30: (AP) 30 Dias | M30: 10000578 | N30: Grava Triturada Caliza 20 mm - 3/4" | O30: D845 | P30: MX-CED. SLP | Q30: 20190415 | R30: 20291231 | S30: 20250708 | T30: 20301231 | U30: 231 | V30: MXN | W30: TN | X30: 50 | Y30: MXN | Z30: TN | AA30: 67307402 | AB30: C1802 WTC 3B SLP | AC30: 56103637 | AD30: 6622351540 | AE30: 4 | AF30: ENTREGA DIRECTA | AG30: 1 | AH30: TO | AI30: X | AJ30: 4 | AK30: V4 | AL30: 20250711 | AM30: D845-900006074-67307402-10000578-4
A31: 900006074D8456705950510000578 | B31: 4600044538-520 | C31: 4600044538 | D31: 520 | E31: MXPO | F31: MXL | G31: 900006074 | H31: SF TP-ED- GRAMOL SLP | I31: 5005459 | J31: TRITURADOS GRAMOL SA DE CV | K31: Z04 | L31: (AP) 30 Dias | M31: 10000578 | N31: Grava Triturada Caliza 20 mm - 3/4" | O31: D845 | P31: MX-CED. SLP | Q31: 20190415 | R31: 20291231 | S31: 20240227 | T31: 20291231 | U31: 209 | V31: MXN | W31: TN | X31: 59 | Y31: MXN | Z31: TN | AA31: 67059505 | AB31: PLANTA SAN LUIS POTOSI | AC31: 56103637 | AD31: 6622351540 | AE31: 4 | AF31: ENTREGA DIRECTA | AG31: 1 | AH31: TO | AI31: X | AJ31: 4 | AK31: V4 | AL31: 20240417 | AM31: D845-900006074-67059505-10000578-4
A32: 900006074D8456730740210000617 | B32: 4600044538-1120 | C32: 4600044538 | D32: 1120 | E32: MXPO | F32: MXL | G32: 900006074 | H32: SF TP-ED- GRAMOL SLP | I32: 5005459 | J32: TRITURADOS GRAMOL SA DE CV | K32: Z04 | L32: (AP) 30 Dias | M32: 10000617 | N32: Arena Triturada Caliza Malla 5 | O32: D845 | P32: MX-CED. SLP | Q32: 20190415 | R32: 20291231 | S32: 20250708 | T32: 20301231 | U32: 240 | V32: MXN | W32: TN | X32: 50 | Y32: MXN | Z32: TN | AA32: 67307402 | AB32: C1802 WTC 3B SLP | AC32: 56103638 | AD32: 6622351540 | AE32: 4 | AF32: ENTREGA DIRECTA | AG32: 1 | AH32: TO | AI32: X | AJ32: 4 | AK32: V4 | AL32: 20250711 | AM32: D845-900006074-67307402-10000617-4
... A38: 900006074D8456500513910000536 | B38: 4600044538-700 | C38: 4600044538 | D38: 700 | E38: MXPO | F38: MXL | G38: 900006074 | H38: SF TP-ED- GRAMOL SLP | I38: 5005459 | J38: TRITURADOS GRAMOL SA DE CV | K38: Z04 | L38: (AP) 30 Dias | M38: 10000536 | N38: Grava Triturada Caliza 40 mm - 1 1/2" | O38: D845 | P38: MX-CED. SLP | Q38: 20190415 | R38: 20291231 | S38: 20260212 | T38: 20301231 | U38: 296 | V38: MXN | W38: TN | X38: 68 | Y38: MXN | Z38: TN | AA38: 65005139 | AB38: CONSTRUCTORA QUID S.A. DE C.V. | AC38: 56103637 | AD38: 6622351540 | AE38: 4 | AF38: ENTREGA DIRECTA | AG38: 1 | AH38: TO | AI38: X | AJ38: 4 | AK38: V4 | AL38: 20260216 | AM38: D845-900006074-65005139-10000536-4
A39: 900005260D84510268651 | B39: 4600068951-210 | C39: 4600068951 | D39: 210 | E39: MXPO | F39: MXL | G39: 900005260 | H39: TP-GRAMOL SLP ESPECIAL | I39: 5005459 | J39: TRITURADOS GRAMOL SA DE CV | K39: Z04 | L39: (AP) 30 Dias | M39: 10268651 | N39: MP PIEDRA CALIZA 6 - 8" | O39: D845 | P39: MX-CED. SLP | Q39: 20231201 | R39: 20291231 | S39: 20260210 | T39: 20301231 | U39: 200 | V39: MXN | W39: TN | X39: 0 | Y39: MXN | Z39: TN | AC39: 56103637 | AD39: 6622351540 | AE39: 1 | AF39: ENTREGADO | AG39: 1 | AH39: TO | AI39: X | AJ39: 4 | AK39: V4 | AL39: 20260212 | AM39: D845-900005260-10268651
A40: 900005260D84510000536 | B40: 4600068951-150 | C40: 4600068951 | D40: 150 | E40: MXPO | F40: MXL | G40: 900005260 | H40: TP-GRAMOL SLP ESPECIAL | I40: 5005459 | J40: TRITURADOS GRAMOL SA DE CV | K40: Z04 | L40: (AP) 30 Dias | M40: 10000536 | N40: Grava Triturada Caliza 40 mm - 1 1/2" | O40: D845 | P40: MX-CED. SLP | Q40: 20231201 | R40: 20291231 | S40: 20260210 | T40: 20301231 | U40: 228 | V40: MXN | W40: TN | X40: 0 | Y40: MXN | Z40: TN | AC40: 56103637 | AD40: 6622351540 | AE40: 1 | AF40: ENTREGADO | AG40: 1 | AH40: TO | AI40: X | AJ40: 4 | AK40: V4 | AL40: 20260212 | AM40: D845-900005260-10000536
A41: 900005260D84510000617 | B41: 4600068951-130 | C41: 4600068951 | D41: 130 | E41: MXPO | F41: MXL | G41: 900005260 | H41: TP-GRAMOL SLP ESPECIAL | I41: 5005459 | J41: TRITURADOS GRAMOL SA DE CV | K41: Z04 | L41: (AP) 30 Dias | M41: 10000617 | N41: Arena Triturada Caliza Malla 5 | O41: D845 | P41: MX-CED. SLP | Q41: 20231201 | R41: 20291231 | S41: 20260210 | T41: 20301231 | U41: 228 | V41: MXN | W41: TN | X41: 0 | Y41: MXN | Z41: TN | AC41: 56103638 | AD41: 6622351540 | AE41: 1 | AF41: ENTREGADO | AG41: 1 | AH41: TO | AI41: X | AJ41: 4 | AK41: V4 | AL41: 20260212 | AM41: D845-900005260-10000617
A42: 900005260D84510169508 | B42: 4600068951-170 | C42: 4600068951 | D42: 170 | E42: MXPO | F42: MXL | G42: 900005260 | H42: TP-GRAMOL SLP ESPECIAL | I42: 5005459 | J42: TRITURADOS GRAMOL SA DE CV | K42: Z04 | L42: (AP) 30 Dias | M42: 10169508 | N42: GRAVA TRITURADA CALIZA 13 MM - 1/2" | O42: D845 | P42: MX-CED. SLP | Q42: 20231201 | R42: 20291231 | S42: 20260210 | T42: 20301231 | U42: 238 | V42: MXN | W42: TN | X42: 0 | Y42: MXN | Z42: TN | AC42: 56103637 | AD42: 6622351540 | AE42: 1 | AF42: ENTREGADO | AG42: 1 | AH42: TO | AI42: X | AJ42: 4 | AK42: V4 | AL42: 20260212 | AM42: D845-900005260-10169508
A43: 900005260D84510167749 | B43: 4600068951-120 | C43: 4600068951 | D43: 120 | E43: MXPO | F43: MXL | G43: 900005260 | H43: TP-GRAMOL SLP ESPECIAL | I43: 5005459 | J43: TRITURADOS GRAMOL SA DE CV | K43: Z04 | L43: (AP) 30 Dias | M43: 10167749 | N43: BASE H CALIZA 1 1/2" A FINOS ESPECIAL | O43: D845 | P43: MX-CED. SLP | Q43: 20231201 | R43: 20291231 | S43: 20260210 | T43: 20301231 | U43: 220 | V43: MXN | W43: TN | X43: 0 | Y43: MXN | Z43: TN | AC43: 56103590 | AD43: 6622351540 | AE43: 1 | AF43: ENTREGADO | AG43: 1 | AH43: TO | AI43: X | AJ43: 4 | AK43: V4 | AL43: 20260212 | AM43: D845-900005260-10167749
A44: 900005260D84510000656 | B44: 4600068951-160 | C44: 4600068951 | D44: 160 | E44: MXPO | F44: MXL | G44: 900005260 | H44: TP-GRAMOL SLP ESPECIAL | I44: 5005459 | J44: TRITURADOS GRAMOL SA DE CV | K44: Z04 | L44: (AP) 30 Dias | M44: 10000656 | N44: Grava Triturada Caliza 10 mm - 3/8" | O44: D845 | P44: MX-CED. SLP | Q44: 20231201 | R44: 20291231 | S44: 20260210 | T44: 20301231 | U44: 233 | V44: MXN | W44: TN | X44: 0 | Y44: MXN | Z44: TN | AC44: 56103637 | AD44: 6622351540 | AE44: 1 | AF44: ENTREGADO | AG44: 1 | AH44: TO | AI44: X | AJ44: 4 | AK44: V4 | AL44: 20260212 | AM44: D845-900005260-10000656
A45: 900005260D84510000578 | B45: 4600068951-140 | C45: 4600068951 | D45: 140 | E45: MXPO | F45: MXL | G45: 900005260 | H45: TP-GRAMOL SLP ESPECIAL | I45: 5005459 | J45: TRITURADOS GRAMOL SA DE CV | K45: Z04 | L45: (AP) 30 Dias | M45: 10000578 | N45: Grava Triturada Caliza 20 mm - 3/4" | O45: D845 | P45: MX-CED. SLP | Q45: 20231201 | R45: 20291231 | S45: 20260210 | T45: 20301231 | U45: 228 | V45: MXN | W45: TN | X45: 0 | Y45: MXN | Z45: TN | AC45: 56103637 | AD45: 6622351540 | AE45: 1 | AF45: ENTREGADO | AG45: 1 | AH45: TO | AI45: X | AJ45: 4 | AK45: V4 | AL45: 20260212 | AM45: D845-900005260-10000578
A46: 900005260D84510058501 | B46: 4600068951-180 | C46: 4600068951 | D46: 180 | E46: MXPO | F46: MXL | G46: 900005260 | H46: TP-GRAMOL SLP ESPECIAL | I46: 5005459 | J46: TRITURADOS GRAMOL SA DE CV | K46: Z04 | L46: (AP) 30 Dias | M46: 10058501 | N46: Base H Triturada Caliza 1 1/2" a Finos | O46: D845 | P46: MX-CED. SLP | Q46: 20231201 | R46: 20291231 | S46: 20260210 | T46: 20301231 | U46: 207 | V46: MXN | W46: TN | X46: 0 | Y46: MXN | Z46: TN | AC46: 56103590 | AD46: 6622351540 | AE46: 1 | AF46: ENTREGADO | AG46: 1 | AH46: TO | AI46: X | AJ46: 4 | AK46: V4 | AL46: 20260212 | AM46: D845-900005260-10058501
A47: 900005260D84510038941 | B47: 4600068951-220 | C47: 4600068951 | D47: 220 | E47: MXPO | F47: MXL | G47: 900005260 | H47: TP-GRAMOL SLP ESPECIAL | I47: 5005459 | J47: TRITURADOS GRAMOL SA DE CV | K47: Z04 | L47: (AP) 30 Dias | M47: 10038941 | N47: Desperdicio Triturado Caliza | O47: D845 | P47: MX-CED. SLP | Q47: 20231201 | R47: 20291231 | S47: 20260210 | T47: 20301231 | U47: 33 | V47: MXN | W47: TN | X47: 0 | Y47: MXN | Z47: TN | AC47: 56103695 | AD47: 6622351540 | AE47: 1 | AF47: ENTREGADO | AG47: 1 | AH47: TO | AI47: X | AJ47: 4 | AK47: V4 | AL47: 20260212 | AM47: D845-900005260-10038941
A48: 900006074D8456723113810167749 | B48: 4600044538-870 | C48: 4600044538 | D48: 870 | E48: MXPO | F48: MXL | G48: 900006074 | H48: SF TP-ED- GRAMOL SLP | I48: 5005459 | J48: TRITURADOS GRAMOL SA DE CV | K48: Z04 | L48: (AP) 30 Dias | M48: 10167749 | N48: BASE H CALIZA 1 1/2" A FINOS ESPECIAL | O48: D845 | P48: MX-CED. SLP | Q48: 20190415 | R48: 20291231 | S48: 20240624 | T48: 20291231 | U48: 234 | V48: MXN | W48: TN | X48: 81 | Y48: MXN | Z48: TN | AA48: 67231138 | AB48: TMO PARQUE BMW (GBCM) | AC48: 56103590 | AD48: 6622351540 | AE48: 4 | AF48: ENTREGA DIRECTA | AG48: 1 | AH48: TO | AI48: X | AJ48: 4 | AK48: V4 | AL48: 20240806 | AM48: D845-900006074-67231138-10167749-4
A49: 900006074D8456723113810058501 | B49: 4600044538-860 | C49: 4600044538 | D49: 860 | E49: MXPO | F49: MXL | G49: 900006074 | H49: SF TP-ED- GRAMOL SLP | I49: 5005459 | J49: TRITURADOS GRAMOL SA DE CV | K49: Z04 | L49: (AP) 30 Dias | M49: 10058501 | N49: Base H Triturada Caliza 1 1/2" a Finos | O49: D845 | P49: MX-CED. SLP | Q49: 20190415 | R49: 20291231 | S49: 20240624 | T49: 20291231 | U49: 224 | V49: MXN | W49: TN | X49: 81 | Y49: MXN | Z49: TN | AA49: 67231138 | AB49: TMO PARQUE BMW (GBCM) | AC49: 56103590 | AD49: 6622351540 | AE49: 4 | AF49: ENTREGA DIRECTA | AG49: 1 | AH49: TO | AI49: X | AJ49: 4 | AK49: V4 | AL49: 20240806 | AM49: D845-900006074-67231138-10058501-4
A50: 900006074D8456723076610058501 | B50: 4600044538-880 | C50: 4600044538 | D50: 880 | E50: MXPO | F50: MXL | G50: 900006074 | H50: SF TP-ED- GRAMOL SLP | I50: 5005459 | J50: TRITURADOS GRAMOL SA DE CV | K50: Z04 | L50: (AP) 30 Dias | M50: 10058501 | N50: Base H Triturada Caliza 1 1/2" a Finos | O50: D845 | P50: MX-CED. SLP | Q50: 20190415 | R50: 20291231 | S50: 20240624 | T50: 20291231 | U50: 224 | V50: MXN | W50: TN | X50: 81 | Y50: MXN | Z50: TN | AA50: 67230766 | AB50: TKB BMW | AC50: 56103590 | AD50: 6622351540 | AE50: 4 | AF50: ENTREGA DIRECTA | AG50: 1 | AH50: TO | AI50: X | AJ50: 4 | AK50: V4 | AL50: 20240806 | AM50: D845-900006074-67230766-10058501-4
A51: 900006074D8456723076610167749 | B51: 4600044538-890 | C51: 4600044538 | D51: 890 | E51: MXPO | F51: MXL | G51: 900006074 | H51: SF TP-ED- GRAMOL SLP | I51: 5005459 | J51: TRITURADOS GRAMOL SA DE CV | K51: Z04 | L51: (AP) 30 Dias | M51: 10167749 | N51: BASE H CALIZA 1 1/2" A FINOS ESPECIAL | O51: D845 | P51: MX-CED. SLP | Q51: 20190415 | R51: 20291231 | S51: 20240624 | T51: 20291231 | U51: 234 | V51: MXN | W51: TN | X51: 81 | Y51: MXN | Z51: TN | AA51: 67230766 | AB51: TKB BMW | AC51: 56103590 | AD51: 6622351540 | AE51: 4 | AF51: ENTREGA DIRECTA | AG51: 1 | AH51: TO | AI51: X | AJ51: 4 | AK51: V4 | AL51: 20240806 | AM51: D845-900006074-67230766-10167749-4
A52: 900006074D8456708237910000578 | B52: 4600044538-600 | C52: 4600044538 | D52: 600 | E52: MXPO | F52: MXL | G52: 900006074 | H52: SF TP-ED- GRAMOL SLP | I52: 5005459 | J52: TRITURADOS GRAMOL SA DE CV | K52: Z04 | L52: (AP) 30 Dias | M52: 10000578 | N52: Grava Triturada Caliza 20 mm - 3/4" | O52: D845 | P52: MX-CED. SLP | Q52: 20190415 | R52: 20291231 | S52: 20230201 | T52: 20281231 | U52: 177 | V52: MXN | W52: TN | X52: 53 | Y52: MXN | Z52: TN | AA52: 67082379 | AB52: PLANTA ZONA INDUSTRIAL | AC52: 56103637 | AD52: 6622351540 | AE52: 4 | AF52: ENTREGA DIRECTA | AG52: 1 | AH52: TO | AI52: X | AJ52: 4 | AK52: V4 | AL52: 20230920 | AM52: D845-900006074-67082379-10000578-4
A53: 900006074D8456652809410000578 | B53: 4600044538-20 | C53: 4600044538 | D53: 20 | E53: MXPO | F53: MXL | G53: 900006074 | H53: SF TP-ED- GRAMOL SLP | I53: 5005459 | J53: TRITURADOS GRAMOL SA DE CV | K53: Z04 | L53: (AP) 30 Dias | M53: 10000578 | N53: Grava Triturada Caliza 20 mm - 3/4" | O53: D845 | P53: MX-CED. SLP | Q53: 20190415 | R53: 20291231 | S53: 20190412 | T53: 20241231 | U53: 122.8 | V53: MXN | W53: TN | X53: 52.8 | Y53: MXN | Z53: TN | AA53: 66528094 | AB53: TRATADORA EL MORRO | AC53: 56103637 | AD53: 6622351540 | AE53: 4 | AF53: ENTREGA DIRECTA | AG53: 1 | AH53: TO | AI53: X | AJ53: 4 | AK53: V4 | AL53: 20230920 | AM53: D845-900006074-66528094-10000578-4
A54: 900006074D8456708237910000617 | B54: 4600044538-590 | C54: 4600044538 | D54: 590 | E54: MXPO | F54: MXL | G54: 900006074 | H54: SF TP-ED- GRAMOL SLP | I54: 5005459 | J54: TRITURADOS GRAMOL SA DE CV | K54: Z04 | L54: (AP) 30 Dias | M54: 10000617 | N54: Arena Triturada Caliza Malla 5 | O54: D845 | P54: MX-CED. SLP | Q54: 20190415 | R54: 20291231 | S54: 20230201 | T54: 20281231 | U54: 187 | V54: MXN | W54: TN | X54: 53 | Y54: MXN | Z54: TN | AA54: 67082379 | AB54: PLANTA ZONA INDUSTRIAL | AC54: 56103638 | AD54: 6622351540 | AE54: 4 | AF54: ENTREGA DIRECTA | AG54: 1 | AH54: TO | AI54: X | AJ54: 4 | AK54: V4 | AL54: 20230920 | AM54: D845-900006074-67082379-10000617-4
A55: 900006074D8456677912110000617 | B55: 4600044538-30 | C55: 4600044538 | D55: 30 | E55: MXPO | F55: MXL | G55: 900006074 | H55: SF TP-ED- GRAMOL SLP | I55: 5005459 | J55: TRITURADOS GRAMOL SA DE CV | K55: Z04 | L55: (AP) 30 Dias | M55: 10000617 | N55: Arena Triturada Caliza Malla 5 | O55: D845 | P55: MX-CED. SLP | Q55: 20190415 | R55: 20291231 | S55: 20190612 | T55: 20241231 | U55: 179.85 | V55: MXN | W55: TN | X55: 96.85 | Y55: MXN | Z55: TN | AA55: 66779121 | AB55: COCONAL VILLA DE REYES | AC55: 56103638 | AD55: 6622351540 | AE55: 4 | AF55: ENTREGA DIRECTA | AG55: 1 | AH55: TO | AI55: X | AJ55: 4 | AK55: V4 | AL55: 20230920 | AM55: D845-900006074-66779121-10000617-4
A56: 900006074D8456677912110000656 | B56: 4600044538-60 | C56: 4600044538 | D56: 60 | E56: MXPO | F56: MXL | G56: 900006074 | H56: SF TP-ED- GRAMOL SLP | I56: 5005459 | J56: TRITURADOS GRAMOL SA DE CV | K56: Z04 | L56: (AP) 30 Dias | M56: 10000656 | N56: Grava Triturada Caliza 10 mm - 3/8" | O56: D845 | P56: MX-CED. SLP | Q56: 20190415 | R56: 20291231 | S56: 20190612 | T56: 20241231 | U56: 164.85 | V56: MXN | W56: TN | X56: 96.85 | Y56: MXN | Z56: TN | AA56: 66779121 | AB56: COCONAL VILLA DE REYES | AC56: 56103637 | AD56: 6622351540 | AE56: 4 | AF56: ENTREGA DIRECTA | AG56: 1 | AH56: TO | AI56: X | AJ56: 4 | AK56: V4 | AL56: 20230920 | AM56: D845-900006074-66779121-10000656-4
A57: 900006074D8456708237910000536 | B57: 4600044538-610 | C57: 4600044538 | D57: 610 | E57: MXPO | F57: MXL | G57: 900006074 | H57: SF TP-ED- GRAMOL SLP | I57: 5005459 | J57: TRITURADOS GRAMOL SA DE CV | K57: Z04 | L57: (AP) 30 Dias | M57: 10000536 | N57: Grava Triturada Caliza 40 mm - 1 1/2" | O57: D845 | P57: MX-CED. SLP | Q57: 20190415 | R57: 20291231 | S57: 20230201 | T57: 20281231 | U57: 177 | V57: MXN | W57: TN | X57: 53 | Y57: MXN | Z57: TN | AA57: 67082379 | AB57: PLANTA ZONA INDUSTRIAL | AC57: 56103637 | AD57: 6622351540 | AE57: 4 | AF57: ENTREGA DIRECTA | AG57: 1 | AH57: TO | AI57: X | AJ57: 4 | AK57: V4 | AL57: 20230920 | AM57: D845-900006074-67082379-10000536-4
A58: 900006074D8456708237910000656 | B58: 4600044538-620 | C58: 4600044538 | D58: 620 | E58: MXPO | F58: MXL | G58: 900006074 | H58: SF TP-ED- GRAMOL SLP | I58: 5005459 | J58: TRITURADOS GRAMOL SA DE CV | K58: Z04 | L58: (AP) 30 Dias | M58: 10000656 | N58: Grava Triturada Caliza 10 mm - 3/8" | O58: D845 | P58: MX-CED. SLP | Q58: 20190415 | R58: 20291231 | S58: 20230201 | T58: 20281231 | U58: 185 | V58: MXN | W58: TN | X58: 53 | Y58: MXN | Z58: TN | AA58: 67082379 | AB58: PLANTA ZONA INDUSTRIAL | AC58: 56103637 | AD58: 6622351540 | AE58: 4 | AF58: ENTREGA DIRECTA | AG58: 1 | AH58: TO | AI58: X | AJ58: 4 | AK58: V4 | AL58: 20230920 | AM58: D845-900006074-67082379-10000656-4
A59: 900006074D8456677912110000536 | B59: 4600044538-50 | C59: 4600044538 | D59: 50 | E59: MXPO | F59: MXL | G59: 900006074 | H59: SF TP-ED- GRAMOL SLP | I59: 5005459 | J59: TRITURADOS GRAMOL SA DE CV | K59: Z04 | L59: (AP) 30 Dias | M59: 10000536 | N59: Grava Triturada Caliza 40 mm - 1 1/2" | O59: D845 | P59: MX-CED. SLP | Q59: 20190415 | R59: 20291231 | S59: 20190612 | T59: 20241231 | U59: 165.85 | V59: MXN | W59: TN | X59: 96.85 | Y59: MXN | Z59: TN | AA59: 66779121 | AB59: COCONAL VILLA DE REYES | AC59: 56103637 | AD59: 6622351540 | AE59: 4 | AF59: ENTREGA DIRECTA | AG59: 1 | AH59: TO | AI59: X | AJ59: 4 | AK59: V4 | AL59: 20230920 | AM59: D845-900006074-66779121-10000536-4
... A89: 900006074D8456729261710167749 | B89: 4600044538-1010 | C89: 4600044538 | D89: 1010 | E89: MXPO | F89: MXL | G89: 900006074 | H89: SF TP-ED- GRAMOL SLP | I89: 5005459 | J89: TRITURADOS GRAMOL SA DE CV | K89: Z04 | L89: (AP) 30 Dias | M89: 10167749 | N89: BASE H CALIZA 1 1/2" A FINOS ESPECIAL | O89: D845 | P89: MX-CED. SLP | Q89: 20190415 | R89: 20291231 | S89: 20241210 | T89: 20291231 | U89: 225 | V89: MXN | W89: TN | X89: 72 | Y89: MXN | Z89: TN | AA89: 67292617 | AB89: PUENTE CANAL MAGNOLIA | AC89: 56103590 | AD89: 6622351540 | AE89: 4 | AF89: ENTREGA DIRECTA | AG89: 1 | AH89: TO | AI89: X | AJ89: 4 | AK89: V4 | AL89: 20250104 | AM89: D845-900006074-67292617-10167749-4
A90: 900006124D84510000673 | B90: 4600044703-40 | C90: 4600044703 | D90: 40 | E90: MXPO | F90: MXL | G90: 900006124 | H90: SF TP- INCASA | I90: 5001208 | J90: INDUSTRIALIZADORA DE CALIZA SA DE | K90: Z04 | L90: (AP) 30 Dias | M90: 10000673 | N90: Grava Triturada Caliza 10 mm - 3/8" | O90: D845 | P90: MX-CED. SLP | Q90: 20190501 | R90: 20291231 | S90: 20210308 | T90: 20291231 | U90: 95 | V90: MXN | W90: TN | AC90: 56103637 | AD90: 6622351540 | AE90: 1 | AF90: ENTREGADO | AG90: 1 | AH90: TO | AI90: X | AJ90: 4 | AK90: V4 | AL90: 20230920 | AM90: D845-900006124-10000673
A91: 900006074D8456734147210000617 | B91: 4600044538-1160 | C91: 4600044538 | D91: 1160 | E91: MXPO | F91: MXL | G91: 900006074 | H91: SF TP-ED- GRAMOL SLP | I91: 5005459 | J91: TRITURADOS GRAMOL SA DE CV | K91: Z04 | L91: (AP) 30 Dias | M91: 10000617 | N91: Arena Triturada Caliza Malla 5 | O91: D845 | P91: MX-CED. SLP | Q91: 20190415 | R91: 20291231 | S91: 20251015 | T91: 20301231 | U91: 268 | V91: MXN | W91: TN | X91: 78 | Y91: MXN | Z91: TN | AA91: 67341472 | AB91: URBANIZACIÓN CAM. A MEZQUITAL | AC91: 56103638 | AD91: 6622351540 | AE91: 4 | AF91: ENTREGA DIRECTA | AG91: 1 | AH91: TO | AI91: X | AJ91: 4 | AK91: V4 | AL91: 20251016 | AM91: D845-900006074-67341472-10000617-4
A92: 900006074D8456734147210167749 | B92: 4600044538-1190 | C92: 4600044538 | D92: 1190 | E92: MXPO | F92: MXL | G92: 900006074 | H92: SF TP-ED- GRAMOL SLP | I92: 5005459 | J92: TRITURADOS GRAMOL SA DE CV | K92: Z04 | L92: (AP) 30 Dias | M92: 10167749 | N92: BASE H CALIZA 1 1/2" A FINOS ESPECIAL | O92: D845 | P92: MX-CED. SLP | Q92: 20190415 | R92: 20291231 | S92: 20251015 | T92: 20301231 | U92: 261 | V92: MXN | W92: TN | X92: 78 | Y92: MXN | Z92: TN | AA92: 67341472 | AB92: URBANIZACIÓN CAM. A MEZQUITAL | AC92: 56103590 | AD92: 6622351540 | AE92: 4 | AF92: ENTREGA DIRECTA | AG92: 1 | AH92: TO | AI92: X | AJ92: 4 | AK92: V4 | AL92: 20251016 | AM92: D845-900006074-67341472-10167749-4
A93: 900006074D8456734147210000536 | B93: 4600044538-1180 | C93: 4600044538 | D93: 1180 | E93: MXPO | F93: MXL | G93: 900006074 | H93: SF TP-ED- GRAMOL SLP | I93: 5005459 | J93: TRITURADOS GRAMOL SA DE CV | K93: Z04 | L93: (AP) 30 Dias | M93: 10000536 | N93: Grava Triturada Caliza 40 mm - 1 1/2" | O93: D845 | P93: MX-CED. SLP | Q93: 20190415 | R93: 20291231 | S93: 20251015 | T93: 20301231 | U93: 259 | V93: MXN | W93: TN | X93: 78 | Y93: MXN | Z93: TN | AA93: 67341472 | AB93: URBANIZACIÓN CAM. A MEZQUITAL | AC93: 56103637 | AD93: 6622351540 | AE93: 4 | AF93: ENTREGA DIRECTA | AG93: 1 | AH93: TO | AI93: X | AJ93: 4 | AK93: V4 | AL93: 20251016 | AM93: D845-900006074-67341472-10000536-4
A94: 900006074D8456734147210000578 | B94: 4600044538-1170 | C94: 4600044538 | D94: 1170 | E94: MXPO | F94: MXL | G94: 900006074 | H94: SF TP-ED- GRAMOL SLP | I94: 5005459 | J94: TRITURADOS GRAMOL SA DE CV | K94: Z04 | L94: (AP) 30 Dias | M94: 10000578 | N94: GRAVA TRITURADA CALIZA 20 MM - 3/4" | O94: D845 | P94: MX-CED. SLP | Q94: 20190415 | R94: 20291231 | S94: 20251015 | T94: 20301231 | U94: 259 | V94: MXN | W94: TN | X94: 78 | Y94: MXN | Z94: TN | AA94: 67341472 | AB94: URBANIZACIÓN CAM. A MEZQUITAL | AC94: 56103637 | AD94: 6622351540 | AE94: 4 | AF94: ENTREGA DIRECTA | AG94: 1 | AH94: TO | AI94: X | AJ94: 4 | AK94: V4 | AL94: 20251016 | AM94: D845-900006074-67341472-10000578-4
A95: 900006074D8456720390510000578 | B95: 4600044538-810 | C95: 4600044538 | D95: 810 | E95: MXPO | F95: MXL | G95: 900006074 | H95: SF TP-ED- GRAMOL SLP | I95: 5005459 | J95: TRITURADOS GRAMOL SA DE CV | K95: Z04 | L95: (AP) 30 Dias | M95: 10000578 | N95: Grava Triturada Caliza 20 mm - 3/4" | O95: D845 | P95: MX-CED. SLP | Q95: 20190415 | R95: 20291231 | S95: 20231228 | T95: 20281231 | U95: 188 | V95: MXN | W95: TN | X95: 64 | Y95: MXN | Z95: TN | AA95: 67203905 | AB95: VP-SLPI-04 ERD | AC95: 56103637 | AD95: 6622351540 | AE95: 4 | AF95: ENTREGA DIRECTA | AG95: 1 | AH95: TO | AI95: X | AJ95: 4 | AK95: V4 | AL95: 20231230 | AM95: D845-900006074-67203905-10000578-4
A96: 900006074D8456731824610000656 | B96: 4600044538-1080 | C96: 4600044538 | D96: 1080 | E96: MXPO | F96: MXL | G96: 900006074 | H96: SF TP-ED- GRAMOL SLP | I96: 5005459 | J96: TRITURADOS GRAMOL SA DE CV | K96: Z04 | L96: (AP) 30 Dias | M96: 10000656 | N96: Grava Triturada Caliza 10 mm - 3/8" | O96: D845 | P96: MX-CED. SLP | Q96: 20190415 | R96: 20291231 | S96: 20260122 | T96: 20301231 | U96: 301 | V96: MXN | W96: TN | X96: 141 | Y96: MXN | Z96: TN | AA96: 67318246 | AB96: DC CONCRETOS EL FUERTE | AC96: 56103637 | AD96: 6622351540 | AE96: 4 | AF96: ENTREGA DIRECTA | AG96: 1 | AH96: TO | AI96: X | AJ96: 4 | AK96: V4 | AL96: 20260123 | AM96: D845-900006074-67318246-10000656-4
A97: 900006074D8456731824610000536 | B97: 4600044538-1110 | C97: 4600044538 | D97: 1110 | E97: MXPO | F97: MXL | G97: 900006074 | H97: SF TP-ED- GRAMOL SLP | I97: 5005459 | J97: TRITURADOS GRAMOL SA DE CV | K97: Z04 | L97: (AP) 30 Dias | M97: 10000536 | N97: Grava Triturada Caliza 40 mm - 1 1/2" | O97: D845 | P97: MX-CED. SLP | Q97: 20190415 | R97: 20291231 | S97: 20260122 | T97: 20301231 | U97: 291 | V97: MXN | W97: TN | X97: 141 | Y97: MXN | Z97: TN | AA97: 67318246 | AB97: DC CONCRETOS EL FUERTE | AC97: 56103637 | AD97: 6622351540 | AE97: 4 | AF97: ENTREGA DIRECTA | AG97: 1 | AH97: TO | AI97: X | AJ97: 4 | AK97: V4 | AL97: 20260123 | AM97: D845-900006074-67318246-10000536-4
A98: 900006074D8456731824610000617 | B98: 4600044538-1070 | C98: 4600044538 | D98: 1070 | E98: MXPO | F98: MXL | G98: 900006074 | H98: SF TP-ED- GRAMOL SLP | I98: 5005459 | J98: TRITURADOS GRAMOL SA DE CV | K98: Z04 | L98: (AP) 30 Dias | M98: 10000617 | N98: Arena Triturada Caliza Malla 5 | O98: D845 | P98: MX-CED. SLP | Q98: 20190415 | R98: 20291231 | S98: 20260122 | T98: 20301231 | U98: 304 | V98: MXN | W98: TN | X98: 141 | Y98: MXN | Z98: TN | AA98: 67318246 | AB98: DC CONCRETOS EL FUERTE | AC98: 56103638 | AD98: 6622351540 | AE98: 4 | AF98: ENTREGA DIRECTA | AG98: 1 | AH98: TO | AI98: X | AJ98: 4 | AK98: V4 | AL98: 20260123 | AM98: D845-900006074-67318246-10000617-4
A99: 900006074D8456731824610000578 | B99: 4600044538-1100 | C99: 4600044538 | D99: 1100 | E99: MXPO | F99: MXL | G99: 900006074 | H99: SF TP-ED- GRAMOL SLP | I99: 5005459 | J99: TRITURADOS GRAMOL SA DE CV | K99: Z04 | L99: (AP) 30 Dias | M99: 10000578 | N99: Grava Triturada Caliza 20 mm - 3/4" | O99: D845 | P99: MX-CED. SLP | Q99: 20190415 | R99: 20291231 | S99: 20260122 | T99: 20301231 | U99: 291 | V99: MXN | W99: TN | X99: 141 | Y99: MXN | Z99: TN | AA99: 67318246 | AB99: DC CONCRETOS EL FUERTE | AC99: 56103637 | AD99: 6622351540 | AE99: 4 | AF99: ENTREGA DIRECTA | AG99: 1 | AH99: TO | AI99: X | AJ99: 4 | AK99: V4 | AL99: 20260123 | AM99: D845-900006074-67318246-10000578-4
A100: 900006074D8456720390510167749 | B100: 4600044538-820 | C100: 4600044538 | D100: 820 | E100: MXPO | F100: MXL | G100: 900006074 | H100: SF TP-ED- GRAMOL SLP | I100: 5005459 | J100: TRITURADOS GRAMOL SA DE CV | K100: Z04 | L100: (AP) 30 Dias | M100: 10167749 | N100: BASE H CALIZA 1 1/2" A FINOS ESPECIAL | O100: D845 | P100: MX-CED. SLP | Q100: 20190415 | R100: 20291231 | S100: 20231228 | T100: 20281231 | U100: 191 | V100: MXN | W100: TN | X100: 64 | Y100: MXN | Z100: TN | AA100: 67203905 | AB100: VP-SLPI-04 ERD | AC100: 56103590 | AD100: 6622351540 | AE100: 4 | AF100: ENTREGA DIRECTA | AG100: 1 | AH100: TO | AI100: X | AJ100: 4 | AK100: V4 | AL100: 20240331 | AM100: D845-900006074-67203905-10167749-4
A101: 900006074D8456720390510000617 | B101: 4600044538-800 | C101: 4600044538 | D101: 800 | E101: MXPO | F101: MXL | G101: 900006074 | H101: SF TP-ED- GRAMOL SLP | I101: 5005459 | J101: TRITURADOS GRAMOL SA DE CV | K101: Z04 | L101: (AP) 30 Dias | M101: 10000617 | N101: Arena Triturada Caliza Malla 5 | O101: D845 | P101: MX-CED. SLP | Q101: 20190415 | R101: 20291231 | S101: 20231228 | T101: 20281231 | U101: 198 | V101: MXN | W101: TN | X101: 64 | Y101: MXN | Z101: TN | AA101: 67203905 | AB101: VP-SLPI-04 ERD | AC101: 56103638 | AD101: 6622351540 | AE101: 4 | AF101: ENTREGA DIRECTA | AG101: 1 | AH101: TO | AI101: X | AJ101: 4 | AK101: V4 | AL101: 20231230 | AM101: D845-900006074-67203905-10000617-4
A102: 900006074D8456728339310058501 | B102: 4600044538-990 | C102: 4600044538 | D102: 990 | E102: MXPO | F102: MXL | G102: 900006074 | H102: SF TP-ED- GRAMOL SLP | I102: 5005459 | J102: TRITURADOS GRAMOL SA DE CV | K102: Z04 | L102: (AP) 30 Dias | M102: 10058501 | N102: Base H Triturada Caliza 1 1/2" a Finos | O102: D845 | P102: MX-CED. SLP | Q102: 20190415 | R102: 20291231 | S102: 20240924 | T102: 20291231 | U102: 184 | V102: MXN | W102: TN | X102: 41 | Y102: MXN | Z102: TN | AA102: 67283393 | AB102: ACCESO CEDIS COPPEL | AC102: 56103590 | AD102: 6622351540 | AE102: 4 | AF102: ENTREGA DIRECTA | AG102: 1 | AH102: TO | AI102: X | AJ102: 4 | AK102: V4 | AL102: 20241004 | AM102: D845-900006074-67283393-10058501-4
... A108: 900006074D8456719754310167749 | B108: 4600044538-850 | C108: 4600044538 | D108: 850 | E108: MXPO | F108: MXL | G108: 900006074 | H108: SF TP-ED- GRAMOL SLP | I108: 5005459 | J108: TRITURADOS GRAMOL SA DE CV | K108: Z04 | L108: (AP) 30 Dias | M108: 10167749 | N108: BASE H CALIZA 1 1/2" A FINOS ESPECIAL | O108: D845 | P108: MX-CED. SLP | Q108: 20190415 | R108: 20291231 | S108: 20240613 | T108: 20291231 | U108: 227 | V108: MXN | W108: TN | X108: 74 | Y108: MXN | Z108: TN | AA108: 67197543 | AB108: PARQUE INDUSTRIAL WTC (ERA) | AC108: 56103590 | AD108: 6622351540 | AE108: 4 | AF108: ENTREGA DIRECTA | AG108: 1 | AH108: TO | AI108: X | AJ108: 4 | AK108: V4 | AL108: 20240806 | AM108: D845-900006074-67197543-10167749-4
A109: 900006124D84510000337 | B109: 4600044703-30 | C109: 4600044703 | D109: 30 | E109: MXPO | F109: MXL | G109: 900006124 | H109: SF TP- INCASA | I109: 5001208 | J109: INDUSTRIALIZADORA DE CALIZA SA DE | K109: Z04 | L109: (AP) 30 Dias | M109: 10000337 | N109: Arena Triturada Caliza Malla 5 | O109: D845 | P109: MX-CED. SLP | Q109: 20190501 | R109: 20291231 | S109: 20210308 | T109: 20291231 | U109: 100 | V109: MXN | W109: TN | AC109: 56103638 | AD109: 6622351540 | AE109: 1 | AF109: ENTREGADO | AG109: 1 | AH109: TO | AI109: X | AJ109: 4 | AK109: V4 | AL109: 20230920 | AM109: D845-900006124-10000337
A110: 900006074D8456735495710167749 | B110: 4600044538-1240 | C110: 4600044538 | D110: 1240 | E110: MXPO | F110: MXL | G110: 900006074 | H110: SF TP-ED- GRAMOL SLP | I110: 5005459 | J110: TRITURADOS GRAMOL SA DE CV | K110: Z04 | L110: (AP) 30 Dias | M110: 10167749 | N110: BASE H CALIZA 1 1/2" A FINOS ESPECIAL | O110: D845 | P110: MX-CED. SLP | Q110: 20190415 | R110: 20291231 | S110: 20251128 | T110: 20301231 | U110: 263 | V110: MXN | W110: TN | X110: 80 | Y110: MXN | Z110: TN | AA110: 67354957 | AB110: CALLE LUIS BOTELLO | AC110: 56103590 | AD110: 6622351540 | AE110: 4 | AF110: ENTREGA DIRECTA | AG110: 1 | AH110: TO | AI110: X | AJ110: 4 | AK110: V4 | AL110: 20251202 | AM110: D845-900006074-67354957-10167749-4
A111: 900006074D8456725700110167749 | B111: 4600044538-930 | C111: 4600044538 | D111: 930 | E111: MXPO | F111: MXL | G111: 900006074 | H111: SF TP-ED- GRAMOL SLP | I111: 5005459 | J111: TRITURADOS GRAMOL SA DE CV | K111: Z04 | L111: (AP) 30 Dias | M111: 10167749 | N111: BASE H CALIZA 1 1/2" A FINOS ESPECIAL | O111: D845 | P111: MX-CED. SLP | Q111: 20190415 | R111: 20291231 | S111: 20250508 | T111: 20301231 | U111: 272 | V111: MXN | W111: TN | X111: 89 | Y111: MXN | Z111: TN | AA111: 67257001 | AB111: KANSAS TERCERA GRANDE (ERA) | AC111: 56103590 | AD111: 6622351540 | AE111: 4 | AF111: ENTREGA DIRECTA | AG111: 1 | AH111: TO | AI111: X | AJ111: 4 | AK111: V4 | AL111: 20250513 | AM111: D845-900006074-67257001-10167749-4
A112: 900003510D84510058501 | B112: 4600027443-20 | C112: 4600027443 | D112: 20 | E112: MXPO | F112: M02 | G112: 900003510 | H112: TP-TRISEGO | I112: 5041773 | J112: TRISEGO SA DE CV | K112: N90 | L112: (AP) NAFIN 90 Dias | M112: 10058501 | N112: Base H Triturada Caliza 1 1/2" a Finos | O112: D845 | P112: MX-CED. SLP | Q112: 20141106 | R112: 20241231 | S112: 20141106 | T112: 20241231 | U112: 100 | V112: MXN | W112: M3 | X112: 0 | Y112: MXN | Z112: M3 | AC112: 56103590 | AD112: 6622351540 | AE112: 1 | AF112: ENTREGADO | AG112: 1.63 | AH112: M3 | AI112: X | AJ112: 4 | AK112: V4 | AL112: 20230920 | AM112: D845-900003510-10058501
A113: 900006074D8456731981710167749 | B113: 4600044538-1050 | C113: 4600044538 | D113: 1050 | E113: MXPO | F113: MXL | G113: 900006074 | H113: SF TP-ED- GRAMOL SLP | I113: 5005459 | J113: TRITURADOS GRAMOL SA DE CV | K113: Z04 | L113: (AP) 30 Dias | M113: 10167749 | N113: BASE H CALIZA 1 1/2" A FINOS ESPECIAL | O113: D845 | P113: MX-CED. SLP | Q113: 20190415 | R113: 20291231 | S113: 20250509 | T113: 20301231 | U113: 253 | V113: MXN | W113: TN | X113: 70 | Y113: MXN | Z113: TN | AA113: 67319817 | AB113: EXTRAS RANCHO ZAMORA/LAJA | AC113: 56103590 | AD113: 6622351540 | AE113: 4 | AF113: ENTREGA DIRECTA | AG113: 1 | AH113: TO | AI113: X | AJ113: 4 | AK113: V4 | AL113: 20250513 | AM113: D845-900006074-67319817-10167749-4
A114: 900009255D84510000536 | B114: 4600071321-50 | C114: 4600071321 | D114: 50 | E114: MXPO | F114: MXL | G114: 900009255 | H114: SF TP-GRAMOL CLIENTES FORANEOS | I114: 5005459 | J114: TRITURADOS GRAMOL SA DE CV | K114: Z04 | L114: (AP) 30 Dias | M114: 10000536 | N114: Grava Triturada Caliza 40 mm - 1 1/2" | O114: D845 | P114: MX-CED. SLP | Q114: 20250604 | R114: 20301231 | S114: 20260217 | T114: 20301231 | U114: 165 | V114: MXN | W114: TN | X114: 0 | Y114: MXN | Z114: TN | AC114: 56103637 | AD114: 6622351540 | AE114: 1 | AF114: ENTREGADO | AG114: 1 | AH114: TO | AI114: X | AJ114: 4 | AK114: V4 | AL114: 20260218 | AM114: D845-900009255-10000536
A115: 900006074D8456500698910000536 | B115: 4600044538-1280 | C115: 4600044538 | D115: 1280 | E115: MXPO | F115: MXL | G115: 900006074 | H115: SF TP-ED- GRAMOL SLP | I115: 5005459 | J115: TRITURADOS GRAMOL SA DE CV | K115: Z04 | L115: (AP) 30 Dias | M115: 10000536 | N115: Grava Triturada Caliza 40 mm - 1 1/2" | O115: D845 | P115: MX-CED. SLP | Q115: 20190415 | R115: 20291231 | S115: 20251230 | T115: 20301231 | U115: 473 | V115: MXN | W115: TN | X115: 323 | Y115: MXN | Z115: TN | AA115: 65006989 | AB115: (P) PREMEZCLADOS CONCRECO S.A. DE C | AC115: 56103637 | AD115: 6622351540 | AE115: 4 | AF115: ENTREGA DIRECTA | AG115: 1 | AH115: TO | AI115: X | AJ115: 4 | AK115: V4 | AL115: 20251230 | AM115: D845-900006074-65006989-10000536-4
A116: 900006074D8456500698910000578 | B116: 4600044538-1270 | C116: 4600044538 | D116: 1270 | E116: MXPO | F116: MXL | G116: 900006074 | H116: SF TP-ED- GRAMOL SLP | I116: 5005459 | J116: TRITURADOS GRAMOL SA DE CV | K116: Z04 | L116: (AP) 30 Dias | M116: 10000578 | N116: GRAVA TRITURADA CALIZA 20 MM - 3/4" | O116: D845 | P116: MX-CED. SLP | Q116: 20190415 | R116: 20291231 | S116: 20251230 | T116: 20301231 | U116: 473 | V116: MXN | W116: TN | X116: 323 | Y116: MXN | Z116: TN | AA116: 65006989 | AB116: (P) PREMEZCLADOS CONCRECO S.A. DE C | AC116: 56103637 | AD116: 6622351540 | AE116: 4 | AF116: ENTREGA DIRECTA | AG116: 1 | AH116: TO | AI116: X | AJ116: 4 | AK116: V4 | AL116: 20251230 | AM116: D845-900006074-65006989-10000578-4
A117: 900009255D84510169508 | B117: 4600071321-30 | C117: 4600071321 | D117: 30 | E117: MXPO | F117: MXL | G117: 900009255 | H117: SF TP-GRAMOL CLIENTES FORANEOS | I117: 5005459 | J117: TRITURADOS GRAMOL SA DE CV | K117: Z04 | L117: (AP) 30 Dias | M117: 10169508 | N117: GRAVA TRITURADA CALIZA 13 MM - 1/2" | O117: D845 | P117: MX-CED. SLP | Q117: 20250604 | R117: 20301231 | S117: 20260217 | T117: 20301231 | U117: 190 | V117: MXN | W117: TN | X117: 0 | Y117: MXN | Z117: TN | AC117: 56103637 | AD117: 6622351540 | AE117: 1 | AF117: ENTREGADO | AG117: 1 | AH117: TO | AI117: X | AJ117: 4 | AK117: V4 | AL117: 20260218 | AM117: D845-900009255-10169508
A118: 900006074D8456724110210167749 | B118: 4600044538-900 | C118: 4600044538 | D118: 900 | E118: MXPO | F118: MXL | G118: 900006074 | H118: SF TP-ED- GRAMOL SLP | I118: 5005459 | J118: TRITURADOS GRAMOL SA DE CV | K118: Z04 | L118: (AP) 30 Dias | M118: 10167749 | N118: BASE H CALIZA 1 1/2" A FINOS ESPECIAL | O118: D845 | P118: MX-CED. SLP | Q118: 20190415 | R118: 20291231 | S118: 20240715 | T118: 20291231 | U118: 361 | V118: MXN | W118: TN | X118: 208 | Y118: MXN | Z118: TN | AA118: 67241102 | AB118: Estación Moctezuma Lmr | AC118: 56103590 | AD118: 6622351540 | AE118: 4 | AF118: ENTREGA DIRECTA | AG118: 1 | AH118: TO | AI118: X | AJ118: 4 | AK118: V4 | AL118: 20240806 | AM118: D845-900006074-67241102-10167749-4
A119: 900006074D8456500698910000617 | B119: 4600044538-1250 | C119: 4600044538 | D119: 1250 | E119: MXPO | F119: MXL | G119: 900006074 | H119: SF TP-ED- GRAMOL SLP | I119: 5005459 | J119: TRITURADOS GRAMOL SA DE CV | K119: Z04 | L119: (AP) 30 Dias | M119: 10000617 | N119: Arena Triturada Caliza Malla 5 | O119: D845 | P119: MX-CED. SLP | Q119: 20190415 | R119: 20291231 | S119: 20251230 | T119: 20301231 | U119: 486 | V119: MXN | W119: TN | X119: 323 | Y119: MXN | Z119: TN | AA119: 65006989 | AB119: (P) PREMEZCLADOS CONCRECO S.A. DE C | AC119: 56103638 | AD119: 6622351540 | AE119: 4 | AF119: ENTREGA DIRECTA | AG119: 1 | AH119: TO | AI119: X | AJ119: 4 | AK119: V4 | AL119: 20251230 | AM119: D845-900006074-65006989-10000617-4
A120: 900006074D8456500698910000656 | B120: 4600044538-1260 | C120: 4600044538 | D120: 1260 | E120: MXPO | F120: MXL | G120: 900006074 | H120: SF TP-ED- GRAMOL SLP | I120: 5005459 | J120: TRITURADOS GRAMOL SA DE CV | K120: Z04 | L120: (AP) 30 Dias | M120: 10000656 | N120: Grava Triturada Caliza 10 mm - 3/8" | O120: D845 | P120: MX-CED. SLP | Q120: 20190415 | R120: 20291231 | S120: 20251230 | T120: 20301231 | U120: 486 | V120: MXN | W120: TN | X120: 323 | Y120: MXN | Z120: TN | AA120: 65006989 | AB120: (P) PREMEZCLADOS CONCRECO S.A. DE C | AC120: 56103637 | AD120: 6622351540 | AE120: 4 | AF120: ENTREGA DIRECTA | AG120: 1 | AH120: TO | AI120: X | AJ120: 4 | AK120: V4 | AL120: 20251230 | AM120: D845-900006074-65006989-10000656-4
A121: 900009255D84510000617 | B121: 4600071321-10 | C121: 4600071321 | D121: 10 | E121: MXPO | F121: MXL | G121: 900009255 | H121: SF TP-GRAMOL CLIENTES FORANEOS | I121: 5005459 | J121: TRITURADOS GRAMOL SA DE CV | K121: Z04 | L121: (AP) 30 Dias | M121: 10000617 | N121: Arena Triturada Caliza Malla 5 | O121: D845 | P121: MX-CED. SLP | Q121: 20250604 | R121: 20301231 | S121: 20260211 | T121: 20301231 | U121: 179 | V121: MXN | W121: TN | X121: 0 | Y121: MXN | Z121: TN | AC121: 56103638 | AD121: 6622351540 | AE121: 1 | AF121: ENTREGADO | AG121: 1 | AH121: TO | AI121: X | AJ121: 4 | AK121: V4 | AL121: 20260219 | AM121: D845-900009255-10000617
A122: 900009255D84510000578 | B122: 4600071321-40 | C122: 4600071321 | D122: 40 | E122: MXPO | F122: MXL | G122: 900009255 | H122: SF TP-GRAMOL CLIENTES FORANEOS | I122: 5005459 | J122: TRITURADOS GRAMOL SA DE CV | K122: Z04 | L122: (AP) 30 Dias | M122: 10000578 | N122: Grava Triturada Caliza 20 mm - 3/4" | O122: D845 | P122: MX-CED. SLP | Q122: 20250604 | R122: 20301231 | S122: 20260211 | T122: 20301231 | U122: 165 | V122: MXN | W122: TN | X122: 0 | Y122: MXN | Z122: TN | AC122: 56103637 | AD122: 6622351540 | AE122: 1 | AF122: ENTREGADO | AG122: 1 | AH122: TO | AI122: X | AJ122: 4 | AK122: V4 | AL122: 20260219 | AM122: D845-900009255-10000578
A123: 900006074D8456714159410167749 | B123: 4600044538-720 | C123: 4600044538 | D123: 720 | E123: MXPO | F123: MXL | G123: 900006074 | H123: SF TP-ED- GRAMOL SLP | I123: 5005459 | J123: TRITURADOS GRAMOL SA DE CV | K123: Z04 | L123: (AP) 30 Dias | M123: 10167749 | N123: BASE H CALIZA 1 1/2" A FINOS ESPECIAL | O123: D845 | P123: MX-CED. SLP | Q123: 20190415 | R123: 20291231 | S123: 20230418 | T123: 20281231 | U123: 192 | V123: MXN | W123: TN | X123: 70 | Y123: MXN | Z123: TN | AA123: 67141594 | AB123: SUBESTACIÓN CFE | AC123: 56103590 | AD123: 6622351540 | AE123: 4 | AF123: ENTREGA DIRECTA | AG123: 1 | AH123: TO | AI123: X | AJ123: 4 | AK123: V4 | AL123: 20230920 | AM123: D845-900006074-67141594-10167749-4
A124: 900009256D8456736750610000656 | B124: 4600072103-20 | C124: 4600072103 | D124: 20 | E124: MXPO | F124: MXL | G124: 900009256 | H124: SF TP-ED GRAMOL CLIENTES FORANEOS | I124: 5005459 | J124: TRITURADOS GRAMOL SA DE CV | K124: Z04 | L124: (AP) 30 Dias | M124: 10000656 | N124: Grava Triturada Caliza 10 mm - 3/8" | O124: D845 | P124: MX-CED. SLP | Q124: 20260320 | R124: 20301231 | S124: 20260320 | T124: 20301231 | U124: 291 | V124: MXN | W124: TN | X124: 115 | Y124: MXN | Z124: TN | AA124: 67367506 | AB124: P5 VILLA DE REYES | AC124: 56103637 | AD124: 6622351540 | AE124: 4 | AF124: ENTREGA DIRECTA | AG124: 1 | AH124: TO | AI124: X | AJ124: 4 | AK124: V4 | AL124: 20260320 | AM124: D845-900009256-67367506-10000656-4
A125: 900009256D8456736750610000536 | B125: 4600072103-40 | C125: 4600072103 | D125: 40 | E125: MXPO | F125: MXL | G125: 900009256 | H125: SF TP-ED GRAMOL CLIENTES FORANEOS | I125: 5005459 | J125: TRITURADOS GRAMOL SA DE CV | K125: Z04 | L125: (AP) 30 Dias | M125: 10000536 | N125: Grava Triturada Caliza 40 mm - 1 1/2" | O125: D845 | P125: MX-CED. SLP | Q125: 20260320 | R125: 20301231 | S125: 20260320 | T125: 20301231 | U125: 280 | V125: MXN | W125: TN | X125: 115 | Y125: MXN | Z125: TN | AA125: 67367506 | AB125: P5 VILLA DE REYES | AC125: 56103637 | AD125: 6622351540 | AE125: 4 | AF125: ENTREGA DIRECTA | AG125: 1 | AH125: TO | AI125: X | AJ125: 4 | AK125: V4 | AL125: 20260320 | AM125: D845-900009256-67367506-10000536-4
A126: 900009255D84510058507 | B126: 4600071321-60 | C126: 4600071321 | D126: 60 | E126: MXPO | F126: MXL | G126: 900009255 | H126: SF TP-GRAMOL CLIENTES FORANEOS | I126: 5005459 | J126: TRITURADOS GRAMOL SA DE CV | K126: Z04 | L126: (AP) 30 Dias | M126: 10058507 | N126: Base H Triturada Basalto 1 1/2" a Finos | O126: D845 | P126: MX-CED. SLP | Q126: 20250604 | R126: 20301231 | S126: 20251209 | T126: 20301231 | U126: 160 | V126: MXN | W126: TN | X126: 0 | Y126: MXN | Z126: TN | AC126: 56103590 | AD126: 6622351540 | AE126: 1 | AF126: ENTREGADO | AG126: 1 | AH126: TO | AI126: X | AJ126: 4 | AK126: V4 | AL126: 20251219 | AM126: D845-900009255-10058507
A127: 900009256D8456736750610000578 | B127: 4600072103-30 | C127: 4600072103 | D127: 30 | E127: MXPO | F127: MXL | G127: 900009256 | H127: SF TP-ED GRAMOL CLIENTES FORANEOS | I127: 5005459 | J127: TRITURADOS GRAMOL SA DE CV | K127: Z04 | L127: (AP) 30 Dias | M127: 10000578 | N127: GRAVA TRITURADA CALIZA 20 MM - 3/4" | O127: D845 | P127: MX-CED. SLP | Q127: 20260320 | R127: 20301231 | S127: 20260320 | T127: 20301231 | U127: 280 | V127: MXN | W127: TN | X127: 115 | Y127: MXN | Z127: TN | AA127: 67367506 | AB127: P5 VILLA DE REYES | AC127: 56103637 | AD127: 6622351540 | AE127: 4 | AF127: ENTREGA DIRECTA | AG127: 1 | AH127: TO | AI127: X | AJ127: 4 | AK127: V4 | AL127: 20260320 | AM127: D845-900009256-67367506-10000578-4
A128: 900009256D8456736750610000617 | B128: 4600072103-10 | C128: 4600072103 | D128: 10 | E128: MXPO | F128: MXL | G128: 900009256 | H128: SF TP-ED GRAMOL CLIENTES FORANEOS | I128: 5005459 | J128: TRITURADOS GRAMOL SA DE CV | K128: Z04 | L128: (AP) 30 Dias | M128: 10000617 | N128: Arena Triturada Caliza Malla 5 | O128: D845 | P128: MX-CED. SLP | Q128: 20260320 | R128: 20301231 | S128: 20260320 | T128: 20301231 | U128: 294 | V128: MXN | W128: TN | X128: 115 | Y128: MXN | Z128: TN | AA128: 67367506 | AB128: P5 VILLA DE REYES | AC128: 56103638 | AD128: 6622351540 | AE128: 4 | AF128: ENTREGA DIRECTA | AG128: 1 | AH128: TO | AI128: X | AJ128: 4 | AK128: V4 | AL128: 20260320 | AM128: D845-900009256-67367506-10000617-4
A129: 900006074D8456727749410000617 | B129: 4600044538-980 | C129: 4600044538 | D129: 980 | E129: MXPO | F129: MXL | G129: 900006074 | H129: SF TP-ED- GRAMOL SLP | I129: 5005459 | J129: TRITURADOS GRAMOL SA DE CV | K129: Z04 | L129: (AP) 30 Dias | M129: 10000617 | N129: Arena Triturada Caliza Malla 5 | O129: D845 | P129: MX-CED. SLP | Q129: 20190415 | R129: 20291231 | S129: 20240923 | T129: 20291231 | U129: 262 | V129: MXN | W129: TN | X129: 102 | Y129: MXN | Z129: TN | AA129: 67277494 | AB129: C1502 PRIVADA LA JOYA EV | AC129: 56103638 | AD129: 6622351540 | AE129: 4 | AF129: ENTREGA DIRECTA | AG129: 1 | AH129: TO | AI129: X | AJ129: 4 | AK129: V4 | AL129: 20240930 | AM129: D845-900006074-67277494-10000617-4
A130: 900006074D8456731378310167749 | B130: 4600044538-1030 | C130: 4600044538 | D130: 1030 | E130: MXPO | F130: MXL | G130: 900006074 | H130: SF TP-ED- GRAMOL SLP | I130: 5005459 | J130: TRITURADOS GRAMOL SA DE CV | K130: Z04 | L130: (AP) 30 Dias | M130: 10167749 | N130: BASE H CALIZA 1 1/2" A FINOS ESPECIAL | O130: D845 | P130: MX-CED. SLP | Q130: 20190415 | R130: 20291231 | S130: 20250325 | T130: 20301231 | U130: 250 | V130: MXN | W130: TN | X130: 67 | Y130: MXN | Z130: TN | AA130: 67313783 | AB130: ACCESO GASOLINERA EJE 140 WTC/LAJA | AC130: 56103590 | AD130: 6622351540 | AE130: 4 | AF130: ENTREGA DIRECTA | AG130: 1 | AH130: TO | AI130: X | AJ130: 4 | AK130: V4 | AL130: 20250326 | AM130: D845-900006074-67313783-10167749-4
A131: 900006074D8456727749410167749 | B131: 4600044538-940 | C131: 4600044538 | D131: 940 | E131: MXPO | F131: MXL | G131: 900006074 | H131: SF TP-ED- GRAMOL SLP | I131: 5005459 | J131: TRITURADOS GRAMOL SA DE CV | K131: Z04 | L131: (AP) 30 Dias | M131: 10167749 | N131: BASE H CALIZA 1 1/2" A FINOS ESPECIAL | O131: D845 | P131: MX-CED. SLP | Q131: 20190415 | R131: 20291231 | S131: 20240813 | T131: 20291231 | U131: 255 | V131: MXN | W131: TN | X131: 102 | Y131: MXN | Z131: TN | AA131: 67277494 | AB131: C1502 PRIVADA LA JOYA EV | AC131: 56103590 | AD131: 6622351540 | AE131: 4 | AF131: ENTREGA DIRECTA | AG131: 1 | AH131: TO | AI131: X | AJ131: 4 | AK131: V4 | AL131: 20240910 | AM131: D845-900006074-67277494-10167749-4
A132: 900006124D84510000774 | B132: 4600044703-20 | C132: 4600044703 | D132: 20 | E132: MXPO | F132: MXL | G132: 900006124 | H132: SF TP- INCASA | I132: 5001208 | J132: INDUSTRIALIZADORA DE CALIZA SA DE | K132: Z04 | L132: (AP) 30 Dias | M132: 10000774 | N132: Grava Triturada Caliza 40 mm - 1 1/2" | O132: D845 | P132: MX-CED. SLP | Q132: 20190501 | R132: 20291231 | S132: 20210308 | T132: 20291231 | U132: 87 | V132: MXN | W132: TN | AC132: 56103637 | AD132: 6622351540 | AE132: 1 | AF132: ENTREGADO | AG132: 1 | AH132: TO | AI132: X | AJ132: 4 | AK132: V4 | AL132: 20230920 | AM132: D845-900006124-10000774
