Workbook

Sheet Materiales,canteras
A1: No. Cantera | B1: Nombre Cantera | C1: Material | D1: Denominación | E1: PV
A2: D813 | B2: MX-CANTERA SAN VICENTE | C2: 10000252 | D2: Grava Triturada Andesita 10 mm | E2: 1.234
A3: D813 | B3: MX-CANTERA SAN VICENTE | C3: 10000253 | D3: Grava Triturada Andesita 20 mm | E3: 1.385
A4: D813 | B4: MX-CANTERA SAN VICENTE | C4: 10000255 | D4: Arena Triturada Andesita Malla | E4: 1.535
A5: D813 | B5: MX-CANTERA SAN VICENTE | C5: 10001091 | D5: Balasto Triturado Andesita 150 | E5: 1.4
A6: D813 | B6: MX-CANTERA SAN VICENTE | C6: 10002350 | D6: Grava Triturada Andesita 10mm- | E6: 1.246
A7: D813 | B7: MX-CANTERA SAN VICENTE | C7: 10029946 | D7: Arena Triturada Andesita Malla | E7: 1.494
A8: D813 | B8: MX-CANTERA SAN VICENTE | C8: 10032959 | D8: Grava Triturada Andesita 50 mm | E8: 1.279
A9: D813 | B9: MX-CANTERA SAN VICENTE | C9: 10000305 | D9: Tepetate Clasificado Tierra | E9: 1.3
A10: D861 | B10: MX-CANTERA QUERETARO | C10: 10000229 | D10: Grava Triturada Basalto 10 mm | E10: 1.522
A11: D861 | B11: MX-CANTERA QUERETARO | C11: 10000231 | D11: Grava Triturada Basalto 20 mm | E11: 1.565
A12: D861 | B12: MX-CANTERA QUERETARO | C12: 10000233 | D12: Grava Triturada Basalto 40 mm | E12: 1.456
A13: D861 | B13: MX-CANTERA QUERETARO | C13: 10000311 | D13: Arena Triturada Basalto Malla | E13: 1.651
... A111: D917 | B111: MX-CANTERA VALLES AGG | C111: 10248659 | D111: ARENA NO. 4 | E111: 1.673
A112: D824 | B112: MX-CANTERA LEON | C112: 10023108 | D112: =VLOOKUP(C112,'[1]Precio Base '!$D$2:$E$22,2,FALSE) -> Base H Triturada Basalto 1 1/2" a Finos | E112: 1.969
A113: DU07 | B113: MX-CANCÚN III | C113: 10000195 | D113: GRAVA TRITURADA CALIZA 20 MM - 3/4"–CAPA | E113: 1.201
A114: D824 | B114: MX-CANTERA LEON | C114: 10001077 | D114: Crudo Basalto | E114: 1.35
A115: D824 | B115: MX-CANTERA LEON | C115: 10191647 | D115: BALASTO 6# A 3# | E115: 1.441
A116: D824 | B116: MX-CANTERA LEON | C116: 10000289 | D116: Desperdicio Triturado Basalto | E116: 1.55
A117: D816 | B117: MX-CANTERA MONTERREY | C117: 10000248 | D117: Sub-base Triturado Caliza 1 1/2" a Finos | E117: 1.821
A118: D816 | B118: MX-CANTERA MONTERREY | C118: 10269042 | D118: NO CLASIFICADO BALASTO B9 | E118: 1.456
A119: D893 | B119: MX-CANTERA TIJUANA II | C119: 10038957 | D119: Arena Triturada Caliza Block | E119: 1.687
A120: D902 | B120: MX-CALKINI | C120: 10269105 | D120: BALASTO DE 2 ½” DESPERDICIO | E120: 1.494
A121: D816 | B121: MX-CANTERA MONTERREY | C121: 10001222 | D121: Mixto Grava 3/4 - Arena 4 | E121: 1.613
A122: D879 | B122: EPV AGG TAMUIN | C122: 10258182 | D122: SOBRETAMAÑO ROCA NATURAL DE 0.5 A 0.80TN | E122: 1.625
A123: D879 | B123: EPV AGG TAMUIN | C123: 10258183 | D123: SOBRETAMAÑO ROCA NATURAL DE 0.8 A 1.2 TN | E123: 1.625
A124: D879 | B124: EPV AGG TAMUIN | C124: 10258184 | D124: SOBRETAMAÑO ROCA NATURAL DE 0.2 A 0.56TN | E124: 1.625
... A131: D816 | B131: MX-CANTERA MONTERREY | C131: 10148824 | D131: BALASTO PIEDRA CALIZA 4"-6" | E131: 1.5
C132: 10038955 | D132: Base H Triturada Caliza 1 1/2" a Finos | E132: 1.925
A133: D864 | B133: MX-CANTERA CERRO JARDIN | C133: 10279531 | D133: CRUDO CALIZA TIPO B | E133: 1.5

Sheet NO MODIFICAR
A1: No. Cantera | B1: Nombre Cantera | F1: No. Cantera | G1: Nombre Cantera | J1: Nombre Cantera | K1: No. Cantera
A2: D813 | B2: MX-CANTERA SAN VICENTE | C2: c | D2: CENTRO | E2: TN | F2: D813 | G2: MX-CANTERA SAN VICENTE | H2: CENTRO | J2: MX-CANTERA SAN VICENTE | K2: D813
A3: D816 | B3: MX-CANTERA MONTERREY | C3: n | D3: SURESTE | E3: M3 | F3: D861 | G3: MX-CANTERA QUERETARO | H3: CENTRO | J3: MX-CANTERA QUERETARO | K3: D861
A4: D824 | B4: MX-CANTERA LEON | C4: n | F4: D864 | G4: MX-CANTERA CERRO JARDIN | H4: CENTRO | J4: MX-CANTERA CERRO JARDIN | K4: D864
A5: D852 | B5: MX-CANTERA TORREON II | C5: n | F5: D873 | G5: MX-VIRTUAL VALLEJO | H5: CENTRO | J5: MX-VIRTUAL VALLEJO | K5: D873
A6: D861 | B6: MX-CANTERA QUERETARO | C6: c | F6: D902 | G6: MX-CALKINI | H6: SURESTE | J6: MX-CALKINI | K6: D902
A7: D863 | B7: MX-CANTERA TAMUIN | C7: n | F7: DU07 | G7: MX-CANCÚN III | H7: SURESTE | J7: MX-CANCÚN III | K7: DU07
A8: D864 | B8: MX-CANTERA CERRO JARDIN | C8: c | F8: D816 | G8: MX-CANTERA MONTERREY | H8: NORESTE | J8: MX-CANTERA MONTERREY | K8: D816
A9: D866 | B9: MX-CANTERA PONCITLAN | C9: n | F9: D893 | G9: CANTERA TIJUANA II | H9: NORESTE | J9: CANTERA TIJUANA II | K9: D893
A10: D873 | B10: MX-VIRTUAL VALLEJO | C10: c | F10: D917 | G10: MX-CANTERA VALLES AGG | H10: NORESTE | J10: MX-CANTERA VALLES AGG | K10: D917
A11: D893 | B11: MX-CANTERA TIJUANA II | C11: n | F11: D824 | G11: MX-CANTERA LEON | H11: NORESTE | J11: MX-CANTERA PONCITLAN | K11: D866
A12: D902 | B12: MX-CALKINI | C12: c | F12: D866 | G12: MX-CANTERA PONCITLAN | H12: NORESTE | J12: MX-CANTERA TORREON II | K12: D852
A13: D917 | B13: MX-CANTERA VALLES AGG | C13: n | F13: D852 | G13: MX-CANTERA TORREON II | H13: NORESTE | J13: MX-CANTERA LEON | K13: D824
A14: DU07 | B14: MX-CANCÚN III | C14: c | F14: D863 | G14: MX-CANTERA TAMUIN | H14: NORESTE | J14: MX-CANTERA TAMUIN | K14: D863
F15: D815 | G15: CANTERA TESISTAN | H15: NORESTE
F16: D879 | G16: EPV AGG TAMUIN | H16: NORESTE

Sheet Formato Alta Precio
A1: No. | B1: Mes de solicitud | C1: Llave | D1: Centro | E1: Nombre planta | F1: Nueva ZONA | G1: Dest.mercancías | H1: Nombre del Destinatario | I1: Material | J1: Nombre de Material | K1: PV | L1: Precio solicitado | M1: UM | N1: Válido de | O1: Validez a | P1: desc prod | Q1: desc Tamaño | R1: Desc Contado | S1: Precio de lista | T1: GAP | U1: Precio Final Sistema | V1: Flete | W1: Modalidad (01 Entregado,02 Recogido) | X1: Precio Total | Y1: VOBO SOLICITADO | Z1: Precio Referencia | AA1: % de Descuento | AB1: Validación 1 | AC1: Validación 2 | AD1: Observaciones
A2: 1 | C2: =_xlfn.CONCAT($C$1,D2,G2,I2,W2) -> LlaveD86466883318100010731 | D2: =VLOOKUP(E2,'NO MODIFICAR'!J:K,2,0) -> D864 | E2: MX-CANTERA CERRO JARDIN | F2: =VLOOKUP(D2,'NO MODIFICAR'!F:H,3,0) -> CENTRO | G2: 66883318 | H2: CONCRETOS HIDALGO | I2: 10001073 | J2: =VLOOKUP(I2,'Materiales,canteras'!C:D,2,0) -> Arena Triturada Caliza Malla 4 | K2: =VLOOKUP(I2,'Materiales,canteras'!C:E,3,0) -> 1.56 | L2: 115.46 | M2: TN | N2: =TODAY() -> 46267 | O2: 31.12.9999 | S2: 150 | T2: =L2-S2 -> -34.54 | U2: =L2 -> 115.46 | V2: 76 | W2: 1 | X2: =V2+U2 -> 191.46 | Y2: =IF(+VLOOKUP(I2,P.Referencia!E:S,3,FALSE)<=L2,"Champion","Gerente") -> #N/A | Z2: =VLOOKUP(I2,P.Referencia!E:S,3,0) -> #N/A | AA2: =(Z2-U2)/U2 -> #N/A | AB2: =U2*AA2 -> #N/A | AC2: =U2+AB2 -> #N/A
A3: 2 | C3: =_xlfn.CONCAT($C$1,D3,G3,I3,W3) -> LlaveD86466883318100002361 | D3: =VLOOKUP(E3,'NO MODIFICAR'!J:K,2,0) -> D864 | E3: MX-CANTERA CERRO JARDIN | F3: =VLOOKUP(D3,'NO MODIFICAR'!F:H,3,0) -> CENTRO | G3: 66883318 | H3: CONCRETOS HIDALGO | I3: 10000236 | J3: =VLOOKUP(I3,'Materiales,canteras'!C:D,2,0) -> Grava Triturada Caliza 10 mm - | K3: =VLOOKUP(I3,'Materiales,canteras'!C:E,3,0) -> 1.41 | L3: 145 | M3: TN | N3: =TODAY() -> 46267 | O3: 31.12.9999 | T3: =L3-S3 -> 145 | U3: =L3 -> 145 | V3: 76 | W3: 1 | X3: =V3+U3 -> 221 | Y3: =IF(+VLOOKUP(I3,P.Referencia!E:S,3,FALSE)<=L3,"Champion","Gerente") -> #N/A | Z3: =VLOOKUP(I3,P.Referencia!E:S,3,0) -> #N/A | AA3: =(Z3-U3)/U3 -> #N/A | AB3: =U3*AA3 -> #N/A | AC3: =U3+AB3 -> #N/A
A4: 3 | C4: =_xlfn.CONCAT($C$1,D4,G4,I4,W4) -> LlaveD86466883318100002401 | D4: =VLOOKUP(E4,'NO MODIFICAR'!J:K,2,0) -> D864 | E4: MX-CANTERA CERRO JARDIN | F4: =VLOOKUP(D4,'NO MODIFICAR'!F:H,3,0) -> CENTRO | G4: 66883318 | H4: CONCRETOS HIDALGO | I4: 10000240 | J4: =VLOOKUP(I4,'Materiales,canteras'!C:D,2,0) -> Grava Triturada Caliza 20 mm - | K4: =VLOOKUP(I4,'Materiales,canteras'!C:E,3,0) -> 1.462 | L4: 145 | M4: TN | N4: =TODAY() -> 46267 | O4: 31.12.9999 | T4: =L4-S4 -> 145 | U4: =L4 -> 145 | V4: 76 | W4: 1 | X4: =V4+U4 -> 221 | Y4: =IF(+VLOOKUP(I4,P.Referencia!E:S,3,FALSE)<=L4,"Champion","Gerente") -> #N/A | Z4: =VLOOKUP(I4,P.Referencia!E:S,3,0) -> #N/A | AA4: =(Z4-U4)/U4 -> #N/A | AB4: =U4*AA4 -> #N/A | AC4: =U4+AB4 -> #N/A
A5: 4 | C5: =_xlfn.CONCAT($C$1,D5,G5,I5,W5) -> LlaveD86466883318100002691 | D5: =VLOOKUP(E5,'NO MODIFICAR'!J:K,2,0) -> D864 | E5: MX-CANTERA CERRO JARDIN | F5: =VLOOKUP(D5,'NO MODIFICAR'!F:H,3,0) -> CENTRO | G5: 66883318 | H5: CONCRETOS HIDALGO | I5: 10000269 | J5: =VLOOKUP(I5,'Materiales,canteras'!C:D,2,0) -> Grava Triturada Caliza 13 mm - | K5: =VLOOKUP(I5,'Materiales,canteras'!C:E,3,0) -> 1.423 | L5: 161.2 | M5: TN | N5: =TODAY() -> 46267 | O5: 31.12.9999 | T5: =L5-S5 -> 161.2 | U5: =L5 -> 161.2 | V5: 76 | W5: 1 | X5: =V5+U5 -> 237.2 | Y5: =IF(+VLOOKUP(I5,P.Referencia!E:S,3,FALSE)<=L5,"Champion","Gerente") -> #N/A | Z5: =VLOOKUP(I5,P.Referencia!E:S,3,0) -> #N/A | AA5: =(Z5-U5)/U5 -> #N/A | AB5: =U5*AA5 -> #N/A | AC5: =U5+AB5 -> #N/A
A6: 5 | C6: =_xlfn.CONCAT($C$1,D6,G6,I6,W6) -> LlaveD86466883318100010741 | D6: =VLOOKUP(E6,'NO MODIFICAR'!J:K,2,0) -> D864 | E6: MX-CANTERA CERRO JARDIN | F6: =VLOOKUP(D6,'NO MODIFICAR'!F:H,3,0) -> CENTRO | G6: 66883318 | H6: CONCRETOS HIDALGO | I6: 10001074 | J6: =VLOOKUP(I6,'Materiales,canteras'!C:D,2,0) -> Grava Triturada Caliza 40 mm - | K6: =VLOOKUP(I6,'Materiales,canteras'!C:E,3,0) -> 1.4 | L6: 147 | M6: TN | N6: =TODAY() -> 46267 | O6: 31.12.9999 | T6: =L6-S6 -> 147 | U6: =L6 -> 147 | V6: 76 | W6: 1 | X6: =V6+U6 -> 223 | Y6: =IF(+VLOOKUP(I6,P.Referencia!E:S,3,FALSE)<=L6,"Champion","Gerente") -> #N/A | Z6: =VLOOKUP(I6,P.Referencia!E:S,3,0) -> #N/A | AA6: =(Z6-U6)/U6 -> #N/A | AB6: =U6*AA6 -> #N/A | AC6: =U6+AB6 -> #N/A
A7: 6 | C7: =_xlfn.CONCAT($C$1,D7,G7,I7,W7) -> LlaveD86167316915100002902 | D7: =VLOOKUP(E7,'NO MODIFICAR'!J:K,2,0) -> D861 | E7: MX-CANTERA QUERETARO | F7: =VLOOKUP(D7,'NO MODIFICAR'!F:H,3,0) -> CENTRO | G7: 67316915 | H7: PARQUE PYME RECOGIDO | I7: 10000290 | J7: =VLOOKUP(I7,'Materiales,canteras'!C:D,2,0) -> Polvos Triturado Basalto 3/4" | K7: =VLOOKUP(I7,'Materiales,canteras'!C:E,3,0) -> 1.372 | L7: 1.5 | M7: TN | N7: =TODAY() -> 46267 | O7: 31.12.9999 | S7: 25 | T7: =L7-S7 -> -23.5 | U7: =L7 -> 1.5 | V7: 0 | W7: 2 | X7: =V7+U7 -> 1.5 | Y7: =IF(+VLOOKUP(I7,P.Referencia!E:S,3,FALSE)<=L7,"Champion","Gerente") -> #N/A | Z7: =VLOOKUP(I7,P.Referencia!E:S,3,0) -> #N/A | AA7: =(Z7-U7)/U7 -> #N/A | AB7: =U7*AA7 -> #N/A | AC7: =U7+AB7 -> #N/A | AD7: PENDIENTE VOBO DE LALO LÓPEZ | AE7: CORREO SANDRA
A8: 7 | C8: =_xlfn.CONCAT($C$1,D8,G8,I8,W8) -> LlaveD86166781275100002901 | D8: =VLOOKUP(E8,'NO MODIFICAR'!J:K,2,0) -> D861 | E8: MX-CANTERA QUERETARO | F8: =VLOOKUP(D8,'NO MODIFICAR'!F:H,3,0) -> CENTRO | G8: 66781275 | H8: ASFALTO CAÑADA | I8: 10000290 | J8: =VLOOKUP(I8,'Materiales,canteras'!C:D,2,0) -> Polvos Triturado Basalto 3/4" | K8: =VLOOKUP(I8,'Materiales,canteras'!C:E,3,0) -> 1.372 | L8: 1 | M8: TN | N8: =TODAY() -> 46267 | O8: 31.12.9999 | S8: 25 | T8: =L8-S8 -> -24 | U8: =L8 -> 1 | V8: 66.49 | W8: 1 | X8: =V8+U8 -> 67.49 | Y8: =IF(+VLOOKUP(I8,P.Referencia!E:S,3,FALSE)<=L8,"Champion","Gerente") -> #N/A | Z8: =VLOOKUP(I8,P.Referencia!E:S,3,0) -> #N/A | AA8: =(Z8-U8)/U8 -> #N/A | AB8: =U8*AA8 -> #N/A | AC8: =U8+AB8 -> #N/A | AD8: PENDIENTE VOBO DE LALO LÓPEZ | AE8: CORREO CARLOS
A9: 8 | C9: =_xlfn.CONCAT($C$1,D9,G9,I9,W9) -> LlaveD86166617693100014501 | D9: =VLOOKUP(E9,'NO MODIFICAR'!J:K,2,0) -> D861 | E9: MX-CANTERA QUERETARO | F9: =VLOOKUP(D9,'NO MODIFICAR'!F:H,3,0) -> CENTRO | G9: 66617693 | H9: LA ROCA MAYORAZGO | I9: 10001450 | J9: =VLOOKUP(I9,'Materiales,canteras'!C:D,2,0) -> Base Hidraúlica Basalto de 1 /1/2 | K9: =VLOOKUP(I9,'Materiales,canteras'!C:E,3,0) -> 1.749 | L9: 218.28 | M9: TN | N9: =TODAY() -> 46267 | O9: 31.12.9999 | S9: 260 | T9: =L9-S9 -> -41.72 | U9: =L9 -> 218.28 | V9: 70 | W9: 1 | X9: =V9+U9 -> 288.28 | Y9: Gerente | Z9: 222 | AA9: =(Z9-U9)/U9 -> 0.017042331 | AB9: =U9*AA9 -> 3.72 | AC9: =U9+AB9 -> 222 | AD9: PENDIENTE VOBO DE JORGE/ RICARDO
A10: 9 | C10: =_xlfn.CONCAT($C$1,D10,G10,I10,W10) -> LlaveD86166617693100002311 | D10: =VLOOKUP(E10,'NO MODIFICAR'!J:K,2,0) -> D861 | E10: MX-CANTERA QUERETARO | F10: =VLOOKUP(D10,'NO MODIFICAR'!F:H,3,0) -> CENTRO | G10: 66617693 | H10: LA ROCA MAYORAZGO | I10: 10000231 | J10: =VLOOKUP(I10,'Materiales,canteras'!C:D,2,0) -> Grava Triturada Basalto 20 mm | K10: =VLOOKUP(I10,'Materiales,canteras'!C:E,3,0) -> 1.565 | L10: 203.9 | M10: TN | N10: =TODAY() -> 46267 | O10: 31.12.9999 | S10: 280 | T10: =L10-S10 -> -76.1 | U10: =L10 -> 203.9 | V10: 75.58 | W10: 1 | X10: =V10+U10 -> 279.48 | Y10: =IF(+VLOOKUP(I10,P.Referencia!E:S,3,FALSE)<=L10,"Champion","Gerente") -> #N/A | Z10: =VLOOKUP(I10,P.Referencia!E:S,3,0) -> #N/A | AA10: =(Z10-U10)/U10 -> #N/A | AB10: =U10*AA10 -> #N/A | AC10: =U10+AB10 -> #N/A | AD10: PENDIENTE VOBO DE JORGE/ RICARDO
A11: 10 | C11: =_xlfn.CONCAT($C$1,D11,G11,I11,W11) -> LlaveD81365014664100002551 | D11: =VLOOKUP(E11,'NO MODIFICAR'!J:K,2,0) -> D813 | E11: MX-CANTERA SAN VICENTE | F11: =VLOOKUP(D11,'NO MODIFICAR'!F:H,3,0) -> CENTRO | G11: 65014664 | H11: OBR-AGR IBM (DLC) | I11: 10000255 | J11: =VLOOKUP(I11,'Materiales,canteras'!C:D,2,0) -> Arena Triturada Andesita Malla | K11: =VLOOKUP(I11,'Materiales,canteras'!C:E,3,0) -> 1.535 | N11: =TODAY() -> 46267 | O11: 31.12.9999 | T11: =L11-S11 -> 0 | U11: =L11 -> 0 | V11: 58.73 | W11: 1 | X11: =V11+U11 -> 58.73 | Y11: =IF(+VLOOKUP(I11,P.Referencia!E:S,3,FALSE)<=L11,"Champion","Gerente") -> #N/A | Z11: =VLOOKUP(I11,P.Referencia!E:S,3,0) -> #N/A | AA11: =(Z11-U11)/U11 -> #N/A | AB11: =U11*AA11 -> #N/A | AC11: =U11+AB11 -> #N/A | AD11: SOLO PIDEN CAMBIO EN FLETE
A12: 11 | C12: =_xlfn.CONCAT($C$1,D12,G12,I12,W12) -> LlaveD86466828114100002362 | D12: =VLOOKUP(E12,'NO MODIFICAR'!J:K,2,0) -> D864 | E12: MX-CANTERA CERRO JARDIN | F12: =VLOOKUP(D12,'NO MODIFICAR'!F:H,3,0) -> CENTRO | G12: 66828114 | H12: CEMENTOS MOCTEZUMA | I12: 10000236 | J12: =VLOOKUP(I12,'Materiales,canteras'!C:D,2,0) -> Grava Triturada Caliza 10 mm - | K12: =VLOOKUP(I12,'Materiales,canteras'!C:E,3,0) -> 1.41 | L12: 157.2 | M12: TN | N12: =TODAY() -> 46267 | O12: 31.12.9999 | S12: 240 | T12: =L12-S12 -> -82.8 | U12: =L12 -> 157.2 | V12: 0 | W12: 2 | X12: =V12+U12 -> 157.2 | Y12: =IF(+VLOOKUP(I12,P.Referencia!E:S,3,FALSE)<=L12,"Champion","Gerente") -> #N/A | Z12: =VLOOKUP(I12,P.Referencia!E:S,3,0) -> #N/A | AA12: =(Z12-U12)/U12 -> #N/A | AB12: =U12*AA12 -> #N/A | AC12: =U12+AB12 -> #N/A
A13: 12 | C13: =_xlfn.CONCAT($C$1,D13,G13,I13,W13) -> LlaveD86167198586100031532 | D13: =VLOOKUP(E13,'NO MODIFICAR'!J:K,2,0) -> D861 | E13: MX-CANTERA QUERETARO | F13: =VLOOKUP(D13,'NO MODIFICAR'!F:H,3,0) -> CENTRO | G13: 67198586 | H13: CASETA | I13: 10003153 | J13: =VLOOKUP(I13,'Materiales,canteras'!C:D,2,0) -> Grava Triturada Basalto 13 mm | K13: =VLOOKUP(I13,'Materiales,canteras'!C:E,3,0) -> 1.546 | L13: 190 | M13: TN | N13: =TODAY() -> 46267 | O13: 31.12.9999 | S13: 270 | T13: =L13-S13 -> -80 | U13: =L13 -> 190 | V13: 0 | W13: 2 | X13: =V13+U13 -> 190 | Y13: =IF(+VLOOKUP(I13,P.Referencia!E:S,3,FALSE)<=L13,"Champion","Gerente") -> #N/A | Z13: =VLOOKUP(I13,P.Referencia!E:S,3,0) -> #N/A | AA13: =(Z13-U13)/U13 -> #N/A | AB13: =U13*AA13 -> #N/A | AC13: =U13+AB13 -> #N/A
A14: 13 | C14: =_xlfn.CONCAT($C$1,D14,G14,I14,W14) -> LlaveD86167198586100002312 | D14: =VLOOKUP(E14,'NO MODIFICAR'!J:K,2,0) -> D861 | E14: MX-CANTERA QUERETARO | F14: =VLOOKUP(D14,'NO MODIFICAR'!F:H,3,0) -> CENTRO | G14: 67198586 | H14: CASETA | I14: 10000231 | J14: =VLOOKUP(I14,'Materiales,canteras'!C:D,2,0) -> Grava Triturada Basalto 20 mm | K14: =VLOOKUP(I14,'Materiales,canteras'!C:E,3,0) -> 1.565 | L14: 190 | M14: TN | N14: =TODAY() -> 46267 | O14: 31.12.9999 | S14: 280 | T14: =L14-S14 -> -90 | U14: =L14 -> 190 | V14: 0 | W14: 2 | X14: =V14+U14 -> 190 | Y14: =IF(+VLOOKUP(I14,P.Referencia!E:S,3,FALSE)<=L14,"Champion","Gerente") -> #N/A | Z14: =VLOOKUP(I14,P.Referencia!E:S,3,0) -> #N/A | AA14: =(Z14-U14)/U14 -> #N/A | AB14: =U14*AA14 -> #N/A | AC14: =U14+AB14 -> #N/A
A15: 14 | C15: =_xlfn.CONCAT($C$1,D15,G15,I15,W15) -> LlaveD86167198586100002332 | D15: =VLOOKUP(E15,'NO MODIFICAR'!J:K,2,0) -> D861 | E15: MX-CANTERA QUERETARO | F15: =VLOOKUP(D15,'NO MODIFICAR'!F:H,3,0) -> CENTRO | G15: 67198586 | H15: CASETA | I15: 10000233 | J15: =VLOOKUP(I15,'Materiales,canteras'!C:D,2,0) -> Grava Triturada Basalto 40 mm | K15: =VLOOKUP(I15,'Materiales,canteras'!C:E,3,0) -> 1.456 | L15: 190 | M15: TN | N15: =TODAY() -> 46267 | O15: 31.12.9999 | S15: 282 | T15: =L15-S15 -> -92 | U15: =L15 -> 190 | V15: 0 | W15: 2 | X15: =V15+U15 -> 190 | Y15: =IF(+VLOOKUP(I15,P.Referencia!E:S,3,FALSE)<=L15,"Champion","Gerente") -> #N/A | Z15: =VLOOKUP(I15,P.Referencia!E:S,3,0) -> #N/A | AA15: =(Z15-U15)/U15 -> #N/A | AB15: =U15*AA15 -> #N/A | AC15: =U15+AB15 -> #N/A
A16: 15 | C16: =_xlfn.CONCAT($C$1,D16,G16,I16,W16) -> LlaveD86167198586100014502 | D16: =VLOOKUP(E16,'NO MODIFICAR'!J:K,2,0) -> D861 | E16: MX-CANTERA QUERETARO | F16: =VLOOKUP(D16,'NO MODIFICAR'!F:H,3,0) -> CENTRO | G16: 67198586 | H16: CASETA | I16: 10001450 | J16: =VLOOKUP(I16,'Materiales,canteras'!C:D,2,0) -> Base Hidraúlica Basalto de 1 /1/2 | K16: =VLOOKUP(I16,'Materiales,canteras'!C:E,3,0) -> 1.749 | L16: 185 | M16: TN | N16: =TODAY() -> 46267 | O16: 31.12.9999 | S16: 260 | T16: =L16-S16 -> -75 | U16: =L16 -> 185 | V16: 0 | W16: 2 | X16: =V16+U16 -> 185 | Y16: =IF(+VLOOKUP(I16,P.Referencia!E:S,3,FALSE)<=L16,"Champion","Gerente") -> #N/A | Z16: =VLOOKUP(I16,P.Referencia!E:S,3,0) -> #N/A | AA16: =(Z16-U16)/U16 -> #N/A | AB16: =U16*AA16 -> #N/A | AC16: =U16+AB16 -> #N/A
A17: 16 | C17: =_xlfn.CONCAT($C$1,D17,G17,I17,W17) -> LlaveDU0767133267100001032 | D17: =VLOOKUP(E17,'NO MODIFICAR'!J:K,2,0) -> DU07 | E17: MX-CANCÚN III | F17: =VLOOKUP(D17,'NO MODIFICAR'!F:H,3,0) -> SURESTE | G17: 67133267 | H17: Javer Kusamil 2025 | I17: 10000103 | J17: =VLOOKUP(I17,'Materiales,canteras'!C:D,2,0) -> Base H Triturada Caliza 1 1/2" a Finos | K17: =VLOOKUP(I17,'Materiales,canteras'!C:E,3,0) -> 1.462 | L17: 119.699 | M17: TN | N17: =TODAY() -> 46267 | O17: 31.12.9999 | S17: 150 | T17: =L17-S17 -> -30.301 | U17: =L17 -> 119.699 | V17: 0 | W17: 2 | X17: =V17+U17 -> 119.699 | Y17: =IF(+VLOOKUP(I17,P.Referencia!E:S,3,FALSE)<=L17,"Champion","Gerente") -> #N/A | Z17: =VLOOKUP(I17,P.Referencia!E:S,3,0) -> #N/A | AA17: =(Z17-U17)/U17 -> #N/A | AB17: =U17*AA17 -> #N/A | AC17: =U17+AB17 -> #N/A
A18: 17 | C18: =_xlfn.CONCAT($C$1,D18,G18,I18,W18) -> LlaveD81366472003100002552 | D18: =VLOOKUP(E18,'NO MODIFICAR'!J:K,2,0) -> D813 | E18: MX-CANTERA SAN VICENTE | F18: =VLOOKUP(D18,'NO MODIFICAR'!F:H,3,0) -> CENTRO | G18: 66472003 | H18: CONCRETOS PILARES PLANTA TONANITLA | I18: 10000255 | J18: =VLOOKUP(I18,'Materiales,canteras'!C:D,2,0) -> Arena Triturada Andesita Malla | K18: =VLOOKUP(I18,'Materiales,canteras'!C:E,3,0) -> 1.535 | L18: 100 | M18: TN | N18: =TODAY() -> 46267 | O18: 31.12.9999 | T18: =L18-S18 -> 100 | U18: =L18 -> 100 | V18: 0 | W18: 2 | X18: =V18+U18 -> 100 | Y18: =IF(+VLOOKUP(I18,P.Referencia!E:S,3,FALSE)<=L18,"Champion","Gerente") -> #N/A | Z18: =VLOOKUP(I18,P.Referencia!E:S,3,0) -> #N/A | AA18: =(Z18-U18)/U18 -> #N/A | AB18: =U18*AA18 -> #N/A | AC18: =U18+AB18 -> #N/A | AD18: QUEDO PENDIENTE YA QUE COMERCIAL VOLVERIA A REVISARLO
A19: 18 | C19: =_xlfn.CONCAT($C$1,D19,G19,I19,W19) -> LlaveD81366472003100002532 | D19: =VLOOKUP(E19,'NO MODIFICAR'!J:K,2,0) -> D813 | E19: MX-CANTERA SAN VICENTE | F19: =VLOOKUP(D19,'NO MODIFICAR'!F:H,3,0) -> CENTRO | G19: 66472003 | H19: CONCRETOS PILARES PLANTA TONANITLA | I19: 10000253 | J19: =VLOOKUP(I19,'Materiales,canteras'!C:D,2,0) -> Grava Triturada Andesita 20 mm | K19: =VLOOKUP(I19,'Materiales,canteras'!C:E,3,0) -> 1.385 | L19: 100 | M19: TN | N19: =TODAY() -> 46267 | O19: 31.12.9999 | T19: =L19-S19 -> 100 | U19: =L19 -> 100 | V19: 0 | W19: 2 | X19: =V19+U19 -> 100 | Y19: =IF(+VLOOKUP(I19,P.Referencia!E:S,3,FALSE)<=L19,"Champion","Gerente") -> #N/A | Z19: =VLOOKUP(I19,P.Referencia!E:S,3,0) -> #N/A | AA19: =(Z19-U19)/U19 -> #N/A | AB19: =U19*AA19 -> #N/A | AC19: =U19+AB19 -> #N/A | AD19: QUEDO PENDIENTE YA QUE COMERCIAL VOLVERIA A REVISARLO
A20: 19 | C20: =_xlfn.CONCAT($C$1,D20,G20,I20,W20) -> LlaveD81366440645100002552 | D20: =VLOOKUP(E20,'NO MODIFICAR'!J:K,2,0) -> D813 | E20: MX-CANTERA SAN VICENTE | F20: =VLOOKUP(D20,'NO MODIFICAR'!F:H,3,0) -> CENTRO | G20: 66440645 | H20: Concretos Pilares Planta Texcoco | I20: 10000255 | J20: =VLOOKUP(I20,'Materiales,canteras'!C:D,2,0) -> Arena Triturada Andesita Malla | K20: =VLOOKUP(I20,'Materiales,canteras'!C:E,3,0) -> 1.535 | L20: 100 | M20: TN | N20: =TODAY() -> 46267 | O20: 31.12.9999 | T20: =L20-S20 -> 100 | U20: =L20 -> 100 | V20: 0 | W20: 2 | X20: =V20+U20 -> 100 | Y20: =IF(+VLOOKUP(I20,P.Referencia!E:S,3,FALSE)<=L20,"Champion","Gerente") -> #N/A | Z20: =VLOOKUP(I20,P.Referencia!E:S,3,0) -> #N/A | AA20: =(Z20-U20)/U20 -> #N/A | AB20: =U20*AA20 -> #N/A | AC20: =U20+AB20 -> #N/A | AD20: QUEDO PENDIENTE YA QUE COMERCIAL VOLVERIA A REVISARLO
A21: 20 | C21: =_xlfn.CONCAT($C$1,D21,G21,I21,W21) -> LlaveD81366440645100002532 | D21: =VLOOKUP(E21,'NO MODIFICAR'!J:K,2,0) -> D813 | E21: MX-CANTERA SAN VICENTE | F21: =VLOOKUP(D21,'NO MODIFICAR'!F:H,3,0) -> CENTRO | G21: 66440645 | H21: Concretos Pilares Planta Texcoco | I21: 10000253 | J21: =VLOOKUP(I21,'Materiales,canteras'!C:D,2,0) -> Grava Triturada Andesita 20 mm | K21: =VLOOKUP(I21,'Materiales,canteras'!C:E,3,0) -> 1.385 | L21: 100 | M21: TN | N21: =TODAY() -> 46267 | O21: 31.12.9999 | T21: =L21-S21 -> 100 | U21: =L21 -> 100 | V21: 0 | W21: 2 | X21: =V21+U21 -> 100 | Y21: =IF(+VLOOKUP(I21,P.Referencia!E:S,3,FALSE)<=L21,"Champion","Gerente") -> #N/A | Z21: =VLOOKUP(I21,P.Referencia!E:S,3,0) -> #N/A | AA21: =(Z21-U21)/U21 -> #N/A | AB21: =U21*AA21 -> #N/A | AC21: =U21+AB21 -> #N/A | AD21: QUEDO PENDIENTE YA QUE COMERCIAL VOLVERIA A REVISARLO
A22: 21 | C22: =_xlfn.CONCAT($C$1,D22,G22,I22,W22) -> LlaveD86466472003100010732 | D22: =VLOOKUP(E22,'NO MODIFICAR'!J:K,2,0) -> D864 | E22: MX-CANTERA CERRO JARDIN | F22: =VLOOKUP(D22,'NO MODIFICAR'!F:H,3,0) -> CENTRO | G22: 66472003 | H22: CONCRETOS PILARES PLANTA TONANITLA | I22: 10001073 | J22: =VLOOKUP(I22,'Materiales,canteras'!C:D,2,0) -> Arena Triturada Caliza Malla 4 | K22: =VLOOKUP(I22,'Materiales,canteras'!C:E,3,0) -> 1.56 | L22: 95 | M22: TN | N22: =TODAY() -> 46267 | O22: 31.12.9999 | T22: =L22-S22 -> 95 | U22: =L22 -> 95 | V22: 0 | W22: 2 | X22: =V22+U22 -> 95 | Y22: =IF(+VLOOKUP(I22,P.Referencia!E:S,3,FALSE)<=L22,"Champion","Gerente") -> #N/A | Z22: =VLOOKUP(I22,P.Referencia!E:S,3,0) -> #N/A | AA22: =(Z22-U22)/U22 -> #N/A | AB22: =U22*AA22 -> #N/A | AC22: =U22+AB22 -> #N/A | AD22: QUEDO PENDIENTE YA QUE COMERCIAL VOLVERIA A REVISARLO
A23: 22 | C23: =_xlfn.CONCAT($C$1,D23,G23,I23,W23) -> LlaveD86466472003100002402 | D23: =VLOOKUP(E23,'NO MODIFICAR'!J:K,2,0) -> D864 | E23: MX-CANTERA CERRO JARDIN | F23: =VLOOKUP(D23,'NO MODIFICAR'!F:H,3,0) -> CENTRO | G23: 66472003 | H23: CONCRETOS PILARES PLANTA TONANITLA | I23: 10000240 | J23: =VLOOKUP(I23,'Materiales,canteras'!C:D,2,0) -> Grava Triturada Caliza 20 mm - | K23: =VLOOKUP(I23,'Materiales,canteras'!C:E,3,0) -> 1.462 | L23: 151 | M23: TN | N23: =TODAY() -> 46267 | O23: 31.12.9999 | T23: =L23-S23 -> 151 | U23: =L23 -> 151 | V23: 0 | W23: 2 | X23: =V23+U23 -> 151 | Y23: =IF(+VLOOKUP(I23,P.Referencia!E:S,3,FALSE)<=L23,"Champion","Gerente") -> #N/A | Z23: =VLOOKUP(I23,P.Referencia!E:S,3,0) -> #N/A | AA23: =(Z23-U23)/U23 -> #N/A | AB23: =U23*AA23 -> #N/A | AC23: =U23+AB23 -> #N/A | AD23: QUEDO PENDIENTE YA QUE COMERCIAL VOLVERIA A REVISARLO
A24: 23 | C24: =_xlfn.CONCAT($C$1,D24,G24,I24,W24) -> LlaveD86466440645100010732 | D24: =VLOOKUP(E24,'NO MODIFICAR'!J:K,2,0) -> D864 | E24: MX-CANTERA CERRO JARDIN | F24: =VLOOKUP(D24,'NO MODIFICAR'!F:H,3,0) -> CENTRO | G24: 66440645 | H24: Concretos Pilares Planta Texcoco | I24: 10001073 | J24: =VLOOKUP(I24,'Materiales,canteras'!C:D,2,0) -> Arena Triturada Caliza Malla 4 | K24: =VLOOKUP(I24,'Materiales,canteras'!C:E,3,0) -> 1.56 | L24: 95 | M24: TN | N24: =TODAY() -> 46267 | O24: 31.12.9999 | T24: =L24-S24 -> 95 | U24: =L24 -> 95 | V24: 0 | W24: 2 | X24: =V24+U24 -> 95 | Y24: =IF(+VLOOKUP(I24,P.Referencia!E:S,3,FALSE)<=L24,"Champion","Gerente") -> #N/A | Z24: =VLOOKUP(I24,P.Referencia!E:S,3,0) -> #N/A | AA24: =(Z24-U24)/U24 -> #N/A | AB24: =U24*AA24 -> #N/A | AC24: =U24+AB24 -> #N/A | AD24: QUEDO PENDIENTE YA QUE COMERCIAL VOLVERIA A REVISARLO
A25: 24 | C25: =_xlfn.CONCAT($C$1,D25,G25,I25,W25) -> LlaveD86466440645100002402 | D25: =VLOOKUP(E25,'NO MODIFICAR'!J:K,2,0) -> D864 | E25: MX-CANTERA CERRO JARDIN | F25: =VLOOKUP(D25,'NO MODIFICAR'!F:H,3,0) -> CENTRO | G25: 66440645 | H25: Concretos Pilares Planta Texcoco | I25: 10000240 | J25: =VLOOKUP(I25,'Materiales,canteras'!C:D,2,0) -> Grava Triturada Caliza 20 mm - | K25: =VLOOKUP(I25,'Materiales,canteras'!C:E,3,0) -> 1.462 | L25: 151 | M25: TN | N25: =TODAY() -> 46267 | O25: 31.12.9999 | T25: =L25-S25 -> 151 | U25: =L25 -> 151 | V25: 0 | W25: 2 | X25: =V25+U25 -> 151 | Y25: =IF(+VLOOKUP(I25,P.Referencia!E:S,3,FALSE)<=L25,"Champion","Gerente") -> #N/A | Z25: =VLOOKUP(I25,P.Referencia!E:S,3,0) -> #N/A | AA25: =(Z25-U25)/U25 -> #N/A | AB25: =U25*AA25 -> #N/A | AC25: =U25+AB25 -> #N/A | AD25: QUEDO PENDIENTE YA QUE COMERCIAL VOLVERIA A REVISARLO
A26: 25 | C26: =_xlfn.CONCAT($C$1,D26,G26,I26,W26) -> LlaveD86466857228100002402 | D26: =VLOOKUP(E26,'NO MODIFICAR'!J:K,2,0) -> D864 | E26: MX-CANTERA CERRO JARDIN | F26: =VLOOKUP(D26,'NO MODIFICAR'!F:H,3,0) -> CENTRO | G26: 66857228 | H26: PREFAMOVIL ZUMPANGO | I26: 10000240 | J26: =VLOOKUP(I26,'Materiales,canteras'!C:D,2,0) -> Grava Triturada Caliza 20 mm - | K26: =VLOOKUP(I26,'Materiales,canteras'!C:E,3,0) -> 1.462 | L26: 135 | M26: TN | N26: =TODAY() -> 46267 | O26: 31.12.9999 | S26: 280 | T26: =L26-S26 -> -145 | U26: =L26 -> 135 | V26: 0 | W26: 2 | X26: =V26+U26 -> 135 | Y26: =IF(+VLOOKUP(I26,P.Referencia!E:S,3,FALSE)<=L26,"Champion","Gerente") -> #N/A | Z26: =VLOOKUP(I26,P.Referencia!E:S,3,0) -> #N/A | AA26: =(Z26-U26)/U26 -> #N/A | AB26: =U26*AA26 -> #N/A | AC26: =U26+AB26 -> #N/A | AD26: PENDIENTE VOBO LALO Y RICARDO
A27: 26 | C27: =_xlfn.CONCAT($C$1,D27,G27,I27,W27) -> LlaveD86165612044100024991 | D27: =VLOOKUP(E27,'NO MODIFICAR'!J:K,2,0) -> D861 | E27: MX-CANTERA QUERETARO | F27: =VLOOKUP(D27,'NO MODIFICAR'!F:H,3,0) -> CENTRO | G27: 65612044 | H27: OBR-AGR EPCA (LOBS) | I27: 10002499 | J27: =VLOOKUP(I27,'Materiales,canteras'!C:D,2,0) -> Arena Triturada Basalto Malla 4 -Mezcla | K27: =VLOOKUP(I27,'Materiales,canteras'!C:E,3,0) -> 1.666 | L27: 168.62 | M27: TN | N27: =TODAY() -> 46267 | O27: 31.12.9999 | S27: 180 | T27: =L27-S27 -> -11.38 | U27: 168.62 | V27: 51.16 | W27: 1 | X27: =V27+U27 -> 219.78 | Y27: =IF(+VLOOKUP(I27,P.Referencia!E:S,3,FALSE)<=L27,"Champion","Gerente") -> #N/A | Z27: =VLOOKUP(I27,P.Referencia!E:S,3,0) -> #N/A | AA27: =(Z27-U27)/U27 -> #N/A | AB27: =U27*AA27 -> #N/A | AC27: =U27+AB27 -> #N/A | AD27: PENDIENTE VOBO DE RICARDO
A28: 27 | C28: =_xlfn.CONCAT($C$1,D28,G28,I28,W28) -> LlaveD81367019979100023501 | D28: =VLOOKUP(E28,'NO MODIFICAR'!J:K,2,0) -> D813 | E28: MX-CANTERA SAN VICENTE | F28: =VLOOKUP(D28,'NO MODIFICAR'!F:H,3,0) -> CENTRO | G28: 67019979 | H28: FORTALEZA VISE | I28: 10002350 | J28: =VLOOKUP(I28,'Materiales,canteras'!C:D,2,0) -> Grava Triturada Andesita 10mm- | K28: =VLOOKUP(I28,'Materiales,canteras'!C:E,3,0) -> 1.246 | L28: 120.49 | M28: TN | N28: =TODAY() -> 46267 | O28: 31.12.9999 | S28: 150 | T28: =L28-S28 -> -29.51 | U28: 120.49 | V28: 251.46 | W28: 1 | X28: =V28+U28 -> 371.95 | Y28: =IF(+VLOOKUP(I28,P.Referencia!E:S,3,FALSE)<=L28,"Champion","Gerente") -> #N/A | Z28: =VLOOKUP(I28,P.Referencia!E:S,3,0) -> #N/A | AA28: =(Z28-U28)/U28 -> #N/A | AB28: =U28*AA28 -> #N/A | AC28: =U28+AB28 -> #N/A
A29: 28 | C29: =_xlfn.CONCAT($C$1,D29,G29,I29,W29) -> LlaveD86167317983100002901 | D29: =VLOOKUP(E29,'NO MODIFICAR'!J:K,2,0) -> D861 | E29: MX-CANTERA QUERETARO | F29: =VLOOKUP(D29,'NO MODIFICAR'!F:H,3,0) -> CENTRO | G29: 67317983 | H29: EL CAMPANARIO | I29: 10000290 | J29: =VLOOKUP(I29,'Materiales,canteras'!C:D,2,0) -> Polvos Triturado Basalto 3/4" | K29: =VLOOKUP(I29,'Materiales,canteras'!C:E,3,0) -> 1.372 | L29: 1 | M29: TN | N29: =TODAY() -> 46267 | O29: 31.12.9999 | S29: 25 | T29: =L29-S29 -> -24 | U29: 1 | V29: 72.09 | W29: 1 | X29: =V29+U29 -> 73.09 | Y29: =IF(+VLOOKUP(I29,P.Referencia!E:S,3,FALSE)<=L29,"Champion","Gerente") -> #N/A | Z29: =VLOOKUP(I29,P.Referencia!E:S,3,0) -> #N/A | AA29: =(Z29-U29)/U29 -> #N/A | AB29: =U29*AA29 -> #N/A | AC29: =U29+AB29 -> #N/A | AD29: PENDIENTE VOBO DE RICARDO Y LALO
A30: 29 | C30: =_xlfn.CONCAT($C$1,D30,G30,I30,W30) -> LlaveD81366440645100002552 | D30: =VLOOKUP(E30,'NO MODIFICAR'!J:K,2,0) -> D813 | E30: MX-CANTERA SAN VICENTE | F30: =VLOOKUP(D30,'NO MODIFICAR'!F:H,3,0) -> CENTRO | G30: 66440645 | H30: Concretos Pilares S.A. De C.V. | I30: 10000255 | J30: =VLOOKUP(I30,'Materiales,canteras'!C:D,2,0) -> Arena Triturada Andesita Malla | K30: =VLOOKUP(I30,'Materiales,canteras'!C:E,3,0) -> 1.535 | L30: 100 | M30: TN | N30: =TODAY() -> 46267 | O30: 31.12.9999 | S30: 150 | T30: =L30-S30 -> -50 | U30: =L30 -> 100 | V30: 0 | W30: 2 | X30: =V30+U30 -> 100 | Y30: =IF(+VLOOKUP(I30,P.Referencia!E:S,3,FALSE)<=L30,"Champion","Gerente") -> #N/A | Z30: =VLOOKUP(I30,P.Referencia!E:S,3,0) -> #N/A | AA30: =(Z30-U30)/U30 -> #N/A | AB30: =U30*AA30 -> #N/A | AC30: =U30+AB30 -> #N/A
A31: 30 | C31: =_xlfn.CONCAT($C$1,D31,G31,I31,W31) -> LlaveD81366440645100002532 | D31: =VLOOKUP(E31,'NO MODIFICAR'!J:K,2,0) -> D813 | E31: MX-CANTERA SAN VICENTE | F31: =VLOOKUP(D31,'NO MODIFICAR'!F:H,3,0) -> CENTRO | G31: 66440645 | H31: Concretos Pilares S.A. De C.V. | I31: 10000253 | J31: =VLOOKUP(I31,'Materiales,canteras'!C:D,2,0) -> Grava Triturada Andesita 20 mm | K31: =VLOOKUP(I31,'Materiales,canteras'!C:E,3,0) -> 1.385 | L31: 100 | M31: TN | N31: =TODAY() -> 46267 | O31: 31.12.9999 | S31: 150 | T31: =L31-S31 -> -50 | U31: =L31 -> 100 | V31: 0 | W31: 2 | X31: =V31+U31 -> 100 | Y31: =IF(+VLOOKUP(I31,P.Referencia!E:S,3,FALSE)<=L31,"Champion","Gerente") -> #N/A | Z31: =VLOOKUP(I31,P.Referencia!E:S,3,0) -> #N/A | AA31: =(Z31-U31)/U31 -> #N/A | AB31: =U31*AA31 -> #N/A | AC31: =U31+AB31 -> #N/A
A32: 31 | C32: =_xlfn.CONCAT($C$1,D32,G32,I32,W32) -> LlaveD86466440645100010732 | D32: =VLOOKUP(E32,'NO MODIFICAR'!J:K,2,0) -> D864 | E32: MX-CANTERA CERRO JARDIN | F32: =VLOOKUP(D32,'NO MODIFICAR'!F:H,3,0) -> CENTRO | G32: 66440645 | H32: Concretos Pilares S.A. De C.V. | I32: 10001073 | J32: =VLOOKUP(I32,'Materiales,canteras'!C:D,2,0) -> Arena Triturada Caliza Malla 4 | K32: =VLOOKUP(I32,'Materiales,canteras'!C:E,3,0) -> 1.56 | L32: 95 | M32: TN | N32: =TODAY() -> 46267 | O32: 31.12.9999 | S32: 150 | T32: =L32-S32 -> -55 | U32: =L32 -> 95 | V32: 0 | W32: 2 | X32: =V32+U32 -> 95 | Y32: =IF(+VLOOKUP(I32,P.Referencia!E:S,3,FALSE)<=L32,"Champion","Gerente") -> #N/A | Z32: =VLOOKUP(I32,P.Referencia!E:S,3,0) -> #N/A | AA32: =(Z32-U32)/U32 -> #N/A | AB32: =U32*AA32 -> #N/A | AC32: =U32+AB32 -> #N/A
A33: 32 | C33: =_xlfn.CONCAT($C$1,D33,G33,I33,W33) -> LlaveD86466440645100002402 | D33: =VLOOKUP(E33,'NO MODIFICAR'!J:K,2,0) -> D864 | E33: MX-CANTERA CERRO JARDIN | F33: =VLOOKUP(D33,'NO MODIFICAR'!F:H,3,0) -> CENTRO | G33: 66440645 | H33: Concretos Pilares S.A. De C.V. | I33: 10000240 | J33: =VLOOKUP(I33,'Materiales,canteras'!C:D,2,0) -> Grava Triturada Caliza 20 mm - | K33: =VLOOKUP(I33,'Materiales,canteras'!C:E,3,0) -> 1.462 | L33: 151 | M33: TN | N33: =TODAY() -> 46267 | O33: 31.12.9999 | S33: 280 | T33: =L33-S33 -> -129 | U33: =L33 -> 151 | V33: 0 | W33: 2 | X33: =V33+U33 -> 151 | Y33: =IF(+VLOOKUP(I33,P.Referencia!E:S,3,FALSE)<=L33,"Champion","Gerente") -> #N/A | Z33: =VLOOKUP(I33,P.Referencia!E:S,3,0) -> #N/A | AA33: =(Z33-U33)/U33 -> #N/A | AB33: =U33*AA33 -> #N/A | AC33: =U33+AB33 -> #N/A
A34: 33 | C34: =_xlfn.CONCAT($C$1,D34,G34,I34,W34) -> LlaveD86467124204100002402 | D34: =VLOOKUP(E34,'NO MODIFICAR'!J:K,2,0) -> D864 | E34: MX-CANTERA CERRO JARDIN | F34: =VLOOKUP(D34,'NO MODIFICAR'!F:H,3,0) -> CENTRO | G34: 67124204 | H34: Agreg – Premoso | I34: 10000240 | J34: =VLOOKUP(I34,'Materiales,canteras'!C:D,2,0) -> Grava Triturada Caliza 20 mm - | K34: =VLOOKUP(I34,'Materiales,canteras'!C:E,3,0) -> 1.462 | L34: 130 | M34: TN | N34: =TODAY() -> 46267 | O34: 31.12.9999 | S34: 280 | T34: =L34-S34 -> -150 | U34: 130 | V34: 0 | W34: 2 | X34: =V34+U34 -> 130 | Y34: =IF(+VLOOKUP(I34,P.Referencia!E:S,3,FALSE)<=L34,"Champion","Gerente") -> #N/A | Z34: =VLOOKUP(I34,P.Referencia!E:S,3,0) -> #N/A | AA34: =(Z34-U34)/U34 -> #N/A | AB34: =U34*AA34 -> #N/A | AC34: =U34+AB34 -> #N/A
A35: 34 | C35: =_xlfn.CONCAT($C$1,D35,G35,I35,W35) -> LlaveD86467124204100010742 | D35: =VLOOKUP(E35,'NO MODIFICAR'!J:K,2,0) -> D864 | E35: MX-CANTERA CERRO JARDIN | F35: =VLOOKUP(D35,'NO MODIFICAR'!F:H,3,0) -> CENTRO | G35: 67124204 | H35: Agreg – Premoso | I35: 10001074 | J35: =VLOOKUP(I35,'Materiales,canteras'!C:D,2,0) -> Grava Triturada Caliza 40 mm - | K35: =VLOOKUP(I35,'Materiales,canteras'!C:E,3,0) -> 1.4 | L35: 130 | M35: TN | N35: =TODAY() -> 46267 | O35: 31.12.9999 | S35: 220 | T35: =L35-S35 -> -90 | U35: 130 | V35: 0 | W35: 2 | X35: =V35+U35 -> 130 | Y35: =IF(+VLOOKUP(I35,P.Referencia!E:S,3,FALSE)<=L35,"Champion","Gerente") -> #N/A | Z35: =VLOOKUP(I35,P.Referencia!E:S,3,0) -> #N/A | AA35: =(Z35-U35)/U35 -> #N/A | AB35: =U35*AA35 -> #N/A | AC35: =U35+AB35 -> #N/A
A36: 35 | C36: =_xlfn.CONCAT($C$1,D36,G36,I36,W36) -> LlaveD86167320246100002902 | D36: =VLOOKUP(E36,'NO MODIFICAR'!J:K,2,0) -> D861 | E36: MX-CANTERA QUERETARO | F36: =VLOOKUP(D36,'NO MODIFICAR'!F:H,3,0) -> CENTRO | G36: 67320246 | H36: AGACEL DESPOLVE | I36: 10000290 | J36: =VLOOKUP(I36,'Materiales,canteras'!C:D,2,0) -> Polvos Triturado Basalto 3/4" | K36: =VLOOKUP(I36,'Materiales,canteras'!C:E,3,0) -> 1.372 | L36: 1 | M36: TN | N36: =TODAY() -> 46267 | O36: 31.12.9999 | S36: 25 | T36: =L36-S36 -> -24 | U36: 1 | V36: 0 | W36: 2 | X36: =V36+U36 -> 1 | Y36: =IF(+VLOOKUP(I36,P.Referencia!E:S,3,FALSE)<=L36,"Champion","Gerente") -> #N/A | Z36: =VLOOKUP(I36,P.Referencia!E:S,3,0) -> #N/A | AA36: =(Z36-U36)/U36 -> #N/A | AB36: =U36*AA36 -> #N/A | AC36: =U36+AB36 -> #N/A
A37: 36 | C37: =_xlfn.CONCAT($C$1,D37,G37,I37,W37) -> LlaveD81366942072100002551 | D37: =VLOOKUP(E37,'NO MODIFICAR'!J:K,2,0) -> D813 | E37: MX-CANTERA SAN VICENTE | F37: =VLOOKUP(D37,'NO MODIFICAR'!F:H,3,0) -> CENTRO | G37: 66942072 | H37: Prebloquim | I37: 10000255 | J37: =VLOOKUP(I37,'Materiales,canteras'!C:D,2,0) -> Arena Triturada Andesita Malla | K37: =VLOOKUP(I37,'Materiales,canteras'!C:E,3,0) -> 1.535 | L37: 84 | M37: TN | N37: =TODAY() -> 46267 | O37: 31.12.9999 | S37: 150 | T37: =L37-S37 -> -66 | U37: 84 | V37: 143.32 | W37: 1 | X37: =V37+U37 -> 227.32 | Y37: =IF(+VLOOKUP(I37,P.Referencia!E:S,3,FALSE)<=L37,"Champion","Gerente") -> #N/A | Z37: =VLOOKUP(I37,P.Referencia!E:S,3,0) -> #N/A | AA37: =(Z37-U37)/U37 -> #N/A | AB37: =U37*AA37 -> #N/A | AC37: =U37+AB37 -> #N/A
A38: 37 | C38: =_xlfn.CONCAT($C$1,D38,G38,I38,W38) -> LlaveD86166838326100031532 | D38: =VLOOKUP(E38,'NO MODIFICAR'!J:K,2,0) -> D861 | E38: MX-CANTERA QUERETARO | F38: =VLOOKUP(D38,'NO MODIFICAR'!F:H,3,0) -> CENTRO | G38: 66838326 | H38: OBRA FORD | I38: 10003153 | J38: =VLOOKUP(I38,'Materiales,canteras'!C:D,2,0) -> Grava Triturada Basalto 13 mm | K38: =VLOOKUP(I38,'Materiales,canteras'!C:E,3,0) -> 1.546 | L38: 220 | M38: TN | N38: =TODAY() -> 46267 | O38: 31.12.9999 | S38: 270 | T38: =L38-S38 -> -50 | U38: 220 | V38: 0 | W38: 2 | X38: =V38+U38 -> 220 | Y38: =IF(+VLOOKUP(I38,P.Referencia!E:S,3,FALSE)<=L38,"Champion","Gerente") -> #N/A | Z38: =VLOOKUP(I38,P.Referencia!E:S,3,0) -> #N/A | AA38: =(Z38-U38)/U38 -> #N/A | AB38: =U38*AA38 -> #N/A | AC38: =U38+AB38 -> #N/A
A39: 38 | C39: =_xlfn.CONCAT($C$1,D39,G39,I39,W39) -> LlaveD86467320967100002402 | D39: =VLOOKUP(E39,'NO MODIFICAR'!J:K,2,0) -> D864 | E39: MX-CANTERA CERRO JARDIN | F39: =VLOOKUP(D39,'NO MODIFICAR'!F:H,3,0) -> CENTRO | G39: 67320967 | H39: CONSTRUCCIONES Y ASFALTOS | I39: 10000240 | J39: =VLOOKUP(I39,'Materiales,canteras'!C:D,2,0) -> Grava Triturada Caliza 20 mm - | K39: =VLOOKUP(I39,'Materiales,canteras'!C:E,3,0) -> 1.462 | L39: 130 | M39: TN | N39: =TODAY() -> 46267 | O39: 31.12.9999 | S39: 280 | T39: =L39-S39 -> -150 | U39: 130 | V39: 0 | W39: 2 | X39: =V39+U39 -> 130 | Y39: =IF(+VLOOKUP(I39,P.Referencia!E:S,3,FALSE)<=L39,"Champion","Gerente") -> #N/A | Z39: =VLOOKUP(I39,P.Referencia!E:S,3,0) -> #N/A | AA39: =(Z39-U39)/U39 -> #N/A | AB39: =U39*AA39 -> #N/A | AC39: =U39+AB39 -> #N/A
A40: 39 | C40: =_xlfn.CONCAT($C$1,D40,G40,I40,W40) -> LlaveD81367320967100002552 | D40: =VLOOKUP(E40,'NO MODIFICAR'!J:K,2,0) -> D813 | E40: MX-CANTERA SAN VICENTE | F40: =VLOOKUP(D40,'NO MODIFICAR'!F:H,3,0) -> CENTRO | G40: 67320967 | H40: CONSTRUCCIONES Y ASFALTOS | I40: 10000255 | J40: =VLOOKUP(I40,'Materiales,canteras'!C:D,2,0) -> Arena Triturada Andesita Malla | K40: =VLOOKUP(I40,'Materiales,canteras'!C:E,3,0) -> 1.535 | L40: 80 | M40: TN | N40: =TODAY() -> 46267 | O40: 31.12.9999 | S40: 150 | T40: =L40-S40 -> -70 | U40: 80 | V40: 0 | W40: 2 | X40: =V40+U40 -> 80 | Y40: =IF(+VLOOKUP(I40,P.Referencia!E:S,3,FALSE)<=L40,"Champion","Gerente") -> #N/A | Z40: =VLOOKUP(I40,P.Referencia!E:S,3,0) -> #N/A | AA40: =(Z40-U40)/U40 -> #N/A | AB40: =U40*AA40 -> #N/A | AC40: =U40+AB40 -> #N/A
A41: 40 | C41: =_xlfn.CONCAT($C$1,D41,G41,I41,W41) -> LlaveD86467019979100002692 | D41: =VLOOKUP(E41,'NO MODIFICAR'!J:K,2,0) -> D864 | E41: MX-CANTERA CERRO JARDIN | F41: =VLOOKUP(D41,'NO MODIFICAR'!F:H,3,0) -> CENTRO | G41: 67019979 | H41: Fortaleza VISE | I41: 10000269 | J41: =VLOOKUP(I41,'Materiales,canteras'!C:D,2,0) -> Grava Triturada Caliza 13 mm - | K41: =VLOOKUP(I41,'Materiales,canteras'!C:E,3,0) -> 1.423 | L41: 168.51 | M41: TN | N41: =TODAY() -> 46267 | O41: 31.12.9999 | T41: =L41-S41 -> 168.51 | U41: =L41 -> 168.51 | V41: 0 | W41: 2 | X41: =V41+U41 -> 168.51 | Y41: =IF(+VLOOKUP(I41,P.Referencia!E:S,3,FALSE)<=L41,"Champion","Gerente") -> #N/A | Z41: =VLOOKUP(I41,P.Referencia!E:S,3,0) -> #N/A | AA41: =(Z41-U41)/U41 -> #N/A | AB41: =U41*AA41 -> #N/A | AC41: =U41+AB41 -> #N/A
A42: 41 | C42: =_xlfn.CONCAT($C$1,D42,G42,I42,W42) -> LlaveD86466982053100002692 | D42: =VLOOKUP(E42,'NO MODIFICAR'!J:K,2,0) -> D864 | E42: MX-CANTERA CERRO JARDIN | F42: =VLOOKUP(D42,'NO MODIFICAR'!F:H,3,0) -> CENTRO | G42: 66982053 | H42: Fortaleza Naucalpan | I42: 10000269 | J42: =VLOOKUP(I42,'Materiales,canteras'!C:D,2,0) -> Grava Triturada Caliza 13 mm - | K42: =VLOOKUP(I42,'Materiales,canteras'!C:E,3,0) -> 1.423 | L42: 168.51 | M42: TN | N42: =TODAY() -> 46267 | O42: 31.12.9999 | T42: =L42-S42 -> 168.51 | U42: =L42 -> 168.51 | V42: 0 | W42: 2 | X42: =V42+U42 -> 168.51 | Y42: =IF(+VLOOKUP(I42,P.Referencia!E:S,3,FALSE)<=L42,"Champion","Gerente") -> #N/A | Z42: =VLOOKUP(I42,P.Referencia!E:S,3,0) -> #N/A | AA42: =(Z42-U42)/U42 -> #N/A | AB42: =U42*AA42 -> #N/A | AC42: =U42+AB42 -> #N/A
A43: 42 | C43: =_xlfn.CONCAT($C$1,D43,G43,I43,W43) -> LlaveD86466982053100010742 | D43: =VLOOKUP(E43,'NO MODIFICAR'!J:K,2,0) -> D864 | E43: MX-CANTERA CERRO JARDIN | F43: =VLOOKUP(D43,'NO MODIFICAR'!F:H,3,0) -> CENTRO | G43: 66982053 | H43: Fortaleza Naucalpan | I43: 10001074 | J43: =VLOOKUP(I43,'Materiales,canteras'!C:D,2,0) -> Grava Triturada Caliza 40 mm - | K43: =VLOOKUP(I43,'Materiales,canteras'!C:E,3,0) -> 1.4 | L43: 154.26 | M43: TN | N43: =TODAY() -> 46267 | O43: 31.12.9999 | T43: =L43-S43 -> 154.26 | U43: =L43 -> 154.26 | V43: 0 | W43: 2 | X43: =V43+U43 -> 154.26 | Y43: =IF(+VLOOKUP(I43,P.Referencia!E:S,3,FALSE)<=L43,"Champion","Gerente") -> #N/A | Z43: =VLOOKUP(I43,P.Referencia!E:S,3,0) -> #N/A | AA43: =(Z43-U43)/U43 -> #N/A | AB43: =U43*AA43 -> #N/A | AC43: =U43+AB43 -> #N/A
A44: 43 | C44: =_xlfn.CONCAT($C$1,D44,G44,I44,W44) -> LlaveD81366982053100002532 | D44: =VLOOKUP(E44,'NO MODIFICAR'!J:K,2,0) -> D813 | E44: MX-CANTERA SAN VICENTE | F44: =VLOOKUP(D44,'NO MODIFICAR'!F:H,3,0) -> CENTRO | G44: 66982053 | H44: Fortaleza Naucalpan | I44: 10000253 | J44: =VLOOKUP(I44,'Materiales,canteras'!C:D,2,0) -> Grava Triturada Andesita 20 mm | K44: =VLOOKUP(I44,'Materiales,canteras'!C:E,3,0) -> 1.385 | L44: 103.9 | M44: TN | N44: =TODAY() -> 46267 | O44: 31.12.9999 | T44: =L44-S44 -> 103.9 | U44: =L44 -> 103.9 | V44: 0 | W44: 2 | X44: =V44+U44 -> 103.9 | Y44: =IF(+VLOOKUP(I44,P.Referencia!E:S,3,FALSE)<=L44,"Champion","Gerente") -> #N/A | Z44: =VLOOKUP(I44,P.Referencia!E:S,3,0) -> #N/A | AA44: =(Z44-U44)/U44 -> #N/A | AB44: =U44*AA44 -> #N/A | AC44: =U44+AB44 -> #N/A
A45: 44 | C45: =_xlfn.CONCAT($C$1,D45,G45,I45,W45) -> LlaveD81366982053100023502 | D45: =VLOOKUP(E45,'NO MODIFICAR'!J:K,2,0) -> D813 | E45: MX-CANTERA SAN VICENTE | F45: =VLOOKUP(D45,'NO MODIFICAR'!F:H,3,0) -> CENTRO | G45: 66982053 | H45: Fortaleza Naucalpan | I45: 10002350 | J45: =VLOOKUP(I45,'Materiales,canteras'!C:D,2,0) -> Grava Triturada Andesita 10mm- | K45: =VLOOKUP(I45,'Materiales,canteras'!C:E,3,0) -> 1.246 | L45: 120.49 | M45: TN | N45: =TODAY() -> 46267 | O45: 31.12.9999 | T45: =L45-S45 -> 120.49 | U45: =L45 -> 120.49 | V45: 0 | W45: 2 | X45: =V45+U45 -> 120.49 | Y45: =IF(+VLOOKUP(I45,P.Referencia!E:S,3,FALSE)<=L45,"Champion","Gerente") -> #N/A | Z45: =VLOOKUP(I45,P.Referencia!E:S,3,0) -> #N/A | AA45: =(Z45-U45)/U45 -> #N/A | AB45: =U45*AA45 -> #N/A | AC45: =U45+AB45 -> #N/A
A46: 45 | C46: =_xlfn.CONCAT($C$1,D46,G46,I46,W46) -> LlaveD86466864540100002692 | D46: =VLOOKUP(E46,'NO MODIFICAR'!J:K,2,0) -> D864 | E46: MX-CANTERA CERRO JARDIN | F46: =VLOOKUP(D46,'NO MODIFICAR'!F:H,3,0) -> CENTRO | G46: 66864540 | H46: Fortaleza Rosarinos | I46: 10000269 | J46: =VLOOKUP(I46,'Materiales,canteras'!C:D,2,0) -> Grava Triturada Caliza 13 mm - | K46: =VLOOKUP(I46,'Materiales,canteras'!C:E,3,0) -> 1.423 | L46: 168.51 | M46: TN | N46: =TODAY() -> 46267 | O46: 31.12.9999 | T46: =L46-S46 -> 168.51 | U46: =L46 -> 168.51 | V46: 0 | W46: 2 | X46: =V46+U46 -> 168.51 | Y46: =IF(+VLOOKUP(I46,P.Referencia!E:S,3,FALSE)<=L46,"Champion","Gerente") -> #N/A | Z46: =VLOOKUP(I46,P.Referencia!E:S,3,0) -> #N/A | AA46: =(Z46-U46)/U46 -> #N/A | AB46: =U46*AA46 -> #N/A | AC46: =U46+AB46 -> #N/A
A47: 46 | C47: =_xlfn.CONCAT($C$1,D47,G47,I47,W47) -> LlaveD86467243408100002692 | D47: =VLOOKUP(E47,'NO MODIFICAR'!J:K,2,0) -> D864 | E47: MX-CANTERA CERRO JARDIN | F47: =VLOOKUP(D47,'NO MODIFICAR'!F:H,3,0) -> CENTRO | G47: 67243408 | H47: Fortaleza Rosarinos | I47: 10000269 | J47: =VLOOKUP(I47,'Materiales,canteras'!C:D,2,0) -> Grava Triturada Caliza 13 mm - | K47: =VLOOKUP(I47,'Materiales,canteras'!C:E,3,0) -> 1.423 | L47: 168.51 | M47: TN | N47: =TODAY() -> 46267 | O47: 31.12.9999 | T47: =L47-S47 -> 168.51 | U47: =L47 -> 168.51 | V47: 0 | W47: 2 | X47: =V47+U47 -> 168.51 | Y47: =IF(+VLOOKUP(I47,P.Referencia!E:S,3,FALSE)<=L47,"Champion","Gerente") -> #N/A | Z47: =VLOOKUP(I47,P.Referencia!E:S,3,0) -> #N/A | AA47: =(Z47-U47)/U47 -> #N/A | AB47: =U47*AA47 -> #N/A | AC47: =U47+AB47 -> #N/A
A48: 47 | C48: =_xlfn.CONCAT($C$1,D48,G48,I48,W48) -> LlaveD81367243408100002532 | D48: =VLOOKUP(E48,'NO MODIFICAR'!J:K,2,0) -> D813 | E48: MX-CANTERA SAN VICENTE | F48: =VLOOKUP(D48,'NO MODIFICAR'!F:H,3,0) -> CENTRO | G48: 67243408 | H48: Fortaleza Interlomas | I48: 10000253 | J48: =VLOOKUP(I48,'Materiales,canteras'!C:D,2,0) -> Grava Triturada Andesita 20 mm | K48: =VLOOKUP(I48,'Materiales,canteras'!C:E,3,0) -> 1.385 | L48: 103.9 | M48: TN | N48: =TODAY() -> 46267 | O48: 31.12.9999 | S48: 150 | T48: =L48-S48 -> -46.1 | U48: =L48 -> 103.9 | V48: 0 | W48: 2 | X48: =V48+U48 -> 103.9 | Y48: =IF(+VLOOKUP(I48,P.Referencia!E:S,3,FALSE)<=L48,"Champion","Gerente") -> #N/A | Z48: =VLOOKUP(I48,P.Referencia!E:S,3,0) -> #N/A | AA48: =(Z48-U48)/U48 -> #N/A | AB48: =U48*AA48 -> #N/A | AC48: =U48+AB48 -> #N/A
A49: 48 | C49: =_xlfn.CONCAT($C$1,D49,G49,I49,W49) -> LlaveD81367243408100023502 | D49: =VLOOKUP(E49,'NO MODIFICAR'!J:K,2,0) -> D813 | E49: MX-CANTERA SAN VICENTE | F49: =VLOOKUP(D49,'NO MODIFICAR'!F:H,3,0) -> CENTRO | G49: 67243408 | H49: Fortaleza Interlomas | I49: 10002350 | J49: =VLOOKUP(I49,'Materiales,canteras'!C:D,2,0) -> Grava Triturada Andesita 10mm- | K49: =VLOOKUP(I49,'Materiales,canteras'!C:E,3,0) -> 1.246 | L49: 120.49 | M49: TN | N49: =TODAY() -> 46267 | O49: 31.12.9999 | S49: 150 | T49: =L49-S49 -> -29.51 | U49: =L49 -> 120.49 | V49: 0 | W49: 2 | X49: =V49+U49 -> 120.49 | Y49: =IF(+VLOOKUP(I49,P.Referencia!E:S,3,FALSE)<=L49,"Champion","Gerente") -> #N/A | Z49: =VLOOKUP(I49,P.Referencia!E:S,3,0) -> #N/A | AA49: =(Z49-U49)/U49 -> #N/A | AB49: =U49*AA49 -> #N/A | AC49: =U49+AB49 -> #N/A
A50: 49 | C50: =_xlfn.CONCAT($C$1,D50,G50,I50,W50) -> LlaveD86167321663100014501 | D50: =VLOOKUP(E50,'NO MODIFICAR'!J:K,2,0) -> D861 | E50: MX-CANTERA QUERETARO | F50: =VLOOKUP(D50,'NO MODIFICAR'!F:H,3,0) -> CENTRO | G50: 67321663 | H50: BICUPSA | I50: 10001450 | J50: =VLOOKUP(I50,'Materiales,canteras'!C:D,2,0) -> Base Hidraúlica Basalto de 1 /1/2 | K50: =VLOOKUP(I50,'Materiales,canteras'!C:E,3,0) -> 1.749 | L50: 195 | M50: TN | N50: =TODAY() -> 46267 | O50: 31.12.9999 | R50: =1.5/100 -> 0.015 | S50: 260 | T50: =L50-(S50-(S50*R50)) -> -61.1 | U50: =L50 -> 195 | V50: 45 | W50: 1 | X50: =V50+U50 -> 240 | Y50: =IF(+VLOOKUP(I50,P.Referencia!E:S,3,FALSE)<=L50,"Champion","Gerente") -> #N/A | Z50: =VLOOKUP(I50,P.Referencia!E:S,3,0) -> #N/A | AA50: =(Z50-U50)/U50 -> #N/A | AB50: =U50*AA50 -> #N/A | AC50: =U50+AB50 -> #N/A
A51: 50 | C51: =_xlfn.CONCAT($C$1,D51,G51,I51,W51) -> LlaveD86167321663100003111 | D51: =VLOOKUP(E51,'NO MODIFICAR'!J:K,2,0) -> D861 | E51: MX-CANTERA QUERETARO | F51: =VLOOKUP(D51,'NO MODIFICAR'!F:H,3,0) -> CENTRO | G51: 67321663 | H51: BICUPSA | I51: 10000311 | J51: =VLOOKUP(I51,'Materiales,canteras'!C:D,2,0) -> Arena Triturada Basalto Malla | K51: =VLOOKUP(I51,'Materiales,canteras'!C:E,3,0) -> 1.651 | L51: 195 | M51: TN | N51: =TODAY() -> 46267 | O51: 31.12.9999 | R51: =1.5/100 -> 0.015 | S51: 260 | T51: =L51-(S51-(S51*R51)) -> -61.1 | U51: =L51 -> 195 | V51: 45 | W51: 1 | X51: =V51+U51 -> 240 | Y51: =IF(+VLOOKUP(I51,P.Referencia!E:S,3,FALSE)<=L51,"Champion","Gerente") -> #N/A | Z51: =VLOOKUP(I51,P.Referencia!E:S,3,0) -> #N/A | AA51: =(Z51-U51)/U51 -> #N/A | AB51: =U51*AA51 -> #N/A | AC51: =U51+AB51 -> #N/A
A52: 51 | C52: =_xlfn.CONCAT($C$1,D52,G52,I52,W52) -> LlaveD81367248861100002552 | D52: =VLOOKUP(E52,'NO MODIFICAR'!J:K,2,0) -> D813 | E52: MX-CANTERA SAN VICENTE | F52: =VLOOKUP(D52,'NO MODIFICAR'!F:H,3,0) -> CENTRO | G52: 67248861 | H52: EXCANORTE | I52: 10000255 | J52: =VLOOKUP(I52,'Materiales,canteras'!C:D,2,0) -> Arena Triturada Andesita Malla | K52: =VLOOKUP(I52,'Materiales,canteras'!C:E,3,0) -> 1.535 | L52: 85 | M52: TN | N52: =TODAY() -> 46267 | O52: 31.12.9999 | R52: =1.5/100 -> 0.015 | S52: 150 | T52: =L52-(S52-(S52*R52)) -> -62.75 | U52: =L52 -> 85 | V52: 0 | W52: 2 | X52: =V52+U52 -> 85 | Y52: =IF(+VLOOKUP(I52,P.Referencia!E:S,3,FALSE)<=L52,"Champion","Gerente") -> #N/A | Z52: =VLOOKUP(I52,P.Referencia!E:S,3,0) -> #N/A | AA52: =(Z52-U52)/U52 -> #N/A | AB52: =U52*AA52 -> #N/A | AC52: =U52+AB52 -> #N/A
A53: 52 | C53: =_xlfn.CONCAT($C$1,D53,G53,I53,W53) -> LlaveD81367248861100002532 | D53: =VLOOKUP(E53,'NO MODIFICAR'!J:K,2,0) -> D813 | E53: MX-CANTERA SAN VICENTE | F53: =VLOOKUP(D53,'NO MODIFICAR'!F:H,3,0) -> CENTRO | G53: 67248861 | H53: EXCANORTE | I53: 10000253 | J53: =VLOOKUP(I53,'Materiales,canteras'!C:D,2,0) -> Grava Triturada Andesita 20 mm | K53: =VLOOKUP(I53,'Materiales,canteras'!C:E,3,0) -> 1.385 | L53: 100 | M53: TN | N53: =TODAY() -> 46267 | O53: 31.12.9999 | R53: 0.015 | S53: 150 | T53: =L53-(S53-(S53*R53)) -> -47.75 | U53: =L53 -> 100 | V53: 0 | W53: 2 | X53: =V53+U53 -> 100 | Y53: =IF(+VLOOKUP(I53,P.Referencia!E:S,3,FALSE)<=L53,"Champion","Gerente") -> #N/A | Z53: =VLOOKUP(I53,P.Referencia!E:S,3,0) -> #N/A | AA53: =(Z53-U53)/U53 -> #N/A | AB53: =U53*AA53 -> #N/A | AC53: =U53+AB53 -> #N/A
A54: 53 | C54: =_xlfn.CONCAT($C$1,D54,G54,I54,W54) -> LlaveD81367248861100023502 | D54: =VLOOKUP(E54,'NO MODIFICAR'!J:K,2,0) -> D813 | E54: MX-CANTERA SAN VICENTE | F54: =VLOOKUP(D54,'NO MODIFICAR'!F:H,3,0) -> CENTRO | G54: 67248861 | H54: EXCANORTE | I54: 10002350 | J54: =VLOOKUP(I54,'Materiales,canteras'!C:D,2,0) -> Grava Triturada Andesita 10mm- | K54: =VLOOKUP(I54,'Materiales,canteras'!C:E,3,0) -> 1.246 | L54: 95 | M54: TN | N54: =TODAY() -> 46267 | O54: 31.12.9999 | R54: 0.015 | S54: 150 | T54: =L54-(S54-(S54*R54)) -> -52.75 | U54: =L54 -> 95 | V54: 0 | W54: 2 | X54: =V54+U54 -> 95 | Y54: =IF(+VLOOKUP(I54,P.Referencia!E:S,3,FALSE)<=L54,"Champion","Gerente") -> #N/A | Z54: =VLOOKUP(I54,P.Referencia!E:S,3,0) -> #N/A | AA54: =(Z54-U54)/U54 -> #N/A | AB54: =U54*AA54 -> #N/A | AC54: =U54+AB54 -> #N/A
A55: 54 | C55: =_xlfn.CONCAT($C$1,D55,G55,I55,W55) -> LlaveD86466308834100002362 | D55: =VLOOKUP(E55,'NO MODIFICAR'!J:K,2,0) -> D864 | E55: MX-CANTERA CERRO JARDIN | F55: =VLOOKUP(D55,'NO MODIFICAR'!F:H,3,0) -> CENTRO | G55: 66308834 | H55: CITARA CASAS ARA | I55: 10000236 | J55: =VLOOKUP(I55,'Materiales,canteras'!C:D,2,0) -> Grava Triturada Caliza 10 mm - | K55: =VLOOKUP(I55,'Materiales,canteras'!C:E,3,0) -> 1.41 | L55: 157.2 | M55: TN | N55: =TODAY() -> 46267 | O55: 31.12.9999 | S55: 240 | T55: =L55-(S55-(S55*R55)) -> -82.8 | U55: =L55 -> 157.2 | V55: 0 | W55: 2 | X55: =V55+U55 -> 157.2 | Y55: =IF(+VLOOKUP(I55,P.Referencia!E:S,3,FALSE)<=L55,"Champion","Gerente") -> #N/A | Z55: =VLOOKUP(I55,P.Referencia!E:S,3,0) -> #N/A | AA55: =(Z55-U55)/U55 -> #N/A | AB55: =U55*AA55 -> #N/A | AC55: =U55+AB55 -> #N/A
A56: 55 | C56: =_xlfn.CONCAT($C$1,D56,G56,I56,W56) -> LlaveD9026728177410226537 | D56: =VLOOKUP(E56,'NO MODIFICAR'!J:K,2,0) -> D902 | E56: MX-CALKINI | F56: =VLOOKUP(D56,'NO MODIFICAR'!F:H,3,0) -> SURESTE | G56: 67281774 | H56: ERIC RICARDO SORIANO DURAN | I56: 10226537 | J56: =VLOOKUP(I56,'Materiales,canteras'!C:D,2,0) -> SCREEN (DESPOLVE NOCLA) | K56: =VLOOKUP(I56,'Materiales,canteras'!C:E,3,0) -> 1.533 | L56: 29.35 | M56: TN | N56: =TODAY() -> 46267 | O56: 31.12.9999 | S56: 30 | T56: =L56-(S56-(S56*R56)) -> -0.65 | U56: =L56 -> 29.35 | V56: 0 | X56: =V56+U56 -> 29.35 | Y56: =IF(+VLOOKUP(I56,P.Referencia!E:S,3,FALSE)<=L56,"Champion","Gerente") -> #N/A | Z56: =VLOOKUP(I56,P.Referencia!E:S,3,0) -> #N/A | AA56: =(Z56-U56)/U56 -> #N/A | AB56: =U56*AA56 -> #N/A | AC56: =U56+AB56 -> #N/A
A57: 56 | C57: =_xlfn.CONCAT($C$1,D57,G57,I57,W57) -> LlaveD9026521957510226537 | D57: =VLOOKUP(E57,'NO MODIFICAR'!J:K,2,0) -> D902 | E57: MX-CALKINI | F57: =VLOOKUP(D57,'NO MODIFICAR'!F:H,3,0) -> SURESTE | G57: 65219575 | H57: ANA LETICIA CARMONA GARCIA | I57: 10226537 | J57: =VLOOKUP(I57,'Materiales,canteras'!C:D,2,0) -> SCREEN (DESPOLVE NOCLA) | K57: =VLOOKUP(I57,'Materiales,canteras'!C:E,3,0) -> 1.533 | L57: 29.35 | M57: TN | N57: =TODAY() -> 46267 | O57: 31.12.9999 | S57: 30 | T57: =L57-(S57-(S57*R57)) -> -0.65 | U57: =L57 -> 29.35 | V57: 0 | X57: =V57+U57 -> 29.35 | Y57: =IF(+VLOOKUP(I57,P.Referencia!E:S,3,FALSE)<=L57,"Champion","Gerente") -> #N/A | Z57: =VLOOKUP(I57,P.Referencia!E:S,3,0) -> #N/A | AA57: =(Z57-U57)/U57 -> #N/A | AB57: =U57*AA57 -> #N/A | AC57: =U57+AB57 -> #N/A
A58: 57 | C58: =_xlfn.CONCAT($C$1,D58,G58,I58,W58) -> LlaveD9026686305210226537 | D58: =VLOOKUP(E58,'NO MODIFICAR'!J:K,2,0) -> D902 | E58: MX-CALKINI | F58: =VLOOKUP(D58,'NO MODIFICAR'!F:H,3,0) -> SURESTE | G58: 66863052 | H58: ANA LETICIA CARMONA GARCIA | I58: 10226537 | J58: =VLOOKUP(I58,'Materiales,canteras'!C:D,2,0) -> SCREEN (DESPOLVE NOCLA) | K58: =VLOOKUP(I58,'Materiales,canteras'!C:E,3,0) -> 1.533 | L58: 29.35 | M58: TN | N58: =TODAY() -> 46267 | O58: 31.12.9999 | S58: 30 | T58: =L58-(S58-(S58*R58)) -> -0.65 | U58: =L58 -> 29.35 | V58: 0 | X58: =V58+U58 -> 29.35 | Y58: =IF(+VLOOKUP(I58,P.Referencia!E:S,3,FALSE)<=L58,"Champion","Gerente") -> #N/A | Z58: =VLOOKUP(I58,P.Referencia!E:S,3,0) -> #N/A | AA58: =(Z58-U58)/U58 -> #N/A | AB58: =U58*AA58 -> #N/A | AC58: =U58+AB58 -> #N/A
A59: 58 | C59: =_xlfn.CONCAT($C$1,D59,G59,I59,W59) -> LlaveD86165164446100002332 | D59: =VLOOKUP(E59,'NO MODIFICAR'!J:K,2,0) -> D861 | E59: MX-CANTERA QUERETARO | F59: =VLOOKUP(D59,'NO MODIFICAR'!F:H,3,0) -> CENTRO | G59: 65164446 | H59: PAVIMENTOS Y URBANIZACIONES DE QRO SA | I59: 10000233 | J59: =VLOOKUP(I59,'Materiales,canteras'!C:D,2,0) -> Grava Triturada Basalto 40 mm | K59: =VLOOKUP(I59,'Materiales,canteras'!C:E,3,0) -> 1.456 | L59: 235 | M59: TN | N59: =TODAY() -> 46267 | O59: 31.12.2999 | R59: 0.015 | S59: 282 | T59: =L59-(S59-(S59*R59)) -> -42.77 | U59: =L59 -> 235 | V59: 0 | W59: 2 | Y59: =IF(+VLOOKUP(I59,P.Referencia!E:S,3,FALSE)<=L59,"Champion","Gerente") -> #N/A | Z59: =VLOOKUP(I59,P.Referencia!E:S,3,0) -> #N/A | AA59: =(Z59-U59)/U59 -> #N/A | AB59: =U59*AA59 -> #N/A | AC59: =U59+AB59 -> #N/A
A60: 59 | C60: =_xlfn.CONCAT($C$1,D60,G60,I60,W60) -> LlaveD81367320967100002532 | D60: =VLOOKUP(E60,'NO MODIFICAR'!J:K,2,0) -> D813 | E60: MX-CANTERA SAN VICENTE | F60: =VLOOKUP(D60,'NO MODIFICAR'!F:H,3,0) -> CENTRO | G60: 67320967 | H60: CONSTRUCCIONES Y ASFALTOS SOTO'S | I60: 10000253 | J60: Grava Triturada Andesita 20 mm - 3/4" | K60: =VLOOKUP(I60,'Materiales,canteras'!C:E,3,0) -> 1.385 | L60: 100 | M60: TN | N60: =TODAY() -> 46267 | O60: 31.12.2999 | R60: 0.015 | S60: 150 | T60: =L60-(S60-(S60*R60)) -> -47.75 | U60: =L60 -> 100 | V60: 0 | W60: 2 | X60: =U60+V60 -> 100 | Y60: =IF(+VLOOKUP(I60,P.Referencia!E:S,3,FALSE)<=L60,"Champion","Gerente") -> #N/A | Z60: =VLOOKUP(I60,P.Referencia!E:S,3,0) -> #N/A | AA60: =(Z60-U60)/U60 -> #N/A | AB60: =U60*AA60 -> #N/A | AC60: =U60+AB60 -> #N/A
A61: 60 | C61: =_xlfn.CONCAT($C$1,D61,G61,I61,W61) -> LlaveDU0767323242100001032 | D61: =VLOOKUP(E61,'NO MODIFICAR'!J:K,2,0) -> DU07 | E61: MX-CANCÚN III | F61: =VLOOKUP(D61,'NO MODIFICAR'!F:H,3,0) -> SURESTE | G61: 67323242 | H61: SOLUCIONES INTEGRALES DE INGENIERIA | I61: 10000103 | J61: =VLOOKUP(I61,'Materiales,canteras'!C:D,2,0) -> Base H Triturada Caliza 1 1/2" a Finos | K61: =VLOOKUP(I61,'Materiales,canteras'!C:E,3,0) -> 1.462 | L61: 123.119 | M61: TN | N61: =TODAY() -> 46267 | O61: 31.12.2999 | R61: 0.015 | S61: 150 | T61: =L61-(S61-(S61*R61)) -> -24.631 | U61: =L61 -> 123.119 | V61: 0 | W61: 2 | X61: =U61+V61 -> 123.119 | Y61: =IF(+VLOOKUP(I61,P.Referencia!E:S,3,FALSE)<=L61,"Champion","Gerente") -> #N/A | Z61: =VLOOKUP(I61,P.Referencia!E:S,3,0) -> #N/A | AA61: =(Z61-U61)/U61 -> #N/A | AB61: =U61*AA61 -> #N/A | AC61: =U61+AB61 -> #N/A
A62: 61 | C62: =_xlfn.CONCAT($C$1,D62,G62,I62,W62) -> LlaveDU0767323138100001032 | D62: =VLOOKUP(E62,'NO MODIFICAR'!J:K,2,0) -> DU07 | E62: MX-CANCÚN III | F62: =VLOOKUP(D62,'NO MODIFICAR'!F:H,3,0) -> SURESTE | G62: 67323138 | H62: JAC AUTOTRANSPORTE RECOGIDO | I62: 10000103 | J62: =VLOOKUP(I62,'Materiales,canteras'!C:D,2,0) -> Base H Triturada Caliza 1 1/2" a Finos | K62: =VLOOKUP(I62,'Materiales,canteras'!C:E,3,0) -> 1.462 | L62: 123.119 | M62: TN | N62: =TODAY() -> 46267 | O62: 31.12.2999 | R62: 0.015 | S62: 150 | T62: =L62-(S62-(S62*R62)) -> -24.631 | U62: =L62 -> 123.119 | V62: 0 | W62: 2 | X62: =U62+V62 -> 123.119 | Y62: =IF(+VLOOKUP(I62,P.Referencia!E:S,3,FALSE)<=L62,"Champion","Gerente") -> #N/A | Z62: =VLOOKUP(I62,P.Referencia!E:S,3,0) -> #N/A | AA62: =(Z62-U62)/U62 -> #N/A | AB62: =U62*AA62 -> #N/A | AC62: =U62+AB62 -> #N/A
A63: 62 | C63: =_xlfn.CONCAT($C$1,D63,G63,I63,W63) -> LlaveDU0767204433100001032 | D63: =VLOOKUP(E63,'NO MODIFICAR'!J:K,2,0) -> DU07 | E63: MX-CANCÚN III | F63: =VLOOKUP(D63,'NO MODIFICAR'!F:H,3,0) -> SURESTE | G63: 67204433 | H63: JUAN ROMERO RECOG | I63: 10000103 | J63: =VLOOKUP(I63,'Materiales,canteras'!C:D,2,0) -> Base H Triturada Caliza 1 1/2" a Finos | K63: =VLOOKUP(I63,'Materiales,canteras'!C:E,3,0) -> 1.462 | L63: 112.86 | M63: TN | N63: =TODAY() -> 46267 | O63: 31.12.9999 | R63: 0.015 | S63: 150 | T63: =L63-(S63-(S63*R63)) -> -34.89 | U63: =L63 -> 112.86 | V63: 0 | W63: 2 | X63: =U63+V63 -> 112.86 | Y63: =IF(+VLOOKUP(I63,P.Referencia!E:S,3,FALSE)<=L63,"Champion","Gerente") -> #N/A | Z63: =VLOOKUP(I63,P.Referencia!E:S,3,0) -> #N/A | AA63: =(Z63-U63)/U63 -> #N/A | AB63: =U63*AA63 -> #N/A | AC63: =U63+AB63 -> #N/A
A64: 63 | B64: Junio | C64: =_xlfn.CONCAT($C$1,D64,G64,I64,W64) -> LlaveD86467011332100002402 | D64: =VLOOKUP(E64,'NO MODIFICAR'!J:K,2,0) -> D864 | E64: MX-CANTERA CERRO JARDIN | F64: =VLOOKUP(D64,'NO MODIFICAR'!F:H,3,0) -> CENTRO | G64: 67011332 | H64: Gab Rio Remedios | I64: 10000240 | J64: =VLOOKUP(I64,'Materiales,canteras'!C:D,2,0) -> Grava Triturada Caliza 20 mm - | K64: =VLOOKUP(I64,'Materiales,canteras'!C:E,3,0) -> 1.462 | L64: 127 | M64: TN | N64: =TODAY() -> 46267 | O64: 31.12.9999 | R64: 0.015 | S64: 280 | T64: =L64-(S64-(S64*R64)) -> -148.8 | U64: =L64 -> 127 | V64: 0 | W64: 2 | X64: =U64+V64 -> 127 | Y64: =IF(+VLOOKUP(I64,P.Referencia!E:S,3,FALSE)<=L64,"Champion","Gerente") -> #N/A | Z64: =VLOOKUP(I64,P.Referencia!E:S,3,0) -> #N/A | AA64: =(Z64-U64)/U64 -> #N/A | AB64: =U64*AA64 -> #N/A | AC64: =U64+AB64 -> #N/A
A65: 64 | B65: Junio | C65: =_xlfn.CONCAT($C$1,D65,G65,I65,W65) -> LlaveD86467011332100010732 | D65: =VLOOKUP(E65,'NO MODIFICAR'!J:K,2,0) -> D864 | E65: MX-CANTERA CERRO JARDIN | F65: =VLOOKUP(D65,'NO MODIFICAR'!F:H,3,0) -> CENTRO | G65: 67011332 | H65: Gab Rio Remedios | I65: 10001073 | J65: =VLOOKUP(I65,'Materiales,canteras'!C:D,2,0) -> Arena Triturada Caliza Malla 4 | K65: =VLOOKUP(I65,'Materiales,canteras'!C:E,3,0) -> 1.56 | L65: 85 | M65: TN | N65: =TODAY() -> 46267 | O65: 31.12.2999 | R65: 0.015 | S65: 150 | T65: =L65-(S65-(S65*R65)) -> -62.75 | U65: =L65 -> 85 | V65: 0 | W65: 2 | X65: =U65+V65 -> 85 | Y65: =IF(+VLOOKUP(I65,P.Referencia!E:S,3,FALSE)<=L65,"Champion","Gerente") -> #N/A | Z65: =VLOOKUP(I65,P.Referencia!E:S,3,0) -> #N/A | AA65: =(Z65-U65)/U65 -> #N/A | AB65: =U65*AA65 -> #N/A | AC65: =U65+AB65 -> #N/A
A66: 65 | B66: Junio | C66: =_xlfn.CONCAT($C$1,D66,G66,I66,W66) -> LlaveD86467162298100002402 | D66: =VLOOKUP(E66,'NO MODIFICAR'!J:K,2,0) -> D864 | E66: MX-CANTERA CERRO JARDIN | F66: =VLOOKUP(D66,'NO MODIFICAR'!F:H,3,0) -> CENTRO | G66: 67162298 | H66: Gab Los Reyes La Paz | I66: 10000240 | J66: =VLOOKUP(I66,'Materiales,canteras'!C:D,2,0) -> Grava Triturada Caliza 20 mm - | K66: =VLOOKUP(I66,'Materiales,canteras'!C:E,3,0) -> 1.462 | L66: 127 | M66: TN | N66: =TODAY() -> 46267 | O66: 31.12.2999 | R66: 0.015 | S66: 280 | T66: =L66-(S66-(S66*R66)) -> -148.8 | U66: =L66 -> 127 | V66: 0 | W66: 2 | X66: =U66+V66 -> 127 | Y66: =IF(+VLOOKUP(I66,P.Referencia!E:S,3,FALSE)<=L66,"Champion","Gerente") -> #N/A | Z66: =VLOOKUP(I66,P.Referencia!E:S,3,0) -> #N/A | AA66: =(Z66-U66)/U66 -> #N/A | AB66: =U66*AA66 -> #N/A | AC66: =U66+AB66 -> #N/A
A67: 66 | B67: Junio | C67: =_xlfn.CONCAT($C$1,D67,G67,I67,W67) -> LlaveD86467162298100010732 | D67: =VLOOKUP(E67,'NO MODIFICAR'!J:K,2,0) -> D864 | E67: MX-CANTERA CERRO JARDIN | F67: =VLOOKUP(D67,'NO MODIFICAR'!F:H,3,0) -> CENTRO | G67: 67162298 | H67: Gab Los Reyes La Paz | I67: 10001073 | J67: =VLOOKUP(I67,'Materiales,canteras'!C:D,2,0) -> Arena Triturada Caliza Malla 4 | K67: =VLOOKUP(I67,'Materiales,canteras'!C:E,3,0) -> 1.56 | L67: 85 | M67: TN | N67: =TODAY() -> 46267 | O67: 31.12.2999 | R67: 0.015 | S67: 150 | T67: =L67-(S67-(S67*R67)) -> -62.75 | U67: =L67 -> 85 | V67: 0 | W67: 2 | X67: =U67+V67 -> 85 | Y67: =IF(+VLOOKUP(I67,P.Referencia!E:S,3,FALSE)<=L67,"Champion","Gerente") -> #N/A | Z67: =VLOOKUP(I67,P.Referencia!E:S,3,0) -> #N/A | AA67: =(Z67-U67)/U67 -> #N/A | AB67: =U67*AA67 -> #N/A | AC67: =U67+AB67 -> #N/A
A68: 67 | B68: Junio | C68: =_xlfn.CONCAT($C$1,D68,G68,I68,W68) -> LlaveD86467011332100002692 | D68: =VLOOKUP(E68,'NO MODIFICAR'!J:K,2,0) -> D864 | E68: MX-CANTERA CERRO JARDIN | F68: =VLOOKUP(D68,'NO MODIFICAR'!F:H,3,0) -> CENTRO | G68: 67011332 | H68: Gab Rio Remedios | I68: 10000269 | J68: =VLOOKUP(I68,'Materiales,canteras'!C:D,2,0) -> Grava Triturada Caliza 13 mm - | K68: =VLOOKUP(I68,'Materiales,canteras'!C:E,3,0) -> 1.423 | L68: 137 | M68: TN | N68: =TODAY() -> 46267 | O68: 31.12.2999 | R68: 0.015 | S68: 250 | T68: =L68-(S68-(S68*R68)) -> -109.25 | U68: =L68 -> 137 | V68: 0 | W68: 2 | X68: =U68+V68 -> 137 | Y68: =IF(+VLOOKUP(I68,P.Referencia!E:S,3,FALSE)<=L68,"Champion","Gerente") -> #N/A | Z68: =VLOOKUP(I68,P.Referencia!E:S,3,0) -> #N/A | AA68: =(Z68-U68)/U68 -> #N/A | AB68: =U68*AA68 -> #N/A | AC68: =U68+AB68 -> #N/A
A69: 68 | B69: Junio | C69: =_xlfn.CONCAT($C$1,D69,G69,I69,W69) -> LlaveD86467162298100002692 | D69: =VLOOKUP(E69,'NO MODIFICAR'!J:K,2,0) -> D864 | E69: MX-CANTERA CERRO JARDIN | F69: =VLOOKUP(D69,'NO MODIFICAR'!F:H,3,0) -> CENTRO | G69: 67162298 | H69: Gab Los Reyes La Paz | I69: 10000269 | J69: =VLOOKUP(I69,'Materiales,canteras'!C:D,2,0) -> Grava Triturada Caliza 13 mm - | K69: =VLOOKUP(I69,'Materiales,canteras'!C:E,3,0) -> 1.423 | L69: 137 | M69: TN | N69: =TODAY() -> 46267 | O69: 31.12.2999 | R69: 0.015 | S69: 250 | T69: =L69-(S69-(S69*R69)) -> -109.25 | U69: =L69 -> 137 | V69: 0 | W69: 2 | X69: =U69+V69 -> 137 | Y69: =IF(+VLOOKUP(I69,P.Referencia!E:S,3,FALSE)<=L69,"Champion","Gerente") -> #N/A | Z69: =VLOOKUP(I69,P.Referencia!E:S,3,0) -> #N/A | AA69: =(Z69-U69)/U69 -> #N/A | AB69: =U69*AA69 -> #N/A | AC69: =U69+AB69 -> #N/A
A70: 69 | B70: Junio | C70: =_xlfn.CONCAT($C$1,D70,G70,I70,W70) -> LlaveD86466534221100010732 | D70: =VLOOKUP(E70,'NO MODIFICAR'!J:K,2,0) -> D864 | E70: MX-CANTERA CERRO JARDIN | F70: =VLOOKUP(D70,'NO MODIFICAR'!F:H,3,0) -> CENTRO | G70: 66534221 | H70: casas ara tizayuca (MJRM) | I70: 10001073 | J70: =VLOOKUP(I70,'Materiales,canteras'!C:D,2,0) -> Arena Triturada Caliza Malla 4 | K70: =VLOOKUP(I70,'Materiales,canteras'!C:E,3,0) -> 1.56 | L70: 104.52 | M70: TN | N70: =TODAY() -> 46267 | O70: 31.12.2999 | R70: 0.05 | S70: 150 | T70: =L70-(S70-(S70*R70)) -> -37.98 | U70: =L70 -> 104.52 | V70: 0 | W70: 2 | X70: =U70+V70 -> 104.52 | Y70: =IF(+VLOOKUP(I70,P.Referencia!E:S,3,FALSE)<=L70,"Champion","Gerente") -> #N/A | Z70: =VLOOKUP(I70,P.Referencia!E:S,3,0) -> #N/A | AA70: =(Z70-U70)/U70 -> #N/A | AB70: =U70*AA70 -> #N/A | AC70: =U70+AB70 -> #N/A
A71: 70 | B71: Junio | C71: =_xlfn.CONCAT($C$1,D71,G71,I71,W71) -> LlaveD86466534221100002402 | D71: =VLOOKUP(E71,'NO MODIFICAR'!J:K,2,0) -> D864 | E71: MX-CANTERA CERRO JARDIN | F71: =VLOOKUP(D71,'NO MODIFICAR'!F:H,3,0) -> CENTRO | G71: 66534221 | H71: casas ara tizayuca (MJRM) | I71: 10000240 | J71: =VLOOKUP(I71,'Materiales,canteras'!C:D,2,0) -> Grava Triturada Caliza 20 mm - | K71: =VLOOKUP(I71,'Materiales,canteras'!C:E,3,0) -> 1.462 | L71: 186.09 | M71: TN | N71: =TODAY() -> 46267 | O71: 31.12.2999 | R71: 0.05 | S71: 280 | T71: =L71-(S71-(S71*R71)) -> -79.91 | U71: =L71 -> 186.09 | V71: 0 | W71: 2 | X71: =U71+V71 -> 186.09 | Y71: =IF(+VLOOKUP(I71,P.Referencia!E:S,3,FALSE)<=L71,"Champion","Gerente") -> #N/A | Z71: =VLOOKUP(I71,P.Referencia!E:S,3,0) -> #N/A | AA71: =(Z71-U71)/U71 -> #N/A | AB71: =U71*AA71 -> #N/A | AC71: =U71+AB71 -> #N/A
A72: 71 | B72: Junio | C72: =_xlfn.CONCAT($C$1,D72,G72,I72,W72) -> LlaveD8646729725910001203 | D72: =VLOOKUP(E72,'NO MODIFICAR'!J:K,2,0) -> D864 | E72: MX-CANTERA CERRO JARDIN | F72: =VLOOKUP(D72,'NO MODIFICAR'!F:H,3,0) -> CENTRO | G72: 67297259 | H72: CLIENTE GLOBAL SOLUTION TORREBELL | I72: 10001203 | J72: =VLOOKUP(I72,'Materiales,canteras'!C:D,2,0) -> Desperdicio Triturado Caliza | K72: =VLOOKUP(I72,'Materiales,canteras'!C:E,3,0) -> 1.665 | L72: 20 | M72: TN | N72: =TODAY() -> 46267 | O72: 31.12.2999 | R72: 0.015 | S72: 22 | T72: =L72-(S72-(S72*R72)) -> -1.67 | U72: =L72 -> 20 | V72: 100 | X72: =U72+V72 -> 120 | Y72: =IF(+VLOOKUP(I72,P.Referencia!E:S,3,FALSE)<=L72,"Champion","Gerente") -> #N/A | Z72: =VLOOKUP(I72,P.Referencia!E:S,3,0) -> #N/A | AA72: =(Z72-U72)/U72 -> #N/A | AB72: =U72*AA72 -> #N/A | AC72: =U72+AB72 -> #N/A
A73: 72 | B73: Junio | C73: =_xlfn.CONCAT($C$1,D73,G73,I73,W73) -> LlaveD8616691381910000311 | D73: =VLOOKUP(E73,'NO MODIFICAR'!J:K,2,0) -> D861 | E73: MX-CANTERA QUERETARO | F73: =VLOOKUP(D73,'NO MODIFICAR'!F:H,3,0) -> CENTRO | G73: 66913819 | H73: PLANTA SJR (Concretos Mixerplus) | I73: 10000311 | J73: =VLOOKUP(I73,'Materiales,canteras'!C:D,2,0) -> Arena Triturada Basalto Malla | K73: =VLOOKUP(I73,'Materiales,canteras'!C:E,3,0) -> 1.651 | L73: 176 | M73: TN | N73: =TODAY() -> 46267 | O73: 31.12.2999 | S73: 260 | T73: =L73-(S73-(S73*R73)) -> -84 | U73: =L73 -> 176 | V73: 0 | X73: =U73+V73 -> 176 | Y73: =IF(+VLOOKUP(I73,P.Referencia!E:S,3,FALSE)<=L73,"Champion","Gerente") -> #N/A | Z73: =VLOOKUP(I73,P.Referencia!E:S,3,0) -> #N/A | AA73: =(Z73-U73)/U73 -> #N/A | AB73: =U73*AA73 -> #N/A | AC73: =U73+AB73 -> #N/A
A74: 73 | B74: Junio | C74: =_xlfn.CONCAT($C$1,D74,G74,I74,W74) -> LlaveD8616691381910000229 | D74: =VLOOKUP(E74,'NO MODIFICAR'!J:K,2,0) -> D861 | E74: MX-CANTERA QUERETARO | F74: =VLOOKUP(D74,'NO MODIFICAR'!F:H,3,0) -> CENTRO | G74: 66913819 | H74: PLANTA SJR (Concretos Mixerplus) | I74: 10000229 | J74: =VLOOKUP(I74,'Materiales,canteras'!C:D,2,0) -> Grava Triturada Basalto 10 mm | K74: =VLOOKUP(I74,'Materiales,canteras'!C:E,3,0) -> 1.522 | L74: 217.8 | M74: TN | N74: =TODAY() -> 46267 | O74: 31.12.2999 | S74: 320 | T74: =L74-(S74-(S74*R74)) -> -102.2 | U74: =L74 -> 217.8 | V74: 0 | X74: =U74+V74 -> 217.8 | Y74: =IF(+VLOOKUP(I74,P.Referencia!E:S,3,FALSE)<=L74,"Champion","Gerente") -> #N/A | Z74: =VLOOKUP(I74,P.Referencia!E:S,3,0) -> #N/A | AA74: =(Z74-U74)/U74 -> #N/A | AB74: =U74*AA74 -> #N/A | AC74: =U74+AB74 -> #N/A
A75: 74 | B75: Junio | C75: =_xlfn.CONCAT($C$1,D75,G75,I75,W75) -> LlaveD8616691381910000231 | D75: =VLOOKUP(E75,'NO MODIFICAR'!J:K,2,0) -> D861 | E75: MX-CANTERA QUERETARO | F75: =VLOOKUP(D75,'NO MODIFICAR'!F:H,3,0) -> CENTRO | G75: 66913819 | H75: PLANTA SJR (Concretos Mixerplus) | I75: 10000231 | J75: =VLOOKUP(I75,'Materiales,canteras'!C:D,2,0) -> Grava Triturada Basalto 20 mm | K75: =VLOOKUP(I75,'Materiales,canteras'!C:E,3,0) -> 1.565 | L75: 209 | M75: TN | N75: =TODAY() -> 46267 | O75: 31.12.2999 | S75: 280 | T75: =L75-(S75-(S75*R75)) -> -71 | U75: =L75 -> 209 | V75: 0 | X75: =U75+V75 -> 209 | Y75: =IF(+VLOOKUP(I75,P.Referencia!E:S,3,FALSE)<=L75,"Champion","Gerente") -> #N/A | Z75: =VLOOKUP(I75,P.Referencia!E:S,3,0) -> #N/A | AA75: =(Z75-U75)/U75 -> #N/A | AB75: =U75*AA75 -> #N/A | AC75: =U75+AB75 -> #N/A
A76: 75 | B76: Junio | C76: =_xlfn.CONCAT($C$1,D76,G76,I76,W76) -> LlaveD8616691381910000233 | D76: =VLOOKUP(E76,'NO MODIFICAR'!J:K,2,0) -> D861 | E76: MX-CANTERA QUERETARO | F76: =VLOOKUP(D76,'NO MODIFICAR'!F:H,3,0) -> CENTRO | G76: 66913819 | H76: PLANTA SJR (Concretos Mixerplus) | I76: 10000233 | J76: =VLOOKUP(I76,'Materiales,canteras'!C:D,2,0) -> Grava Triturada Basalto 40 mm | K76: =VLOOKUP(I76,'Materiales,canteras'!C:E,3,0) -> 1.456 | L76: 209 | M76: TN | N76: =TODAY() -> 46267 | O76: 31.12.2999 | S76: 282 | T76: =L76-(S76-(S76*R76)) -> -73 | U76: =L76 -> 209 | V76: 0 | X76: =U76+V76 -> 209 | Y76: =IF(+VLOOKUP(I76,P.Referencia!E:S,3,FALSE)<=L76,"Champion","Gerente") -> #N/A | Z76: =VLOOKUP(I76,P.Referencia!E:S,3,0) -> #N/A | AA76: =(Z76-U76)/U76 -> #N/A | AB76: =U76*AA76 -> #N/A | AC76: =U76+AB76 -> #N/A
A77: 76 | B77: Junio | C77: =_xlfn.CONCAT($C$1,D77,G77,I77,W77) -> LlaveD8616691389710000311 | D77: =VLOOKUP(E77,'NO MODIFICAR'!J:K,2,0) -> D861 | E77: MX-CANTERA QUERETARO | F77: =VLOOKUP(D77,'NO MODIFICAR'!F:H,3,0) -> CENTRO | G77: 66913897 | H77: Planta la Griega (Concretos Mixerplus) | I77: 10000311 | J77: =VLOOKUP(I77,'Materiales,canteras'!C:D,2,0) -> Arena Triturada Basalto Malla | K77: =VLOOKUP(I77,'Materiales,canteras'!C:E,3,0) -> 1.651 | L77: 176 | M77: TN | N77: =TODAY() -> 46267 | O77: 31.12.2999 | S77: 260 | T77: =L77-(S77-(S77*R77)) -> -84 | U77: =L77 -> 176 | V77: 0 | X77: =U77+V77 -> 176 | Y77: =IF(+VLOOKUP(I77,P.Referencia!E:S,3,FALSE)<=L77,"Champion","Gerente") -> #N/A | Z77: =VLOOKUP(I77,P.Referencia!E:S,3,0) -> #N/A | AA77: =(Z77-U77)/U77 -> #N/A | AB77: =U77*AA77 -> #N/A | AC77: =U77+AB77 -> #N/A
A78: 77 | B78: Junio | C78: =_xlfn.CONCAT($C$1,D78,G78,I78,W78) -> LlaveD8616691389710000229 | D78: =VLOOKUP(E78,'NO MODIFICAR'!J:K,2,0) -> D861 | E78: MX-CANTERA QUERETARO | F78: =VLOOKUP(D78,'NO MODIFICAR'!F:H,3,0) -> CENTRO | G78: 66913897 | H78: Planta la Griega (Concretos Mixerplus) | I78: 10000229 | J78: =VLOOKUP(I78,'Materiales,canteras'!C:D,2,0) -> Grava Triturada Basalto 10 mm | K78: =VLOOKUP(I78,'Materiales,canteras'!C:E,3,0) -> 1.522 | L78: 217.8 | M78: TN | N78: =TODAY() -> 46267 | O78: 31.12.2999 | S78: 320 | T78: =L78-(S78-(S78*R78)) -> -102.2 | U78: =L78 -> 217.8 | V78: 0 | X78: =U78+V78 -> 217.8 | Y78: =IF(+VLOOKUP(I78,P.Referencia!E:S,3,FALSE)<=L78,"Champion","Gerente") -> #N/A | Z78: =VLOOKUP(I78,P.Referencia!E:S,3,0) -> #N/A | AA78: =(Z78-U78)/U78 -> #N/A | AB78: =U78*AA78 -> #N/A | AC78: =U78+AB78 -> #N/A
A79: 78 | B79: Junio | C79: =_xlfn.CONCAT($C$1,D79,G79,I79,W79) -> LlaveD8616691389710000231 | D79: =VLOOKUP(E79,'NO MODIFICAR'!J:K,2,0) -> D861 | E79: MX-CANTERA QUERETARO | F79: =VLOOKUP(D79,'NO MODIFICAR'!F:H,3,0) -> CENTRO | G79: 66913897 | H79: Planta la Griega (Concretos Mixerplus) | I79: 10000231 | J79: =VLOOKUP(I79,'Materiales,canteras'!C:D,2,0) -> Grava Triturada Basalto 20 mm | K79: =VLOOKUP(I79,'Materiales,canteras'!C:E,3,0) -> 1.565 | L79: 209 | M79: TN | N79: =TODAY() -> 46267 | O79: 31.12.2999 | S79: 280 | T79: =L79-(S79-(S79*R79)) -> -71 | U79: =L79 -> 209 | V79: 0 | X79: =U79+V79 -> 209 | Y79: =IF(+VLOOKUP(I79,P.Referencia!E:S,3,FALSE)<=L79,"Champion","Gerente") -> #N/A | Z79: =VLOOKUP(I79,P.Referencia!E:S,3,0) -> #N/A | AA79: =(Z79-U79)/U79 -> #N/A | AB79: =U79*AA79 -> #N/A | AC79: =U79+AB79 -> #N/A
A80: 79 | B80: Junio | C80: =_xlfn.CONCAT($C$1,D80,G80,I80,W80) -> LlaveD8616691389710000233 | D80: =VLOOKUP(E80,'NO MODIFICAR'!J:K,2,0) -> D861 | E80: MX-CANTERA QUERETARO | F80: =VLOOKUP(D80,'NO MODIFICAR'!F:H,3,0) -> CENTRO | G80: 66913897 | H80: Planta la Griega (Concretos Mixerplus) | I80: 10000233 | J80: =VLOOKUP(I80,'Materiales,canteras'!C:D,2,0) -> Grava Triturada Basalto 40 mm | K80: =VLOOKUP(I80,'Materiales,canteras'!C:E,3,0) -> 1.456 | L80: 209 | M80: TN | N80: =TODAY() -> 46267 | O80: 31.12.2999 | S80: 282 | T80: =L80-(S80-(S80*R80)) -> -73 | U80: =L80 -> 209 | V80: 0 | X80: =U80+V80 -> 209 | Y80: =IF(+VLOOKUP(I80,P.Referencia!E:S,3,FALSE)<=L80,"Champion","Gerente") -> #N/A | Z80: =VLOOKUP(I80,P.Referencia!E:S,3,0) -> #N/A | AA80: =(Z80-U80)/U80 -> #N/A | AB80: =U80*AA80 -> #N/A | AC80: =U80+AB80 -> #N/A
A81: 80 | B81: Junio | C81: =_xlfn.CONCAT($C$1,D81,G81,I81,W81) -> LlaveD8616693678810000311 | D81: =VLOOKUP(E81,'NO MODIFICAR'!J:K,2,0) -> D861 | E81: MX-CANTERA QUERETARO | F81: =VLOOKUP(D81,'NO MODIFICAR'!F:H,3,0) -> CENTRO | G81: 66936788 | H81: Planta El Castillo (Concretos Mixerplus) | I81: 10000311 | J81: =VLOOKUP(I81,'Materiales,canteras'!C:D,2,0) -> Arena Triturada Basalto Malla | K81: =VLOOKUP(I81,'Materiales,canteras'!C:E,3,0) -> 1.651 | L81: 176 | M81: TN | N81: =TODAY() -> 46267 | O81: 31.12.2999 | S81: 260 | T81: =L81-(S81-(S81*R81)) -> -84 | U81: =L81 -> 176 | V81: 0 | X81: =U81+V81 -> 176 | Y81: =IF(+VLOOKUP(I81,P.Referencia!E:S,3,FALSE)<=L81,"Champion","Gerente") -> #N/A | Z81: =VLOOKUP(I81,P.Referencia!E:S,3,0) -> #N/A | AA81: =(Z81-U81)/U81 -> #N/A | AB81: =U81*AA81 -> #N/A | AC81: =U81+AB81 -> #N/A
A82: 81 | B82: Junio | C82: =_xlfn.CONCAT($C$1,D82,G82,I82,W82) -> LlaveD8616693678810000229 | D82: =VLOOKUP(E82,'NO MODIFICAR'!J:K,2,0) -> D861 | E82: MX-CANTERA QUERETARO | F82: =VLOOKUP(D82,'NO MODIFICAR'!F:H,3,0) -> CENTRO | G82: 66936788 | H82: Planta El Castillo (Concretos Mixerplus) | I82: 10000229 | J82: =VLOOKUP(I82,'Materiales,canteras'!C:D,2,0) -> Grava Triturada Basalto 10 mm | K82: =VLOOKUP(I82,'Materiales,canteras'!C:E,3,0) -> 1.522 | L82: 217.8 | M82: TN | N82: =TODAY() -> 46267 | O82: 31.12.2999 | S82: 320 | T82: =L82-(S82-(S82*R82)) -> -102.2 | U82: =L82 -> 217.8 | V82: 0 | X82: =U82+V82 -> 217.8 | Y82: =IF(+VLOOKUP(I82,P.Referencia!E:S,3,FALSE)<=L82,"Champion","Gerente") -> #N/A | Z82: =VLOOKUP(I82,P.Referencia!E:S,3,0) -> #N/A | AA82: =(Z82-U82)/U82 -> #N/A | AB82: =U82*AA82 -> #N/A | AC82: =U82+AB82 -> #N/A
A83: 82 | B83: Junio | C83: =_xlfn.CONCAT($C$1,D83,G83,I83,W83) -> LlaveD8616693678810000231 | D83: =VLOOKUP(E83,'NO MODIFICAR'!J:K,2,0) -> D861 | E83: MX-CANTERA QUERETARO | F83: =VLOOKUP(D83,'NO MODIFICAR'!F:H,3,0) -> CENTRO | G83: 66936788 | H83: Planta El Castillo (Concretos Mixerplus) | I83: 10000231 | J83: =VLOOKUP(I83,'Materiales,canteras'!C:D,2,0) -> Grava Triturada Basalto 20 mm | K83: =VLOOKUP(I83,'Materiales,canteras'!C:E,3,0) -> 1.565 | L83: 209 | M83: TN | N83: =TODAY() -> 46267 | O83: 31.12.2999 | S83: 280 | T83: =L83-(S83-(S83*R83)) -> -71 | U83: =L83 -> 209 | V83: 0 | X83: =U83+V83 -> 209 | Y83: =IF(+VLOOKUP(I83,P.Referencia!E:S,3,FALSE)<=L83,"Champion","Gerente") -> #N/A | Z83: =VLOOKUP(I83,P.Referencia!E:S,3,0) -> #N/A | AA83: =(Z83-U83)/U83 -> #N/A | AB83: =U83*AA83 -> #N/A | AC83: =U83+AB83 -> #N/A
A84: 83 | B84: Junio | C84: =_xlfn.CONCAT($C$1,D84,G84,I84,W84) -> LlaveD8616693678810000233 | D84: =VLOOKUP(E84,'NO MODIFICAR'!J:K,2,0) -> D861 | E84: MX-CANTERA QUERETARO | F84: =VLOOKUP(D84,'NO MODIFICAR'!F:H,3,0) -> CENTRO | G84: 66936788 | H84: Planta El Castillo (Concretos Mixerplus) | I84: 10000233 | J84: =VLOOKUP(I84,'Materiales,canteras'!C:D,2,0) -> Grava Triturada Basalto 40 mm | K84: =VLOOKUP(I84,'Materiales,canteras'!C:E,3,0) -> 1.456 | L84: 209 | M84: TN | N84: =TODAY() -> 46267 | O84: 31.12.2999 | S84: 282 | T84: =L84-(S84-(S84*R84)) -> -73 | U84: =L84 -> 209 | V84: 0 | X84: =U84+V84 -> 209 | Y84: =IF(+VLOOKUP(I84,P.Referencia!E:S,3,FALSE)<=L84,"Champion","Gerente") -> #N/A | Z84: =VLOOKUP(I84,P.Referencia!E:S,3,0) -> #N/A | AA84: =(Z84-U84)/U84 -> #N/A | AB84: =U84*AA84 -> #N/A | AC84: =U84+AB84 -> #N/A
A85: 84 | B85: Junio | C85: =_xlfn.CONCAT($C$1,D85,G85,I85,W85) -> LlaveD8616693281310000311 | D85: =VLOOKUP(E85,'NO MODIFICAR'!J:K,2,0) -> D861 | E85: MX-CANTERA QUERETARO | F85: =VLOOKUP(D85,'NO MODIFICAR'!F:H,3,0) -> CENTRO | G85: 66932813 | H85: Planta Centro Celaya (Concretos Mixerplus) | I85: 10000311 | J85: =VLOOKUP(I85,'Materiales,canteras'!C:D,2,0) -> Arena Triturada Basalto Malla | K85: =VLOOKUP(I85,'Materiales,canteras'!C:E,3,0) -> 1.651 | L85: 176 | M85: TN | N85: =TODAY() -> 46267 | O85: 31.12.2999 | R85: 0.04 | S85: 260 | T85: =L85-(S85-(S85*R85)) -> -73.6 | U85: =L85 -> 176 | V85: 0 | X85: =U85+V85 -> 176 | Y85: =IF(+VLOOKUP(I85,P.Referencia!E:S,3,FALSE)<=L85,"Champion","Gerente") -> #N/A | Z85: =VLOOKUP(I85,P.Referencia!E:S,3,0) -> #N/A | AA85: =(Z85-U85)/U85 -> #N/A | AB85: =U85*AA85 -> #N/A | AC85: =U85+AB85 -> #N/A
A86: 85 | B86: Junio | C86: =_xlfn.CONCAT($C$1,D86,G86,I86,W86) -> LlaveD8616693281310000229 | D86: =VLOOKUP(E86,'NO MODIFICAR'!J:K,2,0) -> D861 | E86: MX-CANTERA QUERETARO | F86: =VLOOKUP(D86,'NO MODIFICAR'!F:H,3,0) -> CENTRO | G86: 66932813 | H86: Planta Centro Celaya (Concretos Mixerplus) | I86: 10000229 | J86: =VLOOKUP(I86,'Materiales,canteras'!C:D,2,0) -> Grava Triturada Basalto 10 mm | K86: =VLOOKUP(I86,'Materiales,canteras'!C:E,3,0) -> 1.522 | L86: 217.8 | M86: TN | N86: =TODAY() -> 46267 | O86: 31.12.2999 | R86: 0.04 | S86: 320 | T86: =L86-(S86-(S86*R86)) -> -89.4 | U86: =L86 -> 217.8 | V86: 0 | X86: =U86+V86 -> 217.8 | Y86: =IF(+VLOOKUP(I86,P.Referencia!E:S,3,FALSE)<=L86,"Champion","Gerente") -> #N/A | Z86: =VLOOKUP(I86,P.Referencia!E:S,3,0) -> #N/A | AA86: =(Z86-U86)/U86 -> #N/A | AB86: =U86*AA86 -> #N/A | AC86: =U86+AB86 -> #N/A
A87: 86 | B87: Junio | C87: =_xlfn.CONCAT($C$1,D87,G87,I87,W87) -> LlaveD8616693281310000231 | D87: =VLOOKUP(E87,'NO MODIFICAR'!J:K,2,0) -> D861 | E87: MX-CANTERA QUERETARO | F87: =VLOOKUP(D87,'NO MODIFICAR'!F:H,3,0) -> CENTRO | G87: 66932813 | H87: Planta Centro Celaya (Concretos Mixerplus) | I87: 10000231 | J87: =VLOOKUP(I87,'Materiales,canteras'!C:D,2,0) -> Grava Triturada Basalto 20 mm | K87: =VLOOKUP(I87,'Materiales,canteras'!C:E,3,0) -> 1.565 | L87: 209 | M87: TN | N87: =TODAY() -> 46267 | O87: 31.12.2999 | R87: 0.04 | S87: 280 | T87: =L87-(S87-(S87*R87)) -> -59.8 | U87: =L87 -> 209 | V87: 0 | X87: =U87+V87 -> 209 | Y87: =IF(+VLOOKUP(I87,P.Referencia!E:S,3,FALSE)<=L87,"Champion","Gerente") -> #N/A | Z87: =VLOOKUP(I87,P.Referencia!E:S,3,0) -> #N/A | AA87: =(Z87-U87)/U87 -> #N/A | AB87: =U87*AA87 -> #N/A | AC87: =U87+AB87 -> #N/A
A88: 87 | B88: Junio | C88: =_xlfn.CONCAT($C$1,D88,G88,I88,W88) -> LlaveD8616693281310000233 | D88: =VLOOKUP(E88,'NO MODIFICAR'!J:K,2,0) -> D861 | E88: MX-CANTERA QUERETARO | F88: =VLOOKUP(D88,'NO MODIFICAR'!F:H,3,0) -> CENTRO | G88: 66932813 | H88: Planta Centro Celaya (Concretos Mixerplus) | I88: 10000233 | J88: =VLOOKUP(I88,'Materiales,canteras'!C:D,2,0) -> Grava Triturada Basalto 40 mm | K88: =VLOOKUP(I88,'Materiales,canteras'!C:E,3,0) -> 1.456 | L88: 209 | M88: TN | N88: =TODAY() -> 46267 | O88: 31.12.2999 | R88: 0.04 | S88: 282 | T88: =L88-(S88-(S88*R88)) -> -61.72 | U88: =L88 -> 209 | V88: 0 | X88: =U88+V88 -> 209 | Y88: =IF(+VLOOKUP(I88,P.Referencia!E:S,3,FALSE)<=L88,"Champion","Gerente") -> #N/A | Z88: =VLOOKUP(I88,P.Referencia!E:S,3,0) -> #N/A | AA88: =(Z88-U88)/U88 -> #N/A | AB88: =U88*AA88 -> #N/A | AC88: =U88+AB88 -> #N/A
A89: 88 | B89: Junio | C89: =_xlfn.CONCAT($C$1,D89,G89,I89,W89) -> LlaveD8136716639410000253 | D89: =VLOOKUP(E89,'NO MODIFICAR'!J:K,2,0) -> D813 | E89: MX-CANTERA SAN VICENTE | F89: =VLOOKUP(D89,'NO MODIFICAR'!F:H,3,0) -> CENTRO | G89: 67166394 | H89: Atizapan | I89: 10000253 | J89: =VLOOKUP(I89,'Materiales,canteras'!C:D,2,0) -> Grava Triturada Andesita 20 mm | K89: =VLOOKUP(I89,'Materiales,canteras'!C:E,3,0) -> 1.385 | L89: 105 | M89: TN | N89: =TODAY() -> 46267 | O89: 31.12.2999 | R89: 0.015 | S89: 150 | T89: =L89-(S89-(S89*R89)) -> -42.75 | U89: =L89 -> 105 | V89: 0 | X89: =U89+V89 -> 105 | Y89: =IF(+VLOOKUP(I89,P.Referencia!E:S,3,FALSE)<=L89,"Champion","Gerente") -> #N/A | Z89: =VLOOKUP(I89,P.Referencia!E:S,3,0) -> #N/A | AA89: =(Z89-U89)/U89 -> #N/A | AB89: =U89*AA89 -> #N/A | AC89: =U89+AB89 -> #N/A
A90: 89 | B90: Junio | C90: =_xlfn.CONCAT($C$1,D90,G90,I90,W90) -> LlaveD8136716639410000255 | D90: =VLOOKUP(E90,'NO MODIFICAR'!J:K,2,0) -> D813 | E90: MX-CANTERA SAN VICENTE | F90: =VLOOKUP(D90,'NO MODIFICAR'!F:H,3,0) -> CENTRO | G90: 67166394 | H90: Atizapan | I90: 10000255 | J90: =VLOOKUP(I90,'Materiales,canteras'!C:D,2,0) -> Arena Triturada Andesita Malla | K90: =VLOOKUP(I90,'Materiales,canteras'!C:E,3,0) -> 1.535 | L90: 104 | M90: TN | N90: =TODAY() -> 46267 | O90: 31.12.2999 | R90: 0.015 | S90: 150 | T90: =L90-(S90-(S90*R90)) -> -43.75 | U90: =L90 -> 104 | V90: 0 | X90: =U90+V90 -> 104 | Y90: =IF(+VLOOKUP(I90,P.Referencia!E:S,3,FALSE)<=L90,"Champion","Gerente") -> #N/A | Z90: =VLOOKUP(I90,P.Referencia!E:S,3,0) -> #N/A | AA90: =(Z90-U90)/U90 -> #N/A | AB90: =U90*AA90 -> #N/A | AC90: =U90+AB90 -> #N/A
A91: 90 | B91: Junio | C91: =_xlfn.CONCAT($C$1,D91,G91,I91,W91) -> LlaveD86167326330100002311 | D91: =VLOOKUP(E91,'NO MODIFICAR'!J:K,2,0) -> D861 | E91: MX-CANTERA QUERETARO | F91: =VLOOKUP(D91,'NO MODIFICAR'!F:H,3,0) -> CENTRO | G91: 67326330 | H91: Tejocote | I91: 10000231 | J91: =VLOOKUP(I91,'Materiales,canteras'!C:D,2,0) -> Grava Triturada Basalto 20 mm | K91: =VLOOKUP(I91,'Materiales,canteras'!C:E,3,0) -> 1.565 | L91: 207 | M91: TN | N91: =TODAY() -> 46267 | O91: 31.12.2999 | R91: 0.015 | S91: 280 | T91: =L91-(S91-(S91*R91)) -> -68.8 | U91: =L91 -> 207 | V91: 90 | W91: 1 | X91: =U91+V91 -> 297 | Y91: =IF(+VLOOKUP(I91,P.Referencia!E:S,3,FALSE)<=L91,"Champion","Gerente") -> #N/A | Z91: =VLOOKUP(I91,P.Referencia!E:S,3,0) -> #N/A | AA91: =(Z91-U91)/U91 -> #N/A | AB91: =U91*AA91 -> #N/A | AC91: =U91+AB91 -> #N/A
A92: 91 | B92: Junio | C92: =_xlfn.CONCAT($C$1,D92,G92,I92,W92) -> LlaveD86167326330100003111 | D92: =VLOOKUP(E92,'NO MODIFICAR'!J:K,2,0) -> D861 | E92: MX-CANTERA QUERETARO | F92: =VLOOKUP(D92,'NO MODIFICAR'!F:H,3,0) -> CENTRO | G92: 67326330 | H92: Tejocote | I92: 10000311 | J92: =VLOOKUP(I92,'Materiales,canteras'!C:D,2,0) -> Arena Triturada Basalto Malla | K92: =VLOOKUP(I92,'Materiales,canteras'!C:E,3,0) -> 1.651 | L92: 187.9215 | M92: TN | N92: =TODAY() -> 46267 | O92: 31.12.2999 | R92: 0.015 | S92: 260 | T92: =L92-(S92-(S92*R92)) -> -68.1785 | U92: =L92 -> 187.9215 | V92: 90 | W92: 1 | X92: =U92+V92 -> 277.9215 | Y92: =IF(+VLOOKUP(I92,P.Referencia!E:S,3,FALSE)<=L92,"Champion","Gerente") -> #N/A | Z92: =VLOOKUP(I92,P.Referencia!E:S,3,0) -> #N/A | AA92: =(Z92-U92)/U92 -> #N/A | AB92: =U92*AA92 -> #N/A | AC92: =U92+AB92 -> #N/A
A93: 92 | B93: Junio | C93: =_xlfn.CONCAT($C$1,D93,G93,I93,W93) -> LlaveD86167326330100024971 | D93: =VLOOKUP(E93,'NO MODIFICAR'!J:K,2,0) -> D861 | E93: MX-CANTERA QUERETARO | F93: =VLOOKUP(D93,'NO MODIFICAR'!F:H,3,0) -> CENTRO | G93: 67326330 | H93: Tejocote | I93: 10002497 | J93: =VLOOKUP(I93,'Materiales,canteras'!C:D,2,0) -> Grava Triturada Basalto 20 mm - 3/4"-Puq | K93: =VLOOKUP(I93,'Materiales,canteras'!C:E,3,0) -> 1.567 | L93: 215.8435 | M93: TN | N93: =TODAY() -> 46267 | O93: 31.12.2999 | R93: 0.015 | S93: 280 | T93: =L93-(S93-(S93*R93)) -> -59.9565 | U93: =L93 -> 215.8435 | V93: 90 | W93: 1 | X93: =U93+V93 -> 305.8435 | Y93: =IF(+VLOOKUP(I93,P.Referencia!E:S,3,FALSE)<=L93,"Champion","Gerente") -> #N/A | Z93: =VLOOKUP(I93,P.Referencia!E:S,3,0) -> #N/A | AA93: =(Z93-U93)/U93 -> #N/A | AB93: =U93*AA93 -> #N/A | AC93: =U93+AB93 -> #N/A
A94: 93 | B94: Junio | C94: =_xlfn.CONCAT($C$1,D94,G94,I94,W94) -> LlaveD86167318801100014502 | D94: =VLOOKUP(E94,'NO MODIFICAR'!J:K,2,0) -> D861 | E94: MX-CANTERA QUERETARO | F94: =VLOOKUP(D94,'NO MODIFICAR'!F:H,3,0) -> CENTRO | G94: 67318801 | H94: CAMOMO | I94: 10001450 | J94: =VLOOKUP(I94,'Materiales,canteras'!C:D,2,0) -> Base Hidraúlica Basalto de 1 /1/2 | K94: =VLOOKUP(I94,'Materiales,canteras'!C:E,3,0) -> 1.749 | L94: 210 | M94: TN | N94: =TODAY() -> 46267 | O94: 31.12.2999 | R94: 0.05 | S94: 260 | T94: =L94-(S94-(S94*R94)) -> -37 | U94: =L94 -> 210 | V94: 0 | W94: 2 | X94: =U94+V94 -> 210 | Y94: =IF(+VLOOKUP(I94,P.Referencia!E:S,3,FALSE)<=L94,"Champion","Gerente") -> #N/A | Z94: =VLOOKUP(I94,P.Referencia!E:S,3,0) -> #N/A | AA94: =(Z94-U94)/U94 -> #N/A | AB94: =U94*AA94 -> #N/A | AC94: =U94+AB94 -> #N/A
A95: 94 | B95: Junio | C95: =_xlfn.CONCAT($C$1,D95,G95,I95,W95) -> LlaveD81367321364100002552 | D95: =VLOOKUP(E95,'NO MODIFICAR'!J:K,2,0) -> D813 | E95: MX-CANTERA SAN VICENTE | F95: =VLOOKUP(D95,'NO MODIFICAR'!F:H,3,0) -> CENTRO | G95: 67321364 | H95: CATSA IXTAPALUCA | I95: 10000255 | J95: =VLOOKUP(I95,'Materiales,canteras'!C:D,2,0) -> Arena Triturada Andesita Malla | K95: =VLOOKUP(I95,'Materiales,canteras'!C:E,3,0) -> 1.535 | L95: 104.1 | M95: TN | N95: =TODAY() -> 46267 | O95: 31.12.2999 | R95: 0.015 | S95: 150 | T95: =L95-(S95-(S95*R95)) -> -43.65 | U95: =L95 -> 104.1 | V95: 0 | W95: 2 | X95: =U95+V95 -> 104.1 | Y95: =IF(+VLOOKUP(I95,P.Referencia!E:S,3,FALSE)<=L95,"Champion","Gerente") -> #N/A | Z95: =VLOOKUP(I95,P.Referencia!E:S,3,0) -> #N/A | AA95: =(Z95-U95)/U95 -> #N/A | AB95: =U95*AA95 -> #N/A | AC95: =U95+AB95 -> #N/A
A96: 95 | B96: Junio | C96: =_xlfn.CONCAT($C$1,D96,G96,I96,W96) -> LlaveD81367321364100002532 | D96: =VLOOKUP(E96,'NO MODIFICAR'!J:K,2,0) -> D813 | E96: MX-CANTERA SAN VICENTE | F96: =VLOOKUP(D96,'NO MODIFICAR'!F:H,3,0) -> CENTRO | G96: 67321364 | H96: CATSA IXTAPALUCA | I96: 10000253 | J96: =VLOOKUP(I96,'Materiales,canteras'!C:D,2,0) -> Grava Triturada Andesita 20 mm | K96: =VLOOKUP(I96,'Materiales,canteras'!C:E,3,0) -> 1.385 | L96: 104.1 | M96: TN | N96: =TODAY() -> 46267 | O96: 31.12.2999 | R96: 0.015 | S96: 150 | T96: =L96-(S96-(S96*R96)) -> -43.65 | U96: =L96 -> 104.1 | V96: 0 | W96: 2 | X96: =U96+V96 -> 104.1 | Y96: =IF(+VLOOKUP(I96,P.Referencia!E:S,3,FALSE)<=L96,"Champion","Gerente") -> #N/A | Z96: =VLOOKUP(I96,P.Referencia!E:S,3,0) -> #N/A | AA96: =(Z96-U96)/U96 -> #N/A | AB96: =U96*AA96 -> #N/A | AC96: =U96+AB96 -> #N/A
A97: 96 | B97: Junio | C97: =_xlfn.CONCAT($C$1,D97,G97,I97,W97) -> LlaveDU076731442310000110 | D97: =VLOOKUP(E97,'NO MODIFICAR'!J:K,2,0) -> DU07 | E97: MX-CANCÚN III | F97: =VLOOKUP(D97,'NO MODIFICAR'!F:H,3,0) -> SURESTE | G97: 67314423 | H97: C2602 PLANTA ARA CANCUN | I97: 10000110 | J97: =VLOOKUP(I97,'Materiales,canteras'!C:D,2,0) -> GRAVA TRITURADA CALIZA 20 MM “3/4"–INTEG | K97: =VLOOKUP(I97,'Materiales,canteras'!C:E,3,0) -> 1.201 | L97: 316.403 | M97: TN | N97: =TODAY() -> 46267 | O97: 31.12.2999 | S97: 390 | T97: =L97-(S97-(S97*R97)) -> -73.597002 | U97: =L97 -> 316.403 | X97: =U97+V97 -> 316.403 | Y97: =IF(+VLOOKUP(I97,P.Referencia!E:S,3,FALSE)<=L97,"Champion","Gerente") -> #N/A | Z97: =VLOOKUP(I97,P.Referencia!E:S,3,0) -> #N/A | AA97: =(Z97-U97)/U97 -> #N/A | AB97: =U97*AA97 -> #N/A | AC97: =U97+AB97 -> #N/A
A98: 97 | B98: Junio | C98: =_xlfn.CONCAT($C$1,D98,G98,I98,W98) -> LlaveDU076731442310000112 | D98: =VLOOKUP(E98,'NO MODIFICAR'!J:K,2,0) -> DU07 | E98: MX-CANCÚN III | F98: =VLOOKUP(D98,'NO MODIFICAR'!F:H,3,0) -> SURESTE | G98: 67314423 | H98: C2602 PLANTA ARA CANCUN | I98: 10000112 | J98: Grava Triturada Caliza 13 mm - 1/2" | K98: =VLOOKUP(I98,'Materiales,canteras'!C:E,3,0) -> 1.194 | L98: 326.63317 | M98: TN | N98: =TODAY() -> 46267 | O98: 31.12.2999 | S98: 320 | T98: =L98-(S98-(S98*R98)) -> 6.6331658 | U98: =L98 -> 326.63317 | X98: =U98+V98 -> 326.63317 | Y98: =IF(+VLOOKUP(I98,P.Referencia!E:S,3,FALSE)<=L98,"Champion","Gerente") -> #N/A | Z98: =VLOOKUP(I98,P.Referencia!E:S,3,0) -> #N/A | AA98: =(Z98-U98)/U98 -> #N/A | AB98: =U98*AA98 -> #N/A | AC98: =U98+AB98 -> #N/A
A99: 98 | B99: Junio | C99: =_xlfn.CONCAT($C$1,D99,G99,I99,W99) -> LlaveDU076731442310000101 | D99: =VLOOKUP(E99,'NO MODIFICAR'!J:K,2,0) -> DU07 | E99: MX-CANCÚN III | F99: =VLOOKUP(D99,'NO MODIFICAR'!F:H,3,0) -> SURESTE | G99: 67314423 | H99: C2602 PLANTA ARA CANCUN | I99: 10000101 | J99: =VLOOKUP(I99,'Materiales,canteras'!C:D,2,0) -> Arena Triturada Caliza Malla 4 | K99: =VLOOKUP(I99,'Materiales,canteras'!C:E,3,0) -> 1.417 | L99: 338.74382 | M99: TN | N99: =TODAY() -> 46267 | O99: 31.12.2999 | S99: 400 | T99: =L99-(S99-(S99*R99)) -> -61.256175 | U99: =L99 -> 338.74382 | X99: =U99+V99 -> 338.74382 | Y99: =IF(+VLOOKUP(I99,P.Referencia!E:S,3,FALSE)<=L99,"Champion","Gerente") -> #N/A | Z99: =VLOOKUP(I99,P.Referencia!E:S,3,0) -> #N/A | AA99: =(Z99-U99)/U99 -> #N/A | AB99: =U99*AA99 -> #N/A | AC99: =U99+AB99 -> #N/A
A100: 99 | B100: Junio | C100: =_xlfn.CONCAT($C$1,D100,G100,I100,W100) -> LlaveDU076731442310000103 | D100: =VLOOKUP(E100,'NO MODIFICAR'!J:K,2,0) -> DU07 | E100: MX-CANCÚN III | F100: =VLOOKUP(D100,'NO MODIFICAR'!F:H,3,0) -> SURESTE | G100: 67314423 | H100: C2602 PLANTA ARA CANCUN | I100: 10000103 | J100: =VLOOKUP(I100,'Materiales,canteras'!C:D,2,0) -> Base H Triturada Caliza 1 1/2" a Finos | K100: =VLOOKUP(I100,'Materiales,canteras'!C:E,3,0) -> 1.462 | L100: 119.69904 | M100: TN | N100: =TODAY() -> 46267 | O100: 31.12.2999 | S100: 150 | T100: =L100-(S100-(S100*R100)) -> -30.300958 | U100: =L100 -> 119.69904 | X100: =U100+V100 -> 119.69904 | Y100: =IF(+VLOOKUP(I100,P.Referencia!E:S,3,FALSE)<=L100,"Champion","Gerente") -> #N/A | Z100: =VLOOKUP(I100,P.Referencia!E:S,3,0) -> #N/A | AA100: =(Z100-U100)/U100 -> #N/A | AB100: =U100*AA100 -> #N/A | AC100: =U100+AB100 -> #N/A
...

Sheet Formato cambio
D2: PRECIOS DE VENTA
C7: Cambio en obra específica
C8: Org Vtas | D8: Sucursal obra | E8: Centro | F8: Material | G8: GAP Importe | H8: Clase condición | I8: flete | J8: Condición | K8: Modalidad
C9: 7180 | D9: 66823169 | E9: D816 | F9: 10001170 | G9: -45.22 | H9: =IF(G9<0,"YMC8","YMC9") -> YMC8 | I9: 0 | J9: =IF(I9>0,"ZMP1","0") -> 0 | K9: =IF(I9>0,"01","02") -> 02
C10: 7180 | D10: 66862802 | E10: D816 | F10: 10001170 | G10: -45.22 | H10: =IF(G10<0,"YMC8","YMC9") -> YMC8 | I10: 0 | J10: =IF(I10>0,"ZMP1","0") -> 0 | K10: =IF(I10>0,"01","02") -> 02

Sheet P.Referencia
J1: 0.04 | T1: RICARDO | U1: EDUARDO | V1: MARZO | W1: ABRIL | Y1: MAYO
A2: Región | B2: llave | C2: UO | D2: Cantera | E2: Material | F2: Material | H2: 46235 | I2: 46113 | J2: $precio26 | K2: $Enero26 | L2: $ Dic '25 | M2: $ Nov '25 | N2: $ Oct '25 | O2: $ Sep '25 | P2: $ Agosto '25 | Q2: $ Julio '25 | R2: $ Ref Junio '25 | S2: $ Ref May'25 | T2: 0.05 | U2: 0.1 | V2: Filial | W2: Filial | X2: Var | Y2: Filial | Z2: Var
A3: CENTRO | B3: =+C3&E3 -> D86410001073 | C3: D864 | D3: MX-CANTERA CERRO JARDIN | E3: 10001073 | F3: Arena Triturada Caliza Malla 4 | G3: =H3-I3 -> #N/A | H3: =VLOOKUP(E3,[2]Conciliacion!$H:$AC,22,0) -> #N/A | I3: =VLOOKUP(B3,'[3]Hoja2 (2)'!$A:$E,5,0) -> 91 | J3: =(L3*4%)+L3 -> 91 | K3: 91 | L3: =VLOOKUP(E3,[4]TRABAJO!$H:$S,9,0) -> 87.5 | M3: =VLOOKUP(E3,[5]TRABAJO!$F:$S,11,0) -> 87.5 | N3: =VLOOKUP(E3,[6]TRABAJO!$H:$S,9,0) -> 87.5 | O3: =VLOOKUP(B3,[7]TRABAJO!$C:$S,14,0) -> 87.5 | P3: =VLOOKUP(B3,[8]TRABAJO!$C:$S,14,0) -> 87.5 | Q3: =VLOOKUP(B3,[9]TRABAJO!$C:$S,14,0) -> 87.5 | R3: =VLOOKUP(B3,[10]TRABAJO!$C:$Q,15,0) -> 87.5 | S3: 87.48 | T3: =S3-(S3*5%) -> 83.106 | U3: =S3-(S3*10%) -> 78.732 | V3: =VLOOKUP(B3,'[11]ZICP-MARZO'!$B:$P,15,0) -> 91.48 | W3: =VLOOKUP(B3,[11]CONSOLIDADO_ABRIL!$B:$J,9,0) -> 91.48 | X3: =V3-W3 -> 0 | Y3: =VLOOKUP(B3,[11]CONSOLIDADO_MAYO!$B:$J,9,0) -> 87.48 | Z3: =S3-Y3 -> 0
A4: CENTRO | B4: =+C4&E4 -> D86410000236 | C4: D864 | D4: MX-CANTERA CERRO JARDIN | E4: 10000236 | F4: Grava Triturada Caliza 10 mm - 3/8" | G4: =H4-I4 -> #N/A | H4: =VLOOKUP(E4,[2]Conciliacion!$H:$AC,22,0) -> #N/A | I4: =VLOOKUP(B4,'[3]Hoja2 (2)'!$A:$E,5,0) -> 124.8 | J4: =(L4*4%)+L4 -> 124.8 | K4: 124.8 | L4: =VLOOKUP(E4,[4]TRABAJO!$H:$S,9,0) -> 120 | M4: =VLOOKUP(E4,[5]TRABAJO!$F:$S,11,0) -> 120 | N4: =VLOOKUP(E4,[6]TRABAJO!$H:$S,9,0) -> 120 | O4: =VLOOKUP(B4,[7]TRABAJO!$C:$S,14,0) -> 120 | P4: =VLOOKUP(B4,[8]TRABAJO!$C:$S,14,0) -> 120 | Q4: =VLOOKUP(B4,[9]TRABAJO!$C:$S,14,0) -> 120 | R4: =VLOOKUP(B4,[10]TRABAJO!$C:$Q,15,0) -> 120 | S4: 120.44 | T4: =S4-(S4*5%) -> 114.418 | U4: =S4-(S4*10%) -> 108.396 | V4: =VLOOKUP(B4,'[11]ZICP-MARZO'!$B:$P,15,0) -> 143.96 | W4: =VLOOKUP(B4,[11]CONSOLIDADO_ABRIL!$B:$J,9,0) -> 150.44 | X4: =V4-W4 -> -6.48 | Y4: =VLOOKUP(B4,[11]CONSOLIDADO_MAYO!$B:$J,9,0) -> 120.44 | Z4: =S4-Y4 -> 0
A5: CENTRO | B5: =+C5&E5 -> D86410000269 | C5: D864 | D5: MX-CANTERA CERRO JARDIN | E5: 10000269 | F5: Grava Triturada Caliza 13 mm - 1/2" | G5: =H5-I5 -> #N/A | H5: =VLOOKUP(E5,[2]Conciliacion!$H:$AC,22,0) -> #N/A | I5: =VLOOKUP(B5,'[3]Hoja2 (2)'!$A:$E,5,0) -> 142.48 | J5: =(L5*4%)+L5 -> 142.48 | K5: 142.48 | L5: =VLOOKUP(E5,[4]TRABAJO!$H:$S,9,0) -> 137 | M5: =VLOOKUP(E5,[5]TRABAJO!$F:$S,11,0) -> 137 | N5: =VLOOKUP(E5,[6]TRABAJO!$H:$S,9,0) -> 137 | O5: 137 | P5: 137 | Q5: =VLOOKUP(B5,[9]TRABAJO!$C:$S,14,0) -> 137 | R5: =VLOOKUP(B5,[10]TRABAJO!$C:$Q,15,0) -> 137 | S5: 131.2 | T5: =S5-(S5*5%) -> 124.64 | U5: =S5-(S5*10%) -> 118.08 | V5: =VLOOKUP(B5,'[11]ZICP-MARZO'!$B:$P,15,0) -> 151.8 | W5: =VLOOKUP(B5,[11]CONSOLIDADO_ABRIL!$B:$J,9,0) -> 167.34 | X5: =V5-W5 -> -15.54 | Y5: =VLOOKUP(B5,[11]CONSOLIDADO_MAYO!$B:$J,9,0) -> 131.2 | Z5: =S5-Y5 -> 0
A6: CENTRO | B6: =+C6&E6 -> D86410000240 | C6: D864 | D6: MX-CANTERA CERRO JARDIN | E6: 10000240 | F6: Grava Triturada Caliza 20 mm - 3/4" | G6: =H6-I6 -> #N/A | H6: =VLOOKUP(E6,[2]Conciliacion!$H:$AC,22,0) -> #N/A | I6: =VLOOKUP(B6,'[3]Hoja2 (2)'!$A:$E,5,0) -> 132.08 | J6: =(L6*4%)+L6 -> 132.08 | K6: 132.08 | L6: =VLOOKUP(E6,[4]TRABAJO!$H:$S,9,0) -> 127 | M6: =VLOOKUP(E6,[5]TRABAJO!$F:$S,11,0) -> 127 | N6: =VLOOKUP(E6,[6]TRABAJO!$H:$S,9,0) -> 127 | O6: =VLOOKUP(B6,[7]TRABAJO!$C:$S,14,0) -> 127 | P6: =VLOOKUP(B6,[8]TRABAJO!$C:$S,14,0) -> 127 | Q6: =VLOOKUP(B6,[9]TRABAJO!$C:$S,14,0) -> 127 | R6: =VLOOKUP(B6,[10]TRABAJO!$C:$Q,15,0) -> 127 | S6: 127.17 | T6: =S6-(S6*5%) -> 120.8115 | U6: =S6-(S6*10%) -> 114.453 | V6: =VLOOKUP(B6,'[11]ZICP-MARZO'!$B:$P,15,0) -> 150.4 | W6: =VLOOKUP(B6,[11]CONSOLIDADO_ABRIL!$B:$J,9,0) -> 157.17 | X6: =V6-W6 -> -6.77 | Y6: =VLOOKUP(B6,[11]CONSOLIDADO_MAYO!$B:$J,9,0) -> 127.17 | Z6: =S6-Y6 -> 0
A7: CENTRO | B7: =+C7&E7 -> D86410001074 | C7: D864 | D7: MX-CANTERA CERRO JARDIN | E7: 10001074 | F7: Grava Triturada Caliza 40 mm - 1 1/2" | G7: =H7-I7 -> #N/A | H7: =VLOOKUP(E7,[2]Conciliacion!$H:$AC,22,0) -> #N/A | I7: =VLOOKUP(B7,'[3]Hoja2 (2)'!$A:$E,5,0) -> 142.48 | J7: =(L7*4%)+L7 -> 142.48 | K7: 142.48 | L7: =VLOOKUP(E7,[4]TRABAJO!$H:$S,9,0) -> 137 | M7: =VLOOKUP(E7,[5]TRABAJO!$F:$S,11,0) -> 137 | N7: =VLOOKUP(E7,[6]TRABAJO!$H:$S,9,0) -> 137 | O7: =VLOOKUP(B7,[7]TRABAJO!$C:$S,14,0) -> 137 | P7: =VLOOKUP(B7,[8]TRABAJO!$C:$S,14,0) -> 137 | Q7: =VLOOKUP(B7,[9]TRABAJO!$C:$S,14,0) -> 137 | R7: =VLOOKUP(B7,[10]TRABAJO!$C:$Q,15,0) -> 137 | S7: 136.64 | T7: =S7-(S7*5%) -> 129.808 | U7: =S7-(S7*10%) -> 122.976 | V7: =VLOOKUP(B7,'[11]ZICP-MARZO'!$B:$P,15,0) -> 177.75 | W7: =VLOOKUP(B7,[11]CONSOLIDADO_ABRIL!$B:$J,9,0) -> 186.64 | X7: =V7-W7 -> -8.89 | Y7: =VLOOKUP(B7,[11]CONSOLIDADO_MAYO!$B:$J,9,0) -> 136.64 | Z7: =S7-Y7 -> 0
A8: CENTRO | B8: =+C8&E8 -> D86110000311 | C8: D861 | D8: MX-CANTERA QUERETARO | E8: 10000311 | F8: Arena Triturada Basalto Malla 4 | G8: =H8-I8 -> #N/A | H8: =VLOOKUP(E8,[2]Conciliacion!$H:$AC,22,0) -> #N/A | I8: =VLOOKUP(B8,'[3]Hoja2 (2)'!$A:$E,5,0) -> 191.26 | J8: 191.26 | K8: 191.26 | L8: =VLOOKUP(E8,[4]TRABAJO!$H:$S,9,0) -> #N/A | M8: =VLOOKUP(E8,[5]TRABAJO!$F:$S,11,0) -> 183.90002 | N8: =VLOOKUP(E8,[6]TRABAJO!$H:$S,9,0) -> 180 | O8: 180.59044 | P8: 180.59044 | Q8: =VLOOKUP(B8,[9]TRABAJO!$C:$S,14,0) -> 180.59044 | R8: =VLOOKUP(B8,[10]TRABAJO!$C:$Q,15,0) -> 184 | S8: 188 | T8: =S8-(S8*5%) -> 178.6 | U8: =S8-(S8*10%) -> 169.2 | V8: =VLOOKUP(B8,'[11]ZICP-MARZO'!$B:$P,15,0) -> 171.19 | W8: =VLOOKUP(B8,[11]CONSOLIDADO_ABRIL!$B:$J,9,0) -> 203.78 | X8: =V8-W8 -> -32.59 | Y8: =VLOOKUP(B8,[11]CONSOLIDADO_MAYO!$B:$J,9,0) -> 188 | Z8: =S8-Y8 -> 0
A9: CENTRO | B9: =+C9&E9 -> D86110000229 | C9: D861 | D9: MX-CANTERA QUERETARO | E9: 10000229 | F9: Grava Triturada Basalto 10 mm - 3/8" | G9: =H9-I9 -> #N/A | H9: =VLOOKUP(E9,[2]Conciliacion!$H:$AC,22,0) -> #N/A | I9: =VLOOKUP(B9,'[3]Hoja2 (2)'!$A:$E,5,0) -> 249.36 | J9: =(L9*4%)+L9 -> 249.3608 | K9: 249.39 | L9: =VLOOKUP(E9,[4]TRABAJO!$H:$S,9,0) -> 239.77 | M9: =VLOOKUP(E9,[5]TRABAJO!$F:$S,11,0) -> 239.77004 | N9: =VLOOKUP(E9,[6]TRABAJO!$H:$S,9,0) -> 239.76995 | O9: =VLOOKUP(B9,[7]TRABAJO!$C:$S,14,0) -> 239.77 | P9: =VLOOKUP(B9,[8]TRABAJO!$C:$S,14,0) -> 216 | Q9: =VLOOKUP(B9,[9]TRABAJO!$C:$S,14,0) -> 239.76995 | R9: =VLOOKUP(B9,[10]TRABAJO!$C:$Q,15,0) -> 239.77002 | S9: 216 | T9: =S9-(S9*5%) -> 205.2 | U9: =S9-(S9*10%) -> 194.4 | V9: =VLOOKUP(B9,'[11]ZICP-MARZO'!$B:$P,15,0) -> 225.14 | W9: =VLOOKUP(B9,[11]CONSOLIDADO_ABRIL!$B:$J,9,0) -> 239.77 | X9: =V9-W9 -> -14.63 | Y9: =VLOOKUP(B9,[11]CONSOLIDADO_MAYO!$B:$J,9,0) -> 216 | Z9: =S9-Y9 -> 0
A10: CENTRO | B10: =+C10&E10 -> D86110000231 | C10: D861 | D10: MX-CANTERA QUERETARO | E10: 10000231 | F10: Grava Triturada Basalto 20 mm - 3/4" | G10: =H10-I10 -> #N/A | H10: =VLOOKUP(E10,[2]Conciliacion!$H:$AC,22,0) -> #N/A | I10: =VLOOKUP(B10,'[3]Hoja2 (2)'!$A:$E,5,0) -> 224.62 | J10: =(L10*4%)+L10 -> 224.6192 | K10: 224.64 | L10: =VLOOKUP(E10,[4]TRABAJO!$H:$S,9,0) -> 215.98 | M10: =VLOOKUP(E10,[5]TRABAJO!$F:$S,11,0) -> 215.98 | N10: =VLOOKUP(E10,[6]TRABAJO!$H:$S,9,0) -> 215.98 | O10: =VLOOKUP(B10,[7]TRABAJO!$C:$S,14,0) -> 215.98 | P10: =VLOOKUP(B10,[8]TRABAJO!$C:$S,14,0) -> 215.98 | Q10: =VLOOKUP(B10,[9]TRABAJO!$C:$S,14,0) -> 215.98001 | R10: =VLOOKUP(B10,[10]TRABAJO!$C:$Q,15,0) -> 215.97999 | S10: 215.98 | T10: =S10-(S10*5%) -> 205.181 | U10: =S10-(S10*10%) -> 194.382 | V10: =VLOOKUP(B10,'[11]ZICP-MARZO'!$B:$P,15,0) -> 205.71 | W10: =VLOOKUP(B10,[11]CONSOLIDADO_ABRIL!$B:$J,9,0) -> 215.98 | X10: =V10-W10 -> -10.27 | Y10: =VLOOKUP(B10,[11]CONSOLIDADO_MAYO!$B:$J,9,0) -> 215.98 | Z10: =S10-Y10 -> -4.0712468e-06
A11: CENTRO | B11: =+C11&E11 -> D86110000233 | C11: D861 | D11: MX-CANTERA QUERETARO | E11: 10000233 | F11: Grava Triturada Basalto 40 mm - 1 1/2" | G11: =H11-I11 -> #N/A | H11: =VLOOKUP(E11,[2]Conciliacion!$H:$AC,22,0) -> #N/A | I11: =VLOOKUP(B11,'[3]Hoja2 (2)'!$A:$E,5,0) -> 224.62 | J11: =(L11*4%)+L11 -> 224.61919 | K11: 224.64 | L11: =VLOOKUP(E11,[4]TRABAJO!$H:$S,9,0) -> 215.97999 | M11: =VLOOKUP(E11,[5]TRABAJO!$F:$S,11,0) -> 215.97998 | N11: =VLOOKUP(E11,[6]TRABAJO!$H:$S,9,0) -> 178 | O11: =VLOOKUP(B11,[7]TRABAJO!$C:$S,14,0) -> 178 | P11: =VLOOKUP(B11,[8]TRABAJO!$C:$S,14,0) -> 178 | Q11: =VLOOKUP(B11,[9]TRABAJO!$C:$S,14,0) -> 215.98001 | R11: =VLOOKUP(B11,[10]TRABAJO!$C:$Q,15,0) -> 215.97998 | S11: 215.98 | T11: =S11-(S11*5%) -> 205.181 | U11: =S11-(S11*10%) -> 194.382 | V11: =VLOOKUP(B11,'[11]ZICP-MARZO'!$B:$P,15,0) -> 208.25 | W11: =VLOOKUP(B11,[11]CONSOLIDADO_ABRIL!$B:$J,9,0) -> 178 | X11: =V11-W11 -> 30.25 | Y11: =VLOOKUP(B11,[11]CONSOLIDADO_MAYO!$B:$J,9,0) -> 215.98 | Z11: =S11-Y11 -> -8.901153e-07
A12: CENTRO | B12: =+C12&E12 -> D81310000255 | C12: D813 | D12: MX-CANTERA SAN VICENTE | E12: 10000255 | F12: Arena Triturada Andesita Malla 4 | G12: =H12-I12 -> #N/A | H12: =VLOOKUP(E12,[2]Conciliacion!$H:$AC,22,0) -> #N/A | I12: =VLOOKUP(B12,'[3]Hoja2 (2)'!$A:$E,5,0) -> 108.31 | J12: =(L12*4%)+L12 -> 108.3056 | K12: 108.26 | L12: =VLOOKUP(E12,[4]TRABAJO!$H:$S,9,0) -> 104.14 | M12: =VLOOKUP(E12,[5]TRABAJO!$F:$S,11,0) -> 104.14001 | N12: =VLOOKUP(E12,[6]TRABAJO!$H:$S,9,0) -> 104.14 | O12: =VLOOKUP(B12,[7]TRABAJO!$C:$S,14,0) -> 104.1 | P12: =VLOOKUP(B12,[8]TRABAJO!$C:$S,14,0) -> 104.14001 | Q12: =VLOOKUP(B12,[9]TRABAJO!$C:$S,14,0) -> 104.14 | R12: =VLOOKUP(B12,[10]TRABAJO!$C:$Q,15,0) -> 104.14 | S12: 104.14 | T12: =S12-(S12*5%) -> 98.933 | U12: =S12-(S12*10%) -> 93.726 | V12: =VLOOKUP(B12,'[11]ZICP-MARZO'!$B:$P,15,0) -> 104.07 | W12: =VLOOKUP(B12,[11]CONSOLIDADO_ABRIL!$B:$J,9,0) -> 104.14 | X12: =V12-W12 -> -0.07 | Y12: =VLOOKUP(B12,[11]CONSOLIDADO_MAYO!$B:$J,9,0) -> 104.14 | Z12: =S12-Y12 -> 0
A13: CENTRO | B13: =+C13&E13 -> D81310002350 | C13: D813 | D13: MX-CANTERA SAN VICENTE | E13: 10002350 | F13: Grava Triturada Andesita 10mm-3/8" | G13: =H13-I13 -> #N/A | H13: =VLOOKUP(E13,[2]Conciliacion!$H:$AC,22,0) -> #N/A | I13: =VLOOKUP(B13,'[3]Hoja2 (2)'!$A:$E,5,0) -> 125.31 | J13: =(L13*4%)+L13 -> 125.30949 | K13: 125.32 | L13: =VLOOKUP(E13,[4]TRABAJO!$H:$S,9,0) -> 120.4899 | M13: =VLOOKUP(E13,[5]TRABAJO!$F:$S,11,0) -> 120.49001 | N13: =VLOOKUP(E13,[6]TRABAJO!$H:$S,9,0) -> 134.60003 | O13: =VLOOKUP(B13,[7]TRABAJO!$C:$S,14,0) -> 134.59999 | P13: =VLOOKUP(B13,[8]TRABAJO!$C:$S,14,0) -> 120.49003 | Q13: =VLOOKUP(B13,[9]TRABAJO!$C:$S,14,0) -> 120.48999 | R13: =VLOOKUP(B13,[10]TRABAJO!$C:$Q,15,0) -> 120.48998 | S13: 134.6 | T13: =S13-(S13*5%) -> 127.87 | U13: =S13-(S13*10%) -> 121.14 | V13: =VLOOKUP(B13,'[11]ZICP-MARZO'!$B:$P,15,0) -> 120.49 | W13: =VLOOKUP(B13,[11]CONSOLIDADO_ABRIL!$B:$J,9,0) -> 120.49 | X13: =V13-W13 -> 0 | Y13: =VLOOKUP(B13,[11]CONSOLIDADO_MAYO!$B:$J,9,0) -> 134.6 | Z13: =S13-Y13 -> 0
A14: CENTRO | B14: =+C14&E14 -> D81310000253 | C14: D813 | D14: MX-CANTERA SAN VICENTE | E14: 10000253 | F14: Grava Triturada Andesita 20 mm - 3/4" | G14: =H14-I14 -> #N/A | H14: =VLOOKUP(E14,[2]Conciliacion!$H:$AC,22,0) -> #N/A | I14: =VLOOKUP(B14,'[3]Hoja2 (2)'!$A:$E,5,0) -> 108.16 | J14: =(L14*4%)+L14 -> 108.16 | K14: 108.16 | L14: =VLOOKUP(E14,[4]TRABAJO!$H:$S,9,0) -> 104 | M14: =VLOOKUP(E14,[5]TRABAJO!$F:$S,11,0) -> 104 | N14: =VLOOKUP(E14,[6]TRABAJO!$H:$S,9,0) -> 104 | O14: =VLOOKUP(B14,[7]TRABAJO!$C:$S,14,0) -> 103.90003 | P14: =VLOOKUP(B14,[8]TRABAJO!$C:$S,14,0) -> 103.90001 | Q14: =VLOOKUP(B14,[9]TRABAJO!$C:$S,14,0) -> 103.90002 | R14: =VLOOKUP(B14,[10]TRABAJO!$C:$Q,15,0) -> 103.9 | S14: 103.90001 | T14: =S14-(S14*5%) -> 98.705014 | U14: =S14-(S14*10%) -> 93.510013 | V14: =VLOOKUP(B14,'[11]ZICP-MARZO'!$B:$P,15,0) -> 103.52 | W14: =VLOOKUP(B14,[11]CONSOLIDADO_ABRIL!$B:$J,9,0) -> 104 | X14: =V14-W14 -> -0.48 | Y14: =VLOOKUP(B14,[11]CONSOLIDADO_MAYO!$B:$J,9,0) -> 103.9 | Z14: =S14-Y14 -> 1.470278e-05
A15: CENTRO | B15: =+C15&E15 -> D87310001073 | C15: D873 | D15: MX-VIRTUAL VALLEJO | E15: 10001073 | F15: Arena Triturada Caliza Malla 4 | G15: =H15-I15 -> #N/A | H15: =VLOOKUP(E15,[2]Conciliacion!$H:$AC,22,0) -> #N/A | I15: =VLOOKUP(B15,'[3]Hoja2 (2)'!$A:$E,5,0) -> 208.28 | J15: 208.28 | L15: =VLOOKUP(E15,[4]TRABAJO!$H:$S,9,0) -> 87.5 | M15: =VLOOKUP(E15,[5]TRABAJO!$F:$S,11,0) -> 87.5 | N15: =VLOOKUP(E15,[6]TRABAJO!$H:$S,9,0) -> 87.5 | O15: =VLOOKUP(B15,[7]TRABAJO!$C:$S,14,0) -> 197.8 | P15: =VLOOKUP(B15,[8]TRABAJO!$C:$S,14,0) -> 197.8 | Q15: =VLOOKUP(B15,[9]TRABAJO!$C:$S,14,0) -> 197.8 | R15: =VLOOKUP(B15,[10]TRABAJO!$C:$Q,15,0) -> 197.8 | S15: 196.88 | T15: =S15-(S15*5%) -> 187.036 | U15: =S15-(S15*10%) -> 177.192 | V15: =VLOOKUP(B15,'[11]ZICP-MARZO'!$B:$P,15,0) -> 200.94 | W15: =VLOOKUP(B15,[11]CONSOLIDADO_ABRIL!$B:$J,9,0) -> 200.88 | X15: =V15-W15 -> 0.06 | Y15: =VLOOKUP(B15,[11]CONSOLIDADO_MAYO!$B:$J,9,0) -> 196.88 | Z15: =S15-Y15 -> 0
A16: CENTRO | B16: =+C16&E16 -> D87310000240 | C16: D873 | D16: MX-VIRTUAL VALLEJO | E16: 10000240 | F16: Grava Triturada Caliza 20 mm - 3/4" | G16: =H16-I16 -> #N/A | H16: =VLOOKUP(E16,[2]Conciliacion!$H:$AC,22,0) -> #N/A | I16: =VLOOKUP(B16,'[3]Hoja2 (2)'!$A:$E,5,0) -> 271.69 | J16: 271.69 | L16: =VLOOKUP(E16,[4]TRABAJO!$H:$S,9,0) -> 127 | M16: =VLOOKUP(E16,[5]TRABAJO!$F:$S,11,0) -> 127 | N16: =VLOOKUP(E16,[6]TRABAJO!$H:$S,9,0) -> 127 | O16: =VLOOKUP(B16,[7]TRABAJO!$C:$S,14,0) -> 258.77 | P16: =VLOOKUP(B16,[8]TRABAJO!$C:$S,14,0) -> 258.77 | Q16: =VLOOKUP(B16,[9]TRABAJO!$C:$S,14,0) -> 258.77 | R16: =VLOOKUP(B16,[10]TRABAJO!$C:$Q,15,0) -> 258.77 | S16: 259.67 | T16: =S16-(S16*5%) -> 246.6865 | U16: =S16-(S16*10%) -> 233.703 | V16: =VLOOKUP(B16,'[11]ZICP-MARZO'!$B:$P,15,0) -> 289.68 | W16: =VLOOKUP(B16,[11]CONSOLIDADO_ABRIL!$B:$J,9,0) -> 289.67 | X16: =V16-W16 -> 0.01 | Y16: =VLOOKUP(B16,[11]CONSOLIDADO_MAYO!$B:$J,9,0) -> 259.67 | Z16: =S16-Y16 -> 0
A17: NORESTE | B17: =+C17&E17 -> D82410000234 | C17: D824 | D17: MX-CANTERA LEON | E17: 10000234 | F17: Arena Triturada Basalto Malla 4 | G17: =H17-I17 -> #N/A | H17: =VLOOKUP(E17,[2]Conciliacion!$H:$AC,22,0) -> #N/A | I17: =VLOOKUP(B17,'[3]Hoja2 (2)'!$A:$E,5,0) -> 165.36 | J17: =(L17*4%)+L17 -> 165.36 | K17: 165.36 | L17: =VLOOKUP(E17,[4]TRABAJO!$H:$S,9,0) -> 159 | M17: =VLOOKUP(E17,[5]TRABAJO!$F:$S,11,0) -> 159 | N17: =VLOOKUP(E17,[6]TRABAJO!$H:$S,9,0) -> 159 | O17: =VLOOKUP(B17,[7]TRABAJO!$C:$S,14,0) -> 159 | P17: =VLOOKUP(B17,[8]TRABAJO!$C:$S,14,0) -> 159 | Q17: =VLOOKUP(B17,[9]TRABAJO!$C:$S,14,0) -> 159 | R17: =VLOOKUP(B17,[10]TRABAJO!$C:$Q,15,0) -> 159 | S17: 159 | T17: =(S17*5%)+S17 -> 166.95 | U17: =(S17*10%)+S17 -> 174.9 | V17: =VLOOKUP(B17,'[11]ZICP-MARZO'!$B:$P,15,0) -> #N/A | W17: =VLOOKUP(B17,[11]CONSOLIDADO_ABRIL!$B:$J,9,0) -> #N/A | X17: =V17-W17 -> #N/A | Y17: =VLOOKUP(B17,[11]CONSOLIDADO_MAYO!$B:$J,9,0) -> #N/A | Z17: =S17-Y17 -> #N/A
A18: NORESTE | B18: =+C18&E18 -> D82410000285 | C18: D824 | D18: MX-CANTERA LEON | E18: 10000285 | F18: Grava Triturada Basalto 10 mm - 3/8" | G18: =H18-I18 -> #N/A | H18: =VLOOKUP(E18,[2]Conciliacion!$H:$AC,22,0) -> #N/A | I18: =VLOOKUP(B18,'[3]Hoja2 (2)'!$A:$E,5,0) -> 182 | J18: =(L18*4%)+L18 -> 182 | K18: 182 | L18: =VLOOKUP(E18,[4]TRABAJO!$H:$S,9,0) -> 175 | M18: =VLOOKUP(E18,[5]TRABAJO!$F:$S,11,0) -> 175 | N18: =VLOOKUP(E18,[6]TRABAJO!$H:$S,9,0) -> 175 | O18: =VLOOKUP(B18,[7]TRABAJO!$C:$S,14,0) -> 175 | P18: =VLOOKUP(B18,[8]TRABAJO!$C:$S,14,0) -> 175 | Q18: =VLOOKUP(B18,[9]TRABAJO!$C:$S,14,0) -> 175 | R18: =VLOOKUP(B18,[10]TRABAJO!$C:$Q,15,0) -> 175 | S18: 175 | T18: =(S18*5%)+S18 -> 183.75 | U18: =(S18*10%)+S18 -> 192.5 | V18: =VLOOKUP(B18,'[11]ZICP-MARZO'!$B:$P,15,0) -> #N/A | W18: =VLOOKUP(B18,[11]CONSOLIDADO_ABRIL!$B:$J,9,0) -> #N/A | X18: =V18-W18 -> #N/A | Y18: =VLOOKUP(B18,[11]CONSOLIDADO_MAYO!$B:$J,9,0) -> #N/A | Z18: =S18-Y18 -> #N/A
A19: NORESTE | B19: =+C19&E19 -> D82410000284 | C19: D824 | D19: MX-CANTERA LEON | E19: 10000284 | F19: Grava Triturada Basalto 20 mm - 3/4" | G19: =H19-I19 -> #N/A | H19: =VLOOKUP(E19,[2]Conciliacion!$H:$AC,22,0) -> #N/A | I19: =VLOOKUP(B19,'[3]Hoja2 (2)'!$A:$E,5,0) -> 182 | J19: =(L19*4%)+L19 -> 182 | K19: 182 | L19: =VLOOKUP(E19,[4]TRABAJO!$H:$S,9,0) -> 175 | M19: =VLOOKUP(E19,[5]TRABAJO!$F:$S,11,0) -> 175 | N19: =VLOOKUP(E19,[6]TRABAJO!$H:$S,9,0) -> 175 | O19: =VLOOKUP(B19,[7]TRABAJO!$C:$S,14,0) -> 175 | P19: =VLOOKUP(B19,[8]TRABAJO!$C:$S,14,0) -> 175 | Q19: =VLOOKUP(B19,[9]TRABAJO!$C:$S,14,0) -> 175 | R19: =VLOOKUP(B19,[10]TRABAJO!$C:$Q,15,0) -> 175 | S19: 175 | T19: =(S19*5%)+S19 -> 183.75 | U19: =(S19*10%)+S19 -> 192.5 | V19: =VLOOKUP(B19,'[11]ZICP-MARZO'!$B:$P,15,0) -> #N/A | W19: =VLOOKUP(B19,[11]CONSOLIDADO_ABRIL!$B:$J,9,0) -> #N/A | X19: =V19-W19 -> #N/A | Y19: =VLOOKUP(B19,[11]CONSOLIDADO_MAYO!$B:$J,9,0) -> #N/A | Z19: =S19-Y19 -> #N/A
A20: NORESTE | B20: =+C20&E20 -> D82410000287 | C20: D824 | D20: MX-CANTERA LEON | E20: 10000287 | F20: Grava Triturada Basalto 40 mm - 1 1/2" | G20: =H20-I20 -> #N/A | H20: =VLOOKUP(E20,[2]Conciliacion!$H:$AC,22,0) -> #N/A | I20: =VLOOKUP(B20,'[3]Hoja2 (2)'!$A:$E,5,0) -> 182 | J20: =(L20*4%)+L20 -> 182 | K20: 182 | L20: =VLOOKUP(E20,[4]TRABAJO!$H:$S,9,0) -> 175 | M20: =VLOOKUP(E20,[5]TRABAJO!$F:$S,11,0) -> 175 | N20: =VLOOKUP(E20,[6]TRABAJO!$H:$S,9,0) -> 175 | O20: =VLOOKUP(B20,[7]TRABAJO!$C:$S,14,0) -> 211 | P20: =VLOOKUP(B20,[8]TRABAJO!$C:$S,14,0) -> 211.04 | Q20: =VLOOKUP(B20,[9]TRABAJO!$C:$S,14,0) -> 175 | R20: =VLOOKUP(B20,[10]TRABAJO!$C:$Q,15,0) -> 175 | S20: 175 | T20: =(S20*5%)+S20 -> 183.75 | U20: =(S20*10%)+S20 -> 192.5 | V20: =VLOOKUP(B20,'[11]ZICP-MARZO'!$B:$P,15,0) -> #N/A | W20: =VLOOKUP(B20,[11]CONSOLIDADO_ABRIL!$B:$J,9,0) -> #N/A | X20: =V20-W20 -> #N/A | Y20: =VLOOKUP(B20,[11]CONSOLIDADO_MAYO!$B:$J,9,0) -> #N/A | Z20: =S20-Y20 -> #N/A
A21: NORESTE | B21: =+C21&E21 -> D81610000124 | C21: D816 | D21: MX-CANTERA MONTERREY | E21: 10000124 | F21: Arena Triturada Caliza Malla 4 | G21: =H21-I21 -> #N/A | H21: =VLOOKUP(E21,[2]Conciliacion!$H:$AC,22,0) -> #N/A | I21: =VLOOKUP(B21,'[3]Hoja2 (2)'!$A:$E,5,0) -> 284.44 | J21: =(L21*4%)+L21 -> 284.44 | K21: 283.92 | L21: =VLOOKUP(E21,[4]TRABAJO!$H:$S,9,0) -> 273.5 | M21: =VLOOKUP(E21,[5]TRABAJO!$F:$S,11,0) -> 273.5 | N21: =VLOOKUP(E21,[6]TRABAJO!$H:$S,9,0) -> 273.5 | O21: =VLOOKUP(B21,[7]TRABAJO!$C:$S,14,0) -> 273.5 | P21: 339.91 | Q21: =VLOOKUP(B21,[9]TRABAJO!$C:$S,14,0) -> #N/A | R21: =VLOOKUP(B21,[10]TRABAJO!$C:$Q,15,0) -> 273.5 | S21: 273.5 | T21: =(S21*5%)+S21 -> 287.175 | U21: =(S21*10%)+S21 -> 300.85 | V21: =VLOOKUP(B21,'[11]ZICP-MARZO'!$B:$P,15,0) -> #N/A | W21: =VLOOKUP(B21,[11]CONSOLIDADO_ABRIL!$B:$J,9,0) -> #N/A | X21: =V21-W21 -> #N/A | Y21: =VLOOKUP(B21,[11]CONSOLIDADO_MAYO!$B:$J,9,0) -> #N/A | Z21: =S21-Y21 -> #N/A
A22: NORESTE | B22: =+C22&E22 -> D81610164169 | C22: D816 | D22: MX-CANTERA MONTERREY | E22: 10164169 | F22: ARENA TRITURADA CALIZA MALLA 4 B47 FILIA | G22: =H22-I22 -> #N/A | H22: =VLOOKUP(E22,[2]Conciliacion!$H:$AC,22,0) -> #N/A | I22: =VLOOKUP(B22,'[3]Hoja2 (2)'!$A:$E,5,0) -> 284.44 | J22: =(L22*4%)+L22 -> 284.44 | K22: 337.48 | L22: 273.5 | M22: =VLOOKUP(E22,[5]TRABAJO!$F:$S,11,0) -> 273.5 | N22: =VLOOKUP(E22,[6]TRABAJO!$H:$S,9,0) -> #N/A | O22: =VLOOKUP(B22,[7]TRABAJO!$C:$S,14,0) -> 273.5 | P22: =VLOOKUP(B22,[8]TRABAJO!$C:$S,14,0) -> 273.5 | Q22: =VLOOKUP(B22,[9]TRABAJO!$C:$S,14,0) -> 273.5 | R22: ,15,0 | S22: 273.5 | T22: =(S22*5%)+S22 -> 287.175 | U22: =(S22*10%)+S22 -> 300.85 | V22: =VLOOKUP(B22,'[11]ZICP-MARZO'!$B:$P,15,0) -> #N/A | W22: =VLOOKUP(B22,[11]CONSOLIDADO_ABRIL!$B:$J,9,0) -> #N/A | X22: =V22-W22 -> #N/A | Y22: =VLOOKUP(B22,[11]CONSOLIDADO_MAYO!$B:$J,9,0) -> #N/A | Z22: =S22-Y22 -> #N/A
A23: NORESTE | B23: =+C23&E23 -> D81610000260 | C23: D816 | D23: MX-CANTERA MONTERREY | E23: 10000260 | F23: Arena Triturada Caliza Malla 5 | G23: =H23-I23 -> #N/A | H23: =VLOOKUP(E23,[2]Conciliacion!$H:$AC,22,0) -> #N/A | I23: =VLOOKUP(B23,'[3]Hoja2 (2)'!$A:$E,5,0) -> 320.32 | J23: =(L23*4%)+L23 -> 320.32 | K23: 320.32 | L23: =VLOOKUP(E23,[4]TRABAJO!$H:$S,9,0) -> 308 | M23: =VLOOKUP(E23,[5]TRABAJO!$F:$S,11,0) -> 308 | N23: 308 | O23: =VLOOKUP(B23,[7]TRABAJO!$C:$S,14,0) -> 395.87464 | P23: =VLOOKUP(B23,[8]TRABAJO!$C:$S,14,0) -> 379.08993 | Q23: =VLOOKUP(B23,[9]TRABAJO!$C:$S,14,0) -> 395.87464 | R23: =VLOOKUP(B23,[10]TRABAJO!$C:$Q,15,0) -> 388.22985 | S23: 388 | T23: =(S23*5%)+S23 -> 407.4 | U23: =(S23*10%)+S23 -> 426.8 | V23: =VLOOKUP(B23,'[11]ZICP-MARZO'!$B:$P,15,0) -> #N/A | W23: =VLOOKUP(B23,[11]CONSOLIDADO_ABRIL!$B:$J,9,0) -> #N/A | X23: =V23-W23 -> #N/A | Y23: =VLOOKUP(B23,[11]CONSOLIDADO_MAYO!$B:$J,9,0) -> #N/A | Z23: =S23-Y23 -> #N/A
A24: NORESTE | B24: =+C24&E24 -> D81610000237 | C24: D816 | D24: MX-CANTERA MONTERREY | E24: 10000237 | F24: Grava Triturada Caliza 10 mm - 3/8" | G24: =H24-I24 -> #N/A | H24: =VLOOKUP(E24,[2]Conciliacion!$H:$AC,22,0) -> #N/A | I24: =VLOOKUP(B24,'[3]Hoja2 (2)'!$A:$E,5,0) -> 294.32 | J24: =(L24*4%)+L24 -> 294.32 | K24: 280.8 | L24: =VLOOKUP(E24,[4]TRABAJO!$H:$S,9,0) -> 283 | M24: =VLOOKUP(E24,[5]TRABAJO!$F:$S,11,0) -> 270 | N24: =VLOOKUP(E24,[6]TRABAJO!$H:$S,9,0) -> 283 | O24: =VLOOKUP(B24,[7]TRABAJO!$C:$S,14,0) -> 335.61 | P24: =VLOOKUP(B24,[8]TRABAJO!$C:$S,14,0) -> 282.6 | Q24: =VLOOKUP(B24,[9]TRABAJO!$C:$S,14,0) -> 282.6 | R24: =VLOOKUP(B24,[10]TRABAJO!$C:$Q,15,0) -> 282.6 | S24: 282.6 | T24: =(S24*5%)+S24 -> 296.73 | U24: =(S24*10%)+S24 -> 310.86 | V24: =VLOOKUP(B24,'[11]ZICP-MARZO'!$B:$P,15,0) -> #N/A | W24: =VLOOKUP(B24,[11]CONSOLIDADO_ABRIL!$B:$J,9,0) -> #N/A | X24: =V24-W24 -> #N/A | Y24: =VLOOKUP(B24,[11]CONSOLIDADO_MAYO!$B:$J,9,0) -> #N/A | Z24: =S24-Y24 -> #N/A
A25: NORESTE | B25: =+C25&E25 -> D81610000241 | C25: D816 | D25: MX-CANTERA MONTERREY | E25: 10000241 | F25: Grava Triturada Caliza 20 mm - 3/4" | G25: =H25-I25 -> #N/A | H25: =VLOOKUP(E25,[2]Conciliacion!$H:$AC,22,0) -> #N/A | I25: =VLOOKUP(B25,'[3]Hoja2 (2)'!$A:$E,5,0) -> 284.44 | J25: =(L25*4%)+L25 -> 284.44 | K25: 284.44 | L25: =VLOOKUP(E25,[4]TRABAJO!$H:$S,9,0) -> 273.5 | M25: =VLOOKUP(E25,[5]TRABAJO!$F:$S,11,0) -> 273.5 | N25: =VLOOKUP(E25,[6]TRABAJO!$H:$S,9,0) -> 273.5 | O25: =VLOOKUP(B25,[7]TRABAJO!$C:$S,14,0) -> 273.5 | P25: =VLOOKUP(B25,[8]TRABAJO!$C:$S,14,0) -> 273.5 | Q25: =VLOOKUP(B25,[9]TRABAJO!$C:$S,14,0) -> 273.5 | R25: =VLOOKUP(B25,[10]TRABAJO!$C:$Q,15,0) -> 273.5 | S25: 273.5 | T25: =(S25*5%)+S25 -> 287.175 | U25: =(S25*10%)+S25 -> 300.85 | V25: =VLOOKUP(B25,'[11]ZICP-MARZO'!$B:$P,15,0) -> #N/A | W25: =VLOOKUP(B25,[11]CONSOLIDADO_ABRIL!$B:$J,9,0) -> #N/A | X25: =V25-W25 -> #N/A | Y25: =VLOOKUP(B25,[11]CONSOLIDADO_MAYO!$B:$J,9,0) -> #N/A | Z25: =S25-Y25 -> #N/A
A26: NORESTE | B26: =+C26&E26 -> D86310038952 | C26: D863 | D26: MX-CANTERA TAMUIN | E26: 10038952 | F26: Arena Triturada Caliza Malla 4 | G26: =H26-I26 -> #N/A | H26: =VLOOKUP(E26,[2]Conciliacion!$H:$AC,22,0) -> #N/A | I26: =VLOOKUP(B26,'[3]Hoja2 (2)'!$A:$E,5,0) -> 160.04 | J26: =(L26*4%)+L26 -> 160.03515 | K26: 167.23 | L26: =VLOOKUP(E26,[4]TRABAJO!$H:$S,9,0) -> 153.87995 | M26: =VLOOKUP(E26,[5]TRABAJO!$F:$S,11,0) -> 153.87995 | N26: =VLOOKUP(E26,[6]TRABAJO!$H:$S,9,0) -> 153.87996 | O26: =VLOOKUP(B26,[7]TRABAJO!$C:$S,14,0) -> 153.87994 | P26: =VLOOKUP(B26,[8]TRABAJO!$C:$S,14,0) -> 153.87995 | Q26: =VLOOKUP(B26,[9]TRABAJO!$C:$S,14,0) -> 153.87994 | R26: =VLOOKUP(B26,[10]TRABAJO!$C:$Q,15,0) -> 153.88 | S26: 153.88 | T26: =(S26*5%)+S26 -> 161.574 | U26: =(S26*10%)+S26 -> 169.268 | V26: =VLOOKUP(B26,'[11]ZICP-MARZO'!$B:$P,15,0) -> #N/A | W26: =VLOOKUP(B26,[11]CONSOLIDADO_ABRIL!$B:$J,9,0) -> #N/A | X26: =V26-W26 -> #N/A | Y26: =VLOOKUP(B26,[11]CONSOLIDADO_MAYO!$B:$J,9,0) -> #N/A | Z26: =S26-Y26 -> #N/A
A27: NORESTE | B27: =+C27&E27 -> D86310038949 | C27: D863 | D27: MX-CANTERA TAMUIN | E27: 10038949 | F27: Grava Triturada Caliza 10 mm - 3/8" | G27: =H27-I27 -> #N/A | H27: =VLOOKUP(E27,[2]Conciliacion!$H:$AC,22,0) -> #N/A | I27: =VLOOKUP(B27,'[3]Hoja2 (2)'!$A:$E,5,0) -> 166.97 | J27: =(L27*4%)+L27 -> 166.97196 | K27: 147.08 | L27: =VLOOKUP(E27,[4]TRABAJO!$H:$S,9,0) -> 160.54996 | M27: =VLOOKUP(E27,[5]TRABAJO!$F:$S,11,0) -> #N/A | N27: =VLOOKUP(E27,[6]TRABAJO!$H:$S,9,0) -> 139.3 | O27: =VLOOKUP(B27,[7]TRABAJO!$C:$S,14,0) -> 168.5 | P27: =VLOOKUP(B27,[8]TRABAJO!$C:$S,14,0) -> 170 | Q27: =VLOOKUP(B27,[9]TRABAJO!$C:$S,14,0) -> 170 | R27: =VLOOKUP(B27,[10]TRABAJO!$C:$Q,15,0) -> 168.49997 | S27: 168.49996 | T27: =(S27*5%)+S27 -> 176.92496 | U27: =(S27*10%)+S27 -> 185.34996 | V27: =VLOOKUP(B27,'[11]ZICP-MARZO'!$B:$P,15,0) -> #N/A | W27: =VLOOKUP(B27,[11]CONSOLIDADO_ABRIL!$B:$J,9,0) -> #N/A | X27: =V27-W27 -> #N/A | Y27: =VLOOKUP(B27,[11]CONSOLIDADO_MAYO!$B:$J,9,0) -> #N/A | Z27: =S27-Y27 -> #N/A
A28: NORESTE | B28: =+C28&E28 -> D86310038950 | C28: D863 | D28: MX-CANTERA TAMUIN | E28: 10038950 | F28: Grava Triturada Caliza 20 mm - 3/4" | G28: =H28-I28 -> #N/A | H28: =VLOOKUP(E28,[2]Conciliacion!$H:$AC,22,0) -> #N/A | I28: =VLOOKUP(B28,'[3]Hoja2 (2)'!$A:$E,5,0) -> 160.04 | J28: =(L28*4%)+L28 -> 160.03523 | K28: 161.41 | L28: =VLOOKUP(E28,[4]TRABAJO!$H:$S,9,0) -> 153.88003 | M28: =VLOOKUP(E28,[5]TRABAJO!$F:$S,11,0) -> 153.87996 | N28: =VLOOKUP(E28,[6]TRABAJO!$H:$S,9,0) -> 153.87997 | O28: =VLOOKUP(B28,[7]TRABAJO!$C:$S,14,0) -> 153.87996 | P28: =VLOOKUP(B28,[8]TRABAJO!$C:$S,14,0) -> 141.29001 | Q28: =VLOOKUP(B28,[9]TRABAJO!$C:$S,14,0) -> 153.87999 | R28: =VLOOKUP(B28,[10]TRABAJO!$C:$Q,15,0) -> 153.88 | S28: 153.88 | T28: =(S28*5%)+S28 -> 161.574 | U28: =(S28*10%)+S28 -> 169.268 | V28: =VLOOKUP(B28,'[11]ZICP-MARZO'!$B:$P,15,0) -> #N/A | W28: =VLOOKUP(B28,[11]CONSOLIDADO_ABRIL!$B:$J,9,0) -> #N/A | X28: =V28-W28 -> #N/A | Y28: =VLOOKUP(B28,[11]CONSOLIDADO_MAYO!$B:$J,9,0) -> #N/A | Z28: =S28-Y28 -> #N/A
A29: NORESTE | B29: =+C29&E29 -> D86310049672 | C29: D863 | D29: MX-CANTERA TAMUIN | E29: 10049672 | F29: Grava Triturada Caliza 40 mm - 1 1/2" | G29: =H29-I29 -> #N/A | H29: =VLOOKUP(E29,[2]Conciliacion!$H:$AC,22,0) -> #N/A | I29: =VLOOKUP(B29,'[3]Hoja2 (2)'!$A:$E,5,0) -> 166.4 | J29: =(L29*4%)+L29 -> 166.4 | K29: 166.4 | L29: =VLOOKUP(E29,[4]TRABAJO!$H:$S,9,0) -> 160 | M29: =VLOOKUP(E29,[5]TRABAJO!$F:$S,11,0) -> 160 | N29: =VLOOKUP(E29,[6]TRABAJO!$H:$S,9,0) -> 160 | O29: =VLOOKUP(B29,[7]TRABAJO!$C:$S,14,0) -> 160 | P29: =VLOOKUP(B29,[8]TRABAJO!$C:$S,14,0) -> 160 | Q29: =VLOOKUP(B29,[9]TRABAJO!$C:$S,14,0) -> 105 | R29: =VLOOKUP(B29,[10]TRABAJO!$C:$Q,15,0) -> 160 | S29: 160 | T29: =(S29*5%)+S29 -> 168 | U29: =(S29*10%)+S29 -> 176 | V29: =VLOOKUP(B29,'[11]ZICP-MARZO'!$B:$P,15,0) -> #N/A | W29: =VLOOKUP(B29,[11]CONSOLIDADO_ABRIL!$B:$J,9,0) -> #N/A | X29: =V29-W29 -> #N/A | Y29: =VLOOKUP(B29,[11]CONSOLIDADO_MAYO!$B:$J,9,0) -> #N/A | Z29: =S29-Y29 -> #N/A
A30: NORESTE | B30: =+C30&E30 -> D85210038942 | C30: D852 | D30: MX-CANTERA TORREON II | E30: 10038942 | F30: Arena Triturada Caliza Malla 8 | G30: =H30-I30 -> #N/A | H30: =VLOOKUP(E30,[2]Conciliacion!$H:$AC,22,0) -> #N/A | I30: =VLOOKUP(B30,'[3]Hoja2 (2)'!$A:$E,5,0) -> 131.56 | J30: =(L30*4%)+L30 -> 131.56 | K30: 187.2 | L30: =VLOOKUP(E30,[4]TRABAJO!$H:$S,9,0) -> 126.5 | M30: =VLOOKUP(E30,[5]TRABAJO!$F:$S,11,0) -> 126.49999 | N30: =VLOOKUP(E30,[6]TRABAJO!$H:$S,9,0) -> 126.49999 | O30: =VLOOKUP(B30,[7]TRABAJO!$C:$S,14,0) -> 126.49999 | P30: =VLOOKUP(B30,[8]TRABAJO!$C:$S,14,0) -> 126.49998 | Q30: =VLOOKUP(B30,[9]TRABAJO!$C:$S,14,0) -> 127.33442 | R30: =VLOOKUP(B30,[10]TRABAJO!$C:$Q,15,0) -> 128.8 | S30: 128.8 | T30: =(S30*5%)+S30 -> 135.24 | U30: =(S30*10%)+S30 -> 141.68 | V30: =VLOOKUP(B30,'[11]ZICP-MARZO'!$B:$P,15,0) -> #N/A | W30: =VLOOKUP(B30,[11]CONSOLIDADO_ABRIL!$B:$J,9,0) -> #N/A | X30: =V30-W30 -> #N/A | Y30: =VLOOKUP(B30,[11]CONSOLIDADO_MAYO!$B:$J,9,0) -> #N/A | Z30: =S30-Y30 -> #N/A
A31: NORESTE | B31: =+C31&E31 -> D85210038947 | C31: D852 | D31: MX-CANTERA TORREON II | E31: 10038947 | F31: Grava Triturada Caliza 10 mm - 3/8" | G31: =H31-I31 -> #N/A | H31: =VLOOKUP(E31,[2]Conciliacion!$H:$AC,22,0) -> #N/A | I31: =VLOOKUP(B31,'[3]Hoja2 (2)'!$A:$E,5,0) -> 115.44 | J31: =(L31*4%)+L31 -> 115.44 | K31: 115.44 | L31: =VLOOKUP(E31,[4]TRABAJO!$H:$S,9,0) -> 111 | M31: =VLOOKUP(E31,[5]TRABAJO!$F:$S,11,0) -> 111 | N31: =VLOOKUP(E31,[6]TRABAJO!$H:$S,9,0) -> 111 | O31: =VLOOKUP(B31,[7]TRABAJO!$C:$S,14,0) -> 111 | P31: =VLOOKUP(B31,[8]TRABAJO!$C:$S,14,0) -> 111 | Q31: =VLOOKUP(B31,[9]TRABAJO!$C:$S,14,0) -> 110.9 | R31: =VLOOKUP(B31,[10]TRABAJO!$C:$Q,15,0) -> 110.9 | S31: 110.9 | T31: =(S31*5%)+S31 -> 116.445 | U31: =(S31*10%)+S31 -> 121.99 | V31: =VLOOKUP(B31,'[11]ZICP-MARZO'!$B:$P,15,0) -> #N/A | W31: =VLOOKUP(B31,[11]CONSOLIDADO_ABRIL!$B:$J,9,0) -> #N/A | X31: =V31-W31 -> #N/A | Y31: =VLOOKUP(B31,[11]CONSOLIDADO_MAYO!$B:$J,9,0) -> #N/A | Z31: =S31-Y31 -> #N/A
A32: NORESTE | B32: =+C32&E32 -> D85210038945 | C32: D852 | D32: MX-CANTERA TORREON II | E32: 10038945 | F32: Grava Triturada Caliza 20 mm - 3/4" | G32: =H32-I32 -> #N/A | H32: =VLOOKUP(E32,[2]Conciliacion!$H:$AC,22,0) -> #N/A | I32: =VLOOKUP(B32,'[3]Hoja2 (2)'!$A:$E,5,0) -> 118.56 | J32: =(L32*4%)+L32 -> 118.56 | K32: 139.78 | L32: =VLOOKUP(E32,[4]TRABAJO!$H:$S,9,0) -> 114 | M32: =VLOOKUP(E32,[5]TRABAJO!$F:$S,11,0) -> 134.4 | N32: =VLOOKUP(E32,[6]TRABAJO!$H:$S,9,0) -> 134.39997 | O32: =VLOOKUP(B32,[7]TRABAJO!$C:$S,14,0) -> 134.4 | P32: =VLOOKUP(B32,[8]TRABAJO!$C:$S,14,0) -> 134.39999 | Q32: =VLOOKUP(B32,[9]TRABAJO!$C:$S,14,0) -> 134.40001 | R32: =VLOOKUP(B32,[10]TRABAJO!$C:$Q,15,0) -> 134.40002 | S32: 123.19998 | T32: =(S32*5%)+S32 -> 129.35998 | U32: =(S32*10%)+S32 -> 135.51998 | V32: =VLOOKUP(B32,'[11]ZICP-MARZO'!$B:$P,15,0) -> #N/A | W32: =VLOOKUP(B32,[11]CONSOLIDADO_ABRIL!$B:$J,9,0) -> #N/A | X32: =V32-W32 -> #N/A | Y32: =VLOOKUP(B32,[11]CONSOLIDADO_MAYO!$B:$J,9,0) -> #N/A | Z32: =S32-Y32 -> #N/A
A33: NORESTE | B33: =+C33&E33 -> D85210038659 | C33: D852 | D33: MX-CANTERA TORREON II | E33: 10038659 | F33: Grava Triturada Caliza 40 mm - 1 1/2" | G33: =H33-I33 -> #N/A | H33: =VLOOKUP(E33,[2]Conciliacion!$H:$AC,22,0) -> #N/A | I33: =VLOOKUP(B33,'[3]Hoja2 (2)'!$A:$E,5,0) -> 139.78 | J33: =(L33*4%)+L33 -> 139.77597 | K33: 139.78 | L33: =VLOOKUP(E33,[4]TRABAJO!$H:$S,9,0) -> 134.39997 | M33: =VLOOKUP(E33,[5]TRABAJO!$F:$S,11,0) -> 134.39997 | N33: =VLOOKUP(E33,[6]TRABAJO!$H:$S,9,0) -> 114 | O33: =VLOOKUP(B33,[7]TRABAJO!$C:$S,14,0) -> 131 | P33: =VLOOKUP(B33,[8]TRABAJO!$C:$S,14,0) -> 114 | Q33: =VLOOKUP(B33,[9]TRABAJO!$C:$S,14,0) -> 114 | R33: =VLOOKUP(B33,[10]TRABAJO!$C:$Q,15,0) -> 114 | S33: 114 | T33: =(S33*5%)+S33 -> 119.7 | U33: =(S33*10%)+S33 -> 125.4 | V33: =VLOOKUP(B33,'[11]ZICP-MARZO'!$B:$P,15,0) -> #N/A | W33: =VLOOKUP(B33,[11]CONSOLIDADO_ABRIL!$B:$J,9,0) -> #N/A | X33: =V33-W33 -> #N/A | Y33: =VLOOKUP(B33,[11]CONSOLIDADO_MAYO!$B:$J,9,0) -> #N/A | Z33: =S33-Y33 -> #N/A
A34: PACIFICO | B34: =+C34&E34 -> D86610000266 | C34: D866 | D34: MX-CANTERA PONCITLAN | E34: 10000266 | F34: Arena Triturada Basalto Malla 5 | G34: =H34-I34 -> #N/A | H34: =VLOOKUP(E34,[2]Conciliacion!$H:$AC,22,0) -> #N/A | I34: =VLOOKUP(B34,'[3]Hoja2 (2)'!$A:$E,5,0) -> 206.91 | J34: =(L34*4%)+L34 -> 206.90801 | K34: 206.86 | L34: =VLOOKUP(E34,[4]TRABAJO!$H:$S,9,0) -> 198.95001 | M34: =VLOOKUP(E34,[5]TRABAJO!$F:$S,11,0) -> 198.95001 | N34: =VLOOKUP(E34,[6]TRABAJO!$H:$S,9,0) -> 198.95001 | O34: =VLOOKUP(B34,[7]TRABAJO!$C:$S,14,0) -> 198.95 | P34: =VLOOKUP(B34,[8]TRABAJO!$C:$S,14,0) -> 198.94999 | Q34: =VLOOKUP(B34,[9]TRABAJO!$C:$S,14,0) -> 198.95 | R34: =VLOOKUP(B34,[10]TRABAJO!$C:$Q,15,0) -> 198.95 | S34: 198.95 | T34: =(S34*5%)+S34 -> 208.8975 | U34: =(S34*10%)+S34 -> 218.845 | V34: =VLOOKUP(B34,'[11]ZICP-MARZO'!$B:$P,15,0) -> #N/A | W34: =VLOOKUP(B34,[11]CONSOLIDADO_ABRIL!$B:$J,9,0) -> #N/A | X34: =V34-W34 -> #N/A | Y34: =VLOOKUP(B34,[11]CONSOLIDADO_MAYO!$B:$J,9,0) -> #N/A | Z34: =S34-Y34 -> #N/A
A35: PACIFICO | B35: =+C35&E35 -> D86610000293 | C35: D866 | D35: MX-CANTERA PONCITLAN | E35: 10000293 | F35: Grava Triturada Basalto 10 mm - 3/8" | G35: =H35-I35 -> #N/A | H35: =VLOOKUP(E35,[2]Conciliacion!$H:$AC,22,0) -> #N/A | I35: =VLOOKUP(B35,'[3]Hoja2 (2)'!$A:$E,5,0) -> 267.54 | J35: =(L35*4%)+L35 -> 267.53999 | K35: 267.59 | L35: =VLOOKUP(E35,[4]TRABAJO!$H:$S,9,0) -> 257.25 | M35: =VLOOKUP(E35,[5]TRABAJO!$F:$S,11,0) -> 257.25004 | N35: =VLOOKUP(E35,[6]TRABAJO!$H:$S,9,0) -> 257.25004 | O35: =VLOOKUP(B35,[7]TRABAJO!$C:$S,14,0) -> 257.25004 | P35: =VLOOKUP(B35,[8]TRABAJO!$C:$S,14,0) -> 257.25004 | Q35: =VLOOKUP(B35,[9]TRABAJO!$C:$S,14,0) -> 257.25 | R35: =VLOOKUP(B35,[10]TRABAJO!$C:$Q,15,0) -> 257.25001 | S35: 257.25003 | T35: =(S35*5%)+S35 -> 270.11253 | U35: =(S35*10%)+S35 -> 282.97503 | V35: =VLOOKUP(B35,'[11]ZICP-MARZO'!$B:$P,15,0) -> #N/A | W35: =VLOOKUP(B35,[11]CONSOLIDADO_ABRIL!$B:$J,9,0) -> #N/A | X35: =V35-W35 -> #N/A | Y35: =VLOOKUP(B35,[11]CONSOLIDADO_MAYO!$B:$J,9,0) -> #N/A | Z35: =S35-Y35 -> #N/A
... A40: SURESTE | B40: =+C40&E40 -> DU0710000101 | C40: DU07 | D40: MX-CANCÚN III | E40: 10000101 | F40: Arena Triturada Caliza Malla 4 -Especial | G40: =H40-I40 -> #N/A | H40: =VLOOKUP(E40,[2]Conciliacion!$H:$AC,22,0) -> #N/A | I40: =VLOOKUP(B40,'[3]Hoja2 (2)'!$A:$E,5,0) -> 306.9 | J40: =(L40*4%)+L40 -> 306.904 | K40: 292.66 | L40: =VLOOKUP(E40,[4]TRABAJO!$H:$S,9,0) -> 295.1 | M40: =VLOOKUP(E40,[5]TRABAJO!$F:$S,11,0) -> 295.1 | N40: =VLOOKUP(E40,[6]TRABAJO!$H:$S,9,0) -> 295.1 | O40: =VLOOKUP(B40,[7]TRABAJO!$C:$S,14,0) -> 295.1 | P40: =VLOOKUP(B40,[8]TRABAJO!$C:$S,14,0) -> 310.1 | Q40: =VLOOKUP(B40,[9]TRABAJO!$C:$S,14,0) -> 310.1 | R40: =VLOOKUP(B40,[10]TRABAJO!$C:$Q,15,0) -> 310.1 | S40: 310.1 | T40: =(S40*5%)+S40 -> 325.605 | U40: =(S40*10%)+S40 -> 341.11 | V40: =VLOOKUP(B40,'[11]ZICP-MARZO'!$B:$P,15,0) -> 310.1 | W40: =VLOOKUP(B40,[11]CONSOLIDADO_ABRIL!$B:$J,9,0) -> 310.1 | X40: =V40-W40 -> 0 | Y40: =VLOOKUP(B40,[11]CONSOLIDADO_MAYO!$B:$J,9,0) -> 310.1 | Z40: =S40-Y40 -> 0
A41: SURESTE | B41: =+C41&E41 -> DU0710000112 | C41: DU07 | D41: MX-CANCÚN III | E41: 10000112 | F41: Grava Triturada Caliza 13 mm - 1/2" | G41: =H41-I41 -> #N/A | H41: =VLOOKUP(E41,[2]Conciliacion!$H:$AC,22,0) -> #N/A | I41: =VLOOKUP(B41,'[3]Hoja2 (2)'!$A:$E,5,0) -> 242.32 | J41: =(L41*4%)+L41 -> 242.32 | L41: =VLOOKUP(E41,[4]TRABAJO!$H:$S,9,0) -> 233 | M41: =VLOOKUP(E41,[5]TRABAJO!$F:$S,11,0) -> 233 | N41: =VLOOKUP(E41,[6]TRABAJO!$H:$S,9,0) -> 233 | O41: =VLOOKUP(B41,[7]TRABAJO!$C:$S,14,0) -> 233 | P41: 265.3015 | Q41: =VLOOKUP(B41,[9]TRABAJO!$C:$S,14,0) -> #N/A | R41: =VLOOKUP(B41,[10]TRABAJO!$C:$Q,15,0) -> 248 | S41: 248 | T41: =(S41*5%)+S41 -> 260.4 | U41: =(S41*10%)+S41 -> 272.8 | V41: =VLOOKUP(B41,'[11]ZICP-MARZO'!$B:$P,15,0) -> 218 | W41: =VLOOKUP(B41,[11]CONSOLIDADO_ABRIL!$B:$J,9,0) -> 248 | X41: =V41-W41 -> -30 | Y41: =VLOOKUP(B41,[11]CONSOLIDADO_MAYO!$B:$J,9,0) -> 248 | Z41: =S41-Y41 -> 0
A42: SURESTE | B42: =+C42&E42 -> DU0710000110 | C42: DU07 | D42: MX-CANCÚN III | E42: 10000110 | F42: GRAVA TRITURADA CALIZA 20 MM “3/4"–INTEG | G42: =H42-I42 -> #N/A | H42: =VLOOKUP(E42,[2]Conciliacion!$H:$AC,22,0) -> #N/A | I42: =VLOOKUP(B42,'[3]Hoja2 (2)'!$A:$E,5,0) -> 294.1 | J42: =(L42*4%)+L42 -> 294.1032 | K42: 269.15 | L42: =VLOOKUP(E42,[4]TRABAJO!$H:$S,9,0) -> 282.79154 | M42: =VLOOKUP(E42,[5]TRABAJO!$F:$S,11,0) -> 268 | N42: =VLOOKUP(E42,[6]TRABAJO!$H:$S,9,0) -> 268 | O42: =VLOOKUP(B42,[7]TRABAJO!$C:$S,14,0) -> 268 | P42: 289.66131 | Q42: =VLOOKUP(B42,[9]TRABAJO!$C:$S,14,0) -> 283.10006 | R42: =VLOOKUP(B42,[10]TRABAJO!$C:$Q,15,0) -> 283.10002 | S42: 283.09999 | T42: =(S42*5%)+S42 -> 297.25499 | U42: =(S42*10%)+S42 -> 311.40999 | V42: =VLOOKUP(B42,'[11]ZICP-MARZO'!$B:$P,15,0) -> 266.68 | W42: =VLOOKUP(B42,[11]CONSOLIDADO_ABRIL!$B:$J,9,0) -> 283.1 | X42: =V42-W42 -> -16.42 | Y42: =VLOOKUP(B42,[11]CONSOLIDADO_MAYO!$B:$J,9,0) -> 283.1 | Z42: =S42-Y42 -> -1.25101e-05
A43: CENTRO | B43: =+C43&E43 -> D86110003153 | C43: D861 | D43: MX-CANTERA QUERETARO | E43: 10003153 | F43: Grava Triturada Basalto 13 mm | G43: =H43-I43 -> #N/A | H43: =VLOOKUP(E43,[2]Conciliacion!$H:$AC,22,0) -> #N/A | I43: 211.99 | J43: =(L43*4%)+L43 -> #N/A | L43: =VLOOKUP(E43,[4]TRABAJO!$H:$S,9,0) -> #N/A | M43: =VLOOKUP(E43,[5]TRABAJO!$F:$S,11,0) -> #N/A | N43: 198.38 | O43: 225.12595 | P43: 225.12595 | Q43: 225.12595 | R43: 225.12595 | S43: 221.92 | T43: 225.12595
A44: CENTRO | B44: =+C44&E44 -> D86110001450 | C44: D861 | D44: MX-CANTERA QUERETARO | E44: 10001450 | F44: Base Hidraúlica Basalto de 1 /1/2 | G44: =H44-I44 -> #N/A | H44: =VLOOKUP(E44,[2]Conciliacion!$H:$AC,22,0) -> #N/A | I44: 202.59 | J44: 195.46 | K44: 195.46 | L44: =VLOOKUP(E44,[4]TRABAJO!$H:$S,9,0) -> #N/A | M44: 195.21 | N44: 196.27 | O44: 198.64 | P44: 198.64 | Q44: 236.5095 | R44: 236.5095 | S44: 203.36 | T44: 236.5095
A45: SURESTE | B45: =+C45&E45 -> DU0710000103 | C45: DU07 | D45: MX-CANCÚN III | E45: 10000103 | F45: Base H Triturada Caliza 1 1/2" a Finos | G45: =H45-I45 -> #N/A | H45: =VLOOKUP(E45,[2]Conciliacion!$H:$AC,22,0) -> #N/A | I45: 149.86 | J45: =(L45*4%)+L45 -> 113.8592 | K45: 110.11 | L45: 109.48 | M45: 109.48 | N45: 110.82365 | O45: 115.91537 | P45: 115.91537 | Q45: 116.89 | R45: 116.84 | S45: 110.95161 | T45: 183.71
A46: CENTRO | B46: =+C46&E46 -> D86110002499 | C46: D861 | D46: MX-CANTERA QUERETARO | E46: 10002499 | F46: Arena Triturada Basalto Malla 4 -Mezcla | G46: =H46-I46 -> #N/A | H46: 174.1 | I46: =VLOOKUP(B46,'[3]Hoja2 (2)'!$A:$E,5,0) -> #N/A | K46: 167.78 | L46: =VLOOKUP(E46,[4]TRABAJO!$H:$S,9,0) -> #N/A | M46: =VLOOKUP(E46,[5]TRABAJO!$F:$S,11,0) -> #N/A | N46: 168.52 | O46: 156.32 | P46: 156.32 | Q46: 219.0309 | R46: 219.0309 | S46: 172 | T46: 219.0309
A47: CENTRO | B47: =+C47&E47 -> D86410001203 | C47: D864 | D47: MX-CANTERA CERRO JARDIN | E47: 10001203 | F47: Desperdicio Triturado Caliza | G47: =H47-I47 -> #N/A | H47: =VLOOKUP(E47,[2]Conciliacion!$H:$AC,22,0) -> #N/A | I47: =VLOOKUP(B47,'[3]Hoja2 (2)'!$A:$E,5,0) -> 23.46 | J47: =(L47*4%)+L47 -> #N/A | K47: 23.46 | L47: =VLOOKUP(E47,[4]TRABAJO!$H:$S,9,0) -> #N/A | M47: =VLOOKUP(E47,[5]TRABAJO!$F:$S,11,0) -> #N/A | N47: 17.849 | O47: 1.36 | P47: 1.36 | Q47: 17.849 | R47: 17.849 | S47: 17.849 | T47: 17.849
A48: CENTRO | B48: =+C48&E48 -> D86110066861 | C48: D861 | D48: MX-CANTERA QUERETARO | E48: 10066861 | F48: GRAVA TRITURADA BASALTO DE 40 A 4 MM | G48: =H48-I48 -> #N/A | H48: =VLOOKUP(E48,[2]Conciliacion!$H:$AC,22,0) -> #N/A | I48: =VLOOKUP(B48,'[3]Hoja2 (2)'!$A:$E,5,0) -> 224.62 | J48: =(L48*4%)+L48 -> #N/A | K48: 200 | L48: =VLOOKUP(E48,[4]TRABAJO!$H:$S,9,0) -> #N/A | M48: =VLOOKUP(E48,[5]TRABAJO!$F:$S,11,0) -> 215.97998 | N48: =VLOOKUP(E48,[6]TRABAJO!$H:$S,9,0) -> #N/A | O48: 178 | P48: =VLOOKUP(B48,[8]TRABAJO!$C:$S,14,0) -> 178 | Q48: =VLOOKUP(B48,[9]TRABAJO!$C:$S,14,0) -> 215.98001 | R48: 215.97998 | T48: 215.97998
A49: CENTRO | B49: =+C49&E49 -> D86110002497 | C49: D861 | D49: MX-CANTERA QUERETARO | E49: 10002497 | F49: Grava Triturada Basalto 20 mm - 3/4"-Puq | G49: =H49-I49 -> #N/A | H49: =VLOOKUP(E49,[2]Conciliacion!$H:$AC,22,0) -> #N/A | I49: =VLOOKUP(B49,'[3]Hoja2 (2)'!$A:$E,5,0) -> #N/A | J49: =(L49*4%)+L49 -> #N/A | L49: =VLOOKUP(E49,[4]TRABAJO!$H:$S,9,0) -> #N/A | M49: =VLOOKUP(E49,[5]TRABAJO!$F:$S,11,0) -> #N/A | N49: =VLOOKUP(E49,[6]TRABAJO!$H:$S,9,0) -> #N/A | O49: 240.32 | P49: 240.32 | Q49: 247.74387 | R49: 247.74387 | S49: 247.74387 | T49: 247.74387
A50: CENTRO | B50: =+C50&E50 -> D86410172785 | C50: D864 | D50: MX-CANTERA CERRO JARDIN | E50: 10172785 | F50: BASE HIDRÁULICA 60%FINOS-40%GR | G50: =H50-I50 -> #N/A | H50: =VLOOKUP(E50,[2]Conciliacion!$H:$AC,22,0) -> #N/A | I50: 56.94 | J50: =(L50*4%)+L50 -> #N/A | L50: =VLOOKUP(E50,[4]TRABAJO!$H:$S,9,0) -> #N/A | M50: =VLOOKUP(E50,[5]TRABAJO!$F:$S,11,0) -> #N/A | N50: 55.602202 | O50: 54.99 | P50: 54.99 | Q50: 54.99 | R50: 54.99
A51: CENTRO | B51: =+C51&E51 -> D86410173784 | C51: D864 | D51: MX-CANTERA CERRO JARDIN | E51: 10173784 | F51: BASE HIDRÁULICA 80%FINOS-20%GR | G51: =H51-I51 -> #N/A | H51: =VLOOKUP(E51,[2]Conciliacion!$H:$AC,22,0) -> #N/A | I51: 41.05 | J51: =(L51*4%)+L51 -> #N/A | L51: =VLOOKUP(E51,[4]TRABAJO!$H:$S,9,0) -> #N/A | M51: =VLOOKUP(E51,[5]TRABAJO!$F:$S,11,0) -> #N/A | N51: 38.51 | O51: 38.51 | P51: 38.51 | Q51: 38.61 | R51: 38.61
A52: SURESTE | B52: =+C52&E52 -> DU0710264038 | C52: DU07 | D52: MX-CANCÚN III | E52: 10264038 | F52: MOV ARENA TRITURADA CALIZA MALLA 4 | G52: =H52-I52 -> #N/A | H52: =VLOOKUP(E52,[2]Conciliacion!$H:$AC,22,0) -> #N/A | I52: =VLOOKUP(B52,'[3]Hoja2 (2)'!$A:$E,5,0) -> 306.9 | J52: =(L52*4%)+L52 -> #N/A | L52: =VLOOKUP(E52,[4]TRABAJO!$H:$S,9,0) -> #N/A | M52: =VLOOKUP(E52,[5]TRABAJO!$F:$S,11,0) -> 295.1 | N52: =VLOOKUP(E52,[6]TRABAJO!$H:$S,9,0) -> #N/A | O52: =VLOOKUP(B52,[7]TRABAJO!$C:$S,14,0) -> 295.1 | P52: 310.1 | Q52: =VLOOKUP(B52,[9]TRABAJO!$C:$S,14,0) -> #N/A | R52: 310.1
A53: SURESTE | B53: =+C53&E53 -> DU0710264039 | C53: DU07 | D53: MX-CANCÚN III | E53: 10264039 | F53: MOV GRAVA TRITURADA CALIZA 20MM 3/4 INTE | G53: =H53-I53 -> #N/A | H53: =VLOOKUP(E53,[2]Conciliacion!$H:$AC,22,0) -> #N/A | I53: =VLOOKUP(B53,'[3]Hoja2 (2)'!$A:$E,5,0) -> 294.1 | J53: =(L53*4%)+L53 -> #N/A | L53: =VLOOKUP(E53,[4]TRABAJO!$H:$S,9,0) -> #N/A | M53: =VLOOKUP(E53,[5]TRABAJO!$F:$S,11,0) -> 268 | N53: =VLOOKUP(E53,[6]TRABAJO!$H:$S,9,0) -> #N/A | O53: =VLOOKUP(B53,[7]TRABAJO!$C:$S,14,0) -> 268 | P53: 289.66131 | Q53: =VLOOKUP(B53,[9]TRABAJO!$C:$S,14,0) -> #N/A | R53: 283.10002
A54: CENTRO | B54: =+C54&E54 -> D86110000290 | C54: D861 | D54: MX-CANTERA QUERETARO | E54: 10000290 | F54: Polvos Triturado Basalto 3/4" | G54: =H54-I54 -> #N/A | H54: =VLOOKUP(E54,[2]Conciliacion!$H:$AC,22,0) -> #N/A | I54: =VLOOKUP(B54,'[3]Hoja2 (2)'!$A:$E,5,0) -> #N/A | J54: =(N54*4%)+N54 -> 4.6904 | L54: =VLOOKUP(E54,[4]TRABAJO!$H:$S,9,0) -> #N/A | M54: =VLOOKUP(E54,[5]TRABAJO!$F:$S,11,0) -> #N/A | N54: 4.51 | O54: 4.51 | P54: 4.51 | Q54: 13.326103 | R54: 13.326103
A55: SURESTE | B55: =+C55&E55 -> DU0710264103 | C55: DU07 | D55: MX-CANCÚN III | E55: 10264103 | F55: MOV BASE H TRITURADA CALIZA 1 1/2 | G55: =H55-I55 -> #N/A | H55: =VLOOKUP(E55,[2]Conciliacion!$H:$AC,22,0) -> #N/A | I55: =VLOOKUP(B55,'[3]Hoja2 (2)'!$A:$E,5,0) -> #N/D | J55: =(L55*4%)+L55 -> 113.8592 | K55: 110.11 | L55: 109.48 | M55: 109.48 | N55: 110.82365 | O55: 115.91537 | P55: 115.91537 | Q55: =VLOOKUP(B55,[9]TRABAJO!$C:$S,14,0) -> #N/A | R55: 116.84
A56: SURESTE | B56: =+C56&E56 -> DU0710000355 | C56: DU07 | D56: MX-CANCÚN III | E56: 10000355 | F56: Grava Triturada Caliza 13 mm - 1/2" | G56: =H56-I56 -> #N/A | H56: =VLOOKUP(E56,[2]Conciliacion!$H:$AC,22,0) -> #N/A | I56: =VLOOKUP(B56,'[3]Hoja2 (2)'!$A:$E,5,0) -> #N/A | J56: =(L56*4%)+L56 -> #N/A | L56: =VLOOKUP(E56,[4]TRABAJO!$H:$S,9,0) -> #N/A | M56: =VLOOKUP(E56,[5]TRABAJO!$F:$S,11,0) -> #N/A | N56: =VLOOKUP(E56,[6]TRABAJO!$H:$S,9,0) -> #N/A | O56: 265.3015 | P56: 265.3015 | Q56: 248
A57: NORESTE | B57: =+C57&E57 -> D81610001170 | C57: D816 | D57: MX-CANTERA MONTERREY | E57: 10001170 | F57: Arena Triturada Caliza Block | G57: =H57-I57 -> #N/A | H57: =VLOOKUP(E57,[2]Conciliacion!$H:$AC,22,0) -> #N/A | I57: 282.94951 | J57: =(L57*4%)+L57 -> 288.288 | L57: 277.2 | M57: =VLOOKUP(E57,[5]TRABAJO!$F:$S,11,0) -> #N/A | N57: =VLOOKUP(E57,[6]TRABAJO!$H:$S,9,0) -> #N/A | O57: 300 | P57: 300
A58: SURESTE | B58: =+C58&E58 -> DU0710271224 | C58: DU07 | D58: MX-CANCÚN III | E58: 10271224 | F58: SUBRASANTE | G58: =H58-I58 -> #N/A | H58: =VLOOKUP(E58,[2]Conciliacion!$H:$AC,22,0) -> #N/A | I58: =VLOOKUP(B58,'[3]Hoja2 (2)'!$A:$E,5,0) -> #N/D | J58: =(L58*4%)+L58 -> #N/A | L58: =VLOOKUP(E58,[4]TRABAJO!$H:$S,9,0) -> #N/A | M58: =VLOOKUP(E58,[5]TRABAJO!$F:$S,11,0) -> #N/A | N58: =VLOOKUP(E58,[6]TRABAJO!$H:$S,9,0) -> #N/A
A59: NORESTE | B59: =+C59&E59 -> D81610000262 | C59: D816 | D59: MX-CANTERA MONTERREY | E59: 10000262 | F59: Base H Triturada Caliza 1 1/2" | G59: =H59-I59 -> #N/A | H59: =VLOOKUP(E59,[2]Conciliacion!$H:$AC,22,0) -> #N/A | I59: 310.44 | J59: =(L59*4%)+L59 -> 285.688 | K59: 273.21 | L59: 274.7 | M59: 274.7
A60: NORESTE | B60: =+C60&E60 -> D917 10263701 | C60: D917 | D60: CANTERA VALLES | E60: 10263701 | F60: GRAVA TRITURADA CALIZA 20MM | G60: =H60-I60 -> #N/A | H60: =VLOOKUP(E60,[2]Conciliacion!$H:$AC,22,0) -> #N/A | I60: =VLOOKUP(B60,'[3]Hoja2 (2)'!$A:$E,5,0) -> #N/A | J60: =(L60*4%)+L60 -> #N/A | L60: =VLOOKUP(E60,[4]TRABAJO!$H:$S,9,0) -> #N/A | M60: 158
A61: NORESTE | B61: =+C61&E61 -> D917 10248659 | C61: D917 | D61: CANTERA VALLES | E61: 10248659 | F61: ARENA No 4 | G61: =H61-I61 -> #N/A | H61: =VLOOKUP(E61,[2]Conciliacion!$H:$AC,22,0) -> #N/A | I61: =VLOOKUP(B61,'[3]Hoja2 (2)'!$A:$E,5,0) -> #N/A | J61: =(L61*4%)+L61 -> #N/A | L61: =VLOOKUP(E61,[4]TRABAJO!$H:$S,9,0) -> #N/A | M61: 158
A62: SURESTE | B62: =+C62&E62 -> DU0710000195 | C62: DU07 | D62: MX-CANCÚN III | E62: 10000195 | F62: GRAVA TRITURADA CALIZA 20 MM - 3/4"–CAPA | G62: =H62-I62 -> #N/A | H62: =VLOOKUP(E62,[2]Conciliacion!$H:$AC,22,0) -> #N/A | I62: =VLOOKUP(B62,'[3]Hoja2 (2)'!$A:$E,5,0) -> #N/A | J62: =(L62*4%)+L62 -> 278.72 | L62: 268 | M62: 268
A63: SURESTE | B63: =+C63&E63 -> DU0710000115 | C63: DU07 | D63: MX-CANCÚN III | E63: 10000115 | F63: Grava Triturada Caliza 10 mm - | G63: =H63-I63 -> #N/A | H63: =VLOOKUP(E63,[2]Conciliacion!$H:$AC,22,0) -> #N/A | I63: 384.4571 | J63: =(L63*4%)+L63 -> 340.0696 | L63: 326.99 | M63: 326.99
A64: NORESTE | B64: =+C64&E64 -> D81610036488 | C64: D816 | D64: MX-CANTERA MONTERREY | E64: 10036488 | F64: Base H Trit Caliza 3/4" a Fino | G64: =H64-I64 -> #N/A | H64: =VLOOKUP(E64,[2]Conciliacion!$H:$AC,22,0) -> #N/A | I64: 310.64 | J64: =(L64*4%)+L64 -> 292.1152 | K64: 281.76 | L64: 280.88 | M64: 280.88
A65: NORESTE | B65: =+C65&E65 -> D81610000248 | C65: D816 | D65: MX-CANTERA MONTERREY | E65: 10000248 | F65: Sub-base Triturado Caliza 1 1/2" a Finos | G65: =H65-I65 -> #N/A | H65: =VLOOKUP(E65,[2]Conciliacion!$H:$AC,22,0) -> #N/A | I65: 300.01894 | J65: =(L65*4%)+L65 -> 274.2896 | K65: 265.7 | L65: 263.74 | M65: 263.74
A66: NORESTE | B66: =+C66&E66 -> D81610148825 | C66: D816 | D66: MX-CANTERA MONTERREY | E66: 10148825 | F66: BALASTO PIEDRA CALIZA 2"-4" | G66: =H66-I66 -> #N/A | H66: =VLOOKUP(E66,[2]Conciliacion!$H:$AC,22,0) -> #N/A | I66: =VLOOKUP(B66,'[3]Hoja2 (2)'!$A:$E,5,0) -> #N/A | J66: =(L66*4%)+L66 -> 277.9816 | L66: 267.29
A67: NORESTE | B67: =+C67&E67 -> D81610148824 | C67: D816 | D67: MX-CANTERA MONTERREY | E67: 10148824 | F67: BALASTO PIEDRA CALIZA 4"-6" | G67: =H67-I67 -> #N/A | H67: =VLOOKUP(E67,[2]Conciliacion!$H:$AC,22,0) -> #N/A | I67: =VLOOKUP(B67,'[3]Hoja2 (2)'!$A:$E,5,0) -> #N/A | J67: =(L67*4%)+L67 -> 251.5552 | L67: 241.88
A68: NORESTE | B68: =+C68&E68 -> D81610001222 | C68: D816 | D68: MX-CANTERA MONTERREY | E68: 10001222 | F68: Mixto Grava 3/4 - Arena 4 | G68: =H68-I68 -> #N/A | H68: =VLOOKUP(E68,[2]Conciliacion!$H:$AC,22,0) -> #N/A | I68: 294.25 | J68: =(L68*4%)+L68 -> 292.1464 | K68: 281.91 | L68: 280.91
A69: NORESTE | B69: =+C69&E69 -> D81610001201 | C69: D816 | D69: MX-CANTERA MONTERREY | E69: 10001201 | F69: No Clasificado Triturado Caliza | G69: =H69-I69 -> #N/A | H69: =VLOOKUP(E69,[2]Conciliacion!$H:$AC,22,0) -> #N/A | I69: 279.1 | J69: =(L69*4%)+L69 -> 265.1688 | K69: 254.97 | L69: 254.97
A70: NORESTE | B70: =+C70&E70 -> D82410023108 | C70: D824 | D70: MX-CANTERA LEON | E70: 10023108 | F70: Base H Triturada Basalto 1 1/2" a Finos | G70: =H70-I70 -> #N/A | H70: =VLOOKUP(E70,[2]Conciliacion!$H:$AC,22,0) -> #N/A | I70: =VLOOKUP(B70,'[3]Hoja2 (2)'!$A:$E,5,0) -> #N/A | J70: =(L70*4%)+L70 -> 173.3472 | K70: 166.9 | L70: 166.68
A71: NORESTE | B71: =+C71&E71 -> D82410001077 | C71: D824 | D71: MX-CANTERA LEON | E71: 10001077 | F71: Crudo Basalto | G71: =H71-I71 -> #N/A | H71: =VLOOKUP(E71,[2]Conciliacion!$H:$AC,22,0) -> #N/A | I71: =VLOOKUP(B71,'[3]Hoja2 (2)'!$A:$E,5,0) -> #N/A | J71: =(L71*4%)+L71 -> 119.6 | L71: 115 | M71: 110
A72: NORESTE | B72: =+C72&E72 -> D82410191647 | C72: D824 | D72: MX-CANTERA LEON | E72: 10191647 | F72: BALASTO 6# A 3# | G72: =H72-I72 -> #N/A | H72: =VLOOKUP(E72,[2]Conciliacion!$H:$AC,22,0) -> #N/A | I72: =VLOOKUP(B72,'[3]Hoja2 (2)'!$A:$E,5,0) -> #N/A | J72: =(L72*4%)+L72 -> 145.1736 | K72: 138.8 | L72: 139.59 | M72: 139.58
A73: NORESTE | B73: =+C73&E73 -> D82410000289 | C73: D824 | D73: MX-CANTERA LEON | E73: 10000289 | F73: Desperdicio Triturado Basalto | G73: =H73-I73 -> #N/A | H73: =VLOOKUP(E73,[2]Conciliacion!$H:$AC,22,0) -> #N/A | I73: =VLOOKUP(B73,'[3]Hoja2 (2)'!$A:$E,5,0) -> #N/A | J73: =(L73*4%)+L73 -> 51.8856 | K73: 51.09 | L73: 49.89 | M73: 49.76
A74: NORESTE | B74: =+C74&E74 -> D86310038957 | C74: D863 | D74: MX-CANTERA TAMUIN | E74: 10038957 | F74: Arena Triturada Caliza Block | G74: =H74-I74 -> #N/A | H74: =VLOOKUP(E74,[2]Conciliacion!$H:$AC,22,0) -> #N/A | I74: 92 | J74: =(L74*4%)+L74 -> 0
A75: NORESTE | B75: =+C75&E75 -> D917 10258182 | C75: D917 | D75: CANTERA VALLES | E75: 10258182 | F75: SOBRETAMAÑO ROCA NATURAL DE 0.5 A 0.80TN | G75: =H75-I75 -> #N/A | H75: =VLOOKUP(E75,[2]Conciliacion!$H:$AC,22,0) -> #N/A | I75: =VLOOKUP(B75,'[3]Hoja2 (2)'!$A:$E,5,0) -> #N/A | J75: =(L75*4%)+L75 -> 0 | K75: 127.22
A76: NORESTE | B76: =+C76&E76 -> D917 10258183 | C76: D917 | D76: CANTERA VALLES | E76: 10258183 | F76: SOBRETAMAÑO ROCA NATURAL DE 0.8 A 1.2 TN | G76: =H76-I76 -> #N/A | H76: =VLOOKUP(E76,[2]Conciliacion!$H:$AC,22,0) -> #N/A | I76: =VLOOKUP(B76,'[3]Hoja2 (2)'!$A:$E,5,0) -> #N/A | J76: =(L76*4%)+L76 -> 0 | K76: 127.22 | P76: =(P15*4%) -> 7.912
A77: NORESTE | B77: =+C77&E77 -> D917 10258184 | C77: D917 | D77: CANTERA VALLES | E77: 10258184 | F77: SOBRETAMAÑO ROCA NATURAL DE 0.2 A 0.56TN | G77: =H77-I77 -> #N/A | H77: =VLOOKUP(E77,[2]Conciliacion!$H:$AC,22,0) -> #N/A | I77: =VLOOKUP(B77,'[3]Hoja2 (2)'!$A:$E,5,0) -> #N/A | J77: =(L77*4%)+L77 -> 0 | P77: =P15+P76 -> 205.712
A78: NORESTE | B78: =+C78&E78 -> D917 10258185 | C78: D917 | D78: CANTERA VALLES | E78: 10258185 | F78: SOBRETAMAÑO ROCA NATURAL DE 0.56 A 1TN | G78: =H78-I78 -> #N/A | H78: =VLOOKUP(E78,[2]Conciliacion!$H:$AC,22,0) -> #N/A | I78: =VLOOKUP(B78,'[3]Hoja2 (2)'!$A:$E,5,0) -> #N/A | J78: =(L78*4%)+L78 -> 0
A79: NORESTE | B79: =+C79&E79 -> D85210038943 | C79: D852 | D79: MX-CANTERA TORREON II | E79: 10038943 | F79: Arena Triturada Caliza Malla 4 | G79: =H79-I79 -> #N/A | H79: =VLOOKUP(E79,[2]Conciliacion!$H:$AC,22,0) -> #N/A | I79: 135.24 | J79: =(L79*4%)+L79 -> 0 | K79: 127.69
A80: NORESTE | B80: =+C80&E80 -> D85210152582 | C80: D852 | D80: MX-CANTERA TORREON II | E80: 10152582 | F80: ARENA 4BLOCK MEZCLA ESP | G80: =H80-I80 -> #N/A | H80: =VLOOKUP(E80,[2]Conciliacion!$H:$AC,22,0) -> #N/A | I80: =VLOOKUP(B80,'[3]Hoja2 (2)'!$A:$E,5,0) -> #N/A | J80: =(L80*4%)+L80 -> 0 | K80: 137.64
A81: SURESTE | B81: =+C81&E81 -> DU0710000579 | C81: DU07 | D81: MX-CANCÚN III | E81: 10000579 | F81: Grava Triturada Caliza 40 mm - | G81: =H81-I81 -> #N/A | H81: =VLOOKUP(E81,[2]Conciliacion!$H:$AC,22,0) -> #N/A | I81: =VLOOKUP(B81,'[3]Hoja2 (2)'!$A:$E,5,0) -> 227.11 | J81: =(L81*4%)+L81 -> 0
A82: CENTRO | B82: =+C82&E82 -> D87310000236 | C82: D873 | D82: MX-VIRTUAL VALLEJO | E82: 10000236 | F82: Grava Triturada Caliza 10 mm - 3/8" | G82: =H82-I82 -> #N/A | H82: =VLOOKUP(E82,[2]Conciliacion!$H:$AC,22,0) -> #N/A | I82: =VLOOKUP(B82,'[3]Hoja2 (2)'!$A:$E,5,0) -> 299.45 | J82: 299.45
A83: NORESTE | B83: =+C83&E83 -> D81610148825 | C83: D816 | D83: MX-CANTERA MONTERREY | E83: 10148825 | F83: BALASTO PIEDRA CALIZA 2"-4" | G83: =H83-I83 -> #N/A | H83: =VLOOKUP(E83,[2]Conciliacion!$H:$AC,22,0) -> #N/A | I83: =VLOOKUP(B83,'[3]Hoja2 (2)'!$A:$E,5,0) -> #N/A | J83: 270.78
A84: NORESTE | B84: =+C84&E84 -> D81610269042 | C84: D816 | D84: MX-CANTERA MONTERREY | E84: 10269042 | F84: NO CLASIFICADO BALASTO B9 | G84: =H84-I84 -> #N/A | H84: =VLOOKUP(E84,[2]Conciliacion!$H:$AC,22,0) -> #N/A | I84: 290.76
A85: SURESTE | B85: =+C85&E85 -> DU0710000149 | C85: DU07 | D85: MX-CANCÚN III | E85: 10000149 | F85: Grava Triturada Caliza 10 mm - 3/8" | G85: =H85-I85 -> #N/A | H85: =VLOOKUP(E85,[2]Conciliacion!$H:$AC,22,0) -> #N/A
A86: SURESTE | B86: =+C86&E86 -> DU0710000106 | C86: DU07 | D86: MX-CANCÚN III | E86: 10000106 | F86: Crudo Caliza | G86: =H86-I86 -> #N/A | H86: =VLOOKUP(E86,[2]Conciliacion!$H:$AC,22,0) -> #N/A | I86: 92

Sheet Hoja1
A1: No. Material | B1: Nombre Material | C1: Precio ponderado | E1: No. Material | G1: UO | H1: Cantera | I1: Material | J1: Material
A2: 10001170 | B2: =VLOOKUP(A2,P.Referencia!E:F,2,0) -> Arena Triturada Caliza Block | C2: #N/A | E2: 10001170 | G2: D864 | H2: MX-CANTERA CERRO JARDIN | I2: 10001073 | J2: Arena Triturada Caliza Malla 4
A3: 10001864 | B3: =VLOOKUP(A3,P.Referencia!E:F,2,0) -> #N/A | C3: #N/A | E3: 10001864 | G3: D864 | H3: MX-CANTERA CERRO JARDIN | I3: 10000236 | J3: Grava Triturada Caliza 10 mm - 3/8"
A4: 10000124 | B4: =VLOOKUP(A4,P.Referencia!E:F,2,0) -> Arena Triturada Caliza Malla 4 | C4: 273.5 | E4: 10000124 | G4: D864 | H4: MX-CANTERA CERRO JARDIN | I4: 10000269 | J4: Grava Triturada Caliza 13 mm - 1/2"
A5: 10000260 | B5: =VLOOKUP(A5,P.Referencia!E:F,2,0) -> Arena Triturada Caliza Malla 5 | C5: 308 | E5: 10000260 | G5: D864 | H5: MX-CANTERA CERRO JARDIN | I5: 10000240 | J5: Grava Triturada Caliza 20 mm - 3/4"
A6: 10000241 | B6: =VLOOKUP(A6,P.Referencia!E:F,2,0) -> Grava Triturada Caliza 20 mm - 3/4" | C6: 273.5 | E6: 10000241 | G6: D864 | H6: MX-CANTERA CERRO JARDIN | I6: 10001074 | J6: Grava Triturada Caliza 40 mm - 1 1/2"
A7: 10000237 | B7: =VLOOKUP(A7,P.Referencia!E:F,2,0) -> Grava Triturada Caliza 10 mm - 3/8" | C7: 270 | E7: 10000237 | G7: D861 | H7: MX-CANTERA QUERETARO | I7: 10000311 | J7: Arena Triturada Basalto Malla 4
A8: 10000262 | B8: =VLOOKUP(A8,P.Referencia!E:F,2,0) -> Base H Triturada Caliza 1 1/2" | C8: 274.7 | E8: 10000262 | G8: D861 | H8: MX-CANTERA QUERETARO | I8: 10000229 | J8: Grava Triturada Basalto 10 mm - 3/8"
A9: 10036488 | B9: =VLOOKUP(A9,P.Referencia!E:F,2,0) -> Base H Trit Caliza 3/4" a Fino | C9: 280.88 | E9: 10036488 | G9: D861 | H9: MX-CANTERA QUERETARO | I9: 10000231 | J9: Grava Triturada Basalto 20 mm - 3/4"
A10: 10000248 | B10: =VLOOKUP(A10,P.Referencia!E:F,2,0) -> Sub-base Triturado Caliza 1 1/2" a Finos | C10: 263.74 | E10: 10000248 | G10: D861 | H10: MX-CANTERA QUERETARO | I10: 10000233 | J10: Grava Triturada Basalto 40 mm - 1 1/2"
A11: 10001222 | B11: =VLOOKUP(A11,P.Referencia!E:F,2,0) -> Mixto Grava 3/4 - Arena 4 | C11: #N/A | E11: 10001222 | G11: D813 | H11: MX-CANTERA SAN VICENTE | I11: 10000255 | J11: Arena Triturada Andesita Malla 4
A12: 10001201 | B12: =VLOOKUP(A12,P.Referencia!E:F,2,0) -> No Clasificado Triturado Caliza | C12: #N/A | E12: 10001201 | G12: D813 | H12: MX-CANTERA SAN VICENTE | I12: 10002350 | J12: Grava Triturada Andesita 10mm-3/8"
A13: 10148825 | B13: =VLOOKUP(A13,P.Referencia!E:F,2,0) -> BALASTO PIEDRA CALIZA 2"-4" | C13: #N/A | E13: 10148825 | G13: D813 | H13: MX-CANTERA SAN VICENTE | I13: 10000253 | J13: Grava Triturada Andesita 20 mm - 3/4"
A14: 10148824 | B14: =VLOOKUP(A14,P.Referencia!E:F,2,0) -> BALASTO PIEDRA CALIZA 4"-6" | C14: #N/A | E14: 10148824 | G14: D873 | H14: MX-VIRTUAL VALLEJO | I14: 10001073 | J14: Arena Triturada Caliza Malla 4
G15: D873 | H15: MX-VIRTUAL VALLEJO | I15: 10000240 | J15: Grava Triturada Caliza 20 mm - 3/4"
G16: D824 | H16: MX-CANTERA LEON | I16: 10000234 | J16: Arena Triturada Basalto Malla 4
F17: =110+120 -> 230 | G17: D824 | H17: MX-CANTERA LEON | I17: 10000285 | J17: Grava Triturada Basalto 10 mm - 3/8"
F18: =F17/2 -> 115 | G18: D824 | H18: MX-CANTERA LEON | I18: 10000284 | J18: Grava Triturada Basalto 20 mm - 3/4"
G19: D824 | H19: MX-CANTERA LEON | I19: 10000287 | J19: Grava Triturada Basalto 40 mm - 1 1/2"
G20: D816 | H20: MX-CANTERA MONTERREY | I20: 10000124 | J20: Arena Triturada Caliza Malla 4
G21: D816 | H21: MX-CANTERA MONTERREY | I21: 10164169 | J21: ARENA TRITURADA CALIZA MALLA 4 B47 FILIA
G22: D816 | H22: MX-CANTERA MONTERREY | I22: 10000260 | J22: Arena Triturada Caliza Malla 5
G23: D816 | H23: MX-CANTERA MONTERREY | I23: 10000237 | J23: Grava Triturada Caliza 10 mm - 3/8"
G24: D816 | H24: MX-CANTERA MONTERREY | I24: 10000241 | J24: Grava Triturada Caliza 20 mm - 3/4"
G25: D863 | H25: MX-CANTERA TAMUIN | I25: 10038952 | J25: Arena Triturada Caliza Malla 4
G26: D863 | H26: MX-CANTERA TAMUIN | I26: 10038949 | J26: Grava Triturada Caliza 10 mm - 3/8"
G27: D863 | H27: MX-CANTERA TAMUIN | I27: 10038950 | J27: Grava Triturada Caliza 20 mm - 3/4"
G28: D863 | H28: MX-CANTERA TAMUIN | I28: 10049672 | J28: Grava Triturada Caliza 40 mm - 1 1/2"
G29: D852 | H29: MX-CANTERA TORREON II | I29: 10038942 | J29: Arena Triturada Caliza Malla 8
G30: D852 | H30: MX-CANTERA TORREON II | I30: 10038947 | J30: Grava Triturada Caliza 10 mm - 3/8"
... G73: D863 | H73: MX-CANTERA TAMUIN | I73: 10038957 | J73: Arena Triturada Caliza Block
