Workbook

Sheet Base Cedis D825
N1: VENTA | Q1: COSTO
A2: CONCAT1 | B2: CONCAT2 | C2: No. SF | D2: Nombre SF | E2: Cedis | F2: Destino | G2: Condicion de Expedicion | H2: Nombre Destino | I2: No. de material | J2: Nombre de material | K2: PV | L2: Inicio de vigencia | M2: Fin de vigencia | N2: Importe MP | O2: Importe Flete | P2: UM Venta | Q2: Importe Costo | R2: UM Costo | S2: Validacion 1 | T2: Validacion 2
A3: =CONCATENATE(C3,E3,F3,I3) | B3: =CONCATENATE(C3,E3,I3) | C3: 900006668 | D3: =IFERROR(VLOOKUP(C3,TRAOPE!$G:$H,2,0),"") | E3: D825 | F3: 66356823 | G3: =IFERROR(VLOOKUP(A3,Flete!$A:$E,5,0),"") | H3: =IFERROR(VLOOKUP(F3,TRAOPE!$AA:$AB,2,0),"") | I3: 10211341 | J3: =IFERROR(VLOOKUP(I3,Materiales!$A:$H,8,0),"") | K3: =IFERROR(VLOOKUP(I3,Materiales!$A:$G,7,0),"") | L3: 20230628 | M3: 20240507 | N3: 367.5 | O3: =IFERROR(VLOOKUP(A3,Flete!$A:$J,10,0),"") | P3: M3 | Q3: =IFERROR(IFERROR(VLOOKUP(A3,TRAOPE!$A:$U,21,0),VLOOKUP(B3,TRAOPE!$A:$U,21,0)),"") | R3: =IFERROR(IFERROR(VLOOKUP(A3,TRAOPE!$A:$W,23,0),VLOOKUP(B3,TRAOPE!$A:$W,23,0)),"") | S3: =IF(AND(P3="TN",R3="TN"),N3+N(O3),IF(G3&""="1",N(K3)*N3,(N3+N(O3))*N(K3))) | T3: =IF(Q3="","",Q3-S3)
A4: =CONCATENATE(C4,E4,F4,I4) | B4: =CONCATENATE(C4,E4,I4) | C4: 900006668 | D4: =IFERROR(VLOOKUP(C4,TRAOPE!$G:$H,2,0),"") | E4: D825 | F4: 67093770 | G4: =IFERROR(VLOOKUP(A4,Flete!$A:$E,5,0),"") | H4: =IFERROR(VLOOKUP(F4,TRAOPE!$AA:$AB,2,0),"") | I4: 10179731 | J4: =IFERROR(VLOOKUP(I4,Materiales!$A:$H,8,0),"") | K4: =IFERROR(VLOOKUP(I4,Materiales!$A:$G,7,0),"") | L4: 20221031 | M4: 20240507 | N4: 195 | O4: =IFERROR(VLOOKUP(A4,Flete!$A:$J,10,0),"") | P4: M3 | Q4: =IFERROR(IFERROR(VLOOKUP(A4,TRAOPE!$A:$U,21,0),VLOOKUP(B4,TRAOPE!$A:$U,21,0)),"") | R4: =IFERROR(IFERROR(VLOOKUP(A4,TRAOPE!$A:$W,23,0),VLOOKUP(B4,TRAOPE!$A:$W,23,0)),"") | S4: =IF(AND(P4="TN",R4="TN"),N4+N(O4),IF(G4&""="1",N(K4)*N4,(N4+N(O4))*N(K4))) | T4: =IF(Q4="","",Q4-S4)
A5: =CONCATENATE(C5,E5,F5,I5) | B5: =CONCATENATE(C5,E5,I5) | C5: 900006668 | D5: =IFERROR(VLOOKUP(C5,TRAOPE!$G:$H,2,0),"") | E5: D825 | F5: 67093770 | G5: =IFERROR(VLOOKUP(A5,Flete!$A:$E,5,0),"") | H5: =IFERROR(VLOOKUP(F5,TRAOPE!$AA:$AB,2,0),"") | I5: 10211341 | J5: =IFERROR(VLOOKUP(I5,Materiales!$A:$H,8,0),"") | K5: =IFERROR(VLOOKUP(I5,Materiales!$A:$G,7,0),"") | L5: 20221031 | M5: 20240507 | N5: 335 | O5: =IFERROR(VLOOKUP(A5,Flete!$A:$J,10,0),"") | P5: M3 | Q5: =IFERROR(IFERROR(VLOOKUP(A5,TRAOPE!$A:$U,21,0),VLOOKUP(B5,TRAOPE!$A:$U,21,0)),"") | R5: =IFERROR(IFERROR(VLOOKUP(A5,TRAOPE!$A:$W,23,0),VLOOKUP(B5,TRAOPE!$A:$W,23,0)),"") | S5: =IF(AND(P5="TN",R5="TN"),N5+N(O5),IF(G5&""="1",N(K5)*N5,(N5+N(O5))*N(K5))) | T5: =IF(Q5="","",Q5-S5)
A6: =CONCATENATE(C6,E6,F6,I6) | B6: =CONCATENATE(C6,E6,I6) | C6: 900007749 | D6: =IFERROR(VLOOKUP(C6,TRAOPE!$G:$H,2,0),"") | E6: D825 | F6: 67122724 | G6: =IFERROR(VLOOKUP(A6,Flete!$A:$E,5,0),"") | H6: =IFERROR(VLOOKUP(F6,TRAOPE!$AA:$AB,2,0),"") | I6: 10210657 | J6: =IFERROR(VLOOKUP(I6,Materiales!$A:$H,8,0),"") | K6: =IFERROR(VLOOKUP(I6,Materiales!$A:$G,7,0),"") | L6: 20221027 | M6: 20240507 | N6: 365 | O6: =IFERROR(VLOOKUP(A6,Flete!$A:$J,10,0),"") | P6: M3 | Q6: =IFERROR(IFERROR(VLOOKUP(A6,TRAOPE!$A:$U,21,0),VLOOKUP(B6,TRAOPE!$A:$U,21,0)),"") | R6: =IFERROR(IFERROR(VLOOKUP(A6,TRAOPE!$A:$W,23,0),VLOOKUP(B6,TRAOPE!$A:$W,23,0)),"") | S6: =IF(AND(P6="TN",R6="TN"),N6+N(O6),IF(G6&""="1",N(K6)*N6,(N6+N(O6))*N(K6))) | T6: =IF(Q6="","",Q6-S6)
A7: =CONCATENATE(C7,E7,F7,I7) | B7: =CONCATENATE(C7,E7,I7) | C7: 900000651 | D7: =IFERROR(VLOOKUP(C7,TRAOPE!$G:$H,2,0),"") | E7: D825 | F7: 66948640 | G7: =IFERROR(VLOOKUP(A7,Flete!$A:$E,5,0),"") | H7: =IFERROR(VLOOKUP(F7,TRAOPE!$AA:$AB,2,0),"") | I7: 10052400 | J7: =IFERROR(VLOOKUP(I7,Materiales!$A:$H,8,0),"") | K7: =IFERROR(VLOOKUP(I7,Materiales!$A:$G,7,0),"") | L7: 20221109 | M7: 20251031 | N7: 296.53 | O7: =IFERROR(VLOOKUP(A7,Flete!$A:$J,10,0),"") | P7: TN | Q7: =IFERROR(IFERROR(VLOOKUP(A7,TRAOPE!$A:$U,21,0),VLOOKUP(B7,TRAOPE!$A:$U,21,0)),"") | R7: =IFERROR(IFERROR(VLOOKUP(A7,TRAOPE!$A:$W,23,0),VLOOKUP(B7,TRAOPE!$A:$W,23,0)),"") | S7: =IF(AND(P7="TN",R7="TN"),N7+N(O7),IF(G7&""="1",N(K7)*N7,(N7+N(O7))*N(K7))) | T7: =IF(Q7="","",Q7-S7)
A8: =CONCATENATE(C8,E8,F8,I8) | B8: =CONCATENATE(C8,E8,I8) | C8: 900000651 | D8: =IFERROR(VLOOKUP(C8,TRAOPE!$G:$H,2,0),"") | E8: D825 | F8: 67089986 | G8: =IFERROR(VLOOKUP(A8,Flete!$A:$E,5,0),"") | H8: =IFERROR(VLOOKUP(F8,TRAOPE!$AA:$AB,2,0),"") | I8: 10001078 | J8: =IFERROR(VLOOKUP(I8,Materiales!$A:$H,8,0),"") | K8: =IFERROR(VLOOKUP(I8,Materiales!$A:$G,7,0),"") | L8: 20221109 | M8: 20251031 | N8: 60 | O8: =IFERROR(VLOOKUP(A8,Flete!$A:$J,10,0),"") | P8: M3 | Q8: =IFERROR(IFERROR(VLOOKUP(A8,TRAOPE!$A:$U,21,0),VLOOKUP(B8,TRAOPE!$A:$U,21,0)),"") | R8: =IFERROR(IFERROR(VLOOKUP(A8,TRAOPE!$A:$W,23,0),VLOOKUP(B8,TRAOPE!$A:$W,23,0)),"") | S8: =IF(AND(P8="TN",R8="TN"),N8+N(O8),IF(G8&""="1",N(K8)*N8,(N8+N(O8))*N(K8))) | T8: =IF(Q8="","",Q8-S8)
A9: =CONCATENATE(C9,E9,F9,I9) | B9: =CONCATENATE(C9,E9,I9) | C9: 900004527 | D9: =IFERROR(VLOOKUP(C9,TRAOPE!$G:$H,2,0),"") | E9: D825 | F9: 66273342 | G9: =IFERROR(VLOOKUP(A9,Flete!$A:$E,5,0),"") | H9: =IFERROR(VLOOKUP(F9,TRAOPE!$AA:$AB,2,0),"") | I9: 10125120 | J9: =IFERROR(VLOOKUP(I9,Materiales!$A:$H,8,0),"") | K9: =IFERROR(VLOOKUP(I9,Materiales!$A:$G,7,0),"") | L9: 20221109 | M9: 20251031 | N9: 265 | O9: =IFERROR(VLOOKUP(A9,Flete!$A:$J,10,0),"") | P9: M3 | Q9: =IFERROR(IFERROR(VLOOKUP(A9,TRAOPE!$A:$U,21,0),VLOOKUP(B9,TRAOPE!$A:$U,21,0)),"") | R9: =IFERROR(IFERROR(VLOOKUP(A9,TRAOPE!$A:$W,23,0),VLOOKUP(B9,TRAOPE!$A:$W,23,0)),"") | S9: =IF(AND(P9="TN",R9="TN"),N9+N(O9),IF(G9&""="1",N(K9)*N9,(N9+N(O9))*N(K9))) | T9: =IF(Q9="","",Q9-S9)
A10: =CONCATENATE(C10,E10,F10,I10) | B10: =CONCATENATE(C10,E10,I10) | C10: 900004527 | D10: =IFERROR(VLOOKUP(C10,TRAOPE!$G:$H,2,0),"") | E10: D825 | F10: 66650126 | G10: =IFERROR(VLOOKUP(A10,Flete!$A:$E,5,0),"") | H10: =IFERROR(VLOOKUP(F10,TRAOPE!$AA:$AB,2,0),"") | I10: 10125120 | J10: =IFERROR(VLOOKUP(I10,Materiales!$A:$H,8,0),"") | K10: =IFERROR(VLOOKUP(I10,Materiales!$A:$G,7,0),"") | L10: 20221109 | M10: 20251031 | N10: 180.87 | O10: =IFERROR(VLOOKUP(A10,Flete!$A:$J,10,0),"") | P10: TN | Q10: =IFERROR(IFERROR(VLOOKUP(A10,TRAOPE!$A:$U,21,0),VLOOKUP(B10,TRAOPE!$A:$U,21,0)),"") | R10: =IFERROR(IFERROR(VLOOKUP(A10,TRAOPE!$A:$W,23,0),VLOOKUP(B10,TRAOPE!$A:$W,23,0)),"") | S10: =IF(AND(P10="TN",R10="TN"),N10+N(O10),IF(G10&""="1",N(K10)*N10,(N10+N(O10))*N(K10))) | T10: =IF(Q10="","",Q10-S10)
A11: =CONCATENATE(C11,E11,F11,I11) | B11: =CONCATENATE(C11,E11,I11) | C11: 900004527 | D11: =IFERROR(VLOOKUP(C11,TRAOPE!$G:$H,2,0),"") | E11: D825 | F11: 66650126 | G11: =IFERROR(VLOOKUP(A11,Flete!$A:$E,5,0),"") | H11: =IFERROR(VLOOKUP(F11,TRAOPE!$AA:$AB,2,0),"") | I11: 10137462 | J11: =IFERROR(VLOOKUP(I11,Materiales!$A:$H,8,0),"") | K11: =IFERROR(VLOOKUP(I11,Materiales!$A:$G,7,0),"") | L11: 20221109 | M11: 20251031 | N11: 236.46 | O11: =IFERROR(VLOOKUP(A11,Flete!$A:$J,10,0),"") | P11: TN | Q11: =IFERROR(IFERROR(VLOOKUP(A11,TRAOPE!$A:$U,21,0),VLOOKUP(B11,TRAOPE!$A:$U,21,0)),"") | R11: =IFERROR(IFERROR(VLOOKUP(A11,TRAOPE!$A:$W,23,0),VLOOKUP(B11,TRAOPE!$A:$W,23,0)),"") | S11: =IF(AND(P11="TN",R11="TN"),N11+N(O11),IF(G11&""="1",N(K11)*N11,(N11+N(O11))*N(K11))) | T11: =IF(Q11="","",Q11-S11)
A12: =CONCATENATE(C12,E12,F12,I12) | B12: =CONCATENATE(C12,E12,I12) | C12: 900004527 | D12: =IFERROR(VLOOKUP(C12,TRAOPE!$G:$H,2,0),"") | E12: D825 | F12: 66650242 | G12: =IFERROR(VLOOKUP(A12,Flete!$A:$E,5,0),"") | H12: =IFERROR(VLOOKUP(F12,TRAOPE!$AA:$AB,2,0),"") | I12: 10137462 | J12: =IFERROR(VLOOKUP(I12,Materiales!$A:$H,8,0),"") | K12: =IFERROR(VLOOKUP(I12,Materiales!$A:$G,7,0),"") | L12: 20221109 | M12: 20251031 | N12: 323.95 | O12: =IFERROR(VLOOKUP(A12,Flete!$A:$J,10,0),"") | P12: M3 | Q12: =IFERROR(IFERROR(VLOOKUP(A12,TRAOPE!$A:$U,21,0),VLOOKUP(B12,TRAOPE!$A:$U,21,0)),"") | R12: =IFERROR(IFERROR(VLOOKUP(A12,TRAOPE!$A:$W,23,0),VLOOKUP(B12,TRAOPE!$A:$W,23,0)),"") | S12: =IF(AND(P12="TN",R12="TN"),N12+N(O12),IF(G12&""="1",N(K12)*N12,(N12+N(O12))*N(K12))) | T12: =IF(Q12="","",Q12-S12)
A13: =CONCATENATE(C13,E13,F13,I13) | B13: =CONCATENATE(C13,E13,I13) | C13: 900004527 | D13: =IFERROR(VLOOKUP(C13,TRAOPE!$G:$H,2,0),"") | E13: D825 | F13: 66650326 | G13: =IFERROR(VLOOKUP(A13,Flete!$A:$E,5,0),"") | H13: =IFERROR(VLOOKUP(F13,TRAOPE!$AA:$AB,2,0),"") | I13: 10137462 | J13: =IFERROR(VLOOKUP(I13,Materiales!$A:$H,8,0),"") | K13: =IFERROR(VLOOKUP(I13,Materiales!$A:$G,7,0),"") | L13: 20221109 | M13: 20251031 | N13: 324.25 | O13: =IFERROR(VLOOKUP(A13,Flete!$A:$J,10,0),"") | P13: M3 | Q13: =IFERROR(IFERROR(VLOOKUP(A13,TRAOPE!$A:$U,21,0),VLOOKUP(B13,TRAOPE!$A:$U,21,0)),"") | R13: =IFERROR(IFERROR(VLOOKUP(A13,TRAOPE!$A:$W,23,0),VLOOKUP(B13,TRAOPE!$A:$W,23,0)),"") | S13: =IF(AND(P13="TN",R13="TN"),N13+N(O13),IF(G13&""="1",N(K13)*N13,(N13+N(O13))*N(K13))) | T13: =IF(Q13="","",Q13-S13)
A14: =CONCATENATE(C14,E14,F14,I14) | B14: =CONCATENATE(C14,E14,I14) | C14: 900004527 | D14: =IFERROR(VLOOKUP(C14,TRAOPE!$G:$H,2,0),"") | E14: D825 | F14: 66650366 | G14: =IFERROR(VLOOKUP(A14,Flete!$A:$E,5,0),"") | H14: =IFERROR(VLOOKUP(F14,TRAOPE!$AA:$AB,2,0),"") | I14: 10165992 | J14: =IFERROR(VLOOKUP(I14,Materiales!$A:$H,8,0),"") | K14: =IFERROR(VLOOKUP(I14,Materiales!$A:$G,7,0),"") | L14: 20221109 | M14: 20251031 | N14: 259.99 | O14: =IFERROR(VLOOKUP(A14,Flete!$A:$J,10,0),"") | P14: M3 | Q14: =IFERROR(IFERROR(VLOOKUP(A14,TRAOPE!$A:$U,21,0),VLOOKUP(B14,TRAOPE!$A:$U,21,0)),"") | R14: =IFERROR(IFERROR(VLOOKUP(A14,TRAOPE!$A:$W,23,0),VLOOKUP(B14,TRAOPE!$A:$W,23,0)),"") | S14: =IF(AND(P14="TN",R14="TN"),N14+N(O14),IF(G14&""="1",N(K14)*N14,(N14+N(O14))*N(K14))) | T14: =IF(Q14="","",Q14-S14)
... A398: =CONCATENATE(C398,E398,F398,I398) | B398: =CONCATENATE(C398,E398,I398) | C398: 900007937 | D398: =IFERROR(VLOOKUP(C398,TRAOPE!$G:$H,2,0),"") | E398: D825 | F398: 67076920 | G398: =IFERROR(VLOOKUP(A398,Flete!$A:$E,5,0),"") | H398: =IFERROR(VLOOKUP(F398,TRAOPE!$AA:$AB,2,0),"") | I398: 10211341 | J398: =IFERROR(VLOOKUP(I398,Materiales!$A:$H,8,0),"") | K398: =IFERROR(VLOOKUP(I398,Materiales!$A:$G,7,0),"") | L398: 20220708 | M398: 20251031 | N398: 442 | O398: =IFERROR(VLOOKUP(A398,Flete!$A:$J,10,0),"") | P398: M3 | Q398: =IFERROR(IFERROR(VLOOKUP(A398,TRAOPE!$A:$U,21,0),VLOOKUP(B398,TRAOPE!$A:$U,21,0)),"") | R398: =IFERROR(IFERROR(VLOOKUP(A398,TRAOPE!$A:$W,23,0),VLOOKUP(B398,TRAOPE!$A:$W,23,0)),"") | S398: =IF(AND(P398="TN",R398="TN"),N398+N(O398),IF(G398&""="1",N(K398)*N398,(N398+N(O398))*N(K398))) | T398: =IF(Q398="","",Q398-S398)

Sheet MP
A1: No. SF | B1: Cedis | C1: Destino | D1: No. Material | E1: Nombre Material | F1: Importe MP | G1: Moneda | H1: Cantidad | I1: UM | J1: C | K1: Inicio Vigencia | L1: Fin Vigencia
A2: 900006668 | B2: D825 | C2: 66356823 | D2: 10211341 | F2: 367.5 | I2: M3 | K2: 20230628 | L2: 20240507
A3: 900006668 | B3: D825 | C3: 67093770 | D3: 10179731 | F3: 195 | I3: M3 | K3: 20221031 | L3: 20240507
A4: 900006668 | B4: D825 | C4: 67093770 | D4: 10211341 | F4: 335 | I4: M3 | K4: 20221031 | L4: 20240507
A5: 900007749 | B5: D825 | C5: 67122724 | D5: 10210657 | F5: 365 | I5: M3 | K5: 20221027 | L5: 20240507
A6: 900000651 | B6: D825 | C6: 66948640 | D6: 10052400 | F6: 296.53 | I6: TN | K6: 20221109 | L6: 20251031
A7: 900000651 | B7: D825 | C7: 67089986 | D7: 10001078 | F7: 60 | I7: M3 | K7: 20221109 | L7: 20251031
A8: 900004527 | B8: D825 | C8: 66273342 | D8: 10125120 | F8: 265 | I8: M3 | K8: 20221109 | L8: 20251031
A9: 900004527 | B9: D825 | C9: 66650126 | D9: 10125120 | F9: 180.87 | I9: TN | K9: 20221109 | L9: 20251031
A10: 900004527 | B10: D825 | C10: 66650126 | D10: 10137462 | F10: 236.46 | I10: TN | K10: 20221109 | L10: 20251031
A11: 900004527 | B11: D825 | C11: 66650242 | D11: 10137462 | F11: 323.95 | I11: M3 | K11: 20221109 | L11: 20251031
A12: 900004527 | B12: D825 | C12: 66650326 | D12: 10137462 | F12: 324.25 | I12: M3 | K12: 20221109 | L12: 20251031
A13: 900004527 | B13: D825 | C13: 66650366 | D13: 10165992 | F13: 259.99 | I13: M3 | K13: 20221109 | L13: 20251031
... A397: 900007937 | B397: D825 | C397: 67076920 | D397: 10211341 | F397: 442 | I397: M3 | K397: 20220708 | L397: 20251031

Sheet Flete
A1: Concat1 | B1: No. SF | C1: Cedis | D1: Destino | E1: Cond. Exp. | F1: Material | H1: Nombre Material | J1: Importe Flete | K1: Moneda | L1: Cantidad | M1: UM | N1: C | P1: Inicio Vigencia | Q1: Fin Vigencia
A2: 900001046D8256534030010000354 | B2: 900001046 | C2: D825 | D2: 65340300 | E2: 1 | F2: 10000354 | J2: 37.24 | M2: TN | P2: 20150101 | Q2: 99991231
A3: 900001046D8256534030110000354 | B3: 900001046 | C3: D825 | D3: 65340301 | E3: 1 | F3: 10000354 | J3: 13.79 | M3: TN | P3: 20150101 | Q3: 99991231
A4: 900001046D8256540828310000354 | B4: 900001046 | C4: D825 | D4: 65408283 | E4: 1 | F4: 10000354 | J4: 51.73 | M4: M3 | P4: 20150101 | Q4: 99991231
A5: 900001046D8256596943810000354 | B5: 900001046 | C5: D825 | D5: 65969438 | E5: 1 | F5: 10000354 | J5: 45 | M5: M3 | P5: 20150301 | Q5: 99991231
A6: 900004527D8256538137810110794 | B6: 900004527 | C6: D825 | D6: 65381378 | E6: 1 | F6: 10110794 | J6: 90.09 | M6: M3 | P6: 20170210 | Q6: 99991231
A7: 900004527D8256665012610125120 | B7: 900004527 | C7: D825 | D7: 66650126 | E7: 1 | F7: 10125120 | J7: 53.3 | M7: TN | P7: 20210424 | Q7: 99991231
A8: 900004527D8256665012610137462 | B8: 900004527 | C8: D825 | D8: 66650126 | E8: 1 | F8: 10137462 | J8: 53.3 | M8: TN | P8: 20210424 | Q8: 99991231
A9: 900004527D8256665024210137462 | B9: 900004527 | C9: D825 | D9: 66650242 | E9: 1 | F9: 10137462 | J9: 98.01 | M9: M3 | P9: 20210424 | Q9: 99991231
A10: 900004527D8256665032610137462 | B10: 900004527 | C10: D825 | D10: 66650326 | E10: 1 | F10: 10137462 | J10: 52.39 | M10: M3 | P10: 20210424 | Q10: 99991231
A11: 900004527D8256665069610188311 | B11: 900004527 | C11: D825 | D11: 66650696 | E11: 1 | F11: 10188311 | J11: 66.17 | M11: M3 | P11: 20210424 | Q11: 99991231
A12: 900004527D8256665524310110794 | B12: 900004527 | C12: D825 | D12: 66655243 | E12: 1 | F12: 10110794 | J12: 36.26 | M12: M3 | P12: 20210424 | Q12: 99991231
A13: 900004527D8256665524310137462 | B13: 900004527 | C13: D825 | D13: 66655243 | E13: 1 | F13: 10137462 | J13: 42.32 | M13: M3 | P13: 20210424 | Q13: 99991231
... A181: 900007936D8256722980710139747 | B181: 900007936 | C181: D825 | D181: 67229807 | E181: 1 | F181: 10139747 | J181: 419.62 | M181: M3 | P181: 20240423 | Q181: 99991231

Sheet Materiales
A1: Material | B1: TpMt | C1: Denom | D1: UMA | E1: Contador | F1: UMB | G1: PV | H1: Nombre Material
A2: 10000001 | B2: ZFER | C2: 1000 | D2: M3 | E2: 1000 | F2: TN | G2: 1262 | H2: GRAVA ANDESITA 10 MM (3/8")
A3: 10000003 | B3: ZFER | C3: 1000 | D3: M3 | E3: 1000 | F3: TN | G3: 1443 | H3: GRAVA CALIZA 10 MM (3/8")
A4: 10000006 | B4: ZFER | C4: 1000 | D4: M3 | E4: 1000 | F4: TN | G4: 1490 | H4: GRAVA RIO 10 MM (3/8")
A5: 10000007 | B5: ZFER | C5: 1000 | D5: M3 | E5: 1000 | F5: TN | G5: 1488 | H5: GRAVA BASALTO 13 MM (1/2")
A6: 10000008 | B6: ZFER | C6: 1000 | D6: M3 | E6: 1000 | F6: TN | G6: 1358 | H6: GRAVA CALIZA 13 MM (1/2")
A7: 10000011 | B7: ZFER | C7: 1000 | D7: M3 | E7: 1000 | F7: TN | G7: 1323 | H7: GRAVA ANDESITA 20 MM (3/4")
A8: 10000013 | B8: ZFER | C8: 1000 | D8: M3 | E8: 1000 | F8: TN | G8: 1514 | H8: GRAVA BASALTO 20 MM (3/4")
A9: 10000014 | B9: ZFER | C9: 1000 | D9: M3 | E9: 1000 | F9: TN | G9: 1400 | H9: GRAVA CALIZA 20 MM (3/4")
A10: 10000015 | B10: ZFER | C10: 1000 | D10: M3 | E10: 1000 | F10: TN | G10: 1410 | H10: GRAVA GRANITO 20 MM (3/4")
A11: 10000017 | B11: ZFER | C11: 1000 | D11: M3 | E11: 1000 | F11: TN | G11: 1475 | H11: GRAVA RIOLITA 20 MM (3/4")
A12: 10000019 | B12: ZFER | C12: 1000 | D12: M3 | E12: 1000 | F12: TN | G12: 1515 | H12: GRAVA RIO 20 MM (3/4")
A13: 10000020 | B13: ZFER | C13: 1000 | D13: M3 | E13: 1 | F13: TN | G13: 1 | H13: GRAVA MAQUILA 40MM (1 1/2")
... A2291: 10268770 | B2291: ZFE3 | C2291: 1000 | D2291: M3 | E2291: 1000 | F2291: TN | G2291: 1240 | H2291: MP GRAVA TRIT CALIZA 40MM 1 1/2" - ESP
A2292: 10268901 | B2292: ZFE3 | C2292: 1000 | D2292: M3 | E2292: 1000 | G2292: 1560 | H2292: MP GRAVA ANDESITA GRIS 3/4" - CAPADA
A2293: 10267983 | C2293: 1000 | G2293: 1800 | H2293: ESCORIA ALTO HORNO 3/4
A2294: 10268996 | C2294: 1000 | G2294: 1329 | H2294: GRAVA TRITURADA CALIZA 40 MM - 11/2"
A2295: 10269072 | C2295: 1000 | G2295: 1700 | H2295: BASE HIDRÁULICA SCREEN
A2296: 10269225 | B2296: ZFE3 | C2296: 1000 | D2296: M3 | E2296: 1000 | G2296: 1289 | H2296: MP ARENA CALIZA LAVADA MALLA 4 - DELTA I
A2297: 10269245 | B2297: ZFE3 | C2297: 1000 | D2297: M3 | E2297: 1000 | G2297: 1410 | H2297: MP GRAVA TRITURADA CALIZA 3/8 - 10MM
A2298: 10269246 | B2298: ZFE3 | C2298: 1000 | D2298: M3 | E2298: 1000 | G2298: 1400 | H2298: MP GRAVA TRITURADA CALIZA 1 1/2 - 40MM
A2299: 10269247 | B2299: ZFE3 | C2299: 1000 | D2299: M3 | E2299: 1000 | G2299: 1560 | H2299: MP ARENA TRIT CALIZA M-4
A2300: 10270431 | B2300: ZFE3 | C2300: 1000 | D2300: M3 | E2300: 1000 | G2300: 1423 | H2300: MP GRAVA RIOLITA 13 MM - 1/2"
A2301: 10270898 | B2301: ZFE3 | C2301: 1000 | D2301: M3 | E2301: 1000 | G2301: 1551 | H2301: MP BASE H. TRIT. BASALTO 1 1/2" A FINOS
A2302: 10270911 | B2302: ZFE3 | C2302: 1000 | D2302: M3 | E2302: 1000 | G2302: 1360 | H2302: MP GRAVA TRIT. BASALTO 40 MM - 1 1/2"
A2303: 10270912 | B2303: ZFE3 | C2303: 1000 | D2303: M3 | E2303: 1000 | G2303: 1589 | H2303: MP ARENA TRIT. BASALTO MALLA 4
A2304: 10270913 | B2304: ZFE3 | C2304: 1000 | D2304: M3 | E2304: 1000 | G2304: 1395 | H2304: MP GRAVA TRIT. BASALTO 20 MM - 3/4
A2305: 10270914 | B2305: ZFE3 | C2305: 1000 | D2305: M3 | E2305: 1000 | G2305: 1623 | H2305: MP ARENA ANDESITA BC
A2306: 10270824 | B2306: M3 | C2306: 1000 | D2306: M3 | E2306: 10007640 | G2306: 1325 | H2306: MP ARENA TRITURADA CALIZA MALLA 5
A2307: 10270825 | B2307: M3 | C2307: 1000 | D2307: M3 | E2307: 10000003 | G2307: 1242 | H2307: MP GRAVA TRITURADA CALIZA 10MM (3/8”)
... A2319: 10272527 | B2319: ZFE3 | C2319: 1000 | D2319: M3 | E2319: 1000 | G2319: 1620 | H2319: CNC - NO CLASIFICADO
A2320: 10000332 | C2320: 1000 | D2320: M3 | E2320: 1000 | G2320: 800 | H2320: Grava Triturada Pomez - Jal 20 mm - 3/4"
A2321: 10273001 | B2321: ZFE3 | C2321: 1000 | D2321: M3 | E2321: 1000 | G2321: 1688 | H2321: MP ARENA TRIT. BASALTO MALLA 4
A2322: 10273002 | B2322: ZFE3 | C2322: 1000 | D2322: M3 | E2322: 1000 | G2322: 1466 | H2322: MP GRAVA TRIT. BASALTO 20 MM - 3/4"
A2323: 10273351 | B2323: ZFE3 | C2323: 1000 | D2323: M3 | E2323: 1000 | G2323: 1612 | H2323: MP ARENA TRIT. CALIZA MALLA 4
A2324: 10273352 | B2324: ZFE3 | C2324: 1000 | D2324: M3 | E2324: 1000 | G2324: 1492 | H2324: MP GRAVA TRIT. CALIZA 20 MM - 3/4"
A2325: 10271724 | B2325: ZFE3 | C2325: 1000 | D2325: M3 | E2325: 1000 | G2325: 1900 | H2325: MP RESIDUO DE CONCRETO
A2326: 10000677 | C2326: 1000 | D2326: M3 | G2326: 1164 | H2326: Grava Triturada Caliza 20 mm - 3/4"
A2327: 10274190 | B2327: ZFE3 | C2327: 1000 | D2327: M3 | E2327: 1000 | G2327: 1800 | H2327: MP BASE HIDRAULICA ANDESITA 70-30
A2328: 10274601 | B2328: ZFE3 | C2328: 1000 | D2328: M3 | E2328: 1000 | G2328: 1447 | H2328: MP ARENA BASALTO N° 4
A2329: 10274754 | B2329: ZFE3 | C2329: 1000 | D2329: M3 | E2329: 1000 | G2329: 1397 | H2329: MP GRAVA TRIT. ANDESITA 20 MM - 3/4"
A2330: 10169718 | B2330: ZFE3 | C2330: 1000 | D2330: M3 | E2330: 1000 | G2330: 1400 | H2330: GRAVA CLASIFICADA RÍO 40 MM - 1 1/2"
A2331: 10274813 | B2331: ZFE3 | C2331: 1000 | D2331: M3 | E2331: 1000 | G2331: 1448 | H2331: MP ARENA TRIT RÍO MALLA 4
A2332: 10274815 | B2332: ZFE3 | C2332: 1000 | D2332: M3 | E2332: 1000 | G2332: 1366 | H2332: MP ARENA CLASIFICADA RÍO MALLA 5
A2333: 10274816 | B2333: ZFE3 | C2333: 1000 | D2333: M3 | E2333: 1000 | G2333: 1472 | H2333: MP GRAVA CLASIF RÍO 20 MM - 3/4"
A2334: 10275113 | B2334: ZFE3 | C2334: 1000 | D2334: M3 | E2334: 1000 | G2334: 1409 | H2334: MP ARENA TRIT ANDESITA MALLA 4
A2335: 10275114 | B2335: ZFE3 | C2335: 1000 | D2335: M3 | E2335: 1000 | G2335: 1418 | H2335: MP ARENA CLASIF RIO MALLA 4 - LAVADO
A2336: 10275115 | B2336: ZFE3 | C2336: 1000 | D2336: M3 | E2336: 1000 | G2336: 1259 | H2336: MP ARENA TRIT ANDESITA MALLA 4
A2337: 10275116 | B2337: ZFE3 | C2337: 1000 | D2337: M3 | E2337: 1000 | G2337: 1401 | H2337: MP GRAVA TRIT ANDESITA 3/4 - 20 MM
A2338: 10275118 | B2338: ZFE3 | C2338: 1000 | D2338: M3 | E2338: 1000 | G2338: 1401 | H2338: MP ARENA TRIT ANDESITA MALLA 4
... A2361: 10280049 | B2361: ZFE3 | C2361: 1000 | D2361: M3 | E2361: 1000 | G2361: 1584 | H2361: MP B. HID CALIZA 40% FINOS Y 60% GRUESOS
A2362: 10280365 | C2362: 1000 | D2362: M3 | E2362: 1000 | G2362: 1274 | H2362: MP GRAVA BASALTO 20 MM -3/4
A2363: 10280538 | B2363: ZFE3 | C2363: 1000 | D2363: M3 | E2363: 1000 | G2363: 1262 | H2363: MP GRAVA TRIT BASALTO 3/8 - 10MM
A2364: 10280679 | B2364: ZFE3 | C2364: 1000 | D2364: M3 | E2364: 1000 | G2364: 1349 | H2364: MP GRAVA CLASIF RÍO 13MM - 1/2"
A2365: 10281171 | B2365: ZFE3 | C2365: 1000 | D2365: M3 | E2365: 1000 | G2365: 1271 | H2365: MP GRAVA TRIT CALIZA 10MM - 3/8"
A2366: 10281183 | B2366: ZFE3 | C2366: 1000 | D2366: M3 | E2366: 1000 | G2366: 1468 | H2366: MP ARENA TRIT CALIZA MALLA 4
A2367: 10281384 | B2367: ZFE3 | C2367: 1000 | D2367: M3 | E2367: 1000 | G2367: 1285 | H2367: MP GRAVA BASALTO 40 MM (1 1/2")
A2368: 10281379 | B2368: ZFE3 | C2368: 1000 | D2368: M3 | E2368: 1000 | G2368: 1536 | H2368: MP ARENA CLASIF. RÍO MALLA 4
A2369: 10281450 | B2369: ZFE3 | C2369: 1000 | D2369: M3 | E2369: 1000 | G2369: 1325 | H2369: MP GRAVA CLASIF. RIO 20MM - 3/4
A2370: 10281451 | B2370: ZFE3 | C2370: 1000 | D2370: M3 | E2370: 1000 | G2370: 1564 | H2370: MP ARENA CLASIF. RÍO MALLA 4
A2371: 10281452 | B2371: ZFE3 | C2371: 1000 | D2371: M3 | E2371: 1000 | G2371: 1427 | H2371: MP GRAVA CLASIF. RIO 20MM - 3/4

Sheet TRAOPE
A1: Concat1 | B1: Contrato_Pos | C1: Doc. Compras | D1: Pos | E1: Org.compras | F1: Grp-Compr. | G1: Ship From | H1: Nombre SF | I1: Proveedor | J1: Nombre Prov | K1: Cond. Pago | L1: Descr. Cond Pago | M1: Material | N1: Descripción | O1: Centro | P1: Descripción Centro | Q1: In.perído validez | R1: Fin perído validez | S1: Válido de | T1: Validez a | U1: Precio neto pedido | V1: Moneda | W1: UM Precio Pedido | X1: Importe Condición | Y1: Moneda KONP | Z1: UM Ctd Base | AA1: Destino | AB1: Nombre Destino | AC1: Cuenta de mayor | AD1: Centro de costo | AE1: Cond. Exp. | AF1: Descr. Cond. Exp. | AG1: Peso Vol. | AH1: UMB | AI1: Ind. Oblig. Conf. Ped. | AJ1: Ctrl-Conf. | AK1: IVA | AL1: Modif_Date | AM1: Ruta
A2: 900007935D8256665022910139747 | B2: 4600057825-150 | C2: 4600057825 | D2: 150 | E2: MXPO | F2: MXL | G2: 900007935 | H2: SF TP-ED LUGA-OLGUIN | I2: 5087532 | J2: LUGA AUTO TRANSPORTES SA DE CV | K2: N90 | L2: (AP) NAFIN 90 Dias | M2: 10139747 | N2: ARENA CLASIFICADA RIO MALLA 4 | O2: D825 | P2: MX-CED. GOLFO DE CALIFORNIA | Q2: 20230619 | R2: 20291231 | S2: 20260813 | T2: 20301231 | U2: 345 | V2: MXN | W2: M3 | X2: 139 | Y2: MXN | Z2: M3 | AA2: 66650229 | AB2: I8 OBR-AGR UNICONCRETOS SA DE CV | AC2: 56103638 | AD2: 6622151540 | AE2: 4 | AF2: ENTREGA DIRECTA | AG2: 1.45 | AH2: M3 | AI2: X | AJ2: 4 | AK2: V4 | AL2: 20260817 | AM2: D825-900007935-66650229-10139747-4
A3: 900007935D8256722980710139747 | B3: 4600057825-50 | C3: 4600057825 | D3: 50 | E3: MXPO | F3: MXL | G3: 900007935 | H3: SF TP-ED LUGA-OLGUIN | I3: 5087532 | J3: LUGA AUTO TRANSPORTES SA DE CV | K3: N90 | L3: (AP) NAFIN 90 Dias | M3: 10139747 | N3: ARENA CLASIFICADA RIO MALLA 4 | O3: D825 | P3: MX-CED. GOLFO DE CALIFORNIA | Q3: 20230619 | R3: 20291231 | S3: 20240529 | T3: 20291231 | U3: 406 | V3: MXN | W3: M3 | X3: 200 | Y3: MXN | Z3: M3 | AA3: 67229807 | AB3: DC CONCRETOS CAÑON DEL MATADERO | AC3: 56103638 | AD3: 6622151540 | AE3: 4 | AF3: ENTREGA DIRECTA | AG3: 1.45 | AH3: M3 | AI3: X | AJ3: 4 | AK3: V4 | AL3: 20250402 | AM3: D825-900007935-67229807-10139747-4
A4: 900006891D8256665012610139747 | B4: 4600048585-30 | C4: 4600048585 | D4: 30 | E4: MXPO | F4: MXL | G4: 900006891 | H4: SF TP-ED-TRAZO | I4: 5078812 | J4: TRAZO DEL NORESTE SRL DE CV | K4: N90 | L4: (AP) NAFIN 90 Dias | M4: 10139747 | N4: ARENA CLASIFICADA RIO MALLA 4 | O4: D825 | P4: MX-CED. GOLFO DE CALIFORNIA | Q4: 20201203 | R4: 20291231 | S4: 20210415 | T4: 20251231 | U4: 250 | V4: MXN | W4: M3 | X4: 135 | Y4: MXN | Z4: M3 | AA4: 66650126 | AB4: I8 CONCRETOS T Y G SA DE CV | AC4: 56103638 | AD4: 6622151540 | AE4: 4 | AF4: ENTREGA DIRECTA | AG4: 1.45 | AH4: M3 | AI4: X | AJ4: 4 | AK4: V4 | AL4: 20230920 | AM4: D825-900006891-66650126-10139747-4
A5: 900007935D8256715474310024382 | B5: 4600057825-10 | C5: 4600057825 | D5: 10 | E5: MXPO | F5: MXL | G5: 900007935 | H5: SF TP-ED LUGA-OLGUIN | I5: 5087532 | J5: LUGA AUTO TRANSPORTES SA DE CV | K5: N90 | L5: (AP) NAFIN 90 Dias | M5: 10024382 | N5: Grava Triturada Basalto 20 mm - 3/4" | O5: D825 | P5: MX-CED. GOLFO DE CALIFORNIA | Q5: 20230619 | R5: 20291231 | S5: 20230619 | T5: 20281231 | U5: 360 | V5: MXN | W5: M3 | X5: 130 | Y5: MXN | Z5: M3 | AA5: 67154743 | AB5: Terraplen Proyecto Estrella (dg) | AC5: 56103637 | AD5: 6622151867 | AE5: 4 | AF5: ENTREGA DIRECTA | AG5: 1.457 | AH5: M3 | AI5: X | AJ5: 4 | AK5: V4 | AL5: 20250402 | AM5: D825-900007935-67154743-10024382-4
A6: 900007775D82510217514 | B6: 4600055301-10 | C6: 4600055301 | D6: 10 | E6: MXPO | F6: MXL | G6: 900007775 | H6: SF TP- VTA CRUZADA CEBREROS | I6: 5083830 | J6: CEBRERO AMADOR CHRISTIAN ARIEL | K6: Z09 | L6: (AP) 90 Dias | M6: 10217514 | N6: ECOBASE | O6: D825 | P6: MX-CED. GOLFO DE CALIFORNIA | Q6: 20220926 | R6: 20271231 | S6: 20260512 | T6: 20301231 | U6: 60 | V6: MXN | W6: M3 | X6: 0 | Y6: MXN | Z6: M3 | AC6: 56103590 | AD6: 6622151540 | AE6: 1 | AF6: ENTREGADO | AG6: 1.5 | AH6: M3 | AI6: X | AJ6: 4 | AK6: V4 | AL6: 20260518 | AM6: D825-900007775-10217514
A7: 900006667D8256665032610275058 | B7: 4600069592-180 | C7: 4600069592 | D7: 180 | E7: MXPO | F7: MXL | G7: 900006667 | H7: SF TP-ED TRITURADOS ROCA | I7: 5078620 | J7: TRITURADOS ROCA DE BC SA DE CV | K7: N90 | L7: (AP) NAFIN 90 Dias | M7: 10275058 | N7: MP GRAVA TRIT. BASALTO 40-4MM - 1 1/2" | O7: D825 | P7: MX-CED. GOLFO DE CALIFORNIA | Q7: 20240527 | R7: 20291231 | S7: 20260611 | T7: 20301231 | U7: 286 | V7: MXN | W7: TN | X7: 68 | Y7: MXN | Z7: TN | AA7: 66650326 | AB7: I8 FRACC. PUERTA PLATA | AC7: 56103637 | AD7: 6622151540 | AE7: 4 | AF7: ENTREGA DIRECTA | AG7: 1 | AH7: TO | AI7: X | AJ7: 4 | AK7: V1 | AL7: 20260615 | AM7: D825-900006667-66650326-10275058-4
A8: 900007936D82510139747 | B8: 4600069433-10 | C8: 4600069433 | D8: 10 | E8: MXPO | F8: MXL | G8: 900007936 | H8: SF TP-LUGA-OLGUIN | I8: 5087532 | J8: LUGA AUTO TRANSPORTES SA DE CV | K8: N90 | L8: (AP) NAFIN 90 Dias | M8: 10139747 | N8: ARENA CLASIFICADA RIO MALLA 4 | O8: D825 | P8: MX-CED. GOLFO DE CALIFORNIA | Q8: 20240423 | R8: 20291231 | S8: 20240423 | T8: 20291231 | U8: 206 | V8: MXN | W8: M3 | X8: 0 | Y8: MXN | Z8: M3 | AC8: 56103638 | AD8: 6622151540 | AE8: 1 | AF8: ENTREGADO | AG8: 1.45 | AH8: M3 | AI8: X | AJ8: 4 | AK8: V4 | AL8: 20250402 | AM8: D825-900007936-10139747
A9: 900007935D8256723172410139747 | B9: 4600057825-70 | C9: 4600057825 | D9: 70 | E9: MXPO | F9: MXL | G9: 900007935 | H9: SF TP-ED LUGA-OLGUIN | I9: 5087532 | J9: LUGA AUTO TRANSPORTES SA DE CV | K9: N90 | L9: (AP) NAFIN 90 Dias | M9: 10139747 | N9: ARENA CLASIFICADA RIO MALLA 4 | O9: D825 | P9: MX-CED. GOLFO DE CALIFORNIA | Q9: 20230619 | R9: 20291231 | S9: 20240423 | T9: 20291231 | U9: 421 | V9: MXN | W9: M3 | X9: 215 | Y9: MXN | Z9: M3 | AA9: 67231724 | AB9: COMSA CAÑON DEL MATADERO | AC9: 56103638 | AD9: 6622151540 | AE9: 4 | AF9: ENTREGA DIRECTA | AG9: 1.45 | AH9: M3 | AI9: X | AJ9: 4 | AK9: V4 | AL9: 20250402 | AM9: D825-900007935-67231724-10139747-4
A10: 900007935D8256723163310139747 | B10: 4600057825-60 | C10: 4600057825 | D10: 60 | E10: MXPO | F10: MXL | G10: 900007935 | H10: SF TP-ED LUGA-OLGUIN | I10: 5087532 | J10: LUGA AUTO TRANSPORTES SA DE CV | K10: N90 | L10: (AP) NAFIN 90 Dias | M10: 10139747 | N10: ARENA CLASIFICADA RIO MALLA 4 | O10: D825 | P10: MX-CED. GOLFO DE CALIFORNIA | Q10: 20230619 | R10: 20291231 | S10: 20240423 | T10: 20291231 | U10: 379 | V10: MXN | W10: M3 | X10: 173 | Y10: MXN | Z10: M3 | AA10: 67231633 | AB10: COMSA OTAY | AC10: 56103638 | AD10: 6622151540 | AE10: 4 | AF10: ENTREGA DIRECTA | AG10: 1.45 | AH10: M3 | AI10: X | AJ10: 4 | AK10: V4 | AL10: 20250402 | AM10: D825-900007935-67231633-10139747-4
A11: 900004527D82510171201 | B11: 4600033292-140 | C11: 4600033292 | D11: 140 | E11: MXPO | F11: MXL | G11: 900004527 | H11: TP- GUSA | I11: 5002503 | J11: CONSTRUCTORA GUSA SA DE CV | K11: Z03 | L11: (AP) 15 Dias | M11: 10171201 | N11: ARENA CLASIFICADA BASALTO MALLA 4 | O11: D825 | P11: MX-CED. GOLFO DE CALIFORNIA | Q11: 20160301 | R11: 20281231 | S11: 20220101 | T11: 20251231 | U11: 91.08 | V11: MXN | W11: M3 | X11: 0 | Y11: MXN | Z11: M3 | AC11: 56103638 | AD11: 6622151540 | AE11: 1 | AF11: ENTREGADO | AG11: 1.511 | AH11: M3 | AI11: X | AJ11: 4 | AK11: V1 | AL11: 20230920 | AM11: D825-900004527-10171201
A12: 900005099D82510141536 | B12: 4600037066-30 | C12: 4600037066 | D12: 30 | E12: MXPO | F12: MXL | G12: 900005099 | H12: TP- JL CONCRETOS Y AGREGADOS | I12: 5066849 | J12: JL CONCRETOS Y AGREGADOS SR L DE CV | K12: Z09 | L12: (AP) 90 Dias | M12: 10141536 | N12: GRAVA TRITURADA BASALTO 20 MM - 3/4" | O12: D825 | P12: MX-CED. GOLFO DE CALIFORNIA | Q12: 20170306 | R12: 20241231 | S12: 20170320 | T12: 20241231 | U12: 145 | V12: MXN | W12: M3 | X12: 0 | Y12: MXN | Z12: M3 | AC12: 56103637 | AD12: 6622151540 | AE12: 1 | AF12: ENTREGADO | AG12: 1.38 | AH12: M3 | AI12: X | AJ12: 4 | AK12: V1 | AL12: 20230920 | AM12: D825-900005099-10141536
A13: 900005099D82510141571 | B13: 4600037066-10 | C13: 4600037066 | D13: 10 | E13: MXPO | F13: MXL | G13: 900005099 | H13: TP- JL CONCRETOS Y AGREGADOS | I13: 5066849 | J13: JL CONCRETOS Y AGREGADOS SR L DE CV | K13: Z09 | L13: (AP) 90 Dias | M13: 10141571 | N13: POLVO TRITURADO BASALTO | O13: D825 | P13: MX-CED. GOLFO DE CALIFORNIA | Q13: 20170306 | R13: 20241231 | S13: 20170306 | T13: 20241231 | U13: 80 | V13: MXN | W13: M3 | X13: 0 | Y13: MXN | Z13: M3 | AC13: 56103638 | AD13: 6622151540 | AE13: 1 | AF13: ENTREGADO | AG13: 1.34 | AH13: M3 | AI13: X | AJ13: 4 | AK13: V1 | AL13: 20230920 | AM13: D825-900005099-10141571
A14: 900004527D82510165992 | B14: 4600033292-160 | C14: 4600033292 | D14: 160 | E14: MXPO | F14: MXL | G14: 900004527 | H14: TP- GUSA | I14: 5002503 | J14: CONSTRUCTORA GUSA SA DE CV | K14: Z03 | L14: (AP) 15 Dias | M14: 10165992 | N14: GRAVA TRITURADA BASALTO 13 MM - 1/2" | O14: D825 | P14: MX-CED. GOLFO DE CALIFORNIA | Q14: 20160301 | R14: 20281231 | S14: 20200511 | T14: 20291231 | U14: 239.2 | V14: MXN | W14: M3 | X14: 0 | Y14: MXN | Z14: M3 | AC14: 56103637 | AD14: 6622151867 | AE14: 1 | AF14: ENTREGADO | AG14: 1.226 | AH14: M3 | AI14: X | AJ14: 4 | AK14: V1 | AL14: 20230920 | AM14: D825-900004527-10165992
A15: 900004848D82510139747 | B15: 4600035173-20 | C15: 4600035173 | D15: 20 | E15: MXPO | F15: MXL | G15: 900004848 | H15: TP- CONSTRUCTORA SEXTIN VALLE | I15: 5042038 | J15: CONSTRUCTORA SEXTIN SA DE CV | K15: N120 | L15: (AP) NAFIN 120 Dias | M15: 10139747 | N15: ARENA CLASIFICADA RIO MALLA 4 | O15: D825 | P15: MX-CED. GOLFO DE CALIFORNIA | Q15: 20160831 | R15: 20241231 | S15: 20210415 | T15: 20241231 | U15: 140 | V15: MXN | W15: M3 | X15: 0 | Y15: MXN | Z15: M3 | AC15: 56103638 | AD15: 6622151540 | AE15: 1 | AF15: ENTREGADO | AG15: 1.45 | AH15: M3 | AI15: X | AJ15: 4 | AK15: V1 | AL15: 20230920 | AM15: D825-900004848-10139747
A16: 900005099D82510141537 | B16: 4600037066-40 | C16: 4600037066 | D16: 40 | E16: MXPO | F16: MXL | G16: 900005099 | H16: TP- JL CONCRETOS Y AGREGADOS | I16: 5066849 | J16: JL CONCRETOS Y AGREGADOS SR L DE CV | K16: Z09 | L16: (AP) 90 Dias | M16: 10141537 | N16: GRAVA TRITURADA BASALTO 40 MM - 1 1/2" | O16: D825 | P16: MX-CED. GOLFO DE CALIFORNIA | Q16: 20170306 | R16: 20241231 | S16: 20180724 | T16: 20241231 | U16: 141.5 | V16: MXN | W16: M3 | X16: 0 | Y16: MXN | Z16: M3 | AC16: 56103637 | AD16: 6622151540 | AE16: 1 | AF16: ENTREGADO | AG16: 1.421 | AH16: M3 | AI16: X | AJ16: 4 | AK16: V1 | AL16: 20230920 | AM16: D825-900005099-10141537
A17: 900004527D82510153332 | B17: 4600033292-100 | C17: 4600033292 | D17: 100 | E17: MXPO | F17: MXL | G17: 900004527 | H17: TP- GUSA | I17: 5002503 | J17: CONSTRUCTORA GUSA SA DE CV | K17: Z03 | L17: (AP) 15 Dias | M17: 10153332 | N17: GRAVA TRITURADA BASALTO 40 MM - 1 1/2" | O17: D825 | P17: MX-CED. GOLFO DE CALIFORNIA | Q17: 20160301 | R17: 20281231 | S17: 20220801 | T17: 20271231 | U17: 300 | V17: MXN | W17: M3 | X17: 0 | Y17: MXN | Z17: M3 | AC17: 56103637 | AD17: 6622151540 | AE17: 1 | AF17: ENTREGADO | AG17: 1.5 | AH17: M3 | AI17: X | AJ17: 4 | AK17: V1 | AL17: 20230920 | AM17: D825-900004527-10153332
A18: 900004527D82510137462 | B18: 4600033292-180 | C18: 4600033292 | D18: 180 | E18: MXPO | F18: MXL | G18: 900004527 | H18: TP- GUSA | I18: 5002503 | J18: CONSTRUCTORA GUSA SA DE CV | K18: Z03 | L18: (AP) 15 Dias | M18: 10137462 | N18: GRAVA TRITURADA BASALTO 10 MM - 3/8" | O18: D825 | P18: MX-CED. GOLFO DE CALIFORNIA | Q18: 20160301 | R18: 20281231 | S18: 20220801 | T18: 20271231 | U18: 369 | V18: MXN | W18: M3 | X18: 0 | Y18: MXN | Z18: M3 | AC18: 56103637 | AD18: 6622151540 | AE18: 1 | AF18: ENTREGADO | AG18: 1.37 | AH18: M3 | AI18: X | AJ18: 4 | AK18: V1 | AL18: 20230920 | AM18: D825-900004527-10137462
A19: 900005099D82510179731 | B19: 4600037066-50 | C19: 4600037066 | D19: 50 | E19: MXPO | F19: MXL | G19: 900005099 | H19: TP- JL CONCRETOS Y AGREGADOS | I19: 5066849 | J19: JL CONCRETOS Y AGREGADOS SR L DE CV | K19: Z09 | L19: (AP) 90 Dias | M19: 10179731 | N19: BASE H TRITURADA BASALTO 1 1/2" A FINOS | O19: D825 | P19: MX-CED. GOLFO DE CALIFORNIA | Q19: 20170306 | R19: 20241231 | S19: 20200108 | T19: 20291231 | U19: 144.09 | V19: MXN | W19: M3 | X19: 0 | Y19: MXN | Z19: M3 | AC19: 56103590 | AD19: 6622151540 | AE19: 1 | AF19: ENTREGADO | AG19: 1.619 | AH19: M3 | AI19: X | AJ19: 4 | AK19: V1 | AL19: 20230920 | AM19: D825-900005099-10179731
A20: 900005187D82510147585 | B20: 4600044437-10 | C20: 4600044437 | D20: 10 | E20: MXPO | F20: MXL | G20: 900005187 | H20: TP- DECOP CONSTRUCTORA | I20: 5057105 | J20: DECOP CONSTRUCTORA S A DE CV | K20: N120 | L20: (AP) NAFIN 120 Dias | M20: 10147585 | N20: TUCURUGUAY TRITURADO GRANITO | O20: D825 | P20: MX-CED. GOLFO DE CALIFORNIA | Q20: 20190401 | R20: 20241231 | S20: 20190401 | T20: 20241231 | U20: 30.8 | V20: MXN | W20: M3 | X20: 0 | Y20: MXN | Z20: M3 | AC20: 56103638 | AD20: 6622151540 | AE20: 1 | AF20: ENTREGADO | AG20: 1.4 | AH20: M3 | AI20: X | AJ20: 4 | AK20: V4 | AL20: 20230920 | AM20: D825-900005187-10147585
A21: 900006873D82510000191 | B21: 4600048798-20 | C21: 4600048798 | D21: 20 | E21: MXPO | F21: MXL | G21: 900006873 | H21: SF TP-LO INFRA EL REFUGIO | I21: 5078800 | J21: LO INFRAESTRUCTURA S DE RL DE CV | K21: N30 | L21: (AP) NAFIN 30 Dias | M21: 10000191 | N21: Grava Triturada Basalto 20 mm - 3/4" | O21: D825 | P21: MX-CED. GOLFO DE CALIFORNIA | Q21: 20210106 | R21: 20291231 | S21: 20220215 | T21: 20271231 | U21: 220 | V21: MXN | W21: M3 | X21: 0 | Y21: MXN | Z21: M3 | AC21: 56103637 | AD21: 6622151540 | AE21: 1 | AF21: ENTREGADO | AG21: 1.41 | AH21: M3 | AI21: X | AJ21: 4 | AK21: V4 | AL21: 20230920 | AM21: D825-900006873-10000191
A22: 900004527D82510125120 | B22: 4600033292-190 | C22: 4600033292 | D22: 190 | E22: MXPO | F22: MXL | G22: 900004527 | H22: TP- GUSA | I22: 5002503 | J22: CONSTRUCTORA GUSA SA DE CV | K22: Z03 | L22: (AP) 15 Dias | M22: 10125120 | N22: GRAVA TRITURADA BASALTO 20 MM (3/4") | O22: D825 | P22: MX-CED. GOLFO DE CALIFORNIA | Q22: 20160301 | R22: 20281231 | S22: 20230718 | T22: 20281231 | U22: 300 | V22: MXN | W22: M3 | X22: 0 | Y22: MXN | Z22: M3 | AC22: 56103637 | AD22: 6622151540 | AE22: 1 | AF22: ENTREGADO | AG22: 1.402 | AH22: M3 | AI22: X | AJ22: 4 | AK22: V1 | AL22: 20230920 | AM22: D825-900004527-10125120
... A29: 900007330D82510152920 | B29: 4600052083-20 | C29: 4600052083 | D29: 20 | E29: MXPO | F29: MXL | G29: 900007330 | H29: SF TP-RECOGIDO-APR | I29: 5081100 | J29: APR OBRAS Y AGREGADOS S DE RL DE CV | K29: N90 | L29: (AP) NAFIN 90 Dias | M29: 10152920 | N29: POLVO TRITURADO GRANITO | O29: D825 | P29: MX-CED. GOLFO DE CALIFORNIA | Q29: 20211001 | R29: 20261231 | S29: 20210930 | T29: 20251231 | U29: 40 | V29: MXN | W29: M3 | X29: 0 | Y29: MXN | Z29: M3 | AC29: 56103591 | AD29: 6622151540 | AE29: 2 | AF29: RECOGIDO | AG29: 1.615 | AH29: M3 | AI29: X | AJ29: 4 | AK29: V4 | AL29: 20230920 | AM29: D825-900007330-10152920
A30: 900005121D8256665012610139747 | B30: 4600047224-10 | C30: 4600047224 | D30: 10 | E30: MXPO | F30: MXL | G30: 900005121 | H30: TP- SEXTIN TIJUANA | I30: 5042038 | J30: CONSTRUCTORA SEXTIN SA DE CV | K30: N120 | L30: (AP) NAFIN 120 Dias | M30: 10139747 | N30: ARENA CLASIFICADA RIO MALLA 4 | O30: D825 | P30: MX-CED. GOLFO DE CALIFORNIA | Q30: 20200527 | R30: 20301231 | S30: 20200527 | T30: 20301231 | U30: 228 | V30: MXN | W30: M3 | X30: 108 | Y30: MXN | Z30: M3 | AA30: 66650126 | AB30: I8 CONCRETOS T Y G SA DE CV | AC30: 56103638 | AD30: 6622151540 | AE30: 4 | AF30: ENTREGA DIRECTA | AG30: 1.45 | AH30: M3 | AI30: X | AJ30: 4 | AK30: V1 | AL30: 20230920 | AM30: D825-900005121-66650126-10139747-4
A31: 900005281D8256665044910184157 | B31: 4600038431-80 | C31: 4600038431 | D31: 80 | E31: MXPO | F31: MXL | G31: 900005281 | H31: TP- ED PETREOS LA PURISIMA | I31: 5011228 | J31: PETREOS LA PURISIMA SA DE CV | K31: N90 | L31: (AP) NAFIN 90 Dias | M31: 10184157 | N31: GRAVA TRITURADA BASALTO 20 MM - 3/4" | O31: D825 | P31: MX-CED. GOLFO DE CALIFORNIA | Q31: 20170616 | R31: 20291231 | S31: 20200824 | T31: 20291231 | U31: 330 | V31: MXN | W31: M3 | X31: 108 | Y31: MXN | Z31: M3 | AA31: 66650449 | AB31: I8 CONCRETOS FLOMEX | AC31: 56103637 | AD31: 6622151540 | AE31: 4 | AF31: ENTREGA DIRECTA | AG31: 1.383 | AH31: M3 | AI31: X | AJ31: 4 | AK31: V4 | AL31: 20230920 | AM31: D825-900005281-66650449-10184157-4
A32: 900005281D8256705909710137462 | B32: 4600038431-120 | C32: 4600038431 | D32: 120 | E32: MXPO | F32: MXL | G32: 900005281 | H32: TP- ED PETREOS LA PURISIMA | I32: 5011228 | J32: PETREOS LA PURISIMA SA DE CV | K32: N90 | L32: (AP) NAFIN 90 Dias | M32: 10137462 | N32: GRAVA TRITURADA BASALTO 10 MM - 3/8" | O32: D825 | P32: MX-CED. GOLFO DE CALIFORNIA | Q32: 20170616 | R32: 20291231 | S32: 20220505 | T32: 20271231 | U32: 360 | V32: MXN | W32: M3 | X32: 65 | Y32: MXN | Z32: M3 | AA32: 67059097 | AB32: PUERTA PLATA (dg) | AC32: 56103637 | AD32: 6622151540 | AE32: 4 | AF32: ENTREGA DIRECTA | AG32: 1.37 | AH32: M3 | AI32: X | AJ32: 4 | AK32: V4 | AL32: 20230920 | AM32: D825-900005281-67059097-10137462-4
A33: 900005281D8256694864010052400 | B33: 4600038431-140 | C33: 4600038431 | D33: 140 | E33: MXPO | F33: MXL | G33: 900005281 | H33: TP- ED PETREOS LA PURISIMA | I33: 5011228 | J33: PETREOS LA PURISIMA SA DE CV | K33: N90 | L33: (AP) NAFIN 90 Dias | M33: 10052400 | N33: Arena Clasificada Río Malla 4 - Lavado | O33: D825 | P33: MX-CED. GOLFO DE CALIFORNIA | Q33: 20170616 | R33: 20291231 | S33: 20221028 | T33: 20271231 | U33: 269.58 | V33: MXN | W33: M3 | X33: 134 | Y33: MXN | Z33: M3 | AA33: 66948640 | AB33: WESTLAKE ROYAL MEXICO | AC33: 56103638 | AD33: 6622151867 | AE33: 4 | AF33: ENTREGA DIRECTA | AG33: 1.655 | AH33: M3 | AI33: X | AJ33: 4 | AK33: V4 | AL33: 20230920 | AM33: D825-900005281-66948640-10052400-4
A34: 900007935D8256713962210139747 | B34: 4600057825-30 | C34: 4600057825 | D34: 30 | E34: MXPO | F34: MXL | G34: 900007935 | H34: SF TP-ED LUGA-OLGUIN | I34: 5087532 | J34: LUGA AUTO TRANSPORTES SA DE CV | K34: N90 | L34: (AP) NAFIN 90 Dias | M34: 10139747 | N34: ARENA CLASIFICADA RIO MALLA 4 | O34: D825 | P34: MX-CED. GOLFO DE CALIFORNIA | Q34: 20230619 | R34: 20291231 | S34: 20230720 | T34: 20281231 | U34: 415 | V34: MXN | W34: M3 | X34: 219 | Y34: MXN | Z34: M3 | AA34: 67139622 | AB34: CPI VILLAS VGD (FA) | AC34: 56103638 | AD34: 6622151540 | AE34: 4 | AF34: ENTREGA DIRECTA | AG34: 1.45 | AH34: M3 | AI34: X | AJ34: 4 | AK34: V4 | AL34: 20250402 | AM34: D825-900007935-67139622-10139747-4
A35: 900006891D8256698692410179731 | B35: 4600048585-60 | C35: 4600048585 | D35: 60 | E35: MXPO | F35: MXL | G35: 900006891 | H35: SF TP-ED-TRAZO | I35: 5078812 | J35: TRAZO DEL NORESTE SRL DE CV | K35: N90 | L35: (AP) NAFIN 90 Dias | M35: 10179731 | N35: BASE H TRITURADA BASALTO 1 1/2" A FINOS | O35: D825 | P35: MX-CED. GOLFO DE CALIFORNIA | Q35: 20201203 | R35: 20291231 | S35: 20210721 | T35: 20251231 | U35: 321 | V35: MXN | W35: M3 | X35: 131 | Y35: MXN | Z35: M3 | AA35: 66986924 | AB35: AY CALLE PADRE KINO SALVATIERRA(LHC | AC35: 56103590 | AD35: 6622151540 | AE35: 4 | AF35: ENTREGA DIRECTA | AG35: 1.619 | AH35: M3 | AI35: X | AJ35: 4 | AK35: V4 | AL35: 20230920 | AM35: D825-900006891-66986924-10179731-4
A36: 900007935D8256734153110125120 | B36: 4600057825-140 | C36: 4600057825 | D36: 140 | E36: MXPO | F36: MXL | G36: 900007935 | H36: SF TP-ED LUGA-OLGUIN | I36: 5087532 | J36: LUGA AUTO TRANSPORTES SA DE CV | K36: N90 | L36: (AP) NAFIN 90 Dias | M36: 10125120 | N36: GRAVA TRITURADA BASALTO 20 MM (3/4") | O36: D825 | P36: MX-CED. GOLFO DE CALIFORNIA | Q36: 20230619 | R36: 20291231 | S36: 20260225 | T36: 20301231 | U36: 380 | V36: MXN | W36: M3 | X36: 75 | Y36: MXN | Z36: M3 | AA36: 67341531 | AB36: PROSPERITY SPEC 09 GAAB | AC36: 56103637 | AD36: 6622151540 | AE36: 4 | AF36: ENTREGA DIRECTA | AG36: 1.35 | AH36: M3 | AI36: X | AJ36: 4 | AK36: V4 | AL36: 20260227 | AM36: D825-900007935-67341531-10125120-4
A37: 900000651D82510052400 | B37: 4600047841-40 | C37: 4600047841 | D37: 40 | E37: MXPO | F37: MXL | G37: 900000651 | H37: SF TP PETREOS LA PURISIMA | I37: 5011228 | J37: PETREOS LA PURISIMA SA DE CV | K37: N90 | L37: (AP) NAFIN 90 Dias | M37: 10052400 | N37: Arena Clasificada Río Malla 4 - Lavado | O37: D825 | P37: MX-CED. GOLFO DE CALIFORNIA | Q37: 20200824 | R37: 20261231 | S37: 20250512 | T37: 20301231 | U37: 226.34 | V37: MXN | W37: M3 | X37: 0 | Y37: MXN | Z37: M3 | AC37: 56103638 | AD37: 6622151867 | AE37: 1 | AF37: ENTREGADO | AG37: 1.655 | AH37: M3 | AI37: X | AJ37: 4 | AK37: V4 | AL37: 20250604 | AM37: D825-900000651-10052400
A38: 900007935D8256515636510139747 | B38: 4600057825-130 | C38: 4600057825 | D38: 130 | E38: MXPO | F38: MXL | G38: 900007935 | H38: SF TP-ED LUGA-OLGUIN | I38: 5087532 | J38: LUGA AUTO TRANSPORTES SA DE CV | K38: N90 | L38: (AP) NAFIN 90 Dias | M38: 10139747 | N38: ARENA CLASIFICADA RIO MALLA 4 | O38: D825 | P38: MX-CED. GOLFO DE CALIFORNIA | Q38: 20230619 | R38: 20291231 | S38: 20260213 | T38: 20301231 | U38: 390 | V38: MXN | W38: M3 | X38: 184 | Y38: MXN | Z38: M3 | AA38: 65156365 | AB38: PROMEXMA TIJUANA | AC38: 56103638 | AD38: 6622151540 | AE38: 4 | AF38: ENTREGA DIRECTA | AG38: 1.45 | AH38: M3 | AI38: X | AJ38: 4 | AK38: V4 | AL38: 20260306 | AM38: D825-900007935-65156365-10139747-4
A39: 900006667D8256702277910211341 | B39: 4600069592-160 | C39: 4600069592 | D39: 160 | E39: MXPO | F39: MXL | G39: 900006667 | H39: SF TP-ED TRITURADOS ROCA | I39: 5078620 | J39: TRITURADOS ROCA DE BC SA DE CV | K39: N90 | L39: (AP) NAFIN 90 Dias | M39: 10211341 | N39: GRAVA TRITURADA BASALTO 10 MM - 3/8" | O39: D825 | P39: MX-CED. GOLFO DE CALIFORNIA | Q39: 20240527 | R39: 20291231 | S39: 20260429 | T39: 20301231 | U39: 367 | V39: MXN | W39: TN | X39: 55 | Y39: MXN | Z39: TN | AA39: 67022779 | AB39: SOLIDBLOCK SA DE CV | AC39: 56103637 | AD39: 6622151867 | AE39: 4 | AF39: ENTREGA DIRECTA | AG39: 1 | AH39: TO | AI39: X | AJ39: 4 | AK39: V1 | AL39: 20260505 | AM39: D825-900006667-67022779-10211341-4
A40: 900006667D8256733352910211341 | B40: 4600069592-120 | C40: 4600069592 | D40: 120 | E40: MXPO | F40: MXL | G40: 900006667 | H40: SF TP-ED TRITURADOS ROCA | I40: 5078620 | J40: TRITURADOS ROCA DE BC SA DE CV | K40: N90 | L40: (AP) NAFIN 90 Dias | M40: 10211341 | N40: GRAVA TRITURADA BASALTO 10 MM - 3/8" | O40: D825 | P40: MX-CED. GOLFO DE CALIFORNIA | Q40: 20240527 | R40: 20291231 | S40: 20260429 | T40: 20301231 | U40: 352 | V40: MXN | W40: TN | X40: 40 | Y40: MXN | Z40: TN | AA40: 67333529 | AB40: MAT BLOQUE | AC40: 56103637 | AD40: 6622151867 | AE40: 4 | AF40: ENTREGA DIRECTA | AG40: 1 | AH40: TO | AI40: X | AJ40: 4 | AK40: V1 | AL40: 20260505 | AM40: D825-900006667-67333529-10211341-4
A41: 900006667D8256723796910211341 | B41: 4600069592-140 | C41: 4600069592 | D41: 140 | E41: MXPO | F41: MXL | G41: 900006667 | H41: SF TP-ED TRITURADOS ROCA | I41: 5078620 | J41: TRITURADOS ROCA DE BC SA DE CV | K41: N90 | L41: (AP) NAFIN 90 Dias | M41: 10211341 | N41: GRAVA TRITURADA BASALTO 10 MM - 3/8" | O41: D825 | P41: MX-CED. GOLFO DE CALIFORNIA | Q41: 20240527 | R41: 20291231 | S41: 20260429 | T41: 20301231 | U41: 347 | V41: MXN | W41: TN | X41: 35 | Y41: MXN | Z41: TN | AA41: 67237969 | AB41: BLOQUERA CEMENQUIN | AC41: 56103637 | AD41: 6622151867 | AE41: 4 | AF41: ENTREGA DIRECTA | AG41: 1 | AH41: TO | AI41: X | AJ41: 4 | AK41: V1 | AL41: 20260505 | AM41: D825-900006667-67237969-10211341-4
A42: 900006667D8256733352910274601 | B42: 4600069592-130 | C42: 4600069592 | D42: 130 | E42: MXPO | F42: MXL | G42: 900006667 | H42: SF TP-ED TRITURADOS ROCA | I42: 5078620 | J42: TRITURADOS ROCA DE BC SA DE CV | K42: N90 | L42: (AP) NAFIN 90 Dias | M42: 10274601 | N42: MP ARENA BASALTO N° 4 | O42: D825 | P42: MX-CED. GOLFO DE CALIFORNIA | Q42: 20240527 | R42: 20291231 | S42: 20260429 | T42: 20301231 | U42: 163 | V42: MXN | W42: TN | X42: 40 | Y42: MXN | Z42: TN | AA42: 67333529 | AB42: MAT BLOQUE | AC42: 56103638 | AD42: 6622151540 | AE42: 4 | AF42: ENTREGA DIRECTA | AG42: 1 | AH42: TO | AI42: X | AJ42: 4 | AK42: V1 | AL42: 20260505 | AM42: D825-900006667-67333529-10274601-4
A43: 900006667D8256723796910274601 | B43: 4600069592-150 | C43: 4600069592 | D43: 150 | E43: MXPO | F43: MXL | G43: 900006667 | H43: SF TP-ED TRITURADOS ROCA | I43: 5078620 | J43: TRITURADOS ROCA DE BC SA DE CV | K43: N90 | L43: (AP) NAFIN 90 Dias | M43: 10274601 | N43: MP ARENA BASALTO N° 4 | O43: D825 | P43: MX-CED. GOLFO DE CALIFORNIA | Q43: 20240527 | R43: 20291231 | S43: 20260429 | T43: 20301231 | U43: 158 | V43: MXN | W43: TN | X43: 35 | Y43: MXN | Z43: TN | AA43: 67237969 | AB43: BLOQUERA CEMENQUIN | AC43: 56103638 | AD43: 6622151540 | AE43: 4 | AF43: ENTREGA DIRECTA | AG43: 1 | AH43: TO | AI43: X | AJ43: 4 | AK43: V1 | AL43: 20260505 | AM43: D825-900006667-67237969-10274601-4
A44: 900006667D8256702277910274601 | B44: 4600069592-170 | C44: 4600069592 | D44: 170 | E44: MXPO | F44: MXL | G44: 900006667 | H44: SF TP-ED TRITURADOS ROCA | I44: 5078620 | J44: TRITURADOS ROCA DE BC SA DE CV | K44: N90 | L44: (AP) NAFIN 90 Dias | M44: 10274601 | N44: MP ARENA BASALTO N° 4 | O44: D825 | P44: MX-CED. GOLFO DE CALIFORNIA | Q44: 20240527 | R44: 20291231 | S44: 20260429 | T44: 20301231 | U44: 178 | V44: MXN | W44: TN | X44: 55 | Y44: MXN | Z44: TN | AA44: 67022779 | AB44: SOLIDBLOCK SA DE CV | AC44: 56103638 | AD44: 6622151540 | AE44: 4 | AF44: ENTREGA DIRECTA | AG44: 1 | AH44: TO | AI44: X | AJ44: 4 | AK44: V1 | AL44: 20260505 | AM44: D825-900006667-67022779-10274601-4
A45: 900007935D8256719543210139747 | B45: 4600057825-80 | C45: 4600057825 | D45: 80 | E45: MXPO | F45: MXL | G45: 900007935 | H45: SF TP-ED LUGA-OLGUIN | I45: 5087532 | J45: LUGA AUTO TRANSPORTES SA DE CV | K45: N90 | L45: (AP) NAFIN 90 Dias | M45: 10139747 | N45: ARENA CLASIFICADA RIO MALLA 4 | O45: D825 | P45: MX-CED. GOLFO DE CALIFORNIA | Q45: 20230619 | R45: 20291231 | S45: 20240701 | T45: 20291231 | U45: 358 | V45: MXN | W45: M3 | X45: 152 | Y45: MXN | Z45: M3 | AA45: 67195432 | AB45: EL CAÑON SUC OTAY | AC45: 56103638 | AD45: 6622151540 | AE45: 4 | AF45: ENTREGA DIRECTA | AG45: 1.45 | AH45: M3 | AI45: X | AJ45: 4 | AK45: V4 | AL45: 20250402 | AM45: D825-900007935-67195432-10139747-4
A46: 900005281D8256722980810052400 | B46: 4600038431-150 | C46: 4600038431 | D46: 150 | E46: MXPO | F46: MXL | G46: 900005281 | H46: TP- ED PETREOS LA PURISIMA | I46: 5011228 | J46: PETREOS LA PURISIMA SA DE CV | K46: N90 | L46: (AP) NAFIN 90 Dias | M46: 10052400 | N46: Arena Clasificada Río Malla 4 - Lavado | O46: D825 | P46: MX-CED. GOLFO DE CALIFORNIA | Q46: 20170616 | R46: 20291231 | S46: 20240603 | T46: 20291231 | U46: 376.34 | V46: MXN | W46: M3 | X46: 150 | Y46: MXN | Z46: M3 | AA46: 67229808 | AB46: DC CONCRETOS VALLE REDONDO | AC46: 56103638 | AD46: 6622151867 | AE46: 4 | AF46: ENTREGA DIRECTA | AG46: 1.655 | AH46: M3 | AI46: X | AJ46: 4 | AK46: V4 | AL46: 20240606 | AM46: D825-900005281-67229808-10052400-4
A47: 900006875D82510256402 | B47: 4600048797-40 | C47: 4600048797 | D47: 40 | E47: MXPO | F47: MXL | G47: 900006875 | H47: SF TP-REC-LO INFRA EL REFUGIO | I47: 5078800 | J47: LO INFRAESTRUCTURA S DE RL DE CV | K47: N30 | L47: (AP) NAFIN 30 Dias | M47: 10256402 | N47: BASE H TRITURADA BASALTO 1 1/2" A FINOS | O47: D825 | P47: MX-CED. GOLFO DE CALIFORNIA | Q47: 20210106 | R47: 20291231 | S47: 20240415 | T47: 20291231 | U47: 190 | V47: MXN | W47: M3 | X47: 0 | Y47: MXN | Z47: M3 | AC47: 56103590 | AD47: 6622151540 | AE47: 2 | AF47: RECOGIDO | AG47: 1.518 | AH47: M3 | AI47: X | AJ47: 4 | AK47: V4 | AL47: 20250204 | AM47: D825-900006875-10256402
A48: 900005281D8256665012610137462 | B48: 4600038431-70 | C48: 4600038431 | D48: 70 | E48: MXPO | F48: MXL | G48: 900005281 | H48: TP- ED PETREOS LA PURISIMA | I48: 5011228 | J48: PETREOS LA PURISIMA SA DE CV | K48: N90 | L48: (AP) NAFIN 90 Dias | M48: 10137462 | N48: GRAVA TRITURADA BASALTO 10 MM - 3/8" | O48: D825 | P48: MX-CED. GOLFO DE CALIFORNIA | Q48: 20170616 | R48: 20291231 | S48: 20200820 | T48: 20291231 | U48: 400 | V48: MXN | W48: M3 | X48: 105 | Y48: MXN | Z48: M3 | AA48: 66650126 | AB48: I8 CONCRETOS T Y G SA DE CV | AC48: 56103637 | AD48: 6622151540 | AE48: 4 | AF48: ENTREGA DIRECTA | AG48: 1.37 | AH48: M3 | AI48: X | AJ48: 4 | AK48: V4 | AL48: 20230920 | AM48: D825-900005281-66650126-10137462-4
A49: 900006891D8256705909710139747 | B49: 4600048585-70 | C49: 4600048585 | D49: 70 | E49: MXPO | F49: MXL | G49: 900006891 | H49: SF TP-ED-TRAZO | I49: 5078812 | J49: TRAZO DEL NORESTE SRL DE CV | K49: N90 | L49: (AP) NAFIN 90 Dias | M49: 10139747 | N49: ARENA CLASIFICADA RIO MALLA 4 | O49: D825 | P49: MX-CED. GOLFO DE CALIFORNIA | Q49: 20201203 | R49: 20291231 | S49: 20220505 | T49: 20271231 | U49: 220 | V49: MXN | W49: M3 | X49: 105 | Y49: MXN | Z49: M3 | AA49: 67059097 | AB49: PUERTA PLATA (dg) | AC49: 56103638 | AD49: 6622151540 | AE49: 4 | AF49: ENTREGA DIRECTA | AG49: 1.45 | AH49: M3 | AI49: X | AJ49: 4 | AK49: V4 | AL49: 20230920 | AM49: D825-900006891-67059097-10139747-4
A50: 900006667D8256665012610211341 | B50: 4600069592-100 | C50: 4600069592 | D50: 100 | E50: MXPO | F50: MXL | G50: 900006667 | H50: SF TP-ED TRITURADOS ROCA | I50: 5078620 | J50: TRITURADOS ROCA DE BC SA DE CV | K50: N90 | L50: (AP) NAFIN 90 Dias | M50: 10211341 | N50: GRAVA TRITURADA BASALTO 10 MM - 3/8" | O50: D825 | P50: MX-CED. GOLFO DE CALIFORNIA | Q50: 20240527 | R50: 20291231 | S50: 20260410 | T50: 20301231 | U50: 400 | V50: MXN | W50: TN | X50: 88 | Y50: MXN | Z50: TN | AA50: 66650126 | AB50: I8 CONCRETOS T Y G SA DE CV | AC50: 56103637 | AD50: 6622151867 | AE50: 4 | AF50: ENTREGA DIRECTA | AG50: 1 | AH50: TO | AI50: X | AJ50: 4 | AK50: V1 | AL50: 20260909 | AM50: D825-900006667-66650126-10211341-4
A51: 900006667D8256724801610275058 | B51: 4600069592-80 | C51: 4600069592 | D51: 80 | E51: MXPO | F51: MXL | G51: 900006667 | H51: SF TP-ED TRITURADOS ROCA | I51: 5078620 | J51: TRITURADOS ROCA DE BC SA DE CV | K51: N90 | L51: (AP) NAFIN 90 Dias | M51: 10275058 | N51: MP GRAVA TRIT. BASALTO 40-4MM - 1 1/2" | O51: D825 | P51: MX-CED. GOLFO DE CALIFORNIA | Q51: 20240527 | R51: 20291231 | S51: 20260410 | T51: 20301231 | U51: 248 | V51: MXN | W51: TN | X51: 30 | Y51: MXN | Z51: TN | AA51: 67248016 | AB51: CONCRETOS TYG MONTE VERDE | AC51: 56103637 | AD51: 6622151540 | AE51: 4 | AF51: ENTREGA DIRECTA | AG51: 1 | AH51: TO | AI51: X | AJ51: 4 | AK51: V1 | AL51: 20260909 | AM51: D825-900006667-67248016-10275058-4
A52: 900006667D8256665012610275058 | B52: 4600069592-70 | C52: 4600069592 | D52: 70 | E52: MXPO | F52: MXL | G52: 900006667 | H52: SF TP-ED TRITURADOS ROCA | I52: 5078620 | J52: TRITURADOS ROCA DE BC SA DE CV | K52: N90 | L52: (AP) NAFIN 90 Dias | M52: 10275058 | N52: MP GRAVA TRIT. BASALTO 40-4MM - 1 1/2" | O52: D825 | P52: MX-CED. GOLFO DE CALIFORNIA | Q52: 20240527 | R52: 20291231 | S52: 20260410 | T52: 20301231 | U52: 306 | V52: MXN | W52: TN | X52: 88 | Y52: MXN | Z52: TN | AA52: 66650126 | AB52: I8 CONCRETOS T Y G SA DE CV | AC52: 56103637 | AD52: 6622151540 | AE52: 4 | AF52: ENTREGA DIRECTA | AG52: 1 | AH52: TO | AI52: X | AJ52: 4 | AK52: V4 | AL52: 20260414 | AM52: D825-900006667-66650126-10275058-4
A53: 900007329D8256665022910139747 | B53: 4600052082-80 | C53: 4600052082 | D53: 80 | E53: MXPO | F53: MXL | G53: 900007329 | H53: SF TP-ED APR | I53: 5081100 | J53: APR OBRAS Y AGREGADOS S DE RL DE CV | K53: N90 | L53: (AP) NAFIN 90 Dias | M53: 10139747 | N53: ARENA CLASIFICADA RIO MALLA 4 | O53: D825 | P53: MX-CED. GOLFO DE CALIFORNIA | Q53: 20211001 | R53: 20271231 | S53: 20211208 | T53: 20261231 | U53: 240 | V53: MXN | W53: M3 | X53: 115 | Y53: MXN | Z53: M3 | AA53: 66650229 | AB53: I8 OBR-AGR UNICONCRETOS SA DE CV | AC53: 56103638 | AD53: 6622151540 | AE53: 4 | AF53: ENTREGA DIRECTA | AG53: 1.45 | AH53: M3 | AI53: X | AJ53: 4 | AK53: V4 | AL53: 20230920 | AM53: D825-900007329-66650229-10139747-4
A54: 900006891D8256665524310139747 | B54: 4600048585-20 | C54: 4600048585 | D54: 20 | E54: MXPO | F54: MXL | G54: 900006891 | H54: SF TP-ED-TRAZO | I54: 5078812 | J54: TRAZO DEL NORESTE SRL DE CV | K54: N90 | L54: (AP) NAFIN 90 Dias | M54: 10139747 | N54: ARENA CLASIFICADA RIO MALLA 4 | O54: D825 | P54: MX-CED. GOLFO DE CALIFORNIA | Q54: 20201203 | R54: 20291231 | S54: 20210415 | T54: 20251231 | U54: 230 | V54: MXN | W54: M3 | X54: 115 | Y54: MXN | Z54: M3 | AA54: 66655243 | AB54: I8 CONCRETOS T Y G PLANTA LA PRESA | AC54: 56103638 | AD54: 6622151540 | AE54: 4 | AF54: ENTREGA DIRECTA | AG54: 1.45 | AH54: M3 | AI54: X | AJ54: 4 | AK54: V4 | AL54: 20230920 | AM54: D825-900006891-66655243-10139747-4
A55: 900007329D8256705909710139747 | B55: 4600052082-90 | C55: 4600052082 | D55: 90 | E55: MXPO | F55: MXL | G55: 900007329 | H55: SF TP-ED APR | I55: 5081100 | J55: APR OBRAS Y AGREGADOS S DE RL DE CV | K55: N90 | L55: (AP) NAFIN 90 Dias | M55: 10139747 | N55: ARENA CLASIFICADA RIO MALLA 4 | O55: D825 | P55: MX-CED. GOLFO DE CALIFORNIA | Q55: 20211001 | R55: 20271231 | S55: 20220505 | T55: 20271231 | U55: 242 | V55: MXN | W55: M3 | X55: 105 | Y55: MXN | Z55: M3 | AA55: 67059097 | AB55: PUERTA PLATA (dg) | AC55: 56103638 | AD55: 6622151540 | AE55: 4 | AF55: ENTREGA DIRECTA | AG55: 1.45 | AH55: M3 | AI55: X | AJ55: 4 | AK55: V4 | AL55: 20230920 | AM55: D825-900007329-67059097-10139747-4
A56: 900005281D8256705909710139747 | B56: 4600038431-130 | C56: 4600038431 | D56: 130 | E56: MXPO | F56: MXL | G56: 900005281 | H56: TP- ED PETREOS LA PURISIMA | I56: 5011228 | J56: PETREOS LA PURISIMA SA DE CV | K56: N90 | L56: (AP) NAFIN 90 Dias | M56: 10139747 | N56: ARENA CLASIFICADA RIO MALLA 4 | O56: D825 | P56: MX-CED. GOLFO DE CALIFORNIA | Q56: 20170616 | R56: 20291231 | S56: 20220505 | T56: 20271231 | U56: 275 | V56: MXN | W56: M3 | X56: 115 | Y56: MXN | Z56: M3 | AA56: 67059097 | AB56: PUERTA PLATA (dg) | AC56: 56103638 | AD56: 6622151540 | AE56: 4 | AF56: ENTREGA DIRECTA | AG56: 1.45 | AH56: M3 | AI56: X | AJ56: 4 | AK56: V4 | AL56: 20230920 | AM56: D825-900005281-67059097-10139747-4
A57: 900006667D8256665012610210657 | B57: 4600069592-40 | C57: 4600069592 | D57: 40 | E57: MXPO | F57: MXL | G57: 900006667 | H57: SF TP-ED TRITURADOS ROCA | I57: 5078620 | J57: TRITURADOS ROCA DE BC SA DE CV | K57: N90 | L57: (AP) NAFIN 90 Dias | M57: 10210657 | N57: GRAVA TRITURADA BASALTO 20 MM - 3/4" | O57: D825 | P57: MX-CED. GOLFO DE CALIFORNIA | Q57: 20240527 | R57: 20291231 | S57: 20260410 | T57: 20301231 | U57: 306 | V57: MXN | W57: TN | X57: 88 | Y57: MXN | Z57: TN | AA57: 66650126 | AB57: I8 CONCRETOS T Y G SA DE CV | AC57: 56103637 | AD57: 6622151540 | AE57: 4 | AF57: ENTREGA DIRECTA | AG57: 1 | AH57: TO | AI57: X | AJ57: 4 | AK57: V1 | AL57: 20260414 | AM57: D825-900006667-66650126-10210657-4
A58: 900006667D8256665032610211341 | B58: 4600069592-90 | C58: 4600069592 | D58: 90 | E58: MXPO | F58: MXL | G58: 900006667 | H58: SF TP-ED TRITURADOS ROCA | I58: 5078620 | J58: TRITURADOS ROCA DE BC SA DE CV | K58: N90 | L58: (AP) NAFIN 90 Dias | M58: 10211341 | N58: GRAVA TRITURADA BASALTO 10 MM - 3/8" | O58: D825 | P58: MX-CED. GOLFO DE CALIFORNIA | Q58: 20240527 | R58: 20291231 | S58: 20260410 | T58: 20301231 | U58: 380 | V58: MXN | W58: TN | X58: 68 | Y58: MXN | Z58: TN | AA58: 66650326 | AB58: I8 FRACC. PUERTA PLATA | AC58: 56103637 | AD58: 6622151867 | AE58: 4 | AF58: ENTREGA DIRECTA | AG58: 1 | AH58: TO | AI58: X | AJ58: 4 | AK58: V1 | AL58: 20260615 | AM58: D825-900006667-66650326-10211341-4
A59: 900006668D82510211341 | B59: 4600069795-20 | C59: 4600069795 | D59: 20 | E59: MXPO | F59: MXL | G59: 900006668 | H59: SF TP-TRIT. ROCA | I59: 5078620 | J59: TRITURADOS ROCA DE BC SA DE CV | K59: N90 | L59: (AP) NAFIN 90 Dias | M59: 10211341 | N59: GRAVA TRITURADA BASALTO 10 MM - 3/8" | O59: D825 | P59: MX-CED. GOLFO DE CALIFORNIA | Q59: 20240701 | R59: 20291231 | S59: 20260410 | T59: 20301231 | U59: 312 | V59: MXN | W59: TN | X59: 0 | Y59: MXN | Z59: TN | AC59: 56103637 | AD59: 6622151867 | AE59: 1 | AF59: ENTREGADO | AG59: 1 | AH59: TO | AI59: X | AJ59: 4 | AK59: V1 | AL59: 20260414 | AM59: D825-900006668-10211341
A60: 900006668D82510275058 | B60: 4600069795-50 | C60: 4600069795 | D60: 50 | E60: MXPO | F60: MXL | G60: 900006668 | H60: SF TP-TRIT. ROCA | I60: 5078620 | J60: TRITURADOS ROCA DE BC SA DE CV | K60: N90 | L60: (AP) NAFIN 90 Dias | M60: 10275058 | N60: MP GRAVA TRIT. BASALTO 40-4MM - 1 1/2" | O60: D825 | P60: MX-CED. GOLFO DE CALIFORNIA | Q60: 20240701 | R60: 20291231 | S60: 20260410 | T60: 20301231 | U60: 218 | V60: MXN | W60: TN | X60: 0 | Y60: MXN | Z60: TN | AC60: 56103637 | AD60: 6622151540 | AE60: 1 | AF60: ENTREGADO | AG60: 1 | AH60: TO | AI60: X | AJ60: 4 | AK60: V1 | AL60: 20260909 | AM60: D825-900006668-10275058
A61: 900005281D8256665012610139747 | B61: 4600038431-110 | C61: 4600038431 | D61: 110 | E61: MXPO | F61: MXL | G61: 900005281 | H61: TP- ED PETREOS LA PURISIMA | I61: 5011228 | J61: PETREOS LA PURISIMA SA DE CV | K61: N90 | L61: (AP) NAFIN 90 Dias | M61: 10139747 | N61: ARENA CLASIFICADA RIO MALLA 4 | O61: D825 | P61: MX-CED. GOLFO DE CALIFORNIA | Q61: 20170616 | R61: 20291231 | S61: 20220215 | T61: 20271231 | U61: 305 | V61: MXN | W61: M3 | X61: 105 | Y61: MXN | Z61: M3 | AA61: 66650126 | AB61: I8 CONCRETOS T Y G SA DE CV | AC61: 56103638 | AD61: 6622151540 | AE61: 4 | AF61: ENTREGA DIRECTA | AG61: 1.45 | AH61: M3 | AI61: X | AJ61: 4 | AK61: V4 | AL61: 20230920 | AM61: D825-900005281-66650126-10139747-4
A62: 900005281D8256665012610137462 | B62: 4600038431-90 | C62: 4600038431 | D62: 90 | E62: MXPO | F62: MXL | G62: 900005281 | H62: TP- ED PETREOS LA PURISIMA | I62: 5011228 | J62: PETREOS LA PURISIMA SA DE CV | K62: N90 | L62: (AP) NAFIN 90 Dias | M62: 10137462 | N62: GRAVA TRITURADA BASALTO 10 MM - 3/8" | O62: D825 | P62: MX-CED. GOLFO DE CALIFORNIA | Q62: 20170616 | R62: 20291231 | S62: 20200824 | T62: 20291231 | U62: 400 | V62: MXN | W62: M3 | X62: 105 | Y62: MXN | Z62: M3 | AA62: 66650126 | AB62: I8 CONCRETOS T Y G SA DE CV | AC62: 56103637 | AD62: 6622151540 | AE62: 4 | AF62: ENTREGA DIRECTA | AG62: 1.37 | AH62: M3 | AI62: X | AJ62: 4 | AK62: V4 | AL62: 20230920 | AM62: D825-900005281-66650126-10137462-4
A63: 900006667D8256724801610211341 | B63: 4600069592-110 | C63: 4600069592 | D63: 110 | E63: MXPO | F63: MXL | G63: 900006667 | H63: SF TP-ED TRITURADOS ROCA | I63: 5078620 | J63: TRITURADOS ROCA DE BC SA DE CV | K63: N90 | L63: (AP) NAFIN 90 Dias | M63: 10211341 | N63: GRAVA TRITURADA BASALTO 10 MM - 3/8" | O63: D825 | P63: MX-CED. GOLFO DE CALIFORNIA | Q63: 20240527 | R63: 20291231 | S63: 20260410 | T63: 20301231 | U63: 342 | V63: MXN | W63: TN | X63: 30 | Y63: MXN | Z63: TN | AA63: 67248016 | AB63: CONCRETOS TYG MONTE VERDE | AC63: 56103637 | AD63: 6622151867 | AE63: 4 | AF63: ENTREGA DIRECTA | AG63: 1 | AH63: TO | AI63: X | AJ63: 4 | AK63: V1 | AL63: 20260909 | AM63: D825-900006667-67248016-10211341-4
A64: 900006667D8256724801610210657 | B64: 4600069592-60 | C64: 4600069592 | D64: 60 | E64: MXPO | F64: MXL | G64: 900006667 | H64: SF TP-ED TRITURADOS ROCA | I64: 5078620 | J64: TRITURADOS ROCA DE BC SA DE CV | K64: N90 | L64: (AP) NAFIN 90 Dias | M64: 10210657 | N64: GRAVA TRITURADA BASALTO 20 MM - 3/4" | O64: D825 | P64: MX-CED. GOLFO DE CALIFORNIA | Q64: 20240527 | R64: 20291231 | S64: 20260410 | T64: 20301231 | U64: 248 | V64: MXN | W64: TN | X64: 30 | Y64: MXN | Z64: TN | AA64: 67248016 | AB64: CONCRETOS TYG MONTE VERDE | AC64: 56103637 | AD64: 6622151540 | AE64: 4 | AF64: ENTREGA DIRECTA | AG64: 1 | AH64: TO | AI64: X | AJ64: 4 | AK64: V1 | AL64: 20260414 | AM64: D825-900006667-67248016-10210657-4
A65: 900006875D82510000191 | B65: 4600048797-20 | C65: 4600048797 | D65: 20 | E65: MXPO | F65: MXL | G65: 900006875 | H65: SF TP-REC-LO INFRA EL REFUGIO | I65: 5078800 | J65: LO INFRAESTRUCTURA S DE RL DE CV | K65: N30 | L65: (AP) NAFIN 30 Dias | M65: 10000191 | N65: Grava Triturada Basalto 20 mm - 3/4" | O65: D825 | P65: MX-CED. GOLFO DE CALIFORNIA | Q65: 20210106 | R65: 20291231 | S65: 20210106 | T65: 20291231 | U65: 200 | V65: MXN | W65: M3 | AC65: 56103637 | AD65: 6622151540 | AE65: 2 | AF65: RECOGIDO | AG65: 1.41 | AH65: M3 | AI65: X | AJ65: 4 | AK65: V4 | AL65: 20230920 | AM65: D825-900006875-10000191
A66: 900006873D82510141571 | B66: 4600048798-30 | C66: 4600048798 | D66: 30 | E66: MXPO | F66: MXL | G66: 900006873 | H66: SF TP-LO INFRA EL REFUGIO | I66: 5078800 | J66: LO INFRAESTRUCTURA S DE RL DE CV | K66: N30 | L66: (AP) NAFIN 30 Dias | M66: 10141571 | N66: POLVO TRITURADO BASALTO | O66: D825 | P66: MX-CED. GOLFO DE CALIFORNIA | Q66: 20210106 | R66: 20291231 | S66: 20210106 | T66: 20291231 | U66: 105 | V66: MXN | W66: M3 | AC66: 56103638 | AD66: 6622151540 | AE66: 1 | AF66: ENTREGADO | AG66: 1.34 | AH66: M3 | AI66: X | AJ66: 4 | AK66: V4 | AL66: 20230920 | AM66: D825-900006873-10141571
A67: 900007329D8256698692410179731 | B67: 4600052082-60 | C67: 4600052082 | D67: 60 | E67: MXPO | F67: MXL | G67: 900007329 | H67: SF TP-ED APR | I67: 5081100 | J67: APR OBRAS Y AGREGADOS S DE RL DE CV | K67: N90 | L67: (AP) NAFIN 90 Dias | M67: 10179731 | N67: BASE H TRITURADA BASALTO 1 1/2" A FINOS | O67: D825 | P67: MX-CED. GOLFO DE CALIFORNIA | Q67: 20211001 | R67: 20271231 | U67: 321 | V67: MXN | W67: M3 | AA67: 66986924 | AB67: AY CALLE PADRE KINO SALVATIERRA(LHC | AC67: 56103590 | AD67: 6622151540 | AE67: 4 | AF67: ENTREGA DIRECTA | AG67: 1.619 | AH67: M3 | AI67: X | AJ67: 4 | AK67: V4 | AL67: 20230920 | AM67: D825-900007329-66986924-10179731-4
A68: 900007329D8256694820810125120 | B68: 4600052082-50 | C68: 4600052082 | D68: 50 | E68: MXPO | F68: MXL | G68: 900007329 | H68: SF TP-ED APR | I68: 5081100 | J68: APR OBRAS Y AGREGADOS S DE RL DE CV | K68: N90 | L68: (AP) NAFIN 90 Dias | M68: 10125120 | N68: GRAVA TRITURADA BASALTO 20 MM (3/4") | O68: D825 | P68: MX-CED. GOLFO DE CALIFORNIA | Q68: 20211001 | R68: 20271231 | U68: 305 | V68: MXN | W68: M3 | AA68: 66948208 | AB68: NEP-AIT Aeropuerto Tijuana | AC68: 56103637 | AD68: 6622151540 | AE68: 4 | AF68: ENTREGA DIRECTA | AG68: 1.402 | AH68: M3 | AI68: X | AJ68: 4 | AK68: V4 | AL68: 20230920 | AM68: D825-900007329-66948208-10125120-4
A69: 900007329D8256665524310139747 | B69: 4600052082-20 | C69: 4600052082 | D69: 20 | E69: MXPO | F69: MXL | G69: 900007329 | H69: SF TP-ED APR | I69: 5081100 | J69: APR OBRAS Y AGREGADOS S DE RL DE CV | K69: N90 | L69: (AP) NAFIN 90 Dias | M69: 10139747 | N69: ARENA CLASIFICADA RIO MALLA 4 | O69: D825 | P69: MX-CED. GOLFO DE CALIFORNIA | Q69: 20211001 | R69: 20271231 | U69: 253 | V69: MXN | W69: M3 | AA69: 66655243 | AB69: I8 CONCRETOS T Y G PLANTA LA PRESA | AC69: 56103638 | AD69: 6622151540 | AE69: 4 | AF69: ENTREGA DIRECTA | AG69: 1.45 | AH69: M3 | AI69: X | AJ69: 4 | AK69: V4 | AL69: 20230920 | AM69: D825-900007329-66655243-10139747-4
A70: 900006875D82510141571 | B70: 4600048797-30 | C70: 4600048797 | D70: 30 | E70: MXPO | F70: MXL | G70: 900006875 | H70: SF TP-REC-LO INFRA EL REFUGIO | I70: 5078800 | J70: LO INFRAESTRUCTURA S DE RL DE CV | K70: N30 | L70: (AP) NAFIN 30 Dias | M70: 10141571 | N70: POLVO TRITURADO BASALTO | O70: D825 | P70: MX-CED. GOLFO DE CALIFORNIA | Q70: 20210106 | R70: 20291231 | S70: 20210106 | T70: 20291231 | U70: 105 | V70: MXN | W70: M3 | AC70: 56103638 | AD70: 6622151540 | AE70: 2 | AF70: RECOGIDO | AG70: 1.34 | AH70: M3 | AI70: X | AJ70: 4 | AK70: V4 | AL70: 20230920 | AM70: D825-900006875-10141571
A71: 900007010D82510139747 | B71: 4600049097-10 | C71: 4600049097 | D71: 10 | E71: MXPO | F71: MXL | G71: 900007010 | H71: SF TP-RECOGIDO SEXTIN | I71: 5042038 | J71: CONSTRUCTORA SEXTIN SA DE CV | K71: N120 | L71: (AP) NAFIN 120 Dias | M71: 10139747 | N71: ARENA CLASIFICADA RIO MALLA 4 | O71: D825 | P71: MX-CED. GOLFO DE CALIFORNIA | Q71: 20210202 | R71: 20291231 | S71: 20210202 | T71: 20291231 | U71: 120 | V71: MXN | W71: M3 | AC71: 56103638 | AD71: 6622151540 | AE71: 2 | AF71: RECOGIDO | AG71: 1.45 | AH71: M3 | AI71: X | AJ71: 4 | AK71: V1 | AL71: 20230920 | AM71: D825-900007010-10139747
A72: 900006668D82510274601 | B72: 4600069795-40 | C72: 4600069795 | D72: 40 | E72: MXPO | F72: MXL | G72: 900006668 | H72: SF TP-TRIT. ROCA | I72: 5078620 | J72: TRITURADOS ROCA DE BC SA DE CV | K72: N90 | L72: (AP) NAFIN 90 Dias | M72: 10274601 | N72: MP ARENA BASALTO N° 4 | O72: D825 | P72: MX-CED. GOLFO DE CALIFORNIA | Q72: 20240701 | R72: 20291231 | S72: 20260213 | T72: 20301231 | U72: 123 | V72: MXN | W72: TN | X72: 0 | Y72: MXN | Z72: TN | AC72: 56103638 | AD72: 6622151540 | AE72: 1 | AF72: ENTREGADO | AG72: 1 | AH72: TO | AI72: X | AJ72: 4 | AK72: V1 | AL72: 20260313 | AM72: D825-900006668-10274601
A73: 900007929D82510139747 | B73: 4600056023-10 | C73: 4600056023 | D73: 10 | E73: MXPO | F73: MXL | G73: 900007929 | H73: SF TP-REC LUGA-OLGUIN | I73: 5087532 | J73: LUGA AUTO TRANSPORTES SA DE CV | K73: N90 | L73: (AP) NAFIN 90 Dias | M73: 10139747 | N73: ARENA CLASIFICADA RIO MALLA 4 | O73: D825 | P73: MX-CED. GOLFO DE CALIFORNIA | Q73: 20221221 | R73: 20291231 | S73: 20260414 | T73: 20301231 | U73: 185 | V73: MXN | W73: M3 | X73: 0 | Y73: MXN | Z73: M3 | AC73: 56103638 | AD73: 6622151540 | AE73: 1 | AF73: ENTREGADO | AG73: 1.45 | AH73: M3 | AI73: X | AJ73: 4 | AK73: V4 | AL73: 20260417 | AM73: D825-900007929-10139747
A74: 900005281D8256728505310052400 | B74: 4600038431-180 | C74: 4600038431 | D74: 180 | E74: MXPO | F74: MXL | G74: 900005281 | H74: TP- ED PETREOS LA PURISIMA | I74: 5011228 | J74: PETREOS LA PURISIMA SA DE CV | K74: N90 | L74: (AP) NAFIN 90 Dias | M74: 10052400 | N74: Arena Clasificada Río Malla 4 - Lavado | O74: D825 | P74: MX-CED. GOLFO DE CALIFORNIA | Q74: 20170616 | R74: 20291231 | S74: 20240926 | T74: 20291231 | U74: 436.34 | V74: MXN | W74: M3 | X74: 210 | Y74: MXN | Z74: M3 | AA74: 67285053 | AB74: DC CONCRETOS PLANTA AEROPUERTO | AC74: 56103638 | AD74: 6622151867 | AE74: 4 | AF74: ENTREGA DIRECTA | AG74: 1.655 | AH74: M3 | AI74: X | AJ74: 4 | AK74: V4 | AL74: 20241004 | AM74: D825-900005281-67285053-10052400-4
A75: 900007935D8256728505310139747 | B75: 4600057825-110 | C75: 4600057825 | D75: 110 | E75: MXPO | F75: MXL | G75: 900007935 | H75: SF TP-ED LUGA-OLGUIN | I75: 5087532 | J75: LUGA AUTO TRANSPORTES SA DE CV | K75: N90 | L75: (AP) NAFIN 90 Dias | M75: 10139747 | N75: ARENA CLASIFICADA RIO MALLA 4 | O75: D825 | P75: MX-CED. GOLFO DE CALIFORNIA | Q75: 20230619 | R75: 20291231 | S75: 20240926 | T75: 20291231 | U75: 382 | V75: MXN | W75: M3 | X75: 176 | Y75: MXN | Z75: M3 | AA75: 67285053 | AB75: DC CONCRETOS PLANTA AEROPUERTO | AC75: 56103638 | AD75: 6622151540 | AE75: 4 | AF75: ENTREGA DIRECTA | AG75: 1.45 | AH75: M3 | AI75: X | AJ75: 4 | AK75: V4 | AL75: 20240929 | AM75: D825-900007935-67285053-10139747-4
A76: 900007329D8256694820810139747 | B76: 4600052082-40 | C76: 4600052082 | D76: 40 | E76: MXPO | F76: MXL | G76: 900007329 | H76: SF TP-ED APR | I76: 5081100 | J76: APR OBRAS Y AGREGADOS S DE RL DE CV | K76: N90 | L76: (AP) NAFIN 90 Dias | M76: 10139747 | N76: ARENA CLASIFICADA RIO MALLA 4 | O76: D825 | P76: MX-CED. GOLFO DE CALIFORNIA | Q76: 20211001 | R76: 20271231 | U76: 275 | V76: MXN | W76: M3 | AA76: 66948208 | AB76: NEP-AIT Aeropuerto Tijuana | AC76: 56103638 | AD76: 6622151540 | AE76: 4 | AF76: ENTREGA DIRECTA | AG76: 1.45 | AH76: M3 | AI76: X | AJ76: 4 | AK76: V4 | AL76: 20230920 | AM76: D825-900007329-66948208-10139747-4
A77: 900007329D8256698692710152920 | B77: 4600052082-70 | C77: 4600052082 | D77: 70 | E77: MXPO | F77: MXL | G77: 900007329 | H77: SF TP-ED APR | I77: 5081100 | J77: APR OBRAS Y AGREGADOS S DE RL DE CV | K77: N90 | L77: (AP) NAFIN 90 Dias | M77: 10152920 | N77: POLVO TRITURADO GRANITO | O77: D825 | P77: MX-CED. GOLFO DE CALIFORNIA | Q77: 20211001 | R77: 20271231 | U77: 180 | V77: MXN | W77: M3 | AA77: 66986927 | AB77: AY CALLE LA PNDEROSA (LHCB) | AC77: 56103591 | AD77: 6622151540 | AE77: 4 | AF77: ENTREGA DIRECTA | AG77: 1.615 | AH77: M3 | AI77: X | AJ77: 4 | AK77: V4 | AL77: 20230920 | AM77: D825-900007329-66986927-10152920-4
A78: 900006894D82510152920 | B78: 4600050843-20 | C78: 4600050843 | D78: 20 | E78: MXPO | F78: MXL | G78: 900006894 | H78: SF TP-RECOGIDO TRAZO | I78: 5078812 | J78: TRAZO DEL NORESTE SRL DE CV | K78: N90 | L78: (AP) NAFIN 90 Dias | M78: 10152920 | N78: POLVO TRITURADO GRANITO | O78: D825 | P78: MX-CED. GOLFO DE CALIFORNIA | Q78: 20210716 | R78: 20261231 | S78: 20210814 | T78: 20251231 | U78: 40 | V78: MXN | W78: M3 | AC78: 56103591 | AD78: 6622151540 | AE78: 2 | AF78: RECOGIDO | AG78: 1.615 | AH78: M3 | AI78: X | AJ78: 4 | AK78: V4 | AL78: 20230920 | AM78: D825-900006894-10152920
A79: 900000651D82510139747 | B79: 4600047841-10 | C79: 4600047841 | D79: 10 | E79: MXPO | F79: MXL | G79: 900000651 | H79: SF TP PETREOS LA PURISIMA | I79: 5011228 | J79: PETREOS LA PURISIMA SA DE CV | K79: N90 | L79: (AP) NAFIN 90 Dias | M79: 10139747 | N79: ARENA CLASIFICADA RIO MALLA 4 | O79: D825 | P79: MX-CED. GOLFO DE CALIFORNIA | Q79: 20200824 | R79: 20261231 | S79: 20210304 | T79: 20251231 | U79: 124.5 | V79: MXN | W79: M3 | AC79: 56103638 | AD79: 6622151540 | AE79: 1 | AF79: ENTREGADO | AG79: 1.45 | AH79: M3 | AI79: X | AJ79: 4 | AK79: V4 | AL79: 20230920 | AM79: D825-900000651-10139747
A80: 900006667D8256665039310211341 | B80: 4600069592-220 | C80: 4600069592 | D80: 220 | E80: MXPO | F80: MXL | G80: 900006667 | H80: SF TP-ED TRITURADOS ROCA | I80: 5078620 | J80: TRITURADOS ROCA DE BC SA DE CV | K80: N90 | L80: (AP) NAFIN 90 Dias | M80: 10211341 | N80: GRAVA TRITURADA BASALTO 10 MM - 3/8" | O80: D825 | P80: MX-CED. GOLFO DE CALIFORNIA | Q80: 20240527 | R80: 20291231 | S80: 20260904 | T80: 20301231 | U80: 357 | V80: MXN | W80: TN | X80: 45 | Y80: MXN | Z80: TN | AA80: 66650393 | AB80: I8 PLANTA DE CONCRETO (MAC) | AC80: 56103637 | AD80: 6622151867 | AE80: 4 | AF80: ENTREGA DIRECTA | AG80: 1 | AH80: TO | AI80: X | AJ80: 4 | AK80: V4 | AL80: 20260909 | AM80: D825-900006667-66650393-10211341-4
A81: 900006667D8256665039310274601 | B81: 4600069592-200 | C81: 4600069592 | D81: 200 | E81: MXPO | F81: MXL | G81: 900006667 | H81: SF TP-ED TRITURADOS ROCA | I81: 5078620 | J81: TRITURADOS ROCA DE BC SA DE CV | K81: N90 | L81: (AP) NAFIN 90 Dias | M81: 10274601 | N81: MP ARENA BASALTO N° 4 | O81: D825 | P81: MX-CED. GOLFO DE CALIFORNIA | Q81: 20240527 | R81: 20291231 | S81: 20260904 | T81: 20301231 | U81: 168 | V81: MXN | W81: TN | X81: 45 | Y81: MXN | Z81: TN | AA81: 66650393 | AB81: I8 PLANTA DE CONCRETO (MAC) | AC81: 56103638 | AD81: 6622151540 | AE81: 4 | AF81: ENTREGA DIRECTA | AG81: 1 | AH81: TO | AI81: X | AJ81: 4 | AK81: V4 | AL81: 20260909 | AM81: D825-900006667-66650393-10274601-4
A82: 900006667D8256665039310210657 | B82: 4600069592-190 | C82: 4600069592 | D82: 190 | E82: MXPO | F82: MXL | G82: 900006667 | H82: SF TP-ED TRITURADOS ROCA | I82: 5078620 | J82: TRITURADOS ROCA DE BC SA DE CV | K82: N90 | L82: (AP) NAFIN 90 Dias | M82: 10210657 | N82: GRAVA TRITURADA BASALTO 20 MM - 3/4" | O82: D825 | P82: MX-CED. GOLFO DE CALIFORNIA | Q82: 20240527 | R82: 20291231 | S82: 20260904 | T82: 20301231 | U82: 263 | V82: MXN | W82: TN | X82: 45 | Y82: MXN | Z82: TN | AA82: 66650393 | AB82: I8 PLANTA DE CONCRETO (MAC) | AC82: 56103637 | AD82: 6622151540 | AE82: 4 | AF82: ENTREGA DIRECTA | AG82: 1 | AH82: TO | AI82: X | AJ82: 4 | AK82: V4 | AL82: 20260909 | AM82: D825-900006667-66650393-10210657-4
A83: 900006667D8256665039310275058 | B83: 4600069592-210 | C83: 4600069592 | D83: 210 | E83: MXPO | F83: MXL | G83: 900006667 | H83: SF TP-ED TRITURADOS ROCA | I83: 5078620 | J83: TRITURADOS ROCA DE BC SA DE CV | K83: N90 | L83: (AP) NAFIN 90 Dias | M83: 10275058 | N83: MP GRAVA TRIT. BASALTO 40-4MM - 1 1/2" | O83: D825 | P83: MX-CED. GOLFO DE CALIFORNIA | Q83: 20240527 | R83: 20291231 | S83: 20260904 | T83: 20301231 | U83: 263 | V83: MXN | W83: TN | X83: 45 | Y83: MXN | Z83: TN | AA83: 66650393 | AB83: I8 PLANTA DE CONCRETO (MAC) | AC83: 56103637 | AD83: 6622151540 | AE83: 4 | AF83: ENTREGA DIRECTA | AG83: 1 | AH83: TO | AI83: X | AJ83: 4 | AK83: V4 | AL83: 20260909 | AM83: D825-900006667-66650393-10275058-4
A84: 900005281D8256731818310052400 | B84: 4600038431-190 | C84: 4600038431 | D84: 190 | E84: MXPO | F84: MXL | G84: 900005281 | H84: TP- ED PETREOS LA PURISIMA | I84: 5011228 | J84: PETREOS LA PURISIMA SA DE CV | K84: N90 | L84: (AP) NAFIN 90 Dias | M84: 10052400 | N84: Arena Clasificada Río Malla 4 - Lavado | O84: D825 | P84: MX-CED. GOLFO DE CALIFORNIA | Q84: 20170616 | R84: 20291231 | S84: 20250512 | T84: 20301231 | U84: 446.34 | V84: MXN | W84: M3 | X84: 220 | Y84: MXN | Z84: M3 | AA84: 67318183 | AB84: DC CONCRETOS PLAYAS DE TIJUANA | AC84: 56103638 | AD84: 6622151867 | AE84: 4 | AF84: ENTREGA DIRECTA | AG84: 1.655 | AH84: M3 | AI84: X | AJ84: 4 | AK84: V4 | AL84: 20250604 | AM84: D825-900005281-67318183-10052400-4
A85: 900005281D8256722980710052400 | B85: 4600038431-170 | C85: 4600038431 | D85: 170 | E85: MXPO | F85: MXL | G85: 900005281 | H85: TP- ED PETREOS LA PURISIMA | I85: 5011228 | J85: PETREOS LA PURISIMA SA DE CV | K85: N90 | L85: (AP) NAFIN 90 Dias | M85: 10052400 | N85: Arena Clasificada Río Malla 4 - Lavado | O85: D825 | P85: MX-CED. GOLFO DE CALIFORNIA | Q85: 20170616 | R85: 20291231 | S85: 20240902 | T85: 20291231 | U85: 476.34 | V85: MXN | W85: M3 | X85: 250 | Y85: MXN | Z85: M3 | AA85: 67229807 | AB85: DC CONCRETOS CAÑON DEL MATADERO | AC85: 56103638 | AD85: 6622151867 | AE85: 4 | AF85: ENTREGA DIRECTA | AG85: 1.655 | AH85: M3 | AI85: X | AJ85: 4 | AK85: V4 | AL85: 20240910 | AM85: D825-900005281-67229807-10052400-4
A86: 900006894D82510179731 | B86: 4600050843-10 | C86: 4600050843 | D86: 10 | E86: MXPO | F86: MXL | G86: 900006894 | H86: SF TP-RECOGIDO TRAZO | I86: 5078812 | J86: TRAZO DEL NORESTE SRL DE CV | K86: N90 | L86: (AP) NAFIN 90 Dias | M86: 10179731 | N86: BASE H TRITURADA BASALTO 1 1/2" A FINOS | O86: D825 | P86: MX-CED. GOLFO DE CALIFORNIA | Q86: 20210716 | R86: 20261231 | S86: 20210716 | T86: 20251231 | U86: 143 | V86: MXN | W86: M3 | AC86: 56103590 | AD86: 6622151540 | AE86: 2 | AF86: RECOGIDO | AG86: 1.619 | AH86: M3 | AI86: X | AJ86: 4 | AK86: V4 | AL86: 20230920 | AM86: D825-900006894-10179731
A87: 900006875D82510141572 | B87: 4600048797-10 | C87: 4600048797 | D87: 10 | E87: MXPO | F87: MXL | G87: 900006875 | H87: SF TP-REC-LO INFRA EL REFUGIO | I87: 5078800 | J87: LO INFRAESTRUCTURA S DE RL DE CV | K87: N30 | L87: (AP) NAFIN 30 Dias | M87: 10141572 | N87: GRAVA TRITURADA BASALTO 10 MM - 3/8" | O87: D825 | P87: MX-CED. GOLFO DE CALIFORNIA | Q87: 20210106 | R87: 20291231 | S87: 20200909 | T87: 20251231 | U87: 250 | V87: MXN | W87: M3 | AC87: 56103637 | AD87: 6622151540 | AE87: 2 | AF87: RECOGIDO | AG87: 1.3 | AH87: M3 | AI87: X | AJ87: 4 | AK87: V4 | AL87: 20230920 | AM87: D825-900006875-10141572
A88: 900004527D82510179731 | B88: 4600033292-150 | C88: 4600033292 | D88: 150 | E88: MXPO | F88: MXL | G88: 900004527 | H88: TP- GUSA | I88: 5002503 | J88: CONSTRUCTORA GUSA SA DE CV | K88: Z03 | L88: (AP) 15 Dias | M88: 10179731 | N88: BASE H TRITURADA BASALTO 1 1/2" A FINOS | O88: D825 | P88: MX-CED. GOLFO DE CALIFORNIA | Q88: 20160301 | R88: 20281231 | S88: 20240521 | T88: 20291231 | U88: 190.58 | V88: MXN | W88: M3 | X88: 0 | Y88: MXN | Z88: M3 | AC88: 56103590 | AD88: 6622151540 | AE88: 1 | AF88: ENTREGADO | AG88: 1.619 | AH88: M3 | AI88: X | AJ88: 4 | AK88: V1 | AL88: 20240524 | AM88: D825-900004527-10179731
A89: 900007935D8256702277910139747 | B89: 4600057825-120 | C89: 4600057825 | D89: 120 | E89: MXPO | F89: MXL | G89: 900007935 | H89: SF TP-ED LUGA-OLGUIN | I89: 5087532 | J89: LUGA AUTO TRANSPORTES SA DE CV | K89: N90 | L89: (AP) NAFIN 90 Dias | M89: 10139747 | N89: ARENA CLASIFICADA RIO MALLA 4 | O89: D825 | P89: MX-CED. GOLFO DE CALIFORNIA | Q89: 20230619 | R89: 20291231 | S89: 20241016 | T89: 20291231 | U89: 277 | V89: MXN | W89: M3 | X89: 71 | Y89: MXN | Z89: M3 | AA89: 67022779 | AB89: SOLIDBLOCK SA DE CV | AC89: 56103638 | AD89: 6622151540 | AE89: 4 | AF89: ENTREGA DIRECTA | AG89: 1.45 | AH89: M3 | AI89: X | AJ89: 4 | AK89: V4 | AL89: 20241018 | AM89: D825-900007935-67022779-10139747-4
A90: 900007935D8256724558910139747 | B90: 4600057825-100 | C90: 4600057825 | D90: 100 | E90: MXPO | F90: MXL | G90: 900007935 | H90: SF TP-ED LUGA-OLGUIN | I90: 5087532 | J90: LUGA AUTO TRANSPORTES SA DE CV | K90: N90 | L90: (AP) NAFIN 90 Dias | M90: 10139747 | N90: ARENA CLASIFICADA RIO MALLA 4 | O90: D825 | P90: MX-CED. GOLFO DE CALIFORNIA | Q90: 20230619 | R90: 20291231 | S90: 20240729 | T90: 20291231 | U90: 451 | V90: MXN | W90: M3 | X90: 245 | Y90: MXN | Z90: M3 | AA90: 67245589 | AB90: DC CONCRETOS PTAR | AC90: 56103638 | AD90: 6622151540 | AE90: 4 | AF90: ENTREGA DIRECTA | AG90: 1.45 | AH90: M3 | AI90: X | AJ90: 4 | AK90: V4 | AL90: 20250402 | AM90: D825-900007935-67245589-10139747-4
A91: 900007329D8256665012610139747 | B91: 4600052082-30 | C91: 4600052082 | D91: 30 | E91: MXPO | F91: MXL | G91: 900007329 | H91: SF TP-ED APR | I91: 5081100 | J91: APR OBRAS Y AGREGADOS S DE RL DE CV | K91: N90 | L91: (AP) NAFIN 90 Dias | M91: 10139747 | N91: ARENA CLASIFICADA RIO MALLA 4 | O91: D825 | P91: MX-CED. GOLFO DE CALIFORNIA | Q91: 20211001 | R91: 20271231 | U91: 275 | V91: MXN | W91: M3 | AA91: 66650126 | AB91: I8 CONCRETOS T Y G SA DE CV | AC91: 56103638 | AD91: 6622151540 | AE91: 4 | AF91: ENTREGA DIRECTA | AG91: 1.45 | AH91: M3 | AI91: X | AJ91: 4 | AK91: V4 | AL91: 20230920 | AM91: D825-900007329-66650126-10139747-4
A92: 900007763D82510211341 | B92: 4600055086-30 | C92: 4600055086 | D92: 30 | E92: MXPO | F92: MXL | G92: 900007763 | H92: SF TP-REC VTA CRUZADA OLGUIN | I92: 5082449 | J92: TORRES ALANIS MIGUEL ANGEL | K92: E90 | L92: (AP) E-FACTOR 90 Dias | M92: 10211341 | N92: GRAVA TRITURADA BASALTO 10 MM - 3/8" | O92: D825 | P92: MX-CED. GOLFO DE CALIFORNIA | Q92: 20220903 | R92: 20271231 | S92: 20220903 | T92: 20271231 | U92: 385 | V92: MXN | W92: M3 | X92: 0 | Y92: MXN | Z92: M3 | AC92: 56103637 | AD92: 6622151867 | AE92: 2 | AF92: RECOGIDO | AG92: 1.21 | AH92: M3 | AI92: X | AJ92: 4 | AK92: V4 | AL92: 20230920 | AM92: D825-900007763-10211341
A93: 900007831D82510152920 | B93: 4600055146-10 | C93: 4600055146 | D93: 10 | E93: MXPO | F93: MXL | G93: 900007831 | H93: SF TP-REC-URB Y PAV BC | I93: 5066533 | J93: URBANIZADO Y PAVIMENTACION | K93: Z09 | L93: (AP) 90 Dias | M93: 10152920 | N93: POLVO TRITURADO GRANITO | O93: D825 | P93: MX-CED. GOLFO DE CALIFORNIA | Q93: 20220903 | R93: 20271231 | S93: 20220903 | T93: 20271231 | U93: 55 | V93: MXN | W93: M3 | X93: 0 | Y93: MXN | Z93: M3 | AC93: 56103591 | AD93: 6622151540 | AE93: 2 | AF93: RECOGIDO | AG93: 1.615 | AH93: M3 | AI93: X | AJ93: 4 | AK93: V1 | AL93: 20230920 | AM93: D825-900007831-10152920
A94: 900007763D82510139747 | B94: 4600055086-10 | C94: 4600055086 | D94: 10 | E94: MXPO | F94: MXL | G94: 900007763 | H94: SF TP-REC VTA CRUZADA OLGUIN | I94: 5082449 | J94: TORRES ALANIS MIGUEL ANGEL | K94: E90 | L94: (AP) E-FACTOR 90 Dias | M94: 10139747 | N94: ARENA CLASIFICADA RIO MALLA 4 | O94: D825 | P94: MX-CED. GOLFO DE CALIFORNIA | Q94: 20220903 | R94: 20271231 | S94: 20220903 | T94: 20271231 | U94: 331 | V94: MXN | W94: M3 | X94: 0 | Y94: MXN | Z94: M3 | AC94: 56103638 | AD94: 6622151540 | AE94: 2 | AF94: RECOGIDO | AG94: 1.45 | AH94: M3 | AI94: X | AJ94: 4 | AK94: V4 | AL94: 20230920 | AM94: D825-900007763-10139747
A95: 900007763D82510052400 | B95: 4600055086-20 | C95: 4600055086 | D95: 20 | E95: MXPO | F95: MXL | G95: 900007763 | H95: SF TP-REC VTA CRUZADA OLGUIN | I95: 5082449 | J95: TORRES ALANIS MIGUEL ANGEL | K95: E90 | L95: (AP) E-FACTOR 90 Dias | M95: 10052400 | N95: Arena Clasificada Río Malla 4 - Lavado | O95: D825 | P95: MX-CED. GOLFO DE CALIFORNIA | Q95: 20220903 | R95: 20271231 | S95: 20220903 | T95: 20271231 | U95: 370 | V95: MXN | W95: M3 | X95: 0 | Y95: MXN | Z95: M3 | AC95: 56103638 | AD95: 6622151867 | AE95: 2 | AF95: RECOGIDO | AG95: 1.655 | AH95: M3 | AI95: X | AJ95: 4 | AK95: V4 | AL95: 20230920 | AM95: D825-900007763-10052400
A96: 900007935D8256665032610139747 | B96: 4600057825-40 | C96: 4600057825 | D96: 40 | E96: MXPO | F96: MXL | G96: 900007935 | H96: SF TP-ED LUGA-OLGUIN | I96: 5087532 | J96: LUGA AUTO TRANSPORTES SA DE CV | K96: N90 | L96: (AP) NAFIN 90 Dias | M96: 10139747 | N96: ARENA CLASIFICADA RIO MALLA 4 | O96: D825 | P96: MX-CED. GOLFO DE CALIFORNIA | Q96: 20230619 | R96: 20291231 | S96: 20240510 | T96: 20291231 | U96: 331 | V96: MXN | W96: M3 | X96: 125 | Y96: MXN | Z96: M3 | AA96: 66650326 | AB96: I8 FRACC. PUERTA PLATA | AC96: 56103638 | AD96: 6622151540 | AE96: 4 | AF96: ENTREGA DIRECTA | AG96: 1.45 | AH96: M3 | AI96: X | AJ96: 4 | AK96: V4 | AL96: 20250402 | AM96: D825-900007935-66650326-10139747-4
A97: 900007937D82510139747 | B97: 4600057824-20 | C97: 4600057824 | D97: 20 | E97: MXPO | F97: MXL | G97: 900007937 | H97: SF TP-REC VTA LUGA-OLGUIN | I97: 5087532 | J97: LUGA AUTO TRANSPORTES SA DE CV | K97: N90 | L97: (AP) NAFIN 90 Dias | M97: 10139747 | N97: ARENA CLASIFICADA RIO MALLA 4 | O97: D825 | P97: MX-CED. GOLFO DE CALIFORNIA | Q97: 20230621 | R97: 20281231 | S97: 20230621 | T97: 20281231 | U97: 331 | V97: MXN | W97: M3 | X97: 0 | Y97: MXN | Z97: M3 | AC97: 56103638 | AD97: 6622151540 | AE97: 1 | AF97: ENTREGADO | AG97: 1.45 | AH97: M3 | AI97: X | AJ97: 4 | AK97: V4 | AL97: 20250402 | AM97: D825-900007937-10139747
A98: 900007937D82510052400 | B98: 4600057824-10 | C98: 4600057824 | D98: 10 | E98: MXPO | F98: MXL | G98: 900007937 | H98: SF TP-REC VTA LUGA-OLGUIN | I98: 5087532 | J98: LUGA AUTO TRANSPORTES SA DE CV | K98: N90 | L98: (AP) NAFIN 90 Dias | M98: 10052400 | N98: Arena Clasificada Río Malla 4 - Lavado | O98: D825 | P98: MX-CED. GOLFO DE CALIFORNIA | Q98: 20230621 | R98: 20281231 | S98: 20230621 | T98: 20281231 | U98: 370 | V98: MXN | W98: M3 | X98: 0 | Y98: MXN | Z98: M3 | AC98: 56103638 | AD98: 6622151867 | AE98: 1 | AF98: ENTREGADO | AG98: 1.655 | AH98: M3 | AI98: X | AJ98: 4 | AK98: V4 | AL98: 20250402 | AM98: D825-900007937-10052400
A99: 900007937D82510211341 | B99: 4600057824-30 | C99: 4600057824 | D99: 30 | E99: MXPO | F99: MXL | G99: 900007937 | H99: SF TP-REC VTA LUGA-OLGUIN | I99: 5087532 | J99: LUGA AUTO TRANSPORTES SA DE CV | K99: N90 | L99: (AP) NAFIN 90 Dias | M99: 10211341 | N99: GRAVA TRITURADA BASALTO 10 MM - 3/8" | O99: D825 | P99: MX-CED. GOLFO DE CALIFORNIA | Q99: 20230621 | R99: 20281231 | S99: 20230621 | T99: 20281231 | U99: 385 | V99: MXN | W99: M3 | X99: 0 | Y99: MXN | Z99: M3 | AC99: 56103637 | AD99: 6622151867 | AE99: 1 | AF99: ENTREGADO | AG99: 1.21 | AH99: M3 | AI99: X | AJ99: 4 | AK99: V4 | AL99: 20250402 | AM99: D825-900007937-10211341
A100: 900000651D82510001078 | B100: 4600047841-20 | C100: 4600047841 | D100: 20 | E100: MXPO | F100: MXL | G100: 900000651 | H100: SF TP PETREOS LA PURISIMA | I100: 5011228 | J100: PETREOS LA PURISIMA SA DE CV | K100: N90 | L100: (AP) NAFIN 90 Dias | M100: 10001078 | N100: Crudo Granito | O100: D825 | P100: MX-CED. GOLFO DE CALIFORNIA | Q100: 20200824 | R100: 20261231 | S100: 20221028 | T100: 20271231 | U100: 56.75 | V100: MXN | W100: M3 | X100: 0 | Y100: MXN | Z100: M3 | AC100: 56103636 | AD100: 6622151540 | AE100: 2 | AF100: RECOGIDO | AG100: 1.6 | AH100: M3 | AI100: X | AJ100: 4 | AK100: V4 | AL100: 20230920 | AM100: D825-900000651-10001078
A101: 900005249D82510141537 | B101: 4600042740-10 | C101: 4600042740 | D101: 10 | E101: MXPO | F101: MXL | G101: 900005249 | H101: TP- JL PROMOCION TEMPORAL | I101: 5066849 | J101: JL CONCRETOS Y AGREGADOS SR L DE CV | K101: Z09 | L101: (AP) 90 Dias | M101: 10141537 | N101: GRAVA TRITURADA BASALTO 40 MM - 1 1/2" | O101: D825 | P101: MX-CED. GOLFO DE CALIFORNIA | Q101: 20180808 | R101: 20281231 | S101: 20180808 | T101: 20241231 | U101: 104 | V101: MXN | W101: TN | X101: 0 | Y101: MXN | Z101: TN | AC101: 56103637 | AD101: 6622151540 | AE101: 1 | AF101: ENTREGADO | AG101: 1 | AH101: TO | AI101: X | AJ101: 4 | AK101: V1 | AL101: 20230920 | AM101: D825-900005249-10141537
A102: 900005249D82510141536 | B102: 4600042740-20 | C102: 4600042740 | D102: 20 | E102: MXPO | F102: MXL | G102: 900005249 | H102: TP- JL PROMOCION TEMPORAL | I102: 5066849 | J102: JL CONCRETOS Y AGREGADOS SR L DE CV | K102: Z09 | L102: (AP) 90 Dias | M102: 10141536 | N102: GRAVA TRITURADA BASALTO 20 MM - 3/4" | O102: D825 | P102: MX-CED. GOLFO DE CALIFORNIA | Q102: 20180808 | R102: 20281231 | S102: 20230426 | T102: 20281231 | U102: 191.48 | V102: MXN | W102: TN | X102: 0 | Y102: MXN | Z102: TN | AC102: 56103637 | AD102: 6622151540 | AE102: 1 | AF102: ENTREGADO | AG102: 1 | AH102: TO | AI102: X | AJ102: 4 | AK102: V1 | AL102: 20230920 | AM102: D825-900005249-10141536
A103: 900006891D8256694820810139747 | B103: 4600048585-40 | C103: 4600048585 | D103: 40 | E103: MXPO | F103: MXL | G103: 900006891 | H103: SF TP-ED-TRAZO | I103: 5078812 | J103: TRAZO DEL NORESTE SRL DE CV | K103: N90 | L103: (AP) NAFIN 90 Dias | M103: 10139747 | N103: ARENA CLASIFICADA RIO MALLA 4 | O103: D825 | P103: MX-CED. GOLFO DE CALIFORNIA | Q103: 20201203 | R103: 20291231 | S103: 20210517 | T103: 20251231 | U103: 275 | V103: MXN | W103: M3 | X103: 120 | Y103: MXN | Z103: M3 | AA103: 66948208 | AB103: NEP-AIT Aeropuerto Tijuana | AC103: 56103638 | AD103: 6622151540 | AE103: 4 | AF103: ENTREGA DIRECTA | AG103: 1.45 | AH103: M3 | AI103: X | AJ103: 4 | AK103: V4 | AL103: 20230920 | AM103: D825-900006891-66948208-10139747-4
A104: 900007935D8256715884310139747 | B104: 4600057825-20 | C104: 4600057825 | D104: 20 | E104: MXPO | F104: MXL | G104: 900007935 | H104: SF TP-ED LUGA-OLGUIN | I104: 5087532 | J104: LUGA AUTO TRANSPORTES SA DE CV | K104: N90 | L104: (AP) NAFIN 90 Dias | M104: 10139747 | N104: ARENA CLASIFICADA RIO MALLA 4 | O104: D825 | P104: MX-CED. GOLFO DE CALIFORNIA | Q104: 20230619 | R104: 20291231 | S104: 20230714 | T104: 20281231 | U104: 371 | V104: MXN | W104: M3 | X104: 180 | Y104: MXN | Z104: M3 | AA104: 67158843 | AB104: Concrejal | AC104: 56103638 | AD104: 6622151540 | AE104: 4 | AF104: ENTREGA DIRECTA | AG104: 1.45 | AH104: M3 | AI104: X | AJ104: 4 | AK104: V4 | AL104: 20250402 | AM104: D825-900007935-67158843-10139747-4
A105: 900007704D8256665032610139747 | B105: 4600054910-10 | C105: 4600054910 | D105: 10 | E105: MXPO | F105: MXL | G105: 900007704 | H105: SF TP- ED CEBREROS | I105: 5083830 | J105: CEBRERO AMADOR CHRISTIAN ARIEL | K105: Z09 | L105: (AP) 90 Dias | M105: 10139747 | N105: ARENA CLASIFICADA RIO MALLA 4 | O105: D825 | P105: MX-CED. GOLFO DE CALIFORNIA | Q105: 20220816 | R105: 20271231 | S105: 20220816 | T105: 20271231 | U105: 310 | V105: MXN | W105: M3 | X105: 50 | Y105: MXN | Z105: M3 | AA105: 66650326 | AB105: I8 FRACC. PUERTA PLATA | AC105: 56103638 | AD105: 6622151540 | AE105: 4 | AF105: ENTREGA DIRECTA | AG105: 1.45 | AH105: M3 | AI105: X | AJ105: 4 | AK105: V4 | AL105: 20230828 | AM105: D825-900007704-66650326-10139747-4
A106: 900006891D8256694820810125120 | B106: 4600048585-50 | C106: 4600048585 | D106: 50 | E106: MXPO | F106: MXL | G106: 900006891 | H106: SF TP-ED-TRAZO | I106: 5078812 | J106: TRAZO DEL NORESTE SRL DE CV | K106: N90 | L106: (AP) NAFIN 90 Dias | M106: 10125120 | N106: GRAVA TRITURADA BASALTO 20 MM (3/4") | O106: D825 | P106: MX-CED. GOLFO DE CALIFORNIA | Q106: 20201203 | R106: 20291231 | S106: 20210517 | T106: 20251231 | U106: 305 | V106: MXN | W106: M3 | X106: 120 | Y106: MXN | Z106: M3 | AA106: 66948208 | AB106: NEP-AIT Aeropuerto Tijuana | AC106: 56103637 | AD106: 6622151540 | AE106: 4 | AF106: ENTREGA DIRECTA | AG106: 1.402 | AH106: M3 | AI106: X | AJ106: 4 | AK106: V4 | AL106: 20230920 | AM106: D825-900006891-66948208-10125120-4
...
