Workbook

Sheet Base Cedis DW83
N1: VENTA | Q1: COSTO
A2: CONCAT1 | B2: CONCAT2 | C2: No. SF | D2: Nombre SF | E2: Cedis | F2: Destino | G2: Condicion de Expedicion | H2: Nombre Destino | I2: No. de material | J2: Nombre de material | K2: PV | L2: Inicio de vigencia | M2: Fin de vigencia | N2: Importe MP | O2: Importe Flete | P2: UM Venta | Q2: Importe Costo | R2: UM Costo | S2: Validacion 1 | T2: Validacion 2
A3: =CONCATENATE(C3,E3,F3,I3) | B3: =CONCATENATE(C3,E3,I3) | C3: 900000045 | D3: =IFERROR(VLOOKUP(C3,TRAOPE!$G:$H,2,0),"") | E3: DW83 | F3: D216 | G3: =IFERROR(VLOOKUP(A3,Flete!$A:$E,5,0),"") | H3: =IFERROR(VLOOKUP(F3,TRAOPE!$AA:$AB,2,0),"") | I3: 10000377 | J3: =IFERROR(VLOOKUP(I3,Materiales!$A:$H,8,0),"") | K3: =IFERROR(VLOOKUP(I3,Materiales!$A:$G,7,0),"") | L3: 20210620 | M3: 20251031 | N3: 107.59 | O3: =IFERROR(VLOOKUP(A3,Flete!$A:$J,10,0),"") | P3: TN | Q3: =IFERROR(IFERROR(VLOOKUP(A3,TRAOPE!$A:$U,21,0),VLOOKUP(B3,TRAOPE!$A:$U,21,0)),"") | R3: =IFERROR(IFERROR(VLOOKUP(A3,TRAOPE!$A:$W,23,0),VLOOKUP(B3,TRAOPE!$A:$W,23,0)),"") | S3: =IF(AND(P3="TN",R3="TN"),N3+N(O3),IF(G3&""="1",N(K3)*N3,(N3+N(O3))*N(K3))) | T3: =IF(Q3="","",Q3-S3)
A4: =CONCATENATE(C4,E4,F4,I4) | B4: =CONCATENATE(C4,E4,I4) | C4: 900000045 | D4: =IFERROR(VLOOKUP(C4,TRAOPE!$G:$H,2,0),"") | E4: DW83 | F4: D216 | G4: =IFERROR(VLOOKUP(A4,Flete!$A:$E,5,0),"") | H4: =IFERROR(VLOOKUP(F4,TRAOPE!$AA:$AB,2,0),"") | I4: 10000379 | J4: =IFERROR(VLOOKUP(I4,Materiales!$A:$H,8,0),"") | K4: =IFERROR(VLOOKUP(I4,Materiales!$A:$G,7,0),"") | L4: 20210620 | M4: 20251031 | N4: 119.23 | O4: =IFERROR(VLOOKUP(A4,Flete!$A:$J,10,0),"") | P4: TN | Q4: =IFERROR(IFERROR(VLOOKUP(A4,TRAOPE!$A:$U,21,0),VLOOKUP(B4,TRAOPE!$A:$U,21,0)),"") | R4: =IFERROR(IFERROR(VLOOKUP(A4,TRAOPE!$A:$W,23,0),VLOOKUP(B4,TRAOPE!$A:$W,23,0)),"") | S4: =IF(AND(P4="TN",R4="TN"),N4+N(O4),IF(G4&""="1",N(K4)*N4,(N4+N(O4))*N(K4))) | T4: =IF(Q4="","",Q4-S4)
A5: =CONCATENATE(C5,E5,F5,I5) | B5: =CONCATENATE(C5,E5,I5) | C5: 900000045 | D5: =IFERROR(VLOOKUP(C5,TRAOPE!$G:$H,2,0),"") | E5: DW83 | F5: D216 | G5: =IFERROR(VLOOKUP(A5,Flete!$A:$E,5,0),"") | H5: =IFERROR(VLOOKUP(F5,TRAOPE!$AA:$AB,2,0),"") | I5: 10000381 | J5: =IFERROR(VLOOKUP(I5,Materiales!$A:$H,8,0),"") | K5: =IFERROR(VLOOKUP(I5,Materiales!$A:$G,7,0),"") | L5: 20210620 | M5: 20251031 | N5: 69.97 | O5: =IFERROR(VLOOKUP(A5,Flete!$A:$J,10,0),"") | P5: TN | Q5: =IFERROR(IFERROR(VLOOKUP(A5,TRAOPE!$A:$U,21,0),VLOOKUP(B5,TRAOPE!$A:$U,21,0)),"") | R5: =IFERROR(IFERROR(VLOOKUP(A5,TRAOPE!$A:$W,23,0),VLOOKUP(B5,TRAOPE!$A:$W,23,0)),"") | S5: =IF(AND(P5="TN",R5="TN"),N5+N(O5),IF(G5&""="1",N(K5)*N5,(N5+N(O5))*N(K5))) | T5: =IF(Q5="","",Q5-S5)
A6: =CONCATENATE(C6,E6,F6,I6) | B6: =CONCATENATE(C6,E6,I6) | C6: 900000045 | D6: =IFERROR(VLOOKUP(C6,TRAOPE!$G:$H,2,0),"") | E6: DW83 | F6: D216 | G6: =IFERROR(VLOOKUP(A6,Flete!$A:$E,5,0),"") | H6: =IFERROR(VLOOKUP(F6,TRAOPE!$AA:$AB,2,0),"") | I6: 10000719 | J6: =IFERROR(VLOOKUP(I6,Materiales!$A:$H,8,0),"") | K6: =IFERROR(VLOOKUP(I6,Materiales!$A:$G,7,0),"") | L6: 20210620 | M6: 20251031 | N6: 79.92 | O6: =IFERROR(VLOOKUP(A6,Flete!$A:$J,10,0),"") | P6: TN | Q6: =IFERROR(IFERROR(VLOOKUP(A6,TRAOPE!$A:$U,21,0),VLOOKUP(B6,TRAOPE!$A:$U,21,0)),"") | R6: =IFERROR(IFERROR(VLOOKUP(A6,TRAOPE!$A:$W,23,0),VLOOKUP(B6,TRAOPE!$A:$W,23,0)),"") | S6: =IF(AND(P6="TN",R6="TN"),N6+N(O6),IF(G6&""="1",N(K6)*N6,(N6+N(O6))*N(K6))) | T6: =IF(Q6="","",Q6-S6)
A7: =CONCATENATE(C7,E7,F7,I7) | B7: =CONCATENATE(C7,E7,I7) | C7: 900000045 | D7: =IFERROR(VLOOKUP(C7,TRAOPE!$G:$H,2,0),"") | E7: DW83 | F7: D216 | G7: =IFERROR(VLOOKUP(A7,Flete!$A:$E,5,0),"") | H7: =IFERROR(VLOOKUP(F7,TRAOPE!$AA:$AB,2,0),"") | I7: 10192197 | J7: =IFERROR(VLOOKUP(I7,Materiales!$A:$H,8,0),"") | K7: =IFERROR(VLOOKUP(I7,Materiales!$A:$G,7,0),"") | L7: 20210620 | M7: 20251031 | N7: 76.39 | O7: =IFERROR(VLOOKUP(A7,Flete!$A:$J,10,0),"") | P7: TN | Q7: =IFERROR(IFERROR(VLOOKUP(A7,TRAOPE!$A:$U,21,0),VLOOKUP(B7,TRAOPE!$A:$U,21,0)),"") | R7: =IFERROR(IFERROR(VLOOKUP(A7,TRAOPE!$A:$W,23,0),VLOOKUP(B7,TRAOPE!$A:$W,23,0)),"") | S7: =IF(AND(P7="TN",R7="TN"),N7+N(O7),IF(G7&""="1",N(K7)*N7,(N7+N(O7))*N(K7))) | T7: =IF(Q7="","",Q7-S7)
A8: =CONCATENATE(C8,E8,F8,I8) | B8: =CONCATENATE(C8,E8,I8) | C8: 900000045 | D8: =IFERROR(VLOOKUP(C8,TRAOPE!$G:$H,2,0),"") | E8: DW83 | F8: D243 | G8: =IFERROR(VLOOKUP(A8,Flete!$A:$E,5,0),"") | H8: =IFERROR(VLOOKUP(F8,TRAOPE!$AA:$AB,2,0),"") | I8: 10000379 | J8: =IFERROR(VLOOKUP(I8,Materiales!$A:$H,8,0),"") | K8: =IFERROR(VLOOKUP(I8,Materiales!$A:$G,7,0),"") | L8: 20230301 | M8: 20250129 | N8: 119.23 | O8: =IFERROR(VLOOKUP(A8,Flete!$A:$J,10,0),"") | P8: TN | Q8: =IFERROR(IFERROR(VLOOKUP(A8,TRAOPE!$A:$U,21,0),VLOOKUP(B8,TRAOPE!$A:$U,21,0)),"") | R8: =IFERROR(IFERROR(VLOOKUP(A8,TRAOPE!$A:$W,23,0),VLOOKUP(B8,TRAOPE!$A:$W,23,0)),"") | S8: =IF(AND(P8="TN",R8="TN"),N8+N(O8),IF(G8&""="1",N(K8)*N8,(N8+N(O8))*N(K8))) | T8: =IF(Q8="","",Q8-S8)
A9: =CONCATENATE(C9,E9,F9,I9) | B9: =CONCATENATE(C9,E9,I9) | C9: 900000045 | D9: =IFERROR(VLOOKUP(C9,TRAOPE!$G:$H,2,0),"") | E9: DW83 | F9: D243 | G9: =IFERROR(VLOOKUP(A9,Flete!$A:$E,5,0),"") | H9: =IFERROR(VLOOKUP(F9,TRAOPE!$AA:$AB,2,0),"") | I9: 10000719 | J9: =IFERROR(VLOOKUP(I9,Materiales!$A:$H,8,0),"") | K9: =IFERROR(VLOOKUP(I9,Materiales!$A:$G,7,0),"") | L9: 20230301 | M9: 20250129 | N9: 91.54 | O9: =IFERROR(VLOOKUP(A9,Flete!$A:$J,10,0),"") | P9: TN | Q9: =IFERROR(IFERROR(VLOOKUP(A9,TRAOPE!$A:$U,21,0),VLOOKUP(B9,TRAOPE!$A:$U,21,0)),"") | R9: =IFERROR(IFERROR(VLOOKUP(A9,TRAOPE!$A:$W,23,0),VLOOKUP(B9,TRAOPE!$A:$W,23,0)),"") | S9: =IF(AND(P9="TN",R9="TN"),N9+N(O9),IF(G9&""="1",N(K9)*N9,(N9+N(O9))*N(K9))) | T9: =IF(Q9="","",Q9-S9)
A10: =CONCATENATE(C10,E10,F10,I10) | B10: =CONCATENATE(C10,E10,I10) | C10: 900000045 | D10: =IFERROR(VLOOKUP(C10,TRAOPE!$G:$H,2,0),"") | E10: DW83 | F10: D243 | G10: =IFERROR(VLOOKUP(A10,Flete!$A:$E,5,0),"") | H10: =IFERROR(VLOOKUP(F10,TRAOPE!$AA:$AB,2,0),"") | I10: 10192197 | J10: =IFERROR(VLOOKUP(I10,Materiales!$A:$H,8,0),"") | K10: =IFERROR(VLOOKUP(I10,Materiales!$A:$G,7,0),"") | L10: 20230301 | M10: 20250129 | N10: 76.39 | O10: =IFERROR(VLOOKUP(A10,Flete!$A:$J,10,0),"") | P10: TN | Q10: =IFERROR(IFERROR(VLOOKUP(A10,TRAOPE!$A:$U,21,0),VLOOKUP(B10,TRAOPE!$A:$U,21,0)),"") | R10: =IFERROR(IFERROR(VLOOKUP(A10,TRAOPE!$A:$W,23,0),VLOOKUP(B10,TRAOPE!$A:$W,23,0)),"") | S10: =IF(AND(P10="TN",R10="TN"),N10+N(O10),IF(G10&""="1",N(K10)*N10,(N10+N(O10))*N(K10))) | T10: =IF(Q10="","",Q10-S10)
A11: =CONCATENATE(C11,E11,F11,I11) | B11: =CONCATENATE(C11,E11,I11) | C11: 900000045 | D11: =IFERROR(VLOOKUP(C11,TRAOPE!$G:$H,2,0),"") | E11: DW83 | F11: D269 | G11: =IFERROR(VLOOKUP(A11,Flete!$A:$E,5,0),"") | H11: =IFERROR(VLOOKUP(F11,TRAOPE!$AA:$AB,2,0),"") | I11: 10000332 | J11: =IFERROR(VLOOKUP(I11,Materiales!$A:$H,8,0),"") | K11: =IFERROR(VLOOKUP(I11,Materiales!$A:$G,7,0),"") | L11: 20230203 | M11: 20240201 | N11: 327.5 | O11: =IFERROR(VLOOKUP(A11,Flete!$A:$J,10,0),"") | P11: TN | Q11: =IFERROR(IFERROR(VLOOKUP(A11,TRAOPE!$A:$U,21,0),VLOOKUP(B11,TRAOPE!$A:$U,21,0)),"") | R11: =IFERROR(IFERROR(VLOOKUP(A11,TRAOPE!$A:$W,23,0),VLOOKUP(B11,TRAOPE!$A:$W,23,0)),"") | S11: =IF(AND(P11="TN",R11="TN"),N11+N(O11),IF(G11&""="1",N(K11)*N11,(N11+N(O11))*N(K11))) | T11: =IF(Q11="","",Q11-S11)
A12: =CONCATENATE(C12,E12,F12,I12) | B12: =CONCATENATE(C12,E12,I12) | C12: 900000045 | D12: =IFERROR(VLOOKUP(C12,TRAOPE!$G:$H,2,0),"") | E12: DW83 | F12: D269 | G12: =IFERROR(VLOOKUP(A12,Flete!$A:$E,5,0),"") | H12: =IFERROR(VLOOKUP(F12,TRAOPE!$AA:$AB,2,0),"") | I12: 10000377 | J12: =IFERROR(VLOOKUP(I12,Materiales!$A:$H,8,0),"") | K12: =IFERROR(VLOOKUP(I12,Materiales!$A:$G,7,0),"") | L12: 20260601 | M12: 99991231 | N12: 94.88 | O12: =IFERROR(VLOOKUP(A12,Flete!$A:$J,10,0),"") | P12: TN | Q12: =IFERROR(IFERROR(VLOOKUP(A12,TRAOPE!$A:$U,21,0),VLOOKUP(B12,TRAOPE!$A:$U,21,0)),"") | R12: =IFERROR(IFERROR(VLOOKUP(A12,TRAOPE!$A:$W,23,0),VLOOKUP(B12,TRAOPE!$A:$W,23,0)),"") | S12: =IF(AND(P12="TN",R12="TN"),N12+N(O12),IF(G12&""="1",N(K12)*N12,(N12+N(O12))*N(K12))) | T12: =IF(Q12="","",Q12-S12)
A13: =CONCATENATE(C13,E13,F13,I13) | B13: =CONCATENATE(C13,E13,I13) | C13: 900000045 | D13: =IFERROR(VLOOKUP(C13,TRAOPE!$G:$H,2,0),"") | E13: DW83 | F13: D269 | G13: =IFERROR(VLOOKUP(A13,Flete!$A:$E,5,0),"") | H13: =IFERROR(VLOOKUP(F13,TRAOPE!$AA:$AB,2,0),"") | I13: 10000379 | J13: =IFERROR(VLOOKUP(I13,Materiales!$A:$H,8,0),"") | K13: =IFERROR(VLOOKUP(I13,Materiales!$A:$G,7,0),"") | L13: 20260601 | M13: 99991231 | N13: 144.17 | O13: =IFERROR(VLOOKUP(A13,Flete!$A:$J,10,0),"") | P13: TN | Q13: =IFERROR(IFERROR(VLOOKUP(A13,TRAOPE!$A:$U,21,0),VLOOKUP(B13,TRAOPE!$A:$U,21,0)),"") | R13: =IFERROR(IFERROR(VLOOKUP(A13,TRAOPE!$A:$W,23,0),VLOOKUP(B13,TRAOPE!$A:$W,23,0)),"") | S13: =IF(AND(P13="TN",R13="TN"),N13+N(O13),IF(G13&""="1",N(K13)*N13,(N13+N(O13))*N(K13))) | T13: =IF(Q13="","",Q13-S13)
A14: =CONCATENATE(C14,E14,F14,I14) | B14: =CONCATENATE(C14,E14,I14) | C14: 900000045 | D14: =IFERROR(VLOOKUP(C14,TRAOPE!$G:$H,2,0),"") | E14: DW83 | F14: D269 | G14: =IFERROR(VLOOKUP(A14,Flete!$A:$E,5,0),"") | H14: =IFERROR(VLOOKUP(F14,TRAOPE!$AA:$AB,2,0),"") | I14: 10000381 | J14: =IFERROR(VLOOKUP(I14,Materiales!$A:$H,8,0),"") | K14: =IFERROR(VLOOKUP(I14,Materiales!$A:$G,7,0),"") | L14: 20230203 | M14: 20240201 | N14: 46.17 | O14: =IFERROR(VLOOKUP(A14,Flete!$A:$J,10,0),"") | P14: TN | Q14: =IFERROR(IFERROR(VLOOKUP(A14,TRAOPE!$A:$U,21,0),VLOOKUP(B14,TRAOPE!$A:$U,21,0)),"") | R14: =IFERROR(IFERROR(VLOOKUP(A14,TRAOPE!$A:$W,23,0),VLOOKUP(B14,TRAOPE!$A:$W,23,0)),"") | S14: =IF(AND(P14="TN",R14="TN"),N14+N(O14),IF(G14&""="1",N(K14)*N14,(N14+N(O14))*N(K14))) | T14: =IF(Q14="","",Q14-S14)
... A218: =CONCATENATE(C218,E218,F218,I218) | B218: =CONCATENATE(C218,E218,I218) | C218: 900009275 | D218: =IFERROR(VLOOKUP(C218,TRAOPE!$G:$H,2,0),"") | E218: DW83 | F218: D216 | G218: =IFERROR(VLOOKUP(A218,Flete!$A:$E,5,0),"") | H218: =IFERROR(VLOOKUP(F218,TRAOPE!$AA:$AB,2,0),"") | I218: 10258539 | J218: =IFERROR(VLOOKUP(I218,Materiales!$A:$H,8,0),"") | K218: =IFERROR(VLOOKUP(I218,Materiales!$A:$G,7,0),"") | L218: 20260605 | M218: 99991231 | N218: 277.8 | O218: =IFERROR(VLOOKUP(A218,Flete!$A:$J,10,0),"") | P218: TN | Q218: =IFERROR(IFERROR(VLOOKUP(A218,TRAOPE!$A:$U,21,0),VLOOKUP(B218,TRAOPE!$A:$U,21,0)),"") | R218: =IFERROR(IFERROR(VLOOKUP(A218,TRAOPE!$A:$W,23,0),VLOOKUP(B218,TRAOPE!$A:$W,23,0)),"") | S218: =IF(AND(P218="TN",R218="TN"),N218+N(O218),IF(G218&""="1",N(K218)*N218,(N218+N(O218))*N(K218))) | T218: =IF(Q218="","",Q218-S218)

Sheet MP
A1: No. SF | B1: Cedis | C1: Destino | D1: No. Material | E1: Nombre Material | F1: Importe MP | G1: Moneda | H1: Cantidad | I1: UM | J1: C | K1: Inicio Vigencia | L1: Fin Vigencia
A2: 900000045 | B2: DW83 | C2: D216 | D2: 10000377 | F2: 107.59 | I2: TN | K2: 20210620 | L2: 20251031
A3: 900000045 | B3: DW83 | C3: D216 | D3: 10000379 | F3: 119.23 | I3: TN | K3: 20210620 | L3: 20251031
A4: 900000045 | B4: DW83 | C4: D216 | D4: 10000381 | F4: 69.97 | I4: TN | K4: 20210620 | L4: 20251031
A5: 900000045 | B5: DW83 | C5: D216 | D5: 10000719 | F5: 79.92 | I5: TN | K5: 20210620 | L5: 20251031
A6: 900000045 | B6: DW83 | C6: D216 | D6: 10192197 | F6: 76.39 | I6: TN | K6: 20210620 | L6: 20251031
A7: 900000045 | B7: DW83 | C7: D243 | D7: 10000379 | F7: 119.23 | I7: TN | K7: 20230301 | L7: 20250129
A8: 900000045 | B8: DW83 | C8: D243 | D8: 10000719 | F8: 91.54 | I8: TN | K8: 20230301 | L8: 20250129
A9: 900000045 | B9: DW83 | C9: D243 | D9: 10192197 | F9: 76.39 | I9: TN | K9: 20230301 | L9: 20250129
A10: 900000045 | B10: DW83 | C10: D269 | D10: 10000332 | F10: 327.5 | I10: TN | K10: 20230203 | L10: 20240201
A11: 900000045 | B11: DW83 | C11: D269 | D11: 10000377 | F11: 94.88 | I11: TN | K11: 20260601 | L11: 99991231
A12: 900000045 | B12: DW83 | C12: D269 | D12: 10000379 | F12: 144.17 | I12: TN | K12: 20260601 | L12: 99991231
A13: 900000045 | B13: DW83 | C13: D269 | D13: 10000381 | F13: 46.17 | I13: TN | K13: 20230203 | L13: 20240201
... A217: 900009275 | B217: DW83 | C217: D216 | D217: 10258539 | F217: 277.8 | I217: TN | K217: 20260605 | L217: 99991231

Sheet Flete
A1: Concat1 | B1: No. SF | C1: Cedis | D1: Destino | E1: Cond. Exp. | F1: Material | H1: Nombre Material | J1: Importe Flete | K1: Moneda | L1: Cantidad | M1: UM | N1: C | P1: Inicio Vigencia | Q1: Fin Vigencia
A2: 900000045DW83D21610000377 | B2: 900000045 | C2: DW83 | D2: D216 | E2: 4 | F2: 10000377 | J2: 86.01 | M2: TN | P2: 20210620 | Q2: 20251031
A3: 900000045DW83D21610000379 | B3: 900000045 | C3: DW83 | D3: D216 | E3: 4 | F3: 10000379 | J3: 246.5 | M3: TN | P3: 20210620 | Q3: 20251031
A4: 900000045DW83D21610000381 | B4: 900000045 | C4: DW83 | D4: D216 | E4: 4 | F4: 10000381 | J4: 73.34 | M4: TN | P4: 20210620 | Q4: 20251031
A5: 900000045DW83D21610000719 | B5: 900000045 | C5: DW83 | D5: D216 | E5: 4 | F5: 10000719 | J5: 83.22 | M5: TN | P5: 20210620 | Q5: 20251031
A6: 900000045DW83D21610192197 | B6: 900000045 | C6: DW83 | D6: D216 | E6: 4 | F6: 10192197 | J6: 277.73 | M6: TN | P6: 20210620 | Q6: 20251031
A7: 900000045DW83D24310000379 | B7: 900000045 | C7: DW83 | D7: D243 | E7: 4 | F7: 10000379 | J7: 218.53 | M7: TN | P7: 20230301 | Q7: 20250129
A8: 900000045DW83D24310000719 | B8: 900000045 | C8: DW83 | D8: D243 | E8: 4 | F8: 10000719 | J8: 224.41 | M8: TN | P8: 20230301 | Q8: 20250129
A9: 900000045DW83D24310192197 | B9: 900000045 | C9: DW83 | D9: D243 | E9: 4 | F9: 10192197 | J9: 268.73 | M9: TN | P9: 20230301 | Q9: 20250129
A10: 900000045DW83D26910000332 | B10: 900000045 | C10: DW83 | D10: D269 | E10: 4 | F10: 10000332 | J10: 62.5 | M10: TN | P10: 20230203 | Q10: 20240201
A11: 900000045DW83D26910000377 | B11: 900000045 | C11: DW83 | D11: D269 | E11: 4 | F11: 10000377 | J11: 32.92 | M11: TN | P11: 20260601 | Q11: 99991231
A12: 900000045DW83D26910000379 | B12: 900000045 | C12: DW83 | D12: D269 | E12: 4 | F12: 10000379 | J12: 33.45 | M12: TN | P12: 20260601 | Q12: 99991231
A13: 900000045DW83D26910000381 | B13: 900000045 | C13: DW83 | D13: D269 | E13: 4 | F13: 10000381 | J13: 32.89 | M13: TN | P13: 20230203 | Q13: 20240201
... A213: 900009275DW83D21610258539 | B213: 900009275 | C213: DW83 | D213: D216 | E213: 4 | F213: 10258539 | J213: 110.45 | M213: TN | P213: 20260605 | Q213: 99991231

Sheet Materiales
A1: Material | B1: TpMt | C1: Denom | D1: UMA | E1: Contador | F1: UMB | G1: PV | H1: Nombre Material
A2: 10000001 | B2: ZFER | C2: 1000 | D2: M3 | E2: 1000 | F2: TN | G2: 1262 | H2: GRAVA ANDESITA 10 MM (3/8")
A3: 10000003 | B3: ZFER | C3: 1000 | D3: M3 | E3: 1000 | F3: TN | G3: 1443 | H3: GRAVA CALIZA 10 MM (3/8")
A4: 10000006 | B4: ZFER | C4: 1000 | D4: M3 | E4: 1000 | F4: TN | G4: 1490 | H4: GRAVA RIO 10 MM (3/8")
A5: 10000007 | B5: ZFER | C5: 1000 | D5: M3 | E5: 1000 | F5: TN | G5: 1488 | H5: GRAVA BASALTO 13 MM (1/2")
A6: 10000008 | B6: ZFER | C6: 1000 | D6: M3 | E6: 1000 | F6: TN | G6: 1358 | H6: GRAVA CALIZA 13 MM (1/2")
A7: 10000011 | B7: ZFER | C7: 1000 | D7: M3 | E7: 1000 | F7: TN | G7: 1323 | H7: GRAVA ANDESITA 20 MM (3/4")
A8: 10000013 | B8: ZFER | C8: 1000 | D8: M3 | E8: 1000 | F8: TN | G8: 1514 | H8: GRAVA BASALTO 20 MM (3/4")
A9: 10000014 | B9: ZFER | C9: 1000 | D9: M3 | E9: 1000 | F9: TN | G9: 1400 | H9: GRAVA CALIZA 20 MM (3/4")
A10: 10000015 | B10: ZFER | C10: 1000 | D10: M3 | E10: 1000 | F10: TN | G10: 1410 | H10: GRAVA GRANITO 20 MM (3/4")
A11: 10000017 | B11: ZFER | C11: 1000 | D11: M3 | E11: 1000 | F11: TN | G11: 1475 | H11: GRAVA RIOLITA 20 MM (3/4")
A12: 10000019 | B12: ZFER | C12: 1000 | D12: M3 | E12: 1000 | F12: TN | G12: 1515 | H12: GRAVA RIO 20 MM (3/4")
A13: 10000020 | B13: ZFER | C13: 1000 | D13: M3 | E13: 1 | F13: TN | G13: 1 | H13: GRAVA MAQUILA 40MM (1 1/2")
... A2291: 10268770 | B2291: ZFE3 | C2291: 1000 | D2291: M3 | E2291: 1000 | F2291: TN | G2291: 1240 | H2291: MP GRAVA TRIT CALIZA 40MM 1 1/2" - ESP
A2292: 10268901 | B2292: ZFE3 | C2292: 1000 | D2292: M3 | E2292: 1000 | G2292: 1560 | H2292: MP GRAVA ANDESITA GRIS 3/4" - CAPADA
A2293: 10267983 | C2293: 1000 | G2293: 1800 | H2293: ESCORIA ALTO HORNO 3/4
A2294: 10268996 | C2294: 1000 | G2294: 1329 | H2294: GRAVA TRITURADA CALIZA 40 MM - 11/2"
A2295: 10269072 | C2295: 1000 | G2295: 1700 | H2295: BASE HIDRÁULICA SCREEN
A2296: 10269225 | B2296: ZFE3 | C2296: 1000 | D2296: M3 | E2296: 1000 | G2296: 1289 | H2296: MP ARENA CALIZA LAVADA MALLA 4 - DELTA I
A2297: 10269245 | B2297: ZFE3 | C2297: 1000 | D2297: M3 | E2297: 1000 | G2297: 1410 | H2297: MP GRAVA TRITURADA CALIZA 3/8 - 10MM
A2298: 10269246 | B2298: ZFE3 | C2298: 1000 | D2298: M3 | E2298: 1000 | G2298: 1400 | H2298: MP GRAVA TRITURADA CALIZA 1 1/2 - 40MM
A2299: 10269247 | B2299: ZFE3 | C2299: 1000 | D2299: M3 | E2299: 1000 | G2299: 1560 | H2299: MP ARENA TRIT CALIZA M-4
A2300: 10270431 | B2300: ZFE3 | C2300: 1000 | D2300: M3 | E2300: 1000 | G2300: 1423 | H2300: MP GRAVA RIOLITA 13 MM - 1/2"
A2301: 10270898 | B2301: ZFE3 | C2301: 1000 | D2301: M3 | E2301: 1000 | G2301: 1551 | H2301: MP BASE H. TRIT. BASALTO 1 1/2" A FINOS
A2302: 10270911 | B2302: ZFE3 | C2302: 1000 | D2302: M3 | E2302: 1000 | G2302: 1360 | H2302: MP GRAVA TRIT. BASALTO 40 MM - 1 1/2"
A2303: 10270912 | B2303: ZFE3 | C2303: 1000 | D2303: M3 | E2303: 1000 | G2303: 1589 | H2303: MP ARENA TRIT. BASALTO MALLA 4
A2304: 10270913 | B2304: ZFE3 | C2304: 1000 | D2304: M3 | E2304: 1000 | G2304: 1395 | H2304: MP GRAVA TRIT. BASALTO 20 MM - 3/4
A2305: 10270914 | B2305: ZFE3 | C2305: 1000 | D2305: M3 | E2305: 1000 | G2305: 1623 | H2305: MP ARENA ANDESITA BC
A2306: 10270824 | B2306: M3 | C2306: 1000 | D2306: M3 | E2306: 10007640 | G2306: 1325 | H2306: MP ARENA TRITURADA CALIZA MALLA 5
A2307: 10270825 | B2307: M3 | C2307: 1000 | D2307: M3 | E2307: 10000003 | G2307: 1242 | H2307: MP GRAVA TRITURADA CALIZA 10MM (3/8”)
... A2319: 10272527 | B2319: ZFE3 | C2319: 1000 | D2319: M3 | E2319: 1000 | G2319: 1620 | H2319: CNC - NO CLASIFICADO
A2320: 10000332 | C2320: 1000 | D2320: M3 | E2320: 1000 | G2320: 800 | H2320: Grava Triturada Pomez - Jal 20 mm - 3/4"
A2321: 10273001 | B2321: ZFE3 | C2321: 1000 | D2321: M3 | E2321: 1000 | G2321: 1688 | H2321: MP ARENA TRIT. BASALTO MALLA 4
A2322: 10273002 | B2322: ZFE3 | C2322: 1000 | D2322: M3 | E2322: 1000 | G2322: 1466 | H2322: MP GRAVA TRIT. BASALTO 20 MM - 3/4"
A2323: 10273351 | B2323: ZFE3 | C2323: 1000 | D2323: M3 | E2323: 1000 | G2323: 1612 | H2323: MP ARENA TRIT. CALIZA MALLA 4
A2324: 10273352 | B2324: ZFE3 | C2324: 1000 | D2324: M3 | E2324: 1000 | G2324: 1492 | H2324: MP GRAVA TRIT. CALIZA 20 MM - 3/4"
A2325: 10271724 | B2325: ZFE3 | C2325: 1000 | D2325: M3 | E2325: 1000 | G2325: 1900 | H2325: MP RESIDUO DE CONCRETO
A2326: 10000677 | C2326: 1000 | D2326: M3 | G2326: 1164 | H2326: Grava Triturada Caliza 20 mm - 3/4"
A2327: 10274190 | B2327: ZFE3 | C2327: 1000 | D2327: M3 | E2327: 1000 | G2327: 1800 | H2327: MP BASE HIDRAULICA ANDESITA 70-30
A2328: 10274601 | B2328: ZFE3 | C2328: 1000 | D2328: M3 | E2328: 1000 | G2328: 1447 | H2328: MP ARENA BASALTO N° 4
A2329: 10274754 | B2329: ZFE3 | C2329: 1000 | D2329: M3 | E2329: 1000 | G2329: 1397 | H2329: MP GRAVA TRIT. ANDESITA 20 MM - 3/4"
A2330: 10169718 | B2330: ZFE3 | C2330: 1000 | D2330: M3 | E2330: 1000 | G2330: 1400 | H2330: GRAVA CLASIFICADA RÍO 40 MM - 1 1/2"
A2331: 10274813 | B2331: ZFE3 | C2331: 1000 | D2331: M3 | E2331: 1000 | G2331: 1448 | H2331: MP ARENA TRIT RÍO MALLA 4
A2332: 10274815 | B2332: ZFE3 | C2332: 1000 | D2332: M3 | E2332: 1000 | G2332: 1366 | H2332: MP ARENA CLASIFICADA RÍO MALLA 5
A2333: 10274816 | B2333: ZFE3 | C2333: 1000 | D2333: M3 | E2333: 1000 | G2333: 1472 | H2333: MP GRAVA CLASIF RÍO 20 MM - 3/4"
A2334: 10275113 | B2334: ZFE3 | C2334: 1000 | D2334: M3 | E2334: 1000 | G2334: 1409 | H2334: MP ARENA TRIT ANDESITA MALLA 4
A2335: 10275114 | B2335: ZFE3 | C2335: 1000 | D2335: M3 | E2335: 1000 | G2335: 1418 | H2335: MP ARENA CLASIF RIO MALLA 4 - LAVADO
A2336: 10275115 | B2336: ZFE3 | C2336: 1000 | D2336: M3 | E2336: 1000 | G2336: 1259 | H2336: MP ARENA TRIT ANDESITA MALLA 4
A2337: 10275116 | B2337: ZFE3 | C2337: 1000 | D2337: M3 | E2337: 1000 | G2337: 1401 | H2337: MP GRAVA TRIT ANDESITA 3/4 - 20 MM
A2338: 10275118 | B2338: ZFE3 | C2338: 1000 | D2338: M3 | E2338: 1000 | G2338: 1401 | H2338: MP ARENA TRIT ANDESITA MALLA 4
... A2361: 10280049 | B2361: ZFE3 | C2361: 1000 | D2361: M3 | E2361: 1000 | G2361: 1584 | H2361: MP B. HID CALIZA 40% FINOS Y 60% GRUESOS
A2362: 10280365 | C2362: 1000 | D2362: M3 | E2362: 1000 | G2362: 1274 | H2362: MP GRAVA BASALTO 20 MM -3/4
A2363: 10280538 | B2363: ZFE3 | C2363: 1000 | D2363: M3 | E2363: 1000 | G2363: 1262 | H2363: MP GRAVA TRIT BASALTO 3/8 - 10MM
A2364: 10280679 | B2364: ZFE3 | C2364: 1000 | D2364: M3 | E2364: 1000 | G2364: 1349 | H2364: MP GRAVA CLASIF RÍO 13MM - 1/2"
A2365: 10281171 | B2365: ZFE3 | C2365: 1000 | D2365: M3 | E2365: 1000 | G2365: 1271 | H2365: MP GRAVA TRIT CALIZA 10MM - 3/8"
A2366: 10281183 | B2366: ZFE3 | C2366: 1000 | D2366: M3 | E2366: 1000 | G2366: 1468 | H2366: MP ARENA TRIT CALIZA MALLA 4
A2367: 10281384 | B2367: ZFE3 | C2367: 1000 | D2367: M3 | E2367: 1000 | G2367: 1285 | H2367: MP GRAVA BASALTO 40 MM (1 1/2")
A2368: 10281379 | B2368: ZFE3 | C2368: 1000 | D2368: M3 | E2368: 1000 | G2368: 1536 | H2368: MP ARENA CLASIF. RÍO MALLA 4
A2369: 10281450 | B2369: ZFE3 | C2369: 1000 | D2369: M3 | E2369: 1000 | G2369: 1325 | H2369: MP GRAVA CLASIF. RIO 20MM - 3/4
A2370: 10281451 | B2370: ZFE3 | C2370: 1000 | D2370: M3 | E2370: 1000 | G2370: 1564 | H2370: MP ARENA CLASIF. RÍO MALLA 4
A2371: 10281452 | B2371: ZFE3 | C2371: 1000 | D2371: M3 | E2371: 1000 | G2371: 1427 | H2371: MP GRAVA CLASIF. RIO 20MM - 3/4

Sheet TRAOPE
A1: Concat1 | B1: Contrato_Pos | C1: Doc. Compras | D1: Pos | E1: Org.compras | F1: Grp-Compr. | G1: Ship From | H1: Nombre SF | I1: Proveedor | J1: Nombre Prov | K1: Cond. Pago | L1: Descr. Cond Pago | M1: Material | N1: Descripción | O1: Centro | P1: Descripción Centro | Q1: In.perído validez | R1: Fin perído validez | S1: Válido de | T1: Validez a | U1: Precio neto pedido | V1: Moneda | W1: UM Precio Pedido | X1: Importe Condición | Y1: Moneda KONP | Z1: UM Ctd Base | AA1: Destino | AB1: Nombre Destino | AC1: Cuenta de mayor | AD1: Centro de costo | AE1: Cond. Exp. | AF1: Descr. Cond. Exp. | AG1: Peso Vol. | AH1: UMB | AI1: Ind. Oblig. Conf. Ped. | AJ1: Ctrl-Conf. | AK1: IVA | AL1: Modif_Date | AM1: Ruta
A2: 900003017DW83D21610049556 | B2: 4600050426-130 | C2: 4600050426 | D2: 130 | E2: MXPO | F2: MXL | G2: 900003017 | H2: TC-ED-SALDAÑA MORONES- LAS VARAS | I2: 5002163 | J2: SALDANA MORONES HERIBERTO | K2: N30 | L2: (AP) NAFIN 30 Dias | M2: 10049556 | N2: Grava Triturada Basalto 10 mm - 3/8" | O2: DW83 | P2: MX-CED. VALLARTA | Q2: 20210801 | R2: 20281231 | S2: 20220121 | T2: 20271231 | U2: 365 | V2: MXN | W2: M3 | X2: 190 | Y2: MXN | Z2: M3 | AA2: D216 | AB2: PD0130 TEPIC | AC2: 56103637 | AD2: 6644411540 | AE2: 4 | AF2: ENTREGA DIRECTA | AG2: 1.328 | AH2: M3 | AI2: X | AJ2: 4 | AK2: V4 | AL2: 20230920 | AM2: DW83-900003017-D216-10049556-4
A3: 900000560DW8310258539 | B3: 4600056862-30 | C3: 4600056862 | D3: 30 | E3: MXPO | F3: MXL | G3: 900000560 | H3: SF TC-TEPYC LA REPISA | I3: 5006993 | J3: TERRACERIAS PAVIMENTOS Y CAMINOS SA | K3: Z04 | L3: (AP) 30 Dias | M3: 10258539 | N3: ARENA TRITURADA BASALTO MALLA 5 | O3: DW83 | P3: MX-CED. VALLARTA | Q3: 20230310 | R3: 20281231 | S3: 20240704 | T3: 20291231 | U3: 350 | V3: MXN | W3: M3 | X3: 0 | Y3: MXN | Z3: M3 | AC3: 56103638 | AD3: 6644411540 | AE3: 1 | AF3: ENTREGADO | AG3: 1.591 | AH3: M3 | AI3: X | AJ3: 4 | AK3: V4 | AL3: 20240711 | AM3: DW83-900000560-10258539
A4: 900003368DW83D21510192197 | B4: 4600050463-60 | C4: 4600050463 | D4: 60 | E4: MXPO | F4: MXL | G4: 900003368 | H4: TC-ED SALDAÑA PORVENIR | I4: 5002163 | J4: SALDANA MORONES HERIBERTO | K4: N30 | L4: (AP) NAFIN 30 Dias | M4: 10192197 | N4: ARENA CLASIFICADA RIO MALLA 5 | O4: DW83 | P4: MX-CED. VALLARTA | Q4: 20210801 | R4: 20291231 | S4: 20260601 | T4: 20301231 | U4: 198.54 | V4: MXN | W4: M3 | X4: 44.04 | Y4: MXN | Z4: M3 | AA4: D215 | AB4: PD0159 PUERTO VALLARTA | AC4: 56103638 | AD4: 6644411540 | AE4: 4 | AF4: ENTREGA DIRECTA | AG4: 1.443 | AH4: M3 | AI4: X | AJ4: 4 | AK4: V4 | AL4: 20260615 | AM4: DW83-900003368-D215-10192197-4
A5: 900004830DW83D38610000379 | B5: 4600050438-130 | C5: 4600050438 | D5: 130 | E5: MXPO | F5: MXL | G5: 900004830 | H5: TC-ED ARMAMPET LAS VARAS | I5: 5061801 | J5: ARMAMPET SA DE CV | K5: N30 | L5: (AP) NAFIN 30 Dias | M5: 10000379 | N5: Grava Triturada Basalto 20 mm - 3/4" | O5: DW83 | P5: MX-CED. VALLARTA | Q5: 20210801 | R5: 20291231 | S5: 20260601 | T5: 20301231 | U5: 367.94 | V5: MXN | W5: M3 | X5: 168.38 | Y5: MXN | Z5: M3 | AA5: D386 | AB5: PD0563 PUNTA DE MITA | AC5: 56103637 | AD5: 6644411540 | AE5: 4 | AF5: ENTREGA DIRECTA | AG5: 1.43 | AH5: M3 | AI5: X | AJ5: 4 | AK5: V4 | AL5: 20260615 | AM5: DW83-900004830-D386-10000379-4
A6: 900000045DW83D26910000377 | B6: 4600050401-50 | C6: 4600050401 | D6: 50 | E6: MXPO | F6: MXL | G6: 900000045 | H6: TC-ED SALDAÑA MORONES | I6: 5002163 | J6: SALDANA MORONES HERIBERTO | K6: N30 | L6: (AP) NAFIN 30 Dias | M6: 10000377 | N6: Grava Triturada Basalto 10 mm - 3/8" | O6: DW83 | P6: MX-CED. VALLARTA | Q6: 20210712 | R6: 20291231 | S6: 20260601 | T6: 20301231 | U6: 186.34 | V6: MXN | W6: M3 | X6: 48 | Y6: MXN | Z6: M3 | AA6: D269 | AB6: PD0434 PLANTA MAYAN | AC6: 56103637 | AD6: 6644411540 | AE6: 4 | AF6: ENTREGA DIRECTA | AG6: 1.458 | AH6: M3 | AI6: X | AJ6: 4 | AK6: V4 | AL6: 20260615 | AM6: DW83-900000045-D269-10000377-4
A7: 900003368DW83D55710000377 | B7: 4600050463-120 | C7: 4600050463 | D7: 120 | E7: MXPO | F7: MXL | G7: 900003368 | H7: TC-ED SALDAÑA PORVENIR | I7: 5002163 | J7: SALDANA MORONES HERIBERTO | K7: N30 | L7: (AP) NAFIN 30 Dias | M7: 10000377 | N7: Grava Triturada Basalto 10 mm - 3/8" | O7: DW83 | P7: MX-CED. VALLARTA | Q7: 20210801 | R7: 20291231 | S7: 20260601 | T7: 20301231 | U7: 402.85 | V7: MXN | W7: M3 | X7: 268.97 | Y7: MXN | Z7: M3 | AA7: D557 | AB7: PD0432 TRONCAL SAN PANCHO | AC7: 56103637 | AD7: 6644411540 | AE7: 4 | AF7: ENTREGA DIRECTA | AG7: 1.458 | AH7: M3 | AI7: X | AJ7: 4 | AK7: V4 | AL7: 20260615 | AM7: DW83-900003368-D557-10000377-4
A8: 900004830DW83D38610000719 | B8: 4600050438-100 | C8: 4600050438 | D8: 100 | E8: MXPO | F8: MXL | G8: 900004830 | H8: TC-ED ARMAMPET LAS VARAS | I8: 5061801 | J8: ARMAMPET SA DE CV | K8: N30 | L8: (AP) NAFIN 30 Dias | M8: 10000719 | N8: Arena Clasificada Río Malla 8 | O8: DW83 | P8: MX-CED. VALLARTA | Q8: 20210801 | R8: 20291231 | S8: 20260601 | T8: 20301231 | U8: 335.89 | V8: MXN | W8: M3 | X8: 181.39 | Y8: MXN | Z8: M3 | AA8: D386 | AB8: PD0563 PUNTA DE MITA | AC8: 56103638 | AD8: 6644411540 | AE8: 4 | AF8: ENTREGA DIRECTA | AG8: 1.442 | AH8: M3 | AI8: X | AJ8: 4 | AK8: V4 | AL8: 20260615 | AM8: DW83-900004830-D386-10000719-4
A9: 900003368DW83D21510000383 | B9: 4600050463-40 | C9: 4600050463 | D9: 40 | E9: MXPO | F9: MXL | G9: 900003368 | H9: TC-ED SALDAÑA PORVENIR | I9: 5002163 | J9: SALDANA MORONES HERIBERTO | K9: N30 | L9: (AP) NAFIN 30 Dias | M9: 10000383 | N9: Grava Triturada Basalto 40 mm - 1 1/2" | O9: DW83 | P9: MX-CED. VALLARTA | Q9: 20210801 | R9: 20291231 | S9: 20260601 | T9: 20301231 | U9: 274.82 | V9: MXN | W9: M3 | X9: 75.27 | Y9: MXN | Z9: M3 | AA9: D215 | AB9: PD0159 PUERTO VALLARTA | AC9: 56103637 | AD9: 6644411540 | AE9: 4 | AF9: ENTREGA DIRECTA | AG9: 1.359 | AH9: M3 | AI9: X | AJ9: 4 | AK9: V4 | AL9: 20260615 | AM9: DW83-900003368-D215-10000383-4
A10: 900003368DW83D55710192197 | B10: 4600050463-150 | C10: 4600050463 | D10: 150 | E10: MXPO | F10: MXL | G10: 900003368 | H10: TC-ED SALDAÑA PORVENIR | I10: 5002163 | J10: SALDANA MORONES HERIBERTO | K10: N30 | L10: (AP) NAFIN 30 Dias | M10: 10192197 | N10: ARENA CLASIFICADA RIO MALLA 5 | O10: DW83 | P10: MX-CED. VALLARTA | Q10: 20210801 | R10: 20291231 | S10: 20260601 | T10: 20301231 | U10: 352.5 | V10: MXN | W10: M3 | X10: 198 | Y10: MXN | Z10: M3 | AA10: D557 | AB10: PD0432 TRONCAL SAN PANCHO | AC10: 56103638 | AD10: 6644411540 | AE10: 4 | AF10: ENTREGA DIRECTA | AG10: 1.443 | AH10: M3 | AI10: X | AJ10: 4 | AK10: V4 | AL10: 20260615 | AM10: DW83-900003368-D557-10192197-4
A11: 900003368DW83D21510000379 | B11: 4600050463-30 | C11: 4600050463 | D11: 30 | E11: MXPO | F11: MXL | G11: 900003368 | H11: TC-ED SALDAÑA PORVENIR | I11: 5002163 | J11: SALDANA MORONES HERIBERTO | K11: N30 | L11: (AP) NAFIN 30 Dias | M11: 10000379 | N11: Grava Triturada Basalto 20 mm - 3/4" | O11: DW83 | P11: MX-CED. VALLARTA | Q11: 20210801 | R11: 20291231 | S11: 20260601 | T11: 20301231 | U11: 274.82 | V11: MXN | W11: M3 | X11: 75.27 | Y11: MXN | Z11: M3 | AA11: D215 | AB11: PD0159 PUERTO VALLARTA | AC11: 56103637 | AD11: 6644411540 | AE11: 4 | AF11: ENTREGA DIRECTA | AG11: 1.43 | AH11: M3 | AI11: X | AJ11: 4 | AK11: V4 | AL11: 20260615 | AM11: DW83-900003368-D215-10000379-4
A12: 900003368DW83D55710000379 | B12: 4600050463-130 | C12: 4600050463 | D12: 130 | E12: MXPO | F12: MXL | G12: 900003368 | H12: TC-ED SALDAÑA PORVENIR | I12: 5002163 | J12: SALDANA MORONES HERIBERTO | K12: N30 | L12: (AP) NAFIN 30 Dias | M12: 10000379 | N12: Grava Triturada Basalto 20 mm - 3/4" | O12: DW83 | P12: MX-CED. VALLARTA | Q12: 20210801 | R12: 20291231 | S12: 20260601 | T12: 20301231 | U12: 424.44 | V12: MXN | W12: M3 | X12: 224.89 | Y12: MXN | Z12: M3 | AA12: D557 | AB12: PD0432 TRONCAL SAN PANCHO | AC12: 56103637 | AD12: 6644411540 | AE12: 4 | AF12: ENTREGA DIRECTA | AG12: 1.43 | AH12: M3 | AI12: X | AJ12: 4 | AK12: V4 | AL12: 20260615 | AM12: DW83-900003368-D557-10000379-4
A13: 900000045DW83D26910000379 | B13: 4600050401-30 | C13: 4600050401 | D13: 30 | E13: MXPO | F13: MXL | G13: 900000045 | H13: TC-ED SALDAÑA MORONES | I13: 5002163 | J13: SALDANA MORONES HERIBERTO | K13: N30 | L13: (AP) NAFIN 30 Dias | M13: 10000379 | N13: Grava Triturada Basalto 20 mm - 3/4" | O13: DW83 | P13: MX-CED. VALLARTA | Q13: 20210712 | R13: 20291231 | S13: 20260601 | T13: 20301231 | U13: 254.01 | V13: MXN | W13: M3 | X13: 47.84 | Y13: MXN | Z13: M3 | AA13: D269 | AB13: PD0434 PLANTA MAYAN | AC13: 56103637 | AD13: 6644411540 | AE13: 4 | AF13: ENTREGA DIRECTA | AG13: 1.43 | AH13: M3 | AI13: X | AJ13: 4 | AK13: V4 | AL13: 20260615 | AM13: DW83-900000045-D269-10000379-4
A14: 900004830DW83D38610000383 | B14: 4600050438-120 | C14: 4600050438 | D14: 120 | E14: MXPO | F14: MXL | G14: 900004830 | H14: TC-ED ARMAMPET LAS VARAS | I14: 5061801 | J14: ARMAMPET SA DE CV | K14: N30 | L14: (AP) NAFIN 30 Dias | M14: 10000383 | N14: Grava Triturada Basalto 40 mm - 1 1/2" | O14: DW83 | P14: MX-CED. VALLARTA | Q14: 20210801 | R14: 20291231 | S14: 20260601 | T14: 20301231 | U14: 367.93 | V14: MXN | W14: M3 | X14: 168.37 | Y14: MXN | Z14: M3 | AA14: D386 | AB14: PD0563 PUNTA DE MITA | AC14: 56103637 | AD14: 6644411540 | AE14: 4 | AF14: ENTREGA DIRECTA | AG14: 1.359 | AH14: M3 | AI14: X | AJ14: 4 | AK14: V4 | AL14: 20260615 | AM14: DW83-900004830-D386-10000383-4
A15: 900004830DW83D38610000377 | B15: 4600050438-110 | C15: 4600050438 | D15: 110 | E15: MXPO | F15: MXL | G15: 900004830 | H15: TC-ED ARMAMPET LAS VARAS | I15: 5061801 | J15: ARMAMPET SA DE CV | K15: N30 | L15: (AP) NAFIN 30 Dias | M15: 10000377 | N15: Grava Triturada Basalto 10 mm - 3/8" | O15: DW83 | P15: MX-CED. VALLARTA | Q15: 20210801 | R15: 20291231 | S15: 20260601 | T15: 20301231 | U15: 334.48 | V15: MXN | W15: M3 | X15: 170.62 | Y15: MXN | Z15: M3 | AA15: D386 | AB15: PD0563 PUNTA DE MITA | AC15: 56103637 | AD15: 6644411540 | AE15: 4 | AF15: ENTREGA DIRECTA | AG15: 1.458 | AH15: M3 | AI15: X | AJ15: 4 | AK15: V4 | AL15: 20260615 | AM15: DW83-900004830-D386-10000377-4
... A20: 900003368DW83D55710000719 | B20: 4600050463-100 | C20: 4600050463 | D20: 100 | E20: MXPO | F20: MXL | G20: 900003368 | H20: TC-ED SALDAÑA PORVENIR | I20: 5002163 | J20: SALDANA MORONES HERIBERTO | K20: N30 | L20: (AP) NAFIN 30 Dias | M20: 10000719 | N20: Arena Clasificada Río Malla 8 | O20: DW83 | P20: MX-CED. VALLARTA | Q20: 20210801 | R20: 20291231 | S20: 20260601 | T20: 20301231 | U20: 431.63 | V20: MXN | W20: M3 | X20: 277.14 | Y20: MXN | Z20: M3 | AA20: D557 | AB20: PD0432 TRONCAL SAN PANCHO | AC20: 56103638 | AD20: 6644411540 | AE20: 4 | AF20: ENTREGA DIRECTA | AG20: 1.442 | AH20: M3 | AI20: X | AJ20: 4 | AK20: V4 | AL20: 20260615 | AM20: DW83-900003368-D557-10000719-4
A21: 900000434DW8310000320 | B21: 4600050409-40 | C21: 4600050409 | D21: 40 | E21: MXPO | F21: MXL | G21: 900000434 | H21: TC-SALDAÑA SANTA FE | I21: 5002163 | J21: SALDANA MORONES HERIBERTO | K21: N30 | L21: (AP) NAFIN 30 Dias | M21: 10000320 | N21: Arena Triturada Caliza Malla 4 | O21: DW83 | P21: MX-CED. VALLARTA | Q21: 20210712 | R21: 20291231 | S21: 20260301 | T21: 20301231 | U21: 132 | V21: MXN | W21: M3 | X21: 0 | Y21: MXN | Z21: M3 | AC21: 56103638 | AD21: 6644411540 | AE21: 1 | AF21: ENTREGADO | AG21: 1.512 | AH21: M3 | AI21: X | AJ21: 4 | AK21: V4 | AL21: 20260619 | AM21: DW83-900000434-10000320
A22: 900000045DW83D26910192197 | B22: 4600050401-10 | C22: 4600050401 | D22: 10 | E22: MXPO | F22: MXL | G22: 900000045 | H22: TC-ED SALDAÑA MORONES | I22: 5002163 | J22: SALDANA MORONES HERIBERTO | K22: N30 | L22: (AP) NAFIN 30 Dias | M22: 10192197 | N22: ARENA CLASIFICADA RIO MALLA 5 | O22: DW83 | P22: MX-CED. VALLARTA | Q22: 20210712 | R22: 20291231 | S22: 20260601 | T22: 20301231 | U22: 195.63 | V22: MXN | W22: M3 | X22: 36.01 | Y22: MXN | Z22: M3 | AA22: D269 | AB22: PD0434 PLANTA MAYAN | AC22: 56103638 | AD22: 6644411540 | AE22: 4 | AF22: ENTREGA DIRECTA | AG22: 1.443 | AH22: M3 | AI22: X | AJ22: 4 | AK22: V4 | AL22: 20260615 | AM22: DW83-900000045-D269-10192197-4
A23: 900000434DW8310000379 | B23: 4600050409-20 | C23: 4600050409 | D23: 20 | E23: MXPO | F23: MXL | G23: 900000434 | H23: TC-SALDAÑA SANTA FE | I23: 5002163 | J23: SALDANA MORONES HERIBERTO | K23: N30 | L23: (AP) NAFIN 30 Dias | M23: 10000379 | N23: Grava Triturada Basalto 20 mm - 3/4" | O23: DW83 | P23: MX-CED. VALLARTA | Q23: 20210712 | R23: 20291231 | S23: 20260601 | T23: 20301231 | U23: 199.56 | V23: MXN | W23: M3 | X23: 0 | Y23: MXN | Z23: M3 | AC23: 56103637 | AD23: 6644411540 | AE23: 1 | AF23: ENTREGADO | AG23: 1.43 | AH23: M3 | AI23: X | AJ23: 4 | AK23: V4 | AL23: 20260619 | AM23: DW83-900000434-10000379
A24: 900000045DW83D26910000719 | B24: 4600050401-60 | C24: 4600050401 | D24: 60 | E24: MXPO | F24: MXL | G24: 900000045 | H24: TC-ED SALDAÑA MORONES | I24: 5002163 | J24: SALDANA MORONES HERIBERTO | K24: N30 | L24: (AP) NAFIN 30 Dias | M24: 10000719 | N24: Arena Clasificada Río Malla 8 | O24: DW83 | P24: MX-CED. VALLARTA | Q24: 20210712 | R24: 20291231 | S24: 20260601 | T24: 20301231 | U24: 192.23 | V24: MXN | W24: M3 | X24: 22.94 | Y24: MXN | Z24: M3 | AA24: D269 | AB24: PD0434 PLANTA MAYAN | AC24: 56103638 | AD24: 6644411540 | AE24: 4 | AF24: ENTREGA DIRECTA | AG24: 1.442 | AH24: M3 | AI24: X | AJ24: 4 | AK24: V4 | AL24: 20260615 | AM24: DW83-900000045-D269-10000719-4
A25: 900000434DW8310000383 | B25: 4600050409-30 | C25: 4600050409 | D25: 30 | E25: MXPO | F25: MXL | G25: 900000434 | H25: TC-SALDAÑA SANTA FE | I25: 5002163 | J25: SALDANA MORONES HERIBERTO | K25: N30 | L25: (AP) NAFIN 30 Dias | M25: 10000383 | N25: Grava Triturada Basalto 40 mm - 1 1/2" | O25: DW83 | P25: MX-CED. VALLARTA | Q25: 20210712 | R25: 20291231 | S25: 20260601 | T25: 20301231 | U25: 199.56 | V25: MXN | W25: M3 | X25: 0 | Y25: MXN | Z25: M3 | AC25: 56103637 | AD25: 6644411540 | AE25: 1 | AF25: ENTREGADO | AG25: 1.359 | AH25: M3 | AI25: X | AJ25: 4 | AK25: V4 | AL25: 20260619 | AM25: DW83-900000434-10000383
A26: 900000434DW8310192197 | B26: 4600050409-50 | C26: 4600050409 | D26: 50 | E26: MXPO | F26: MXL | G26: 900000434 | H26: TC-SALDAÑA SANTA FE | I26: 5002163 | J26: SALDANA MORONES HERIBERTO | K26: N30 | L26: (AP) NAFIN 30 Dias | M26: 10192197 | N26: ARENA CLASIFICADA RIO MALLA 5 | O26: DW83 | P26: MX-CED. VALLARTA | Q26: 20210712 | R26: 20291231 | S26: 20260601 | T26: 20301231 | U26: 154.49 | V26: MXN | W26: M3 | X26: 0 | Y26: MXN | Z26: M3 | AC26: 56103638 | AD26: 6644411540 | AE26: 1 | AF26: ENTREGADO | AG26: 1.443 | AH26: M3 | AI26: X | AJ26: 4 | AK26: V4 | AL26: 20260622 | AM26: DW83-900000434-10192197
A27: 900003368DW83D21510000719 | B27: 4600050463-10 | C27: 4600050463 | D27: 10 | E27: MXPO | F27: MXL | G27: 900003368 | H27: TC-ED SALDAÑA PORVENIR | I27: 5002163 | J27: SALDANA MORONES HERIBERTO | K27: N30 | L27: (AP) NAFIN 30 Dias | M27: 10000719 | N27: Arena Clasificada Río Malla 8 | O27: DW83 | P27: MX-CED. VALLARTA | Q27: 20210801 | R27: 20291231 | S27: 20260601 | T27: 20301231 | U27: 276.02 | V27: MXN | W27: M3 | X27: 121.53 | Y27: MXN | Z27: M3 | AA27: D215 | AB27: PD0159 PUERTO VALLARTA | AC27: 56103638 | AD27: 6644411540 | AE27: 4 | AF27: ENTREGA DIRECTA | AG27: 1.442 | AH27: M3 | AI27: X | AJ27: 4 | AK27: V4 | AL27: 20260615 | AM27: DW83-900003368-D215-10000719-4
A28: 900004830DW83D03310000377 | B28: 4600050438-230 | C28: 4600050438 | D28: 230 | E28: MXPO | F28: MXL | G28: 900004830 | H28: TC-ED ARMAMPET LAS VARAS | I28: 5061801 | J28: ARMAMPET SA DE CV | K28: N30 | L28: (AP) NAFIN 30 Dias | M28: 10000377 | N28: Grava Triturada Basalto 10 mm - 3/8" | O28: DW83 | P28: MX-CED. VALLARTA | Q28: 20210801 | R28: 20291231 | S28: 20260601 | T28: 20301231 | U28: 273.07 | V28: MXN | W28: M3 | X28: 139.19 | Y28: MXN | Z28: M3 | AA28: D033 | AB28: PD0446 TUNELES GUAMUCHIL | AC28: 56103637 | AD28: 6644411540 | AE28: 4 | AF28: ENTREGA DIRECTA | AG28: 1.458 | AH28: M3 | AI28: X | AJ28: 4 | AK28: V4 | AL28: 20260615 | AM28: DW83-900004830-D033-10000377-4
A29: 900004830DW83D03310000379 | B29: 4600050438-30 | C29: 4600050438 | D29: 30 | E29: MXPO | F29: MXL | G29: 900004830 | H29: TC-ED ARMAMPET LAS VARAS | I29: 5061801 | J29: ARMAMPET SA DE CV | K29: N30 | L29: (AP) NAFIN 30 Dias | M29: 10000379 | N29: Grava Triturada Basalto 20 mm - 3/4" | O29: DW83 | P29: MX-CED. VALLARTA | Q29: 20210801 | R29: 20291231 | S29: 20260601 | T29: 20301231 | U29: 303.01 | V29: MXN | W29: M3 | X29: 103.46 | Y29: MXN | Z29: M3 | AA29: D033 | AB29: PD0446 TUNELES GUAMUCHIL | AC29: 56103637 | AD29: 6644411540 | AE29: 4 | AF29: ENTREGA DIRECTA | AG29: 1.43 | AH29: M3 | AI29: X | AJ29: 4 | AK29: V4 | AL29: 20260615 | AM29: DW83-900004830-D033-10000379-4
A30: 900004830DW83D03310000719 | B30: 4600050438-220 | C30: 4600050438 | D30: 220 | E30: MXPO | F30: MXL | G30: 900004830 | H30: TC-ED ARMAMPET LAS VARAS | I30: 5061801 | J30: ARMAMPET SA DE CV | K30: N30 | L30: (AP) NAFIN 30 Dias | M30: 10000719 | N30: Arena Clasificada Río Malla 8 | O30: DW83 | P30: MX-CED. VALLARTA | Q30: 20210801 | R30: 20291231 | S30: 20260601 | T30: 20301231 | U30: 282.27 | V30: MXN | W30: M3 | X30: 127.77 | Y30: MXN | Z30: M3 | AA30: D033 | AB30: PD0446 TUNELES GUAMUCHIL | AC30: 56103638 | AD30: 6644411540 | AE30: 4 | AF30: ENTREGA DIRECTA | AG30: 1.442 | AH30: M3 | AI30: X | AJ30: 4 | AK30: V4 | AL30: 20260615 | AM30: DW83-900004830-D033-10000719-4
A31: 900004830DW83D03310192197 | B31: 4600050438-140 | C31: 4600050438 | D31: 140 | E31: MXPO | F31: MXL | G31: 900004830 | H31: TC-ED ARMAMPET LAS VARAS | I31: 5061801 | J31: ARMAMPET SA DE CV | K31: N30 | L31: (AP) NAFIN 30 Dias | M31: 10192197 | N31: ARENA CLASIFICADA RIO MALLA 5 | O31: DW83 | P31: MX-CED. VALLARTA | Q31: 20210801 | R31: 20291231 | S31: 20260601 | T31: 20301231 | U31: 221.55 | V31: MXN | W31: M3 | X31: 67.04 | Y31: MXN | Z31: M3 | AA31: D033 | AB31: PD0446 TUNELES GUAMUCHIL | AC31: 56103638 | AD31: 6644411540 | AE31: 4 | AF31: ENTREGA DIRECTA | AG31: 1.443 | AH31: M3 | AI31: X | AJ31: 4 | AK31: V4 | AL31: 20260615 | AM31: DW83-900004830-D033-10192197-4
A32: 900003368DW83D21510000377 | B32: 4600050463-20 | C32: 4600050463 | D32: 20 | E32: MXPO | F32: MXL | G32: 900003368 | H32: TC-ED SALDAÑA PORVENIR | I32: 5002163 | J32: SALDANA MORONES HERIBERTO | K32: N30 | L32: (AP) NAFIN 30 Dias | M32: 10000377 | N32: Grava Triturada Basalto 10 mm - 3/8" | O32: DW83 | P32: MX-CED. VALLARTA | Q32: 20210801 | R32: 20291231 | S32: 20260601 | T32: 20301231 | U32: 216.22 | V32: MXN | W32: M3 | X32: 82.33 | Y32: MXN | Z32: M3 | AA32: D215 | AB32: PD0159 PUERTO VALLARTA | AC32: 56103637 | AD32: 6644411540 | AE32: 4 | AF32: ENTREGA DIRECTA | AG32: 1.458 | AH32: M3 | AI32: X | AJ32: 4 | AK32: V4 | AL32: 20260615 | AM32: DW83-900003368-D215-10000377-4
A33: 900007907DW83D21610258539 | B33: 4600056704-30 | C33: 4600056704 | D33: 30 | E33: MXPO | F33: MXL | G33: 900007907 | H33: SF TC-ED- TEPYC LA REPISA | I33: 5006993 | J33: TERRACERIAS PAVIMENTOS Y CAMINOS SA | K33: Z04 | L33: (AP) 30 Dias | M33: 10258539 | N33: ARENA TRITURADA BASALTO MALLA 5 | O33: DW83 | P33: MX-CED. VALLARTA | Q33: 20230227 | R33: 20291231 | S33: 20250301 | T33: 20301231 | U33: 580 | V33: MXN | W33: M3 | X33: 165 | Y33: MXN | Z33: M3 | AA33: D216 | AB33: PD0130 TEPIC | AC33: 56103638 | AD33: 6644411540 | AE33: 4 | AF33: ENTREGA DIRECTA | AG33: 1.591 | AH33: M3 | AI33: X | AJ33: 4 | AK33: V4 | AL33: 20250328 | AM33: DW83-900007907-D216-10258539-4
A34: 900007907DW83D21610000437 | B34: 4600056704-10 | C34: 4600056704 | D34: 10 | E34: MXPO | F34: MXL | G34: 900007907 | H34: SF TC-ED- TEPYC LA REPISA | I34: 5006993 | J34: TERRACERIAS PAVIMENTOS Y CAMINOS SA | K34: Z04 | L34: (AP) 30 Dias | M34: 10000437 | N34: Grava Triturada Basalto 20 mm - 3/4" | O34: DW83 | P34: MX-CED. VALLARTA | Q34: 20230227 | R34: 20291231 | S34: 20250301 | T34: 20301231 | U34: 580 | V34: MXN | W34: M3 | X34: 165 | Y34: MXN | Z34: M3 | AA34: D216 | AB34: PD0130 TEPIC | AC34: 56103637 | AD34: 6644411540 | AE34: 4 | AF34: ENTREGA DIRECTA | AG34: 1.505 | AH34: M3 | AI34: X | AJ34: 4 | AK34: V4 | AL34: 20250328 | AM34: DW83-900007907-D216-10000437-4
A35: 900000434DW8310000719 | B35: 4600050409-60 | C35: 4600050409 | D35: 60 | E35: MXPO | F35: MXL | G35: 900000434 | H35: TC-SALDAÑA SANTA FE | I35: 5002163 | J35: SALDANA MORONES HERIBERTO | K35: N30 | L35: (AP) NAFIN 30 Dias | M35: 10000719 | N35: Arena Clasificada Río Malla 8 | O35: DW83 | P35: MX-CED. VALLARTA | Q35: 20210712 | R35: 20291231 | S35: 20230424 | T35: 20281231 | U35: 165 | V35: MXN | W35: M3 | X35: 0 | Y35: MXN | Z35: M3 | AC35: 56103638 | AD35: 6644411540 | AE35: 1 | AF35: ENTREGADO | AG35: 1.442 | AH35: M3 | AI35: X | AJ35: 4 | AK35: V4 | AL35: 20230920 | AM35: DW83-900000434-10000719
A36: 900000434DW8310000377 | B36: 4600050409-10 | C36: 4600050409 | D36: 10 | E36: MXPO | F36: MXL | G36: 900000434 | H36: TC-SALDAÑA SANTA FE | I36: 5002163 | J36: SALDANA MORONES HERIBERTO | K36: N30 | L36: (AP) NAFIN 30 Dias | M36: 10000377 | N36: Grava Triturada Basalto 10 mm - 3/8" | O36: DW83 | P36: MX-CED. VALLARTA | Q36: 20210712 | R36: 20291231 | S36: 20230301 | T36: 20281231 | U36: 114.4 | V36: MXN | W36: M3 | X36: 0 | Y36: MXN | Z36: M3 | AC36: 56103637 | AD36: 6644411540 | AE36: 1 | AF36: ENTREGADO | AG36: 1.458 | AH36: M3 | AI36: X | AJ36: 4 | AK36: V4 | AL36: 20230920 | AM36: DW83-900000434-10000377
A37: 900007615DW8310049556 | B37: 4600054016-30 | C37: 4600054016 | D37: 30 | E37: MXPO | F37: MXL | G37: 900007615 | H37: SF TC- ARMAMPET LAS VARAS | I37: 5061801 | J37: ARMAMPET SA DE CV | K37: N30 | L37: (AP) NAFIN 30 Dias | M37: 10049556 | N37: Grava Triturada Basalto 10 mm - 3/8" | O37: DW83 | P37: MX-CED. VALLARTA | Q37: 20220523 | R37: 20281231 | S37: 20220523 | T37: 20271231 | U37: 220 | V37: MXN | W37: M3 | X37: 0 | Y37: MXN | Z37: M3 | AC37: 56103637 | AD37: 6644411540 | AE37: 1 | AF37: ENTREGADO | AG37: 1.328 | AH37: M3 | AI37: X | AJ37: 4 | AK37: V4 | AL37: 20230920 | AM37: DW83-900007615-10049556
A38: 900007706DW8310000554 | B38: 4600054398-30 | C38: 4600054398 | D38: 30 | E38: MXPO | F38: MXL | G38: 900007706 | H38: SF TC- CLADIMACO | I38: 5002330 | J38: CLASIFICADORA Y DISTR DE MAT P/CONS | K38: Z03 | L38: (AP) 15 Dias | M38: 10000554 | N38: Grava Triturada Caliza 40 mm - 1 1/2" | O38: DW83 | P38: MX-CED. VALLARTA | Q38: 20220704 | R38: 20271231 | S38: 20220704 | T38: 20271231 | U38: 282.55 | V38: MXN | W38: M3 | X38: 0 | Y38: MXN | Z38: M3 | AC38: 56103637 | AD38: 6644411540 | AE38: 1 | AF38: ENTREGADO | AG38: 1.37 | AH38: M3 | AI38: X | AJ38: 4 | AK38: V4 | AL38: 20230920 | AM38: DW83-900007706-10000554
A39: 900007706DW8310045015 | B39: 4600054398-50 | C39: 4600054398 | D39: 50 | E39: MXPO | F39: MXL | G39: 900007706 | H39: SF TC- CLADIMACO | I39: 5002330 | J39: CLASIFICADORA Y DISTR DE MAT P/CONS | K39: Z03 | L39: (AP) 15 Dias | M39: 10045015 | N39: Sello Triturado Caliza 13 mm - 1/2" | O39: DW83 | P39: MX-CED. VALLARTA | Q39: 20220704 | R39: 20271231 | S39: 20220704 | T39: 20271231 | U39: 420.95 | V39: MXN | W39: M3 | X39: 0 | Y39: MXN | Z39: M3 | AC39: 56103637 | AD39: 6644411540 | AE39: 1 | AF39: ENTREGADO | AG39: 1.43 | AH39: M3 | AI39: X | AJ39: 4 | AK39: V4 | AL39: 20230920 | AM39: DW83-900007706-10045015
A40: 900007706DW8310000332 | B40: 4600054398-60 | C40: 4600054398 | D40: 60 | E40: MXPO | F40: MXL | G40: 900007706 | H40: SF TC- CLADIMACO | I40: 5002330 | J40: CLASIFICADORA Y DISTR DE MAT P/CONS | K40: Z03 | L40: (AP) 15 Dias | M40: 10000332 | N40: Grava Triturada Pomez - Jal 20 mm - 3/4" | O40: DW83 | P40: MX-CED. VALLARTA | Q40: 20220704 | R40: 20271231 | S40: 20220704 | T40: 20271231 | U40: 108.93 | V40: MXN | W40: M3 | X40: 0 | Y40: MXN | Z40: M3 | AC40: 56103637 | AD40: 6644411540 | AE40: 1 | AF40: ENTREGADO | AG40: 0.8 | AH40: M3 | AI40: X | AJ40: 4 | AK40: V4 | AL40: 20230920 | AM40: DW83-900007706-10000332
A41: 900007706DW8310000320 | B41: 4600054398-10 | C41: 4600054398 | D41: 10 | E41: MXPO | F41: MXL | G41: 900007706 | H41: SF TC- CLADIMACO | I41: 5002330 | J41: CLASIFICADORA Y DISTR DE MAT P/CONS | K41: Z03 | L41: (AP) 15 Dias | M41: 10000320 | N41: Arena Triturada Caliza Malla 4 | O41: DW83 | P41: MX-CED. VALLARTA | Q41: 20220704 | R41: 20271231 | S41: 20220704 | T41: 20271231 | U41: 301.38 | V41: MXN | W41: M3 | X41: 0 | Y41: MXN | Z41: M3 | AC41: 56103638 | AD41: 6644411540 | AE41: 1 | AF41: ENTREGADO | AG41: 1.512 | AH41: M3 | AI41: X | AJ41: 4 | AK41: V4 | AL41: 20230920 | AM41: DW83-900007706-10000320
A42: 900007706DW8310000237 | B42: 4600054398-40 | C42: 4600054398 | D42: 40 | E42: MXPO | F42: MXL | G42: 900007706 | H42: SF TC- CLADIMACO | I42: 5002330 | J42: CLASIFICADORA Y DISTR DE MAT P/CONS | K42: Z03 | L42: (AP) 15 Dias | M42: 10000237 | N42: Grava Triturada Caliza 10 mm - 3/8" | O42: DW83 | P42: MX-CED. VALLARTA | Q42: 20220704 | R42: 20271231 | S42: 20220704 | T42: 20271231 | U42: 420.95 | V42: MXN | W42: M3 | X42: 0 | Y42: MXN | Z42: M3 | AC42: 56103637 | AD42: 6644411540 | AE42: 1 | AF42: ENTREGADO | AG42: 1.562 | AH42: M3 | AI42: X | AJ42: 4 | AK42: V4 | AL42: 20230920 | AM42: DW83-900007706-10000237
A43: 900007615DW8310000383 | B43: 4600054016-20 | C43: 4600054016 | D43: 20 | E43: MXPO | F43: MXL | G43: 900007615 | H43: SF TC- ARMAMPET LAS VARAS | I43: 5061801 | J43: ARMAMPET SA DE CV | K43: N30 | L43: (AP) NAFIN 30 Dias | M43: 10000383 | N43: Grava Triturada Basalto 40 mm - 1 1/2" | O43: DW83 | P43: MX-CED. VALLARTA | Q43: 20220523 | R43: 20281231 | S43: 20220523 | T43: 20271231 | U43: 220 | V43: MXN | W43: M3 | X43: 0 | Y43: MXN | Z43: M3 | AC43: 56103637 | AD43: 6644411540 | AE43: 1 | AF43: ENTREGADO | AG43: 1.359 | AH43: M3 | AI43: X | AJ43: 4 | AK43: V4 | AL43: 20230920 | AM43: DW83-900007615-10000383
A44: 900007615DW8310000320 | B44: 4600054016-40 | C44: 4600054016 | D44: 40 | E44: MXPO | F44: MXL | G44: 900007615 | H44: SF TC- ARMAMPET LAS VARAS | I44: 5061801 | J44: ARMAMPET SA DE CV | K44: N30 | L44: (AP) NAFIN 30 Dias | M44: 10000320 | N44: Arena Triturada Caliza Malla 4 | O44: DW83 | P44: MX-CED. VALLARTA | Q44: 20220523 | R44: 20281231 | S44: 20230714 | T44: 20281231 | U44: 386 | V44: MXN | W44: M3 | X44: 0 | Y44: MXN | Z44: M3 | AC44: 56103638 | AD44: 6644411540 | AE44: 1 | AF44: ENTREGADO | AG44: 1.512 | AH44: M3 | AI44: X | AJ44: 4 | AK44: V4 | AL44: 20230920 | AM44: DW83-900007615-10000320
A45: 900007616DW8310000379 | B45: 4600054018-10 | C45: 4600054018 | D45: 10 | E45: MXPO | F45: MXL | G45: 900007616 | H45: SF TC- SALDANA LAS VARAS | I45: 5002163 | J45: SALDANA MORONES HERIBERTO | K45: N30 | L45: (AP) NAFIN 30 Dias | M45: 10000379 | N45: Grava Triturada Basalto 20 mm - 3/4" | O45: DW83 | P45: MX-CED. VALLARTA | Q45: 20220523 | R45: 20281231 | S45: 20220523 | T45: 20271231 | U45: 220 | V45: MXN | W45: M3 | X45: 0 | Y45: MXN | Z45: M3 | AC45: 56103637 | AD45: 6644411540 | AE45: 1 | AF45: ENTREGADO | AG45: 1.43 | AH45: M3 | AI45: X | AJ45: 4 | AK45: V4 | AL45: 20230920 | AM45: DW83-900007616-10000379
A46: 900007616DW8310000383 | B46: 4600054018-20 | C46: 4600054018 | D46: 20 | E46: MXPO | F46: MXL | G46: 900007616 | H46: SF TC- SALDANA LAS VARAS | I46: 5002163 | J46: SALDANA MORONES HERIBERTO | K46: N30 | L46: (AP) NAFIN 30 Dias | M46: 10000383 | N46: Grava Triturada Basalto 40 mm - 1 1/2" | O46: DW83 | P46: MX-CED. VALLARTA | Q46: 20220523 | R46: 20281231 | S46: 20220523 | T46: 20271231 | U46: 220 | V46: MXN | W46: M3 | X46: 0 | Y46: MXN | Z46: M3 | AC46: 56103637 | AD46: 6644411540 | AE46: 1 | AF46: ENTREGADO | AG46: 1.359 | AH46: M3 | AI46: X | AJ46: 4 | AK46: V4 | AL46: 20230920 | AM46: DW83-900007616-10000383
... A49: 900007616DW8310049556 | B49: 4600054018-30 | C49: 4600054018 | D49: 30 | E49: MXPO | F49: MXL | G49: 900007616 | H49: SF TC- SALDANA LAS VARAS | I49: 5002163 | J49: SALDANA MORONES HERIBERTO | K49: N30 | L49: (AP) NAFIN 30 Dias | M49: 10049556 | N49: Grava Triturada Basalto 10 mm - 3/8" | O49: DW83 | P49: MX-CED. VALLARTA | Q49: 20220523 | R49: 20281231 | S49: 20220523 | T49: 20271231 | U49: 220 | V49: MXN | W49: M3 | X49: 0 | Y49: MXN | Z49: M3 | AC49: 56103637 | AD49: 6644411540 | AE49: 1 | AF49: ENTREGADO | AG49: 1.328 | AH49: M3 | AI49: X | AJ49: 4 | AK49: V4 | AL49: 20230920 | AM49: DW83-900007616-10049556
A50: 900007661DW83D21610000383 | B50: 4600054216-30 | C50: 4600054216 | D50: 30 | E50: MXPO | F50: MXL | G50: 900007661 | H50: SF TC-ED- CASCO TEPIC | I50: 5086002 | J50: RENTAS Y CONSTRUCCIONES CASCO DE NA | K50: Z09 | L50: (AP) 90 Dias | M50: 10000383 | N50: Grava Triturada Basalto 40 mm - 1 1/2" | O50: DW83 | P50: MX-CED. VALLARTA | Q50: 20220613 | R50: 20281231 | S50: 20230602 | T50: 20281231 | U50: 453 | V50: MXN | W50: M3 | X50: 73 | Y50: MXN | Z50: M3 | AA50: D216 | AB50: PD0130 TEPIC | AC50: 56103637 | AD50: 6644411540 | AE50: 4 | AF50: ENTREGA DIRECTA | AG50: 1.359 | AH50: M3 | AI50: X | AJ50: 4 | AK50: V4 | AL50: 20230920 | AM50: DW83-900007661-D216-10000383-4
A51: 900008141DW83D21610000377 | B51: 4600057252-80 | C51: 4600057252 | D51: 80 | E51: MXPO | F51: MXL | G51: 900008141 | H51: SF TC-ED TONY SILVA EL COLOMO | I51: 5011365 | J51: SILVA CARVAJAL MARCO ANTONIO | K51: Z03 | L51: (AP) 15 Dias | M51: 10000377 | N51: Grava Triturada Basalto 10 mm - 3/8" | O51: DW83 | P51: MX-CED. VALLARTA | Q51: 20230417 | R51: 20291231 | S51: 20230602 | T51: 20281231 | U51: 540 | V51: MXN | W51: M3 | X51: 430 | Y51: MXN | Z51: M3 | AA51: D216 | AB51: PD0130 TEPIC | AC51: 56103637 | AD51: 6644411540 | AE51: 4 | AF51: ENTREGA DIRECTA | AG51: 1.458 | AH51: M3 | AI51: X | AJ51: 4 | AK51: V4 | AL51: 20230920 | AM51: DW83-900008141-D216-10000377-4
A52: 900007661DW83D21610000379 | B52: 4600054216-20 | C52: 4600054216 | D52: 20 | E52: MXPO | F52: MXL | G52: 900007661 | H52: SF TC-ED- CASCO TEPIC | I52: 5086002 | J52: RENTAS Y CONSTRUCCIONES CASCO DE NA | K52: Z09 | L52: (AP) 90 Dias | M52: 10000379 | N52: Grava Triturada Basalto 20 mm - 3/4" | O52: DW83 | P52: MX-CED. VALLARTA | Q52: 20220613 | R52: 20281231 | S52: 20230602 | T52: 20281231 | U52: 453 | V52: MXN | W52: M3 | X52: 73 | Y52: MXN | Z52: M3 | AA52: D216 | AB52: PD0130 TEPIC | AC52: 56103637 | AD52: 6644411540 | AE52: 4 | AF52: ENTREGA DIRECTA | AG52: 1.43 | AH52: M3 | AI52: X | AJ52: 4 | AK52: V4 | AL52: 20230920 | AM52: DW83-900007661-D216-10000379-4
A53: 900007661DW83D21610000726 | B53: 4600054216-50 | C53: 4600054216 | D53: 50 | E53: MXPO | F53: MXL | G53: 900007661 | H53: SF TC-ED- CASCO TEPIC | I53: 5086002 | J53: RENTAS Y CONSTRUCCIONES CASCO DE NA | K53: Z09 | L53: (AP) 90 Dias | M53: 10000726 | N53: Grava Triturada Basalto 13 mm - 1/2" | O53: DW83 | P53: MX-CED. VALLARTA | Q53: 20220613 | R53: 20281231 | S53: 20220704 | T53: 20271231 | U53: 427.5 | V53: MXN | W53: M3 | X53: 87.5 | Y53: MXN | Z53: M3 | AA53: D216 | AB53: PD0130 TEPIC | AC53: 56103637 | AD53: 6644411540 | AE53: 4 | AF53: ENTREGA DIRECTA | AG53: 1.333 | AH53: M3 | AI53: X | AJ53: 4 | AK53: V4 | AL53: 20230920 | AM53: DW83-900007661-D216-10000726-4
A54: 900007631DW83D21610000318 | B54: 4600054083-20 | C54: 4600054083 | D54: 20 | E54: MXPO | F54: MXL | G54: 900007631 | H54: SF TC-ED- ADAHAN CASAS | I54: 5038881 | K54: Z09 | L54: (AP) 90 Dias | M54: 10000318 | N54: Grava Triturada Caliza 20 mm - 3/4" | O54: DW83 | P54: MX-CED. VALLARTA | Q54: 20220526 | R54: 20271231 | S54: 20220526 | T54: 20271231 | U54: 387.5 | V54: MXN | W54: M3 | X54: 87.5 | Y54: MXN | Z54: M3 | AA54: D216 | AB54: PD0130 TEPIC | AC54: 56103637 | AD54: 6644411540 | AE54: 4 | AF54: ENTREGA DIRECTA | AG54: 1.35 | AH54: M3 | AI54: X | AJ54: 4 | AK54: V4 | AL54: 20230828 | AM54: DW83-900007631-D216-10000318-4
A55: 900007631DW83D21610000554 | B55: 4600054083-30 | C55: 4600054083 | D55: 30 | E55: MXPO | F55: MXL | G55: 900007631 | H55: SF TC-ED- ADAHAN CASAS | I55: 5038881 | K55: Z09 | L55: (AP) 90 Dias | M55: 10000554 | N55: Grava Triturada Caliza 40 mm - 1 1/2" | O55: DW83 | P55: MX-CED. VALLARTA | Q55: 20220526 | R55: 20271231 | S55: 20220526 | T55: 20271231 | U55: 387.5 | V55: MXN | W55: M3 | X55: 87.5 | Y55: MXN | Z55: M3 | AA55: D216 | AB55: PD0130 TEPIC | AC55: 56103637 | AD55: 6644411540 | AE55: 4 | AF55: ENTREGA DIRECTA | AG55: 1.37 | AH55: M3 | AI55: X | AJ55: 4 | AK55: V4 | AL55: 20230828 | AM55: DW83-900007631-D216-10000554-4
A56: 900007661DW83D21610049556 | B56: 4600054216-40 | C56: 4600054216 | D56: 40 | E56: MXPO | F56: MXL | G56: 900007661 | H56: SF TC-ED- CASCO TEPIC | I56: 5086002 | J56: RENTAS Y CONSTRUCCIONES CASCO DE NA | K56: Z09 | L56: (AP) 90 Dias | M56: 10049556 | N56: Grava Triturada Basalto 10 mm - 3/8" | O56: DW83 | P56: MX-CED. VALLARTA | Q56: 20220613 | R56: 20281231 | S56: 20230602 | T56: 20281231 | U56: 453 | V56: MXN | W56: M3 | X56: 73 | Y56: MXN | Z56: M3 | AA56: D216 | AB56: PD0130 TEPIC | AC56: 56103637 | AD56: 6644411540 | AE56: 4 | AF56: ENTREGA DIRECTA | AG56: 1.328 | AH56: M3 | AI56: X | AJ56: 4 | AK56: V4 | AL56: 20230920 | AM56: DW83-900007661-D216-10049556-4
A57: 900008141DW83D21610000719 | B57: 4600057252-70 | C57: 4600057252 | D57: 70 | E57: MXPO | F57: MXL | G57: 900008141 | H57: SF TC-ED TONY SILVA EL COLOMO | I57: 5011365 | J57: SILVA CARVAJAL MARCO ANTONIO | K57: Z03 | L57: (AP) 15 Dias | M57: 10000719 | N57: Arena Clasificada Río Malla 8 | O57: DW83 | P57: MX-CED. VALLARTA | Q57: 20230417 | R57: 20291231 | S57: 20230602 | T57: 20281231 | U57: 590 | V57: MXN | W57: M3 | X57: 430 | Y57: MXN | Z57: M3 | AA57: D216 | AB57: PD0130 TEPIC | AC57: 56103638 | AD57: 6644411540 | AE57: 4 | AF57: ENTREGA DIRECTA | AG57: 1.442 | AH57: M3 | AI57: X | AJ57: 4 | AK57: V4 | AL57: 20230920 | AM57: DW83-900008141-D216-10000719-4
A58: 900007631DW83D21610000237 | B58: 4600054083-40 | C58: 4600054083 | D58: 40 | E58: MXPO | F58: MXL | G58: 900007631 | H58: SF TC-ED- ADAHAN CASAS | I58: 5038881 | K58: Z09 | L58: (AP) 90 Dias | M58: 10000237 | N58: Grava Triturada Caliza 10 mm - 3/8" | O58: DW83 | P58: MX-CED. VALLARTA | Q58: 20220526 | R58: 20271231 | S58: 20220526 | T58: 20271231 | U58: 437.5 | V58: MXN | W58: M3 | X58: 87.5 | Y58: MXN | Z58: M3 | AA58: D216 | AB58: PD0130 TEPIC | AC58: 56103637 | AD58: 6644411540 | AE58: 4 | AF58: ENTREGA DIRECTA | AG58: 1.562 | AH58: M3 | AI58: X | AJ58: 4 | AK58: V4 | AL58: 20230828 | AM58: DW83-900007631-D216-10000237-4
A59: 900003368DW83D21610000719 | B59: 4600050463-70 | C59: 4600050463 | D59: 70 | E59: MXPO | F59: MXL | G59: 900003368 | H59: TC-ED SALDAÑA PORVENIR | I59: 5002163 | J59: SALDANA MORONES HERIBERTO | K59: N30 | L59: (AP) NAFIN 30 Dias | M59: 10000719 | N59: Arena Clasificada Río Malla 8 | O59: DW83 | P59: MX-CED. VALLARTA | Q59: 20210801 | R59: 20291231 | S59: 20230203 | T59: 20281231 | U59: 460 | V59: MXN | W59: M3 | X59: 320 | Y59: MXN | Z59: M3 | AA59: D216 | AB59: PD0130 TEPIC | AC59: 56103638 | AD59: 6644411540 | AE59: 4 | AF59: ENTREGA DIRECTA | AG59: 1.442 | AH59: M3 | AI59: X | AJ59: 4 | AK59: V4 | AL59: 20230920 | AM59: DW83-900003368-D216-10000719-4
A60: 900007631DW83D21610000320 | B60: 4600054083-10 | C60: 4600054083 | D60: 10 | E60: MXPO | F60: MXL | G60: 900007631 | H60: SF TC-ED- ADAHAN CASAS | I60: 5038881 | K60: Z09 | L60: (AP) 90 Dias | M60: 10000320 | N60: Arena Triturada Caliza Malla 4 | O60: DW83 | P60: MX-CED. VALLARTA | Q60: 20220526 | R60: 20271231 | S60: 20220526 | T60: 20271231 | U60: 407.5 | V60: MXN | W60: M3 | X60: 87.5 | Y60: MXN | Z60: M3 | AA60: D216 | AB60: PD0130 TEPIC | AC60: 56103638 | AD60: 6644411540 | AE60: 4 | AF60: ENTREGA DIRECTA | AG60: 1.512 | AH60: M3 | AI60: X | AJ60: 4 | AK60: V4 | AL60: 20230828 | AM60: DW83-900007631-D216-10000320-4
A61: 900007661DW83D21610000857 | B61: 4600054216-10 | C61: 4600054216 | D61: 10 | E61: MXPO | F61: MXL | G61: 900007661 | H61: SF TC-ED- CASCO TEPIC | I61: 5086002 | J61: RENTAS Y CONSTRUCCIONES CASCO DE NA | K61: Z09 | L61: (AP) 90 Dias | M61: 10000857 | N61: Arena Triturada Basalto Malla 4 | O61: DW83 | P61: MX-CED. VALLARTA | Q61: 20220613 | R61: 20281231 | S61: 20230602 | T61: 20281231 | U61: 463 | V61: MXN | W61: M3 | X61: 73 | Y61: MXN | Z61: M3 | AA61: D216 | AB61: PD0130 TEPIC | AC61: 56103638 | AD61: 6644411540 | AE61: 4 | AF61: ENTREGA DIRECTA | AG61: 1.51 | AH61: M3 | AI61: X | AJ61: 4 | AK61: V4 | AL61: 20230920 | AM61: DW83-900007661-D216-10000857-4
A62: 900000050DW83D21610000332 | B62: 4600050402-20 | C62: 4600050402 | D62: 20 | E62: MXPO | F62: MXL | G62: 900000050 | H62: TC-ED-CLADIMACO | I62: 5002330 | J62: CLASIFICADORA Y DISTR DE MAT P/CONS | K62: Z03 | L62: (AP) 15 Dias | M62: 10000332 | N62: Grava Triturada Pomez - Jal 20 mm - 3/4" | O62: DW83 | P62: MX-CED. VALLARTA | Q62: 20210712 | R62: 20271231 | S62: 20220701 | T62: 20251231 | U62: 157.45 | V62: MXN | W62: M3 | X62: 48.52 | Y62: MXN | Z62: M3 | AA62: D216 | AB62: PD0130 TEPIC | AC62: 56103637 | AD62: 6644411540 | AE62: 4 | AF62: ENTREGA DIRECTA | AG62: 0.8 | AH62: M3 | AI62: X | AJ62: 4 | AK62: V4 | AL62: 20230920 | AM62: DW83-900000050-D216-10000332-4
A63: 900000050DW83D21610000237 | B63: 4600050402-50 | C63: 4600050402 | D63: 50 | E63: MXPO | F63: MXL | G63: 900000050 | H63: TC-ED-CLADIMACO | I63: 5002330 | J63: CLASIFICADORA Y DISTR DE MAT P/CONS | K63: Z03 | L63: (AP) 15 Dias | M63: 10000237 | N63: Grava Triturada Caliza 10 mm - 3/8" | O63: DW83 | P63: MX-CED. VALLARTA | Q63: 20210712 | R63: 20271231 | S63: 20230201 | T63: 20271231 | U63: 510.14 | V63: MXN | W63: M3 | X63: 59.71 | Y63: MXN | Z63: M3 | AA63: D216 | AB63: PD0130 TEPIC | AC63: 56103637 | AD63: 6644411540 | AE63: 4 | AF63: ENTREGA DIRECTA | AG63: 1.562 | AH63: M3 | AI63: X | AJ63: 4 | AK63: V4 | AL63: 20230920 | AM63: DW83-900000050-D216-10000237-4
A64: 900000050DW83D21610000320 | B64: 4600050402-30 | C64: 4600050402 | D64: 30 | E64: MXPO | F64: MXL | G64: 900000050 | H64: TC-ED-CLADIMACO | I64: 5002330 | J64: CLASIFICADORA Y DISTR DE MAT P/CONS | K64: Z03 | L64: (AP) 15 Dias | M64: 10000320 | N64: Arena Triturada Caliza Malla 4 | O64: DW83 | P64: MX-CED. VALLARTA | Q64: 20210712 | R64: 20271231 | S64: 20230201 | T64: 20271231 | U64: 383.2 | V64: MXN | W64: M3 | X64: 59.71 | Y64: MXN | Z64: M3 | AA64: D216 | AB64: PD0130 TEPIC | AC64: 56103638 | AD64: 6644411540 | AE64: 4 | AF64: ENTREGA DIRECTA | AG64: 1.512 | AH64: M3 | AI64: X | AJ64: 4 | AK64: V4 | AL64: 20230920 | AM64: DW83-900000050-D216-10000320-4
A65: 900000050DW83D21610000318 | B65: 4600050402-40 | C65: 4600050402 | D65: 40 | E65: MXPO | F65: MXL | G65: 900000050 | H65: TC-ED-CLADIMACO | I65: 5002330 | J65: CLASIFICADORA Y DISTR DE MAT P/CONS | K65: Z03 | L65: (AP) 15 Dias | M65: 10000318 | N65: Grava Triturada Caliza 20 mm - 3/4" | O65: DW83 | P65: MX-CED. VALLARTA | Q65: 20210712 | R65: 20271231 | S65: 20230201 | T65: 20271231 | U65: 362.73 | V65: MXN | W65: M3 | X65: 59.71 | Y65: MXN | Z65: M3 | AA65: D216 | AB65: PD0130 TEPIC | AC65: 56103637 | AD65: 6644411540 | AE65: 4 | AF65: ENTREGA DIRECTA | AG65: 1.35 | AH65: M3 | AI65: X | AJ65: 4 | AK65: V4 | AL65: 20230920 | AM65: DW83-900000050-D216-10000318-4
A66: 900000050DW83D38610000332 | B66: 4600050402-70 | C66: 4600050402 | D66: 70 | E66: MXPO | F66: MXL | G66: 900000050 | H66: TC-ED-CLADIMACO | I66: 5002330 | J66: CLASIFICADORA Y DISTR DE MAT P/CONS | K66: Z03 | L66: (AP) 15 Dias | M66: 10000332 | N66: Grava Triturada Pomez - Jal 20 mm - 3/4" | O66: DW83 | P66: MX-CED. VALLARTA | Q66: 20210712 | R66: 20271231 | S66: 20211125 | T66: 20261231 | U66: 461 | V66: MXN | W66: M3 | X66: 382 | Y66: MXN | Z66: M3 | AA66: D386 | AB66: PD0563 PUNTA DE MITA | AC66: 56103637 | AD66: 6644411540 | AE66: 4 | AF66: ENTREGA DIRECTA | AG66: 0.8 | AH66: M3 | AI66: X | AJ66: 4 | AK66: V4 | AL66: 20230920 | AM66: DW83-900000050-D386-10000332-4
A67: 900004830DW83D03310000726 | B67: 4600050438-10 | C67: 4600050438 | D67: 10 | E67: MXPO | F67: MXL | G67: 900004830 | H67: TC-ED ARMAMPET LAS VARAS | I67: 5061801 | J67: ARMAMPET SA DE CV | K67: N30 | L67: (AP) NAFIN 30 Dias | M67: 10000726 | N67: Grava Triturada Basalto 13 mm - 1/2" | O67: DW83 | P67: MX-CED. VALLARTA | Q67: 20210801 | R67: 20291231 | S67: 20230301 | T67: 20281231 | U67: 348.38 | V67: MXN | W67: M3 | X67: 183.38 | Y67: MXN | Z67: M3 | AA67: D033 | AB67: PD0446 TUNELES GUAMUCHIL | AC67: 56103637 | AD67: 6644411540 | AE67: 4 | AF67: ENTREGA DIRECTA | AG67: 1.333 | AH67: M3 | AI67: X | AJ67: 4 | AK67: V4 | AL67: 20230920 | AM67: DW83-900004830-D033-10000726-4
A68: 900004830DW83D21610000379 | B68: 4600050438-250 | C68: 4600050438 | D68: 250 | E68: MXPO | F68: MXL | G68: 900004830 | H68: TC-ED ARMAMPET LAS VARAS | I68: 5061801 | J68: ARMAMPET SA DE CV | K68: N30 | L68: (AP) NAFIN 30 Dias | M68: 10000379 | N68: Grava Triturada Basalto 20 mm - 3/4" | O68: DW83 | P68: MX-CED. VALLARTA | Q68: 20210801 | R68: 20291231 | S68: 20230203 | T68: 20281231 | U68: 410 | V68: MXN | W68: M3 | X68: 239.5 | Y68: MXN | Z68: M3 | AA68: D216 | AB68: PD0130 TEPIC | AC68: 56103637 | AD68: 6644411540 | AE68: 4 | AF68: ENTREGA DIRECTA | AG68: 1.43 | AH68: M3 | AI68: X | AJ68: 4 | AK68: V4 | AL68: 20230920 | AM68: DW83-900004830-D216-10000379-4
A69: 900000050DW83D21610000554 | B69: 4600050402-10 | C69: 4600050402 | D69: 10 | E69: MXPO | F69: MXL | G69: 900000050 | H69: TC-ED-CLADIMACO | I69: 5002330 | J69: CLASIFICADORA Y DISTR DE MAT P/CONS | K69: Z03 | L69: (AP) 15 Dias | M69: 10000554 | N69: Grava Triturada Caliza 40 mm - 1 1/2" | O69: DW83 | P69: MX-CED. VALLARTA | Q69: 20210712 | R69: 20271231 | S69: 20230201 | T69: 20271231 | U69: 362.73 | V69: MXN | W69: M3 | X69: 59.71 | Y69: MXN | Z69: M3 | AA69: D216 | AB69: PD0130 TEPIC | AC69: 56103637 | AD69: 6644411540 | AE69: 4 | AF69: ENTREGA DIRECTA | AG69: 1.37 | AH69: M3 | AI69: X | AJ69: 4 | AK69: V4 | AL69: 20230920 | AM69: DW83-900000050-D216-10000554-4
A70: 900000050DW83D21610045015 | B70: 4600050402-60 | C70: 4600050402 | D70: 60 | E70: MXPO | F70: MXL | G70: 900000050 | H70: TC-ED-CLADIMACO | I70: 5002330 | J70: CLASIFICADORA Y DISTR DE MAT P/CONS | K70: Z03 | L70: (AP) 15 Dias | M70: 10045015 | N70: Sello Triturado Caliza 13 mm - 1/2" | O70: DW83 | P70: MX-CED. VALLARTA | Q70: 20210712 | R70: 20271231 | S70: 20220701 | T70: 20251231 | U70: 469.47 | V70: MXN | W70: M3 | X70: 48.52 | Y70: MXN | Z70: M3 | AA70: D216 | AB70: PD0130 TEPIC | AC70: 56103637 | AD70: 6644411540 | AE70: 4 | AF70: ENTREGA DIRECTA | AG70: 1.43 | AH70: M3 | AI70: X | AJ70: 4 | AK70: V4 | AL70: 20230920 | AM70: DW83-900000050-D216-10045015-4
A71: 900004830DW83D21610000383 | B71: 4600050438-240 | C71: 4600050438 | D71: 240 | E71: MXPO | F71: MXL | G71: 900004830 | H71: TC-ED ARMAMPET LAS VARAS | I71: 5061801 | J71: ARMAMPET SA DE CV | K71: N30 | L71: (AP) NAFIN 30 Dias | M71: 10000383 | N71: Grava Triturada Basalto 40 mm - 1 1/2" | O71: DW83 | P71: MX-CED. VALLARTA | Q71: 20210801 | R71: 20291231 | S71: 20230203 | T71: 20281231 | U71: 410 | V71: MXN | W71: M3 | X71: 239.5 | Y71: MXN | Z71: M3 | AA71: D216 | AB71: PD0130 TEPIC | AC71: 56103637 | AD71: 6644411540 | AE71: 4 | AF71: ENTREGA DIRECTA | AG71: 1.359 | AH71: M3 | AI71: X | AJ71: 4 | AK71: V4 | AL71: 20230920 | AM71: DW83-900004830-D216-10000383-4
A72: 900007347DW83D21610000318 | B72: 4600052206-20 | C72: 4600052206 | D72: 20 | E72: MXPO | F72: MXL | G72: 900007347 | H72: SF TC-ED- CLADIMACO 14 | I72: 5002330 | J72: CLASIFICADORA Y DISTR DE MAT P/CONS | K72: Z03 | L72: (AP) 15 Dias | M72: 10000318 | N72: Grava Triturada Caliza 20 mm - 3/4" | O72: DW83 | P72: MX-CED. VALLARTA | Q72: 20211012 | R72: 20261231 | S72: 20211012 | T72: 20261231 | U72: 283.24 | V72: MXN | W72: M3 | X72: 44.11 | Y72: MXN | Z72: M3 | AA72: D216 | AB72: PD0130 TEPIC | AC72: 56103637 | AD72: 6644411540 | AE72: 4 | AF72: ENTREGA DIRECTA | AG72: 1.35 | AH72: M3 | AI72: X | AJ72: 4 | AK72: V4 | AL72: 20260108 | AM72: DW83-900007347-D216-10000318-4
A73: 900007868DW8310000191 | B73: 4600057014-10 | C73: 4600057014 | D73: 10 | E73: MXPO | F73: MXL | G73: 900007868 | H73: SF TC- SAN MIGUEL CUYUTLAN | I73: 5002462 | J73: GRAVA Y ARENA DEL SALTO SA DE CV | K73: Z09 | L73: (AP) 90 Dias | M73: 10000191 | N73: Grava Triturada Basalto 20 mm - 3/4" | O73: DW83 | P73: MX-CED. VALLARTA | Q73: 20230324 | R73: 20291231 | S73: 20250224 | T73: 20301231 | U73: 251.9 | V73: MXN | W73: M3 | X73: 0 | Y73: MXN | Z73: M3 | AC73: 56103637 | AD73: 6644411540 | AE73: 1 | AF73: ENTREGADO | AG73: 1.41 | AH73: M3 | AI73: X | AJ73: 4 | AK73: V4 | AL73: 20250310 | AM73: DW83-900007868-10000191
A74: 900007347DW83D21610000320 | B74: 4600052206-10 | C74: 4600052206 | D74: 10 | E74: MXPO | F74: MXL | G74: 900007347 | H74: SF TC-ED- CLADIMACO 14 | I74: 5002330 | J74: CLASIFICADORA Y DISTR DE MAT P/CONS | K74: Z03 | L74: (AP) 15 Dias | M74: 10000320 | N74: Arena Triturada Caliza Malla 4 | O74: DW83 | P74: MX-CED. VALLARTA | Q74: 20211012 | R74: 20261231 | S74: 20211012 | T74: 20261231 | U74: 283.24 | V74: MXN | W74: M3 | X74: 44.11 | Y74: MXN | Z74: M3 | AA74: D216 | AB74: PD0130 TEPIC | AC74: 56103638 | AD74: 6644411540 | AE74: 4 | AF74: ENTREGA DIRECTA | AG74: 1.512 | AH74: M3 | AI74: X | AJ74: 4 | AK74: V4 | AL74: 20260108 | AM74: DW83-900007347-D216-10000320-4
A75: 900007868DW8310000388 | B75: 4600057014-20 | C75: 4600057014 | D75: 20 | E75: MXPO | F75: MXL | G75: 900007868 | H75: SF TC- SAN MIGUEL CUYUTLAN | I75: 5002462 | J75: GRAVA Y ARENA DEL SALTO SA DE CV | K75: Z09 | L75: (AP) 90 Dias | M75: 10000388 | N75: Grava Triturada Basalto 40 mm - 1 1/2" | O75: DW83 | P75: MX-CED. VALLARTA | Q75: 20230324 | R75: 20291231 | S75: 20250224 | T75: 20301231 | U75: 251.91 | V75: MXN | W75: M3 | X75: 0 | Y75: MXN | Z75: M3 | AC75: 56103637 | AD75: 6644411540 | AE75: 1 | AF75: ENTREGADO | AG75: 1.395 | AH75: M3 | AI75: X | AJ75: 4 | AK75: V4 | AL75: 20250310 | AM75: DW83-900007868-10000388
A76: 900008141DW83D21610192197 | B76: 4600057252-110 | C76: 4600057252 | D76: 110 | E76: MXPO | F76: MXL | G76: 900008141 | H76: SF TC-ED TONY SILVA EL COLOMO | I76: 5011365 | J76: SILVA CARVAJAL MARCO ANTONIO | K76: Z03 | L76: (AP) 15 Dias | M76: 10192197 | N76: ARENA CLASIFICADA RIO MALLA 5 | O76: DW83 | P76: MX-CED. VALLARTA | Q76: 20230417 | R76: 20291231 | S76: 20230705 | T76: 20281231 | U76: 560 | V76: MXN | W76: M3 | X76: 428 | Y76: MXN | Z76: M3 | AA76: D216 | AB76: PD0130 TEPIC | AC76: 56103638 | AD76: 6644411540 | AE76: 4 | AF76: ENTREGA DIRECTA | AG76: 1.443 | AH76: M3 | AI76: X | AJ76: 4 | AK76: V4 | AL76: 20230920 | AM76: DW83-900008141-D216-10192197-4
A77: 900008141DW83D21610000379 | B77: 4600057252-10 | C77: 4600057252 | D77: 10 | E77: MXPO | F77: MXL | G77: 900008141 | H77: SF TC-ED TONY SILVA EL COLOMO | I77: 5011365 | J77: SILVA CARVAJAL MARCO ANTONIO | K77: Z03 | L77: (AP) 15 Dias | M77: 10000379 | N77: Grava Triturada Basalto 20 mm - 3/4" | O77: DW83 | P77: MX-CED. VALLARTA | Q77: 20230417 | R77: 20291231 | S77: 20230417 | T77: 20281231 | U77: 590 | V77: MXN | W77: M3 | X77: 419.5 | Y77: MXN | Z77: M3 | AA77: D216 | AB77: PD0130 TEPIC | AC77: 56103637 | AD77: 6644411540 | AE77: 4 | AF77: ENTREGA DIRECTA | AG77: 1.43 | AH77: M3 | AI77: X | AJ77: 4 | AK77: V4 | AL77: 20230920 | AM77: DW83-900008141-D216-10000379-4
A78: 900008141DW83D21610000383 | B78: 4600057252-20 | C78: 4600057252 | D78: 20 | E78: MXPO | F78: MXL | G78: 900008141 | H78: SF TC-ED TONY SILVA EL COLOMO | I78: 5011365 | J78: SILVA CARVAJAL MARCO ANTONIO | K78: Z03 | L78: (AP) 15 Dias | M78: 10000383 | N78: Grava Triturada Basalto 40 mm - 1 1/2" | O78: DW83 | P78: MX-CED. VALLARTA | Q78: 20230417 | R78: 20291231 | S78: 20230417 | T78: 20281231 | U78: 590 | V78: MXN | W78: M3 | X78: 419.5 | Y78: MXN | Z78: M3 | AA78: D216 | AB78: PD0130 TEPIC | AC78: 56103637 | AD78: 6644411540 | AE78: 4 | AF78: ENTREGA DIRECTA | AG78: 1.359 | AH78: M3 | AI78: X | AJ78: 4 | AK78: V4 | AL78: 20230920 | AM78: DW83-900008141-D216-10000383-4
A79: 900008141DW83D21610000320 | B79: 4600057252-30 | C79: 4600057252 | D79: 30 | E79: MXPO | F79: MXL | G79: 900008141 | H79: SF TC-ED TONY SILVA EL COLOMO | I79: 5011365 | J79: SILVA CARVAJAL MARCO ANTONIO | K79: Z03 | L79: (AP) 15 Dias | M79: 10000320 | N79: Arena Triturada Caliza Malla 4 | O79: DW83 | P79: MX-CED. VALLARTA | Q79: 20230417 | R79: 20291231 | S79: 20230417 | T79: 20281231 | U79: 560 | V79: MXN | W79: M3 | X79: 428 | Y79: MXN | Z79: M3 | AA79: D216 | AB79: PD0130 TEPIC | AC79: 56103638 | AD79: 6644411540 | AE79: 4 | AF79: ENTREGA DIRECTA | AG79: 1.512 | AH79: M3 | AI79: X | AJ79: 4 | AK79: V4 | AL79: 20230920 | AM79: DW83-900008141-D216-10000320-4
A80: 900004995DW83D38610210656 | B80: 4600054529-10 | C80: 4600054529 | D80: 10 | E80: MXPO | F80: MXL | G80: 900004995 | H80: TC-ED LA FUNDICION | I80: 5065714 | J80: GRUPO MINERO LA FUNDICION SA DE CV | K80: N60 | L80: (AP) NAFIN 60 Dias | M80: 10210656 | N80: GRAVA TRITURADA POMEZ - JAL 20 MM - 3/4" | O80: DW83 | P80: MX-CED. VALLARTA | Q80: 20220630 | R80: 20291231 | S80: 20240301 | T80: 20291231 | U80: 773.7 | V80: MXN | W80: M3 | X80: 614.7 | Y80: MXN | Z80: M3 | AA80: D386 | AB80: PD0563 PUNTA DE MITA | AC80: 56103637 | AD80: 6644411540 | AE80: 4 | AF80: ENTREGA DIRECTA | AG80: 0.8 | AH80: M3 | AI80: X | AJ80: 4 | AK80: V4 | AL80: 20240531 | AM80: DW83-900004995-D386-10210656-4
A81: 900008141DW83D21510000332 | B81: 4600057252-150 | C81: 4600057252 | D81: 150 | E81: MXPO | F81: MXL | G81: 900008141 | H81: SF TC-ED TONY SILVA EL COLOMO | I81: 5011365 | J81: SILVA CARVAJAL MARCO ANTONIO | K81: Z03 | L81: (AP) 15 Dias | M81: 10000332 | N81: Grava Triturada Pomez - Jal 20 mm - 3/4" | O81: DW83 | P81: MX-CED. VALLARTA | Q81: 20230417 | R81: 20291231 | S81: 20240307 | T81: 20291231 | U81: 500 | V81: MXN | W81: M3 | X81: 250 | Y81: MXN | Z81: M3 | AA81: D215 | AB81: PD0159 PUERTO VALLARTA | AC81: 56103637 | AD81: 6644411540 | AE81: 4 | AF81: ENTREGA DIRECTA | AG81: 0.8 | AH81: M3 | AI81: X | AJ81: 4 | AK81: V4 | AL81: 20240312 | AM81: DW83-900008141-D215-10000332-4
A82: 900001405DW83D21510001867 | B82: 4600050415-10 | C82: 4600050415 | D82: 10 | E82: MXPO | F82: MXL | G82: 900001405 | H82: TC-ED CALCIO Y MARMOLINAS | I82: 5002495 | J82: CALCIO Y MARMOLINAS SA DE CV | K82: Z09 | L82: (AP) 90 Dias | M82: 10001867 | N82: GRAVA TRITURADA MARMOL 10 MM - 3/8" | O82: DW83 | P82: MX-CED. VALLARTA | Q82: 20210712 | R82: 20261231 | S82: 20210712 | T82: 20261231 | U82: 1250 | V82: MXN | W82: TN | X82: 1000 | Y82: MXN | Z82: TN | AA82: D215 | AB82: PD0159 PUERTO VALLARTA | AC82: 56103637 | AD82: 6644411540 | AE82: 4 | AF82: ENTREGA DIRECTA | AG82: 1 | AH82: TO | AI82: X | AJ82: 4 | AK82: V4 | AL82: 20260108 | AM82: DW83-900001405-D215-10001867-4
A83: 900008141DW83D55710000332 | B83: 4600057252-180 | C83: 4600057252 | D83: 180 | E83: MXPO | F83: MXL | G83: 900008141 | H83: SF TC-ED TONY SILVA EL COLOMO | I83: 5011365 | J83: SILVA CARVAJAL MARCO ANTONIO | K83: Z03 | L83: (AP) 15 Dias | M83: 10000332 | N83: Grava Triturada Pomez - Jal 20 mm - 3/4" | O83: DW83 | P83: MX-CED. VALLARTA | Q83: 20230417 | R83: 20291231 | S83: 20240307 | T83: 20291231 | U83: 450 | V83: MXN | W83: M3 | X83: 200 | Y83: MXN | Z83: M3 | AA83: D557 | AB83: PD0432 TRONCAL SAN PANCHO | AC83: 56103637 | AD83: 6644411540 | AE83: 4 | AF83: ENTREGA DIRECTA | AG83: 0.8 | AH83: M3 | AI83: X | AJ83: 4 | AK83: V4 | AL83: 20240312 | AM83: DW83-900008141-D557-10000332-4
A84: 900008141DW83D03310000332 | B84: 4600057252-170 | C84: 4600057252 | D84: 170 | E84: MXPO | F84: MXL | G84: 900008141 | H84: SF TC-ED TONY SILVA EL COLOMO | I84: 5011365 | J84: SILVA CARVAJAL MARCO ANTONIO | K84: Z03 | L84: (AP) 15 Dias | M84: 10000332 | N84: Grava Triturada Pomez - Jal 20 mm - 3/4" | O84: DW83 | P84: MX-CED. VALLARTA | Q84: 20230417 | R84: 20291231 | S84: 20240307 | T84: 20291231 | U84: 475 | V84: MXN | W84: M3 | X84: 225 | Y84: MXN | Z84: M3 | AA84: D033 | AB84: PD0446 TUNELES GUAMUCHIL | AC84: 56103637 | AD84: 6644411540 | AE84: 4 | AF84: ENTREGA DIRECTA | AG84: 0.8 | AH84: M3 | AI84: X | AJ84: 4 | AK84: V4 | AL84: 20240312 | AM84: DW83-900008141-D033-10000332-4
A85: 900008141DW83D38610000332 | B85: 4600057252-160 | C85: 4600057252 | D85: 160 | E85: MXPO | F85: MXL | G85: 900008141 | H85: SF TC-ED TONY SILVA EL COLOMO | I85: 5011365 | J85: SILVA CARVAJAL MARCO ANTONIO | K85: Z03 | L85: (AP) 15 Dias | M85: 10000332 | N85: Grava Triturada Pomez - Jal 20 mm - 3/4" | O85: DW83 | P85: MX-CED. VALLARTA | Q85: 20230417 | R85: 20291231 | S85: 20240307 | T85: 20291231 | U85: 500 | V85: MXN | W85: M3 | X85: 250 | Y85: MXN | Z85: M3 | AA85: D386 | AB85: PD0563 PUNTA DE MITA | AC85: 56103637 | AD85: 6644411540 | AE85: 4 | AF85: ENTREGA DIRECTA | AG85: 0.8 | AH85: M3 | AI85: X | AJ85: 4 | AK85: V4 | AL85: 20240312 | AM85: DW83-900008141-D386-10000332-4
A86: 900005573DW83D21510000377 | B86: 4600050449-10 | C86: 4600050449 | D86: 10 | E86: MXPO | F86: MXL | G86: 900005573 | H86: TC-ED COMERCIALIZADORA MC | I86: 5069533 | J86: COMERCIALIZADORA DE MATERIALES DE | K86: Z09 | L86: (AP) 90 Dias | M86: 10000377 | N86: Grava Triturada Basalto 10 mm - 3/8" | O86: DW83 | P86: MX-CED. VALLARTA | Q86: 20210801 | R86: 20261231 | S86: 20210712 | T86: 20261231 | U86: 100 | V86: MXN | W86: M3 | X86: 30 | Y86: MXN | Z86: M3 | AA86: D215 | AB86: PD0159 PUERTO VALLARTA | AC86: 56103637 | AD86: 6644411540 | AE86: 4 | AF86: ENTREGA DIRECTA | AG86: 1.458 | AH86: M3 | AI86: X | AJ86: 4 | AK86: V4 | AL86: 20260108 | AM86: DW83-900005573-D215-10000377-4
A87: 900005573DW83D21510000383 | B87: 4600050449-20 | C87: 4600050449 | D87: 20 | E87: MXPO | F87: MXL | G87: 900005573 | H87: TC-ED COMERCIALIZADORA MC | I87: 5069533 | J87: COMERCIALIZADORA DE MATERIALES DE | K87: Z09 | L87: (AP) 90 Dias | M87: 10000383 | N87: Grava Triturada Basalto 40 mm - 1 1/2" | O87: DW83 | P87: MX-CED. VALLARTA | Q87: 20210801 | R87: 20261231 | S87: 20210712 | T87: 20261231 | U87: 147 | V87: MXN | W87: M3 | X87: 30 | Y87: MXN | Z87: M3 | AA87: D215 | AB87: PD0159 PUERTO VALLARTA | AC87: 56103637 | AD87: 6644411540 | AE87: 4 | AF87: ENTREGA DIRECTA | AG87: 1.359 | AH87: M3 | AI87: X | AJ87: 4 | AK87: V4 | AL87: 20260108 | AM87: DW83-900005573-D215-10000383-4
... A95: 900009275DW83D21610258539 | B95: 4600071408-20 | C95: 4600071408 | D95: 20 | E95: MXPO | F95: MXL | G95: 900009275 | H95: SF TC-ED LA TEPYC LA REPISA | I95: 5095816 | J95: LA TEPYC SA DE CV | K95: Z04 | L95: (AP) 30 Dias | M95: 10258539 | N95: ARENA TRITURADA BASALTO MALLA 5 | O95: DW83 | P95: MX-CED. VALLARTA | Q95: 20250701 | R95: 20301231 | S95: 20260605 | T95: 20301231 | U95: 617.7 | V95: MXN | W95: M3 | X95: 175.73 | Y95: MXN | Z95: M3 | AA95: D216 | AB95: PD0130 TEPIC | AC95: 56103638 | AD95: 6644411540 | AE95: 4 | AF95: ENTREGA DIRECTA | AG95: 1.591 | AH95: M3 | AI95: X | AJ95: 4 | AK95: V4 | AL95: 20260622 | AM95: DW83-900009275-D216-10258539-4
A96: 900009274DW8310258539 | B96: 4600071407-20 | C96: 4600071407 | D96: 20 | E96: MXPO | F96: MXL | G96: 900009274 | H96: SF TC-LA TEPYC LA REPISA | I96: 5095816 | J96: LA TEPYC SA DE CV | K96: Z04 | L96: (AP) 30 Dias | M96: 10258539 | N96: ARENA TRITURADA BASALTO MALLA 5 | O96: DW83 | P96: MX-CED. VALLARTA | Q96: 20250701 | R96: 20301231 | S96: 20250701 | T96: 20301231 | U96: 350 | V96: MXN | W96: M3 | X96: 0 | Y96: MXN | Z96: M3 | AC96: 56103638 | AD96: 6644411540 | AE96: 1 | AF96: ENTREGADO | AG96: 1.591 | AH96: M3 | AI96: X | AJ96: 4 | AK96: V4 | AL96: 20250704 | AM96: DW83-900009274-10258539
A97: 900009274DW8310000437 | B97: 4600071407-10 | C97: 4600071407 | D97: 10 | E97: MXPO | F97: MXL | G97: 900009274 | H97: SF TC-LA TEPYC LA REPISA | I97: 5095816 | J97: LA TEPYC SA DE CV | K97: Z04 | L97: (AP) 30 Dias | M97: 10000437 | N97: Grava Triturada Basalto 20 mm - 3/4" | O97: DW83 | P97: MX-CED. VALLARTA | Q97: 20250701 | R97: 20301231 | S97: 20250701 | T97: 20301231 | U97: 350 | V97: MXN | W97: M3 | X97: 0 | Y97: MXN | Z97: M3 | AC97: 56103637 | AD97: 6644411540 | AE97: 1 | AF97: ENTREGADO | AG97: 1.505 | AH97: M3 | AI97: X | AJ97: 4 | AK97: V4 | AL97: 20250704 | AM97: DW83-900009274-10000437
A98: 900000472DW83D21510000643 | B98: 4600052492-10 | C98: 4600052492 | D98: 10 | E98: MXPO | F98: MXL | G98: 900000472 | H98: TC-ED-TRIMCAV | I98: 5010147 | J98: TRITURACIONES DE MARMOL Y CALCIOS | K98: Z04 | L98: (AP) 30 Dias | M98: 10000643 | N98: Grava Triturada Marmol 20 mm - 3/4" | O98: DW83 | P98: MX-CED. VALLARTA | Q98: 20211116 | R98: 20291231 | S98: 20240215 | T98: 20291231 | U98: 2268.57 | V98: MXN | W98: TN | X98: 919.15 | Y98: MXN | Z98: TN | AA98: D215 | AB98: PD0159 PUERTO VALLARTA | AC98: 56103637 | AD98: 6644411540 | AE98: 4 | AF98: ENTREGA DIRECTA | AG98: 1 | AH98: TO | AI98: X | AJ98: 4 | AK98: V4 | AL98: 20240319 | AM98: DW83-900000472-D215-10000643-4
A99: 900000472DW83D21510001456 | B99: 4600052492-40 | C99: 4600052492 | D99: 40 | E99: MXPO | F99: MXL | G99: 900000472 | H99: TC-ED-TRIMCAV | I99: 5010147 | J99: TRITURACIONES DE MARMOL Y CALCIOS | K99: Z04 | L99: (AP) 30 Dias | M99: 10001456 | N99: Grava Triturada Marmol 40 mm - 1 1/2" | O99: DW83 | P99: MX-CED. VALLARTA | Q99: 20211116 | R99: 20291231 | S99: 20240215 | T99: 20291231 | U99: 2268.57 | V99: MXN | W99: TN | X99: 919.15 | Y99: MXN | Z99: TN | AA99: D215 | AB99: PD0159 PUERTO VALLARTA | AC99: 56103637 | AD99: 6644411867 | AE99: 4 | AF99: ENTREGA DIRECTA | AG99: 1 | AH99: TO | AI99: X | AJ99: 4 | AK99: V4 | AL99: 20240319 | AM99: DW83-900000472-D215-10001456-4
A100: 900004995DW83D21510000332 | B100: 4600054529-20 | C100: 4600054529 | D100: 20 | E100: MXPO | F100: MXL | G100: 900004995 | H100: TC-ED LA FUNDICION | I100: 5065714 | J100: GRUPO MINERO LA FUNDICION SA DE CV | K100: N60 | L100: (AP) NAFIN 60 Dias | M100: 10000332 | N100: Grava Triturada Pomez - Jal 20 mm - 3/4" | O100: DW83 | P100: MX-CED. VALLARTA | Q100: 20220630 | R100: 20291231 | S100: 20240301 | T100: 20291231 | U100: 737.76 | V100: MXN | W100: M3 | X100: 578.76 | Y100: MXN | Z100: M3 | AA100: D215 | AB100: PD0159 PUERTO VALLARTA | AC100: 56103637 | AD100: 6644411540 | AE100: 4 | AF100: ENTREGA DIRECTA | AG100: 0.8 | AH100: M3 | AI100: X | AJ100: 4 | AK100: V4 | AL100: 20240319 | AM100: DW83-900004995-D215-10000332-4
A101: 900008141DW83D21610000332 | B101: 4600057252-130 | C101: 4600057252 | D101: 130 | E101: MXPO | F101: MXL | G101: 900008141 | H101: SF TC-ED TONY SILVA EL COLOMO | I101: 5011365 | J101: SILVA CARVAJAL MARCO ANTONIO | K101: Z03 | L101: (AP) 15 Dias | M101: 10000332 | N101: Grava Triturada Pomez - Jal 20 mm - 3/4" | O101: DW83 | P101: MX-CED. VALLARTA | Q101: 20230417 | R101: 20291231 | S101: 20240118 | T101: 20291231 | U101: 325 | V101: MXN | W101: M3 | X101: 50 | Y101: MXN | Z101: M3 | AA101: D216 | AB101: PD0130 TEPIC | AC101: 56103637 | AD101: 6644411540 | AE101: 4 | AF101: ENTREGA DIRECTA | AG101: 0.8 | AH101: M3 | AI101: X | AJ101: 4 | AK101: V4 | AL101: 20240119 | AM101: DW83-900008141-D216-10000332-4
A102: 900008907DW83D21610069534 | B102: 4600069944-20 | C102: 4600069944 | D102: 20 | E102: MXPO | F102: MXL | G102: 900008907 | H102: TC- ED SORIA AHUACATLAN | I102: 5004655 | J102: SORIA VILLARREAL ALFREDO | K102: Z03 | L102: (AP) 15 Dias | M102: 10069534 | N102: ARENA CLASIFICADA BASALTO MALLA 4 | O102: DW83 | P102: MX-CED. VALLARTA | Q102: 20240723 | R102: 20291231 | S102: 20260215 | T102: 20301231 | U102: 546 | V102: MXN | W102: M3 | X102: 241.5 | Y102: MXN | Z102: M3 | AA102: D216 | AB102: PD0130 TEPIC | AC102: 56103638 | AD102: 6644411540 | AE102: 4 | AF102: ENTREGA DIRECTA | AG102: 1.498 | AH102: M3 | AI102: X | AJ102: 4 | AK102: V4 | AL102: 20260217 | AM102: DW83-900008907-D216-10069534-4
A103: 900008907DW83D21610000191 | B103: 4600069944-30 | C103: 4600069944 | D103: 30 | E103: MXPO | F103: MXL | G103: 900008907 | H103: TC- ED SORIA AHUACATLAN | I103: 5004655 | J103: SORIA VILLARREAL ALFREDO | K103: Z03 | L103: (AP) 15 Dias | M103: 10000191 | N103: Grava Triturada Basalto 20 mm - 3/4" | O103: DW83 | P103: MX-CED. VALLARTA | Q103: 20240723 | R103: 20291231 | S103: 20260215 | T103: 20301231 | U103: 577.5 | V103: MXN | W103: M3 | X103: 241.5 | Y103: MXN | Z103: M3 | AA103: D216 | AB103: PD0130 TEPIC | AC103: 56103637 | AD103: 6644411540 | AE103: 4 | AF103: ENTREGA DIRECTA | AG103: 1.41 | AH103: M3 | AI103: X | AJ103: 4 | AK103: V4 | AL103: 20260217 | AM103: DW83-900008907-D216-10000191-4
A104: 900008907DW83D24310069534 | B104: 4600069944-50 | C104: 4600069944 | D104: 50 | E104: MXPO | F104: MXL | G104: 900008907 | H104: TC- ED SORIA AHUACATLAN | I104: 5004655 | J104: SORIA VILLARREAL ALFREDO | K104: Z03 | L104: (AP) 15 Dias | M104: 10069534 | N104: ARENA CLASIFICADA BASALTO MALLA 4 | O104: DW83 | P104: MX-CED. VALLARTA | Q104: 20240723 | R104: 20291231 | S104: 20260215 | T104: 20301231 | U104: 546 | V104: MXN | W104: M3 | X104: 241.5 | Y104: MXN | Z104: M3 | AA104: D243 | AB104: PD0423 OJO DE AGUA | AC104: 56103638 | AD104: 6644411540 | AE104: 4 | AF104: ENTREGA DIRECTA | AG104: 1.498 | AH104: M3 | AI104: X | AJ104: 4 | AK104: V4 | AL104: 20260217 | AM104: DW83-900008907-D243-10069534-4
A105: 900008907DW83D24310000191 | B105: 4600069944-40 | C105: 4600069944 | D105: 40 | E105: MXPO | F105: MXL | G105: 900008907 | H105: TC- ED SORIA AHUACATLAN | I105: 5004655 | J105: SORIA VILLARREAL ALFREDO | K105: Z03 | L105: (AP) 15 Dias | M105: 10000191 | N105: Grava Triturada Basalto 20 mm - 3/4" | O105: DW83 | P105: MX-CED. VALLARTA | Q105: 20240723 | R105: 20291231 | S105: 20260215 | T105: 20301231 | U105: 577.5 | V105: MXN | W105: M3 | X105: 241.5 | Y105: MXN | Z105: M3 | AA105: D243 | AB105: PD0423 OJO DE AGUA | AC105: 56103637 | AD105: 6644411540 | AE105: 4 | AF105: ENTREGA DIRECTA | AG105: 1.41 | AH105: M3 | AI105: X | AJ105: 4 | AK105: V4 | AL105: 20260217 | AM105: DW83-900008907-D243-10000191-4
A106: 900003894DW8310000383 | B106: 4600050427-30 | C106: 4600050427 | D106: 30 | E106: MXPO | F106: MXL | G106: 900003894 | H106: TC-SALDAÑA ALMACEN NUEVO VALLARTA | I106: 5002163 | J106: SALDANA MORONES HERIBERTO | K106: N30 | L106: (AP) NAFIN 30 Dias | M106: 10000383 | N106: Grava Triturada Basalto 40 mm - 1 1/2" | O106: DW83 | P106: MX-CED. VALLARTA | Q106: 20210801 | R106: 20261231 | S106: 20210712 | T106: 20261231 | U106: 147.67 | V106: MXN | W106: M3 | X106: 0 | Y106: MXN | Z106: M3 | AC106: 56103637 | AD106: 6644411540 | AE106: 1 | AF106: ENTREGADO | AG106: 1.359 | AH106: M3 | AI106: X | AJ106: 4 | AK106: V4 | AL106: 20260108 | AM106: DW83-900003894-10000383
A107: 900003894DW8310000377 | B107: 4600050427-10 | C107: 4600050427 | D107: 10 | E107: MXPO | F107: MXL | G107: 900003894 | H107: TC-SALDAÑA ALMACEN NUEVO VALLARTA | I107: 5002163 | J107: SALDANA MORONES HERIBERTO | K107: N30 | L107: (AP) NAFIN 30 Dias | M107: 10000377 | N107: Grava Triturada Basalto 10 mm - 3/8" | O107: DW83 | P107: MX-CED. VALLARTA | Q107: 20210801 | R107: 20261231 | S107: 20210712 | T107: 20261231 | U107: 111.05 | V107: MXN | W107: M3 | X107: 0 | Y107: MXN | Z107: M3 | AC107: 56103637 | AD107: 6644411540 | AE107: 1 | AF107: ENTREGADO | AG107: 1.458 | AH107: M3 | AI107: X | AJ107: 4 | AK107: V4 | AL107: 20260108 | AM107: DW83-900003894-10000377
A108: 900008104DW8310154410 | B108: 4600057092-50 | C108: 4600057092 | D108: 50 | E108: MXPO | F108: MXL | G108: 900008104 | H108: SF TC- SORIA AHUACATLAN | I108: 5004655 | J108: SORIA VILLARREAL ALFREDO | K108: Z03 | L108: (AP) 15 Dias | M108: 10154410 | N108: ARENA CRIBADA ANDESITA MALLA 4 | O108: DW83 | P108: MX-CED. VALLARTA | Q108: 20230331 | R108: 20281231 | S108: 20230502 | T108: 20281231 | U108: 290 | V108: MXN | W108: M3 | X108: 0 | Y108: MXN | Z108: M3 | AC108: 56103638 | AD108: 6644411540 | AE108: 1 | AF108: ENTREGADO | AG108: 1.4 | AH108: M3 | AI108: X | AJ108: 4 | AK108: V4 | AL108: 20230920 | AM108: DW83-900008104-10154410
A109: 900008104DW8310000191 | B109: 4600057092-10 | C109: 4600057092 | D109: 10 | E109: MXPO | F109: MXL | G109: 900008104 | H109: SF TC- SORIA AHUACATLAN | I109: 5004655 | J109: SORIA VILLARREAL ALFREDO | K109: Z03 | L109: (AP) 15 Dias | M109: 10000191 | N109: Grava Triturada Basalto 20 mm - 3/4" | O109: DW83 | P109: MX-CED. VALLARTA | Q109: 20230331 | R109: 20281231 | S109: 20230331 | T109: 20281231 | U109: 320 | V109: MXN | W109: M3 | X109: 0 | Y109: MXN | Z109: M3 | AC109: 56103637 | AD109: 6644411540 | AE109: 1 | AF109: ENTREGADO | AG109: 1.41 | AH109: M3 | AI109: X | AJ109: 4 | AK109: V4 | AL109: 20230920 | AM109: DW83-900008104-10000191
A110: 900008104DW8310004258 | B110: 4600057092-40 | C110: 4600057092 | D110: 40 | E110: MXPO | F110: MXL | G110: 900008104 | H110: SF TC- SORIA AHUACATLAN | I110: 5004655 | J110: SORIA VILLARREAL ALFREDO | K110: Z03 | L110: (AP) 15 Dias | M110: 10004258 | N110: Sello Triturado Basalto 10 mm - 3/8" | O110: DW83 | P110: MX-CED. VALLARTA | Q110: 20230331 | R110: 20281231 | S110: 20230331 | T110: 20281231 | U110: 320 | V110: MXN | W110: M3 | X110: 0 | Y110: MXN | Z110: M3 | AC110: 56103637 | AD110: 6644411540 | AE110: 1 | AF110: ENTREGADO | AG110: 1.53 | AH110: M3 | AI110: X | AJ110: 4 | AK110: V4 | AL110: 20230920 | AM110: DW83-900008104-10004258
A111: 900008104DW8310000388 | B111: 4600057092-20 | C111: 4600057092 | D111: 20 | E111: MXPO | F111: MXL | G111: 900008104 | H111: SF TC- SORIA AHUACATLAN | I111: 5004655 | J111: SORIA VILLARREAL ALFREDO | K111: Z03 | L111: (AP) 15 Dias | M111: 10000388 | N111: Grava Triturada Basalto 40 mm - 1 1/2" | O111: DW83 | P111: MX-CED. VALLARTA | Q111: 20230331 | R111: 20281231 | S111: 20230331 | T111: 20281231 | U111: 320 | V111: MXN | W111: M3 | X111: 0 | Y111: MXN | Z111: M3 | AC111: 56103637 | AD111: 6644411540 | AE111: 1 | AF111: ENTREGADO | AG111: 1.395 | AH111: M3 | AI111: X | AJ111: 4 | AK111: V4 | AL111: 20230920 | AM111: DW83-900008104-10000388
A112: 900008104DW8310000384 | B112: 4600057092-30 | C112: 4600057092 | D112: 30 | E112: MXPO | F112: MXL | G112: 900008104 | H112: SF TC- SORIA AHUACATLAN | I112: 5004655 | J112: SORIA VILLARREAL ALFREDO | K112: Z03 | L112: (AP) 15 Dias | M112: 10000384 | N112: Arena Triturada Basalto Malla 4 | O112: DW83 | P112: MX-CED. VALLARTA | Q112: 20230331 | R112: 20281231 | S112: 20230331 | T112: 20281231 | U112: 320 | V112: MXN | W112: M3 | X112: 0 | Y112: MXN | Z112: M3 | AC112: 56103638 | AD112: 6644411540 | AE112: 1 | AF112: ENTREGADO | AG112: 1.61 | AH112: M3 | AI112: X | AJ112: 4 | AK112: V4 | AL112: 20230920 | AM112: DW83-900008104-10000384
A113: 900003894DW8310000379 | B113: 4600050427-20 | C113: 4600050427 | D113: 20 | E113: MXPO | F113: MXL | G113: 900003894 | H113: TC-SALDAÑA ALMACEN NUEVO VALLARTA | I113: 5002163 | J113: SALDANA MORONES HERIBERTO | K113: N30 | L113: (AP) NAFIN 30 Dias | M113: 10000379 | N113: Grava Triturada Basalto 20 mm - 3/4" | O113: DW83 | P113: MX-CED. VALLARTA | Q113: 20210801 | R113: 20261231 | S113: 20210712 | T113: 20261231 | U113: 147.67 | V113: MXN | W113: M3 | X113: 0 | Y113: MXN | Z113: M3 | AC113: 56103637 | AD113: 6644411540 | AE113: 1 | AF113: ENTREGADO | AG113: 1.43 | AH113: M3 | AI113: X | AJ113: 4 | AK113: V4 | AL113: 20260108 | AM113: DW83-900003894-10000379
...
